package m9;

import eb.e;
import eb.e.a;

public final class r
  extends e.a<Object>
{
  public r(v paramv, a0 parama0, e[] paramArrayOfe) {}
  
  /* Error */
  public final void a(eb.s0 params0, eb.e1 parame1)
  {
    // Byte code:
    //   0: aload_0
    //   1: getfield 17	m9/r:a	Lm9/a0;
    //   4: checkcast 26	m9/a$c
    //   7: astore_3
    //   8: aload_3
    //   9: getfield 29	m9/a$c:a	Lm9/a$a;
    //   12: astore 4
    //   14: new 31	w/g
    //   17: astore_1
    //   18: aload_1
    //   19: bipush 21
    //   21: aload_3
    //   22: aload_2
    //   23: invokespecial 34	w/g:<init>	(ILjava/lang/Object;Ljava/lang/Object;)V
    //   26: aload 4
    //   28: aload_1
    //   29: invokevirtual 39	m9/a$a:a	(Ljava/lang/Runnable;)V
    //   32: goto +15 -> 47
    //   35: astore_1
    //   36: aload_0
    //   37: getfield 15	m9/r:c	Lm9/v;
    //   40: getfield 44	m9/v:a	Ln9/a;
    //   43: aload_1
    //   44: invokevirtual 49	n9/a:c	(Ljava/lang/Throwable;)V
    //   47: return
    // Local variable table:
    //   start	length	slot	name	signature
    //   0	48	0	this	r
    //   0	48	1	params0	eb.s0
    //   0	48	2	parame1	eb.e1
    //   7	15	3	localc	a.c
    //   12	15	4	locala	a.a
    // Exception table:
    //   from	to	target	type
    //   0	32	35	finally
  }
  
  /* Error */
  public final void b(eb.s0 params0)
  {
    // Byte code:
    //   0: aload_0
    //   1: getfield 17	m9/r:a	Lm9/a0;
    //   4: checkcast 26	m9/a$c
    //   7: astore_2
    //   8: aload_2
    //   9: getfield 29	m9/a$c:a	Lm9/a$a;
    //   12: astore_3
    //   13: new 52	x0/f
    //   16: astore 4
    //   18: aload 4
    //   20: bipush 19
    //   22: aload_2
    //   23: aload_1
    //   24: invokespecial 53	x0/f:<init>	(ILjava/lang/Object;Ljava/lang/Object;)V
    //   27: aload_3
    //   28: aload 4
    //   30: invokevirtual 39	m9/a$a:a	(Ljava/lang/Runnable;)V
    //   33: goto +15 -> 48
    //   36: astore_1
    //   37: aload_0
    //   38: getfield 15	m9/r:c	Lm9/v;
    //   41: getfield 44	m9/v:a	Ln9/a;
    //   44: aload_1
    //   45: invokevirtual 49	n9/a:c	(Ljava/lang/Throwable;)V
    //   48: return
    // Local variable table:
    //   start	length	slot	name	signature
    //   0	49	0	this	r
    //   0	49	1	params0	eb.s0
    //   7	16	2	localc	a.c
    //   12	16	3	locala	a.a
    //   16	13	4	localf	x0.f
    // Exception table:
    //   from	to	target	type
    //   0	33	36	finally
  }
  
  /* Error */
  public final void c(Object paramObject)
  {
    // Byte code:
    //   0: aload_0
    //   1: getfield 17	m9/r:a	Lm9/a0;
    //   4: checkcast 26	m9/a$c
    //   7: astore_2
    //   8: aload_2
    //   9: getfield 57	m9/a$c:b	I
    //   12: iconst_1
    //   13: iadd
    //   14: istore_3
    //   15: aload_2
    //   16: getfield 29	m9/a$c:a	Lm9/a$a;
    //   19: astore 4
    //   21: new 59	n1/a
    //   24: astore 5
    //   26: aload 5
    //   28: aload_2
    //   29: iload_3
    //   30: aload_1
    //   31: iconst_2
    //   32: invokespecial 62	n1/a:<init>	(Ljava/lang/Object;ILjava/lang/Object;I)V
    //   35: aload 4
    //   37: aload 5
    //   39: invokevirtual 39	m9/a$a:a	(Ljava/lang/Runnable;)V
    //   42: aload_2
    //   43: iload_3
    //   44: putfield 57	m9/a$c:b	I
    //   47: aload_0
    //   48: getfield 19	m9/r:b	[Leb/e;
    //   51: iconst_0
    //   52: aaload
    //   53: iconst_1
    //   54: invokevirtual 67	eb/e:c	(I)V
    //   57: goto +15 -> 72
    //   60: astore_1
    //   61: aload_0
    //   62: getfield 15	m9/r:c	Lm9/v;
    //   65: getfield 44	m9/v:a	Ln9/a;
    //   68: aload_1
    //   69: invokevirtual 49	n9/a:c	(Ljava/lang/Throwable;)V
    //   72: return
    // Local variable table:
    //   start	length	slot	name	signature
    //   0	73	0	this	r
    //   0	73	1	paramObject	Object
    //   7	36	2	localc	a.c
    //   14	30	3	i	int
    //   19	17	4	locala	a.a
    //   24	14	5	locala1	n1.a
    // Exception table:
    //   from	to	target	type
    //   0	57	60	finally
  }
  
  public final void d() {}
}

/* Location:
 * Qualified Name:     m9.r
 * Java Class Version: 6 (50.0)
 * JD-Core Version:    0.7.1
 */