package com.google.android.gms.common.internal;

import android.os.Looper;
import com.google.android.gms.internal.common.zzh;

public final class h
  extends zzh
{
  public h(a parama, Looper paramLooper)
  {
    super(paramLooper);
  }
  
  /* Error */
  public final void handleMessage(android.os.Message paramMessage)
  {
    // Byte code:
    //   0: aload_0
    //   1: getfield 10	com/google/android/gms/common/internal/h:a	Lcom/google/android/gms/common/internal/a;
    //   4: getfield 24	com/google/android/gms/common/internal/a:zzd	Ljava/util/concurrent/atomic/AtomicInteger;
    //   7: invokevirtual 30	java/util/concurrent/atomic/AtomicInteger:get	()I
    //   10: istore_2
    //   11: aload_1
    //   12: getfield 36	android/os/Message:arg1	I
    //   15: istore_3
    //   16: iconst_0
    //   17: istore 4
    //   19: iconst_0
    //   20: istore 5
    //   22: aconst_null
    //   23: astore 6
    //   25: iload_2
    //   26: iload_3
    //   27: if_icmpeq +106 -> 133
    //   30: aload_1
    //   31: getfield 39	android/os/Message:what	I
    //   34: istore_3
    //   35: iload_3
    //   36: iconst_2
    //   37: if_icmpeq +18 -> 55
    //   40: iload_3
    //   41: iconst_1
    //   42: if_icmpeq +13 -> 55
    //   45: iload 5
    //   47: istore 4
    //   49: iload_3
    //   50: bipush 7
    //   52: if_icmpne +6 -> 58
    //   55: iconst_1
    //   56: istore 4
    //   58: iload 4
    //   60: ifeq +72 -> 132
    //   63: aload_1
    //   64: getfield 43	android/os/Message:obj	Ljava/lang/Object;
    //   67: checkcast 45	m6/k0
    //   70: astore 6
    //   72: aload 6
    //   74: invokevirtual 49	m6/k0:b	()V
    //   77: aload 6
    //   79: monitorenter
    //   80: aload 6
    //   82: aconst_null
    //   83: putfield 51	m6/k0:a	Ljava/lang/Object;
    //   86: aload 6
    //   88: monitorexit
    //   89: aload 6
    //   91: getfield 54	m6/k0:c	Lcom/google/android/gms/common/internal/a;
    //   94: invokestatic 58	com/google/android/gms/common/internal/a:zzf	(Lcom/google/android/gms/common/internal/a;)Ljava/util/ArrayList;
    //   97: astore_1
    //   98: aload_1
    //   99: monitorenter
    //   100: aload 6
    //   102: getfield 54	m6/k0:c	Lcom/google/android/gms/common/internal/a;
    //   105: invokestatic 58	com/google/android/gms/common/internal/a:zzf	(Lcom/google/android/gms/common/internal/a;)Ljava/util/ArrayList;
    //   108: aload 6
    //   110: invokevirtual 64	java/util/ArrayList:remove	(Ljava/lang/Object;)Z
    //   113: pop
    //   114: aload_1
    //   115: monitorexit
    //   116: goto +16 -> 132
    //   119: astore 6
    //   121: aload_1
    //   122: monitorexit
    //   123: aload 6
    //   125: athrow
    //   126: astore_1
    //   127: aload 6
    //   129: monitorexit
    //   130: aload_1
    //   131: athrow
    //   132: return
    //   133: aload_1
    //   134: getfield 39	android/os/Message:what	I
    //   137: istore 5
    //   139: iload 5
    //   141: iconst_1
    //   142: if_icmpeq +34 -> 176
    //   145: iload 5
    //   147: bipush 7
    //   149: if_icmpeq +27 -> 176
    //   152: iload 5
    //   154: iconst_4
    //   155: if_icmpne +13 -> 168
    //   158: aload_0
    //   159: getfield 10	com/google/android/gms/common/internal/h:a	Lcom/google/android/gms/common/internal/a;
    //   162: invokevirtual 68	com/google/android/gms/common/internal/a:enableLocalFallback	()Z
    //   165: ifeq +11 -> 176
    //   168: aload_1
    //   169: getfield 39	android/os/Message:what	I
    //   172: iconst_5
    //   173: if_icmpne +13 -> 186
    //   176: aload_0
    //   177: getfield 10	com/google/android/gms/common/internal/h:a	Lcom/google/android/gms/common/internal/a;
    //   180: invokevirtual 71	com/google/android/gms/common/internal/a:isConnecting	()Z
    //   183: ifeq +611 -> 794
    //   186: aload_1
    //   187: getfield 39	android/os/Message:what	I
    //   190: istore 5
    //   192: iload 5
    //   194: iconst_4
    //   195: if_icmpne +105 -> 300
    //   198: aload_0
    //   199: getfield 10	com/google/android/gms/common/internal/h:a	Lcom/google/android/gms/common/internal/a;
    //   202: new 73	j6/b
    //   205: dup
    //   206: aload_1
    //   207: getfield 76	android/os/Message:arg2	I
    //   210: invokespecial 79	j6/b:<init>	(I)V
    //   213: invokestatic 83	com/google/android/gms/common/internal/a:zzg	(Lcom/google/android/gms/common/internal/a;Lj6/b;)V
    //   216: aload_0
    //   217: getfield 10	com/google/android/gms/common/internal/h:a	Lcom/google/android/gms/common/internal/a;
    //   220: invokestatic 87	com/google/android/gms/common/internal/a:zzo	(Lcom/google/android/gms/common/internal/a;)Z
    //   223: ifeq +25 -> 248
    //   226: aload_0
    //   227: getfield 10	com/google/android/gms/common/internal/h:a	Lcom/google/android/gms/common/internal/a;
    //   230: astore_1
    //   231: aload_1
    //   232: invokestatic 90	com/google/android/gms/common/internal/a:zzm	(Lcom/google/android/gms/common/internal/a;)Z
    //   235: ifeq +6 -> 241
    //   238: goto +10 -> 248
    //   241: aload_1
    //   242: iconst_3
    //   243: aconst_null
    //   244: invokestatic 94	com/google/android/gms/common/internal/a:zzi	(Lcom/google/android/gms/common/internal/a;ILandroid/os/IInterface;)V
    //   247: return
    //   248: aload_0
    //   249: getfield 10	com/google/android/gms/common/internal/h:a	Lcom/google/android/gms/common/internal/a;
    //   252: astore_1
    //   253: aload_1
    //   254: invokestatic 98	com/google/android/gms/common/internal/a:zza	(Lcom/google/android/gms/common/internal/a;)Lj6/b;
    //   257: ifnull +11 -> 268
    //   260: aload_1
    //   261: invokestatic 98	com/google/android/gms/common/internal/a:zza	(Lcom/google/android/gms/common/internal/a;)Lj6/b;
    //   264: astore_1
    //   265: goto +13 -> 278
    //   268: new 73	j6/b
    //   271: dup
    //   272: bipush 8
    //   274: invokespecial 79	j6/b:<init>	(I)V
    //   277: astore_1
    //   278: aload_0
    //   279: getfield 10	com/google/android/gms/common/internal/h:a	Lcom/google/android/gms/common/internal/a;
    //   282: getfield 102	com/google/android/gms/common/internal/a:zzc	Lcom/google/android/gms/common/internal/a$c;
    //   285: aload_1
    //   286: invokeinterface 107 2 0
    //   291: aload_0
    //   292: getfield 10	com/google/android/gms/common/internal/h:a	Lcom/google/android/gms/common/internal/a;
    //   295: aload_1
    //   296: invokevirtual 110	com/google/android/gms/common/internal/a:onConnectionFailed	(Lj6/b;)V
    //   299: return
    //   300: iload 5
    //   302: iconst_5
    //   303: if_icmpne +55 -> 358
    //   306: aload_0
    //   307: getfield 10	com/google/android/gms/common/internal/h:a	Lcom/google/android/gms/common/internal/a;
    //   310: astore_1
    //   311: aload_1
    //   312: invokestatic 98	com/google/android/gms/common/internal/a:zza	(Lcom/google/android/gms/common/internal/a;)Lj6/b;
    //   315: ifnull +11 -> 326
    //   318: aload_1
    //   319: invokestatic 98	com/google/android/gms/common/internal/a:zza	(Lcom/google/android/gms/common/internal/a;)Lj6/b;
    //   322: astore_1
    //   323: goto +13 -> 336
    //   326: new 73	j6/b
    //   329: dup
    //   330: bipush 8
    //   332: invokespecial 79	j6/b:<init>	(I)V
    //   335: astore_1
    //   336: aload_0
    //   337: getfield 10	com/google/android/gms/common/internal/h:a	Lcom/google/android/gms/common/internal/a;
    //   340: getfield 102	com/google/android/gms/common/internal/a:zzc	Lcom/google/android/gms/common/internal/a$c;
    //   343: aload_1
    //   344: invokeinterface 107 2 0
    //   349: aload_0
    //   350: getfield 10	com/google/android/gms/common/internal/h:a	Lcom/google/android/gms/common/internal/a;
    //   353: aload_1
    //   354: invokevirtual 110	com/google/android/gms/common/internal/a:onConnectionFailed	(Lj6/b;)V
    //   357: return
    //   358: iload 5
    //   360: iconst_3
    //   361: if_icmpne +60 -> 421
    //   364: aload_1
    //   365: getfield 43	android/os/Message:obj	Ljava/lang/Object;
    //   368: astore 7
    //   370: aload 7
    //   372: instanceof 112
    //   375: ifeq +10 -> 385
    //   378: aload 7
    //   380: checkcast 112	android/app/PendingIntent
    //   383: astore 6
    //   385: new 73	j6/b
    //   388: dup
    //   389: aload_1
    //   390: getfield 76	android/os/Message:arg2	I
    //   393: aload 6
    //   395: invokespecial 115	j6/b:<init>	(ILandroid/app/PendingIntent;)V
    //   398: astore_1
    //   399: aload_0
    //   400: getfield 10	com/google/android/gms/common/internal/h:a	Lcom/google/android/gms/common/internal/a;
    //   403: getfield 102	com/google/android/gms/common/internal/a:zzc	Lcom/google/android/gms/common/internal/a$c;
    //   406: aload_1
    //   407: invokeinterface 107 2 0
    //   412: aload_0
    //   413: getfield 10	com/google/android/gms/common/internal/h:a	Lcom/google/android/gms/common/internal/a;
    //   416: aload_1
    //   417: invokevirtual 110	com/google/android/gms/common/internal/a:onConnectionFailed	(Lj6/b;)V
    //   420: return
    //   421: iload 5
    //   423: bipush 6
    //   425: if_icmpne +63 -> 488
    //   428: aload_0
    //   429: getfield 10	com/google/android/gms/common/internal/h:a	Lcom/google/android/gms/common/internal/a;
    //   432: iconst_5
    //   433: aconst_null
    //   434: invokestatic 94	com/google/android/gms/common/internal/a:zzi	(Lcom/google/android/gms/common/internal/a;ILandroid/os/IInterface;)V
    //   437: aload_0
    //   438: getfield 10	com/google/android/gms/common/internal/h:a	Lcom/google/android/gms/common/internal/a;
    //   441: astore 6
    //   443: aload 6
    //   445: invokestatic 119	com/google/android/gms/common/internal/a:zzb	(Lcom/google/android/gms/common/internal/a;)Lcom/google/android/gms/common/internal/a$a;
    //   448: ifnull +17 -> 465
    //   451: aload 6
    //   453: invokestatic 119	com/google/android/gms/common/internal/a:zzb	(Lcom/google/android/gms/common/internal/a;)Lcom/google/android/gms/common/internal/a$a;
    //   456: aload_1
    //   457: getfield 76	android/os/Message:arg2	I
    //   460: invokeinterface 124 2 0
    //   465: aload_0
    //   466: getfield 10	com/google/android/gms/common/internal/h:a	Lcom/google/android/gms/common/internal/a;
    //   469: aload_1
    //   470: getfield 76	android/os/Message:arg2	I
    //   473: invokevirtual 127	com/google/android/gms/common/internal/a:onConnectionSuspended	(I)V
    //   476: aload_0
    //   477: getfield 10	com/google/android/gms/common/internal/h:a	Lcom/google/android/gms/common/internal/a;
    //   480: iconst_5
    //   481: iconst_1
    //   482: aconst_null
    //   483: invokestatic 131	com/google/android/gms/common/internal/a:zzn	(Lcom/google/android/gms/common/internal/a;IILandroid/os/IInterface;)Z
    //   486: pop
    //   487: return
    //   488: iload 5
    //   490: iconst_2
    //   491: if_icmpne +83 -> 574
    //   494: aload_0
    //   495: getfield 10	com/google/android/gms/common/internal/h:a	Lcom/google/android/gms/common/internal/a;
    //   498: invokevirtual 134	com/google/android/gms/common/internal/a:isConnected	()Z
    //   501: ifeq +6 -> 507
    //   504: goto +70 -> 574
    //   507: aload_1
    //   508: getfield 43	android/os/Message:obj	Ljava/lang/Object;
    //   511: checkcast 45	m6/k0
    //   514: astore 6
    //   516: aload 6
    //   518: invokevirtual 49	m6/k0:b	()V
    //   521: aload 6
    //   523: monitorenter
    //   524: aload 6
    //   526: aconst_null
    //   527: putfield 51	m6/k0:a	Ljava/lang/Object;
    //   530: aload 6
    //   532: monitorexit
    //   533: aload 6
    //   535: getfield 54	m6/k0:c	Lcom/google/android/gms/common/internal/a;
    //   538: invokestatic 58	com/google/android/gms/common/internal/a:zzf	(Lcom/google/android/gms/common/internal/a;)Ljava/util/ArrayList;
    //   541: astore_1
    //   542: aload_1
    //   543: monitorenter
    //   544: aload 6
    //   546: getfield 54	m6/k0:c	Lcom/google/android/gms/common/internal/a;
    //   549: invokestatic 58	com/google/android/gms/common/internal/a:zzf	(Lcom/google/android/gms/common/internal/a;)Ljava/util/ArrayList;
    //   552: aload 6
    //   554: invokevirtual 64	java/util/ArrayList:remove	(Ljava/lang/Object;)Z
    //   557: pop
    //   558: aload_1
    //   559: monitorexit
    //   560: return
    //   561: astore 6
    //   563: aload_1
    //   564: monitorexit
    //   565: aload 6
    //   567: athrow
    //   568: astore_1
    //   569: aload 6
    //   571: monitorexit
    //   572: aload_1
    //   573: athrow
    //   574: aload_1
    //   575: getfield 39	android/os/Message:what	I
    //   578: istore 5
    //   580: iload 5
    //   582: iconst_2
    //   583: if_icmpeq +16 -> 599
    //   586: iload 5
    //   588: iconst_1
    //   589: if_icmpeq +10 -> 599
    //   592: iload 5
    //   594: bipush 7
    //   596: if_icmpne +6 -> 602
    //   599: iconst_1
    //   600: istore 4
    //   602: iload 4
    //   604: ifeq +169 -> 773
    //   607: aload_1
    //   608: getfield 43	android/os/Message:obj	Ljava/lang/Object;
    //   611: checkcast 45	m6/k0
    //   614: astore_1
    //   615: aload_1
    //   616: monitorenter
    //   617: aload_1
    //   618: getfield 51	m6/k0:a	Ljava/lang/Object;
    //   621: astore 8
    //   623: aload_1
    //   624: getfield 137	m6/k0:b	Z
    //   627: ifeq +54 -> 681
    //   630: aload_1
    //   631: invokevirtual 143	java/lang/Object:toString	()Ljava/lang/String;
    //   634: astore 7
    //   636: new 145	java/lang/StringBuilder
    //   639: astore 6
    //   641: aload 6
    //   643: invokespecial 147	java/lang/StringBuilder:<init>	()V
    //   646: aload 6
    //   648: ldc -107
    //   650: invokevirtual 153	java/lang/StringBuilder:append	(Ljava/lang/String;)Ljava/lang/StringBuilder;
    //   653: pop
    //   654: aload 6
    //   656: aload 7
    //   658: invokevirtual 153	java/lang/StringBuilder:append	(Ljava/lang/String;)Ljava/lang/StringBuilder;
    //   661: pop
    //   662: aload 6
    //   664: ldc -101
    //   666: invokevirtual 153	java/lang/StringBuilder:append	(Ljava/lang/String;)Ljava/lang/StringBuilder;
    //   669: pop
    //   670: ldc -99
    //   672: aload 6
    //   674: invokevirtual 158	java/lang/StringBuilder:toString	()Ljava/lang/String;
    //   677: invokestatic 164	android/util/Log:w	(Ljava/lang/String;Ljava/lang/String;)I
    //   680: pop
    //   681: aload_1
    //   682: monitorexit
    //   683: aload 8
    //   685: ifnull +15 -> 700
    //   688: aload_1
    //   689: aload 8
    //   691: invokevirtual 167	m6/k0:a	(Ljava/lang/Object;)V
    //   694: goto +6 -> 700
    //   697: astore_1
    //   698: aload_1
    //   699: athrow
    //   700: aload_1
    //   701: monitorenter
    //   702: aload_1
    //   703: iconst_1
    //   704: putfield 137	m6/k0:b	Z
    //   707: aload_1
    //   708: monitorexit
    //   709: aload_1
    //   710: monitorenter
    //   711: aload_1
    //   712: aconst_null
    //   713: putfield 51	m6/k0:a	Ljava/lang/Object;
    //   716: aload_1
    //   717: monitorexit
    //   718: aload_1
    //   719: getfield 54	m6/k0:c	Lcom/google/android/gms/common/internal/a;
    //   722: invokestatic 58	com/google/android/gms/common/internal/a:zzf	(Lcom/google/android/gms/common/internal/a;)Ljava/util/ArrayList;
    //   725: astore 6
    //   727: aload 6
    //   729: monitorenter
    //   730: aload_1
    //   731: getfield 54	m6/k0:c	Lcom/google/android/gms/common/internal/a;
    //   734: invokestatic 58	com/google/android/gms/common/internal/a:zzf	(Lcom/google/android/gms/common/internal/a;)Ljava/util/ArrayList;
    //   737: aload_1
    //   738: invokevirtual 64	java/util/ArrayList:remove	(Ljava/lang/Object;)Z
    //   741: pop
    //   742: aload 6
    //   744: monitorexit
    //   745: return
    //   746: astore_1
    //   747: aload 6
    //   749: monitorexit
    //   750: aload_1
    //   751: athrow
    //   752: astore 6
    //   754: aload_1
    //   755: monitorexit
    //   756: aload 6
    //   758: athrow
    //   759: astore 6
    //   761: aload_1
    //   762: monitorexit
    //   763: aload 6
    //   765: athrow
    //   766: astore 6
    //   768: aload_1
    //   769: monitorexit
    //   770: aload 6
    //   772: athrow
    //   773: ldc -99
    //   775: ldc -87
    //   777: iload 5
    //   779: invokestatic 175	f:h	(Ljava/lang/String;I)Ljava/lang/String;
    //   782: new 177	java/lang/Exception
    //   785: dup
    //   786: invokespecial 178	java/lang/Exception:<init>	()V
    //   789: invokestatic 182	android/util/Log:wtf	(Ljava/lang/String;Ljava/lang/String;Ljava/lang/Throwable;)I
    //   792: pop
    //   793: return
    //   794: aload_1
    //   795: getfield 43	android/os/Message:obj	Ljava/lang/Object;
    //   798: checkcast 45	m6/k0
    //   801: astore_1
    //   802: aload_1
    //   803: invokevirtual 49	m6/k0:b	()V
    //   806: aload_1
    //   807: monitorenter
    //   808: aload_1
    //   809: aconst_null
    //   810: putfield 51	m6/k0:a	Ljava/lang/Object;
    //   813: aload_1
    //   814: monitorexit
    //   815: aload_1
    //   816: getfield 54	m6/k0:c	Lcom/google/android/gms/common/internal/a;
    //   819: invokestatic 58	com/google/android/gms/common/internal/a:zzf	(Lcom/google/android/gms/common/internal/a;)Ljava/util/ArrayList;
    //   822: astore 6
    //   824: aload 6
    //   826: monitorenter
    //   827: aload_1
    //   828: getfield 54	m6/k0:c	Lcom/google/android/gms/common/internal/a;
    //   831: invokestatic 58	com/google/android/gms/common/internal/a:zzf	(Lcom/google/android/gms/common/internal/a;)Ljava/util/ArrayList;
    //   834: aload_1
    //   835: invokevirtual 64	java/util/ArrayList:remove	(Ljava/lang/Object;)Z
    //   838: pop
    //   839: aload 6
    //   841: monitorexit
    //   842: return
    //   843: astore_1
    //   844: aload 6
    //   846: monitorexit
    //   847: aload_1
    //   848: athrow
    //   849: astore 6
    //   851: aload_1
    //   852: monitorexit
    //   853: aload 6
    //   855: athrow
    // Local variable table:
    //   start	length	slot	name	signature
    //   0	856	0	this	h
    //   0	856	1	paramMessage	android.os.Message
    //   10	18	2	i	int
    //   15	38	3	j	int
    //   17	586	4	k	int
    //   20	758	5	m	int
    //   23	86	6	localk0	m6.k0
    //   119	9	6	localObject1	Object
    //   383	170	6	localObject2	Object
    //   561	9	6	localObject3	Object
    //   639	109	6	localObject4	Object
    //   752	5	6	localObject5	Object
    //   759	5	6	localObject6	Object
    //   766	5	6	localObject7	Object
    //   849	5	6	localObject8	Object
    //   368	289	7	localObject9	Object
    //   621	69	8	localObject10	Object
    // Exception table:
    //   from	to	target	type
    //   100	116	119	finally
    //   121	123	119	finally
    //   80	89	126	finally
    //   127	130	126	finally
    //   544	560	561	finally
    //   563	565	561	finally
    //   524	533	568	finally
    //   569	572	568	finally
    //   688	694	697	java/lang/RuntimeException
    //   730	745	746	finally
    //   747	750	746	finally
    //   711	718	752	finally
    //   754	756	752	finally
    //   702	709	759	finally
    //   761	763	759	finally
    //   617	681	766	finally
    //   681	683	766	finally
    //   768	770	766	finally
    //   827	842	843	finally
    //   844	847	843	finally
    //   808	815	849	finally
    //   851	853	849	finally
  }
}

/* Location:
 * Qualified Name:     com.google.android.gms.common.internal.h
 * Java Class Version: 6 (50.0)
 * JD-Core Version:    0.7.1
 */