package y1;

public final class o
{
  public static final o a = new o();
  public static final String b = o.class.getName();
  
  /* Error */
  public static final void a(a parama, H paramH)
  {
    // Byte code:
    //   0: ldc 2
    //   2: monitorenter
    //   3: ldc 2
    //   5: invokestatic 32	T1/a:d	(Ljava/lang/Object;)Z
    //   8: istore_2
    //   9: iload_2
    //   10: ifeq +7 -> 17
    //   13: ldc 2
    //   15: monitorexit
    //   16: return
    //   17: aload_0
    //   18: ldc 34
    //   20: invokestatic 40	kotlin/jvm/internal/Intrinsics:checkNotNullParameter	(Ljava/lang/Object;Ljava/lang/String;)V
    //   23: aload_1
    //   24: ldc 42
    //   26: invokestatic 40	kotlin/jvm/internal/Intrinsics:checkNotNullParameter	(Ljava/lang/Object;Ljava/lang/String;)V
    //   29: invokestatic 46	G1/g:b	()V
    //   32: invokestatic 51	y1/g:a	()Ly1/G;
    //   35: astore_3
    //   36: aload_3
    //   37: aload_0
    //   38: aload_1
    //   39: invokevirtual 56	y1/H:d	()Ljava/util/List;
    //   42: invokevirtual 61	y1/G:a	(Ly1/a;Ljava/util/List;)V
    //   45: aload_3
    //   46: invokestatic 64	y1/g:b	(Ly1/G;)V
    //   49: ldc 2
    //   51: monitorexit
    //   52: return
    //   53: astore_0
    //   54: aload_0
    //   55: ldc 2
    //   57: invokestatic 67	T1/a:b	(Ljava/lang/Throwable;Ljava/lang/Object;)V
    //   60: ldc 2
    //   62: monitorexit
    //   63: return
    //   64: astore_0
    //   65: ldc 2
    //   67: monitorexit
    //   68: aload_0
    //   69: athrow
    // Local variable table:
    //   start	length	slot	name	signature
    //   0	70	0	parama	a
    //   0	70	1	paramH	H
    //   8	2	2	bool	boolean
    //   35	11	3	localG	G
    // Exception table:
    //   from	to	target	type
    //   17	49	53	finally
    //   3	9	64	finally
    //   54	60	64	finally
  }
  
  /* Error */
  public static final void b(f paramf)
  {
    // Byte code:
    //   0: ldc 2
    //   2: monitorenter
    //   3: ldc 2
    //   5: invokestatic 32	T1/a:d	(Ljava/lang/Object;)Z
    //   8: istore_1
    //   9: iload_1
    //   10: ifeq +7 -> 17
    //   13: ldc 2
    //   15: monitorexit
    //   16: return
    //   17: aload_0
    //   18: ldc 70
    //   20: invokestatic 40	kotlin/jvm/internal/Intrinsics:checkNotNullParameter	(Ljava/lang/Object;Ljava/lang/String;)V
    //   23: invokestatic 46	G1/g:b	()V
    //   26: invokestatic 51	y1/g:a	()Ly1/G;
    //   29: astore_2
    //   30: aload_0
    //   31: invokevirtual 76	y1/f:f	()Ljava/util/Set;
    //   34: invokeinterface 82 1 0
    //   39: astore_3
    //   40: aload_3
    //   41: invokeinterface 88 1 0
    //   46: ifeq +60 -> 106
    //   49: aload_3
    //   50: invokeinterface 92 1 0
    //   55: checkcast 94	y1/a
    //   58: astore 4
    //   60: aload_0
    //   61: aload 4
    //   63: invokevirtual 98	y1/f:c	(Ly1/a;)Ly1/H;
    //   66: astore 5
    //   68: aload 5
    //   70: ifnull +21 -> 91
    //   73: aload_2
    //   74: aload 4
    //   76: aload 5
    //   78: invokevirtual 56	y1/H:d	()Ljava/util/List;
    //   81: invokevirtual 61	y1/G:a	(Ly1/a;Ljava/util/List;)V
    //   84: goto -44 -> 40
    //   87: astore_0
    //   88: goto +26 -> 114
    //   91: new 100	java/lang/IllegalStateException
    //   94: astore_0
    //   95: aload_0
    //   96: ldc 102
    //   98: invokevirtual 105	java/lang/Object:toString	()Ljava/lang/String;
    //   101: invokespecial 108	java/lang/IllegalStateException:<init>	(Ljava/lang/String;)V
    //   104: aload_0
    //   105: athrow
    //   106: aload_2
    //   107: invokestatic 64	y1/g:b	(Ly1/G;)V
    //   110: ldc 2
    //   112: monitorexit
    //   113: return
    //   114: aload_0
    //   115: ldc 2
    //   117: invokestatic 67	T1/a:b	(Ljava/lang/Throwable;Ljava/lang/Object;)V
    //   120: ldc 2
    //   122: monitorexit
    //   123: return
    //   124: astore_0
    //   125: ldc 2
    //   127: monitorexit
    //   128: aload_0
    //   129: athrow
    // Local variable table:
    //   start	length	slot	name	signature
    //   0	130	0	paramf	f
    //   8	2	1	bool	boolean
    //   29	78	2	localG	G
    //   39	11	3	localIterator	java.util.Iterator
    //   58	17	4	locala	a
    //   66	11	5	localH	H
    // Exception table:
    //   from	to	target	type
    //   17	40	87	finally
    //   40	68	87	finally
    //   73	84	87	finally
    //   91	106	87	finally
    //   106	110	87	finally
    //   3	9	124	finally
    //   114	120	124	finally
  }
}

/* Location:
 * Qualified Name:     y1.o
 * Java Class Version: 6 (50.0)
 * JD-Core Version:    0.7.1
 */