package p2;

import android.content.Context;
import q1.b;

public final class n0
  extends b
{
  public final Context c;
  
  public n0(Context paramContext)
  {
    super(9, 10);
    c = paramContext;
  }
  
  /* Error */
  public final void a(u1.c paramc)
  {
    // Byte code:
    //   0: aload_1
    //   1: ldc 18
    //   3: invokevirtual 24	u1/c:m	(Ljava/lang/String;)V
    //   6: aload_0
    //   7: getfield 13	p2/n0:c	Landroid/content/Context;
    //   10: ldc 26
    //   12: iconst_0
    //   13: invokevirtual 32	android/content/Context:getSharedPreferences	(Ljava/lang/String;I)Landroid/content/SharedPreferences;
    //   16: astore_2
    //   17: aload_2
    //   18: ldc 34
    //   20: invokeinterface 40 2 0
    //   25: ifne +14 -> 39
    //   28: aload_2
    //   29: ldc 42
    //   31: invokeinterface 40 2 0
    //   36: ifeq +103 -> 139
    //   39: lconst_0
    //   40: lstore_3
    //   41: aload_2
    //   42: ldc 42
    //   44: lconst_0
    //   45: invokeinterface 46 4 0
    //   50: lstore 5
    //   52: aload_2
    //   53: ldc 34
    //   55: iconst_0
    //   56: invokeinterface 50 3 0
    //   61: ifeq +5 -> 66
    //   64: lconst_1
    //   65: lstore_3
    //   66: aload_1
    //   67: invokevirtual 54	u1/c:h	()V
    //   70: aload_1
    //   71: ldc 56
    //   73: iconst_2
    //   74: anewarray 58	java/lang/Object
    //   77: dup
    //   78: iconst_0
    //   79: ldc 42
    //   81: aastore
    //   82: dup
    //   83: iconst_1
    //   84: lload 5
    //   86: invokestatic 64	java/lang/Long:valueOf	(J)Ljava/lang/Long;
    //   89: aastore
    //   90: invokevirtual 68	u1/c:f	(Ljava/lang/String;[Ljava/lang/Object;)V
    //   93: aload_1
    //   94: ldc 56
    //   96: iconst_2
    //   97: anewarray 58	java/lang/Object
    //   100: dup
    //   101: iconst_0
    //   102: ldc 34
    //   104: aastore
    //   105: dup
    //   106: iconst_1
    //   107: lload_3
    //   108: invokestatic 64	java/lang/Long:valueOf	(J)Ljava/lang/Long;
    //   111: aastore
    //   112: invokevirtual 68	u1/c:f	(Ljava/lang/String;[Ljava/lang/Object;)V
    //   115: aload_2
    //   116: invokeinterface 72 1 0
    //   121: invokeinterface 77 1 0
    //   126: invokeinterface 80 1 0
    //   131: aload_1
    //   132: invokevirtual 83	u1/c:G	()V
    //   135: aload_1
    //   136: invokevirtual 86	u1/c:X	()V
    //   139: aload_0
    //   140: getfield 13	p2/n0:c	Landroid/content/Context;
    //   143: astore_2
    //   144: aload_2
    //   145: ldc 88
    //   147: invokestatic 94	ec/i:e	(Ljava/lang/Object;Ljava/lang/String;)V
    //   150: aload_2
    //   151: ldc 96
    //   153: iconst_0
    //   154: invokevirtual 32	android/content/Context:getSharedPreferences	(Ljava/lang/String;I)Landroid/content/SharedPreferences;
    //   157: astore_2
    //   158: aload_2
    //   159: ldc 98
    //   161: invokeinterface 40 2 0
    //   166: ifne +14 -> 180
    //   169: aload_2
    //   170: ldc 98
    //   172: invokeinterface 40 2 0
    //   177: ifeq +99 -> 276
    //   180: aload_2
    //   181: ldc 98
    //   183: iconst_0
    //   184: invokeinterface 102 3 0
    //   189: istore 7
    //   191: aload_2
    //   192: ldc 104
    //   194: iconst_0
    //   195: invokeinterface 102 3 0
    //   200: istore 8
    //   202: aload_1
    //   203: invokevirtual 54	u1/c:h	()V
    //   206: aload_1
    //   207: ldc 56
    //   209: iconst_2
    //   210: anewarray 58	java/lang/Object
    //   213: dup
    //   214: iconst_0
    //   215: ldc 98
    //   217: aastore
    //   218: dup
    //   219: iconst_1
    //   220: iload 7
    //   222: invokestatic 109	java/lang/Integer:valueOf	(I)Ljava/lang/Integer;
    //   225: aastore
    //   226: invokevirtual 68	u1/c:f	(Ljava/lang/String;[Ljava/lang/Object;)V
    //   229: aload_1
    //   230: ldc 56
    //   232: iconst_2
    //   233: anewarray 58	java/lang/Object
    //   236: dup
    //   237: iconst_0
    //   238: ldc 104
    //   240: aastore
    //   241: dup
    //   242: iconst_1
    //   243: iload 8
    //   245: invokestatic 109	java/lang/Integer:valueOf	(I)Ljava/lang/Integer;
    //   248: aastore
    //   249: invokevirtual 68	u1/c:f	(Ljava/lang/String;[Ljava/lang/Object;)V
    //   252: aload_2
    //   253: invokeinterface 72 1 0
    //   258: invokeinterface 77 1 0
    //   263: invokeinterface 80 1 0
    //   268: aload_1
    //   269: invokevirtual 83	u1/c:G	()V
    //   272: aload_1
    //   273: invokevirtual 86	u1/c:X	()V
    //   276: return
    //   277: astore_2
    //   278: aload_1
    //   279: invokevirtual 86	u1/c:X	()V
    //   282: aload_2
    //   283: athrow
    //   284: astore_2
    //   285: aload_1
    //   286: invokevirtual 86	u1/c:X	()V
    //   289: aload_2
    //   290: athrow
    // Local variable table:
    //   start	length	slot	name	signature
    //   0	291	0	this	n0
    //   0	291	1	paramc	u1.c
    //   16	237	2	localObject1	Object
    //   277	6	2	localObject2	Object
    //   284	6	2	localObject3	Object
    //   40	68	3	l1	long
    //   50	35	5	l2	long
    //   189	32	7	i	int
    //   200	44	8	j	int
    // Exception table:
    //   from	to	target	type
    //   206	272	277	finally
    //   70	135	284	finally
  }
}

/* Location:
 * Qualified Name:     p2.n0
 * Java Class Version: 6 (50.0)
 * JD-Core Version:    0.7.1
 */