package p2;

import z2.c;

public final class o0
  implements Runnable
{
  public o0(q0 paramq0, c paramc) {}
  
  /* Error */
  public final void run()
  {
    // Byte code:
    //   0: aload_0
    //   1: getfield 14	p2/o0:b	Lp2/q0;
    //   4: getfield 27	p2/q0:x	Lz2/c;
    //   7: getfield 32	z2/a:a	Ljava/lang/Object;
    //   10: instanceof 34
    //   13: ifeq +4 -> 17
    //   16: return
    //   17: aload_0
    //   18: getfield 16	p2/o0:a	Ls7/e;
    //   21: invokeinterface 40 1 0
    //   26: pop
    //   27: invokestatic 46	o2/j:d	()Lo2/j;
    //   30: astore_1
    //   31: getstatic 50	p2/q0:z	Ljava/lang/String;
    //   34: astore_2
    //   35: new 52	java/lang/StringBuilder
    //   38: astore_3
    //   39: aload_3
    //   40: invokespecial 53	java/lang/StringBuilder:<init>	()V
    //   43: aload_3
    //   44: ldc 55
    //   46: invokevirtual 59	java/lang/StringBuilder:append	(Ljava/lang/String;)Ljava/lang/StringBuilder;
    //   49: pop
    //   50: aload_3
    //   51: aload_0
    //   52: getfield 14	p2/o0:b	Lp2/q0;
    //   55: getfield 63	p2/q0:c	Lx2/s;
    //   58: getfield 67	x2/s:c	Ljava/lang/String;
    //   61: invokevirtual 59	java/lang/StringBuilder:append	(Ljava/lang/String;)Ljava/lang/StringBuilder;
    //   64: pop
    //   65: aload_1
    //   66: aload_2
    //   67: aload_3
    //   68: invokevirtual 71	java/lang/StringBuilder:toString	()Ljava/lang/String;
    //   71: invokevirtual 74	o2/j:a	(Ljava/lang/String;Ljava/lang/String;)V
    //   74: aload_0
    //   75: getfield 14	p2/o0:b	Lp2/q0;
    //   78: astore_1
    //   79: aload_1
    //   80: getfield 27	p2/q0:x	Lz2/c;
    //   83: aload_1
    //   84: getfield 77	p2/q0:d	Landroidx/work/d;
    //   87: invokevirtual 83	androidx/work/d:h	()Lz2/c;
    //   90: invokevirtual 89	z2/c:k	(Ls7/e;)Z
    //   93: pop
    //   94: goto +16 -> 110
    //   97: astore_1
    //   98: aload_0
    //   99: getfield 14	p2/o0:b	Lp2/q0;
    //   102: getfield 27	p2/q0:x	Lz2/c;
    //   105: aload_1
    //   106: invokevirtual 93	z2/c:j	(Ljava/lang/Throwable;)Z
    //   109: pop
    //   110: return
    // Local variable table:
    //   start	length	slot	name	signature
    //   0	111	0	this	o0
    //   30	54	1	localObject	Object
    //   97	9	1	localThrowable	Throwable
    //   34	33	2	str	String
    //   38	30	3	localStringBuilder	StringBuilder
    // Exception table:
    //   from	to	target	type
    //   17	94	97	finally
  }
}

/* Location:
 * Qualified Name:     p2.o0
 * Java Class Version: 6 (50.0)
 * JD-Core Version:    0.7.1
 */