package p2;

public final class p0
  implements Runnable
{
  /* Error */
  public final void run()
  {
    // Byte code:
    //   0: aload_0
    //   1: getfield 14	p2/p0:b	Lp2/q0;
    //   4: getfield 34	p2/q0:x	Lz2/c;
    //   7: invokevirtual 40	z2/a:get	()Ljava/lang/Object;
    //   10: checkcast 42	androidx/work/d$a
    //   13: astore_1
    //   14: aload_1
    //   15: ifnonnull +53 -> 68
    //   18: invokestatic 48	o2/j:d	()Lo2/j;
    //   21: astore_1
    //   22: getstatic 51	p2/q0:z	Ljava/lang/String;
    //   25: astore_2
    //   26: new 53	java/lang/StringBuilder
    //   29: astore_3
    //   30: aload_3
    //   31: invokespecial 54	java/lang/StringBuilder:<init>	()V
    //   34: aload_3
    //   35: aload_0
    //   36: getfield 14	p2/p0:b	Lp2/q0;
    //   39: getfield 58	p2/q0:c	Lx2/s;
    //   42: getfield 62	x2/s:c	Ljava/lang/String;
    //   45: invokevirtual 66	java/lang/StringBuilder:append	(Ljava/lang/String;)Ljava/lang/StringBuilder;
    //   48: pop
    //   49: aload_3
    //   50: ldc 68
    //   52: invokevirtual 66	java/lang/StringBuilder:append	(Ljava/lang/String;)Ljava/lang/StringBuilder;
    //   55: pop
    //   56: aload_1
    //   57: aload_2
    //   58: aload_3
    //   59: invokevirtual 72	java/lang/StringBuilder:toString	()Ljava/lang/String;
    //   62: invokevirtual 75	o2/j:b	(Ljava/lang/String;Ljava/lang/String;)V
    //   65: goto +195 -> 260
    //   68: invokestatic 48	o2/j:d	()Lo2/j;
    //   71: astore_2
    //   72: getstatic 51	p2/q0:z	Ljava/lang/String;
    //   75: astore 4
    //   77: new 53	java/lang/StringBuilder
    //   80: astore_3
    //   81: aload_3
    //   82: invokespecial 54	java/lang/StringBuilder:<init>	()V
    //   85: aload_3
    //   86: aload_0
    //   87: getfield 14	p2/p0:b	Lp2/q0;
    //   90: getfield 58	p2/q0:c	Lx2/s;
    //   93: getfield 62	x2/s:c	Ljava/lang/String;
    //   96: invokevirtual 66	java/lang/StringBuilder:append	(Ljava/lang/String;)Ljava/lang/StringBuilder;
    //   99: pop
    //   100: aload_3
    //   101: ldc 77
    //   103: invokevirtual 66	java/lang/StringBuilder:append	(Ljava/lang/String;)Ljava/lang/StringBuilder;
    //   106: pop
    //   107: aload_3
    //   108: aload_1
    //   109: invokevirtual 80	java/lang/StringBuilder:append	(Ljava/lang/Object;)Ljava/lang/StringBuilder;
    //   112: pop
    //   113: aload_3
    //   114: ldc 82
    //   116: invokevirtual 66	java/lang/StringBuilder:append	(Ljava/lang/String;)Ljava/lang/StringBuilder;
    //   119: pop
    //   120: aload_2
    //   121: aload 4
    //   123: aload_3
    //   124: invokevirtual 72	java/lang/StringBuilder:toString	()Ljava/lang/String;
    //   127: invokevirtual 84	o2/j:a	(Ljava/lang/String;Ljava/lang/String;)V
    //   130: aload_0
    //   131: getfield 14	p2/p0:b	Lp2/q0;
    //   134: aload_1
    //   135: putfield 88	p2/q0:f	Landroidx/work/d$a;
    //   138: goto +122 -> 260
    //   141: astore_3
    //   142: goto +126 -> 268
    //   145: astore_3
    //   146: goto +4 -> 150
    //   149: astore_3
    //   150: invokestatic 48	o2/j:d	()Lo2/j;
    //   153: astore 4
    //   155: getstatic 51	p2/q0:z	Ljava/lang/String;
    //   158: astore_2
    //   159: new 53	java/lang/StringBuilder
    //   162: astore_1
    //   163: aload_1
    //   164: invokespecial 54	java/lang/StringBuilder:<init>	()V
    //   167: aload_1
    //   168: aload_0
    //   169: getfield 16	p2/p0:a	Ljava/lang/String;
    //   172: invokevirtual 66	java/lang/StringBuilder:append	(Ljava/lang/String;)Ljava/lang/StringBuilder;
    //   175: pop
    //   176: aload_1
    //   177: ldc 90
    //   179: invokevirtual 66	java/lang/StringBuilder:append	(Ljava/lang/String;)Ljava/lang/StringBuilder;
    //   182: pop
    //   183: aload 4
    //   185: aload_2
    //   186: aload_1
    //   187: invokevirtual 72	java/lang/StringBuilder:toString	()Ljava/lang/String;
    //   190: aload_3
    //   191: invokevirtual 93	o2/j:c	(Ljava/lang/String;Ljava/lang/String;Ljava/lang/Throwable;)V
    //   194: goto +66 -> 260
    //   197: astore_1
    //   198: invokestatic 48	o2/j:d	()Lo2/j;
    //   201: astore_2
    //   202: getstatic 51	p2/q0:z	Ljava/lang/String;
    //   205: astore_3
    //   206: new 53	java/lang/StringBuilder
    //   209: astore 4
    //   211: aload 4
    //   213: invokespecial 54	java/lang/StringBuilder:<init>	()V
    //   216: aload 4
    //   218: aload_0
    //   219: getfield 16	p2/p0:a	Ljava/lang/String;
    //   222: invokevirtual 66	java/lang/StringBuilder:append	(Ljava/lang/String;)Ljava/lang/StringBuilder;
    //   225: pop
    //   226: aload 4
    //   228: ldc 95
    //   230: invokevirtual 66	java/lang/StringBuilder:append	(Ljava/lang/String;)Ljava/lang/StringBuilder;
    //   233: pop
    //   234: aload 4
    //   236: invokevirtual 72	java/lang/StringBuilder:toString	()Ljava/lang/String;
    //   239: astore 4
    //   241: aload_2
    //   242: checkcast 97	o2/j$a
    //   245: getfield 100	o2/j$a:c	I
    //   248: iconst_4
    //   249: if_icmpgt +11 -> 260
    //   252: aload_3
    //   253: aload 4
    //   255: aload_1
    //   256: invokestatic 106	android/util/Log:i	(Ljava/lang/String;Ljava/lang/String;Ljava/lang/Throwable;)I
    //   259: pop
    //   260: aload_0
    //   261: getfield 14	p2/p0:b	Lp2/q0;
    //   264: invokevirtual 108	p2/q0:c	()V
    //   267: return
    //   268: aload_0
    //   269: getfield 14	p2/p0:b	Lp2/q0;
    //   272: invokevirtual 108	p2/q0:c	()V
    //   275: aload_3
    //   276: athrow
    // Local variable table:
    //   start	length	slot	name	signature
    //   0	277	0	this	p0
    //   13	174	1	localObject1	Object
    //   197	59	1	localCancellationException	java.util.concurrent.CancellationException
    //   25	217	2	localObject2	Object
    //   29	95	3	localStringBuilder	StringBuilder
    //   141	1	3	localObject3	Object
    //   145	1	3	localExecutionException	java.util.concurrent.ExecutionException
    //   149	42	3	localInterruptedException	InterruptedException
    //   205	71	3	str	String
    //   75	179	4	localObject4	Object
    // Exception table:
    //   from	to	target	type
    //   0	14	141	finally
    //   18	65	141	finally
    //   68	138	141	finally
    //   150	194	141	finally
    //   198	260	141	finally
    //   0	14	145	java/util/concurrent/ExecutionException
    //   18	65	145	java/util/concurrent/ExecutionException
    //   68	138	145	java/util/concurrent/ExecutionException
    //   0	14	149	java/lang/InterruptedException
    //   18	65	149	java/lang/InterruptedException
    //   68	138	149	java/lang/InterruptedException
    //   0	14	197	java/util/concurrent/CancellationException
    //   18	65	197	java/util/concurrent/CancellationException
    //   68	138	197	java/util/concurrent/CancellationException
  }
}

/* Location:
 * Qualified Name:     p2.p0
 * Java Class Version: 6 (50.0)
 * JD-Core Version:    0.7.1
 */