package x2;

import java.util.List;
import java.util.concurrent.Callable;
import p1.l;

public final class v
  implements Callable<List<s.c>>
{
  /* Error */
  public final Object call()
  {
    // Byte code:
    //   0: aload_0
    //   1: getfield 15	x2/v:b	Lx2/u;
    //   4: getfield 29	x2/u:a	Lp1/j;
    //   7: invokevirtual 34	p1/j:c	()V
    //   10: aload_0
    //   11: getfield 15	x2/v:b	Lx2/u;
    //   14: getfield 29	x2/u:a	Lp1/j;
    //   17: aload_0
    //   18: getfield 17	x2/v:a	Lp1/l;
    //   21: iconst_1
    //   22: invokestatic 40	b/z:o	(Lp1/j;Lp1/l;Z)Landroid/database/Cursor;
    //   25: astore_1
    //   26: new 42	java/util/HashMap
    //   29: astore_2
    //   30: aload_2
    //   31: invokespecial 43	java/util/HashMap:<init>	()V
    //   34: new 42	java/util/HashMap
    //   37: astore_3
    //   38: aload_3
    //   39: invokespecial 43	java/util/HashMap:<init>	()V
    //   42: aload_1
    //   43: invokeinterface 49 1 0
    //   48: ifeq +86 -> 134
    //   51: aload_1
    //   52: iconst_0
    //   53: invokeinterface 53 2 0
    //   58: astore 4
    //   60: aload_2
    //   61: aload 4
    //   63: invokevirtual 57	java/util/HashMap:get	(Ljava/lang/Object;)Ljava/lang/Object;
    //   66: checkcast 59	java/util/ArrayList
    //   69: ifnonnull +22 -> 91
    //   72: new 59	java/util/ArrayList
    //   75: astore 5
    //   77: aload 5
    //   79: invokespecial 60	java/util/ArrayList:<init>	()V
    //   82: aload_2
    //   83: aload 4
    //   85: aload 5
    //   87: invokevirtual 64	java/util/HashMap:put	(Ljava/lang/Object;Ljava/lang/Object;)Ljava/lang/Object;
    //   90: pop
    //   91: aload_1
    //   92: iconst_0
    //   93: invokeinterface 53 2 0
    //   98: astore 5
    //   100: aload_3
    //   101: aload 5
    //   103: invokevirtual 57	java/util/HashMap:get	(Ljava/lang/Object;)Ljava/lang/Object;
    //   106: checkcast 59	java/util/ArrayList
    //   109: ifnonnull -67 -> 42
    //   112: new 59	java/util/ArrayList
    //   115: astore 4
    //   117: aload 4
    //   119: invokespecial 60	java/util/ArrayList:<init>	()V
    //   122: aload_3
    //   123: aload 5
    //   125: aload 4
    //   127: invokevirtual 64	java/util/HashMap:put	(Ljava/lang/Object;Ljava/lang/Object;)Ljava/lang/Object;
    //   130: pop
    //   131: goto -89 -> 42
    //   134: aload_1
    //   135: iconst_m1
    //   136: invokeinterface 68 2 0
    //   141: pop
    //   142: aload_0
    //   143: getfield 15	x2/v:b	Lx2/u;
    //   146: aload_2
    //   147: invokevirtual 72	x2/u:D	(Ljava/util/HashMap;)V
    //   150: aload_0
    //   151: getfield 15	x2/v:b	Lx2/u;
    //   154: aload_3
    //   155: invokevirtual 75	x2/u:C	(Ljava/util/HashMap;)V
    //   158: new 59	java/util/ArrayList
    //   161: astore 6
    //   163: aload 6
    //   165: aload_1
    //   166: invokeinterface 79 1 0
    //   171: invokespecial 82	java/util/ArrayList:<init>	(I)V
    //   174: aload_1
    //   175: invokeinterface 49 1 0
    //   180: ifeq +485 -> 665
    //   183: aload_1
    //   184: iconst_0
    //   185: invokeinterface 85 2 0
    //   190: ifeq +9 -> 199
    //   193: aconst_null
    //   194: astore 5
    //   196: goto +12 -> 208
    //   199: aload_1
    //   200: iconst_0
    //   201: invokeinterface 53 2 0
    //   206: astore 5
    //   208: aload_1
    //   209: iconst_1
    //   210: invokeinterface 89 2 0
    //   215: invokestatic 95	x2/z:e	(I)Lo2/o$b;
    //   218: astore 7
    //   220: aload_1
    //   221: iconst_2
    //   222: invokeinterface 85 2 0
    //   227: ifeq +9 -> 236
    //   230: aconst_null
    //   231: astore 4
    //   233: goto +12 -> 245
    //   236: aload_1
    //   237: iconst_2
    //   238: invokeinterface 99 2 0
    //   243: astore 4
    //   245: aload 4
    //   247: invokestatic 104	androidx/work/c:a	([B)Landroidx/work/c;
    //   250: astore 8
    //   252: aload_1
    //   253: iconst_3
    //   254: invokeinterface 89 2 0
    //   259: istore 9
    //   261: aload_1
    //   262: iconst_4
    //   263: invokeinterface 89 2 0
    //   268: istore 10
    //   270: aload_1
    //   271: bipush 13
    //   273: invokeinterface 108 2 0
    //   278: lstore 11
    //   280: aload_1
    //   281: bipush 14
    //   283: invokeinterface 108 2 0
    //   288: lstore 13
    //   290: aload_1
    //   291: bipush 15
    //   293: invokeinterface 108 2 0
    //   298: lstore 15
    //   300: aload_1
    //   301: bipush 16
    //   303: invokeinterface 89 2 0
    //   308: invokestatic 110	x2/z:b	(I)I
    //   311: istore 17
    //   313: aload_1
    //   314: bipush 17
    //   316: invokeinterface 108 2 0
    //   321: lstore 18
    //   323: aload_1
    //   324: bipush 18
    //   326: invokeinterface 108 2 0
    //   331: lstore 20
    //   333: aload_1
    //   334: bipush 19
    //   336: invokeinterface 89 2 0
    //   341: istore 22
    //   343: aload_1
    //   344: bipush 20
    //   346: invokeinterface 108 2 0
    //   351: lstore 23
    //   353: aload_1
    //   354: bipush 21
    //   356: invokeinterface 89 2 0
    //   361: istore 25
    //   363: aload_1
    //   364: iconst_5
    //   365: invokeinterface 89 2 0
    //   370: invokestatic 112	x2/z:c	(I)I
    //   373: istore 26
    //   375: aload_1
    //   376: bipush 6
    //   378: invokeinterface 89 2 0
    //   383: ifeq +9 -> 392
    //   386: iconst_1
    //   387: istore 27
    //   389: goto +6 -> 395
    //   392: iconst_0
    //   393: istore 27
    //   395: aload_1
    //   396: bipush 7
    //   398: invokeinterface 89 2 0
    //   403: ifeq +9 -> 412
    //   406: iconst_1
    //   407: istore 28
    //   409: goto +6 -> 415
    //   412: iconst_0
    //   413: istore 28
    //   415: aload_1
    //   416: bipush 8
    //   418: invokeinterface 89 2 0
    //   423: ifeq +9 -> 432
    //   426: iconst_1
    //   427: istore 29
    //   429: goto +6 -> 435
    //   432: iconst_0
    //   433: istore 29
    //   435: aload_1
    //   436: bipush 9
    //   438: invokeinterface 89 2 0
    //   443: ifeq +9 -> 452
    //   446: iconst_1
    //   447: istore 30
    //   449: goto +6 -> 455
    //   452: iconst_0
    //   453: istore 30
    //   455: aload_1
    //   456: bipush 10
    //   458: invokeinterface 108 2 0
    //   463: lstore 31
    //   465: aload_1
    //   466: bipush 11
    //   468: invokeinterface 108 2 0
    //   473: lstore 33
    //   475: aload_1
    //   476: bipush 12
    //   478: invokeinterface 85 2 0
    //   483: ifeq +9 -> 492
    //   486: aconst_null
    //   487: astore 4
    //   489: goto +13 -> 502
    //   492: aload_1
    //   493: bipush 12
    //   495: invokeinterface 99 2 0
    //   500: astore 4
    //   502: aload 4
    //   504: invokestatic 115	x2/z:a	([B)Ljava/util/LinkedHashSet;
    //   507: astore 4
    //   509: new 117	o2/c
    //   512: astore 35
    //   514: aload 35
    //   516: iload 26
    //   518: iload 27
    //   520: iload 28
    //   522: iload 29
    //   524: iload 30
    //   526: lload 31
    //   528: lload 33
    //   530: aload 4
    //   532: invokespecial 120	o2/c:<init>	(IZZZZJJLjava/util/Set;)V
    //   535: aload_2
    //   536: aload_1
    //   537: iconst_0
    //   538: invokeinterface 53 2 0
    //   543: invokevirtual 57	java/util/HashMap:get	(Ljava/lang/Object;)Ljava/lang/Object;
    //   546: checkcast 59	java/util/ArrayList
    //   549: astore 36
    //   551: aload 36
    //   553: astore 4
    //   555: aload 36
    //   557: ifnonnull +13 -> 570
    //   560: new 59	java/util/ArrayList
    //   563: astore 4
    //   565: aload 4
    //   567: invokespecial 60	java/util/ArrayList:<init>	()V
    //   570: aload_3
    //   571: aload_1
    //   572: iconst_0
    //   573: invokeinterface 53 2 0
    //   578: invokevirtual 57	java/util/HashMap:get	(Ljava/lang/Object;)Ljava/lang/Object;
    //   581: checkcast 59	java/util/ArrayList
    //   584: astore 37
    //   586: aload 37
    //   588: astore 36
    //   590: aload 37
    //   592: ifnonnull +13 -> 605
    //   595: new 59	java/util/ArrayList
    //   598: astore 36
    //   600: aload 36
    //   602: invokespecial 60	java/util/ArrayList:<init>	()V
    //   605: new 122	x2/s$c
    //   608: astore 37
    //   610: aload 37
    //   612: aload 5
    //   614: aload 7
    //   616: aload 8
    //   618: lload 11
    //   620: lload 13
    //   622: lload 15
    //   624: aload 35
    //   626: iload 9
    //   628: iload 17
    //   630: lload 18
    //   632: lload 20
    //   634: iload 22
    //   636: iload 10
    //   638: lload 23
    //   640: iload 25
    //   642: aload 4
    //   644: aload 36
    //   646: invokespecial 125	x2/s$c:<init>	(Ljava/lang/String;Lo2/o$b;Landroidx/work/c;JJJLo2/c;IIJJIIJILjava/util/ArrayList;Ljava/util/ArrayList;)V
    //   649: aload 6
    //   651: aload 37
    //   653: invokevirtual 129	java/util/ArrayList:add	(Ljava/lang/Object;)Z
    //   656: pop
    //   657: goto -483 -> 174
    //   660: astore 5
    //   662: goto +32 -> 694
    //   665: aload_0
    //   666: getfield 15	x2/v:b	Lx2/u;
    //   669: getfield 29	x2/u:a	Lp1/j;
    //   672: invokevirtual 132	p1/j:n	()V
    //   675: aload_1
    //   676: invokeinterface 135 1 0
    //   681: aload_0
    //   682: getfield 15	x2/v:b	Lx2/u;
    //   685: getfield 29	x2/u:a	Lp1/j;
    //   688: invokevirtual 138	p1/j:j	()V
    //   691: aload 6
    //   693: areturn
    //   694: aload_1
    //   695: invokeinterface 135 1 0
    //   700: aload 5
    //   702: athrow
    //   703: astore 5
    //   705: aload_0
    //   706: getfield 15	x2/v:b	Lx2/u;
    //   709: getfield 29	x2/u:a	Lp1/j;
    //   712: invokevirtual 138	p1/j:j	()V
    //   715: aload 5
    //   717: athrow
    // Local variable table:
    //   start	length	slot	name	signature
    //   0	718	0	this	v
    //   25	670	1	localCursor	android.database.Cursor
    //   29	507	2	localHashMap1	java.util.HashMap
    //   37	534	3	localHashMap2	java.util.HashMap
    //   58	585	4	localObject1	Object
    //   75	538	5	localObject2	Object
    //   660	41	5	localObject3	Object
    //   703	13	5	localObject4	Object
    //   161	531	6	localArrayList	java.util.ArrayList
    //   218	397	7	localb	o2.o.b
    //   250	367	8	localc	androidx.work.c
    //   259	368	9	i	int
    //   268	369	10	j	int
    //   278	341	11	l1	long
    //   288	333	13	l2	long
    //   298	325	15	l3	long
    //   311	318	17	k	int
    //   321	310	18	l4	long
    //   331	302	20	l5	long
    //   341	294	22	m	int
    //   351	288	23	l6	long
    //   361	280	25	n	int
    //   373	144	26	i1	int
    //   387	132	27	bool1	boolean
    //   407	114	28	bool2	boolean
    //   427	96	29	bool3	boolean
    //   447	78	30	bool4	boolean
    //   463	64	31	l7	long
    //   473	56	33	l8	long
    //   512	113	35	localc1	o2.c
    //   549	96	36	localObject5	Object
    //   584	68	37	localObject6	Object
    // Exception table:
    //   from	to	target	type
    //   26	42	660	finally
    //   42	91	660	finally
    //   91	131	660	finally
    //   134	174	660	finally
    //   174	193	660	finally
    //   199	208	660	finally
    //   208	230	660	finally
    //   236	245	660	finally
    //   245	386	660	finally
    //   395	406	660	finally
    //   415	426	660	finally
    //   435	446	660	finally
    //   455	486	660	finally
    //   492	502	660	finally
    //   502	551	660	finally
    //   560	570	660	finally
    //   570	586	660	finally
    //   595	605	660	finally
    //   605	657	660	finally
    //   665	675	660	finally
    //   10	26	703	finally
    //   675	681	703	finally
    //   694	703	703	finally
  }
  
  public final void finalize()
  {
    a.H();
  }
}

/* Location:
 * Qualified Name:     x2.v
 * Java Class Version: 6 (50.0)
 * JD-Core Version:    0.7.1
 */