package com.appsflyer.internal;

import androidx.annotation.NonNull;
import java.io.BufferedReader;
import java.io.InputStream;
import java.io.InputStreamReader;
import java.io.Reader;
import java.net.HttpURLConnection;
import java.net.URLConnection;
import java.nio.charset.Charset;

public final class AFc1lSDK
{
  private final int AFInAppEventType;
  
  public AFc1lSDK(int paramInt)
  {
    AFInAppEventType = paramInt;
  }
  
  @NonNull
  private static String AFKeystoreWrapper(HttpURLConnection paramHttpURLConnection, boolean paramBoolean)
  {
    Object localObject1 = null;
    Object localObject3;
    if (paramBoolean) {
      try
      {
        InputStream localInputStream = paramHttpURLConnection.getInputStream();
      }
      finally
      {
        localStringBuilder = null;
        paramHttpURLConnection = (HttpURLConnection)localObject1;
        localObject1 = localStringBuilder;
        break label133;
      }
    } else {
      localObject3 = paramHttpURLConnection.getErrorStream();
    }
    if (localObject3 == null) {
      return "";
    }
    StringBuilder localStringBuilder = new java/lang/StringBuilder;
    localStringBuilder.<init>();
    paramHttpURLConnection = new java/io/InputStreamReader;
    paramHttpURLConnection.<init>((InputStream)localObject3, Charset.defaultCharset());
    try
    {
      localObject1 = new java/io/BufferedReader;
      ((BufferedReader)localObject1).<init>(paramHttpURLConnection);
      for (int i = 1;; i = 0)
      {
        try
        {
          localObject3 = ((BufferedReader)localObject1).readLine();
          if (localObject3 == null) {
            break;
          }
          if (i == 0) {
            localStringBuilder.append('\n');
          }
        }
        finally
        {
          break label133;
        }
        localStringBuilder.append(str1);
      }
      String str2 = localStringBuilder.toString();
      paramHttpURLConnection.close();
      ((Reader)localObject1).close();
      return str2;
    }
    finally
    {
      localObject1 = null;
    }
    label133:
    if (paramHttpURLConnection != null) {
      paramHttpURLConnection.close();
    }
    if (localObject1 != null) {
      ((Reader)localObject1).close();
    }
    throw ((Throwable)localObject4);
  }
  
  /* Error */
  public final AFc1gSDK<String> AFInAppEventParameterName(AFa1aSDK paramAFa1aSDK)
  {
    // Byte code:
    //   0: invokestatic 79	java/lang/System:currentTimeMillis	()J
    //   3: lstore_2
    //   4: aload_1
    //   5: invokevirtual 85	com/appsflyer/internal/AFa1aSDK:valueOf	()[B
    //   8: astore 4
    //   10: new 32	java/lang/StringBuilder
    //   13: astore 5
    //   15: new 32	java/lang/StringBuilder
    //   18: astore 6
    //   20: aload 6
    //   22: invokespecial 33	java/lang/StringBuilder:<init>	()V
    //   25: aload 6
    //   27: aload_1
    //   28: getfield 88	com/appsflyer/internal/AFa1aSDK:AFInAppEventParameterName	Ljava/lang/String;
    //   31: invokevirtual 60	java/lang/StringBuilder:append	(Ljava/lang/String;)Ljava/lang/StringBuilder;
    //   34: pop
    //   35: aload 6
    //   37: ldc 90
    //   39: invokevirtual 60	java/lang/StringBuilder:append	(Ljava/lang/String;)Ljava/lang/StringBuilder;
    //   42: pop
    //   43: aload 6
    //   45: aload_1
    //   46: getfield 92	com/appsflyer/internal/AFa1aSDK:valueOf	Ljava/lang/String;
    //   49: invokevirtual 60	java/lang/StringBuilder:append	(Ljava/lang/String;)Ljava/lang/StringBuilder;
    //   52: pop
    //   53: aload 5
    //   55: aload 6
    //   57: invokevirtual 63	java/lang/Object:toString	()Ljava/lang/String;
    //   60: invokespecial 95	java/lang/StringBuilder:<init>	(Ljava/lang/String;)V
    //   63: aload_1
    //   64: invokevirtual 85	com/appsflyer/internal/AFa1aSDK:valueOf	()[B
    //   67: astore 6
    //   69: aload_1
    //   70: invokevirtual 99	com/appsflyer/internal/AFa1aSDK:values	()Z
    //   73: istore 7
    //   75: iload 7
    //   77: ifeq +67 -> 144
    //   80: aload 6
    //   82: ifnull +62 -> 144
    //   85: aload_1
    //   86: invokevirtual 101	com/appsflyer/internal/AFa1aSDK:AFKeystoreWrapper	()Z
    //   89: ifeq +25 -> 114
    //   92: ldc 103
    //   94: astore 6
    //   96: goto +32 -> 128
    //   99: astore_1
    //   100: aconst_null
    //   101: astore 6
    //   103: goto +900 -> 1003
    //   106: astore 5
    //   108: aconst_null
    //   109: astore 6
    //   111: goto +751 -> 862
    //   114: new 105	java/lang/String
    //   117: dup
    //   118: aload 6
    //   120: invokestatic 41	java/nio/charset/Charset:defaultCharset	()Ljava/nio/charset/Charset;
    //   123: invokespecial 108	java/lang/String:<init>	([BLjava/nio/charset/Charset;)V
    //   126: astore 6
    //   128: aload 5
    //   130: ldc 110
    //   132: invokevirtual 60	java/lang/StringBuilder:append	(Ljava/lang/String;)Ljava/lang/StringBuilder;
    //   135: pop
    //   136: aload 5
    //   138: aload 6
    //   140: invokevirtual 60	java/lang/StringBuilder:append	(Ljava/lang/String;)Ljava/lang/StringBuilder;
    //   143: pop
    //   144: aload_1
    //   145: getfield 113	com/appsflyer/internal/AFa1aSDK:AFKeystoreWrapper	Ljava/util/Map;
    //   148: invokeinterface 119 1 0
    //   153: invokeinterface 125 1 0
    //   158: astore 8
    //   160: aload 8
    //   162: invokeinterface 130 1 0
    //   167: istore 7
    //   169: iload 7
    //   171: ifeq +66 -> 237
    //   174: aload 8
    //   176: invokeinterface 134 1 0
    //   181: checkcast 136	java/util/Map$Entry
    //   184: astore 6
    //   186: aload 5
    //   188: ldc -118
    //   190: invokevirtual 60	java/lang/StringBuilder:append	(Ljava/lang/String;)Ljava/lang/StringBuilder;
    //   193: pop
    //   194: aload 5
    //   196: aload 6
    //   198: invokeinterface 141 1 0
    //   203: checkcast 105	java/lang/String
    //   206: invokevirtual 60	java/lang/StringBuilder:append	(Ljava/lang/String;)Ljava/lang/StringBuilder;
    //   209: pop
    //   210: aload 5
    //   212: ldc -113
    //   214: invokevirtual 60	java/lang/StringBuilder:append	(Ljava/lang/String;)Ljava/lang/StringBuilder;
    //   217: pop
    //   218: aload 5
    //   220: aload 6
    //   222: invokeinterface 146 1 0
    //   227: checkcast 105	java/lang/String
    //   230: invokevirtual 60	java/lang/StringBuilder:append	(Ljava/lang/String;)Ljava/lang/StringBuilder;
    //   233: pop
    //   234: goto -74 -> 160
    //   237: new 32	java/lang/StringBuilder
    //   240: astore 6
    //   242: aload 6
    //   244: ldc -108
    //   246: invokespecial 95	java/lang/StringBuilder:<init>	(Ljava/lang/String;)V
    //   249: aload 6
    //   251: aload_1
    //   252: invokevirtual 152	java/lang/Object:hashCode	()I
    //   255: invokevirtual 155	java/lang/StringBuilder:append	(I)Ljava/lang/StringBuilder;
    //   258: pop
    //   259: aload 6
    //   261: ldc -99
    //   263: invokevirtual 60	java/lang/StringBuilder:append	(Ljava/lang/String;)Ljava/lang/StringBuilder;
    //   266: pop
    //   267: aload 6
    //   269: aload 5
    //   271: invokevirtual 160	java/lang/StringBuilder:append	(Ljava/lang/Object;)Ljava/lang/StringBuilder;
    //   274: pop
    //   275: aload 6
    //   277: invokevirtual 63	java/lang/Object:toString	()Ljava/lang/String;
    //   280: invokestatic 165	com/appsflyer/AFLogger:afDebugLog	(Ljava/lang/String;)V
    //   283: new 167	java/net/URL
    //   286: astore 6
    //   288: aload 6
    //   290: aload_1
    //   291: getfield 92	com/appsflyer/internal/AFa1aSDK:valueOf	Ljava/lang/String;
    //   294: invokespecial 168	java/net/URL:<init>	(Ljava/lang/String;)V
    //   297: aload 6
    //   299: invokevirtual 172	java/net/URL:openConnection	()Ljava/net/URLConnection;
    //   302: invokestatic 178	com/google/firebase/perf/network/FirebasePerfUrlConnection:instrument	(Ljava/lang/Object;)Ljava/lang/Object;
    //   305: checkcast 19	java/net/URLConnection
    //   308: checkcast 25	java/net/HttpURLConnection
    //   311: astore 6
    //   313: aload 6
    //   315: aload_1
    //   316: getfield 88	com/appsflyer/internal/AFa1aSDK:AFInAppEventParameterName	Ljava/lang/String;
    //   319: invokevirtual 181	java/net/HttpURLConnection:setRequestMethod	(Ljava/lang/String;)V
    //   322: aload_1
    //   323: invokevirtual 183	com/appsflyer/internal/AFa1aSDK:AFInAppEventParameterName	()Z
    //   326: ifeq +21 -> 347
    //   329: aload 6
    //   331: iconst_0
    //   332: invokevirtual 187	java/net/URLConnection:setUseCaches	(Z)V
    //   335: goto +12 -> 347
    //   338: astore_1
    //   339: goto +664 -> 1003
    //   342: astore 5
    //   344: goto +518 -> 862
    //   347: aload_1
    //   348: invokevirtual 189	com/appsflyer/internal/AFa1aSDK:afDebugLog	()Z
    //   351: ifne +9 -> 360
    //   354: aload 6
    //   356: iconst_0
    //   357: invokevirtual 192	java/net/HttpURLConnection:setInstanceFollowRedirects	(Z)V
    //   360: aload_0
    //   361: getfield 13	com/appsflyer/internal/AFc1lSDK:AFInAppEventType	I
    //   364: istore 9
    //   366: aload_1
    //   367: getfield 194	com/appsflyer/internal/AFa1aSDK:afDebugLog	I
    //   370: istore 10
    //   372: iload 10
    //   374: iconst_m1
    //   375: if_icmpeq +7 -> 382
    //   378: iload 10
    //   380: istore 9
    //   382: aload 6
    //   384: iload 9
    //   386: invokevirtual 197	java/net/URLConnection:setConnectTimeout	(I)V
    //   389: aload 6
    //   391: iload 9
    //   393: invokevirtual 200	java/net/URLConnection:setReadTimeout	(I)V
    //   396: aload_1
    //   397: invokevirtual 101	com/appsflyer/internal/AFa1aSDK:AFKeystoreWrapper	()Z
    //   400: ifeq +19 -> 419
    //   403: ldc -54
    //   405: astore 5
    //   407: goto +16 -> 423
    //   410: astore_1
    //   411: goto -72 -> 339
    //   414: astore 5
    //   416: goto -72 -> 344
    //   419: ldc -52
    //   421: astore 5
    //   423: aload 6
    //   425: ldc -50
    //   427: aload 5
    //   429: invokevirtual 210	java/net/URLConnection:addRequestProperty	(Ljava/lang/String;Ljava/lang/String;)V
    //   432: aload_1
    //   433: getfield 113	com/appsflyer/internal/AFa1aSDK:AFKeystoreWrapper	Ljava/util/Map;
    //   436: invokeinterface 119 1 0
    //   441: invokeinterface 125 1 0
    //   446: astore 5
    //   448: aload 5
    //   450: invokeinterface 130 1 0
    //   455: ifeq +43 -> 498
    //   458: aload 5
    //   460: invokeinterface 134 1 0
    //   465: checkcast 136	java/util/Map$Entry
    //   468: astore 8
    //   470: aload 6
    //   472: aload 8
    //   474: invokeinterface 141 1 0
    //   479: checkcast 105	java/lang/String
    //   482: aload 8
    //   484: invokeinterface 146 1 0
    //   489: checkcast 105	java/lang/String
    //   492: invokevirtual 213	java/net/URLConnection:setRequestProperty	(Ljava/lang/String;Ljava/lang/String;)V
    //   495: goto -47 -> 448
    //   498: iconst_1
    //   499: istore 7
    //   501: aload 4
    //   503: ifnull +93 -> 596
    //   506: aload 6
    //   508: iconst_1
    //   509: invokevirtual 216	java/net/URLConnection:setDoOutput	(Z)V
    //   512: new 32	java/lang/StringBuilder
    //   515: astore 5
    //   517: aload 5
    //   519: invokespecial 33	java/lang/StringBuilder:<init>	()V
    //   522: aload 5
    //   524: aload 4
    //   526: arraylength
    //   527: invokevirtual 155	java/lang/StringBuilder:append	(I)Ljava/lang/StringBuilder;
    //   530: pop
    //   531: aload 6
    //   533: ldc -38
    //   535: aload 5
    //   537: invokevirtual 63	java/lang/Object:toString	()Ljava/lang/String;
    //   540: invokevirtual 213	java/net/URLConnection:setRequestProperty	(Ljava/lang/String;Ljava/lang/String;)V
    //   543: new 220	java/io/BufferedOutputStream
    //   546: astore 8
    //   548: aload 8
    //   550: aload 6
    //   552: invokevirtual 224	java/net/URLConnection:getOutputStream	()Ljava/io/OutputStream;
    //   555: invokespecial 227	java/io/BufferedOutputStream:<init>	(Ljava/io/OutputStream;)V
    //   558: aload 8
    //   560: aload 4
    //   562: invokevirtual 233	java/io/OutputStream:write	([B)V
    //   565: aload 8
    //   567: invokevirtual 234	java/io/OutputStream:close	()V
    //   570: goto +26 -> 596
    //   573: astore 5
    //   575: goto +8 -> 583
    //   578: astore 5
    //   580: aconst_null
    //   581: astore 8
    //   583: aload 8
    //   585: ifnull +8 -> 593
    //   588: aload 8
    //   590: invokevirtual 234	java/io/OutputStream:close	()V
    //   593: aload 5
    //   595: athrow
    //   596: aload 6
    //   598: invokevirtual 237	java/net/HttpURLConnection:getResponseCode	()I
    //   601: bipush 100
    //   603: idiv
    //   604: iconst_2
    //   605: if_icmpne +6 -> 611
    //   608: goto +6 -> 614
    //   611: iconst_0
    //   612: istore 7
    //   614: aload_1
    //   615: invokevirtual 239	com/appsflyer/internal/AFa1aSDK:AFInAppEventType	()Z
    //   618: ifeq +15 -> 633
    //   621: aload 6
    //   623: iload 7
    //   625: invokestatic 241	com/appsflyer/internal/AFc1lSDK:AFKeystoreWrapper	(Ljava/net/HttpURLConnection;Z)Ljava/lang/String;
    //   628: astore 5
    //   630: goto +7 -> 637
    //   633: ldc 30
    //   635: astore 5
    //   637: invokestatic 79	java/lang/System:currentTimeMillis	()J
    //   640: lstore 11
    //   642: new 243	com/appsflyer/internal/AFc1kSDK
    //   645: astore 8
    //   647: aload 8
    //   649: lload 11
    //   651: lload_2
    //   652: lsub
    //   653: invokespecial 246	com/appsflyer/internal/AFc1kSDK:<init>	(J)V
    //   656: new 32	java/lang/StringBuilder
    //   659: astore 4
    //   661: aload 4
    //   663: ldc -8
    //   665: invokespecial 95	java/lang/StringBuilder:<init>	(Ljava/lang/String;)V
    //   668: aload 4
    //   670: aload 6
    //   672: invokevirtual 237	java/net/HttpURLConnection:getResponseCode	()I
    //   675: invokevirtual 155	java/lang/StringBuilder:append	(I)Ljava/lang/StringBuilder;
    //   678: pop
    //   679: aload 4
    //   681: ldc -6
    //   683: invokevirtual 60	java/lang/StringBuilder:append	(Ljava/lang/String;)Ljava/lang/StringBuilder;
    //   686: pop
    //   687: aload 4
    //   689: aload 6
    //   691: invokevirtual 253	java/net/HttpURLConnection:getResponseMessage	()Ljava/lang/String;
    //   694: invokevirtual 60	java/lang/StringBuilder:append	(Ljava/lang/String;)Ljava/lang/StringBuilder;
    //   697: pop
    //   698: aload 4
    //   700: ldc -1
    //   702: invokevirtual 60	java/lang/StringBuilder:append	(Ljava/lang/String;)Ljava/lang/StringBuilder;
    //   705: pop
    //   706: aload 4
    //   708: aload 5
    //   710: invokevirtual 60	java/lang/StringBuilder:append	(Ljava/lang/String;)Ljava/lang/StringBuilder;
    //   713: pop
    //   714: aload 4
    //   716: ldc_w 257
    //   719: invokevirtual 60	java/lang/StringBuilder:append	(Ljava/lang/String;)Ljava/lang/StringBuilder;
    //   722: pop
    //   723: aload 4
    //   725: aload 8
    //   727: getfield 260	com/appsflyer/internal/AFc1kSDK:AFKeystoreWrapper	J
    //   730: invokevirtual 263	java/lang/StringBuilder:append	(J)Ljava/lang/StringBuilder;
    //   733: pop
    //   734: aload 4
    //   736: ldc_w 265
    //   739: invokevirtual 60	java/lang/StringBuilder:append	(Ljava/lang/String;)Ljava/lang/StringBuilder;
    //   742: pop
    //   743: aload 4
    //   745: invokevirtual 63	java/lang/Object:toString	()Ljava/lang/String;
    //   748: astore 4
    //   750: new 32	java/lang/StringBuilder
    //   753: astore 13
    //   755: aload 13
    //   757: ldc -108
    //   759: invokespecial 95	java/lang/StringBuilder:<init>	(Ljava/lang/String;)V
    //   762: aload 13
    //   764: aload_1
    //   765: invokevirtual 152	java/lang/Object:hashCode	()I
    //   768: invokevirtual 155	java/lang/StringBuilder:append	(I)Ljava/lang/StringBuilder;
    //   771: pop
    //   772: aload 13
    //   774: ldc -99
    //   776: invokevirtual 60	java/lang/StringBuilder:append	(Ljava/lang/String;)Ljava/lang/StringBuilder;
    //   779: pop
    //   780: aload 13
    //   782: aload 4
    //   784: invokevirtual 60	java/lang/StringBuilder:append	(Ljava/lang/String;)Ljava/lang/StringBuilder;
    //   787: pop
    //   788: aload 13
    //   790: invokevirtual 63	java/lang/Object:toString	()Ljava/lang/String;
    //   793: invokestatic 165	com/appsflyer/AFLogger:afDebugLog	(Ljava/lang/String;)V
    //   796: new 267	java/util/HashMap
    //   799: astore 4
    //   801: aload 4
    //   803: aload 6
    //   805: invokevirtual 271	java/net/URLConnection:getHeaderFields	()Ljava/util/Map;
    //   808: invokespecial 274	java/util/HashMap:<init>	(Ljava/util/Map;)V
    //   811: aload 4
    //   813: aconst_null
    //   814: invokeinterface 277 2 0
    //   819: pop
    //   820: new 279	com/appsflyer/internal/AFc1gSDK
    //   823: dup
    //   824: aload 5
    //   826: aload 6
    //   828: invokevirtual 237	java/net/HttpURLConnection:getResponseCode	()I
    //   831: iload 7
    //   833: aload 4
    //   835: aload 8
    //   837: invokespecial 282	com/appsflyer/internal/AFc1gSDK:<init>	(Ljava/lang/Object;IZLjava/util/Map;Lcom/appsflyer/internal/AFc1kSDK;)V
    //   840: astore 5
    //   842: aload 6
    //   844: invokevirtual 285	java/net/HttpURLConnection:disconnect	()V
    //   847: aload 5
    //   849: areturn
    //   850: astore_1
    //   851: aconst_null
    //   852: astore 6
    //   854: goto +149 -> 1003
    //   857: astore 5
    //   859: aconst_null
    //   860: astore 6
    //   862: invokestatic 79	java/lang/System:currentTimeMillis	()J
    //   865: lstore 11
    //   867: new 243	com/appsflyer/internal/AFc1kSDK
    //   870: astore 8
    //   872: aload 8
    //   874: lload 11
    //   876: lload_2
    //   877: lsub
    //   878: invokespecial 246	com/appsflyer/internal/AFc1kSDK:<init>	(J)V
    //   881: new 32	java/lang/StringBuilder
    //   884: astore 4
    //   886: aload 4
    //   888: ldc_w 287
    //   891: invokespecial 95	java/lang/StringBuilder:<init>	(Ljava/lang/String;)V
    //   894: aload 4
    //   896: aload 5
    //   898: invokevirtual 160	java/lang/StringBuilder:append	(Ljava/lang/Object;)Ljava/lang/StringBuilder;
    //   901: pop
    //   902: aload 4
    //   904: ldc_w 257
    //   907: invokevirtual 60	java/lang/StringBuilder:append	(Ljava/lang/String;)Ljava/lang/StringBuilder;
    //   910: pop
    //   911: aload 4
    //   913: aload 8
    //   915: getfield 260	com/appsflyer/internal/AFc1kSDK:AFKeystoreWrapper	J
    //   918: invokevirtual 263	java/lang/StringBuilder:append	(J)Ljava/lang/StringBuilder;
    //   921: pop
    //   922: aload 4
    //   924: ldc_w 265
    //   927: invokevirtual 60	java/lang/StringBuilder:append	(Ljava/lang/String;)Ljava/lang/StringBuilder;
    //   930: pop
    //   931: aload 4
    //   933: invokevirtual 63	java/lang/Object:toString	()Ljava/lang/String;
    //   936: astore 13
    //   938: new 32	java/lang/StringBuilder
    //   941: astore 4
    //   943: aload 4
    //   945: ldc -108
    //   947: invokespecial 95	java/lang/StringBuilder:<init>	(Ljava/lang/String;)V
    //   950: aload 4
    //   952: aload_1
    //   953: invokevirtual 152	java/lang/Object:hashCode	()I
    //   956: invokevirtual 155	java/lang/StringBuilder:append	(I)Ljava/lang/StringBuilder;
    //   959: pop
    //   960: aload 4
    //   962: ldc -99
    //   964: invokevirtual 60	java/lang/StringBuilder:append	(Ljava/lang/String;)Ljava/lang/StringBuilder;
    //   967: pop
    //   968: aload 4
    //   970: aload 13
    //   972: invokevirtual 60	java/lang/StringBuilder:append	(Ljava/lang/String;)Ljava/lang/StringBuilder;
    //   975: pop
    //   976: aload 4
    //   978: invokevirtual 63	java/lang/Object:toString	()Ljava/lang/String;
    //   981: aload 5
    //   983: iconst_0
    //   984: iconst_0
    //   985: invokestatic 291	com/appsflyer/AFLogger:afErrorLog	(Ljava/lang/String;Ljava/lang/Throwable;ZZ)V
    //   988: new 293	com/appsflyer/internal/components/network/http/exceptions/HttpException
    //   991: astore_1
    //   992: aload_1
    //   993: aload 5
    //   995: aload 8
    //   997: invokespecial 296	com/appsflyer/internal/components/network/http/exceptions/HttpException:<init>	(Ljava/lang/Throwable;Lcom/appsflyer/internal/AFc1kSDK;)V
    //   1000: aload_1
    //   1001: athrow
    //   1002: astore_1
    //   1003: aload 6
    //   1005: ifnull +8 -> 1013
    //   1008: aload 6
    //   1010: invokevirtual 285	java/net/HttpURLConnection:disconnect	()V
    //   1013: aload_1
    //   1014: athrow
    // Local variable table:
    //   start	length	slot	name	signature
    //   0	1015	0	this	AFc1lSDK
    //   0	1015	1	paramAFa1aSDK	AFa1aSDK
    //   3	874	2	l1	long
    //   8	969	4	localObject1	Object
    //   13	41	5	localStringBuilder	StringBuilder
    //   106	164	5	localException1	Exception
    //   342	1	5	localException2	Exception
    //   405	1	5	str	String
    //   414	1	5	localException3	Exception
    //   421	115	5	localObject2	Object
    //   573	1	5	localObject3	Object
    //   578	16	5	localObject4	Object
    //   628	220	5	localObject5	Object
    //   857	137	5	localException4	Exception
    //   18	991	6	localObject6	Object
    //   73	759	7	bool	boolean
    //   158	838	8	localObject7	Object
    //   364	28	9	i	int
    //   370	9	10	j	int
    //   640	235	11	l2	long
    //   753	218	13	localObject8	Object
    // Exception table:
    //   from	to	target	type
    //   85	92	99	finally
    //   114	128	99	finally
    //   128	144	99	finally
    //   174	234	99	finally
    //   85	92	106	java/lang/Exception
    //   114	128	106	java/lang/Exception
    //   128	144	106	java/lang/Exception
    //   174	234	106	java/lang/Exception
    //   313	335	338	finally
    //   347	360	338	finally
    //   313	335	342	java/lang/Exception
    //   347	360	342	java/lang/Exception
    //   360	372	410	finally
    //   382	403	410	finally
    //   423	448	410	finally
    //   448	495	410	finally
    //   506	543	410	finally
    //   565	570	410	finally
    //   588	593	410	finally
    //   593	596	410	finally
    //   596	608	410	finally
    //   614	630	410	finally
    //   637	842	410	finally
    //   360	372	414	java/lang/Exception
    //   382	403	414	java/lang/Exception
    //   423	448	414	java/lang/Exception
    //   448	495	414	java/lang/Exception
    //   506	543	414	java/lang/Exception
    //   565	570	414	java/lang/Exception
    //   588	593	414	java/lang/Exception
    //   593	596	414	java/lang/Exception
    //   596	608	414	java/lang/Exception
    //   614	630	414	java/lang/Exception
    //   637	842	414	java/lang/Exception
    //   558	565	573	finally
    //   543	558	578	finally
    //   4	75	850	finally
    //   144	160	850	finally
    //   160	169	850	finally
    //   237	313	850	finally
    //   4	75	857	java/lang/Exception
    //   144	160	857	java/lang/Exception
    //   160	169	857	java/lang/Exception
    //   237	313	857	java/lang/Exception
    //   862	1002	1002	finally
  }
}

/* Location:
 * Qualified Name:     com.appsflyer.internal.AFc1lSDK
 * Java Class Version: 6 (50.0)
 * JD-Core Version:    0.7.1
 */