// 
// Decompiled by Procyon v1.0-SNAPSHOT
// 

package com.appsflyer.internal;

import kotlin.jvm.internal.Intrinsics;
import java.util.Map;
import org.jetbrains.annotations.NotNull;
import kotlin.Metadata;

@Metadata
public final class AFc1tSDK
{
    @NotNull
    private static String valueOf;
    @NotNull
    private byte[] AFInAppEventParameterName;
    private Map<String, String> AFKeystoreWrapper;
    private final int values;
    
    static {
        new AFa1wSDK((byte)0);
        AFc1tSDK.valueOf = "https://%smonitorsdk.%s/remote-debug/exception-manager";
    }
    
    public AFc1tSDK(@NotNull final byte[] afInAppEventParameterName, final Map<String, String> afKeystoreWrapper, final int values) {
        Intrinsics.checkNotNullParameter(afInAppEventParameterName, "");
        this.AFInAppEventParameterName = afInAppEventParameterName;
        this.AFKeystoreWrapper = afKeystoreWrapper;
        this.values = values;
    }
    
    public final boolean AFInAppEventParameterName() {
        // 
        // This method could not be decompiled.
        // 
        // Original Bytecode:
        // 
        //     3: lstore_2       
        //     4: aconst_null    
        //     5: astore          7
        //     7: getstatic       com/appsflyer/internal/AFc1tSDK.valueOf:Ljava/lang/String;
        //    10: iconst_2       
        //    11: anewarray       Ljava/lang/Object;
        //    14: dup            
        //    15: iconst_0       
        //    16: invokestatic    com/appsflyer/AppsFlyerLib.getInstance:()Lcom/appsflyer/AppsFlyerLib;
        //    19: invokevirtual   com/appsflyer/AppsFlyerLib.getHostPrefix:()Ljava/lang/String;
        //    22: aastore        
        //    23: dup            
        //    24: iconst_1       
        //    25: invokestatic    com/appsflyer/internal/AFa1eSDK.valueOf:()Lcom/appsflyer/internal/AFa1eSDK;
        //    28: invokevirtual   com/appsflyer/AppsFlyerLib.getHostName:()Ljava/lang/String;
        //    31: aastore        
        //    32: invokestatic    java/lang/String.format:(Ljava/lang/String;[Ljava/lang/Object;)Ljava/lang/String;
        //    35: astore          8
        //    37: aload           8
        //    39: ldc             ""
        //    41: invokestatic    kotlin/jvm/internal/Intrinsics.checkNotNullExpressionValue:(Ljava/lang/Object;Ljava/lang/String;)V
        //    44: aload           8
        //    46: ldc             ""
        //    48: invokestatic    kotlin/jvm/internal/Intrinsics.checkNotNullParameter:(Ljava/lang/Object;Ljava/lang/String;)V
        //    51: new             Ljava/net/URL;
        //    54: dup            
        //    55: aload           8
        //    57: invokespecial   java/net/URL.<init>:(Ljava/lang/String;)V
        //    60: invokevirtual   java/net/URL.openConnection:()Ljava/net/URLConnection;
        //    63: invokestatic    com/google/firebase/perf/network/FirebasePerfUrlConnection.instrument:(Ljava/lang/Object;)Ljava/lang/Object;
        //    66: checkcast       Ljava/net/URLConnection;
        //    69: astore          8
        //    71: aload           8
        //    73: ifnull          819
        //    76: aload           8
        //    78: checkcast       Ljava/net/HttpURLConnection;
        //    81: astore          8
        //    83: aload           8
        //    85: ldc             "POST"
        //    87: invokevirtual   java/net/HttpURLConnection.setRequestMethod:(Ljava/lang/String;)V
        //    90: new             Ljava/lang/StringBuilder;
        //    93: dup            
        //    94: invokespecial   java/lang/StringBuilder.<init>:()V
        //    97: astore          7
        //    99: aload           7
        //   101: aload           8
        //   103: invokevirtual   java/net/HttpURLConnection.getRequestMethod:()Ljava/lang/String;
        //   106: invokevirtual   java/lang/StringBuilder.append:(Ljava/lang/String;)Ljava/lang/StringBuilder;
        //   109: pop            
        //   110: aload           7
        //   112: bipush          58
        //   114: invokevirtual   java/lang/StringBuilder.append:(C)Ljava/lang/StringBuilder;
        //   117: pop            
        //   118: aload           7
        //   120: aload           8
        //   122: invokevirtual   java/net/URLConnection.getURL:()Ljava/net/URL;
        //   125: invokevirtual   java/lang/StringBuilder.append:(Ljava/lang/Object;)Ljava/lang/StringBuilder;
        //   128: pop            
        //   129: new             Ljava/lang/StringBuilder;
        //   132: dup            
        //   133: aload           7
        //   135: invokevirtual   java/lang/Object.toString:()Ljava/lang/String;
        //   138: invokespecial   java/lang/StringBuilder.<init>:(Ljava/lang/String;)V
        //   141: astore          7
        //   143: aload           7
        //   145: ldc             "\n length: "
        //   147: invokevirtual   java/lang/StringBuilder.append:(Ljava/lang/String;)Ljava/lang/StringBuilder;
        //   150: pop            
        //   151: aload           7
        //   153: new             Ljava/lang/String;
        //   156: dup            
        //   157: aload_0        
        //   158: getfield        com/appsflyer/internal/AFc1tSDK.AFInAppEventParameterName:[B
        //   161: getstatic       kotlin/text/b.b:Ljava/nio/charset/Charset;
        //   164: invokespecial   java/lang/String.<init>:([BLjava/nio/charset/Charset;)V
        //   167: invokevirtual   java/lang/String.length:()I
        //   170: invokevirtual   java/lang/StringBuilder.append:(I)Ljava/lang/StringBuilder;
        //   173: pop            
        //   174: aload_0        
        //   175: getfield        com/appsflyer/internal/AFc1tSDK.AFKeystoreWrapper:Ljava/util/Map;
        //   178: astore          9
        //   180: aload           9
        //   182: ifnull          272
        //   185: aload           9
        //   187: invokeinterface java/util/Map.entrySet:()Ljava/util/Set;
        //   192: invokeinterface java/util/Set.iterator:()Ljava/util/Iterator;
        //   197: astore          9
        //   199: aload           9
        //   201: invokeinterface java/util/Iterator.hasNext:()Z
        //   206: ifeq            272
        //   209: aload           9
        //   211: invokeinterface java/util/Iterator.next:()Ljava/lang/Object;
        //   216: checkcast       Ljava/util/Map$Entry;
        //   219: astore          10
        //   221: aload           7
        //   223: ldc             "\n "
        //   225: invokevirtual   java/lang/StringBuilder.append:(Ljava/lang/String;)Ljava/lang/StringBuilder;
        //   228: pop            
        //   229: aload           7
        //   231: aload           10
        //   233: invokeinterface java/util/Map$Entry.getKey:()Ljava/lang/Object;
        //   238: checkcast       Ljava/lang/String;
        //   241: invokevirtual   java/lang/StringBuilder.append:(Ljava/lang/String;)Ljava/lang/StringBuilder;
        //   244: pop            
        //   245: aload           7
        //   247: ldc             ": "
        //   249: invokevirtual   java/lang/StringBuilder.append:(Ljava/lang/String;)Ljava/lang/StringBuilder;
        //   252: pop            
        //   253: aload           7
        //   255: aload           10
        //   257: invokeinterface java/util/Map$Entry.getValue:()Ljava/lang/Object;
        //   262: checkcast       Ljava/lang/String;
        //   265: invokevirtual   java/lang/StringBuilder.append:(Ljava/lang/String;)Ljava/lang/StringBuilder;
        //   268: pop            
        //   269: goto            199
        //   272: new             Ljava/lang/StringBuilder;
        //   275: dup            
        //   276: ldc             "HTTP: ["
        //   278: invokespecial   java/lang/StringBuilder.<init>:(Ljava/lang/String;)V
        //   281: astore          9
        //   283: aload           9
        //   285: aload           8
        //   287: invokevirtual   java/lang/Object.hashCode:()I
        //   290: invokevirtual   java/lang/StringBuilder.append:(I)Ljava/lang/StringBuilder;
        //   293: pop            
        //   294: aload           9
        //   296: ldc             "] "
        //   298: invokevirtual   java/lang/StringBuilder.append:(Ljava/lang/String;)Ljava/lang/StringBuilder;
        //   301: pop            
        //   302: aload           9
        //   304: aload           7
        //   306: invokevirtual   java/lang/StringBuilder.append:(Ljava/lang/Object;)Ljava/lang/StringBuilder;
        //   309: pop            
        //   310: aload           9
        //   312: invokevirtual   java/lang/Object.toString:()Ljava/lang/String;
        //   315: astore          7
        //   317: aload           7
        //   319: ldc             ""
        //   321: invokestatic    kotlin/jvm/internal/Intrinsics.checkNotNullParameter:(Ljava/lang/Object;Ljava/lang/String;)V
        //   324: ldc             "[Exception Manager]: "
        //   326: aload           7
        //   328: invokestatic    java/lang/String.valueOf:(Ljava/lang/Object;)Ljava/lang/String;
        //   331: invokevirtual   java/lang/String.concat:(Ljava/lang/String;)Ljava/lang/String;
        //   334: invokestatic    com/appsflyer/AFLogger.afRDLog:(Ljava/lang/String;)V
        //   337: aload           8
        //   339: iconst_0       
        //   340: invokevirtual   java/net/HttpURLConnection.setInstanceFollowRedirects:(Z)V
        //   343: aload           8
        //   345: iconst_0       
        //   346: invokevirtual   java/net/URLConnection.setUseCaches:(Z)V
        //   349: aload           8
        //   351: aload_0        
        //   352: getfield        com/appsflyer/internal/AFc1tSDK.values:I
        //   355: invokevirtual   java/net/URLConnection.setReadTimeout:(I)V
        //   358: aload           8
        //   360: aload_0        
        //   361: getfield        com/appsflyer/internal/AFc1tSDK.values:I
        //   364: invokevirtual   java/net/URLConnection.setConnectTimeout:(I)V
        //   367: aload           8
        //   369: ldc             "Content-Type"
        //   371: ldc             "application/json"
        //   373: invokevirtual   java/net/URLConnection.addRequestProperty:(Ljava/lang/String;Ljava/lang/String;)V
        //   376: aload_0        
        //   377: getfield        com/appsflyer/internal/AFc1tSDK.AFKeystoreWrapper:Ljava/util/Map;
        //   380: astore          7
        //   382: aload           7
        //   384: ifnull          451
        //   387: aload           7
        //   389: invokeinterface java/util/Map.entrySet:()Ljava/util/Set;
        //   394: invokeinterface java/util/Set.iterator:()Ljava/util/Iterator;
        //   399: astore          7
        //   401: aload           7
        //   403: invokeinterface java/util/Iterator.hasNext:()Z
        //   408: ifeq            451
        //   411: aload           7
        //   413: invokeinterface java/util/Iterator.next:()Ljava/lang/Object;
        //   418: checkcast       Ljava/util/Map$Entry;
        //   421: astore          9
        //   423: aload           8
        //   425: aload           9
        //   427: invokeinterface java/util/Map$Entry.getKey:()Ljava/lang/Object;
        //   432: checkcast       Ljava/lang/String;
        //   435: aload           9
        //   437: invokeinterface java/util/Map$Entry.getValue:()Ljava/lang/Object;
        //   442: checkcast       Ljava/lang/String;
        //   445: invokevirtual   java/net/URLConnection.addRequestProperty:(Ljava/lang/String;Ljava/lang/String;)V
        //   448: goto            401
        //   451: aload           8
        //   453: iconst_1       
        //   454: invokevirtual   java/net/URLConnection.setDoOutput:(Z)V
        //   457: aload           8
        //   459: ldc             "Content-Length"
        //   461: aload_0        
        //   462: getfield        com/appsflyer/internal/AFc1tSDK.AFInAppEventParameterName:[B
        //   465: arraylength    
        //   466: invokestatic    java/lang/String.valueOf:(I)Ljava/lang/String;
        //   469: invokevirtual   java/net/URLConnection.setRequestProperty:(Ljava/lang/String;Ljava/lang/String;)V
        //   472: aload           8
        //   474: invokevirtual   java/net/URLConnection.getOutputStream:()Ljava/io/OutputStream;
        //   477: astore          7
        //   479: aload           7
        //   481: ldc             ""
        //   483: invokestatic    kotlin/jvm/internal/Intrinsics.checkNotNullExpressionValue:(Ljava/lang/Object;Ljava/lang/String;)V
        //   486: aload           7
        //   488: instanceof      Ljava/io/BufferedOutputStream;
        //   491: ifeq            504
        //   494: aload           7
        //   496: checkcast       Ljava/io/BufferedOutputStream;
        //   499: astore          7
        //   501: goto            518
        //   504: new             Ljava/io/BufferedOutputStream;
        //   507: dup            
        //   508: aload           7
        //   510: sipush          8192
        //   513: invokespecial   java/io/BufferedOutputStream.<init>:(Ljava/io/OutputStream;I)V
        //   516: astore          7
        //   518: aload           7
        //   520: aload_0        
        //   521: getfield        com/appsflyer/internal/AFc1tSDK.AFInAppEventParameterName:[B
        //   524: invokevirtual   java/io/OutputStream.write:([B)V
        //   527: aload           7
        //   529: invokevirtual   java/io/OutputStream.close:()V
        //   532: aload           8
        //   534: invokestatic    com/appsflyer/internal/AFc1uSDK$AFa1wSDK.values:(Ljava/net/HttpURLConnection;)Z
        //   537: ifeq            550
        //   540: aload           8
        //   542: invokevirtual   java/net/URLConnection.getInputStream:()Ljava/io/InputStream;
        //   545: astore          7
        //   547: goto            557
        //   550: aload           8
        //   552: invokevirtual   java/net/HttpURLConnection.getErrorStream:()Ljava/io/InputStream;
        //   555: astore          7
        //   557: aload           7
        //   559: ifnull          1019
        //   562: aload           7
        //   564: ldc             ""
        //   566: invokestatic    kotlin/jvm/internal/Intrinsics.checkNotNullExpressionValue:(Ljava/lang/Object;Ljava/lang/String;)V
        //   569: new             Ljava/io/BufferedReader;
        //   572: dup            
        //   573: new             Ljava/io/InputStreamReader;
        //   576: dup            
        //   577: aload           7
        //   579: getstatic       kotlin/text/b.b:Ljava/nio/charset/Charset;
        //   582: invokespecial   java/io/InputStreamReader.<init>:(Ljava/io/InputStream;Ljava/nio/charset/Charset;)V
        //   585: sipush          8192
        //   588: invokespecial   java/io/BufferedReader.<init>:(Ljava/io/Reader;I)V
        //   591: astore          7
        //   593: aload           7
        //   595: invokestatic    e6/m.e:(Ljava/io/Reader;)Ljava/util/List;
        //   598: checkcast       Ljava/lang/Iterable;
        //   601: aconst_null    
        //   602: aconst_null    
        //   603: aconst_null    
        //   604: iconst_0       
        //   605: aconst_null    
        //   606: aconst_null    
        //   607: bipush          63
        //   609: aconst_null    
        //   610: invokestatic    W5/m.x:(Ljava/lang/Iterable;Ljava/lang/CharSequence;Ljava/lang/CharSequence;Ljava/lang/CharSequence;ILjava/lang/CharSequence;Lg6/l;ILjava/lang/Object;)Ljava/lang/String;
        //   613: astore          9
        //   615: aload           7
        //   617: invokevirtual   java/io/Reader.close:()V
        //   620: aload           9
        //   622: astore          7
        //   624: aload           9
        //   626: ifnonnull       632
        //   629: goto            1019
        //   632: invokestatic    java/lang/System.currentTimeMillis:()J
        //   635: lstore          4
        //   637: new             Ljava/lang/StringBuilder;
        //   640: dup            
        //   641: ldc_w           "response code:"
        //   644: invokespecial   java/lang/StringBuilder.<init>:(Ljava/lang/String;)V
        //   647: astore          9
        //   649: aload           9
        //   651: aload           8
        //   653: invokevirtual   java/net/HttpURLConnection.getResponseCode:()I
        //   656: invokevirtual   java/lang/StringBuilder.append:(I)Ljava/lang/StringBuilder;
        //   659: pop            
        //   660: aload           9
        //   662: bipush          32
        //   664: invokevirtual   java/lang/StringBuilder.append:(C)Ljava/lang/StringBuilder;
        //   667: pop            
        //   668: aload           9
        //   670: aload           8
        //   672: invokevirtual   java/net/HttpURLConnection.getResponseMessage:()Ljava/lang/String;
        //   675: invokevirtual   java/lang/StringBuilder.append:(Ljava/lang/String;)Ljava/lang/StringBuilder;
        //   678: pop            
        //   679: aload           9
        //   681: ldc_w           "\n\tbody:"
        //   684: invokevirtual   java/lang/StringBuilder.append:(Ljava/lang/String;)Ljava/lang/StringBuilder;
        //   687: pop            
        //   688: aload           9
        //   690: aload           7
        //   692: invokevirtual   java/lang/StringBuilder.append:(Ljava/lang/String;)Ljava/lang/StringBuilder;
        //   695: pop            
        //   696: aload           9
        //   698: ldc_w           "\n\ttook "
        //   701: invokevirtual   java/lang/StringBuilder.append:(Ljava/lang/String;)Ljava/lang/StringBuilder;
        //   704: pop            
        //   705: aload           9
        //   707: lload           4
        //   709: lload_2        
        //   710: lsub           
        //   711: invokevirtual   java/lang/StringBuilder.append:(J)Ljava/lang/StringBuilder;
        //   714: pop            
        //   715: aload           9
        //   717: ldc_w           "ms"
        //   720: invokevirtual   java/lang/StringBuilder.append:(Ljava/lang/String;)Ljava/lang/StringBuilder;
        //   723: pop            
        //   724: aload           9
        //   726: invokevirtual   java/lang/Object.toString:()Ljava/lang/String;
        //   729: astore          7
        //   731: new             Ljava/lang/StringBuilder;
        //   734: dup            
        //   735: ldc             "HTTP: ["
        //   737: invokespecial   java/lang/StringBuilder.<init>:(Ljava/lang/String;)V
        //   740: astore          9
        //   742: aload           9
        //   744: aload           8
        //   746: invokevirtual   java/lang/Object.hashCode:()I
        //   749: invokevirtual   java/lang/StringBuilder.append:(I)Ljava/lang/StringBuilder;
        //   752: pop            
        //   753: aload           9
        //   755: ldc             "] "
        //   757: invokevirtual   java/lang/StringBuilder.append:(Ljava/lang/String;)Ljava/lang/StringBuilder;
        //   760: pop            
        //   761: aload           9
        //   763: aload           7
        //   765: invokevirtual   java/lang/StringBuilder.append:(Ljava/lang/String;)Ljava/lang/StringBuilder;
        //   768: pop            
        //   769: aload           9
        //   771: invokevirtual   java/lang/Object.toString:()Ljava/lang/String;
        //   774: astore          7
        //   776: aload           7
        //   778: ldc             ""
        //   780: invokestatic    kotlin/jvm/internal/Intrinsics.checkNotNullParameter:(Ljava/lang/Object;Ljava/lang/String;)V
        //   783: ldc             "[Exception Manager]: "
        //   785: aload           7
        //   787: invokestatic    java/lang/String.valueOf:(Ljava/lang/Object;)Ljava/lang/String;
        //   790: invokevirtual   java/lang/String.concat:(Ljava/lang/String;)Ljava/lang/String;
        //   793: invokestatic    com/appsflyer/AFLogger.afRDLog:(Ljava/lang/String;)V
        //   796: aload           8
        //   798: invokestatic    com/appsflyer/internal/AFc1uSDK$AFa1wSDK.values:(Ljava/net/HttpURLConnection;)Z
        //   801: istore          6
        //   803: aload           8
        //   805: invokevirtual   java/net/HttpURLConnection.disconnect:()V
        //   808: iload           6
        //   810: ireturn        
        //   811: aload           7
        //   813: athrow         
        //   814: astore          8
        //   816: goto            830
        //   819: new             Ljava/lang/NullPointerException;
        //   822: dup            
        //   823: ldc_w           "null cannot be cast to non-null type java.net.HttpURLConnection"
        //   826: invokespecial   java/lang/NullPointerException.<init>:(Ljava/lang/String;)V
        //   829: athrow         
        //   830: invokestatic    java/lang/System.currentTimeMillis:()J
        //   833: lstore          4
        //   835: new             Ljava/lang/StringBuilder;
        //   838: dup            
        //   839: ldc_w           "error: "
        //   842: invokespecial   java/lang/StringBuilder.<init>:(Ljava/lang/String;)V
        //   845: astore          9
        //   847: aload           9
        //   849: aload           8
        //   851: invokevirtual   java/lang/StringBuilder.append:(Ljava/lang/Object;)Ljava/lang/StringBuilder;
        //   854: pop            
        //   855: aload           9
        //   857: ldc_w           "\n\ttook "
        //   860: invokevirtual   java/lang/StringBuilder.append:(Ljava/lang/String;)Ljava/lang/StringBuilder;
        //   863: pop            
        //   864: aload           9
        //   866: lload           4
        //   868: lload_2        
        //   869: lsub           
        //   870: invokevirtual   java/lang/StringBuilder.append:(J)Ljava/lang/StringBuilder;
        //   873: pop            
        //   874: aload           9
        //   876: ldc_w           "ms\n\t"
        //   879: invokevirtual   java/lang/StringBuilder.append:(Ljava/lang/String;)Ljava/lang/StringBuilder;
        //   882: pop            
        //   883: aload           9
        //   885: aload           8
        //   887: invokevirtual   java/lang/Throwable.getMessage:()Ljava/lang/String;
        //   890: invokevirtual   java/lang/StringBuilder.append:(Ljava/lang/String;)Ljava/lang/StringBuilder;
        //   893: pop            
        //   894: aload           9
        //   896: invokevirtual   java/lang/Object.toString:()Ljava/lang/String;
        //   899: astore          8
        //   901: new             Ljava/lang/StringBuilder;
        //   904: dup            
        //   905: ldc             "HTTP: ["
        //   907: invokespecial   java/lang/StringBuilder.<init>:(Ljava/lang/String;)V
        //   910: astore          9
        //   912: aload           7
        //   914: ifnull          1031
        //   917: aload           7
        //   919: invokevirtual   java/lang/Object.hashCode:()I
        //   922: istore_1       
        //   923: goto            926
        //   926: aload           9
        //   928: iload_1        
        //   929: invokevirtual   java/lang/StringBuilder.append:(I)Ljava/lang/StringBuilder;
        //   932: pop            
        //   933: aload           9
        //   935: ldc             "] "
        //   937: invokevirtual   java/lang/StringBuilder.append:(Ljava/lang/String;)Ljava/lang/StringBuilder;
        //   940: pop            
        //   941: aload           9
        //   943: aload           8
        //   945: invokevirtual   java/lang/StringBuilder.append:(Ljava/lang/String;)Ljava/lang/StringBuilder;
        //   948: pop            
        //   949: aload           9
        //   951: invokevirtual   java/lang/Object.toString:()Ljava/lang/String;
        //   954: astore          8
        //   956: aload           8
        //   958: ldc             ""
        //   960: invokestatic    kotlin/jvm/internal/Intrinsics.checkNotNullParameter:(Ljava/lang/Object;Ljava/lang/String;)V
        //   963: ldc             "[Exception Manager]: "
        //   965: aload           8
        //   967: invokestatic    java/lang/String.valueOf:(Ljava/lang/Object;)Ljava/lang/String;
        //   970: invokevirtual   java/lang/String.concat:(Ljava/lang/String;)Ljava/lang/String;
        //   973: invokestatic    com/appsflyer/AFLogger.afRDLog:(Ljava/lang/String;)V
        //   976: aload           7
        //   978: ifnull          986
        //   981: aload           7
        //   983: invokevirtual   java/net/HttpURLConnection.disconnect:()V
        //   986: iconst_0       
        //   987: ireturn        
        //   988: aload           7
        //   990: ifnull          998
        //   993: aload           7
        //   995: invokevirtual   java/net/HttpURLConnection.disconnect:()V
        //   998: aload           8
        //  1000: athrow         
        //  1001: astore          9
        //  1003: aload           8
        //  1005: astore          7
        //  1007: aload           9
        //  1009: astore          8
        //  1011: goto            830
        //  1014: astore          7
        //  1016: goto            811
        //  1019: ldc             ""
        //  1021: astore          7
        //  1023: goto            632
        //  1026: astore          8
        //  1028: goto            988
        //  1031: iconst_0       
        //  1032: istore_1       
        //  1033: goto            926
        //    Exceptions:
        //  Try           Handler
        //  Start  End    Start  End    Type
        //  -----  -----  -----  -----  ----
        //  7      71     814    819    Any
        //  76     83     814    819    Any
        //  83     180    1001   1014   Any
        //  185    199    1001   1014   Any
        //  199    269    1001   1014   Any
        //  272    382    1001   1014   Any
        //  387    401    1001   1014   Any
        //  401    448    1001   1014   Any
        //  451    472    1001   1014   Any
        //  472    501    1014   814    Any
        //  504    518    1014   814    Any
        //  518    527    1014   814    Any
        //  527    547    1001   1014   Any
        //  550    557    1001   1014   Any
        //  562    620    1001   1014   Any
        //  632    803    1001   1014   Any
        //  811    814    1001   1014   Any
        //  819    830    814    819    Any
        //  830    912    1026   1001   Any
        //  917    923    1026   1001   Any
        //  926    976    1026   1001   Any
        // 
        // The error that occurred was:
        // 
        // java.lang.IndexOutOfBoundsException: Index 454 out of bounds for length 454
        //     at java.base/jdk.internal.util.Preconditions.outOfBounds(Preconditions.java:64)
        //     at java.base/jdk.internal.util.Preconditions.outOfBoundsCheckIndex(Preconditions.java:70)
        //     at java.base/jdk.internal.util.Preconditions.checkIndex(Preconditions.java:248)
        //     at java.base/java.util.Objects.checkIndex(Objects.java:374)
        //     at java.base/java.util.ArrayList.get(ArrayList.java:459)
        //     at com.strobel.decompiler.ast.AstBuilder.convertToAst(AstBuilder.java:3321)
        //     at com.strobel.decompiler.ast.AstBuilder.build(AstBuilder.java:113)
        //     at com.strobel.decompiler.languages.java.ast.AstMethodBodyBuilder.createMethodBody(AstMethodBodyBuilder.java:211)
        //     at com.strobel.decompiler.languages.java.ast.AstMethodBodyBuilder.createMethodBody(AstMethodBodyBuilder.java:99)
        //     at com.strobel.decompiler.languages.java.ast.AstBuilder.createMethodBody(AstBuilder.java:782)
        //     at com.strobel.decompiler.languages.java.ast.AstBuilder.createMethod(AstBuilder.java:675)
        //     at com.strobel.decompiler.languages.java.ast.AstBuilder.addTypeMembers(AstBuilder.java:552)
        //     at com.strobel.decompiler.languages.java.ast.AstBuilder.createTypeCore(AstBuilder.java:519)
        //     at com.strobel.decompiler.languages.java.ast.AstBuilder.createTypeNoCache(AstBuilder.java:161)
        //     at com.strobel.decompiler.languages.java.ast.AstBuilder.createType(AstBuilder.java:150)
        //     at com.strobel.decompiler.languages.java.ast.AstBuilder.addType(AstBuilder.java:125)
        //     at com.strobel.decompiler.languages.java.JavaLanguage.buildAst(JavaLanguage.java:71)
        //     at com.strobel.decompiler.languages.java.JavaLanguage.decompileType(JavaLanguage.java:59)
        //     at com.strobel.decompiler.DecompilerDriver.decompileType(DecompilerDriver.java:330)
        //     at com.strobel.decompiler.DecompilerDriver.decompileJar(DecompilerDriver.java:251)
        //     at com.strobel.decompiler.DecompilerDriver.main(DecompilerDriver.java:141)
        // 
        throw new IllegalStateException("An error occurred while decompiling this method.");
    }
    
    @Metadata
    public static final class AFa1wSDK
    {
        private AFa1wSDK() {
        }
    }
}
