package hb;

import pb.b;

public final class a$a
  extends a.e
{
  public a$a(a parama)
  {
    super(parama);
    b.b();
  }
  
  /* Error */
  public final void a()
  {
    // Byte code:
    //   0: new 26	xc/f
    //   3: dup
    //   4: invokespecial 28	xc/f:<init>	()V
    //   7: astore_1
    //   8: invokestatic 31	pb/b:c	()V
    //   11: getstatic 34	pb/b:a	Lpb/a;
    //   14: astore_2
    //   15: aload_2
    //   16: invokevirtual 40	java/lang/Object:getClass	()Ljava/lang/Class;
    //   19: pop
    //   20: aload_0
    //   21: getfield 15	hb/a$a:b	Lhb/a;
    //   24: getfield 43	hb/a:a	Ljava/lang/Object;
    //   27: astore_3
    //   28: aload_3
    //   29: monitorenter
    //   30: aload_0
    //   31: getfield 15	hb/a$a:b	Lhb/a;
    //   34: getfield 46	hb/a:b	Lxc/f;
    //   37: astore 4
    //   39: aload_1
    //   40: aload 4
    //   42: aload 4
    //   44: invokevirtual 50	xc/f:g	()J
    //   47: invokevirtual 51	xc/f:g0	(Lxc/f;J)V
    //   50: aload_0
    //   51: getfield 15	hb/a$a:b	Lhb/a;
    //   54: astore 4
    //   56: aload 4
    //   58: iconst_0
    //   59: putfield 55	hb/a:f	Z
    //   62: aload 4
    //   64: getfield 59	hb/a:u	I
    //   67: istore 5
    //   69: aload_3
    //   70: monitorexit
    //   71: aload 4
    //   73: getfield 63	hb/a:q	Lxc/w;
    //   76: aload_1
    //   77: aload_1
    //   78: getfield 66	xc/f:b	J
    //   81: invokeinterface 69 4 0
    //   86: aload_0
    //   87: getfield 15	hb/a$a:b	Lhb/a;
    //   90: getfield 43	hb/a:a	Ljava/lang/Object;
    //   93: astore_3
    //   94: aload_3
    //   95: monitorenter
    //   96: aload_0
    //   97: getfield 15	hb/a$a:b	Lhb/a;
    //   100: astore_1
    //   101: aload_1
    //   102: aload_1
    //   103: getfield 59	hb/a:u	I
    //   106: iload 5
    //   108: isub
    //   109: putfield 59	hb/a:u	I
    //   112: aload_3
    //   113: monitorexit
    //   114: aload_2
    //   115: invokevirtual 40	java/lang/Object:getClass	()Ljava/lang/Class;
    //   118: pop
    //   119: return
    //   120: astore_2
    //   121: aload_3
    //   122: monitorexit
    //   123: aload_2
    //   124: athrow
    //   125: astore_2
    //   126: aload_3
    //   127: monitorexit
    //   128: aload_2
    //   129: athrow
    //   130: astore_3
    //   131: getstatic 34	pb/b:a	Lpb/a;
    //   134: invokevirtual 40	java/lang/Object:getClass	()Ljava/lang/Class;
    //   137: pop
    //   138: goto +9 -> 147
    //   141: astore_2
    //   142: aload_3
    //   143: aload_2
    //   144: invokevirtual 75	java/lang/Throwable:addSuppressed	(Ljava/lang/Throwable;)V
    //   147: aload_3
    //   148: athrow
    // Local variable table:
    //   start	length	slot	name	signature
    //   0	149	0	this	a
    //   7	96	1	localObject1	Object
    //   14	101	2	locala	pb.a
    //   120	4	2	localObject2	Object
    //   125	4	2	localObject3	Object
    //   141	3	2	localThrowable	Throwable
    //   27	100	3	localObject4	Object
    //   130	18	3	localObject5	Object
    //   37	35	4	localObject6	Object
    //   67	42	5	i	int
    // Exception table:
    //   from	to	target	type
    //   96	114	120	finally
    //   121	123	120	finally
    //   30	71	125	finally
    //   126	128	125	finally
    //   11	30	130	finally
    //   71	96	130	finally
    //   123	125	130	finally
    //   128	130	130	finally
    //   131	138	141	finally
  }
}

/* Location:
 * Qualified Name:     hb.a.a
 * Java Class Version: 6 (50.0)
 * JD-Core Version:    0.7.1
 */