package hb;

public final class h$a
{
  public h$a(h paramh) {}
  
  /* Error */
  public final void a(eb.s0 params0, byte[] paramArrayOfByte)
  {
    // Byte code:
    //   0: invokestatic 22	pb/b:c	()V
    //   3: new 24	java/lang/StringBuilder
    //   6: astore_3
    //   7: aload_3
    //   8: invokespecial 25	java/lang/StringBuilder:<init>	()V
    //   11: aload_3
    //   12: ldc 27
    //   14: invokevirtual 31	java/lang/StringBuilder:append	(Ljava/lang/String;)Ljava/lang/StringBuilder;
    //   17: pop
    //   18: aload_3
    //   19: aload_0
    //   20: getfield 12	hb/h$a:a	Lhb/h;
    //   23: getfield 35	hb/h:h	Leb/t0;
    //   26: getfield 41	eb/t0:b	Ljava/lang/String;
    //   29: invokevirtual 31	java/lang/StringBuilder:append	(Ljava/lang/String;)Ljava/lang/StringBuilder;
    //   32: pop
    //   33: aload_3
    //   34: invokevirtual 45	java/lang/StringBuilder:toString	()Ljava/lang/String;
    //   37: astore 4
    //   39: aload 4
    //   41: astore_3
    //   42: aload_2
    //   43: ifnull +50 -> 93
    //   46: aload_0
    //   47: getfield 12	hb/h$a:a	Lhb/h;
    //   50: iconst_1
    //   51: putfield 49	hb/h:o	Z
    //   54: new 24	java/lang/StringBuilder
    //   57: astore_3
    //   58: aload_3
    //   59: invokespecial 25	java/lang/StringBuilder:<init>	()V
    //   62: aload_3
    //   63: aload 4
    //   65: invokevirtual 31	java/lang/StringBuilder:append	(Ljava/lang/String;)Ljava/lang/StringBuilder;
    //   68: pop
    //   69: aload_3
    //   70: ldc 51
    //   72: invokevirtual 31	java/lang/StringBuilder:append	(Ljava/lang/String;)Ljava/lang/StringBuilder;
    //   75: pop
    //   76: aload_3
    //   77: getstatic 56	p7/a:a	Lp7/a$c;
    //   80: aload_2
    //   81: invokevirtual 59	p7/a:c	([B)Ljava/lang/String;
    //   84: invokevirtual 31	java/lang/StringBuilder:append	(Ljava/lang/String;)Ljava/lang/StringBuilder;
    //   87: pop
    //   88: aload_3
    //   89: invokevirtual 45	java/lang/StringBuilder:toString	()Ljava/lang/String;
    //   92: astore_3
    //   93: aload_0
    //   94: getfield 12	hb/h$a:a	Lhb/h;
    //   97: getfield 63	hb/h:l	Lhb/h$b;
    //   100: getfield 69	hb/h$b:x	Ljava/lang/Object;
    //   103: astore_2
    //   104: aload_2
    //   105: monitorenter
    //   106: aload_0
    //   107: getfield 12	hb/h$a:a	Lhb/h;
    //   110: getfield 63	hb/h:l	Lhb/h$b;
    //   113: aload_1
    //   114: aload_3
    //   115: invokestatic 73	hb/h$b:m	(Lhb/h$b;Leb/s0;Ljava/lang/String;)V
    //   118: aload_2
    //   119: monitorexit
    //   120: getstatic 76	pb/b:a	Lpb/a;
    //   123: invokevirtual 80	java/lang/Object:getClass	()Ljava/lang/Class;
    //   126: pop
    //   127: return
    //   128: astore_1
    //   129: aload_2
    //   130: monitorexit
    //   131: aload_1
    //   132: athrow
    //   133: astore_1
    //   134: getstatic 76	pb/b:a	Lpb/a;
    //   137: invokevirtual 80	java/lang/Object:getClass	()Ljava/lang/Class;
    //   140: pop
    //   141: goto +9 -> 150
    //   144: astore_2
    //   145: aload_1
    //   146: aload_2
    //   147: invokevirtual 86	java/lang/Throwable:addSuppressed	(Ljava/lang/Throwable;)V
    //   150: aload_1
    //   151: athrow
    // Local variable table:
    //   start	length	slot	name	signature
    //   0	152	0	this	a
    //   0	152	1	params0	eb.s0
    //   0	152	2	paramArrayOfByte	byte[]
    //   6	109	3	localObject	Object
    //   37	27	4	str	String
    // Exception table:
    //   from	to	target	type
    //   106	120	128	finally
    //   129	131	128	finally
    //   3	39	133	finally
    //   46	93	133	finally
    //   93	106	133	finally
    //   131	133	133	finally
    //   134	141	144	finally
  }
}

/* Location:
 * Qualified Name:     hb.h.a
 * Java Class Version: 6 (50.0)
 * JD-Core Version:    0.7.1
 */