package hb;

import java.util.concurrent.CountDownLatch;
import xc.f;
import xc.y;
import xc.z;

public final class i$b
  implements Runnable
{
  public i$b(i parami, CountDownLatch paramCountDownLatch, a parama) {}
  
  /* Error */
  public final void run()
  {
    // Byte code:
    //   0: aload_0
    //   1: getfield 25	hb/i$b:a	Ljava/util/concurrent/CountDownLatch;
    //   4: invokevirtual 43	java/util/concurrent/CountDownLatch:await	()V
    //   7: goto +10 -> 17
    //   10: astore_1
    //   11: invokestatic 49	java/lang/Thread:currentThread	()Ljava/lang/Thread;
    //   14: invokevirtual 52	java/lang/Thread:interrupt	()V
    //   17: new 54	xc/s
    //   20: dup
    //   21: new 13	hb/i$b$a
    //   24: dup
    //   25: invokespecial 55	hb/i$b$a:<init>	()V
    //   28: invokespecial 58	xc/s:<init>	(Lxc/y;)V
    //   31: astore_2
    //   32: aconst_null
    //   33: astore_3
    //   34: aload_2
    //   35: astore_1
    //   36: aload_0
    //   37: getfield 23	hb/i$b:c	Lhb/i;
    //   40: astore 4
    //   42: aload_2
    //   43: astore_1
    //   44: aload 4
    //   46: getfield 62	hb/i:Q	Leb/a0;
    //   49: astore 5
    //   51: aload 5
    //   53: ifnonnull +42 -> 95
    //   56: aload_2
    //   57: astore_1
    //   58: aload 4
    //   60: getfield 66	hb/i:A	Ljavax/net/SocketFactory;
    //   63: aload 4
    //   65: getfield 69	hb/i:a	Ljava/net/InetSocketAddress;
    //   68: invokevirtual 75	java/net/InetSocketAddress:getAddress	()Ljava/net/InetAddress;
    //   71: aload_0
    //   72: getfield 23	hb/i$b:c	Lhb/i;
    //   75: getfield 69	hb/i:a	Ljava/net/InetSocketAddress;
    //   78: invokevirtual 79	java/net/InetSocketAddress:getPort	()I
    //   81: invokevirtual 85	javax/net/SocketFactory:createSocket	(Ljava/net/InetAddress;I)Ljava/net/Socket;
    //   84: astore 4
    //   86: aload 4
    //   88: astore_1
    //   89: aload_1
    //   90: astore 4
    //   92: goto +57 -> 149
    //   95: aload_2
    //   96: astore_1
    //   97: aload 5
    //   99: getfield 90	eb/a0:a	Ljava/net/SocketAddress;
    //   102: astore 6
    //   104: aload_2
    //   105: astore_1
    //   106: aload 6
    //   108: instanceof 71
    //   111: ifeq +364 -> 475
    //   114: aload_2
    //   115: astore_1
    //   116: aload 4
    //   118: aload 5
    //   120: getfield 92	eb/a0:b	Ljava/net/InetSocketAddress;
    //   123: aload 6
    //   125: checkcast 71	java/net/InetSocketAddress
    //   128: aload 5
    //   130: getfield 95	eb/a0:c	Ljava/lang/String;
    //   133: aload 5
    //   135: getfield 98	eb/a0:d	Ljava/lang/String;
    //   138: invokestatic 102	hb/i:j	(Lhb/i;Ljava/net/InetSocketAddress;Ljava/net/InetSocketAddress;Ljava/lang/String;Ljava/lang/String;)Ljava/net/Socket;
    //   141: astore 4
    //   143: aload 4
    //   145: astore_1
    //   146: goto -57 -> 89
    //   149: aload_2
    //   150: astore_1
    //   151: aload_0
    //   152: getfield 23	hb/i$b:c	Lhb/i;
    //   155: astore 7
    //   157: aload_2
    //   158: astore_1
    //   159: aload 7
    //   161: getfield 106	hb/i:B	Ljavax/net/ssl/SSLSocketFactory;
    //   164: astore 6
    //   166: aload 4
    //   168: astore 5
    //   170: aload 6
    //   172: ifnull +46 -> 218
    //   175: aload_2
    //   176: astore_1
    //   177: aload 6
    //   179: aload 7
    //   181: getfield 110	hb/i:C	Ljavax/net/ssl/HostnameVerifier;
    //   184: aload 4
    //   186: aload 7
    //   188: invokevirtual 114	hb/i:m	()Ljava/lang/String;
    //   191: aload_0
    //   192: getfield 23	hb/i$b:c	Lhb/i;
    //   195: invokevirtual 117	hb/i:n	()I
    //   198: aload_0
    //   199: getfield 23	hb/i$b:c	Lhb/i;
    //   202: getfield 121	hb/i:F	Lib/b;
    //   205: invokestatic 126	hb/n:a	(Ljavax/net/ssl/SSLSocketFactory;Ljavax/net/ssl/HostnameVerifier;Ljava/net/Socket;Ljava/lang/String;ILib/b;)Ljavax/net/ssl/SSLSocket;
    //   208: astore 5
    //   210: aload_2
    //   211: astore_1
    //   212: aload 5
    //   214: invokevirtual 132	javax/net/ssl/SSLSocket:getSession	()Ljavax/net/ssl/SSLSession;
    //   217: astore_3
    //   218: aload_2
    //   219: astore_1
    //   220: aload 5
    //   222: iconst_1
    //   223: invokevirtual 138	java/net/Socket:setTcpNoDelay	(Z)V
    //   226: aload_2
    //   227: astore_1
    //   228: aload 5
    //   230: invokestatic 144	p2/m0:b0	(Ljava/net/Socket;)Lxc/e;
    //   233: astore 6
    //   235: aload_2
    //   236: astore_1
    //   237: new 54	xc/s
    //   240: astore 4
    //   242: aload_2
    //   243: astore_1
    //   244: aload 4
    //   246: aload 6
    //   248: invokespecial 58	xc/s:<init>	(Lxc/y;)V
    //   251: aload_0
    //   252: getfield 27	hb/i$b:b	Lhb/a;
    //   255: aload 5
    //   257: invokestatic 148	p2/m0:a0	(Ljava/net/Socket;)Lxc/d;
    //   260: aload 5
    //   262: invokevirtual 154	hb/a:f	(Lxc/d;Ljava/net/Socket;)V
    //   265: aload_0
    //   266: getfield 23	hb/i$b:c	Lhb/i;
    //   269: astore 6
    //   271: aload 6
    //   273: getfield 158	hb/i:u	Leb/a;
    //   276: astore_1
    //   277: aload_1
    //   278: invokevirtual 162	java/lang/Object:getClass	()Ljava/lang/Class;
    //   281: pop
    //   282: new 164	eb/a$a
    //   285: astore_2
    //   286: aload_2
    //   287: aload_1
    //   288: invokespecial 167	eb/a$a:<init>	(Leb/a;)V
    //   291: aload_2
    //   292: getstatic 172	eb/z:a	Leb/a$b;
    //   295: aload 5
    //   297: invokevirtual 176	java/net/Socket:getRemoteSocketAddress	()Ljava/net/SocketAddress;
    //   300: invokevirtual 179	eb/a$a:c	(Leb/a$b;Ljava/lang/Object;)V
    //   303: aload_2
    //   304: getstatic 181	eb/z:b	Leb/a$b;
    //   307: aload 5
    //   309: invokevirtual 184	java/net/Socket:getLocalSocketAddress	()Ljava/net/SocketAddress;
    //   312: invokevirtual 179	eb/a$a:c	(Leb/a$b;Ljava/lang/Object;)V
    //   315: aload_2
    //   316: getstatic 186	eb/z:c	Leb/a$b;
    //   319: aload_3
    //   320: invokevirtual 179	eb/a$a:c	(Leb/a$b;Ljava/lang/Object;)V
    //   323: getstatic 189	gb/u0:a	Leb/a$b;
    //   326: astore 5
    //   328: aload_3
    //   329: ifnonnull +10 -> 339
    //   332: getstatic 194	eb/a1:a	Leb/a1;
    //   335: astore_1
    //   336: goto +7 -> 343
    //   339: getstatic 196	eb/a1:b	Leb/a1;
    //   342: astore_1
    //   343: aload_2
    //   344: aload 5
    //   346: aload_1
    //   347: invokevirtual 179	eb/a$a:c	(Leb/a$b;Ljava/lang/Object;)V
    //   350: aload 6
    //   352: aload_2
    //   353: invokevirtual 199	eb/a$a:a	()Leb/a;
    //   356: putfield 158	hb/i:u	Leb/a;
    //   359: aload_0
    //   360: getfield 23	hb/i$b:c	Lhb/i;
    //   363: astore_1
    //   364: aload_1
    //   365: new 201	hb/i$d
    //   368: dup
    //   369: aload_1
    //   370: aload_1
    //   371: getfield 204	hb/i:g	Ljb/h;
    //   374: aload 4
    //   376: invokeinterface 209 2 0
    //   381: invokespecial 212	hb/i$d:<init>	(Lhb/i;Ljb/b;)V
    //   384: putfield 216	hb/i:t	Lhb/i$d;
    //   387: aload_0
    //   388: getfield 23	hb/i$b:c	Lhb/i;
    //   391: getfield 220	hb/i:k	Ljava/lang/Object;
    //   394: astore_1
    //   395: aload_1
    //   396: monitorenter
    //   397: aload_0
    //   398: getfield 23	hb/i$b:c	Lhb/i;
    //   401: invokevirtual 162	java/lang/Object:getClass	()Ljava/lang/Class;
    //   404: pop
    //   405: aload_3
    //   406: ifnull +20 -> 426
    //   409: aload_0
    //   410: getfield 23	hb/i$b:c	Lhb/i;
    //   413: astore_2
    //   414: new 222	eb/c0$a
    //   417: aload_3
    //   418: invokespecial 225	eb/c0$a:<init>	(Ljavax/net/ssl/SSLSession;)V
    //   421: aload_2
    //   422: invokevirtual 162	java/lang/Object:getClass	()Ljava/lang/Class;
    //   425: pop
    //   426: aload_1
    //   427: monitorexit
    //   428: return
    //   429: astore_2
    //   430: aload_1
    //   431: monitorexit
    //   432: aload_2
    //   433: athrow
    //   434: astore_2
    //   435: aload 4
    //   437: astore_1
    //   438: goto +205 -> 643
    //   441: astore_1
    //   442: aload 4
    //   444: astore_2
    //   445: aload_1
    //   446: astore 4
    //   448: goto +109 -> 557
    //   451: astore_1
    //   452: aload 4
    //   454: astore_2
    //   455: aload_1
    //   456: astore 4
    //   458: goto +140 -> 598
    //   461: astore_2
    //   462: goto +181 -> 643
    //   465: astore 4
    //   467: goto +90 -> 557
    //   470: astore 4
    //   472: goto +126 -> 598
    //   475: aload_2
    //   476: astore_1
    //   477: getstatic 230	eb/e1:m	Leb/e1;
    //   480: astore_3
    //   481: aload_2
    //   482: astore_1
    //   483: new 232	java/lang/StringBuilder
    //   486: astore 4
    //   488: aload_2
    //   489: astore_1
    //   490: aload 4
    //   492: invokespecial 233	java/lang/StringBuilder:<init>	()V
    //   495: aload_2
    //   496: astore_1
    //   497: aload 4
    //   499: ldc -21
    //   501: invokevirtual 239	java/lang/StringBuilder:append	(Ljava/lang/String;)Ljava/lang/StringBuilder;
    //   504: pop
    //   505: aload_2
    //   506: astore_1
    //   507: aload 4
    //   509: aload_0
    //   510: getfield 23	hb/i$b:c	Lhb/i;
    //   513: getfield 62	hb/i:Q	Leb/a0;
    //   516: getfield 90	eb/a0:a	Ljava/net/SocketAddress;
    //   519: invokevirtual 162	java/lang/Object:getClass	()Ljava/lang/Class;
    //   522: invokevirtual 242	java/lang/StringBuilder:append	(Ljava/lang/Object;)Ljava/lang/StringBuilder;
    //   525: pop
    //   526: aload_2
    //   527: astore_1
    //   528: aload_3
    //   529: aload 4
    //   531: invokevirtual 245	java/lang/StringBuilder:toString	()Ljava/lang/String;
    //   534: invokevirtual 248	eb/e1:g	(Ljava/lang/String;)Leb/e1;
    //   537: astore 4
    //   539: aload_2
    //   540: astore_1
    //   541: new 36	eb/f1
    //   544: astore_3
    //   545: aload_2
    //   546: astore_1
    //   547: aload_3
    //   548: aload 4
    //   550: invokespecial 251	eb/f1:<init>	(Leb/e1;)V
    //   553: aload_2
    //   554: astore_1
    //   555: aload_3
    //   556: athrow
    //   557: aload_2
    //   558: astore_1
    //   559: aload_0
    //   560: getfield 23	hb/i$b:c	Lhb/i;
    //   563: aload 4
    //   565: invokevirtual 254	hb/i:a	(Ljava/lang/Exception;)V
    //   568: aload_0
    //   569: getfield 23	hb/i$b:c	Lhb/i;
    //   572: astore_1
    //   573: new 201	hb/i$d
    //   576: dup
    //   577: aload_1
    //   578: aload_1
    //   579: getfield 204	hb/i:g	Ljb/h;
    //   582: aload_2
    //   583: invokeinterface 209 2 0
    //   588: invokespecial 212	hb/i$d:<init>	(Lhb/i;Ljb/b;)V
    //   591: astore_2
    //   592: aload_1
    //   593: aload_2
    //   594: putfield 216	hb/i:t	Lhb/i$d;
    //   597: return
    //   598: aload_2
    //   599: astore_1
    //   600: aload_0
    //   601: getfield 23	hb/i$b:c	Lhb/i;
    //   604: iconst_0
    //   605: getstatic 259	jb/a:d	Ljb/a;
    //   608: aload 4
    //   610: getfield 261	eb/f1:a	Leb/e1;
    //   613: invokevirtual 264	hb/i:t	(ILjb/a;Leb/e1;)V
    //   616: aload_0
    //   617: getfield 23	hb/i$b:c	Lhb/i;
    //   620: astore_1
    //   621: new 201	hb/i$d
    //   624: dup
    //   625: aload_1
    //   626: aload_1
    //   627: getfield 204	hb/i:g	Ljb/h;
    //   630: aload_2
    //   631: invokeinterface 209 2 0
    //   636: invokespecial 212	hb/i$d:<init>	(Lhb/i;Ljb/b;)V
    //   639: astore_2
    //   640: goto -48 -> 592
    //   643: aload_0
    //   644: getfield 23	hb/i$b:c	Lhb/i;
    //   647: astore 4
    //   649: aload 4
    //   651: new 201	hb/i$d
    //   654: dup
    //   655: aload 4
    //   657: aload 4
    //   659: getfield 204	hb/i:g	Ljb/h;
    //   662: aload_1
    //   663: invokeinterface 209 2 0
    //   668: invokespecial 212	hb/i$d:<init>	(Lhb/i;Ljb/b;)V
    //   671: putfield 216	hb/i:t	Lhb/i$d;
    //   674: aload_2
    //   675: athrow
    // Local variable table:
    //   start	length	slot	name	signature
    //   0	676	0	this	b
    //   10	1	1	localInterruptedException	InterruptedException
    //   35	403	1	localObject1	Object
    //   441	5	1	localException1	Exception
    //   451	5	1	localf11	eb.f1
    //   476	187	1	localObject2	Object
    //   31	391	2	localObject3	Object
    //   429	4	2	localObject4	Object
    //   434	1	2	localObject5	Object
    //   444	11	2	localObject6	Object
    //   461	122	2	locals	xc.s
    //   591	84	2	locald	i.d
    //   33	523	3	localObject7	Object
    //   40	417	4	localObject8	Object
    //   465	1	4	localException2	Exception
    //   470	1	4	localf12	eb.f1
    //   486	172	4	localObject9	Object
    //   49	296	5	localObject10	Object
    //   102	249	6	localObject11	Object
    //   155	32	7	locali	i
    // Exception table:
    //   from	to	target	type
    //   0	7	10	java/lang/InterruptedException
    //   397	405	429	finally
    //   409	426	429	finally
    //   426	428	429	finally
    //   430	432	429	finally
    //   251	328	434	finally
    //   332	336	434	finally
    //   339	343	434	finally
    //   343	359	434	finally
    //   251	328	441	java/lang/Exception
    //   332	336	441	java/lang/Exception
    //   339	343	441	java/lang/Exception
    //   343	359	441	java/lang/Exception
    //   251	328	451	eb/f1
    //   332	336	451	eb/f1
    //   339	343	451	eb/f1
    //   343	359	451	eb/f1
    //   36	42	461	finally
    //   44	51	461	finally
    //   58	86	461	finally
    //   97	104	461	finally
    //   106	114	461	finally
    //   116	143	461	finally
    //   151	157	461	finally
    //   159	166	461	finally
    //   177	210	461	finally
    //   212	218	461	finally
    //   220	226	461	finally
    //   228	235	461	finally
    //   237	242	461	finally
    //   244	251	461	finally
    //   477	481	461	finally
    //   483	488	461	finally
    //   490	495	461	finally
    //   497	505	461	finally
    //   507	526	461	finally
    //   528	539	461	finally
    //   541	545	461	finally
    //   547	553	461	finally
    //   555	557	461	finally
    //   559	568	461	finally
    //   600	616	461	finally
    //   36	42	465	java/lang/Exception
    //   44	51	465	java/lang/Exception
    //   58	86	465	java/lang/Exception
    //   97	104	465	java/lang/Exception
    //   106	114	465	java/lang/Exception
    //   116	143	465	java/lang/Exception
    //   151	157	465	java/lang/Exception
    //   159	166	465	java/lang/Exception
    //   177	210	465	java/lang/Exception
    //   212	218	465	java/lang/Exception
    //   220	226	465	java/lang/Exception
    //   228	235	465	java/lang/Exception
    //   237	242	465	java/lang/Exception
    //   244	251	465	java/lang/Exception
    //   477	481	465	java/lang/Exception
    //   483	488	465	java/lang/Exception
    //   490	495	465	java/lang/Exception
    //   497	505	465	java/lang/Exception
    //   507	526	465	java/lang/Exception
    //   528	539	465	java/lang/Exception
    //   541	545	465	java/lang/Exception
    //   547	553	465	java/lang/Exception
    //   555	557	465	java/lang/Exception
    //   36	42	470	eb/f1
    //   44	51	470	eb/f1
    //   58	86	470	eb/f1
    //   97	104	470	eb/f1
    //   106	114	470	eb/f1
    //   116	143	470	eb/f1
    //   151	157	470	eb/f1
    //   159	166	470	eb/f1
    //   177	210	470	eb/f1
    //   212	218	470	eb/f1
    //   220	226	470	eb/f1
    //   228	235	470	eb/f1
    //   237	242	470	eb/f1
    //   244	251	470	eb/f1
    //   477	481	470	eb/f1
    //   483	488	470	eb/f1
    //   490	495	470	eb/f1
    //   497	505	470	eb/f1
    //   507	526	470	eb/f1
    //   528	539	470	eb/f1
    //   541	545	470	eb/f1
    //   547	553	470	eb/f1
    //   555	557	470	eb/f1
  }
  
  public final class a
    implements y
  {
    public final z c()
    {
      return z.d;
    }
    
    public final void close() {}
    
    public final long e0(f paramf, long paramLong)
    {
      return -1L;
    }
  }
}

/* Location:
 * Qualified Name:     hb.i.b
 * Java Class Version: 6 (50.0)
 * JD-Core Version:    0.7.1
 */