package hb;

import java.util.logging.Level;
import jb.b;
import jb.b.a;

public final class i$d
  implements b.a, Runnable
{
  public final j a = new j(Level.FINE);
  public b b;
  public boolean c = true;
  
  public i$d(i parami, b paramb)
  {
    b = paramb;
  }
  
  /* Error */
  public final void run()
  {
    // Byte code:
    //   0: invokestatic 54	java/lang/Thread:currentThread	()Ljava/lang/Thread;
    //   3: invokevirtual 58	java/lang/Thread:getName	()Ljava/lang/String;
    //   6: astore_1
    //   7: invokestatic 54	java/lang/Thread:currentThread	()Ljava/lang/Thread;
    //   10: ldc 60
    //   12: invokevirtual 64	java/lang/Thread:setName	(Ljava/lang/String;)V
    //   15: aload_0
    //   16: getfield 42	hb/i$d:b	Ljb/b;
    //   19: checkcast 66	jb/f$c
    //   22: aload_0
    //   23: invokevirtual 70	jb/f$c:f	(Ljb/b$a;)Z
    //   26: ifeq +22 -> 48
    //   29: aload_0
    //   30: getfield 22	hb/i$d:d	Lhb/i;
    //   33: getfield 74	hb/i:G	Lgb/o1;
    //   36: astore_2
    //   37: aload_2
    //   38: ifnull -23 -> 15
    //   41: aload_2
    //   42: invokevirtual 78	gb/o1:a	()V
    //   45: goto -30 -> 15
    //   48: aload_0
    //   49: getfield 22	hb/i$d:d	Lhb/i;
    //   52: getfield 82	hb/i:k	Ljava/lang/Object;
    //   55: astore_2
    //   56: aload_2
    //   57: monitorenter
    //   58: aload_0
    //   59: getfield 22	hb/i$d:d	Lhb/i;
    //   62: getfield 86	hb/i:v	Leb/e1;
    //   65: astore_3
    //   66: aload_2
    //   67: monitorexit
    //   68: aload_3
    //   69: astore_2
    //   70: aload_3
    //   71: ifnonnull +12 -> 83
    //   74: getstatic 91	eb/e1:n	Leb/e1;
    //   77: ldc 93
    //   79: invokevirtual 97	eb/e1:g	(Ljava/lang/String;)Leb/e1;
    //   82: astore_2
    //   83: aload_0
    //   84: getfield 22	hb/i$d:d	Lhb/i;
    //   87: iconst_0
    //   88: getstatic 102	jb/a:d	Ljb/a;
    //   91: aload_2
    //   92: invokevirtual 106	hb/i:t	(ILjb/a;Leb/e1;)V
    //   95: aload_0
    //   96: getfield 42	hb/i$d:b	Ljb/b;
    //   99: checkcast 66	jb/f$c
    //   102: invokevirtual 109	jb/f$c:close	()V
    //   105: goto +113 -> 218
    //   108: astore_2
    //   109: ldc 111
    //   111: aload_2
    //   112: invokevirtual 116	java/lang/Throwable:getMessage	()Ljava/lang/String;
    //   115: invokevirtual 122	java/lang/String:equals	(Ljava/lang/Object;)Z
    //   118: ifeq +6 -> 124
    //   121: goto +97 -> 218
    //   124: aload_2
    //   125: athrow
    //   126: astore_2
    //   127: goto +79 -> 206
    //   130: astore_3
    //   131: aload_2
    //   132: monitorexit
    //   133: aload_3
    //   134: athrow
    //   135: astore 4
    //   137: aload_0
    //   138: getfield 22	hb/i$d:d	Lhb/i;
    //   141: astore_2
    //   142: getstatic 124	jb/a:c	Ljb/a;
    //   145: astore_3
    //   146: getstatic 127	eb/e1:m	Leb/e1;
    //   149: ldc -127
    //   151: invokevirtual 97	eb/e1:g	(Ljava/lang/String;)Leb/e1;
    //   154: aload 4
    //   156: invokevirtual 132	eb/e1:f	(Ljava/lang/Throwable;)Leb/e1;
    //   159: astore 4
    //   161: getstatic 136	hb/i:S	Ljava/util/Map;
    //   164: astore 5
    //   166: aload_2
    //   167: iconst_0
    //   168: aload_3
    //   169: aload 4
    //   171: invokevirtual 106	hb/i:t	(ILjb/a;Leb/e1;)V
    //   174: aload_0
    //   175: getfield 42	hb/i$d:b	Ljb/b;
    //   178: checkcast 66	jb/f$c
    //   181: invokevirtual 109	jb/f$c:close	()V
    //   184: goto +34 -> 218
    //   187: astore_2
    //   188: ldc 111
    //   190: aload_2
    //   191: invokevirtual 116	java/lang/Throwable:getMessage	()Ljava/lang/String;
    //   194: invokevirtual 122	java/lang/String:equals	(Ljava/lang/Object;)Z
    //   197: ifeq +6 -> 203
    //   200: goto +18 -> 218
    //   203: aload_2
    //   204: athrow
    //   205: astore_2
    //   206: getstatic 140	hb/i:T	Ljava/util/logging/Logger;
    //   209: getstatic 143	java/util/logging/Level:INFO	Ljava/util/logging/Level;
    //   212: ldc -111
    //   214: aload_2
    //   215: invokevirtual 151	java/util/logging/Logger:log	(Ljava/util/logging/Level;Ljava/lang/String;Ljava/lang/Throwable;)V
    //   218: aload_0
    //   219: getfield 22	hb/i$d:d	Lhb/i;
    //   222: getfield 155	hb/i:h	Lgb/h2$a;
    //   225: invokeinterface 159 1 0
    //   230: invokestatic 54	java/lang/Thread:currentThread	()Ljava/lang/Thread;
    //   233: aload_1
    //   234: invokevirtual 64	java/lang/Thread:setName	(Ljava/lang/String;)V
    //   237: return
    //   238: astore_2
    //   239: aload_0
    //   240: getfield 42	hb/i$d:b	Ljb/b;
    //   243: checkcast 66	jb/f$c
    //   246: invokevirtual 109	jb/f$c:close	()V
    //   249: goto +31 -> 280
    //   252: astore_3
    //   253: ldc 111
    //   255: aload_3
    //   256: invokevirtual 116	java/lang/Throwable:getMessage	()Ljava/lang/String;
    //   259: invokevirtual 122	java/lang/String:equals	(Ljava/lang/Object;)Z
    //   262: ifne +18 -> 280
    //   265: aload_3
    //   266: athrow
    //   267: astore_3
    //   268: getstatic 140	hb/i:T	Ljava/util/logging/Logger;
    //   271: getstatic 143	java/util/logging/Level:INFO	Ljava/util/logging/Level;
    //   274: ldc -111
    //   276: aload_3
    //   277: invokevirtual 151	java/util/logging/Logger:log	(Ljava/util/logging/Level;Ljava/lang/String;Ljava/lang/Throwable;)V
    //   280: aload_0
    //   281: getfield 22	hb/i$d:d	Lhb/i;
    //   284: getfield 155	hb/i:h	Lgb/h2$a;
    //   287: invokeinterface 159 1 0
    //   292: invokestatic 54	java/lang/Thread:currentThread	()Ljava/lang/Thread;
    //   295: aload_1
    //   296: invokevirtual 64	java/lang/Thread:setName	(Ljava/lang/String;)V
    //   299: aload_2
    //   300: athrow
    // Local variable table:
    //   start	length	slot	name	signature
    //   0	301	0	this	d
    //   6	290	1	str	String
    //   108	17	2	localRuntimeException1	RuntimeException
    //   126	6	2	localIOException1	java.io.IOException
    //   141	26	2	locali	i
    //   187	17	2	localRuntimeException2	RuntimeException
    //   205	10	2	localIOException2	java.io.IOException
    //   238	62	2	localObject2	Object
    //   65	6	3	locale11	eb.e1
    //   130	4	3	localObject3	Object
    //   145	24	3	locala	jb.a
    //   252	14	3	localRuntimeException3	RuntimeException
    //   267	10	3	localIOException3	java.io.IOException
    //   135	20	4	localThrowable	Throwable
    //   159	11	4	locale12	eb.e1
    //   164	1	5	localMap	java.util.Map
    // Exception table:
    //   from	to	target	type
    //   95	105	108	java/lang/RuntimeException
    //   95	105	126	java/io/IOException
    //   58	68	130	finally
    //   131	133	130	finally
    //   15	37	135	finally
    //   41	45	135	finally
    //   48	58	135	finally
    //   74	83	135	finally
    //   83	95	135	finally
    //   133	135	135	finally
    //   174	184	187	java/lang/RuntimeException
    //   174	184	205	java/io/IOException
    //   137	174	238	finally
    //   239	249	252	java/lang/RuntimeException
    //   239	249	267	java/io/IOException
  }
}

/* Location:
 * Qualified Name:     hb.i.d
 * Java Class Version: 6 (50.0)
 * JD-Core Version:    0.7.1
 */