package com.google.ads.interactivemedia.v3.internal;

import android.content.Context;
import android.util.DisplayMetrics;
import android.view.MotionEvent;
import java.io.UnsupportedEncodingException;
import java.lang.reflect.InvocationTargetException;
import java.lang.reflect.Method;
import java.nio.ByteBuffer;
import java.util.ArrayList;

public class ago
  extends agp
{
  private static Method c;
  private static Method d;
  private static Method e;
  private static Method f;
  private static Method g;
  private static Method h;
  private static Method i;
  private static Method j;
  private static Method k;
  private static Method l;
  private static Method m;
  private static Method n;
  private static Method o;
  private static String p;
  private static String q;
  private static String r;
  private static long s = 0L;
  private static agx t;
  private static boolean u = false;
  
  public ago(Context paramContext, agv paramagv, agu paramagu)
  {
    super(paramContext, paramagv, paramagu);
  }
  
  private static String a()
    throws agr
  {
    String str = p;
    if (str != null) {
      return str;
    }
    throw new agr();
  }
  
  private static String a(Context paramContext, agv paramagv)
    throws agr
  {
    Object localObject = q;
    if (localObject != null) {
      return (String)localObject;
    }
    localObject = f;
    if (localObject != null) {
      try
      {
        paramContext = (ByteBuffer)((Method)localObject).invoke(null, new Object[] { paramContext });
        if (paramContext != null)
        {
          paramContext = paramagv.a(paramContext.array(), true);
          q = paramContext;
          return paramContext;
        }
        paramContext = new com/google/ads/interactivemedia/v3/internal/agr;
        paramContext.<init>();
        throw paramContext;
      }
      catch (InvocationTargetException paramContext)
      {
        throw new agr(paramContext);
      }
      catch (IllegalAccessException paramContext)
      {
        throw new agr(paramContext);
      }
    }
    throw new agr();
  }
  
  private static ArrayList<Long> a(MotionEvent paramMotionEvent, DisplayMetrics paramDisplayMetrics)
    throws agr
  {
    Method localMethod = g;
    if ((localMethod != null) && (paramMotionEvent != null)) {
      try
      {
        paramMotionEvent = (ArrayList)localMethod.invoke(null, new Object[] { paramMotionEvent, paramDisplayMetrics });
        return paramMotionEvent;
      }
      catch (InvocationTargetException paramMotionEvent)
      {
        throw new agr(paramMotionEvent);
      }
      catch (IllegalAccessException paramMotionEvent)
      {
        throw new agr(paramMotionEvent);
      }
    }
    throw new agr();
  }
  
  /* Error */
  public static void a(String paramString, Context paramContext, agv paramagv)
  {
    // Byte code:
    //   0: ldc 2
    //   2: monitorenter
    //   3: getstatic 101	com/google/ads/interactivemedia/v3/internal/ago:u	Z
    //   6: istore_3
    //   7: iload_3
    //   8: ifne +843 -> 851
    //   11: new 103	com/google/ads/interactivemedia/v3/internal/agx
    //   14: astore 4
    //   16: aload 4
    //   18: aload_2
    //   19: aconst_null
    //   20: invokespecial 106	com/google/ads/interactivemedia/v3/internal/agx:<init>	(Lcom/google/ads/interactivemedia/v3/internal/agv;Ljava/security/SecureRandom;)V
    //   23: aload 4
    //   25: putstatic 108	com/google/ads/interactivemedia/v3/internal/ago:t	Lcom/google/ads/interactivemedia/v3/internal/agx;
    //   28: aload_0
    //   29: putstatic 42	com/google/ads/interactivemedia/v3/internal/ago:p	Ljava/lang/String;
    //   32: aload 4
    //   34: invokestatic 112	com/google/ads/interactivemedia/v3/internal/rp:f	()Ljava/lang/String;
    //   37: invokevirtual 115	com/google/ads/interactivemedia/v3/internal/agx:a	(Ljava/lang/String;)[B
    //   40: astore 4
    //   42: getstatic 108	com/google/ads/interactivemedia/v3/internal/ago:t	Lcom/google/ads/interactivemedia/v3/internal/agx;
    //   45: aload 4
    //   47: invokestatic 117	com/google/ads/interactivemedia/v3/internal/rp:g	()Ljava/lang/String;
    //   50: invokevirtual 120	com/google/ads/interactivemedia/v3/internal/agx:a	([BLjava/lang/String;)[B
    //   53: astore 5
    //   55: aload_1
    //   56: invokevirtual 126	android/content/Context:getCacheDir	()Ljava/io/File;
    //   59: astore_0
    //   60: aload_0
    //   61: ifnonnull +28 -> 89
    //   64: aload_1
    //   65: ldc -128
    //   67: iconst_0
    //   68: invokevirtual 132	android/content/Context:getDir	(Ljava/lang/String;I)Ljava/io/File;
    //   71: astore_0
    //   72: aload_0
    //   73: ifnull +6 -> 79
    //   76: goto +13 -> 89
    //   79: new 40	com/google/ads/interactivemedia/v3/internal/agr
    //   82: astore_0
    //   83: aload_0
    //   84: invokespecial 45	com/google/ads/interactivemedia/v3/internal/agr:<init>	()V
    //   87: aload_0
    //   88: athrow
    //   89: ldc -122
    //   91: ldc -120
    //   93: aload_0
    //   94: invokestatic 142	java/io/File:createTempFile	(Ljava/lang/String;Ljava/lang/String;Ljava/io/File;)Ljava/io/File;
    //   97: astore_2
    //   98: new 144	java/io/FileOutputStream
    //   101: astore 6
    //   103: aload 6
    //   105: aload_2
    //   106: invokespecial 147	java/io/FileOutputStream:<init>	(Ljava/io/File;)V
    //   109: aload 6
    //   111: aload 5
    //   113: iconst_0
    //   114: aload 5
    //   116: arraylength
    //   117: invokevirtual 151	java/io/FileOutputStream:write	([BII)V
    //   120: aload 6
    //   122: invokevirtual 154	java/io/FileOutputStream:close	()V
    //   125: new 156	dalvik/system/DexClassLoader
    //   128: astore 7
    //   130: aload 7
    //   132: aload_2
    //   133: invokevirtual 159	java/io/File:getAbsolutePath	()Ljava/lang/String;
    //   136: aload_0
    //   137: invokevirtual 159	java/io/File:getAbsolutePath	()Ljava/lang/String;
    //   140: aconst_null
    //   141: aload_1
    //   142: invokevirtual 163	android/content/Context:getClassLoader	()Ljava/lang/ClassLoader;
    //   145: invokespecial 166	dalvik/system/DexClassLoader:<init>	(Ljava/lang/String;Ljava/lang/String;Ljava/lang/String;Ljava/lang/ClassLoader;)V
    //   148: aload 7
    //   150: aload 4
    //   152: invokestatic 168	com/google/ads/interactivemedia/v3/internal/rp:p	()Ljava/lang/String;
    //   155: invokestatic 172	com/google/ads/interactivemedia/v3/internal/ago:b	([BLjava/lang/String;)Ljava/lang/String;
    //   158: invokevirtual 178	java/lang/ClassLoader:loadClass	(Ljava/lang/String;)Ljava/lang/Class;
    //   161: astore 8
    //   163: aload 7
    //   165: aload 4
    //   167: invokestatic 181	com/google/ads/interactivemedia/v3/internal/rp:D	()Ljava/lang/String;
    //   170: invokestatic 172	com/google/ads/interactivemedia/v3/internal/ago:b	([BLjava/lang/String;)Ljava/lang/String;
    //   173: invokevirtual 178	java/lang/ClassLoader:loadClass	(Ljava/lang/String;)Ljava/lang/Class;
    //   176: astore 5
    //   178: aload 7
    //   180: aload 4
    //   182: invokestatic 184	com/google/ads/interactivemedia/v3/internal/rp:x	()Ljava/lang/String;
    //   185: invokestatic 172	com/google/ads/interactivemedia/v3/internal/ago:b	([BLjava/lang/String;)Ljava/lang/String;
    //   188: invokevirtual 178	java/lang/ClassLoader:loadClass	(Ljava/lang/String;)Ljava/lang/Class;
    //   191: astore 9
    //   193: aload 7
    //   195: aload 4
    //   197: invokestatic 186	com/google/ads/interactivemedia/v3/internal/rp:t	()Ljava/lang/String;
    //   200: invokestatic 172	com/google/ads/interactivemedia/v3/internal/ago:b	([BLjava/lang/String;)Ljava/lang/String;
    //   203: invokevirtual 178	java/lang/ClassLoader:loadClass	(Ljava/lang/String;)Ljava/lang/Class;
    //   206: astore 10
    //   208: aload 7
    //   210: aload 4
    //   212: invokestatic 189	com/google/ads/interactivemedia/v3/internal/rp:F	()Ljava/lang/String;
    //   215: invokestatic 172	com/google/ads/interactivemedia/v3/internal/ago:b	([BLjava/lang/String;)Ljava/lang/String;
    //   218: invokevirtual 178	java/lang/ClassLoader:loadClass	(Ljava/lang/String;)Ljava/lang/Class;
    //   221: astore 6
    //   223: aload 7
    //   225: aload 4
    //   227: invokestatic 191	com/google/ads/interactivemedia/v3/internal/rp:r	()Ljava/lang/String;
    //   230: invokestatic 172	com/google/ads/interactivemedia/v3/internal/ago:b	([BLjava/lang/String;)Ljava/lang/String;
    //   233: invokevirtual 178	java/lang/ClassLoader:loadClass	(Ljava/lang/String;)Ljava/lang/Class;
    //   236: astore 11
    //   238: aload 7
    //   240: aload 4
    //   242: invokestatic 194	com/google/ads/interactivemedia/v3/internal/rp:B	()Ljava/lang/String;
    //   245: invokestatic 172	com/google/ads/interactivemedia/v3/internal/ago:b	([BLjava/lang/String;)Ljava/lang/String;
    //   248: invokevirtual 178	java/lang/ClassLoader:loadClass	(Ljava/lang/String;)Ljava/lang/Class;
    //   251: astore 12
    //   253: aload 7
    //   255: aload 4
    //   257: invokestatic 197	com/google/ads/interactivemedia/v3/internal/rp:z	()Ljava/lang/String;
    //   260: invokestatic 172	com/google/ads/interactivemedia/v3/internal/ago:b	([BLjava/lang/String;)Ljava/lang/String;
    //   263: invokevirtual 178	java/lang/ClassLoader:loadClass	(Ljava/lang/String;)Ljava/lang/Class;
    //   266: astore 13
    //   268: aload 7
    //   270: aload 4
    //   272: invokestatic 199	com/google/ads/interactivemedia/v3/internal/rp:n	()Ljava/lang/String;
    //   275: invokestatic 172	com/google/ads/interactivemedia/v3/internal/ago:b	([BLjava/lang/String;)Ljava/lang/String;
    //   278: invokevirtual 178	java/lang/ClassLoader:loadClass	(Ljava/lang/String;)Ljava/lang/Class;
    //   281: astore 14
    //   283: aload 7
    //   285: aload 4
    //   287: invokestatic 201	com/google/ads/interactivemedia/v3/internal/rp:l	()Ljava/lang/String;
    //   290: invokestatic 172	com/google/ads/interactivemedia/v3/internal/ago:b	([BLjava/lang/String;)Ljava/lang/String;
    //   293: invokevirtual 178	java/lang/ClassLoader:loadClass	(Ljava/lang/String;)Ljava/lang/Class;
    //   296: astore 15
    //   298: aload 7
    //   300: aload 4
    //   302: invokestatic 203	com/google/ads/interactivemedia/v3/internal/rp:j	()Ljava/lang/String;
    //   305: invokestatic 172	com/google/ads/interactivemedia/v3/internal/ago:b	([BLjava/lang/String;)Ljava/lang/String;
    //   308: invokevirtual 178	java/lang/ClassLoader:loadClass	(Ljava/lang/String;)Ljava/lang/Class;
    //   311: astore 16
    //   313: aload 7
    //   315: aload 4
    //   317: invokestatic 206	com/google/ads/interactivemedia/v3/internal/rp:v	()Ljava/lang/String;
    //   320: invokestatic 172	com/google/ads/interactivemedia/v3/internal/ago:b	([BLjava/lang/String;)Ljava/lang/String;
    //   323: invokevirtual 178	java/lang/ClassLoader:loadClass	(Ljava/lang/String;)Ljava/lang/Class;
    //   326: astore 17
    //   328: aload_2
    //   329: astore_1
    //   330: aload 7
    //   332: aload 4
    //   334: invokestatic 208	com/google/ads/interactivemedia/v3/internal/rp:h	()Ljava/lang/String;
    //   337: invokestatic 172	com/google/ads/interactivemedia/v3/internal/ago:b	([BLjava/lang/String;)Ljava/lang/String;
    //   340: invokevirtual 178	java/lang/ClassLoader:loadClass	(Ljava/lang/String;)Ljava/lang/Class;
    //   343: astore 7
    //   345: aload 8
    //   347: aload 4
    //   349: invokestatic 210	com/google/ads/interactivemedia/v3/internal/rp:q	()Ljava/lang/String;
    //   352: invokestatic 172	com/google/ads/interactivemedia/v3/internal/ago:b	([BLjava/lang/String;)Ljava/lang/String;
    //   355: iconst_0
    //   356: anewarray 212	java/lang/Class
    //   359: invokevirtual 216	java/lang/Class:getMethod	(Ljava/lang/String;[Ljava/lang/Class;)Ljava/lang/reflect/Method;
    //   362: putstatic 218	com/google/ads/interactivemedia/v3/internal/ago:c	Ljava/lang/reflect/Method;
    //   365: aload 5
    //   367: aload 4
    //   369: invokestatic 221	com/google/ads/interactivemedia/v3/internal/rp:E	()Ljava/lang/String;
    //   372: invokestatic 172	com/google/ads/interactivemedia/v3/internal/ago:b	([BLjava/lang/String;)Ljava/lang/String;
    //   375: iconst_0
    //   376: anewarray 212	java/lang/Class
    //   379: invokevirtual 216	java/lang/Class:getMethod	(Ljava/lang/String;[Ljava/lang/Class;)Ljava/lang/reflect/Method;
    //   382: putstatic 223	com/google/ads/interactivemedia/v3/internal/ago:d	Ljava/lang/reflect/Method;
    //   385: aload 9
    //   387: aload 4
    //   389: invokestatic 226	com/google/ads/interactivemedia/v3/internal/rp:y	()Ljava/lang/String;
    //   392: invokestatic 172	com/google/ads/interactivemedia/v3/internal/ago:b	([BLjava/lang/String;)Ljava/lang/String;
    //   395: iconst_0
    //   396: anewarray 212	java/lang/Class
    //   399: invokevirtual 216	java/lang/Class:getMethod	(Ljava/lang/String;[Ljava/lang/Class;)Ljava/lang/reflect/Method;
    //   402: putstatic 228	com/google/ads/interactivemedia/v3/internal/ago:e	Ljava/lang/reflect/Method;
    //   405: aload 10
    //   407: aload 4
    //   409: invokestatic 230	com/google/ads/interactivemedia/v3/internal/rp:u	()Ljava/lang/String;
    //   412: invokestatic 172	com/google/ads/interactivemedia/v3/internal/ago:b	([BLjava/lang/String;)Ljava/lang/String;
    //   415: iconst_1
    //   416: anewarray 212	java/lang/Class
    //   419: dup
    //   420: iconst_0
    //   421: ldc 122
    //   423: aastore
    //   424: invokevirtual 216	java/lang/Class:getMethod	(Ljava/lang/String;[Ljava/lang/Class;)Ljava/lang/reflect/Method;
    //   427: putstatic 55	com/google/ads/interactivemedia/v3/internal/ago:f	Ljava/lang/reflect/Method;
    //   430: aload 6
    //   432: aload 4
    //   434: invokestatic 233	com/google/ads/interactivemedia/v3/internal/rp:G	()Ljava/lang/String;
    //   437: invokestatic 172	com/google/ads/interactivemedia/v3/internal/ago:b	([BLjava/lang/String;)Ljava/lang/String;
    //   440: iconst_2
    //   441: anewarray 212	java/lang/Class
    //   444: dup
    //   445: iconst_0
    //   446: ldc -21
    //   448: aastore
    //   449: dup
    //   450: iconst_1
    //   451: ldc -19
    //   453: aastore
    //   454: invokevirtual 216	java/lang/Class:getMethod	(Ljava/lang/String;[Ljava/lang/Class;)Ljava/lang/reflect/Method;
    //   457: putstatic 80	com/google/ads/interactivemedia/v3/internal/ago:g	Ljava/lang/reflect/Method;
    //   460: aload 11
    //   462: aload 4
    //   464: invokestatic 239	com/google/ads/interactivemedia/v3/internal/rp:s	()Ljava/lang/String;
    //   467: invokestatic 172	com/google/ads/interactivemedia/v3/internal/ago:b	([BLjava/lang/String;)Ljava/lang/String;
    //   470: iconst_1
    //   471: anewarray 212	java/lang/Class
    //   474: dup
    //   475: iconst_0
    //   476: ldc 122
    //   478: aastore
    //   479: invokevirtual 216	java/lang/Class:getMethod	(Ljava/lang/String;[Ljava/lang/Class;)Ljava/lang/reflect/Method;
    //   482: putstatic 241	com/google/ads/interactivemedia/v3/internal/ago:h	Ljava/lang/reflect/Method;
    //   485: aload 12
    //   487: aload 4
    //   489: invokestatic 244	com/google/ads/interactivemedia/v3/internal/rp:C	()Ljava/lang/String;
    //   492: invokestatic 172	com/google/ads/interactivemedia/v3/internal/ago:b	([BLjava/lang/String;)Ljava/lang/String;
    //   495: iconst_1
    //   496: anewarray 212	java/lang/Class
    //   499: dup
    //   500: iconst_0
    //   501: ldc 122
    //   503: aastore
    //   504: invokevirtual 216	java/lang/Class:getMethod	(Ljava/lang/String;[Ljava/lang/Class;)Ljava/lang/reflect/Method;
    //   507: putstatic 246	com/google/ads/interactivemedia/v3/internal/ago:i	Ljava/lang/reflect/Method;
    //   510: aload 13
    //   512: aload 4
    //   514: invokestatic 249	com/google/ads/interactivemedia/v3/internal/rp:A	()Ljava/lang/String;
    //   517: invokestatic 172	com/google/ads/interactivemedia/v3/internal/ago:b	([BLjava/lang/String;)Ljava/lang/String;
    //   520: iconst_1
    //   521: anewarray 212	java/lang/Class
    //   524: dup
    //   525: iconst_0
    //   526: ldc 122
    //   528: aastore
    //   529: invokevirtual 216	java/lang/Class:getMethod	(Ljava/lang/String;[Ljava/lang/Class;)Ljava/lang/reflect/Method;
    //   532: putstatic 251	com/google/ads/interactivemedia/v3/internal/ago:j	Ljava/lang/reflect/Method;
    //   535: aload 14
    //   537: aload 4
    //   539: invokestatic 253	com/google/ads/interactivemedia/v3/internal/rp:o	()Ljava/lang/String;
    //   542: invokestatic 172	com/google/ads/interactivemedia/v3/internal/ago:b	([BLjava/lang/String;)Ljava/lang/String;
    //   545: iconst_1
    //   546: anewarray 212	java/lang/Class
    //   549: dup
    //   550: iconst_0
    //   551: ldc 122
    //   553: aastore
    //   554: invokevirtual 216	java/lang/Class:getMethod	(Ljava/lang/String;[Ljava/lang/Class;)Ljava/lang/reflect/Method;
    //   557: putstatic 255	com/google/ads/interactivemedia/v3/internal/ago:k	Ljava/lang/reflect/Method;
    //   560: aload 15
    //   562: aload 4
    //   564: invokestatic 257	com/google/ads/interactivemedia/v3/internal/rp:m	()Ljava/lang/String;
    //   567: invokestatic 172	com/google/ads/interactivemedia/v3/internal/ago:b	([BLjava/lang/String;)Ljava/lang/String;
    //   570: iconst_1
    //   571: anewarray 212	java/lang/Class
    //   574: dup
    //   575: iconst_0
    //   576: ldc 122
    //   578: aastore
    //   579: invokevirtual 216	java/lang/Class:getMethod	(Ljava/lang/String;[Ljava/lang/Class;)Ljava/lang/reflect/Method;
    //   582: putstatic 259	com/google/ads/interactivemedia/v3/internal/ago:l	Ljava/lang/reflect/Method;
    //   585: aload 16
    //   587: aload 4
    //   589: invokestatic 261	com/google/ads/interactivemedia/v3/internal/rp:k	()Ljava/lang/String;
    //   592: invokestatic 172	com/google/ads/interactivemedia/v3/internal/ago:b	([BLjava/lang/String;)Ljava/lang/String;
    //   595: iconst_1
    //   596: anewarray 212	java/lang/Class
    //   599: dup
    //   600: iconst_0
    //   601: ldc 122
    //   603: aastore
    //   604: invokevirtual 216	java/lang/Class:getMethod	(Ljava/lang/String;[Ljava/lang/Class;)Ljava/lang/reflect/Method;
    //   607: putstatic 263	com/google/ads/interactivemedia/v3/internal/ago:m	Ljava/lang/reflect/Method;
    //   610: aload 17
    //   612: aload 4
    //   614: invokestatic 266	com/google/ads/interactivemedia/v3/internal/rp:w	()Ljava/lang/String;
    //   617: invokestatic 172	com/google/ads/interactivemedia/v3/internal/ago:b	([BLjava/lang/String;)Ljava/lang/String;
    //   620: iconst_1
    //   621: anewarray 212	java/lang/Class
    //   624: dup
    //   625: iconst_0
    //   626: ldc 122
    //   628: aastore
    //   629: invokevirtual 216	java/lang/Class:getMethod	(Ljava/lang/String;[Ljava/lang/Class;)Ljava/lang/reflect/Method;
    //   632: putstatic 268	com/google/ads/interactivemedia/v3/internal/ago:n	Ljava/lang/reflect/Method;
    //   635: aload 7
    //   637: aload 4
    //   639: invokestatic 270	com/google/ads/interactivemedia/v3/internal/rp:i	()Ljava/lang/String;
    //   642: invokestatic 172	com/google/ads/interactivemedia/v3/internal/ago:b	([BLjava/lang/String;)Ljava/lang/String;
    //   645: iconst_1
    //   646: anewarray 212	java/lang/Class
    //   649: dup
    //   650: iconst_0
    //   651: ldc 122
    //   653: aastore
    //   654: invokevirtual 216	java/lang/Class:getMethod	(Ljava/lang/String;[Ljava/lang/Class;)Ljava/lang/reflect/Method;
    //   657: putstatic 272	com/google/ads/interactivemedia/v3/internal/ago:o	Ljava/lang/reflect/Method;
    //   660: aload_1
    //   661: invokevirtual 275	java/io/File:getName	()Ljava/lang/String;
    //   664: astore_2
    //   665: aload_1
    //   666: invokevirtual 279	java/io/File:delete	()Z
    //   669: pop
    //   670: new 138	java/io/File
    //   673: astore_1
    //   674: aload_1
    //   675: aload_0
    //   676: aload_2
    //   677: ldc -120
    //   679: ldc_w 281
    //   682: invokevirtual 287	java/lang/String:replace	(Ljava/lang/CharSequence;Ljava/lang/CharSequence;)Ljava/lang/String;
    //   685: invokespecial 290	java/io/File:<init>	(Ljava/io/File;Ljava/lang/String;)V
    //   688: aload_1
    //   689: invokevirtual 279	java/io/File:delete	()Z
    //   692: pop
    //   693: invokestatic 293	com/google/ads/interactivemedia/v3/internal/ago:b	()Ljava/lang/Long;
    //   696: invokevirtual 299	java/lang/Long:longValue	()J
    //   699: putstatic 301	com/google/ads/interactivemedia/v3/internal/ago:s	J
    //   702: iconst_1
    //   703: putstatic 101	com/google/ads/interactivemedia/v3/internal/ago:u	Z
    //   706: ldc 2
    //   708: monitorexit
    //   709: return
    //   710: astore 4
    //   712: aload_0
    //   713: astore_1
    //   714: aload 4
    //   716: astore_0
    //   717: goto +20 -> 737
    //   720: astore 4
    //   722: aload_0
    //   723: astore_1
    //   724: aload 4
    //   726: astore_0
    //   727: goto +10 -> 737
    //   730: astore 4
    //   732: aload_0
    //   733: astore_1
    //   734: aload 4
    //   736: astore_0
    //   737: aload_2
    //   738: invokevirtual 275	java/io/File:getName	()Ljava/lang/String;
    //   741: astore 4
    //   743: aload_2
    //   744: invokevirtual 279	java/io/File:delete	()Z
    //   747: pop
    //   748: new 138	java/io/File
    //   751: astore_2
    //   752: aload_2
    //   753: aload_1
    //   754: aload 4
    //   756: ldc -120
    //   758: ldc_w 281
    //   761: invokevirtual 287	java/lang/String:replace	(Ljava/lang/CharSequence;Ljava/lang/CharSequence;)Ljava/lang/String;
    //   764: invokespecial 290	java/io/File:<init>	(Ljava/io/File;Ljava/lang/String;)V
    //   767: aload_2
    //   768: invokevirtual 279	java/io/File:delete	()Z
    //   771: pop
    //   772: aload_0
    //   773: athrow
    //   774: astore_0
    //   775: new 40	com/google/ads/interactivemedia/v3/internal/agr
    //   778: astore_1
    //   779: aload_1
    //   780: aload_0
    //   781: invokespecial 77	com/google/ads/interactivemedia/v3/internal/agr:<init>	(Ljava/lang/Throwable;)V
    //   784: aload_1
    //   785: athrow
    //   786: astore_1
    //   787: new 40	com/google/ads/interactivemedia/v3/internal/agr
    //   790: astore_0
    //   791: aload_0
    //   792: aload_1
    //   793: invokespecial 77	com/google/ads/interactivemedia/v3/internal/agr:<init>	(Ljava/lang/Throwable;)V
    //   796: aload_0
    //   797: athrow
    //   798: astore_0
    //   799: new 40	com/google/ads/interactivemedia/v3/internal/agr
    //   802: astore_1
    //   803: aload_1
    //   804: aload_0
    //   805: invokespecial 77	com/google/ads/interactivemedia/v3/internal/agr:<init>	(Ljava/lang/Throwable;)V
    //   808: aload_1
    //   809: athrow
    //   810: astore_1
    //   811: new 40	com/google/ads/interactivemedia/v3/internal/agr
    //   814: astore_0
    //   815: aload_0
    //   816: aload_1
    //   817: invokespecial 77	com/google/ads/interactivemedia/v3/internal/agr:<init>	(Ljava/lang/Throwable;)V
    //   820: aload_0
    //   821: athrow
    //   822: astore_0
    //   823: new 40	com/google/ads/interactivemedia/v3/internal/agr
    //   826: astore_1
    //   827: aload_1
    //   828: aload_0
    //   829: invokespecial 77	com/google/ads/interactivemedia/v3/internal/agr:<init>	(Ljava/lang/Throwable;)V
    //   832: aload_1
    //   833: athrow
    //   834: astore_0
    //   835: new 40	com/google/ads/interactivemedia/v3/internal/agr
    //   838: astore_1
    //   839: aload_1
    //   840: aload_0
    //   841: invokespecial 77	com/google/ads/interactivemedia/v3/internal/agr:<init>	(Ljava/lang/Throwable;)V
    //   844: aload_1
    //   845: athrow
    //   846: astore_0
    //   847: ldc 2
    //   849: monitorexit
    //   850: return
    //   851: ldc 2
    //   853: monitorexit
    //   854: return
    //   855: astore_0
    //   856: ldc 2
    //   858: monitorexit
    //   859: aload_0
    //   860: athrow
    //   861: astore_0
    //   862: goto -11 -> 851
    // Local variable table:
    //   start	length	slot	name	signature
    //   0	865	0	paramString	String
    //   0	865	1	paramContext	Context
    //   0	865	2	paramagv	agv
    //   6	2	3	bool	boolean
    //   14	624	4	localObject1	Object
    //   710	5	4	localObject2	Object
    //   720	5	4	localObject3	Object
    //   730	5	4	localObject4	Object
    //   741	14	4	str	String
    //   53	313	5	localObject5	Object
    //   101	330	6	localObject6	Object
    //   128	508	7	localObject7	Object
    //   161	185	8	localClass1	Class
    //   191	195	9	localClass2	Class
    //   206	200	10	localClass3	Class
    //   236	225	11	localClass4	Class
    //   251	235	12	localClass5	Class
    //   266	245	13	localClass6	Class
    //   281	255	14	localClass7	Class
    //   296	265	15	localClass8	Class
    //   311	275	16	localClass9	Class
    //   326	285	17	localClass10	Class
    // Exception table:
    //   from	to	target	type
    //   330	660	710	finally
    //   313	328	720	finally
    //   125	313	730	finally
    //   32	60	774	java/lang/NullPointerException
    //   64	72	774	java/lang/NullPointerException
    //   79	89	774	java/lang/NullPointerException
    //   89	125	774	java/lang/NullPointerException
    //   660	693	774	java/lang/NullPointerException
    //   737	774	774	java/lang/NullPointerException
    //   32	60	786	java/lang/NoSuchMethodException
    //   64	72	786	java/lang/NoSuchMethodException
    //   79	89	786	java/lang/NoSuchMethodException
    //   89	125	786	java/lang/NoSuchMethodException
    //   660	693	786	java/lang/NoSuchMethodException
    //   737	774	786	java/lang/NoSuchMethodException
    //   32	60	798	com/google/ads/interactivemedia/v3/internal/agw
    //   64	72	798	com/google/ads/interactivemedia/v3/internal/agw
    //   79	89	798	com/google/ads/interactivemedia/v3/internal/agw
    //   89	125	798	com/google/ads/interactivemedia/v3/internal/agw
    //   660	693	798	com/google/ads/interactivemedia/v3/internal/agw
    //   737	774	798	com/google/ads/interactivemedia/v3/internal/agw
    //   32	60	810	java/lang/ClassNotFoundException
    //   64	72	810	java/lang/ClassNotFoundException
    //   79	89	810	java/lang/ClassNotFoundException
    //   89	125	810	java/lang/ClassNotFoundException
    //   660	693	810	java/lang/ClassNotFoundException
    //   737	774	810	java/lang/ClassNotFoundException
    //   32	60	822	java/io/IOException
    //   64	72	822	java/io/IOException
    //   79	89	822	java/io/IOException
    //   89	125	822	java/io/IOException
    //   660	693	822	java/io/IOException
    //   737	774	822	java/io/IOException
    //   32	60	834	java/io/FileNotFoundException
    //   64	72	834	java/io/FileNotFoundException
    //   79	89	834	java/io/FileNotFoundException
    //   89	125	834	java/io/FileNotFoundException
    //   660	693	834	java/io/FileNotFoundException
    //   737	774	834	java/io/FileNotFoundException
    //   11	32	846	com/google/ads/interactivemedia/v3/internal/agr
    //   32	60	846	com/google/ads/interactivemedia/v3/internal/agr
    //   64	72	846	com/google/ads/interactivemedia/v3/internal/agr
    //   79	89	846	com/google/ads/interactivemedia/v3/internal/agr
    //   89	125	846	com/google/ads/interactivemedia/v3/internal/agr
    //   660	693	846	com/google/ads/interactivemedia/v3/internal/agr
    //   693	706	846	com/google/ads/interactivemedia/v3/internal/agr
    //   737	774	846	com/google/ads/interactivemedia/v3/internal/agr
    //   775	786	846	com/google/ads/interactivemedia/v3/internal/agr
    //   787	798	846	com/google/ads/interactivemedia/v3/internal/agr
    //   799	810	846	com/google/ads/interactivemedia/v3/internal/agr
    //   811	822	846	com/google/ads/interactivemedia/v3/internal/agr
    //   823	834	846	com/google/ads/interactivemedia/v3/internal/agr
    //   835	846	846	com/google/ads/interactivemedia/v3/internal/agr
    //   3	7	855	finally
    //   11	32	855	finally
    //   32	60	855	finally
    //   64	72	855	finally
    //   79	89	855	finally
    //   89	125	855	finally
    //   660	693	855	finally
    //   693	706	855	finally
    //   737	774	855	finally
    //   775	786	855	finally
    //   787	798	855	finally
    //   799	810	855	finally
    //   811	822	855	finally
    //   823	834	855	finally
    //   835	846	855	finally
    //   11	32	861	java/lang/UnsupportedOperationException
    //   32	60	861	java/lang/UnsupportedOperationException
    //   64	72	861	java/lang/UnsupportedOperationException
    //   79	89	861	java/lang/UnsupportedOperationException
    //   89	125	861	java/lang/UnsupportedOperationException
    //   660	693	861	java/lang/UnsupportedOperationException
    //   693	706	861	java/lang/UnsupportedOperationException
    //   737	774	861	java/lang/UnsupportedOperationException
    //   775	786	861	java/lang/UnsupportedOperationException
    //   787	798	861	java/lang/UnsupportedOperationException
    //   799	810	861	java/lang/UnsupportedOperationException
    //   811	822	861	java/lang/UnsupportedOperationException
    //   823	834	861	java/lang/UnsupportedOperationException
    //   835	846	861	java/lang/UnsupportedOperationException
  }
  
  private static Long b()
    throws agr
  {
    Object localObject = c;
    if (localObject != null) {
      try
      {
        localObject = (Long)((Method)localObject).invoke(null, new Object[0]);
        return (Long)localObject;
      }
      catch (InvocationTargetException localInvocationTargetException)
      {
        throw new agr(localInvocationTargetException);
      }
      catch (IllegalAccessException localIllegalAccessException)
      {
        throw new agr(localIllegalAccessException);
      }
    }
    throw new agr();
  }
  
  private static String b(Context paramContext, agv paramagv)
    throws agr
  {
    Object localObject = r;
    if (localObject != null) {
      return (String)localObject;
    }
    localObject = i;
    if (localObject != null) {
      try
      {
        paramContext = (ByteBuffer)((Method)localObject).invoke(null, new Object[] { paramContext });
        if (paramContext != null)
        {
          paramContext = paramagv.a(paramContext.array(), true);
          r = paramContext;
          return paramContext;
        }
        paramContext = new com/google/ads/interactivemedia/v3/internal/agr;
        paramContext.<init>();
        throw paramContext;
      }
      catch (InvocationTargetException paramContext)
      {
        throw new agr(paramContext);
      }
      catch (IllegalAccessException paramContext)
      {
        throw new agr(paramContext);
      }
    }
    throw new agr();
  }
  
  private static String b(byte[] paramArrayOfByte, String paramString)
    throws agr
  {
    try
    {
      paramArrayOfByte = new String(t.a(paramArrayOfByte, paramString), "UTF-8");
      return paramArrayOfByte;
    }
    catch (UnsupportedEncodingException paramArrayOfByte)
    {
      throw new agr(paramArrayOfByte);
    }
    catch (agw paramArrayOfByte)
    {
      throw new agr(paramArrayOfByte);
    }
  }
  
  private static String c()
    throws agr
  {
    Object localObject = e;
    if (localObject != null) {
      try
      {
        localObject = (String)((Method)localObject).invoke(null, new Object[0]);
        return (String)localObject;
      }
      catch (InvocationTargetException localInvocationTargetException)
      {
        throw new agr(localInvocationTargetException);
      }
      catch (IllegalAccessException localIllegalAccessException)
      {
        throw new agr(localIllegalAccessException);
      }
    }
    throw new agr();
  }
  
  public static String c(Context paramContext)
    throws agr
  {
    Method localMethod = h;
    if (localMethod != null) {
      try
      {
        paramContext = (String)localMethod.invoke(null, new Object[] { paramContext });
        if (paramContext != null) {
          return paramContext;
        }
        paramContext = new com/google/ads/interactivemedia/v3/internal/agr;
        paramContext.<init>();
        throw paramContext;
      }
      catch (InvocationTargetException paramContext)
      {
        throw new agr(paramContext);
      }
      catch (IllegalAccessException paramContext)
      {
        throw new agr(paramContext);
      }
    }
    throw new agr();
  }
  
  private static Long d()
    throws agr
  {
    Object localObject = d;
    if (localObject != null) {
      try
      {
        localObject = (Long)((Method)localObject).invoke(null, new Object[0]);
        return (Long)localObject;
      }
      catch (InvocationTargetException localInvocationTargetException)
      {
        throw new agr(localInvocationTargetException);
      }
      catch (IllegalAccessException localIllegalAccessException)
      {
        throw new agr(localIllegalAccessException);
      }
    }
    throw new agr();
  }
  
  private static String e(Context paramContext)
    throws agr
  {
    Method localMethod = l;
    if (localMethod != null) {
      try
      {
        paramContext = (String)localMethod.invoke(null, new Object[] { paramContext });
        return paramContext;
      }
      catch (InvocationTargetException paramContext)
      {
        throw new agr(paramContext);
      }
      catch (IllegalAccessException paramContext)
      {
        throw new agr(paramContext);
      }
    }
    throw new agr();
  }
  
  private static Long f(Context paramContext)
    throws agr
  {
    Method localMethod = m;
    if (localMethod != null) {
      try
      {
        paramContext = (Long)localMethod.invoke(null, new Object[] { paramContext });
        return paramContext;
      }
      catch (InvocationTargetException paramContext)
      {
        throw new agr(paramContext);
      }
      catch (IllegalAccessException paramContext)
      {
        throw new agr(paramContext);
      }
    }
    throw new agr();
  }
  
  private static ArrayList<Long> g(Context paramContext)
    throws agr
  {
    Method localMethod = j;
    if (localMethod != null) {
      try
      {
        paramContext = (ArrayList)localMethod.invoke(null, new Object[] { paramContext });
        if ((paramContext != null) && (paramContext.size() == 2)) {
          return paramContext;
        }
        paramContext = new com/google/ads/interactivemedia/v3/internal/agr;
        paramContext.<init>();
        throw paramContext;
      }
      catch (InvocationTargetException paramContext)
      {
        throw new agr(paramContext);
      }
      catch (IllegalAccessException paramContext)
      {
        throw new agr(paramContext);
      }
    }
    throw new agr();
  }
  
  private static int[] h(Context paramContext)
    throws agr
  {
    Method localMethod = k;
    if (localMethod != null) {
      try
      {
        paramContext = (int[])localMethod.invoke(null, new Object[] { paramContext });
        return paramContext;
      }
      catch (InvocationTargetException paramContext)
      {
        throw new agr(paramContext);
      }
      catch (IllegalAccessException paramContext)
      {
        throw new agr(paramContext);
      }
    }
    throw new agr();
  }
  
  private static int i(Context paramContext)
    throws agr
  {
    Method localMethod = n;
    if (localMethod != null) {
      try
      {
        int i1 = ((Integer)localMethod.invoke(null, new Object[] { paramContext })).intValue();
        return i1;
      }
      catch (InvocationTargetException paramContext)
      {
        throw new agr(paramContext);
      }
      catch (IllegalAccessException paramContext)
      {
        throw new agr(paramContext);
      }
    }
    throw new agr();
  }
  
  private static int j(Context paramContext)
    throws agr
  {
    Method localMethod = o;
    if (localMethod != null) {
      try
      {
        int i1 = ((Integer)localMethod.invoke(null, new Object[] { paramContext })).intValue();
        return i1;
      }
      catch (InvocationTargetException paramContext)
      {
        throw new agr(paramContext);
      }
      catch (IllegalAccessException paramContext)
      {
        throw new agr(paramContext);
      }
    }
    throw new agr();
  }
  
  /* Error */
  public void a(Context paramContext)
  {
    // Byte code:
    //   0: aload_0
    //   1: iconst_1
    //   2: invokestatic 330	com/google/ads/interactivemedia/v3/internal/ago:c	()Ljava/lang/String;
    //   5: invokevirtual 333	com/google/ads/interactivemedia/v3/internal/agp:a	(ILjava/lang/String;)V
    //   8: aload_0
    //   9: iconst_2
    //   10: invokestatic 335	com/google/ads/interactivemedia/v3/internal/ago:a	()Ljava/lang/String;
    //   13: invokevirtual 333	com/google/ads/interactivemedia/v3/internal/agp:a	(ILjava/lang/String;)V
    //   16: invokestatic 293	com/google/ads/interactivemedia/v3/internal/ago:b	()Ljava/lang/Long;
    //   19: invokevirtual 299	java/lang/Long:longValue	()J
    //   22: lstore_2
    //   23: aload_0
    //   24: bipush 25
    //   26: lload_2
    //   27: invokevirtual 338	com/google/ads/interactivemedia/v3/internal/agp:a	(IJ)V
    //   30: getstatic 301	com/google/ads/interactivemedia/v3/internal/ago:s	J
    //   33: lstore 4
    //   35: lload 4
    //   37: lconst_0
    //   38: lcmp
    //   39: ifeq +22 -> 61
    //   42: aload_0
    //   43: bipush 17
    //   45: lload_2
    //   46: lload 4
    //   48: lsub
    //   49: invokevirtual 338	com/google/ads/interactivemedia/v3/internal/agp:a	(IJ)V
    //   52: aload_0
    //   53: bipush 23
    //   55: getstatic 301	com/google/ads/interactivemedia/v3/internal/ago:s	J
    //   58: invokevirtual 338	com/google/ads/interactivemedia/v3/internal/agp:a	(IJ)V
    //   61: aload_1
    //   62: invokestatic 340	com/google/ads/interactivemedia/v3/internal/ago:g	(Landroid/content/Context;)Ljava/util/ArrayList;
    //   65: astore 6
    //   67: aload_0
    //   68: bipush 31
    //   70: aload 6
    //   72: iconst_0
    //   73: invokevirtual 344	java/util/ArrayList:get	(I)Ljava/lang/Object;
    //   76: checkcast 295	java/lang/Long
    //   79: invokevirtual 299	java/lang/Long:longValue	()J
    //   82: invokevirtual 338	com/google/ads/interactivemedia/v3/internal/agp:a	(IJ)V
    //   85: aload_0
    //   86: bipush 32
    //   88: aload 6
    //   90: iconst_1
    //   91: invokevirtual 344	java/util/ArrayList:get	(I)Ljava/lang/Object;
    //   94: checkcast 295	java/lang/Long
    //   97: invokevirtual 299	java/lang/Long:longValue	()J
    //   100: invokevirtual 338	com/google/ads/interactivemedia/v3/internal/agp:a	(IJ)V
    //   103: aload_0
    //   104: bipush 33
    //   106: invokestatic 346	com/google/ads/interactivemedia/v3/internal/ago:d	()Ljava/lang/Long;
    //   109: invokevirtual 299	java/lang/Long:longValue	()J
    //   112: invokevirtual 338	com/google/ads/interactivemedia/v3/internal/agp:a	(IJ)V
    //   115: aload_0
    //   116: bipush 27
    //   118: aload_1
    //   119: aload_0
    //   120: getfield 349	com/google/ads/interactivemedia/v3/internal/agp:b	Lcom/google/ads/interactivemedia/v3/internal/agv;
    //   123: invokestatic 351	com/google/ads/interactivemedia/v3/internal/ago:a	(Landroid/content/Context;Lcom/google/ads/interactivemedia/v3/internal/agv;)Ljava/lang/String;
    //   126: invokevirtual 333	com/google/ads/interactivemedia/v3/internal/agp:a	(ILjava/lang/String;)V
    //   129: aload_0
    //   130: bipush 29
    //   132: aload_1
    //   133: aload_0
    //   134: getfield 349	com/google/ads/interactivemedia/v3/internal/agp:b	Lcom/google/ads/interactivemedia/v3/internal/agv;
    //   137: invokestatic 353	com/google/ads/interactivemedia/v3/internal/ago:b	(Landroid/content/Context;Lcom/google/ads/interactivemedia/v3/internal/agv;)Ljava/lang/String;
    //   140: invokevirtual 333	com/google/ads/interactivemedia/v3/internal/agp:a	(ILjava/lang/String;)V
    //   143: aload_1
    //   144: invokestatic 355	com/google/ads/interactivemedia/v3/internal/ago:h	(Landroid/content/Context;)[I
    //   147: astore 6
    //   149: aload_0
    //   150: iconst_5
    //   151: aload 6
    //   153: iconst_0
    //   154: iaload
    //   155: i2l
    //   156: invokevirtual 338	com/google/ads/interactivemedia/v3/internal/agp:a	(IJ)V
    //   159: aload_0
    //   160: bipush 6
    //   162: aload 6
    //   164: iconst_1
    //   165: iaload
    //   166: i2l
    //   167: invokevirtual 338	com/google/ads/interactivemedia/v3/internal/agp:a	(IJ)V
    //   170: aload_0
    //   171: bipush 12
    //   173: aload_1
    //   174: invokestatic 357	com/google/ads/interactivemedia/v3/internal/ago:i	(Landroid/content/Context;)I
    //   177: i2l
    //   178: invokevirtual 338	com/google/ads/interactivemedia/v3/internal/agp:a	(IJ)V
    //   181: aload_0
    //   182: iconst_3
    //   183: aload_1
    //   184: invokestatic 359	com/google/ads/interactivemedia/v3/internal/ago:j	(Landroid/content/Context;)I
    //   187: i2l
    //   188: invokevirtual 338	com/google/ads/interactivemedia/v3/internal/agp:a	(IJ)V
    //   191: aload_0
    //   192: bipush 34
    //   194: aload_1
    //   195: invokestatic 361	com/google/ads/interactivemedia/v3/internal/ago:e	(Landroid/content/Context;)Ljava/lang/String;
    //   198: invokevirtual 333	com/google/ads/interactivemedia/v3/internal/agp:a	(ILjava/lang/String;)V
    //   201: aload_0
    //   202: bipush 35
    //   204: aload_1
    //   205: invokestatic 363	com/google/ads/interactivemedia/v3/internal/ago:f	(Landroid/content/Context;)Ljava/lang/Long;
    //   208: invokevirtual 299	java/lang/Long:longValue	()J
    //   211: invokevirtual 338	com/google/ads/interactivemedia/v3/internal/agp:a	(IJ)V
    //   214: return
    //   215: astore 6
    //   217: goto -209 -> 8
    //   220: astore_1
    //   221: goto -7 -> 214
    //   224: astore 6
    //   226: goto -210 -> 16
    //   229: astore 6
    //   231: goto -170 -> 61
    //   234: astore 6
    //   236: goto -133 -> 103
    //   239: astore 6
    //   241: goto -126 -> 115
    //   244: astore 6
    //   246: goto -117 -> 129
    //   249: astore 6
    //   251: goto -108 -> 143
    //   254: astore 6
    //   256: goto -86 -> 170
    //   259: astore 6
    //   261: goto -80 -> 181
    //   264: astore 6
    //   266: goto -75 -> 191
    //   269: astore 6
    //   271: goto -70 -> 201
    // Local variable table:
    //   start	length	slot	name	signature
    //   0	274	0	this	ago
    //   0	274	1	paramContext	Context
    //   22	24	2	l1	long
    //   33	14	4	l2	long
    //   65	98	6	localObject	Object
    //   215	1	6	localagr1	agr
    //   224	1	6	localagr2	agr
    //   229	1	6	localagr3	agr
    //   234	1	6	localagr4	agr
    //   239	1	6	localagr5	agr
    //   244	1	6	localagr6	agr
    //   249	1	6	localagr7	agr
    //   254	1	6	localagr8	agr
    //   259	1	6	localagr9	agr
    //   264	1	6	localagr10	agr
    //   269	1	6	localagr11	agr
    // Exception table:
    //   from	to	target	type
    //   0	8	215	com/google/ads/interactivemedia/v3/internal/agr
    //   0	8	220	java/io/IOException
    //   8	16	220	java/io/IOException
    //   16	35	220	java/io/IOException
    //   42	61	220	java/io/IOException
    //   61	103	220	java/io/IOException
    //   103	115	220	java/io/IOException
    //   115	129	220	java/io/IOException
    //   129	143	220	java/io/IOException
    //   143	170	220	java/io/IOException
    //   170	181	220	java/io/IOException
    //   181	191	220	java/io/IOException
    //   191	201	220	java/io/IOException
    //   201	214	220	com/google/ads/interactivemedia/v3/internal/agr
    //   201	214	220	java/io/IOException
    //   8	16	224	com/google/ads/interactivemedia/v3/internal/agr
    //   16	35	229	com/google/ads/interactivemedia/v3/internal/agr
    //   42	61	229	com/google/ads/interactivemedia/v3/internal/agr
    //   61	103	234	com/google/ads/interactivemedia/v3/internal/agr
    //   103	115	239	com/google/ads/interactivemedia/v3/internal/agr
    //   115	129	244	com/google/ads/interactivemedia/v3/internal/agr
    //   129	143	249	com/google/ads/interactivemedia/v3/internal/agr
    //   143	170	254	com/google/ads/interactivemedia/v3/internal/agr
    //   170	181	259	com/google/ads/interactivemedia/v3/internal/agr
    //   181	191	264	com/google/ads/interactivemedia/v3/internal/agr
    //   191	201	269	com/google/ads/interactivemedia/v3/internal/agr
  }
  
  /* Error */
  public final void b(Context paramContext)
  {
    // Byte code:
    //   0: aload_0
    //   1: iconst_2
    //   2: invokestatic 335	com/google/ads/interactivemedia/v3/internal/ago:a	()Ljava/lang/String;
    //   5: invokevirtual 333	com/google/ads/interactivemedia/v3/internal/agp:a	(ILjava/lang/String;)V
    //   8: aload_0
    //   9: iconst_1
    //   10: invokestatic 330	com/google/ads/interactivemedia/v3/internal/ago:c	()Ljava/lang/String;
    //   13: invokevirtual 333	com/google/ads/interactivemedia/v3/internal/agp:a	(ILjava/lang/String;)V
    //   16: aload_0
    //   17: bipush 25
    //   19: invokestatic 293	com/google/ads/interactivemedia/v3/internal/ago:b	()Ljava/lang/Long;
    //   22: invokevirtual 299	java/lang/Long:longValue	()J
    //   25: invokevirtual 338	com/google/ads/interactivemedia/v3/internal/agp:a	(IJ)V
    //   28: aconst_null
    //   29: aload_0
    //   30: getfield 366	com/google/ads/interactivemedia/v3/internal/agp:a	Landroid/util/DisplayMetrics;
    //   33: invokestatic 368	com/google/ads/interactivemedia/v3/internal/ago:a	(Landroid/view/MotionEvent;Landroid/util/DisplayMetrics;)Ljava/util/ArrayList;
    //   36: astore_2
    //   37: aload_0
    //   38: bipush 14
    //   40: aload_2
    //   41: iconst_0
    //   42: invokevirtual 344	java/util/ArrayList:get	(I)Ljava/lang/Object;
    //   45: checkcast 295	java/lang/Long
    //   48: invokevirtual 299	java/lang/Long:longValue	()J
    //   51: invokevirtual 338	com/google/ads/interactivemedia/v3/internal/agp:a	(IJ)V
    //   54: aload_0
    //   55: bipush 15
    //   57: aload_2
    //   58: iconst_1
    //   59: invokevirtual 344	java/util/ArrayList:get	(I)Ljava/lang/Object;
    //   62: checkcast 295	java/lang/Long
    //   65: invokevirtual 299	java/lang/Long:longValue	()J
    //   68: invokevirtual 338	com/google/ads/interactivemedia/v3/internal/agp:a	(IJ)V
    //   71: aload_2
    //   72: invokevirtual 317	java/util/ArrayList:size	()I
    //   75: iconst_3
    //   76: if_icmplt +20 -> 96
    //   79: aload_0
    //   80: bipush 16
    //   82: aload_2
    //   83: iconst_2
    //   84: invokevirtual 344	java/util/ArrayList:get	(I)Ljava/lang/Object;
    //   87: checkcast 295	java/lang/Long
    //   90: invokevirtual 299	java/lang/Long:longValue	()J
    //   93: invokevirtual 338	com/google/ads/interactivemedia/v3/internal/agp:a	(IJ)V
    //   96: aload_0
    //   97: bipush 34
    //   99: aload_1
    //   100: invokestatic 361	com/google/ads/interactivemedia/v3/internal/ago:e	(Landroid/content/Context;)Ljava/lang/String;
    //   103: invokevirtual 333	com/google/ads/interactivemedia/v3/internal/agp:a	(ILjava/lang/String;)V
    //   106: aload_0
    //   107: bipush 35
    //   109: aload_1
    //   110: invokestatic 363	com/google/ads/interactivemedia/v3/internal/ago:f	(Landroid/content/Context;)Ljava/lang/Long;
    //   113: invokevirtual 299	java/lang/Long:longValue	()J
    //   116: invokevirtual 338	com/google/ads/interactivemedia/v3/internal/agp:a	(IJ)V
    //   119: return
    //   120: astore_2
    //   121: goto -113 -> 8
    //   124: astore_1
    //   125: goto -6 -> 119
    //   128: astore_2
    //   129: goto -113 -> 16
    //   132: astore_2
    //   133: goto -105 -> 28
    //   136: astore_2
    //   137: goto -41 -> 96
    //   140: astore_2
    //   141: goto -35 -> 106
    // Local variable table:
    //   start	length	slot	name	signature
    //   0	144	0	this	ago
    //   0	144	1	paramContext	Context
    //   36	47	2	localArrayList	ArrayList
    //   120	1	2	localagr1	agr
    //   128	1	2	localagr2	agr
    //   132	1	2	localagr3	agr
    //   136	1	2	localagr4	agr
    //   140	1	2	localagr5	agr
    // Exception table:
    //   from	to	target	type
    //   0	8	120	com/google/ads/interactivemedia/v3/internal/agr
    //   0	8	124	java/io/IOException
    //   8	16	124	java/io/IOException
    //   16	28	124	java/io/IOException
    //   28	96	124	java/io/IOException
    //   96	106	124	java/io/IOException
    //   106	119	124	com/google/ads/interactivemedia/v3/internal/agr
    //   106	119	124	java/io/IOException
    //   8	16	128	com/google/ads/interactivemedia/v3/internal/agr
    //   16	28	132	com/google/ads/interactivemedia/v3/internal/agr
    //   28	96	136	com/google/ads/interactivemedia/v3/internal/agr
    //   96	106	140	com/google/ads/interactivemedia/v3/internal/agr
  }
}

/* Location:
 * Qualified Name:     com.google.ads.interactivemedia.v3.internal.ago
 * Java Class Version: 6 (50.0)
 * JD-Core Version:    0.7.1
 */