package com.google.ads.interactivemedia.v3.internal;

import android.os.Handler;
import android.os.Handler.Callback;
import android.os.HandlerThread;
import android.os.Looper;
import android.os.Message;
import android.util.Log;
import android.util.Pair;
import java.util.ArrayList;

final class bo
  implements Handler.Callback, ax, ck, mr, ms, th
{
  private boolean A;
  private boolean B;
  private int C;
  private bu D;
  private long E;
  private int F;
  private final cj[] a;
  private final cm[] b;
  private final te c;
  private final tg d;
  private final ca e;
  private final tm f;
  private final vo g;
  private final HandlerThread h;
  private final Handler i;
  private final cw j;
  private final ct k;
  private final long l;
  private final boolean m;
  private final ay n;
  private final br o;
  private final ArrayList<bs> p;
  private final vh q;
  private final cb r;
  private cn s;
  private cd t;
  private mq u;
  private cj[] v;
  private boolean w;
  private boolean x;
  private boolean y;
  private int z;
  
  public bo(cj[] paramArrayOfcj, te paramte, tg paramtg, ca paramca, tm paramtm, boolean paramBoolean1, int paramInt, boolean paramBoolean2, Handler paramHandler, vh paramvh)
  {
    a = paramArrayOfcj;
    c = paramte;
    d = paramtg;
    e = paramca;
    f = paramtm;
    x = paramBoolean1;
    z = paramInt;
    A = paramBoolean2;
    i = paramHandler;
    q = paramvh;
    r = new cb();
    l = paramca.e();
    m = paramca.f();
    s = cn.b;
    t = cd.a(-9223372036854775807L, paramtg);
    o = new br((byte)0);
    b = new cm[paramArrayOfcj.length];
    for (paramInt = 0; paramInt < paramArrayOfcj.length; paramInt++)
    {
      paramArrayOfcj[paramInt].a(paramInt);
      b[paramInt] = paramArrayOfcj[paramInt].b();
    }
    n = new ay(this, paramvh);
    p = new ArrayList();
    v = new cj[0];
    j = new cw();
    k = new ct();
    paramte.a(this, paramtm);
    paramArrayOfcj = new HandlerThread("ExoPlayerImplInternal:Handler", -16);
    h = paramArrayOfcj;
    paramArrayOfcj.start();
    g = paramvh.a(paramArrayOfcj.getLooper(), this);
  }
  
  private final long a(mt parammt, long paramLong)
    throws ba
  {
    boolean bool;
    if (r.c() != r.d()) {
      bool = true;
    } else {
      bool = false;
    }
    return a(parammt, paramLong, bool);
  }
  
  private final long a(mt parammt, long paramLong, boolean paramBoolean)
    throws ba
  {
    e();
    y = false;
    a(2);
    bz localbz1 = r.c();
    for (bz localbz2 = localbz1; localbz2 != null; localbz2 = r.f()) {
      if ((parammt.equals(f.a)) && (d))
      {
        r.a(localbz2);
        break;
      }
    }
    if ((!paramBoolean) && (localbz1 == localbz2))
    {
      parammt = localbz1;
      if (localbz2 != null)
      {
        parammt = localbz1;
        if (localbz2.a() + paramLong >= 0L) {}
      }
    }
    else
    {
      parammt = v;
      int i1 = parammt.length;
      for (int i2 = 0; i2 < i1; i2++) {
        b(parammt[i2]);
      }
      v = new cj[0];
      localbz1 = null;
      parammt = localbz1;
      if (localbz2 != null)
      {
        localbz2.c(0L);
        parammt = localbz1;
      }
    }
    if (localbz2 != null)
    {
      a(parammt);
      long l1 = paramLong;
      if (e)
      {
        l1 = a.b(paramLong);
        a.a(l1 - l, m);
      }
      a(l1);
      k();
      paramLong = l1;
    }
    else
    {
      r.b(true);
      t = t.a(of.a, d);
      a(paramLong);
    }
    e(false);
    g.a(2);
    return paramLong;
  }
  
  private final Pair<Object, Long> a(bu parambu, boolean paramBoolean)
  {
    cr localcr1 = t.a;
    cr localcr2 = a;
    if (localcr1.a()) {
      return null;
    }
    cr localcr3 = localcr2;
    if (localcr2.a()) {
      localcr3 = localcr1;
    }
    try
    {
      parambu = localcr3.a(j, k, b, c);
      if (localcr1 == localcr3) {
        return parambu;
      }
      int i1 = localcr1.a(first);
      if (i1 != -1) {
        return parambu;
      }
      if ((paramBoolean) && (a(first, localcr3, localcr1) != null)) {
        return b(localcr1, ak, false).b, -9223372036854775807L);
      }
    }
    catch (IndexOutOfBoundsException parambu)
    {
      for (;;) {}
    }
    return null;
  }
  
  private final Object a(Object paramObject, cr paramcr1, cr paramcr2)
  {
    int i1 = paramcr1.a(paramObject);
    int i2 = paramcr1.c();
    int i3 = 0;
    int i4 = -1;
    while ((i3 < i2) && (i4 == -1))
    {
      i1 = paramcr1.a(i1, k, j, z, A);
      if (i1 == -1) {
        break;
      }
      i4 = paramcr2.a(paramcr1.a(i1));
      i3++;
    }
    if (i4 == -1) {
      return null;
    }
    return paramcr2.a(i4);
  }
  
  private final void a(int paramInt)
  {
    cd localcd = t;
    if (e != paramInt) {
      t = new cd(a, b, c, d, paramInt, f, g, h, i, j, k, l, m);
    }
  }
  
  private final void a(long paramLong)
    throws ba
  {
    Object localObject = r.c();
    if (localObject != null) {
      paramLong += ((bz)localObject).a();
    }
    E = paramLong;
    n.a(paramLong);
    localObject = v;
    int i1 = localObject.length;
    for (int i2 = 0; i2 < i1; i2++) {
      localObject[i2].a(E);
    }
    for (localObject = r.c(); localObject != null; localObject = ((bz)localObject).f()) {
      for (sy localsy : hc.a()) {
        if (localsy != null) {
          localsy.j();
        }
      }
    }
  }
  
  private final void a(long paramLong1, long paramLong2)
  {
    g.b(2);
    g.a(2, paramLong1 + paramLong2);
  }
  
  private final void a(bz parambz)
    throws ba
  {
    bz localbz = r.c();
    if ((localbz != null) && (parambz != localbz))
    {
      boolean[] arrayOfBoolean = new boolean[a.length];
      int i1 = 0;
      int i4;
      for (int i2 = i1;; i2 = i4)
      {
        Object localObject = a;
        if (i1 >= localObject.length) {
          break;
        }
        localObject = localObject[i1];
        int i3;
        if (((cj)localObject).f() != 0) {
          i3 = 1;
        } else {
          i3 = 0;
        }
        arrayOfBoolean[i1] = i3;
        i4 = i2;
        if (localbz.h().a(i1)) {
          i4 = i2 + 1;
        }
        if ((arrayOfBoolean[i1] != 0) && ((!localbz.h().a(i1)) || ((((cj)localObject).l()) && (((cj)localObject).h() == c[i1])))) {
          b((cj)localObject);
        }
        i1++;
      }
      t = t.a(localbz.g(), localbz.h());
      a(arrayOfBoolean, i2);
    }
  }
  
  private final void a(cg paramcg, boolean paramBoolean)
  {
    g.a(17, paramBoolean, 0, paramcg).sendToTarget();
  }
  
  private static void a(cj paramcj)
    throws ba
  {
    if (paramcj.f() == 2) {
      paramcj.p();
    }
  }
  
  private final void a(of paramof, tg paramtg)
  {
    e.a(a, c);
  }
  
  private final void a(boolean paramBoolean1, boolean paramBoolean2, boolean paramBoolean3)
  {
    if ((!paramBoolean1) && (B)) {
      paramBoolean1 = false;
    } else {
      paramBoolean1 = true;
    }
    a(paramBoolean1, true, paramBoolean2, paramBoolean2, paramBoolean2);
    o.a(C + paramBoolean3);
    C = 0;
    e.b();
    a(1);
  }
  
  private final void a(boolean paramBoolean1, boolean paramBoolean2, boolean paramBoolean3, boolean paramBoolean4, boolean paramBoolean5)
  {
    g.b(2);
    y = false;
    n.b();
    E = 0L;
    for (cj localcj : v)
    {
      try
      {
        b(localcj);
      }
      catch (RuntimeException localRuntimeException2) {}catch (ba localba1) {}
      vr.b("ExoPlayerImplInternal", "Disable failed.", localba1);
    }
    if (paramBoolean1) {
      for (??? : a) {
        try
        {
          ???.r();
        }
        catch (RuntimeException localRuntimeException1)
        {
          vr.b("ExoPlayerImplInternal", "Reset failed.", localRuntimeException1);
        }
      }
    }
    v = new cj[0];
    long l1;
    long l2;
    if (paramBoolean3)
    {
      D = null;
    }
    else if (paramBoolean4)
    {
      if ((D == null) && (!t.a.a()))
      {
        ??? = t;
        a.a(b.a, k);
        l1 = t.m;
        l2 = k.b();
        D = new bu(cr.a, k.b, l2 + l1);
      }
      paramBoolean1 = true;
      break label270;
    }
    paramBoolean1 = paramBoolean3;
    label270:
    r.b(paramBoolean4 ^ true);
    c(false);
    Object localObject1;
    if (paramBoolean4)
    {
      r.a(cr.a);
      localObject1 = p;
      ??? = ((ArrayList)localObject1).size();
      ??? = 0;
      while (??? < ???)
      {
        ??? = ((ArrayList)localObject1).get(???);
        ???++;
        a.a(false);
      }
      p.clear();
      F = 0;
    }
    if (paramBoolean1) {
      ??? = t.a(A, j, k);
    } else {
      ??? = t.b;
    }
    if (paramBoolean1) {
      l2 = -9223372036854775807L;
    } else {
      l2 = t.m;
    }
    if (paramBoolean1) {
      l1 = -9223372036854775807L;
    } else {
      l1 = t.d;
    }
    if (paramBoolean4) {
      localObject1 = cr.a;
    } else {
      localObject1 = t.a;
    }
    Object localObject3 = t;
    ??? = e;
    ba localba2;
    if (paramBoolean5) {
      localba2 = null;
    } else {
      localba2 = f;
    }
    of localof;
    if (paramBoolean4) {
      localof = of.a;
    } else {
      localof = h;
    }
    if (paramBoolean4) {
      localObject3 = d;
    } else {
      localObject3 = i;
    }
    t = new cd((cr)localObject1, (mt)???, l2, l1, ???, localba2, false, localof, (tg)localObject3, (mt)???, l2, 0L, l2);
    if (paramBoolean2)
    {
      ??? = u;
      if (??? != null)
      {
        ((mq)???).c(this);
        u = null;
      }
    }
  }
  
  private final void a(boolean[] paramArrayOfBoolean, int paramInt)
    throws ba
  {
    v = new cj[paramInt];
    tg localtg = r.c().h();
    for (paramInt = 0; paramInt < a.length; paramInt++) {
      if (!localtg.a(paramInt)) {
        a[paramInt].r();
      }
    }
    int i1 = 0;
    int i2;
    for (paramInt = i1; i1 < a.length; paramInt = i2)
    {
      i2 = paramInt;
      if (localtg.a(i1))
      {
        int i3 = paramArrayOfBoolean[i1];
        bz localbz = r.c();
        cj localcj = a[i1];
        v[paramInt] = localcj;
        if (localcj.f() == 0)
        {
          Object localObject = localbz.h();
          cl localcl = b[i1];
          localObject = a(c.a(i1));
          if ((x) && (t.e == 3)) {
            i2 = 1;
          } else {
            i2 = 0;
          }
          if ((i3 == 0) && (i2 != 0)) {
            i3 = 1;
          } else {
            i3 = 0;
          }
          localcj.a(localcl, (bw[])localObject, c[i1], E, i3, localbz.a());
          n.a(localcj);
          if (i2 != 0) {
            localcj.g();
          }
        }
        i2 = paramInt + 1;
      }
      i1++;
    }
  }
  
  private final boolean a(bs parambs)
  {
    Object localObject = d;
    int i1;
    if (localObject == null)
    {
      localObject = a(new bu(a.a(), a.g(), av.b(a.f())), false);
      if (localObject == null) {
        return false;
      }
      i1 = t.a.a(first);
      long l1 = ((Long)second).longValue();
      localObject = first;
      b = i1;
      c = l1;
      d = localObject;
    }
    else
    {
      i1 = t.a.a(localObject);
      if (i1 == -1) {
        return false;
      }
      b = i1;
    }
    return true;
  }
  
  private static bw[] a(sy paramsy)
  {
    int i1 = 0;
    int i2;
    if (paramsy != null) {
      i2 = paramsy.g();
    } else {
      i2 = 0;
    }
    bw[] arrayOfbw = new bw[i2];
    while (i1 < i2)
    {
      arrayOfbw[i1] = paramsy.a(i1);
      i1++;
    }
    return arrayOfbw;
  }
  
  private final long b(long paramLong)
  {
    bz localbz = r.b();
    if (localbz == null) {
      return 0L;
    }
    return Math.max(0L, paramLong - (E - localbz.a()));
  }
  
  private final Pair<Object, Long> b(cr paramcr, int paramInt, long paramLong)
  {
    return paramcr.a(j, k, paramInt, -9223372036854775807L);
  }
  
  private final void b(cj paramcj)
    throws ba
  {
    n.b(paramcj);
    a(paramcj);
    paramcj.q();
  }
  
  private final void c()
  {
    if (o.a(t))
    {
      Handler localHandler = i;
      int i1 = br.a(o);
      int i2;
      if (br.b(o)) {
        i2 = br.c(o);
      } else {
        i2 = -1;
      }
      localHandler.obtainMessage(0, i1, i2, t).sendToTarget();
      o.b(t);
    }
  }
  
  private final void c(ch paramch)
    throws ba
  {
    if (paramch.e().getLooper() == g.a())
    {
      d(paramch);
      int i1 = t.e;
      if ((i1 == 3) || (i1 == 2)) {
        g.a(2);
      }
    }
    else
    {
      g.a(16, paramch).sendToTarget();
    }
  }
  
  private final void c(boolean paramBoolean)
  {
    cd localcd = t;
    if (g != paramBoolean) {
      t = new cd(a, b, c, d, e, f, paramBoolean, h, i, j, k, l, m);
    }
  }
  
  private final void d()
    throws ba
  {
    int i1 = 0;
    y = false;
    n.a();
    cj[] arrayOfcj = v;
    int i2 = arrayOfcj.length;
    while (i1 < i2)
    {
      arrayOfcj[i1].g();
      i1++;
    }
  }
  
  private static void d(ch paramch)
    throws ba
  {
    if (paramch.j()) {
      return;
    }
    try
    {
      paramch.b().a(paramch.c(), paramch.d());
      return;
    }
    finally
    {
      paramch.a(true);
    }
  }
  
  private final void d(boolean paramBoolean)
    throws ba
  {
    mt localmt = r.c().f.a;
    long l1 = a(localmt, t.m, true);
    if (l1 != t.m)
    {
      cd localcd = t;
      t = localcd.a(localmt, l1, d, l());
      if (paramBoolean) {
        o.b(4);
      }
    }
  }
  
  private final void e()
    throws ba
  {
    n.b();
    cj[] arrayOfcj = v;
    int i1 = arrayOfcj.length;
    for (int i2 = 0; i2 < i1; i2++) {
      a(arrayOfcj[i2]);
    }
  }
  
  private final void e(boolean paramBoolean)
  {
    Object localObject1 = this;
    bz localbz = r.b();
    if (localbz == null) {
      localObject2 = t.b;
    } else {
      localObject2 = f.a;
    }
    boolean bool = t.j.equals(localObject2) ^ true;
    if (bool)
    {
      localObject1 = t;
      t = new cd(a, b, c, d, e, f, g, h, i, (mt)localObject2, k, l, m);
    }
    Object localObject2 = this;
    localObject1 = t;
    long l1;
    if (localbz == null) {
      l1 = m;
    } else {
      l1 = localbz.d();
    }
    k = l1;
    t.l = l();
    if (((bool) || (paramBoolean)) && (localbz != null) && (d)) {
      ((bo)localObject2).a(localbz.g(), localbz.h());
    }
  }
  
  /* Error */
  private final void f()
    throws ba
  {
    // Byte code:
    //   0: aload_0
    //   1: getfield 102	com/google/ads/interactivemedia/v3/internal/bo:r	Lcom/google/ads/interactivemedia/v3/internal/cb;
    //   4: invokevirtual 209	com/google/ads/interactivemedia/v3/internal/cb:c	()Lcom/google/ads/interactivemedia/v3/internal/bz;
    //   7: astore_1
    //   8: aload_1
    //   9: ifnonnull +4 -> 13
    //   12: return
    //   13: aload_1
    //   14: getfield 238	com/google/ads/interactivemedia/v3/internal/bz:d	Z
    //   17: ifeq +16 -> 33
    //   20: aload_1
    //   21: getfield 259	com/google/ads/interactivemedia/v3/internal/bz:a	Lcom/google/ads/interactivemedia/v3/internal/mo;
    //   24: invokeinterface 617 1 0
    //   29: lstore_2
    //   30: goto +7 -> 37
    //   33: ldc2_w 121
    //   36: lstore_2
    //   37: lload_2
    //   38: ldc2_w 121
    //   41: lcmp
    //   42: ifeq +61 -> 103
    //   45: aload_0
    //   46: lload_2
    //   47: invokespecial 269	com/google/ads/interactivemedia/v3/internal/bo:a	(J)V
    //   50: lload_2
    //   51: aload_0
    //   52: getfield 129	com/google/ads/interactivemedia/v3/internal/bo:t	Lcom/google/ads/interactivemedia/v3/internal/cd;
    //   55: getfield 362	com/google/ads/interactivemedia/v3/internal/cd:m	J
    //   58: lcmp
    //   59: ifeq +627 -> 686
    //   62: aload_0
    //   63: getfield 129	com/google/ads/interactivemedia/v3/internal/bo:t	Lcom/google/ads/interactivemedia/v3/internal/cd;
    //   66: astore 4
    //   68: aload_0
    //   69: aload 4
    //   71: aload 4
    //   73: getfield 343	com/google/ads/interactivemedia/v3/internal/cd:b	Lcom/google/ads/interactivemedia/v3/internal/mt;
    //   76: lload_2
    //   77: aload 4
    //   79: getfield 346	com/google/ads/interactivemedia/v3/internal/cd:d	J
    //   82: aload_0
    //   83: invokespecial 607	com/google/ads/interactivemedia/v3/internal/bo:l	()J
    //   86: invokevirtual 610	com/google/ads/interactivemedia/v3/internal/cd:a	(Lcom/google/ads/interactivemedia/v3/internal/mt;JJJ)Lcom/google/ads/interactivemedia/v3/internal/cd;
    //   89: putfield 129	com/google/ads/interactivemedia/v3/internal/bo:t	Lcom/google/ads/interactivemedia/v3/internal/cd;
    //   92: aload_0
    //   93: getfield 136	com/google/ads/interactivemedia/v3/internal/bo:o	Lcom/google/ads/interactivemedia/v3/internal/br;
    //   96: iconst_4
    //   97: invokevirtual 611	com/google/ads/interactivemedia/v3/internal/br:b	(I)V
    //   100: goto +586 -> 686
    //   103: aload_0
    //   104: getfield 155	com/google/ads/interactivemedia/v3/internal/bo:n	Lcom/google/ads/interactivemedia/v3/internal/ay;
    //   107: astore 4
    //   109: aload_1
    //   110: aload_0
    //   111: getfield 102	com/google/ads/interactivemedia/v3/internal/bo:r	Lcom/google/ads/interactivemedia/v3/internal/cb;
    //   114: invokevirtual 211	com/google/ads/interactivemedia/v3/internal/cb:d	()Lcom/google/ads/interactivemedia/v3/internal/bz;
    //   117: if_acmpeq +9 -> 126
    //   120: iconst_1
    //   121: istore 5
    //   123: goto +6 -> 129
    //   126: iconst_0
    //   127: istore 5
    //   129: aload 4
    //   131: iload 5
    //   133: invokevirtual 620	com/google/ads/interactivemedia/v3/internal/ay:a	(Z)J
    //   136: lstore_2
    //   137: aload_0
    //   138: lload_2
    //   139: putfield 367	com/google/ads/interactivemedia/v3/internal/bo:E	J
    //   142: lload_2
    //   143: aload_1
    //   144: invokevirtual 245	com/google/ads/interactivemedia/v3/internal/bz:a	()J
    //   147: lsub
    //   148: lstore 6
    //   150: aload_0
    //   151: getfield 129	com/google/ads/interactivemedia/v3/internal/bo:t	Lcom/google/ads/interactivemedia/v3/internal/cd;
    //   154: getfield 362	com/google/ads/interactivemedia/v3/internal/cd:m	J
    //   157: lstore 8
    //   159: aload_0
    //   160: getfield 160	com/google/ads/interactivemedia/v3/internal/bo:p	Ljava/util/ArrayList;
    //   163: invokevirtual 623	java/util/ArrayList:isEmpty	()Z
    //   166: ifne +511 -> 677
    //   169: aload_0
    //   170: getfield 129	com/google/ads/interactivemedia/v3/internal/bo:t	Lcom/google/ads/interactivemedia/v3/internal/cd;
    //   173: getfield 343	com/google/ads/interactivemedia/v3/internal/cd:b	Lcom/google/ads/interactivemedia/v3/internal/mt;
    //   176: invokevirtual 624	com/google/ads/interactivemedia/v3/internal/mt:a	()Z
    //   179: ifeq +6 -> 185
    //   182: goto +495 -> 677
    //   185: aload_0
    //   186: getfield 129	com/google/ads/interactivemedia/v3/internal/bo:t	Lcom/google/ads/interactivemedia/v3/internal/cd;
    //   189: astore 4
    //   191: lload 8
    //   193: lstore_2
    //   194: aload 4
    //   196: getfield 344	com/google/ads/interactivemedia/v3/internal/cd:c	J
    //   199: lload 8
    //   201: lcmp
    //   202: ifne +8 -> 210
    //   205: lload 8
    //   207: lconst_1
    //   208: lsub
    //   209: lstore_2
    //   210: aload 4
    //   212: getfield 295	com/google/ads/interactivemedia/v3/internal/cd:a	Lcom/google/ads/interactivemedia/v3/internal/cr;
    //   215: aload 4
    //   217: getfield 343	com/google/ads/interactivemedia/v3/internal/cd:b	Lcom/google/ads/interactivemedia/v3/internal/mt;
    //   220: getfield 456	com/google/ads/interactivemedia/v3/internal/mt:a	Ljava/lang/Object;
    //   223: invokevirtual 318	com/google/ads/interactivemedia/v3/internal/cr:a	(Ljava/lang/Object;)I
    //   226: istore 10
    //   228: aload_0
    //   229: getfield 490	com/google/ads/interactivemedia/v3/internal/bo:F	I
    //   232: istore 11
    //   234: lload_2
    //   235: lstore 8
    //   237: iload 11
    //   239: ifle +22 -> 261
    //   242: aload_0
    //   243: getfield 160	com/google/ads/interactivemedia/v3/internal/bo:p	Ljava/util/ArrayList;
    //   246: iload 11
    //   248: iconst_1
    //   249: isub
    //   250: invokevirtual 476	java/util/ArrayList:get	(I)Ljava/lang/Object;
    //   253: checkcast 478	com/google/ads/interactivemedia/v3/internal/bs
    //   256: astore 4
    //   258: goto +9 -> 267
    //   261: aconst_null
    //   262: astore 4
    //   264: lload 8
    //   266: lstore_2
    //   267: aload 4
    //   269: ifnull +75 -> 344
    //   272: aload 4
    //   274: getfield 540	com/google/ads/interactivemedia/v3/internal/bs:b	I
    //   277: istore 11
    //   279: iload 11
    //   281: iload 10
    //   283: if_icmpgt +20 -> 303
    //   286: iload 11
    //   288: iload 10
    //   290: if_icmpne +54 -> 344
    //   293: aload 4
    //   295: getfield 541	com/google/ads/interactivemedia/v3/internal/bs:c	J
    //   298: lload_2
    //   299: lcmp
    //   300: ifle +44 -> 344
    //   303: aload_0
    //   304: getfield 490	com/google/ads/interactivemedia/v3/internal/bo:F	I
    //   307: iconst_1
    //   308: isub
    //   309: istore 11
    //   311: aload_0
    //   312: iload 11
    //   314: putfield 490	com/google/ads/interactivemedia/v3/internal/bo:F	I
    //   317: lload_2
    //   318: lstore 8
    //   320: iload 11
    //   322: ifle -61 -> 261
    //   325: aload_0
    //   326: getfield 160	com/google/ads/interactivemedia/v3/internal/bo:p	Ljava/util/ArrayList;
    //   329: iload 11
    //   331: iconst_1
    //   332: isub
    //   333: invokevirtual 476	java/util/ArrayList:get	(I)Ljava/lang/Object;
    //   336: checkcast 478	com/google/ads/interactivemedia/v3/internal/bs
    //   339: astore 4
    //   341: goto -74 -> 267
    //   344: lload_2
    //   345: lstore 8
    //   347: aload_0
    //   348: getfield 490	com/google/ads/interactivemedia/v3/internal/bo:F	I
    //   351: aload_0
    //   352: getfield 160	com/google/ads/interactivemedia/v3/internal/bo:p	Ljava/util/ArrayList;
    //   355: invokevirtual 473	java/util/ArrayList:size	()I
    //   358: if_icmpge +22 -> 380
    //   361: aload_0
    //   362: getfield 160	com/google/ads/interactivemedia/v3/internal/bo:p	Ljava/util/ArrayList;
    //   365: aload_0
    //   366: getfield 490	com/google/ads/interactivemedia/v3/internal/bo:F	I
    //   369: invokevirtual 476	java/util/ArrayList:get	(I)Ljava/lang/Object;
    //   372: checkcast 478	com/google/ads/interactivemedia/v3/internal/bs
    //   375: astore 4
    //   377: goto +9 -> 386
    //   380: aconst_null
    //   381: astore 4
    //   383: lload 8
    //   385: lstore_2
    //   386: aload 4
    //   388: astore_1
    //   389: aload 4
    //   391: ifnull +99 -> 490
    //   394: aload 4
    //   396: astore_1
    //   397: aload 4
    //   399: getfield 519	com/google/ads/interactivemedia/v3/internal/bs:d	Ljava/lang/Object;
    //   402: ifnull +88 -> 490
    //   405: aload 4
    //   407: getfield 540	com/google/ads/interactivemedia/v3/internal/bs:b	I
    //   410: istore 11
    //   412: iload 11
    //   414: iload 10
    //   416: if_icmplt +26 -> 442
    //   419: aload 4
    //   421: astore_1
    //   422: iload 11
    //   424: iload 10
    //   426: if_icmpne +64 -> 490
    //   429: aload 4
    //   431: astore_1
    //   432: aload 4
    //   434: getfield 541	com/google/ads/interactivemedia/v3/internal/bs:c	J
    //   437: lload_2
    //   438: lcmp
    //   439: ifgt +51 -> 490
    //   442: aload_0
    //   443: getfield 490	com/google/ads/interactivemedia/v3/internal/bo:F	I
    //   446: iconst_1
    //   447: iadd
    //   448: istore 11
    //   450: aload_0
    //   451: iload 11
    //   453: putfield 490	com/google/ads/interactivemedia/v3/internal/bo:F	I
    //   456: lload_2
    //   457: lstore 8
    //   459: iload 11
    //   461: aload_0
    //   462: getfield 160	com/google/ads/interactivemedia/v3/internal/bo:p	Ljava/util/ArrayList;
    //   465: invokevirtual 473	java/util/ArrayList:size	()I
    //   468: if_icmpge -88 -> 380
    //   471: aload_0
    //   472: getfield 160	com/google/ads/interactivemedia/v3/internal/bo:p	Ljava/util/ArrayList;
    //   475: aload_0
    //   476: getfield 490	com/google/ads/interactivemedia/v3/internal/bo:F	I
    //   479: invokevirtual 476	java/util/ArrayList:get	(I)Ljava/lang/Object;
    //   482: checkcast 478	com/google/ads/interactivemedia/v3/internal/bs
    //   485: astore 4
    //   487: goto -101 -> 386
    //   490: aload_1
    //   491: ifnull +186 -> 677
    //   494: aload_1
    //   495: getfield 519	com/google/ads/interactivemedia/v3/internal/bs:d	Ljava/lang/Object;
    //   498: ifnull +179 -> 677
    //   501: aload_1
    //   502: getfield 540	com/google/ads/interactivemedia/v3/internal/bs:b	I
    //   505: iload 10
    //   507: if_icmpne +170 -> 677
    //   510: aload_1
    //   511: getfield 541	com/google/ads/interactivemedia/v3/internal/bs:c	J
    //   514: lstore 8
    //   516: lload 8
    //   518: lload_2
    //   519: lcmp
    //   520: ifle +157 -> 677
    //   523: lload 8
    //   525: lload 6
    //   527: lcmp
    //   528: ifgt +149 -> 677
    //   531: aload_0
    //   532: aload_1
    //   533: getfield 481	com/google/ads/interactivemedia/v3/internal/bs:a	Lcom/google/ads/interactivemedia/v3/internal/ch;
    //   536: invokespecial 626	com/google/ads/interactivemedia/v3/internal/bo:c	(Lcom/google/ads/interactivemedia/v3/internal/ch;)V
    //   539: aload_1
    //   540: getfield 481	com/google/ads/interactivemedia/v3/internal/bs:a	Lcom/google/ads/interactivemedia/v3/internal/ch;
    //   543: invokevirtual 628	com/google/ads/interactivemedia/v3/internal/ch:h	()Z
    //   546: ifne +29 -> 575
    //   549: aload_1
    //   550: getfield 481	com/google/ads/interactivemedia/v3/internal/bs:a	Lcom/google/ads/interactivemedia/v3/internal/ch;
    //   553: invokevirtual 595	com/google/ads/interactivemedia/v3/internal/ch:j	()Z
    //   556: ifeq +6 -> 562
    //   559: goto +16 -> 575
    //   562: aload_0
    //   563: aload_0
    //   564: getfield 490	com/google/ads/interactivemedia/v3/internal/bo:F	I
    //   567: iconst_1
    //   568: iadd
    //   569: putfield 490	com/google/ads/interactivemedia/v3/internal/bo:F	I
    //   572: goto +15 -> 587
    //   575: aload_0
    //   576: getfield 160	com/google/ads/interactivemedia/v3/internal/bo:p	Ljava/util/ArrayList;
    //   579: aload_0
    //   580: getfield 490	com/google/ads/interactivemedia/v3/internal/bo:F	I
    //   583: invokevirtual 631	java/util/ArrayList:remove	(I)Ljava/lang/Object;
    //   586: pop
    //   587: aload_0
    //   588: getfield 490	com/google/ads/interactivemedia/v3/internal/bo:F	I
    //   591: aload_0
    //   592: getfield 160	com/google/ads/interactivemedia/v3/internal/bo:p	Ljava/util/ArrayList;
    //   595: invokevirtual 473	java/util/ArrayList:size	()I
    //   598: if_icmpge +21 -> 619
    //   601: aload_0
    //   602: getfield 160	com/google/ads/interactivemedia/v3/internal/bo:p	Ljava/util/ArrayList;
    //   605: aload_0
    //   606: getfield 490	com/google/ads/interactivemedia/v3/internal/bo:F	I
    //   609: invokevirtual 476	java/util/ArrayList:get	(I)Ljava/lang/Object;
    //   612: checkcast 478	com/google/ads/interactivemedia/v3/internal/bs
    //   615: astore_1
    //   616: goto -126 -> 490
    //   619: aconst_null
    //   620: astore_1
    //   621: goto -131 -> 490
    //   624: astore 4
    //   626: aload_1
    //   627: getfield 481	com/google/ads/interactivemedia/v3/internal/bs:a	Lcom/google/ads/interactivemedia/v3/internal/ch;
    //   630: invokevirtual 628	com/google/ads/interactivemedia/v3/internal/ch:h	()Z
    //   633: ifne +29 -> 662
    //   636: aload_1
    //   637: getfield 481	com/google/ads/interactivemedia/v3/internal/bs:a	Lcom/google/ads/interactivemedia/v3/internal/ch;
    //   640: invokevirtual 595	com/google/ads/interactivemedia/v3/internal/ch:j	()Z
    //   643: ifeq +6 -> 649
    //   646: goto +16 -> 662
    //   649: aload_0
    //   650: aload_0
    //   651: getfield 490	com/google/ads/interactivemedia/v3/internal/bo:F	I
    //   654: iconst_1
    //   655: iadd
    //   656: putfield 490	com/google/ads/interactivemedia/v3/internal/bo:F	I
    //   659: goto +15 -> 674
    //   662: aload_0
    //   663: getfield 160	com/google/ads/interactivemedia/v3/internal/bo:p	Ljava/util/ArrayList;
    //   666: aload_0
    //   667: getfield 490	com/google/ads/interactivemedia/v3/internal/bo:F	I
    //   670: invokevirtual 631	java/util/ArrayList:remove	(I)Ljava/lang/Object;
    //   673: pop
    //   674: aload 4
    //   676: athrow
    //   677: aload_0
    //   678: getfield 129	com/google/ads/interactivemedia/v3/internal/bo:t	Lcom/google/ads/interactivemedia/v3/internal/cd;
    //   681: lload 6
    //   683: putfield 362	com/google/ads/interactivemedia/v3/internal/cd:m	J
    //   686: aload_0
    //   687: getfield 102	com/google/ads/interactivemedia/v3/internal/bo:r	Lcom/google/ads/interactivemedia/v3/internal/cb;
    //   690: invokevirtual 549	com/google/ads/interactivemedia/v3/internal/cb:b	()Lcom/google/ads/interactivemedia/v3/internal/bz;
    //   693: astore 4
    //   695: aload_0
    //   696: getfield 129	com/google/ads/interactivemedia/v3/internal/bo:t	Lcom/google/ads/interactivemedia/v3/internal/cd;
    //   699: aload 4
    //   701: invokevirtual 613	com/google/ads/interactivemedia/v3/internal/bz:d	()J
    //   704: putfield 359	com/google/ads/interactivemedia/v3/internal/cd:k	J
    //   707: aload_0
    //   708: getfield 129	com/google/ads/interactivemedia/v3/internal/bo:t	Lcom/google/ads/interactivemedia/v3/internal/cd;
    //   711: aload_0
    //   712: invokespecial 607	com/google/ads/interactivemedia/v3/internal/bo:l	()J
    //   715: putfield 360	com/google/ads/interactivemedia/v3/internal/cd:l	J
    //   718: return
    // Local variable table:
    //   start	length	slot	name	signature
    //   0	719	0	this	bo
    //   7	630	1	localObject1	Object
    //   29	490	2	l1	long
    //   66	420	4	localObject2	Object
    //   624	51	4	localObject3	Object
    //   693	7	4	localbz	bz
    //   121	11	5	bool	boolean
    //   148	534	6	l2	long
    //   157	367	8	l3	long
    //   226	282	10	i1	int
    //   232	237	11	i2	int
    // Exception table:
    //   from	to	target	type
    //   531	539	624	finally
  }
  
  private final boolean g()
  {
    bz localbz = r.c();
    long l1 = f.e;
    return (d) && ((l1 == -9223372036854775807L) || (t.m < l1));
  }
  
  private final void h()
  {
    a(4);
    a(false, false, true, false, true);
  }
  
  private final boolean i()
  {
    bz localbz = r.d();
    if (!d) {
      return false;
    }
    for (int i1 = 0;; i1++)
    {
      Object localObject1 = a;
      if (i1 >= localObject1.length) {
        break label78;
      }
      Object localObject2 = localObject1[i1];
      localObject1 = c[i1];
      if ((((cj)localObject2).h() != localObject1) || ((localObject1 != null) && (!((cj)localObject2).i()))) {
        break;
      }
    }
    return false;
    label78:
    return true;
  }
  
  private final void j()
  {
    for (cj localcj : a) {
      if (localcj.h() != null) {
        localcj.k();
      }
    }
  }
  
  private final void k()
  {
    bz localbz = r.b();
    if (!d) {
      l1 = 0L;
    } else {
      l1 = a.e();
    }
    if (l1 == Long.MIN_VALUE)
    {
      c(false);
      return;
    }
    long l1 = b(l1);
    boolean bool = e.a(l1, n.d().b);
    c(bool);
    if (bool) {
      localbz.e(E);
    }
  }
  
  private final long l()
  {
    return b(t.k);
  }
  
  public final void a()
  {
    try
    {
      boolean bool = w;
      if (bool) {
        return;
      }
      g.a(7);
      int i1 = 0;
      for (;;)
      {
        bool = w;
        if (bool) {
          break;
        }
        try
        {
          wait();
        }
        catch (InterruptedException localInterruptedException)
        {
          i1 = 1;
        }
      }
      if (i1 != 0) {
        Thread.currentThread().interrupt();
      }
      return;
    }
    finally {}
  }
  
  public final void a(cg paramcg)
  {
    a(paramcg, false);
  }
  
  public final void a(ch paramch)
  {
    try
    {
      if (w)
      {
        Log.w("ExoPlayerImplInternal", "Ignoring messages sent after release.");
        paramch.a(false);
        return;
      }
      g.a(15, paramch).sendToTarget();
      return;
    }
    finally {}
  }
  
  public final void a(cr paramcr, int paramInt, long paramLong)
  {
    g.a(3, new bu(paramcr, paramInt, paramLong)).sendToTarget();
  }
  
  public final void a(mo parammo)
  {
    g.a(9, parammo).sendToTarget();
  }
  
  public final void a(mq parammq, cr paramcr)
  {
    g.a(8, new bp(parammq, paramcr)).sendToTarget();
  }
  
  public final void a(mq parammq, boolean paramBoolean1, boolean paramBoolean2)
  {
    g.a(0, paramBoolean1, paramBoolean2, parammq).sendToTarget();
  }
  
  public final void a(boolean paramBoolean)
  {
    g.a(1, paramBoolean, 0).sendToTarget();
  }
  
  public final Looper b()
  {
    return h.getLooper();
  }
  
  public final void b(boolean paramBoolean)
  {
    g.a(6, paramBoolean, 0).sendToTarget();
  }
  
  /* Error */
  public final boolean handleMessage(Message paramMessage)
  {
    // Byte code:
    //   0: aload_0
    //   1: astore_2
    //   2: aload_1
    //   3: getfield 701	android/os/Message:what	I
    //   6: istore_3
    //   7: iload_3
    //   8: tableswitch	default:+88->96, 0:+4410->4418, 1:+4312->4320, 2:+2829->2837, 3:+2372->2380, 4:+2341->2349, 5:+2327->2335, 6:+2298->2306, 7:+2249->2257, 8:+1266->1274, 9:+1172->1180, 10:+1135->1143, 11:+610->618, 12:+576->584, 13:+529->537, 14:+415->423, 15:+298->306, 16:+261->269, 17:+90->98
    //   96: iconst_0
    //   97: ireturn
    //   98: aload_1
    //   99: getfield 704	android/os/Message:obj	Ljava/lang/Object;
    //   102: checkcast 645	com/google/ads/interactivemedia/v3/internal/cg
    //   105: astore 4
    //   107: aload_1
    //   108: getfield 707	android/os/Message:arg1	I
    //   111: ifeq +8 -> 119
    //   114: iconst_1
    //   115: istore_3
    //   116: goto +5 -> 121
    //   119: iconst_0
    //   120: istore_3
    //   121: aload_2
    //   122: getfield 95	com/google/ads/interactivemedia/v3/internal/bo:i	Landroid/os/Handler;
    //   125: astore_1
    //   126: iload_3
    //   127: ifeq +8 -> 135
    //   130: iconst_1
    //   131: istore_3
    //   132: goto +5 -> 137
    //   135: iconst_0
    //   136: istore_3
    //   137: aload_1
    //   138: iconst_1
    //   139: iload_3
    //   140: iconst_0
    //   141: aload 4
    //   143: invokevirtual 576	android/os/Handler:obtainMessage	(IIILjava/lang/Object;)Landroid/os/Message;
    //   146: invokevirtual 419	android/os/Message:sendToTarget	()V
    //   149: aload 4
    //   151: getfield 647	com/google/ads/interactivemedia/v3/internal/cg:b	F
    //   154: fstore 5
    //   156: aload_2
    //   157: getfield 102	com/google/ads/interactivemedia/v3/internal/bo:r	Lcom/google/ads/interactivemedia/v3/internal/cb;
    //   160: invokevirtual 209	com/google/ads/interactivemedia/v3/internal/cb:c	()Lcom/google/ads/interactivemedia/v3/internal/bz;
    //   163: astore_1
    //   164: aload_1
    //   165: ifnull +62 -> 227
    //   168: aload_1
    //   169: invokevirtual 372	com/google/ads/interactivemedia/v3/internal/bz:h	()Lcom/google/ads/interactivemedia/v3/internal/tg;
    //   172: getfield 377	com/google/ads/interactivemedia/v3/internal/tg:c	Lcom/google/ads/interactivemedia/v3/internal/td;
    //   175: invokevirtual 382	com/google/ads/interactivemedia/v3/internal/td:a	()[Lcom/google/ads/interactivemedia/v3/internal/sy;
    //   178: astore 6
    //   180: aload 6
    //   182: arraylength
    //   183: istore 7
    //   185: iconst_0
    //   186: istore_3
    //   187: iload_3
    //   188: iload 7
    //   190: if_icmpge +29 -> 219
    //   193: aload 6
    //   195: iload_3
    //   196: aaload
    //   197: astore 8
    //   199: aload 8
    //   201: ifnull +12 -> 213
    //   204: aload 8
    //   206: fload 5
    //   208: invokeinterface 710 2 0
    //   213: iinc 3 1
    //   216: goto -29 -> 187
    //   219: aload_1
    //   220: invokevirtual 387	com/google/ads/interactivemedia/v3/internal/bz:f	()Lcom/google/ads/interactivemedia/v3/internal/bz;
    //   223: astore_1
    //   224: goto -60 -> 164
    //   227: aload_2
    //   228: getfield 79	com/google/ads/interactivemedia/v3/internal/bo:a	[Lcom/google/ads/interactivemedia/v3/internal/cj;
    //   231: astore_2
    //   232: aload_2
    //   233: arraylength
    //   234: istore 7
    //   236: iconst_0
    //   237: istore_3
    //   238: iload_3
    //   239: iload 7
    //   241: if_icmpge +4281 -> 4522
    //   244: aload_2
    //   245: iload_3
    //   246: aaload
    //   247: astore_1
    //   248: aload_1
    //   249: ifnull +14 -> 263
    //   252: aload_1
    //   253: aload 4
    //   255: getfield 647	com/google/ads/interactivemedia/v3/internal/cg:b	F
    //   258: invokeinterface 711 2 0
    //   263: iinc 3 1
    //   266: goto -28 -> 238
    //   269: aload_1
    //   270: getfield 704	android/os/Message:obj	Ljava/lang/Object;
    //   273: checkcast 483	com/google/ads/interactivemedia/v3/internal/ch
    //   276: astore 4
    //   278: aload 4
    //   280: invokevirtual 583	com/google/ads/interactivemedia/v3/internal/ch:e	()Landroid/os/Handler;
    //   283: astore 8
    //   285: new 713	com/google/ads/interactivemedia/v3/internal/bn
    //   288: astore_1
    //   289: aload_1
    //   290: aload_2
    //   291: aload 4
    //   293: invokespecial 716	com/google/ads/interactivemedia/v3/internal/bn:<init>	(Lcom/google/ads/interactivemedia/v3/internal/bo;Lcom/google/ads/interactivemedia/v3/internal/ch;)V
    //   296: aload 8
    //   298: aload_1
    //   299: invokevirtual 720	android/os/Handler:post	(Ljava/lang/Runnable;)Z
    //   302: pop
    //   303: goto +4219 -> 4522
    //   306: aload_1
    //   307: getfield 704	android/os/Message:obj	Ljava/lang/Object;
    //   310: checkcast 483	com/google/ads/interactivemedia/v3/internal/ch
    //   313: astore_1
    //   314: aload_1
    //   315: invokevirtual 526	com/google/ads/interactivemedia/v3/internal/ch:f	()J
    //   318: ldc2_w 121
    //   321: lcmp
    //   322: ifne +11 -> 333
    //   325: aload_2
    //   326: aload_1
    //   327: invokespecial 626	com/google/ads/interactivemedia/v3/internal/bo:c	(Lcom/google/ads/interactivemedia/v3/internal/ch;)V
    //   330: goto +4192 -> 4522
    //   333: aload_2
    //   334: getfield 495	com/google/ads/interactivemedia/v3/internal/bo:u	Lcom/google/ads/interactivemedia/v3/internal/mq;
    //   337: ifnull +61 -> 398
    //   340: aload_2
    //   341: getfield 433	com/google/ads/interactivemedia/v3/internal/bo:C	I
    //   344: ifle +6 -> 350
    //   347: goto +51 -> 398
    //   350: new 478	com/google/ads/interactivemedia/v3/internal/bs
    //   353: astore 4
    //   355: aload 4
    //   357: aload_1
    //   358: invokespecial 722	com/google/ads/interactivemedia/v3/internal/bs:<init>	(Lcom/google/ads/interactivemedia/v3/internal/ch;)V
    //   361: aload_2
    //   362: aload 4
    //   364: invokespecial 724	com/google/ads/interactivemedia/v3/internal/bo:a	(Lcom/google/ads/interactivemedia/v3/internal/bs;)Z
    //   367: ifeq +23 -> 390
    //   370: aload_2
    //   371: getfield 160	com/google/ads/interactivemedia/v3/internal/bo:p	Ljava/util/ArrayList;
    //   374: aload 4
    //   376: invokevirtual 727	java/util/ArrayList:add	(Ljava/lang/Object;)Z
    //   379: pop
    //   380: aload_2
    //   381: getfield 160	com/google/ads/interactivemedia/v3/internal/bo:p	Ljava/util/ArrayList;
    //   384: invokestatic 733	java/util/Collections:sort	(Ljava/util/List;)V
    //   387: goto +4135 -> 4522
    //   390: aload_1
    //   391: iconst_0
    //   392: invokevirtual 485	com/google/ads/interactivemedia/v3/internal/ch:a	(Z)V
    //   395: goto +4127 -> 4522
    //   398: aload_2
    //   399: getfield 160	com/google/ads/interactivemedia/v3/internal/bo:p	Ljava/util/ArrayList;
    //   402: astore 4
    //   404: new 478	com/google/ads/interactivemedia/v3/internal/bs
    //   407: astore_2
    //   408: aload_2
    //   409: aload_1
    //   410: invokespecial 722	com/google/ads/interactivemedia/v3/internal/bs:<init>	(Lcom/google/ads/interactivemedia/v3/internal/ch;)V
    //   413: aload 4
    //   415: aload_2
    //   416: invokevirtual 727	java/util/ArrayList:add	(Ljava/lang/Object;)Z
    //   419: pop
    //   420: goto +4102 -> 4522
    //   423: aload_1
    //   424: getfield 707	android/os/Message:arg1	I
    //   427: ifeq +9 -> 436
    //   430: iconst_1
    //   431: istore 9
    //   433: goto +6 -> 439
    //   436: iconst_0
    //   437: istore 9
    //   439: aload_1
    //   440: getfield 704	android/os/Message:obj	Ljava/lang/Object;
    //   443: checkcast 735	java/util/concurrent/atomic/AtomicBoolean
    //   446: astore_1
    //   447: aload_2
    //   448: getfield 428	com/google/ads/interactivemedia/v3/internal/bo:B	Z
    //   451: iload 9
    //   453: if_icmpeq +59 -> 512
    //   456: aload_2
    //   457: iload 9
    //   459: putfield 428	com/google/ads/interactivemedia/v3/internal/bo:B	Z
    //   462: iload 9
    //   464: ifne +48 -> 512
    //   467: aload_2
    //   468: getfield 79	com/google/ads/interactivemedia/v3/internal/bo:a	[Lcom/google/ads/interactivemedia/v3/internal/cj;
    //   471: astore 4
    //   473: aload 4
    //   475: arraylength
    //   476: istore 7
    //   478: iconst_0
    //   479: istore_3
    //   480: iload_3
    //   481: iload 7
    //   483: if_icmpge +29 -> 512
    //   486: aload 4
    //   488: iload_3
    //   489: aaload
    //   490: astore_2
    //   491: aload_2
    //   492: invokeinterface 395 1 0
    //   497: ifne +9 -> 506
    //   500: aload_2
    //   501: invokeinterface 450 1 0
    //   506: iinc 3 1
    //   509: goto -29 -> 480
    //   512: aload_1
    //   513: ifnull +4009 -> 4522
    //   516: aload_0
    //   517: monitorenter
    //   518: aload_1
    //   519: iconst_1
    //   520: invokevirtual 738	java/util/concurrent/atomic/AtomicBoolean:set	(Z)V
    //   523: aload_0
    //   524: invokevirtual 741	java/lang/Object:notifyAll	()V
    //   527: aload_0
    //   528: monitorexit
    //   529: goto +3993 -> 4522
    //   532: astore_1
    //   533: aload_0
    //   534: monitorexit
    //   535: aload_1
    //   536: athrow
    //   537: aload_1
    //   538: getfield 707	android/os/Message:arg1	I
    //   541: ifeq +9 -> 550
    //   544: iconst_1
    //   545: istore 9
    //   547: goto +6 -> 553
    //   550: iconst_0
    //   551: istore 9
    //   553: aload_2
    //   554: iload 9
    //   556: putfield 93	com/google/ads/interactivemedia/v3/internal/bo:A	Z
    //   559: aload_2
    //   560: getfield 102	com/google/ads/interactivemedia/v3/internal/bo:r	Lcom/google/ads/interactivemedia/v3/internal/cb;
    //   563: iload 9
    //   565: invokevirtual 744	com/google/ads/interactivemedia/v3/internal/cb:a	(Z)Z
    //   568: ifne +8 -> 576
    //   571: aload_2
    //   572: iconst_1
    //   573: invokespecial 746	com/google/ads/interactivemedia/v3/internal/bo:d	(Z)V
    //   576: aload_2
    //   577: iconst_0
    //   578: invokespecial 284	com/google/ads/interactivemedia/v3/internal/bo:e	(Z)V
    //   581: goto +3941 -> 4522
    //   584: aload_1
    //   585: getfield 707	android/os/Message:arg1	I
    //   588: istore_3
    //   589: aload_2
    //   590: iload_3
    //   591: putfield 91	com/google/ads/interactivemedia/v3/internal/bo:z	I
    //   594: aload_2
    //   595: getfield 102	com/google/ads/interactivemedia/v3/internal/bo:r	Lcom/google/ads/interactivemedia/v3/internal/cb;
    //   598: iload_3
    //   599: invokevirtual 747	com/google/ads/interactivemedia/v3/internal/cb:a	(I)Z
    //   602: ifne +8 -> 610
    //   605: aload_2
    //   606: iconst_1
    //   607: invokespecial 746	com/google/ads/interactivemedia/v3/internal/bo:d	(Z)V
    //   610: aload_2
    //   611: iconst_0
    //   612: invokespecial 284	com/google/ads/interactivemedia/v3/internal/bo:e	(Z)V
    //   615: goto +3907 -> 4522
    //   618: aload_2
    //   619: getfield 155	com/google/ads/interactivemedia/v3/internal/bo:n	Lcom/google/ads/interactivemedia/v3/internal/ay;
    //   622: invokevirtual 643	com/google/ads/interactivemedia/v3/internal/ay:d	()Lcom/google/ads/interactivemedia/v3/internal/cg;
    //   625: getfield 647	com/google/ads/interactivemedia/v3/internal/cg:b	F
    //   628: fstore 5
    //   630: aload_2
    //   631: getfield 102	com/google/ads/interactivemedia/v3/internal/bo:r	Lcom/google/ads/interactivemedia/v3/internal/cb;
    //   634: invokevirtual 209	com/google/ads/interactivemedia/v3/internal/cb:c	()Lcom/google/ads/interactivemedia/v3/internal/bz;
    //   637: astore_1
    //   638: aload_2
    //   639: getfield 102	com/google/ads/interactivemedia/v3/internal/bo:r	Lcom/google/ads/interactivemedia/v3/internal/cb;
    //   642: invokevirtual 211	com/google/ads/interactivemedia/v3/internal/cb:d	()Lcom/google/ads/interactivemedia/v3/internal/bz;
    //   645: astore 4
    //   647: iconst_1
    //   648: istore_3
    //   649: aload_1
    //   650: ifnull +3872 -> 4522
    //   653: aload_1
    //   654: getfield 238	com/google/ads/interactivemedia/v3/internal/bz:d	Z
    //   657: ifne +6 -> 663
    //   660: goto +3862 -> 4522
    //   663: aload_1
    //   664: fload 5
    //   666: aload_2
    //   667: getfield 129	com/google/ads/interactivemedia/v3/internal/bo:t	Lcom/google/ads/interactivemedia/v3/internal/cd;
    //   670: getfield 295	com/google/ads/interactivemedia/v3/internal/cd:a	Lcom/google/ads/interactivemedia/v3/internal/cr;
    //   673: invokevirtual 750	com/google/ads/interactivemedia/v3/internal/bz:b	(FLcom/google/ads/interactivemedia/v3/internal/cr;)Lcom/google/ads/interactivemedia/v3/internal/tg;
    //   676: astore 8
    //   678: aload_1
    //   679: invokevirtual 372	com/google/ads/interactivemedia/v3/internal/bz:h	()Lcom/google/ads/interactivemedia/v3/internal/tg;
    //   682: astore 6
    //   684: aload 6
    //   686: ifnull +68 -> 754
    //   689: aload 6
    //   691: getfield 377	com/google/ads/interactivemedia/v3/internal/tg:c	Lcom/google/ads/interactivemedia/v3/internal/td;
    //   694: getfield 752	com/google/ads/interactivemedia/v3/internal/td:a	I
    //   697: aload 8
    //   699: getfield 377	com/google/ads/interactivemedia/v3/internal/tg:c	Lcom/google/ads/interactivemedia/v3/internal/td;
    //   702: getfield 752	com/google/ads/interactivemedia/v3/internal/td:a	I
    //   705: if_icmpeq +6 -> 711
    //   708: goto +46 -> 754
    //   711: iconst_0
    //   712: istore 7
    //   714: iload 7
    //   716: aload 8
    //   718: getfield 377	com/google/ads/interactivemedia/v3/internal/tg:c	Lcom/google/ads/interactivemedia/v3/internal/td;
    //   721: getfield 752	com/google/ads/interactivemedia/v3/internal/td:a	I
    //   724: if_icmpge +24 -> 748
    //   727: aload 8
    //   729: aload 6
    //   731: iload 7
    //   733: invokevirtual 755	com/google/ads/interactivemedia/v3/internal/tg:a	(Lcom/google/ads/interactivemedia/v3/internal/tg;I)Z
    //   736: ifne +6 -> 742
    //   739: goto +15 -> 754
    //   742: iinc 7 1
    //   745: goto -31 -> 714
    //   748: iconst_1
    //   749: istore 7
    //   751: goto +6 -> 757
    //   754: iconst_0
    //   755: istore 7
    //   757: iload 7
    //   759: ifeq +19 -> 778
    //   762: aload_1
    //   763: aload 4
    //   765: if_acmpne +5 -> 770
    //   768: iconst_0
    //   769: istore_3
    //   770: aload_1
    //   771: invokevirtual 387	com/google/ads/interactivemedia/v3/internal/bz:f	()Lcom/google/ads/interactivemedia/v3/internal/bz;
    //   774: astore_1
    //   775: goto -126 -> 649
    //   778: iload_3
    //   779: ifeq +285 -> 1064
    //   782: aload_2
    //   783: getfield 102	com/google/ads/interactivemedia/v3/internal/bo:r	Lcom/google/ads/interactivemedia/v3/internal/cb;
    //   786: invokevirtual 209	com/google/ads/interactivemedia/v3/internal/cb:c	()Lcom/google/ads/interactivemedia/v3/internal/bz;
    //   789: astore_1
    //   790: aload_2
    //   791: getfield 102	com/google/ads/interactivemedia/v3/internal/bo:r	Lcom/google/ads/interactivemedia/v3/internal/cb;
    //   794: aload_1
    //   795: invokevirtual 241	com/google/ads/interactivemedia/v3/internal/cb:a	(Lcom/google/ads/interactivemedia/v3/internal/bz;)Z
    //   798: istore 9
    //   800: aload_2
    //   801: getfield 79	com/google/ads/interactivemedia/v3/internal/bo:a	[Lcom/google/ads/interactivemedia/v3/internal/cj;
    //   804: arraylength
    //   805: newarray <illegal type>
    //   807: astore 4
    //   809: aload_1
    //   810: aload 8
    //   812: aload_2
    //   813: getfield 129	com/google/ads/interactivemedia/v3/internal/bo:t	Lcom/google/ads/interactivemedia/v3/internal/cd;
    //   816: getfield 362	com/google/ads/interactivemedia/v3/internal/cd:m	J
    //   819: iload 9
    //   821: aload 4
    //   823: invokevirtual 758	com/google/ads/interactivemedia/v3/internal/bz:a	(Lcom/google/ads/interactivemedia/v3/internal/tg;JZ[Z)J
    //   826: lstore 10
    //   828: aload_2
    //   829: getfield 129	com/google/ads/interactivemedia/v3/internal/bo:t	Lcom/google/ads/interactivemedia/v3/internal/cd;
    //   832: astore 8
    //   834: aload 8
    //   836: getfield 341	com/google/ads/interactivemedia/v3/internal/cd:e	I
    //   839: iconst_4
    //   840: if_icmpeq +59 -> 899
    //   843: lload 10
    //   845: aload 8
    //   847: getfield 362	com/google/ads/interactivemedia/v3/internal/cd:m	J
    //   850: lcmp
    //   851: ifeq +48 -> 899
    //   854: aload_2
    //   855: getfield 129	com/google/ads/interactivemedia/v3/internal/bo:t	Lcom/google/ads/interactivemedia/v3/internal/cd;
    //   858: astore 8
    //   860: aload_2
    //   861: aload 8
    //   863: aload 8
    //   865: getfield 343	com/google/ads/interactivemedia/v3/internal/cd:b	Lcom/google/ads/interactivemedia/v3/internal/mt;
    //   868: lload 10
    //   870: aload 8
    //   872: getfield 346	com/google/ads/interactivemedia/v3/internal/cd:d	J
    //   875: aload_0
    //   876: invokespecial 607	com/google/ads/interactivemedia/v3/internal/bo:l	()J
    //   879: invokevirtual 610	com/google/ads/interactivemedia/v3/internal/cd:a	(Lcom/google/ads/interactivemedia/v3/internal/mt;JJJ)Lcom/google/ads/interactivemedia/v3/internal/cd;
    //   882: putfield 129	com/google/ads/interactivemedia/v3/internal/bo:t	Lcom/google/ads/interactivemedia/v3/internal/cd;
    //   885: aload_2
    //   886: getfield 136	com/google/ads/interactivemedia/v3/internal/bo:o	Lcom/google/ads/interactivemedia/v3/internal/br;
    //   889: iconst_4
    //   890: invokevirtual 611	com/google/ads/interactivemedia/v3/internal/br:b	(I)V
    //   893: aload_2
    //   894: lload 10
    //   896: invokespecial 269	com/google/ads/interactivemedia/v3/internal/bo:a	(J)V
    //   899: aload_2
    //   900: getfield 79	com/google/ads/interactivemedia/v3/internal/bo:a	[Lcom/google/ads/interactivemedia/v3/internal/cj;
    //   903: arraylength
    //   904: newarray <illegal type>
    //   906: astore 8
    //   908: iconst_0
    //   909: istore_3
    //   910: iload_3
    //   911: istore 7
    //   913: aload_2
    //   914: getfield 79	com/google/ads/interactivemedia/v3/internal/bo:a	[Lcom/google/ads/interactivemedia/v3/internal/cj;
    //   917: astore 6
    //   919: iload_3
    //   920: aload 6
    //   922: arraylength
    //   923: if_icmpge +111 -> 1034
    //   926: aload 6
    //   928: iload_3
    //   929: aaload
    //   930: astore 6
    //   932: aload 6
    //   934: invokeinterface 395 1 0
    //   939: ifeq +9 -> 948
    //   942: iconst_1
    //   943: istore 9
    //   945: goto +6 -> 951
    //   948: iconst_0
    //   949: istore 9
    //   951: aload 8
    //   953: iload_3
    //   954: iload 9
    //   956: bastore
    //   957: aload_1
    //   958: getfield 404	com/google/ads/interactivemedia/v3/internal/bz:c	[Lcom/google/ads/interactivemedia/v3/internal/nw;
    //   961: iload_3
    //   962: aaload
    //   963: astore 12
    //   965: iload 7
    //   967: istore 13
    //   969: aload 12
    //   971: ifnull +9 -> 980
    //   974: iload 7
    //   976: iconst_1
    //   977: iadd
    //   978: istore 13
    //   980: iload 9
    //   982: ifeq +42 -> 1024
    //   985: aload 12
    //   987: aload 6
    //   989: invokeinterface 401 1 0
    //   994: if_acmpeq +12 -> 1006
    //   997: aload_2
    //   998: aload 6
    //   1000: invokespecial 248	com/google/ads/interactivemedia/v3/internal/bo:b	(Lcom/google/ads/interactivemedia/v3/internal/cj;)V
    //   1003: goto +21 -> 1024
    //   1006: aload 4
    //   1008: iload_3
    //   1009: baload
    //   1010: ifeq +14 -> 1024
    //   1013: aload 6
    //   1015: aload_2
    //   1016: getfield 367	com/google/ads/interactivemedia/v3/internal/bo:E	J
    //   1019: invokeinterface 369 3 0
    //   1024: iinc 3 1
    //   1027: iload 13
    //   1029: istore 7
    //   1031: goto -118 -> 913
    //   1034: aload_2
    //   1035: aload_2
    //   1036: getfield 129	com/google/ads/interactivemedia/v3/internal/bo:t	Lcom/google/ads/interactivemedia/v3/internal/cd;
    //   1039: aload_1
    //   1040: invokevirtual 407	com/google/ads/interactivemedia/v3/internal/bz:g	()Lcom/google/ads/interactivemedia/v3/internal/of;
    //   1043: aload_1
    //   1044: invokevirtual 372	com/google/ads/interactivemedia/v3/internal/bz:h	()Lcom/google/ads/interactivemedia/v3/internal/tg;
    //   1047: invokevirtual 282	com/google/ads/interactivemedia/v3/internal/cd:a	(Lcom/google/ads/interactivemedia/v3/internal/of;Lcom/google/ads/interactivemedia/v3/internal/tg;)Lcom/google/ads/interactivemedia/v3/internal/cd;
    //   1050: putfield 129	com/google/ads/interactivemedia/v3/internal/bo:t	Lcom/google/ads/interactivemedia/v3/internal/cd;
    //   1053: aload_2
    //   1054: aload 8
    //   1056: iload 7
    //   1058: invokespecial 410	com/google/ads/interactivemedia/v3/internal/bo:a	([ZI)V
    //   1061: goto +46 -> 1107
    //   1064: aload_2
    //   1065: getfield 102	com/google/ads/interactivemedia/v3/internal/bo:r	Lcom/google/ads/interactivemedia/v3/internal/cb;
    //   1068: aload_1
    //   1069: invokevirtual 241	com/google/ads/interactivemedia/v3/internal/cb:a	(Lcom/google/ads/interactivemedia/v3/internal/bz;)Z
    //   1072: pop
    //   1073: aload_1
    //   1074: getfield 238	com/google/ads/interactivemedia/v3/internal/bz:d	Z
    //   1077: ifeq +30 -> 1107
    //   1080: aload_1
    //   1081: aload 8
    //   1083: aload_1
    //   1084: getfield 225	com/google/ads/interactivemedia/v3/internal/bz:f	Lcom/google/ads/interactivemedia/v3/internal/cc;
    //   1087: getfield 760	com/google/ads/interactivemedia/v3/internal/cc:b	J
    //   1090: aload_2
    //   1091: getfield 367	com/google/ads/interactivemedia/v3/internal/bo:E	J
    //   1094: aload_1
    //   1095: invokevirtual 245	com/google/ads/interactivemedia/v3/internal/bz:a	()J
    //   1098: lsub
    //   1099: invokestatic 555	java/lang/Math:max	(JJ)J
    //   1102: iconst_0
    //   1103: invokevirtual 763	com/google/ads/interactivemedia/v3/internal/bz:a	(Lcom/google/ads/interactivemedia/v3/internal/tg;JZ)J
    //   1106: pop2
    //   1107: aload_2
    //   1108: iconst_1
    //   1109: invokespecial 284	com/google/ads/interactivemedia/v3/internal/bo:e	(Z)V
    //   1112: aload_2
    //   1113: getfield 129	com/google/ads/interactivemedia/v3/internal/bo:t	Lcom/google/ads/interactivemedia/v3/internal/cd;
    //   1116: getfield 341	com/google/ads/interactivemedia/v3/internal/cd:e	I
    //   1119: iconst_4
    //   1120: if_icmpeq +3402 -> 4522
    //   1123: aload_0
    //   1124: invokespecial 271	com/google/ads/interactivemedia/v3/internal/bo:k	()V
    //   1127: aload_0
    //   1128: invokespecial 765	com/google/ads/interactivemedia/v3/internal/bo:f	()V
    //   1131: aload_2
    //   1132: getfield 202	com/google/ads/interactivemedia/v3/internal/bo:g	Lcom/google/ads/interactivemedia/v3/internal/vo;
    //   1135: iconst_2
    //   1136: invokevirtual 289	com/google/ads/interactivemedia/v3/internal/vo:a	(I)Z
    //   1139: pop
    //   1140: goto +3382 -> 4522
    //   1143: aload_1
    //   1144: getfield 704	android/os/Message:obj	Ljava/lang/Object;
    //   1147: checkcast 261	com/google/ads/interactivemedia/v3/internal/mo
    //   1150: astore_1
    //   1151: aload_2
    //   1152: getfield 102	com/google/ads/interactivemedia/v3/internal/bo:r	Lcom/google/ads/interactivemedia/v3/internal/cb;
    //   1155: aload_1
    //   1156: invokevirtual 768	com/google/ads/interactivemedia/v3/internal/cb:a	(Lcom/google/ads/interactivemedia/v3/internal/mo;)Z
    //   1159: ifeq +3363 -> 4522
    //   1162: aload_2
    //   1163: getfield 102	com/google/ads/interactivemedia/v3/internal/bo:r	Lcom/google/ads/interactivemedia/v3/internal/cb;
    //   1166: aload_2
    //   1167: getfield 367	com/google/ads/interactivemedia/v3/internal/bo:E	J
    //   1170: invokevirtual 769	com/google/ads/interactivemedia/v3/internal/cb:a	(J)V
    //   1173: aload_0
    //   1174: invokespecial 271	com/google/ads/interactivemedia/v3/internal/bo:k	()V
    //   1177: goto +3345 -> 4522
    //   1180: aload_1
    //   1181: getfield 704	android/os/Message:obj	Ljava/lang/Object;
    //   1184: checkcast 261	com/google/ads/interactivemedia/v3/internal/mo
    //   1187: astore_1
    //   1188: aload_2
    //   1189: getfield 102	com/google/ads/interactivemedia/v3/internal/bo:r	Lcom/google/ads/interactivemedia/v3/internal/cb;
    //   1192: aload_1
    //   1193: invokevirtual 768	com/google/ads/interactivemedia/v3/internal/cb:a	(Lcom/google/ads/interactivemedia/v3/internal/mo;)Z
    //   1196: ifeq +3326 -> 4522
    //   1199: aload_2
    //   1200: getfield 102	com/google/ads/interactivemedia/v3/internal/bo:r	Lcom/google/ads/interactivemedia/v3/internal/cb;
    //   1203: invokevirtual 549	com/google/ads/interactivemedia/v3/internal/cb:b	()Lcom/google/ads/interactivemedia/v3/internal/bz;
    //   1206: astore_1
    //   1207: aload_1
    //   1208: aload_2
    //   1209: getfield 155	com/google/ads/interactivemedia/v3/internal/bo:n	Lcom/google/ads/interactivemedia/v3/internal/ay;
    //   1212: invokevirtual 643	com/google/ads/interactivemedia/v3/internal/ay:d	()Lcom/google/ads/interactivemedia/v3/internal/cg;
    //   1215: getfield 647	com/google/ads/interactivemedia/v3/internal/cg:b	F
    //   1218: aload_2
    //   1219: getfield 129	com/google/ads/interactivemedia/v3/internal/bo:t	Lcom/google/ads/interactivemedia/v3/internal/cd;
    //   1222: getfield 295	com/google/ads/interactivemedia/v3/internal/cd:a	Lcom/google/ads/interactivemedia/v3/internal/cr;
    //   1225: invokevirtual 772	com/google/ads/interactivemedia/v3/internal/bz:a	(FLcom/google/ads/interactivemedia/v3/internal/cr;)V
    //   1228: aload_2
    //   1229: aload_1
    //   1230: invokevirtual 407	com/google/ads/interactivemedia/v3/internal/bz:g	()Lcom/google/ads/interactivemedia/v3/internal/of;
    //   1233: aload_1
    //   1234: invokevirtual 372	com/google/ads/interactivemedia/v3/internal/bz:h	()Lcom/google/ads/interactivemedia/v3/internal/tg;
    //   1237: invokespecial 615	com/google/ads/interactivemedia/v3/internal/bo:a	(Lcom/google/ads/interactivemedia/v3/internal/of;Lcom/google/ads/interactivemedia/v3/internal/tg;)V
    //   1240: aload_1
    //   1241: aload_2
    //   1242: getfield 102	com/google/ads/interactivemedia/v3/internal/bo:r	Lcom/google/ads/interactivemedia/v3/internal/cb;
    //   1245: invokevirtual 209	com/google/ads/interactivemedia/v3/internal/cb:c	()Lcom/google/ads/interactivemedia/v3/internal/bz;
    //   1248: if_acmpne +19 -> 1267
    //   1251: aload_2
    //   1252: aload_1
    //   1253: getfield 225	com/google/ads/interactivemedia/v3/internal/bz:f	Lcom/google/ads/interactivemedia/v3/internal/cc;
    //   1256: getfield 760	com/google/ads/interactivemedia/v3/internal/cc:b	J
    //   1259: invokespecial 269	com/google/ads/interactivemedia/v3/internal/bo:a	(J)V
    //   1262: aload_2
    //   1263: aconst_null
    //   1264: invokespecial 254	com/google/ads/interactivemedia/v3/internal/bo:a	(Lcom/google/ads/interactivemedia/v3/internal/bz;)V
    //   1267: aload_0
    //   1268: invokespecial 271	com/google/ads/interactivemedia/v3/internal/bo:k	()V
    //   1271: goto +3251 -> 4522
    //   1274: aload_1
    //   1275: getfield 704	android/os/Message:obj	Ljava/lang/Object;
    //   1278: checkcast 680	com/google/ads/interactivemedia/v3/internal/bp
    //   1281: astore_1
    //   1282: aload_1
    //   1283: getfield 774	com/google/ads/interactivemedia/v3/internal/bp:a	Lcom/google/ads/interactivemedia/v3/internal/mq;
    //   1286: aload_2
    //   1287: getfield 495	com/google/ads/interactivemedia/v3/internal/bo:u	Lcom/google/ads/interactivemedia/v3/internal/mq;
    //   1290: if_acmpne +3232 -> 4522
    //   1293: aload_2
    //   1294: getfield 136	com/google/ads/interactivemedia/v3/internal/bo:o	Lcom/google/ads/interactivemedia/v3/internal/br;
    //   1297: aload_2
    //   1298: getfield 433	com/google/ads/interactivemedia/v3/internal/bo:C	I
    //   1301: invokevirtual 434	com/google/ads/interactivemedia/v3/internal/br:a	(I)V
    //   1304: aload_2
    //   1305: iconst_0
    //   1306: putfield 433	com/google/ads/interactivemedia/v3/internal/bo:C	I
    //   1309: aload_2
    //   1310: getfield 129	com/google/ads/interactivemedia/v3/internal/bo:t	Lcom/google/ads/interactivemedia/v3/internal/cd;
    //   1313: getfield 295	com/google/ads/interactivemedia/v3/internal/cd:a	Lcom/google/ads/interactivemedia/v3/internal/cr;
    //   1316: astore 8
    //   1318: aload_1
    //   1319: getfield 776	com/google/ads/interactivemedia/v3/internal/bp:b	Lcom/google/ads/interactivemedia/v3/internal/cr;
    //   1322: astore_1
    //   1323: aload_2
    //   1324: getfield 102	com/google/ads/interactivemedia/v3/internal/bo:r	Lcom/google/ads/interactivemedia/v3/internal/cb;
    //   1327: aload_1
    //   1328: invokevirtual 470	com/google/ads/interactivemedia/v3/internal/cb:a	(Lcom/google/ads/interactivemedia/v3/internal/cr;)V
    //   1331: aload_2
    //   1332: getfield 129	com/google/ads/interactivemedia/v3/internal/bo:t	Lcom/google/ads/interactivemedia/v3/internal/cd;
    //   1335: astore 14
    //   1337: new 124	com/google/ads/interactivemedia/v3/internal/cd
    //   1340: astore_2
    //   1341: aload 14
    //   1343: getfield 343	com/google/ads/interactivemedia/v3/internal/cd:b	Lcom/google/ads/interactivemedia/v3/internal/mt;
    //   1346: astore 15
    //   1348: aload 14
    //   1350: getfield 344	com/google/ads/interactivemedia/v3/internal/cd:c	J
    //   1353: lstore 16
    //   1355: aload 14
    //   1357: getfield 346	com/google/ads/interactivemedia/v3/internal/cd:d	J
    //   1360: lstore 18
    //   1362: aload 14
    //   1364: getfield 341	com/google/ads/interactivemedia/v3/internal/cd:e	I
    //   1367: istore_3
    //   1368: aload 14
    //   1370: getfield 349	com/google/ads/interactivemedia/v3/internal/cd:f	Lcom/google/ads/interactivemedia/v3/internal/ba;
    //   1373: astore 4
    //   1375: aload 14
    //   1377: getfield 351	com/google/ads/interactivemedia/v3/internal/cd:g	Z
    //   1380: istore 9
    //   1382: aload 14
    //   1384: getfield 353	com/google/ads/interactivemedia/v3/internal/cd:h	Lcom/google/ads/interactivemedia/v3/internal/of;
    //   1387: astore 6
    //   1389: aload 14
    //   1391: getfield 355	com/google/ads/interactivemedia/v3/internal/cd:i	Lcom/google/ads/interactivemedia/v3/internal/tg;
    //   1394: astore 20
    //   1396: aload 14
    //   1398: getfield 357	com/google/ads/interactivemedia/v3/internal/cd:j	Lcom/google/ads/interactivemedia/v3/internal/mt;
    //   1401: astore 12
    //   1403: aload 14
    //   1405: getfield 359	com/google/ads/interactivemedia/v3/internal/cd:k	J
    //   1408: lstore 21
    //   1410: aload 14
    //   1412: getfield 360	com/google/ads/interactivemedia/v3/internal/cd:l	J
    //   1415: lstore 10
    //   1417: aload_2
    //   1418: aload_1
    //   1419: aload 15
    //   1421: lload 16
    //   1423: lload 18
    //   1425: iload_3
    //   1426: aload 4
    //   1428: iload 9
    //   1430: aload 6
    //   1432: aload 20
    //   1434: aload 12
    //   1436: lload 21
    //   1438: lload 10
    //   1440: aload 14
    //   1442: getfield 362	com/google/ads/interactivemedia/v3/internal/cd:m	J
    //   1445: invokespecial 365	com/google/ads/interactivemedia/v3/internal/cd:<init>	(Lcom/google/ads/interactivemedia/v3/internal/cr;Lcom/google/ads/interactivemedia/v3/internal/mt;JJILcom/google/ads/interactivemedia/v3/internal/ba;ZLcom/google/ads/interactivemedia/v3/internal/of;Lcom/google/ads/interactivemedia/v3/internal/tg;Lcom/google/ads/interactivemedia/v3/internal/mt;JJJ)V
    //   1448: aload_0
    //   1449: astore 4
    //   1451: aload 4
    //   1453: aload_2
    //   1454: putfield 129	com/google/ads/interactivemedia/v3/internal/bo:t	Lcom/google/ads/interactivemedia/v3/internal/cd;
    //   1457: aload 4
    //   1459: getfield 160	com/google/ads/interactivemedia/v3/internal/bo:p	Ljava/util/ArrayList;
    //   1462: invokevirtual 473	java/util/ArrayList:size	()I
    //   1465: iconst_1
    //   1466: isub
    //   1467: istore_3
    //   1468: iload_3
    //   1469: iflt +70 -> 1539
    //   1472: aload 4
    //   1474: aload 4
    //   1476: getfield 160	com/google/ads/interactivemedia/v3/internal/bo:p	Ljava/util/ArrayList;
    //   1479: iload_3
    //   1480: invokevirtual 476	java/util/ArrayList:get	(I)Ljava/lang/Object;
    //   1483: checkcast 478	com/google/ads/interactivemedia/v3/internal/bs
    //   1486: invokespecial 724	com/google/ads/interactivemedia/v3/internal/bo:a	(Lcom/google/ads/interactivemedia/v3/internal/bs;)Z
    //   1489: ifne +44 -> 1533
    //   1492: aload 4
    //   1494: getfield 160	com/google/ads/interactivemedia/v3/internal/bo:p	Ljava/util/ArrayList;
    //   1497: iload_3
    //   1498: invokevirtual 476	java/util/ArrayList:get	(I)Ljava/lang/Object;
    //   1501: checkcast 478	com/google/ads/interactivemedia/v3/internal/bs
    //   1504: getfield 481	com/google/ads/interactivemedia/v3/internal/bs:a	Lcom/google/ads/interactivemedia/v3/internal/ch;
    //   1507: astore_2
    //   1508: aload_2
    //   1509: iconst_0
    //   1510: invokevirtual 485	com/google/ads/interactivemedia/v3/internal/ch:a	(Z)V
    //   1513: aload 4
    //   1515: getfield 160	com/google/ads/interactivemedia/v3/internal/bo:p	Ljava/util/ArrayList;
    //   1518: iload_3
    //   1519: invokevirtual 631	java/util/ArrayList:remove	(I)Ljava/lang/Object;
    //   1522: pop
    //   1523: goto +10 -> 1533
    //   1526: astore_1
    //   1527: iconst_0
    //   1528: istore 9
    //   1530: goto +3079 -> 4609
    //   1533: iinc 3 -1
    //   1536: goto -68 -> 1468
    //   1539: aload 4
    //   1541: getfield 160	com/google/ads/interactivemedia/v3/internal/bo:p	Ljava/util/ArrayList;
    //   1544: invokestatic 733	java/util/Collections:sort	(Ljava/util/List;)V
    //   1547: aload 4
    //   1549: getfield 129	com/google/ads/interactivemedia/v3/internal/bo:t	Lcom/google/ads/interactivemedia/v3/internal/cd;
    //   1552: getfield 343	com/google/ads/interactivemedia/v3/internal/cd:b	Lcom/google/ads/interactivemedia/v3/internal/mt;
    //   1555: astore 6
    //   1557: aload 6
    //   1559: invokevirtual 624	com/google/ads/interactivemedia/v3/internal/mt:a	()Z
    //   1562: ifeq +16 -> 1578
    //   1565: aload 4
    //   1567: getfield 129	com/google/ads/interactivemedia/v3/internal/bo:t	Lcom/google/ads/interactivemedia/v3/internal/cd;
    //   1570: getfield 346	com/google/ads/interactivemedia/v3/internal/cd:d	J
    //   1573: lstore 10
    //   1575: goto +13 -> 1588
    //   1578: aload 4
    //   1580: getfield 129	com/google/ads/interactivemedia/v3/internal/bo:t	Lcom/google/ads/interactivemedia/v3/internal/cd;
    //   1583: getfield 362	com/google/ads/interactivemedia/v3/internal/cd:m	J
    //   1586: lstore 10
    //   1588: aload 4
    //   1590: getfield 454	com/google/ads/interactivemedia/v3/internal/bo:D	Lcom/google/ads/interactivemedia/v3/internal/bu;
    //   1593: astore_2
    //   1594: aload_2
    //   1595: ifnull +58 -> 1653
    //   1598: aload 4
    //   1600: aload_2
    //   1601: iconst_1
    //   1602: invokespecial 531	com/google/ads/interactivemedia/v3/internal/bo:a	(Lcom/google/ads/interactivemedia/v3/internal/bu;Z)Landroid/util/Pair;
    //   1605: astore_1
    //   1606: aload 4
    //   1608: aconst_null
    //   1609: putfield 454	com/google/ads/interactivemedia/v3/internal/bo:D	Lcom/google/ads/interactivemedia/v3/internal/bu;
    //   1612: aload_1
    //   1613: ifnonnull +10 -> 1623
    //   1616: aload_0
    //   1617: invokespecial 778	com/google/ads/interactivemedia/v3/internal/bo:h	()V
    //   1620: goto +2902 -> 4522
    //   1623: aload_1
    //   1624: getfield 534	android/util/Pair:second	Ljava/lang/Object;
    //   1627: checkcast 536	java/lang/Long
    //   1630: invokevirtual 539	java/lang/Long:longValue	()J
    //   1633: lstore 16
    //   1635: aload 4
    //   1637: getfield 102	com/google/ads/interactivemedia/v3/internal/bo:r	Lcom/google/ads/interactivemedia/v3/internal/cb;
    //   1640: aload_1
    //   1641: getfield 315	android/util/Pair:first	Ljava/lang/Object;
    //   1644: lload 16
    //   1646: invokevirtual 781	com/google/ads/interactivemedia/v3/internal/cb:a	(Ljava/lang/Object;J)Lcom/google/ads/interactivemedia/v3/internal/mt;
    //   1649: astore_1
    //   1650: goto +241 -> 1891
    //   1653: lload 10
    //   1655: ldc2_w 121
    //   1658: lcmp
    //   1659: ifne +81 -> 1740
    //   1662: aload_1
    //   1663: invokevirtual 302	com/google/ads/interactivemedia/v3/internal/cr:a	()Z
    //   1666: ifne +74 -> 1740
    //   1669: aload 4
    //   1671: aload_1
    //   1672: aload_1
    //   1673: aload 4
    //   1675: getfield 93	com/google/ads/interactivemedia/v3/internal/bo:A	Z
    //   1678: invokevirtual 784	com/google/ads/interactivemedia/v3/internal/cr:b	(Z)I
    //   1681: ldc2_w 121
    //   1684: invokespecial 328	com/google/ads/interactivemedia/v3/internal/bo:b	(Lcom/google/ads/interactivemedia/v3/internal/cr;IJ)Landroid/util/Pair;
    //   1687: astore_2
    //   1688: aload 4
    //   1690: getfield 102	com/google/ads/interactivemedia/v3/internal/bo:r	Lcom/google/ads/interactivemedia/v3/internal/cb;
    //   1693: aload_2
    //   1694: getfield 315	android/util/Pair:first	Ljava/lang/Object;
    //   1697: aload_2
    //   1698: getfield 534	android/util/Pair:second	Ljava/lang/Object;
    //   1701: checkcast 536	java/lang/Long
    //   1704: invokevirtual 539	java/lang/Long:longValue	()J
    //   1707: invokevirtual 781	com/google/ads/interactivemedia/v3/internal/cb:a	(Ljava/lang/Object;J)Lcom/google/ads/interactivemedia/v3/internal/mt;
    //   1710: astore_1
    //   1711: aload_1
    //   1712: invokevirtual 624	com/google/ads/interactivemedia/v3/internal/mt:a	()Z
    //   1715: ifne +18 -> 1733
    //   1718: aload_2
    //   1719: getfield 534	android/util/Pair:second	Ljava/lang/Object;
    //   1722: checkcast 536	java/lang/Long
    //   1725: invokevirtual 539	java/lang/Long:longValue	()J
    //   1728: lstore 16
    //   1730: goto +7 -> 1737
    //   1733: lload 10
    //   1735: lstore 16
    //   1737: goto -87 -> 1650
    //   1740: aload_1
    //   1741: aload 6
    //   1743: getfield 456	com/google/ads/interactivemedia/v3/internal/mt:a	Ljava/lang/Object;
    //   1746: invokevirtual 318	com/google/ads/interactivemedia/v3/internal/cr:a	(Ljava/lang/Object;)I
    //   1749: iconst_m1
    //   1750: if_icmpne +81 -> 1831
    //   1753: aload 4
    //   1755: aload 6
    //   1757: getfield 456	com/google/ads/interactivemedia/v3/internal/mt:a	Ljava/lang/Object;
    //   1760: aload 8
    //   1762: aload_1
    //   1763: invokespecial 321	com/google/ads/interactivemedia/v3/internal/bo:a	(Ljava/lang/Object;Lcom/google/ads/interactivemedia/v3/internal/cr;Lcom/google/ads/interactivemedia/v3/internal/cr;)Ljava/lang/Object;
    //   1766: astore_2
    //   1767: aload_2
    //   1768: ifnonnull +10 -> 1778
    //   1771: aload_0
    //   1772: invokespecial 778	com/google/ads/interactivemedia/v3/internal/bo:h	()V
    //   1775: goto +2747 -> 4522
    //   1778: aload 4
    //   1780: aload_1
    //   1781: aload_1
    //   1782: aload_2
    //   1783: aload 4
    //   1785: getfield 172	com/google/ads/interactivemedia/v3/internal/bo:k	Lcom/google/ads/interactivemedia/v3/internal/ct;
    //   1788: invokevirtual 459	com/google/ads/interactivemedia/v3/internal/cr:a	(Ljava/lang/Object;Lcom/google/ads/interactivemedia/v3/internal/ct;)Lcom/google/ads/interactivemedia/v3/internal/ct;
    //   1791: getfield 325	com/google/ads/interactivemedia/v3/internal/ct:b	I
    //   1794: ldc2_w 121
    //   1797: invokespecial 328	com/google/ads/interactivemedia/v3/internal/bo:b	(Lcom/google/ads/interactivemedia/v3/internal/cr;IJ)Landroid/util/Pair;
    //   1800: astore_1
    //   1801: aload_1
    //   1802: getfield 534	android/util/Pair:second	Ljava/lang/Object;
    //   1805: checkcast 536	java/lang/Long
    //   1808: invokevirtual 539	java/lang/Long:longValue	()J
    //   1811: lstore 16
    //   1813: aload 4
    //   1815: getfield 102	com/google/ads/interactivemedia/v3/internal/bo:r	Lcom/google/ads/interactivemedia/v3/internal/cb;
    //   1818: aload_1
    //   1819: getfield 315	android/util/Pair:first	Ljava/lang/Object;
    //   1822: lload 16
    //   1824: invokevirtual 781	com/google/ads/interactivemedia/v3/internal/cb:a	(Ljava/lang/Object;J)Lcom/google/ads/interactivemedia/v3/internal/mt;
    //   1827: astore_1
    //   1828: goto -178 -> 1650
    //   1831: aload 4
    //   1833: getfield 102	com/google/ads/interactivemedia/v3/internal/bo:r	Lcom/google/ads/interactivemedia/v3/internal/cb;
    //   1836: aload 4
    //   1838: getfield 129	com/google/ads/interactivemedia/v3/internal/bo:t	Lcom/google/ads/interactivemedia/v3/internal/cd;
    //   1841: getfield 343	com/google/ads/interactivemedia/v3/internal/cd:b	Lcom/google/ads/interactivemedia/v3/internal/mt;
    //   1844: getfield 456	com/google/ads/interactivemedia/v3/internal/mt:a	Ljava/lang/Object;
    //   1847: lload 10
    //   1849: invokevirtual 781	com/google/ads/interactivemedia/v3/internal/cb:a	(Ljava/lang/Object;J)Lcom/google/ads/interactivemedia/v3/internal/mt;
    //   1852: astore_2
    //   1853: aload_2
    //   1854: astore_1
    //   1855: aload 4
    //   1857: getfield 129	com/google/ads/interactivemedia/v3/internal/bo:t	Lcom/google/ads/interactivemedia/v3/internal/cd;
    //   1860: getfield 343	com/google/ads/interactivemedia/v3/internal/cd:b	Lcom/google/ads/interactivemedia/v3/internal/mt;
    //   1863: invokevirtual 624	com/google/ads/interactivemedia/v3/internal/mt:a	()Z
    //   1866: ifne +21 -> 1887
    //   1869: aload_2
    //   1870: astore_1
    //   1871: aload_2
    //   1872: invokevirtual 624	com/google/ads/interactivemedia/v3/internal/mt:a	()Z
    //   1875: ifne +12 -> 1887
    //   1878: aload 4
    //   1880: getfield 129	com/google/ads/interactivemedia/v3/internal/bo:t	Lcom/google/ads/interactivemedia/v3/internal/cd;
    //   1883: getfield 343	com/google/ads/interactivemedia/v3/internal/cd:b	Lcom/google/ads/interactivemedia/v3/internal/mt;
    //   1886: astore_1
    //   1887: lload 10
    //   1889: lstore 16
    //   1891: aload 4
    //   1893: getfield 129	com/google/ads/interactivemedia/v3/internal/bo:t	Lcom/google/ads/interactivemedia/v3/internal/cd;
    //   1896: getfield 343	com/google/ads/interactivemedia/v3/internal/cd:b	Lcom/google/ads/interactivemedia/v3/internal/mt;
    //   1899: aload_1
    //   1900: invokevirtual 236	com/google/ads/interactivemedia/v3/internal/mt:equals	(Ljava/lang/Object;)Z
    //   1903: ifeq +195 -> 2098
    //   1906: lload 10
    //   1908: lload 16
    //   1910: lcmp
    //   1911: ifne +187 -> 2098
    //   1914: aload 4
    //   1916: getfield 102	com/google/ads/interactivemedia/v3/internal/bo:r	Lcom/google/ads/interactivemedia/v3/internal/cb;
    //   1919: astore_1
    //   1920: aload 4
    //   1922: getfield 367	com/google/ads/interactivemedia/v3/internal/bo:E	J
    //   1925: lstore 21
    //   1927: aload_1
    //   1928: invokevirtual 211	com/google/ads/interactivemedia/v3/internal/cb:d	()Lcom/google/ads/interactivemedia/v3/internal/bz;
    //   1931: astore_2
    //   1932: aload_2
    //   1933: ifnonnull +9 -> 1942
    //   1936: lconst_0
    //   1937: lstore 10
    //   1939: goto +135 -> 2074
    //   1942: aload_2
    //   1943: invokevirtual 245	com/google/ads/interactivemedia/v3/internal/bz:a	()J
    //   1946: lstore 10
    //   1948: lload 10
    //   1950: lstore 16
    //   1952: aload_2
    //   1953: getfield 238	com/google/ads/interactivemedia/v3/internal/bz:d	Z
    //   1956: ifeq +114 -> 2070
    //   1959: iconst_0
    //   1960: istore_3
    //   1961: aload 4
    //   1963: getfield 79	com/google/ads/interactivemedia/v3/internal/bo:a	[Lcom/google/ads/interactivemedia/v3/internal/cj;
    //   1966: astore 8
    //   1968: lload 10
    //   1970: lstore 16
    //   1972: iload_3
    //   1973: aload 8
    //   1975: arraylength
    //   1976: if_icmpge +94 -> 2070
    //   1979: lload 10
    //   1981: lstore 16
    //   1983: aload 8
    //   1985: iload_3
    //   1986: aaload
    //   1987: invokeinterface 395 1 0
    //   1992: ifeq +68 -> 2060
    //   1995: lload 10
    //   1997: lstore 16
    //   1999: aload 4
    //   2001: getfield 79	com/google/ads/interactivemedia/v3/internal/bo:a	[Lcom/google/ads/interactivemedia/v3/internal/cj;
    //   2004: iload_3
    //   2005: aaload
    //   2006: invokeinterface 401 1 0
    //   2011: aload_2
    //   2012: getfield 404	com/google/ads/interactivemedia/v3/internal/bz:c	[Lcom/google/ads/interactivemedia/v3/internal/nw;
    //   2015: iload_3
    //   2016: aaload
    //   2017: if_acmpne +43 -> 2060
    //   2020: aload 4
    //   2022: getfield 79	com/google/ads/interactivemedia/v3/internal/bo:a	[Lcom/google/ads/interactivemedia/v3/internal/cj;
    //   2025: iload_3
    //   2026: aaload
    //   2027: invokeinterface 786 1 0
    //   2032: lstore 16
    //   2034: lload 16
    //   2036: ldc2_w 638
    //   2039: lcmp
    //   2040: ifne +11 -> 2051
    //   2043: ldc2_w 638
    //   2046: lstore 10
    //   2048: goto +26 -> 2074
    //   2051: lload 16
    //   2053: lload 10
    //   2055: invokestatic 555	java/lang/Math:max	(JJ)J
    //   2058: lstore 16
    //   2060: iinc 3 1
    //   2063: lload 16
    //   2065: lstore 10
    //   2067: goto -106 -> 1961
    //   2070: lload 16
    //   2072: lstore 10
    //   2074: aload_1
    //   2075: lload 21
    //   2077: lload 10
    //   2079: invokevirtual 789	com/google/ads/interactivemedia/v3/internal/cb:a	(JJ)Z
    //   2082: istore 9
    //   2084: iload 9
    //   2086: ifne +9 -> 2095
    //   2089: aload 4
    //   2091: iconst_0
    //   2092: invokespecial 746	com/google/ads/interactivemedia/v3/internal/bo:d	(Z)V
    //   2095: goto +123 -> 2218
    //   2098: aload 4
    //   2100: getfield 102	com/google/ads/interactivemedia/v3/internal/bo:r	Lcom/google/ads/interactivemedia/v3/internal/cb;
    //   2103: invokevirtual 209	com/google/ads/interactivemedia/v3/internal/cb:c	()Lcom/google/ads/interactivemedia/v3/internal/bz;
    //   2106: astore_2
    //   2107: aload_2
    //   2108: ifnull +58 -> 2166
    //   2111: aload_2
    //   2112: invokevirtual 387	com/google/ads/interactivemedia/v3/internal/bz:f	()Lcom/google/ads/interactivemedia/v3/internal/bz;
    //   2115: ifnull +51 -> 2166
    //   2118: aload_2
    //   2119: invokevirtual 387	com/google/ads/interactivemedia/v3/internal/bz:f	()Lcom/google/ads/interactivemedia/v3/internal/bz;
    //   2122: astore 8
    //   2124: aload 8
    //   2126: astore_2
    //   2127: aload 8
    //   2129: getfield 225	com/google/ads/interactivemedia/v3/internal/bz:f	Lcom/google/ads/interactivemedia/v3/internal/cc;
    //   2132: getfield 230	com/google/ads/interactivemedia/v3/internal/cc:a	Lcom/google/ads/interactivemedia/v3/internal/mt;
    //   2135: aload_1
    //   2136: invokevirtual 236	com/google/ads/interactivemedia/v3/internal/mt:equals	(Ljava/lang/Object;)Z
    //   2139: ifeq -28 -> 2111
    //   2142: aload 8
    //   2144: aload 4
    //   2146: getfield 102	com/google/ads/interactivemedia/v3/internal/bo:r	Lcom/google/ads/interactivemedia/v3/internal/cb;
    //   2149: aload 8
    //   2151: getfield 225	com/google/ads/interactivemedia/v3/internal/bz:f	Lcom/google/ads/interactivemedia/v3/internal/cc;
    //   2154: invokevirtual 792	com/google/ads/interactivemedia/v3/internal/cb:a	(Lcom/google/ads/interactivemedia/v3/internal/cc;)Lcom/google/ads/interactivemedia/v3/internal/cc;
    //   2157: putfield 225	com/google/ads/interactivemedia/v3/internal/bz:f	Lcom/google/ads/interactivemedia/v3/internal/cc;
    //   2160: aload 8
    //   2162: astore_2
    //   2163: goto -52 -> 2111
    //   2166: aload_1
    //   2167: invokevirtual 624	com/google/ads/interactivemedia/v3/internal/mt:a	()Z
    //   2170: ifeq +9 -> 2179
    //   2173: lconst_0
    //   2174: lstore 10
    //   2176: goto +7 -> 2183
    //   2179: lload 16
    //   2181: lstore 10
    //   2183: aload 4
    //   2185: aload_1
    //   2186: lload 10
    //   2188: invokespecial 794	com/google/ads/interactivemedia/v3/internal/bo:a	(Lcom/google/ads/interactivemedia/v3/internal/mt;J)J
    //   2191: lstore 10
    //   2193: aload 4
    //   2195: aload 4
    //   2197: getfield 129	com/google/ads/interactivemedia/v3/internal/bo:t	Lcom/google/ads/interactivemedia/v3/internal/cd;
    //   2200: aload_1
    //   2201: lload 10
    //   2203: lload 16
    //   2205: aload_0
    //   2206: invokespecial 607	com/google/ads/interactivemedia/v3/internal/bo:l	()J
    //   2209: invokevirtual 610	com/google/ads/interactivemedia/v3/internal/cd:a	(Lcom/google/ads/interactivemedia/v3/internal/mt;JJJ)Lcom/google/ads/interactivemedia/v3/internal/cd;
    //   2212: putfield 129	com/google/ads/interactivemedia/v3/internal/bo:t	Lcom/google/ads/interactivemedia/v3/internal/cd;
    //   2215: goto -120 -> 2095
    //   2218: aload 4
    //   2220: iconst_0
    //   2221: invokespecial 284	com/google/ads/interactivemedia/v3/internal/bo:e	(Z)V
    //   2224: goto +2298 -> 4522
    //   2227: astore_1
    //   2228: iconst_0
    //   2229: istore 9
    //   2231: goto +2378 -> 4609
    //   2234: astore_1
    //   2235: goto +4 -> 2239
    //   2238: astore_1
    //   2239: goto +2302 -> 4541
    //   2242: astore_1
    //   2243: goto +2287 -> 4530
    //   2246: astore_1
    //   2247: goto +2407 -> 4654
    //   2250: astore_1
    //   2251: iconst_0
    //   2252: istore 9
    //   2254: goto +2355 -> 4609
    //   2257: aload_0
    //   2258: iconst_1
    //   2259: iconst_1
    //   2260: iconst_1
    //   2261: iconst_1
    //   2262: iconst_0
    //   2263: invokespecial 431	com/google/ads/interactivemedia/v3/internal/bo:a	(ZZZZZ)V
    //   2266: aload_2
    //   2267: getfield 85	com/google/ads/interactivemedia/v3/internal/bo:e	Lcom/google/ads/interactivemedia/v3/internal/ca;
    //   2270: invokevirtual 796	com/google/ads/interactivemedia/v3/internal/ca:c	()V
    //   2273: aload_2
    //   2274: iconst_1
    //   2275: invokespecial 220	com/google/ads/interactivemedia/v3/internal/bo:a	(I)V
    //   2278: aload_2
    //   2279: getfield 186	com/google/ads/interactivemedia/v3/internal/bo:h	Landroid/os/HandlerThread;
    //   2282: invokevirtual 799	android/os/HandlerThread:quit	()Z
    //   2285: pop
    //   2286: aload_0
    //   2287: monitorenter
    //   2288: aload_2
    //   2289: iconst_1
    //   2290: putfield 656	com/google/ads/interactivemedia/v3/internal/bo:w	Z
    //   2293: aload_0
    //   2294: invokevirtual 741	java/lang/Object:notifyAll	()V
    //   2297: aload_0
    //   2298: monitorexit
    //   2299: iconst_1
    //   2300: ireturn
    //   2301: astore_1
    //   2302: aload_0
    //   2303: monitorexit
    //   2304: aload_1
    //   2305: athrow
    //   2306: aload_1
    //   2307: getfield 707	android/os/Message:arg1	I
    //   2310: istore_3
    //   2311: iload_3
    //   2312: ifeq +9 -> 2321
    //   2315: iconst_1
    //   2316: istore 9
    //   2318: goto +6 -> 2324
    //   2321: iconst_0
    //   2322: istore 9
    //   2324: aload_2
    //   2325: iconst_0
    //   2326: iload 9
    //   2328: iconst_1
    //   2329: invokespecial 801	com/google/ads/interactivemedia/v3/internal/bo:a	(ZZZ)V
    //   2332: goto +2190 -> 4522
    //   2335: aload_2
    //   2336: aload_1
    //   2337: getfield 704	android/os/Message:obj	Ljava/lang/Object;
    //   2340: checkcast 116	com/google/ads/interactivemedia/v3/internal/cn
    //   2343: putfield 120	com/google/ads/interactivemedia/v3/internal/bo:s	Lcom/google/ads/interactivemedia/v3/internal/cn;
    //   2346: goto +2176 -> 4522
    //   2349: aload_1
    //   2350: getfield 704	android/os/Message:obj	Ljava/lang/Object;
    //   2353: checkcast 645	com/google/ads/interactivemedia/v3/internal/cg
    //   2356: astore_1
    //   2357: aload_2
    //   2358: getfield 155	com/google/ads/interactivemedia/v3/internal/bo:n	Lcom/google/ads/interactivemedia/v3/internal/ay;
    //   2361: aload_1
    //   2362: invokevirtual 803	com/google/ads/interactivemedia/v3/internal/ay:a	(Lcom/google/ads/interactivemedia/v3/internal/cg;)V
    //   2365: aload_2
    //   2366: aload_2
    //   2367: getfield 155	com/google/ads/interactivemedia/v3/internal/bo:n	Lcom/google/ads/interactivemedia/v3/internal/ay;
    //   2370: invokevirtual 643	com/google/ads/interactivemedia/v3/internal/ay:d	()Lcom/google/ads/interactivemedia/v3/internal/cg;
    //   2373: iconst_1
    //   2374: invokespecial 669	com/google/ads/interactivemedia/v3/internal/bo:a	(Lcom/google/ads/interactivemedia/v3/internal/cg;Z)V
    //   2377: goto +2145 -> 4522
    //   2380: aload_1
    //   2381: getfield 704	android/os/Message:obj	Ljava/lang/Object;
    //   2384: checkcast 297	com/google/ads/interactivemedia/v3/internal/bu
    //   2387: astore 4
    //   2389: aload_2
    //   2390: getfield 136	com/google/ads/interactivemedia/v3/internal/bo:o	Lcom/google/ads/interactivemedia/v3/internal/br;
    //   2393: iconst_1
    //   2394: invokevirtual 434	com/google/ads/interactivemedia/v3/internal/br:a	(I)V
    //   2397: aload_2
    //   2398: aload 4
    //   2400: iconst_1
    //   2401: invokespecial 531	com/google/ads/interactivemedia/v3/internal/bo:a	(Lcom/google/ads/interactivemedia/v3/internal/bu;Z)Landroid/util/Pair;
    //   2404: astore 8
    //   2406: aload 8
    //   2408: ifnonnull +38 -> 2446
    //   2411: aload_2
    //   2412: getfield 129	com/google/ads/interactivemedia/v3/internal/bo:t	Lcom/google/ads/interactivemedia/v3/internal/cd;
    //   2415: aload_2
    //   2416: getfield 93	com/google/ads/interactivemedia/v3/internal/bo:A	Z
    //   2419: aload_2
    //   2420: getfield 167	com/google/ads/interactivemedia/v3/internal/bo:j	Lcom/google/ads/interactivemedia/v3/internal/cw;
    //   2423: aload_2
    //   2424: getfield 172	com/google/ads/interactivemedia/v3/internal/bo:k	Lcom/google/ads/interactivemedia/v3/internal/ct;
    //   2427: invokevirtual 493	com/google/ads/interactivemedia/v3/internal/cd:a	(ZLcom/google/ads/interactivemedia/v3/internal/cw;Lcom/google/ads/interactivemedia/v3/internal/ct;)Lcom/google/ads/interactivemedia/v3/internal/mt;
    //   2430: astore_1
    //   2431: ldc2_w 121
    //   2434: lstore 10
    //   2436: iconst_1
    //   2437: istore_3
    //   2438: ldc2_w 121
    //   2441: lstore 16
    //   2443: goto +96 -> 2539
    //   2446: aload 8
    //   2448: getfield 315	android/util/Pair:first	Ljava/lang/Object;
    //   2451: astore_1
    //   2452: aload 8
    //   2454: getfield 534	android/util/Pair:second	Ljava/lang/Object;
    //   2457: checkcast 536	java/lang/Long
    //   2460: invokevirtual 539	java/lang/Long:longValue	()J
    //   2463: lstore 10
    //   2465: aload_2
    //   2466: getfield 102	com/google/ads/interactivemedia/v3/internal/bo:r	Lcom/google/ads/interactivemedia/v3/internal/cb;
    //   2469: aload_1
    //   2470: lload 10
    //   2472: invokevirtual 781	com/google/ads/interactivemedia/v3/internal/cb:a	(Ljava/lang/Object;J)Lcom/google/ads/interactivemedia/v3/internal/mt;
    //   2475: astore_1
    //   2476: aload_1
    //   2477: invokevirtual 624	com/google/ads/interactivemedia/v3/internal/mt:a	()Z
    //   2480: ifeq +15 -> 2495
    //   2483: lload 10
    //   2485: lstore 16
    //   2487: lconst_0
    //   2488: lstore 10
    //   2490: iconst_1
    //   2491: istore_3
    //   2492: goto +47 -> 2539
    //   2495: aload 8
    //   2497: getfield 534	android/util/Pair:second	Ljava/lang/Object;
    //   2500: checkcast 536	java/lang/Long
    //   2503: invokevirtual 539	java/lang/Long:longValue	()J
    //   2506: lstore 21
    //   2508: aload 4
    //   2510: getfield 306	com/google/ads/interactivemedia/v3/internal/bu:c	J
    //   2513: lstore 16
    //   2515: lload 16
    //   2517: ldc2_w 121
    //   2520: lcmp
    //   2521: ifne +8 -> 2529
    //   2524: iconst_1
    //   2525: istore_3
    //   2526: goto +5 -> 2531
    //   2529: iconst_0
    //   2530: istore_3
    //   2531: lload 10
    //   2533: lstore 16
    //   2535: lload 21
    //   2537: lstore 10
    //   2539: aload_2
    //   2540: getfield 495	com/google/ads/interactivemedia/v3/internal/bo:u	Lcom/google/ads/interactivemedia/v3/internal/mq;
    //   2543: ifnull +216 -> 2759
    //   2546: aload_2
    //   2547: getfield 433	com/google/ads/interactivemedia/v3/internal/bo:C	I
    //   2550: ifle +6 -> 2556
    //   2553: goto +206 -> 2759
    //   2556: lload 10
    //   2558: ldc2_w 121
    //   2561: lcmp
    //   2562: ifne +20 -> 2582
    //   2565: aload_2
    //   2566: iconst_4
    //   2567: invokespecial 220	com/google/ads/interactivemedia/v3/internal/bo:a	(I)V
    //   2570: aload_0
    //   2571: iconst_0
    //   2572: iconst_0
    //   2573: iconst_1
    //   2574: iconst_0
    //   2575: iconst_1
    //   2576: invokespecial 431	com/google/ads/interactivemedia/v3/internal/bo:a	(ZZZZZ)V
    //   2579: goto +186 -> 2765
    //   2582: aload_1
    //   2583: aload_2
    //   2584: getfield 129	com/google/ads/interactivemedia/v3/internal/bo:t	Lcom/google/ads/interactivemedia/v3/internal/cd;
    //   2587: getfield 343	com/google/ads/interactivemedia/v3/internal/cd:b	Lcom/google/ads/interactivemedia/v3/internal/mt;
    //   2590: invokevirtual 236	com/google/ads/interactivemedia/v3/internal/mt:equals	(Ljava/lang/Object;)Z
    //   2593: ifeq +124 -> 2717
    //   2596: aload_2
    //   2597: getfield 102	com/google/ads/interactivemedia/v3/internal/bo:r	Lcom/google/ads/interactivemedia/v3/internal/cb;
    //   2600: invokevirtual 209	com/google/ads/interactivemedia/v3/internal/cb:c	()Lcom/google/ads/interactivemedia/v3/internal/bz;
    //   2603: astore 4
    //   2605: aload 4
    //   2607: ifnull +39 -> 2646
    //   2610: aload 4
    //   2612: getfield 238	com/google/ads/interactivemedia/v3/internal/bz:d	Z
    //   2615: ifeq +31 -> 2646
    //   2618: lload 10
    //   2620: lconst_0
    //   2621: lcmp
    //   2622: ifeq +24 -> 2646
    //   2625: aload 4
    //   2627: getfield 259	com/google/ads/interactivemedia/v3/internal/bz:a	Lcom/google/ads/interactivemedia/v3/internal/mo;
    //   2630: lload 10
    //   2632: aload_2
    //   2633: getfield 120	com/google/ads/interactivemedia/v3/internal/bo:s	Lcom/google/ads/interactivemedia/v3/internal/cn;
    //   2636: invokeinterface 806 4 0
    //   2641: lstore 21
    //   2643: goto +7 -> 2650
    //   2646: lload 10
    //   2648: lstore 21
    //   2650: lload 21
    //   2652: lstore 18
    //   2654: lload 21
    //   2656: invokestatic 808	com/google/ads/interactivemedia/v3/internal/av:a	(J)J
    //   2659: aload_2
    //   2660: getfield 129	com/google/ads/interactivemedia/v3/internal/bo:t	Lcom/google/ads/interactivemedia/v3/internal/cd;
    //   2663: getfield 362	com/google/ads/interactivemedia/v3/internal/cd:m	J
    //   2666: invokestatic 808	com/google/ads/interactivemedia/v3/internal/av:a	(J)J
    //   2669: lcmp
    //   2670: ifne +51 -> 2721
    //   2673: aload_2
    //   2674: getfield 129	com/google/ads/interactivemedia/v3/internal/bo:t	Lcom/google/ads/interactivemedia/v3/internal/cd;
    //   2677: getfield 362	com/google/ads/interactivemedia/v3/internal/cd:m	J
    //   2680: lstore 21
    //   2682: aload_2
    //   2683: aload_2
    //   2684: getfield 129	com/google/ads/interactivemedia/v3/internal/bo:t	Lcom/google/ads/interactivemedia/v3/internal/cd;
    //   2687: aload_1
    //   2688: lload 21
    //   2690: lload 16
    //   2692: aload_0
    //   2693: invokespecial 607	com/google/ads/interactivemedia/v3/internal/bo:l	()J
    //   2696: invokevirtual 610	com/google/ads/interactivemedia/v3/internal/cd:a	(Lcom/google/ads/interactivemedia/v3/internal/mt;JJJ)Lcom/google/ads/interactivemedia/v3/internal/cd;
    //   2699: putfield 129	com/google/ads/interactivemedia/v3/internal/bo:t	Lcom/google/ads/interactivemedia/v3/internal/cd;
    //   2702: iload_3
    //   2703: ifeq +1819 -> 4522
    //   2706: aload_2
    //   2707: getfield 136	com/google/ads/interactivemedia/v3/internal/bo:o	Lcom/google/ads/interactivemedia/v3/internal/br;
    //   2710: iconst_2
    //   2711: invokevirtual 611	com/google/ads/interactivemedia/v3/internal/br:b	(I)V
    //   2714: goto +1808 -> 4522
    //   2717: lload 10
    //   2719: lstore 18
    //   2721: aload_2
    //   2722: aload_1
    //   2723: lload 18
    //   2725: invokespecial 794	com/google/ads/interactivemedia/v3/internal/bo:a	(Lcom/google/ads/interactivemedia/v3/internal/mt;J)J
    //   2728: lstore 21
    //   2730: lload 10
    //   2732: lload 21
    //   2734: lcmp
    //   2735: ifeq +9 -> 2744
    //   2738: iconst_1
    //   2739: istore 7
    //   2741: goto +6 -> 2747
    //   2744: iconst_0
    //   2745: istore 7
    //   2747: iload_3
    //   2748: iload 7
    //   2750: ior
    //   2751: istore_3
    //   2752: lload 21
    //   2754: lstore 10
    //   2756: goto +9 -> 2765
    //   2759: aload_2
    //   2760: aload 4
    //   2762: putfield 454	com/google/ads/interactivemedia/v3/internal/bo:D	Lcom/google/ads/interactivemedia/v3/internal/bu;
    //   2765: aload_2
    //   2766: aload_2
    //   2767: getfield 129	com/google/ads/interactivemedia/v3/internal/bo:t	Lcom/google/ads/interactivemedia/v3/internal/cd;
    //   2770: aload_1
    //   2771: lload 10
    //   2773: lload 16
    //   2775: aload_0
    //   2776: invokespecial 607	com/google/ads/interactivemedia/v3/internal/bo:l	()J
    //   2779: invokevirtual 610	com/google/ads/interactivemedia/v3/internal/cd:a	(Lcom/google/ads/interactivemedia/v3/internal/mt;JJJ)Lcom/google/ads/interactivemedia/v3/internal/cd;
    //   2782: putfield 129	com/google/ads/interactivemedia/v3/internal/bo:t	Lcom/google/ads/interactivemedia/v3/internal/cd;
    //   2785: iload_3
    //   2786: ifeq +1736 -> 4522
    //   2789: aload_2
    //   2790: getfield 136	com/google/ads/interactivemedia/v3/internal/bo:o	Lcom/google/ads/interactivemedia/v3/internal/br;
    //   2793: iconst_2
    //   2794: invokevirtual 611	com/google/ads/interactivemedia/v3/internal/br:b	(I)V
    //   2797: goto +1725 -> 4522
    //   2800: astore 4
    //   2802: aload_2
    //   2803: aload_2
    //   2804: getfield 129	com/google/ads/interactivemedia/v3/internal/bo:t	Lcom/google/ads/interactivemedia/v3/internal/cd;
    //   2807: aload_1
    //   2808: lload 10
    //   2810: lload 16
    //   2812: aload_0
    //   2813: invokespecial 607	com/google/ads/interactivemedia/v3/internal/bo:l	()J
    //   2816: invokevirtual 610	com/google/ads/interactivemedia/v3/internal/cd:a	(Lcom/google/ads/interactivemedia/v3/internal/mt;JJJ)Lcom/google/ads/interactivemedia/v3/internal/cd;
    //   2819: putfield 129	com/google/ads/interactivemedia/v3/internal/bo:t	Lcom/google/ads/interactivemedia/v3/internal/cd;
    //   2822: iload_3
    //   2823: ifeq +11 -> 2834
    //   2826: aload_2
    //   2827: getfield 136	com/google/ads/interactivemedia/v3/internal/bo:o	Lcom/google/ads/interactivemedia/v3/internal/br;
    //   2830: iconst_2
    //   2831: invokevirtual 611	com/google/ads/interactivemedia/v3/internal/br:b	(I)V
    //   2834: aload 4
    //   2836: athrow
    //   2837: aload_2
    //   2838: getfield 97	com/google/ads/interactivemedia/v3/internal/bo:q	Lcom/google/ads/interactivemedia/v3/internal/vh;
    //   2841: invokeinterface 809 1 0
    //   2846: lstore 10
    //   2848: aload_2
    //   2849: getfield 495	com/google/ads/interactivemedia/v3/internal/bo:u	Lcom/google/ads/interactivemedia/v3/internal/mq;
    //   2852: astore_1
    //   2853: aload_1
    //   2854: ifnull +757 -> 3611
    //   2857: aload_2
    //   2858: getfield 433	com/google/ads/interactivemedia/v3/internal/bo:C	I
    //   2861: ifle +10 -> 2871
    //   2864: aload_1
    //   2865: invokevirtual 810	com/google/ads/interactivemedia/v3/internal/mq:a	()V
    //   2868: goto +743 -> 3611
    //   2871: aload_2
    //   2872: getfield 102	com/google/ads/interactivemedia/v3/internal/bo:r	Lcom/google/ads/interactivemedia/v3/internal/cb;
    //   2875: aload_2
    //   2876: getfield 367	com/google/ads/interactivemedia/v3/internal/bo:E	J
    //   2879: invokevirtual 769	com/google/ads/interactivemedia/v3/internal/cb:a	(J)V
    //   2882: aload_2
    //   2883: getfield 102	com/google/ads/interactivemedia/v3/internal/bo:r	Lcom/google/ads/interactivemedia/v3/internal/cb;
    //   2886: invokevirtual 811	com/google/ads/interactivemedia/v3/internal/cb:a	()Z
    //   2889: ifeq +156 -> 3045
    //   2892: aload_2
    //   2893: getfield 102	com/google/ads/interactivemedia/v3/internal/bo:r	Lcom/google/ads/interactivemedia/v3/internal/cb;
    //   2896: aload_2
    //   2897: getfield 367	com/google/ads/interactivemedia/v3/internal/bo:E	J
    //   2900: aload_2
    //   2901: getfield 129	com/google/ads/interactivemedia/v3/internal/bo:t	Lcom/google/ads/interactivemedia/v3/internal/cd;
    //   2904: invokevirtual 814	com/google/ads/interactivemedia/v3/internal/cb:a	(JLcom/google/ads/interactivemedia/v3/internal/cd;)Lcom/google/ads/interactivemedia/v3/internal/cc;
    //   2907: astore_1
    //   2908: aload_1
    //   2909: ifnonnull +57 -> 2966
    //   2912: aload_2
    //   2913: getfield 102	com/google/ads/interactivemedia/v3/internal/bo:r	Lcom/google/ads/interactivemedia/v3/internal/cb;
    //   2916: invokevirtual 549	com/google/ads/interactivemedia/v3/internal/cb:b	()Lcom/google/ads/interactivemedia/v3/internal/bz;
    //   2919: ifnull +37 -> 2956
    //   2922: aload_2
    //   2923: getfield 162	com/google/ads/interactivemedia/v3/internal/bo:v	[Lcom/google/ads/interactivemedia/v3/internal/cj;
    //   2926: astore_1
    //   2927: aload_1
    //   2928: arraylength
    //   2929: istore 7
    //   2931: iconst_0
    //   2932: istore_3
    //   2933: iload_3
    //   2934: iload 7
    //   2936: if_icmpge +20 -> 2956
    //   2939: aload_1
    //   2940: iload_3
    //   2941: aaload
    //   2942: invokeinterface 635 1 0
    //   2947: ifeq +98 -> 3045
    //   2950: iinc 3 1
    //   2953: goto -20 -> 2933
    //   2956: aload_2
    //   2957: getfield 495	com/google/ads/interactivemedia/v3/internal/bo:u	Lcom/google/ads/interactivemedia/v3/internal/mq;
    //   2960: invokevirtual 810	com/google/ads/interactivemedia/v3/internal/mq:a	()V
    //   2963: goto +82 -> 3045
    //   2966: aload_2
    //   2967: getfield 102	com/google/ads/interactivemedia/v3/internal/bo:r	Lcom/google/ads/interactivemedia/v3/internal/cb;
    //   2970: aload_2
    //   2971: getfield 140	com/google/ads/interactivemedia/v3/internal/bo:b	[Lcom/google/ads/interactivemedia/v3/internal/cm;
    //   2974: aload_2
    //   2975: getfield 81	com/google/ads/interactivemedia/v3/internal/bo:c	Lcom/google/ads/interactivemedia/v3/internal/te;
    //   2978: aload_2
    //   2979: getfield 85	com/google/ads/interactivemedia/v3/internal/bo:e	Lcom/google/ads/interactivemedia/v3/internal/ca;
    //   2982: invokevirtual 817	com/google/ads/interactivemedia/v3/internal/ca:d	()Lcom/google/ads/interactivemedia/v3/internal/tk;
    //   2985: aload_2
    //   2986: getfield 495	com/google/ads/interactivemedia/v3/internal/bo:u	Lcom/google/ads/interactivemedia/v3/internal/mq;
    //   2989: aload_1
    //   2990: aload_2
    //   2991: getfield 83	com/google/ads/interactivemedia/v3/internal/bo:d	Lcom/google/ads/interactivemedia/v3/internal/tg;
    //   2994: invokevirtual 820	com/google/ads/interactivemedia/v3/internal/cb:a	([Lcom/google/ads/interactivemedia/v3/internal/cm;Lcom/google/ads/interactivemedia/v3/internal/te;Lcom/google/ads/interactivemedia/v3/internal/tk;Lcom/google/ads/interactivemedia/v3/internal/mq;Lcom/google/ads/interactivemedia/v3/internal/cc;Lcom/google/ads/interactivemedia/v3/internal/tg;)Lcom/google/ads/interactivemedia/v3/internal/bz;
    //   2997: astore 4
    //   2999: aload 4
    //   3001: getfield 259	com/google/ads/interactivemedia/v3/internal/bz:a	Lcom/google/ads/interactivemedia/v3/internal/mo;
    //   3004: aload_2
    //   3005: aload_1
    //   3006: getfield 760	com/google/ads/interactivemedia/v3/internal/cc:b	J
    //   3009: invokeinterface 823 4 0
    //   3014: aload_2
    //   3015: iconst_1
    //   3016: invokespecial 467	com/google/ads/interactivemedia/v3/internal/bo:c	(Z)V
    //   3019: aload_2
    //   3020: getfield 102	com/google/ads/interactivemedia/v3/internal/bo:r	Lcom/google/ads/interactivemedia/v3/internal/cb;
    //   3023: invokevirtual 209	com/google/ads/interactivemedia/v3/internal/cb:c	()Lcom/google/ads/interactivemedia/v3/internal/bz;
    //   3026: aload 4
    //   3028: if_acmpne +12 -> 3040
    //   3031: aload_2
    //   3032: aload 4
    //   3034: invokevirtual 824	com/google/ads/interactivemedia/v3/internal/bz:b	()J
    //   3037: invokespecial 269	com/google/ads/interactivemedia/v3/internal/bo:a	(J)V
    //   3040: aload_2
    //   3041: iconst_0
    //   3042: invokespecial 284	com/google/ads/interactivemedia/v3/internal/bo:e	(Z)V
    //   3045: aload_2
    //   3046: getfield 102	com/google/ads/interactivemedia/v3/internal/bo:r	Lcom/google/ads/interactivemedia/v3/internal/cb;
    //   3049: invokevirtual 549	com/google/ads/interactivemedia/v3/internal/cb:b	()Lcom/google/ads/interactivemedia/v3/internal/bz;
    //   3052: astore_1
    //   3053: aload_1
    //   3054: ifnull +30 -> 3084
    //   3057: aload_1
    //   3058: invokevirtual 826	com/google/ads/interactivemedia/v3/internal/bz:c	()Z
    //   3061: ifeq +6 -> 3067
    //   3064: goto +20 -> 3084
    //   3067: aload_2
    //   3068: getfield 129	com/google/ads/interactivemedia/v3/internal/bo:t	Lcom/google/ads/interactivemedia/v3/internal/cd;
    //   3071: getfield 351	com/google/ads/interactivemedia/v3/internal/cd:g	Z
    //   3074: ifne +15 -> 3089
    //   3077: aload_0
    //   3078: invokespecial 271	com/google/ads/interactivemedia/v3/internal/bo:k	()V
    //   3081: goto +8 -> 3089
    //   3084: aload_2
    //   3085: iconst_0
    //   3086: invokespecial 467	com/google/ads/interactivemedia/v3/internal/bo:c	(Z)V
    //   3089: aload_2
    //   3090: getfield 102	com/google/ads/interactivemedia/v3/internal/bo:r	Lcom/google/ads/interactivemedia/v3/internal/cb;
    //   3093: invokevirtual 211	com/google/ads/interactivemedia/v3/internal/cb:d	()Lcom/google/ads/interactivemedia/v3/internal/bz;
    //   3096: astore_1
    //   3097: aload_1
    //   3098: ifnull +307 -> 3405
    //   3101: aload_1
    //   3102: invokevirtual 387	com/google/ads/interactivemedia/v3/internal/bz:f	()Lcom/google/ads/interactivemedia/v3/internal/bz;
    //   3105: ifnonnull +82 -> 3187
    //   3108: aload_1
    //   3109: getfield 225	com/google/ads/interactivemedia/v3/internal/bz:f	Lcom/google/ads/interactivemedia/v3/internal/cc;
    //   3112: getfield 827	com/google/ads/interactivemedia/v3/internal/cc:g	Z
    //   3115: ifeq +290 -> 3405
    //   3118: iconst_0
    //   3119: istore_3
    //   3120: aload_2
    //   3121: getfield 79	com/google/ads/interactivemedia/v3/internal/bo:a	[Lcom/google/ads/interactivemedia/v3/internal/cj;
    //   3124: astore 4
    //   3126: iload_3
    //   3127: aload 4
    //   3129: arraylength
    //   3130: if_icmpge +275 -> 3405
    //   3133: aload 4
    //   3135: iload_3
    //   3136: aaload
    //   3137: astore 8
    //   3139: aload_1
    //   3140: getfield 404	com/google/ads/interactivemedia/v3/internal/bz:c	[Lcom/google/ads/interactivemedia/v3/internal/nw;
    //   3143: iload_3
    //   3144: aaload
    //   3145: astore 4
    //   3147: aload 4
    //   3149: ifnull +32 -> 3181
    //   3152: aload 8
    //   3154: invokeinterface 401 1 0
    //   3159: aload 4
    //   3161: if_acmpne +20 -> 3181
    //   3164: aload 8
    //   3166: invokeinterface 635 1 0
    //   3171: ifeq +10 -> 3181
    //   3174: aload 8
    //   3176: invokeinterface 636 1 0
    //   3181: iinc 3 1
    //   3184: goto -64 -> 3120
    //   3187: aload_0
    //   3188: invokespecial 828	com/google/ads/interactivemedia/v3/internal/bo:i	()Z
    //   3191: ifeq +214 -> 3405
    //   3194: aload_1
    //   3195: invokevirtual 387	com/google/ads/interactivemedia/v3/internal/bz:f	()Lcom/google/ads/interactivemedia/v3/internal/bz;
    //   3198: getfield 238	com/google/ads/interactivemedia/v3/internal/bz:d	Z
    //   3201: ifeq +204 -> 3405
    //   3204: aload_1
    //   3205: invokevirtual 372	com/google/ads/interactivemedia/v3/internal/bz:h	()Lcom/google/ads/interactivemedia/v3/internal/tg;
    //   3208: astore 8
    //   3210: aload_2
    //   3211: getfield 102	com/google/ads/interactivemedia/v3/internal/bo:r	Lcom/google/ads/interactivemedia/v3/internal/cb;
    //   3214: invokevirtual 830	com/google/ads/interactivemedia/v3/internal/cb:e	()Lcom/google/ads/interactivemedia/v3/internal/bz;
    //   3217: astore_1
    //   3218: aload_1
    //   3219: invokevirtual 372	com/google/ads/interactivemedia/v3/internal/bz:h	()Lcom/google/ads/interactivemedia/v3/internal/tg;
    //   3222: astore 4
    //   3224: aload_1
    //   3225: getfield 259	com/google/ads/interactivemedia/v3/internal/bz:a	Lcom/google/ads/interactivemedia/v3/internal/mo;
    //   3228: invokeinterface 617 1 0
    //   3233: ldc2_w 121
    //   3236: lcmp
    //   3237: ifeq +10 -> 3247
    //   3240: aload_0
    //   3241: invokespecial 831	com/google/ads/interactivemedia/v3/internal/bo:j	()V
    //   3244: goto +161 -> 3405
    //   3247: iconst_0
    //   3248: istore_3
    //   3249: aload_2
    //   3250: getfield 79	com/google/ads/interactivemedia/v3/internal/bo:a	[Lcom/google/ads/interactivemedia/v3/internal/cj;
    //   3253: astore 6
    //   3255: iload_3
    //   3256: aload 6
    //   3258: arraylength
    //   3259: if_icmpge +146 -> 3405
    //   3262: aload 6
    //   3264: iload_3
    //   3265: aaload
    //   3266: astore 12
    //   3268: aload 8
    //   3270: iload_3
    //   3271: invokevirtual 396	com/google/ads/interactivemedia/v3/internal/tg:a	(I)Z
    //   3274: ifeq +125 -> 3399
    //   3277: aload 12
    //   3279: invokeinterface 398 1 0
    //   3284: ifne +115 -> 3399
    //   3287: aload 4
    //   3289: getfield 377	com/google/ads/interactivemedia/v3/internal/tg:c	Lcom/google/ads/interactivemedia/v3/internal/td;
    //   3292: iload_3
    //   3293: invokevirtual 506	com/google/ads/interactivemedia/v3/internal/td:a	(I)Lcom/google/ads/interactivemedia/v3/internal/sy;
    //   3296: astore 6
    //   3298: aload 4
    //   3300: iload_3
    //   3301: invokevirtual 396	com/google/ads/interactivemedia/v3/internal/tg:a	(I)Z
    //   3304: istore 9
    //   3306: aload_2
    //   3307: getfield 140	com/google/ads/interactivemedia/v3/internal/bo:b	[Lcom/google/ads/interactivemedia/v3/internal/cm;
    //   3310: iload_3
    //   3311: aaload
    //   3312: invokevirtual 833	com/google/ads/interactivemedia/v3/internal/cm:a	()I
    //   3315: bipush 6
    //   3317: if_icmpne +9 -> 3326
    //   3320: iconst_1
    //   3321: istore 7
    //   3323: goto +6 -> 3329
    //   3326: iconst_0
    //   3327: istore 7
    //   3329: aload 8
    //   3331: getfield 503	com/google/ads/interactivemedia/v3/internal/tg:b	[Lcom/google/ads/interactivemedia/v3/internal/cl;
    //   3334: iload_3
    //   3335: aaload
    //   3336: astore 15
    //   3338: aload 4
    //   3340: getfield 503	com/google/ads/interactivemedia/v3/internal/tg:b	[Lcom/google/ads/interactivemedia/v3/internal/cl;
    //   3343: iload_3
    //   3344: aaload
    //   3345: astore 20
    //   3347: iload 9
    //   3349: ifeq +43 -> 3392
    //   3352: aload 20
    //   3354: aload 15
    //   3356: invokevirtual 836	com/google/ads/interactivemedia/v3/internal/cl:equals	(Ljava/lang/Object;)Z
    //   3359: ifeq +33 -> 3392
    //   3362: iload 7
    //   3364: ifne +28 -> 3392
    //   3367: aload 12
    //   3369: aload 6
    //   3371: invokestatic 509	com/google/ads/interactivemedia/v3/internal/bo:a	(Lcom/google/ads/interactivemedia/v3/internal/sy;)[Lcom/google/ads/interactivemedia/v3/internal/bw;
    //   3374: aload_1
    //   3375: getfield 404	com/google/ads/interactivemedia/v3/internal/bz:c	[Lcom/google/ads/interactivemedia/v3/internal/nw;
    //   3378: iload_3
    //   3379: aaload
    //   3380: aload_1
    //   3381: invokevirtual 245	com/google/ads/interactivemedia/v3/internal/bz:a	()J
    //   3384: invokeinterface 839 5 0
    //   3389: goto +10 -> 3399
    //   3392: aload 12
    //   3394: invokeinterface 636 1 0
    //   3399: iinc 3 1
    //   3402: goto -153 -> 3249
    //   3405: iconst_0
    //   3406: istore_3
    //   3407: aload_2
    //   3408: getfield 89	com/google/ads/interactivemedia/v3/internal/bo:x	Z
    //   3411: ifeq +63 -> 3474
    //   3414: aload_2
    //   3415: getfield 102	com/google/ads/interactivemedia/v3/internal/bo:r	Lcom/google/ads/interactivemedia/v3/internal/cb;
    //   3418: invokevirtual 209	com/google/ads/interactivemedia/v3/internal/cb:c	()Lcom/google/ads/interactivemedia/v3/internal/bz;
    //   3421: astore_1
    //   3422: aload_1
    //   3423: ifnull +51 -> 3474
    //   3426: aload_1
    //   3427: invokevirtual 387	com/google/ads/interactivemedia/v3/internal/bz:f	()Lcom/google/ads/interactivemedia/v3/internal/bz;
    //   3430: astore 4
    //   3432: aload 4
    //   3434: ifnull +40 -> 3474
    //   3437: aload_1
    //   3438: aload_2
    //   3439: getfield 102	com/google/ads/interactivemedia/v3/internal/bo:r	Lcom/google/ads/interactivemedia/v3/internal/cb;
    //   3442: invokevirtual 211	com/google/ads/interactivemedia/v3/internal/cb:d	()Lcom/google/ads/interactivemedia/v3/internal/bz;
    //   3445: if_acmpne +10 -> 3455
    //   3448: aload_0
    //   3449: invokespecial 828	com/google/ads/interactivemedia/v3/internal/bo:i	()Z
    //   3452: ifeq +22 -> 3474
    //   3455: aload_2
    //   3456: getfield 367	com/google/ads/interactivemedia/v3/internal/bo:E	J
    //   3459: aload 4
    //   3461: invokevirtual 824	com/google/ads/interactivemedia/v3/internal/bz:b	()J
    //   3464: lcmp
    //   3465: iflt +9 -> 3474
    //   3468: iconst_1
    //   3469: istore 7
    //   3471: goto +6 -> 3477
    //   3474: iconst_0
    //   3475: istore 7
    //   3477: iload 7
    //   3479: ifeq +132 -> 3611
    //   3482: iload_3
    //   3483: ifeq +7 -> 3490
    //   3486: aload_0
    //   3487: invokespecial 840	com/google/ads/interactivemedia/v3/internal/bo:c	()V
    //   3490: aload_2
    //   3491: getfield 102	com/google/ads/interactivemedia/v3/internal/bo:r	Lcom/google/ads/interactivemedia/v3/internal/cb;
    //   3494: invokevirtual 209	com/google/ads/interactivemedia/v3/internal/cb:c	()Lcom/google/ads/interactivemedia/v3/internal/bz;
    //   3497: astore 4
    //   3499: aload 4
    //   3501: aload_2
    //   3502: getfield 102	com/google/ads/interactivemedia/v3/internal/bo:r	Lcom/google/ads/interactivemedia/v3/internal/cb;
    //   3505: invokevirtual 211	com/google/ads/interactivemedia/v3/internal/cb:d	()Lcom/google/ads/interactivemedia/v3/internal/bz;
    //   3508: if_acmpne +7 -> 3515
    //   3511: aload_0
    //   3512: invokespecial 831	com/google/ads/interactivemedia/v3/internal/bo:j	()V
    //   3515: aload_2
    //   3516: getfield 102	com/google/ads/interactivemedia/v3/internal/bo:r	Lcom/google/ads/interactivemedia/v3/internal/cb;
    //   3519: invokevirtual 243	com/google/ads/interactivemedia/v3/internal/cb:f	()Lcom/google/ads/interactivemedia/v3/internal/bz;
    //   3522: astore 8
    //   3524: aload_2
    //   3525: aload 4
    //   3527: invokespecial 254	com/google/ads/interactivemedia/v3/internal/bo:a	(Lcom/google/ads/interactivemedia/v3/internal/bz;)V
    //   3530: aload_2
    //   3531: getfield 129	com/google/ads/interactivemedia/v3/internal/bo:t	Lcom/google/ads/interactivemedia/v3/internal/cd;
    //   3534: astore_1
    //   3535: aload 8
    //   3537: getfield 225	com/google/ads/interactivemedia/v3/internal/bz:f	Lcom/google/ads/interactivemedia/v3/internal/cc;
    //   3540: astore 8
    //   3542: aload_2
    //   3543: aload_1
    //   3544: aload 8
    //   3546: getfield 230	com/google/ads/interactivemedia/v3/internal/cc:a	Lcom/google/ads/interactivemedia/v3/internal/mt;
    //   3549: aload 8
    //   3551: getfield 760	com/google/ads/interactivemedia/v3/internal/cc:b	J
    //   3554: aload 8
    //   3556: getfield 841	com/google/ads/interactivemedia/v3/internal/cc:c	J
    //   3559: aload_0
    //   3560: invokespecial 607	com/google/ads/interactivemedia/v3/internal/bo:l	()J
    //   3563: invokevirtual 610	com/google/ads/interactivemedia/v3/internal/cd:a	(Lcom/google/ads/interactivemedia/v3/internal/mt;JJJ)Lcom/google/ads/interactivemedia/v3/internal/cd;
    //   3566: putfield 129	com/google/ads/interactivemedia/v3/internal/bo:t	Lcom/google/ads/interactivemedia/v3/internal/cd;
    //   3569: aload 4
    //   3571: getfield 225	com/google/ads/interactivemedia/v3/internal/bz:f	Lcom/google/ads/interactivemedia/v3/internal/cc;
    //   3574: getfield 843	com/google/ads/interactivemedia/v3/internal/cc:f	Z
    //   3577: ifeq +8 -> 3585
    //   3580: iconst_0
    //   3581: istore_3
    //   3582: goto +5 -> 3587
    //   3585: iconst_3
    //   3586: istore_3
    //   3587: aload_2
    //   3588: getfield 136	com/google/ads/interactivemedia/v3/internal/bo:o	Lcom/google/ads/interactivemedia/v3/internal/br;
    //   3591: iload_3
    //   3592: invokevirtual 611	com/google/ads/interactivemedia/v3/internal/br:b	(I)V
    //   3595: aload_0
    //   3596: invokespecial 765	com/google/ads/interactivemedia/v3/internal/bo:f	()V
    //   3599: iconst_1
    //   3600: istore_3
    //   3601: goto -194 -> 3407
    //   3604: astore_1
    //   3605: iconst_0
    //   3606: istore 9
    //   3608: goto +1001 -> 4609
    //   3611: aload_2
    //   3612: getfield 102	com/google/ads/interactivemedia/v3/internal/bo:r	Lcom/google/ads/interactivemedia/v3/internal/cb;
    //   3615: invokevirtual 209	com/google/ads/interactivemedia/v3/internal/cb:c	()Lcom/google/ads/interactivemedia/v3/internal/bz;
    //   3618: astore_1
    //   3619: aload_1
    //   3620: ifnonnull +15 -> 3635
    //   3623: aload_2
    //   3624: lload 10
    //   3626: ldc2_w 844
    //   3629: invokespecial 847	com/google/ads/interactivemedia/v3/internal/bo:a	(JJ)V
    //   3632: goto +890 -> 4522
    //   3635: ldc_w 849
    //   3638: invokestatic 854	com/google/ads/interactivemedia/v3/internal/rp:b	(Ljava/lang/String;)V
    //   3641: aload_0
    //   3642: invokespecial 765	com/google/ads/interactivemedia/v3/internal/bo:f	()V
    //   3645: aload_1
    //   3646: getfield 238	com/google/ads/interactivemedia/v3/internal/bz:d	Z
    //   3649: ifeq +274 -> 3923
    //   3652: invokestatic 859	android/os/SystemClock:elapsedRealtime	()J
    //   3655: lstore 16
    //   3657: aload_1
    //   3658: getfield 259	com/google/ads/interactivemedia/v3/internal/bz:a	Lcom/google/ads/interactivemedia/v3/internal/mo;
    //   3661: aload_2
    //   3662: getfield 129	com/google/ads/interactivemedia/v3/internal/bo:t	Lcom/google/ads/interactivemedia/v3/internal/cd;
    //   3665: getfield 362	com/google/ads/interactivemedia/v3/internal/cd:m	J
    //   3668: aload_2
    //   3669: getfield 109	com/google/ads/interactivemedia/v3/internal/bo:l	J
    //   3672: lsub
    //   3673: aload_2
    //   3674: getfield 114	com/google/ads/interactivemedia/v3/internal/bo:m	Z
    //   3677: invokeinterface 267 4 0
    //   3682: iconst_0
    //   3683: istore 13
    //   3685: iconst_1
    //   3686: istore 7
    //   3688: iconst_1
    //   3689: istore_3
    //   3690: aload_2
    //   3691: getfield 79	com/google/ads/interactivemedia/v3/internal/bo:a	[Lcom/google/ads/interactivemedia/v3/internal/cj;
    //   3694: astore 4
    //   3696: iload 7
    //   3698: istore 23
    //   3700: iload_3
    //   3701: istore 24
    //   3703: iload 13
    //   3705: aload 4
    //   3707: arraylength
    //   3708: if_icmpge +230 -> 3938
    //   3711: aload 4
    //   3713: iload 13
    //   3715: aaload
    //   3716: astore 4
    //   3718: iload 7
    //   3720: istore 23
    //   3722: iload_3
    //   3723: istore 24
    //   3725: aload 4
    //   3727: invokeinterface 395 1 0
    //   3732: ifeq +178 -> 3910
    //   3735: aload 4
    //   3737: aload_2
    //   3738: getfield 367	com/google/ads/interactivemedia/v3/internal/bo:E	J
    //   3741: lload 16
    //   3743: ldc2_w 860
    //   3746: lmul
    //   3747: invokeinterface 862 5 0
    //   3752: iload 7
    //   3754: ifeq +19 -> 3773
    //   3757: aload 4
    //   3759: invokeinterface 864 1 0
    //   3764: ifeq +9 -> 3773
    //   3767: iconst_1
    //   3768: istore 7
    //   3770: goto +6 -> 3776
    //   3773: iconst_0
    //   3774: istore 7
    //   3776: aload_1
    //   3777: getfield 404	com/google/ads/interactivemedia/v3/internal/bz:c	[Lcom/google/ads/interactivemedia/v3/internal/nw;
    //   3780: iload 13
    //   3782: aaload
    //   3783: aload 4
    //   3785: invokeinterface 401 1 0
    //   3790: if_acmpeq +9 -> 3799
    //   3793: iconst_1
    //   3794: istore 24
    //   3796: goto +6 -> 3802
    //   3799: iconst_0
    //   3800: istore 24
    //   3802: iload 24
    //   3804: ifne +26 -> 3830
    //   3807: aload_1
    //   3808: invokevirtual 387	com/google/ads/interactivemedia/v3/internal/bz:f	()Lcom/google/ads/interactivemedia/v3/internal/bz;
    //   3811: ifnull +19 -> 3830
    //   3814: aload 4
    //   3816: invokeinterface 635 1 0
    //   3821: ifeq +9 -> 3830
    //   3824: iconst_1
    //   3825: istore 23
    //   3827: goto +6 -> 3833
    //   3830: iconst_0
    //   3831: istore 23
    //   3833: iload 24
    //   3835: ifne +37 -> 3872
    //   3838: iload 23
    //   3840: ifne +32 -> 3872
    //   3843: aload 4
    //   3845: invokeinterface 866 1 0
    //   3850: ifne +22 -> 3872
    //   3853: aload 4
    //   3855: invokeinterface 864 1 0
    //   3860: ifeq +6 -> 3866
    //   3863: goto +9 -> 3872
    //   3866: iconst_0
    //   3867: istore 24
    //   3869: goto +6 -> 3875
    //   3872: iconst_1
    //   3873: istore 24
    //   3875: iload_3
    //   3876: ifeq +13 -> 3889
    //   3879: iload 24
    //   3881: ifeq +8 -> 3889
    //   3884: iconst_1
    //   3885: istore_3
    //   3886: goto +5 -> 3891
    //   3889: iconst_0
    //   3890: istore_3
    //   3891: iload 24
    //   3893: ifne +10 -> 3903
    //   3896: aload 4
    //   3898: invokeinterface 868 1 0
    //   3903: iload_3
    //   3904: istore 24
    //   3906: iload 7
    //   3908: istore 23
    //   3910: iinc 13 1
    //   3913: iload 23
    //   3915: istore 7
    //   3917: iload 24
    //   3919: istore_3
    //   3920: goto -230 -> 3690
    //   3923: aload_1
    //   3924: getfield 259	com/google/ads/interactivemedia/v3/internal/bz:a	Lcom/google/ads/interactivemedia/v3/internal/mo;
    //   3927: invokeinterface 871 1 0
    //   3932: iconst_1
    //   3933: istore 23
    //   3935: iconst_1
    //   3936: istore 24
    //   3938: aload_1
    //   3939: getfield 225	com/google/ads/interactivemedia/v3/internal/bz:f	Lcom/google/ads/interactivemedia/v3/internal/cc;
    //   3942: getfield 633	com/google/ads/interactivemedia/v3/internal/cc:e	J
    //   3945: lstore 16
    //   3947: iload 23
    //   3949: ifeq +54 -> 4003
    //   3952: aload_1
    //   3953: getfield 238	com/google/ads/interactivemedia/v3/internal/bz:d	Z
    //   3956: ifeq +47 -> 4003
    //   3959: lload 16
    //   3961: ldc2_w 121
    //   3964: lcmp
    //   3965: ifeq +16 -> 3981
    //   3968: lload 16
    //   3970: aload_2
    //   3971: getfield 129	com/google/ads/interactivemedia/v3/internal/bo:t	Lcom/google/ads/interactivemedia/v3/internal/cd;
    //   3974: getfield 362	com/google/ads/interactivemedia/v3/internal/cd:m	J
    //   3977: lcmp
    //   3978: ifgt +25 -> 4003
    //   3981: aload_1
    //   3982: getfield 225	com/google/ads/interactivemedia/v3/internal/bz:f	Lcom/google/ads/interactivemedia/v3/internal/cc;
    //   3985: getfield 827	com/google/ads/interactivemedia/v3/internal/cc:g	Z
    //   3988: ifeq +15 -> 4003
    //   3991: aload_2
    //   3992: iconst_4
    //   3993: invokespecial 220	com/google/ads/interactivemedia/v3/internal/bo:a	(I)V
    //   3996: aload_0
    //   3997: invokespecial 217	com/google/ads/interactivemedia/v3/internal/bo:e	()V
    //   4000: goto +196 -> 4196
    //   4003: aload_2
    //   4004: getfield 129	com/google/ads/interactivemedia/v3/internal/bo:t	Lcom/google/ads/interactivemedia/v3/internal/cd;
    //   4007: astore_1
    //   4008: aload_1
    //   4009: getfield 341	com/google/ads/interactivemedia/v3/internal/cd:e	I
    //   4012: iconst_2
    //   4013: if_icmpne +132 -> 4145
    //   4016: aload_2
    //   4017: getfield 162	com/google/ads/interactivemedia/v3/internal/bo:v	[Lcom/google/ads/interactivemedia/v3/internal/cj;
    //   4020: arraylength
    //   4021: ifne +12 -> 4033
    //   4024: aload_0
    //   4025: invokespecial 873	com/google/ads/interactivemedia/v3/internal/bo:g	()Z
    //   4028: istore 9
    //   4030: goto +91 -> 4121
    //   4033: iload 24
    //   4035: ifeq +83 -> 4118
    //   4038: aload_1
    //   4039: getfield 351	com/google/ads/interactivemedia/v3/internal/cd:g	Z
    //   4042: ifne +9 -> 4051
    //   4045: iconst_1
    //   4046: istore 9
    //   4048: goto +73 -> 4121
    //   4051: aload_2
    //   4052: getfield 102	com/google/ads/interactivemedia/v3/internal/bo:r	Lcom/google/ads/interactivemedia/v3/internal/cb;
    //   4055: invokevirtual 549	com/google/ads/interactivemedia/v3/internal/cb:b	()Lcom/google/ads/interactivemedia/v3/internal/bz;
    //   4058: astore_1
    //   4059: aload_1
    //   4060: invokevirtual 826	com/google/ads/interactivemedia/v3/internal/bz:c	()Z
    //   4063: ifeq +18 -> 4081
    //   4066: aload_1
    //   4067: getfield 225	com/google/ads/interactivemedia/v3/internal/bz:f	Lcom/google/ads/interactivemedia/v3/internal/cc;
    //   4070: getfield 827	com/google/ads/interactivemedia/v3/internal/cc:g	Z
    //   4073: ifeq +8 -> 4081
    //   4076: iconst_1
    //   4077: istore_3
    //   4078: goto +5 -> 4083
    //   4081: iconst_0
    //   4082: istore_3
    //   4083: iload_3
    //   4084: ifne -39 -> 4045
    //   4087: aload_2
    //   4088: getfield 85	com/google/ads/interactivemedia/v3/internal/bo:e	Lcom/google/ads/interactivemedia/v3/internal/ca;
    //   4091: aload_0
    //   4092: invokespecial 607	com/google/ads/interactivemedia/v3/internal/bo:l	()J
    //   4095: aload_2
    //   4096: getfield 155	com/google/ads/interactivemedia/v3/internal/bo:n	Lcom/google/ads/interactivemedia/v3/internal/ay;
    //   4099: invokevirtual 643	com/google/ads/interactivemedia/v3/internal/ay:d	()Lcom/google/ads/interactivemedia/v3/internal/cg;
    //   4102: getfield 647	com/google/ads/interactivemedia/v3/internal/cg:b	F
    //   4105: aload_2
    //   4106: getfield 219	com/google/ads/interactivemedia/v3/internal/bo:y	Z
    //   4109: invokevirtual 876	com/google/ads/interactivemedia/v3/internal/ca:a	(JFZ)Z
    //   4112: ifeq +6 -> 4118
    //   4115: goto -70 -> 4045
    //   4118: iconst_0
    //   4119: istore 9
    //   4121: iload 9
    //   4123: ifeq +22 -> 4145
    //   4126: aload_2
    //   4127: iconst_3
    //   4128: invokespecial 220	com/google/ads/interactivemedia/v3/internal/bo:a	(I)V
    //   4131: aload_2
    //   4132: getfield 89	com/google/ads/interactivemedia/v3/internal/bo:x	Z
    //   4135: ifeq +61 -> 4196
    //   4138: aload_0
    //   4139: invokespecial 878	com/google/ads/interactivemedia/v3/internal/bo:d	()V
    //   4142: goto +54 -> 4196
    //   4145: aload_2
    //   4146: getfield 129	com/google/ads/interactivemedia/v3/internal/bo:t	Lcom/google/ads/interactivemedia/v3/internal/cd;
    //   4149: getfield 341	com/google/ads/interactivemedia/v3/internal/cd:e	I
    //   4152: iconst_3
    //   4153: if_icmpne +43 -> 4196
    //   4156: aload_2
    //   4157: getfield 162	com/google/ads/interactivemedia/v3/internal/bo:v	[Lcom/google/ads/interactivemedia/v3/internal/cj;
    //   4160: arraylength
    //   4161: ifne +13 -> 4174
    //   4164: aload_0
    //   4165: invokespecial 873	com/google/ads/interactivemedia/v3/internal/bo:g	()Z
    //   4168: ifeq +11 -> 4179
    //   4171: goto +25 -> 4196
    //   4174: iload 24
    //   4176: ifne +20 -> 4196
    //   4179: aload_2
    //   4180: aload_2
    //   4181: getfield 89	com/google/ads/interactivemedia/v3/internal/bo:x	Z
    //   4184: putfield 219	com/google/ads/interactivemedia/v3/internal/bo:y	Z
    //   4187: aload_2
    //   4188: iconst_2
    //   4189: invokespecial 220	com/google/ads/interactivemedia/v3/internal/bo:a	(I)V
    //   4192: aload_0
    //   4193: invokespecial 217	com/google/ads/interactivemedia/v3/internal/bo:e	()V
    //   4196: aload_2
    //   4197: getfield 129	com/google/ads/interactivemedia/v3/internal/bo:t	Lcom/google/ads/interactivemedia/v3/internal/cd;
    //   4200: getfield 341	com/google/ads/interactivemedia/v3/internal/cd:e	I
    //   4203: iconst_2
    //   4204: if_icmpne +34 -> 4238
    //   4207: aload_2
    //   4208: getfield 162	com/google/ads/interactivemedia/v3/internal/bo:v	[Lcom/google/ads/interactivemedia/v3/internal/cj;
    //   4211: astore_1
    //   4212: aload_1
    //   4213: arraylength
    //   4214: istore 7
    //   4216: iconst_0
    //   4217: istore_3
    //   4218: iload_3
    //   4219: iload 7
    //   4221: if_icmpge +17 -> 4238
    //   4224: aload_1
    //   4225: iload_3
    //   4226: aaload
    //   4227: invokeinterface 868 1 0
    //   4232: iinc 3 1
    //   4235: goto -17 -> 4218
    //   4238: aload_2
    //   4239: getfield 89	com/google/ads/interactivemedia/v3/internal/bo:x	Z
    //   4242: ifeq +14 -> 4256
    //   4245: aload_2
    //   4246: getfield 129	com/google/ads/interactivemedia/v3/internal/bo:t	Lcom/google/ads/interactivemedia/v3/internal/cd;
    //   4249: getfield 341	com/google/ads/interactivemedia/v3/internal/cd:e	I
    //   4252: iconst_3
    //   4253: if_icmpeq +16 -> 4269
    //   4256: aload_2
    //   4257: getfield 129	com/google/ads/interactivemedia/v3/internal/bo:t	Lcom/google/ads/interactivemedia/v3/internal/cd;
    //   4260: getfield 341	com/google/ads/interactivemedia/v3/internal/cd:e	I
    //   4263: istore_3
    //   4264: iload_3
    //   4265: iconst_2
    //   4266: if_icmpne +15 -> 4281
    //   4269: aload_2
    //   4270: lload 10
    //   4272: ldc2_w 844
    //   4275: invokespecial 847	com/google/ads/interactivemedia/v3/internal/bo:a	(JJ)V
    //   4278: goto +36 -> 4314
    //   4281: aload_2
    //   4282: getfield 162	com/google/ads/interactivemedia/v3/internal/bo:v	[Lcom/google/ads/interactivemedia/v3/internal/cj;
    //   4285: arraylength
    //   4286: ifeq +20 -> 4306
    //   4289: iload_3
    //   4290: iconst_4
    //   4291: if_icmpeq +15 -> 4306
    //   4294: aload_2
    //   4295: lload 10
    //   4297: ldc2_w 860
    //   4300: invokespecial 847	com/google/ads/interactivemedia/v3/internal/bo:a	(JJ)V
    //   4303: goto +11 -> 4314
    //   4306: aload_2
    //   4307: getfield 202	com/google/ads/interactivemedia/v3/internal/bo:g	Lcom/google/ads/interactivemedia/v3/internal/vo;
    //   4310: iconst_2
    //   4311: invokevirtual 390	com/google/ads/interactivemedia/v3/internal/vo:b	(I)V
    //   4314: invokestatic 879	com/google/ads/interactivemedia/v3/internal/rp:e	()V
    //   4317: goto +205 -> 4522
    //   4320: aload_1
    //   4321: getfield 707	android/os/Message:arg1	I
    //   4324: istore_3
    //   4325: iload_3
    //   4326: ifeq +9 -> 4335
    //   4329: iconst_1
    //   4330: istore 9
    //   4332: goto +6 -> 4338
    //   4335: iconst_0
    //   4336: istore 9
    //   4338: aload_2
    //   4339: iconst_0
    //   4340: putfield 219	com/google/ads/interactivemedia/v3/internal/bo:y	Z
    //   4343: aload_2
    //   4344: iload 9
    //   4346: putfield 89	com/google/ads/interactivemedia/v3/internal/bo:x	Z
    //   4349: iload 9
    //   4351: ifne +14 -> 4365
    //   4354: aload_0
    //   4355: invokespecial 217	com/google/ads/interactivemedia/v3/internal/bo:e	()V
    //   4358: aload_0
    //   4359: invokespecial 765	com/google/ads/interactivemedia/v3/internal/bo:f	()V
    //   4362: goto +160 -> 4522
    //   4365: aload_2
    //   4366: getfield 129	com/google/ads/interactivemedia/v3/internal/bo:t	Lcom/google/ads/interactivemedia/v3/internal/cd;
    //   4369: getfield 341	com/google/ads/interactivemedia/v3/internal/cd:e	I
    //   4372: istore_3
    //   4373: iload_3
    //   4374: iconst_3
    //   4375: if_icmpne +19 -> 4394
    //   4378: aload_0
    //   4379: invokespecial 878	com/google/ads/interactivemedia/v3/internal/bo:d	()V
    //   4382: aload_2
    //   4383: getfield 202	com/google/ads/interactivemedia/v3/internal/bo:g	Lcom/google/ads/interactivemedia/v3/internal/vo;
    //   4386: iconst_2
    //   4387: invokevirtual 289	com/google/ads/interactivemedia/v3/internal/vo:a	(I)Z
    //   4390: pop
    //   4391: goto +131 -> 4522
    //   4394: iload_3
    //   4395: iconst_2
    //   4396: if_icmpne +126 -> 4522
    //   4399: aload_2
    //   4400: getfield 202	com/google/ads/interactivemedia/v3/internal/bo:g	Lcom/google/ads/interactivemedia/v3/internal/vo;
    //   4403: iconst_2
    //   4404: invokevirtual 289	com/google/ads/interactivemedia/v3/internal/vo:a	(I)Z
    //   4407: pop
    //   4408: goto +114 -> 4522
    //   4411: iconst_0
    //   4412: istore 9
    //   4414: astore_1
    //   4415: goto +194 -> 4609
    //   4418: aload_1
    //   4419: getfield 704	android/os/Message:obj	Ljava/lang/Object;
    //   4422: checkcast 497	com/google/ads/interactivemedia/v3/internal/mq
    //   4425: astore 4
    //   4427: aload_1
    //   4428: getfield 707	android/os/Message:arg1	I
    //   4431: ifeq +9 -> 4440
    //   4434: iconst_1
    //   4435: istore 9
    //   4437: goto +6 -> 4443
    //   4440: iconst_0
    //   4441: istore 9
    //   4443: aload_1
    //   4444: getfield 882	android/os/Message:arg2	I
    //   4447: ifeq +9 -> 4456
    //   4450: iconst_1
    //   4451: istore 25
    //   4453: goto +6 -> 4459
    //   4456: iconst_0
    //   4457: istore 25
    //   4459: aload_2
    //   4460: aload_2
    //   4461: getfield 433	com/google/ads/interactivemedia/v3/internal/bo:C	I
    //   4464: iconst_1
    //   4465: iadd
    //   4466: putfield 433	com/google/ads/interactivemedia/v3/internal/bo:C	I
    //   4469: aload_0
    //   4470: iconst_0
    //   4471: iconst_1
    //   4472: iload 9
    //   4474: iload 25
    //   4476: iconst_1
    //   4477: invokespecial 431	com/google/ads/interactivemedia/v3/internal/bo:a	(ZZZZZ)V
    //   4480: aload_2
    //   4481: getfield 85	com/google/ads/interactivemedia/v3/internal/bo:e	Lcom/google/ads/interactivemedia/v3/internal/ca;
    //   4484: invokevirtual 883	com/google/ads/interactivemedia/v3/internal/ca:a	()V
    //   4487: aload_2
    //   4488: aload 4
    //   4490: putfield 495	com/google/ads/interactivemedia/v3/internal/bo:u	Lcom/google/ads/interactivemedia/v3/internal/mq;
    //   4493: aload_2
    //   4494: iconst_2
    //   4495: invokespecial 220	com/google/ads/interactivemedia/v3/internal/bo:a	(I)V
    //   4498: aload 4
    //   4500: aload_2
    //   4501: aload_2
    //   4502: getfield 87	com/google/ads/interactivemedia/v3/internal/bo:f	Lcom/google/ads/interactivemedia/v3/internal/tm;
    //   4505: invokeinterface 888 1 0
    //   4510: invokevirtual 891	com/google/ads/interactivemedia/v3/internal/mq:a	(Lcom/google/ads/interactivemedia/v3/internal/ms;Lcom/google/ads/interactivemedia/v3/internal/vc;)V
    //   4513: aload_2
    //   4514: getfield 202	com/google/ads/interactivemedia/v3/internal/bo:g	Lcom/google/ads/interactivemedia/v3/internal/vo;
    //   4517: iconst_2
    //   4518: invokevirtual 289	com/google/ads/interactivemedia/v3/internal/vo:a	(I)Z
    //   4521: pop
    //   4522: aload_0
    //   4523: invokespecial 840	com/google/ads/interactivemedia/v3/internal/bo:c	()V
    //   4526: goto +124 -> 4650
    //   4529: astore_1
    //   4530: iconst_0
    //   4531: istore 9
    //   4533: goto +76 -> 4609
    //   4536: astore_1
    //   4537: goto +4 -> 4541
    //   4540: astore_1
    //   4541: aload_0
    //   4542: astore_2
    //   4543: ldc_w 441
    //   4546: ldc_w 893
    //   4549: aload_1
    //   4550: invokestatic 448	com/google/ads/interactivemedia/v3/internal/vr:b	(Ljava/lang/String;Ljava/lang/String;Ljava/lang/Throwable;)V
    //   4553: aload_1
    //   4554: instanceof 698
    //   4557: ifeq +14 -> 4571
    //   4560: aload_1
    //   4561: checkcast 698	java/lang/OutOfMemoryError
    //   4564: invokestatic 896	com/google/ads/interactivemedia/v3/internal/ba:a	(Ljava/lang/OutOfMemoryError;)Lcom/google/ads/interactivemedia/v3/internal/ba;
    //   4567: astore_1
    //   4568: goto +11 -> 4579
    //   4571: aload_1
    //   4572: checkcast 438	java/lang/RuntimeException
    //   4575: invokestatic 899	com/google/ads/interactivemedia/v3/internal/ba:a	(Ljava/lang/RuntimeException;)Lcom/google/ads/interactivemedia/v3/internal/ba;
    //   4578: astore_1
    //   4579: aload_2
    //   4580: iconst_1
    //   4581: iconst_0
    //   4582: iconst_0
    //   4583: invokespecial 801	com/google/ads/interactivemedia/v3/internal/bo:a	(ZZZ)V
    //   4586: aload_2
    //   4587: aload_2
    //   4588: getfield 129	com/google/ads/interactivemedia/v3/internal/bo:t	Lcom/google/ads/interactivemedia/v3/internal/cd;
    //   4591: aload_1
    //   4592: invokevirtual 902	com/google/ads/interactivemedia/v3/internal/cd:a	(Lcom/google/ads/interactivemedia/v3/internal/ba;)Lcom/google/ads/interactivemedia/v3/internal/cd;
    //   4595: putfield 129	com/google/ads/interactivemedia/v3/internal/bo:t	Lcom/google/ads/interactivemedia/v3/internal/cd;
    //   4598: aload_0
    //   4599: invokespecial 840	com/google/ads/interactivemedia/v3/internal/bo:c	()V
    //   4602: goto +48 -> 4650
    //   4605: astore_1
    //   4606: iconst_0
    //   4607: istore 9
    //   4609: aload_0
    //   4610: astore_2
    //   4611: ldc_w 441
    //   4614: ldc_w 904
    //   4617: aload_1
    //   4618: invokestatic 448	com/google/ads/interactivemedia/v3/internal/vr:b	(Ljava/lang/String;Ljava/lang/String;Ljava/lang/Throwable;)V
    //   4621: aload_2
    //   4622: iload 9
    //   4624: iload 9
    //   4626: iload 9
    //   4628: invokespecial 801	com/google/ads/interactivemedia/v3/internal/bo:a	(ZZZ)V
    //   4631: aload_2
    //   4632: aload_2
    //   4633: getfield 129	com/google/ads/interactivemedia/v3/internal/bo:t	Lcom/google/ads/interactivemedia/v3/internal/cd;
    //   4636: aload_1
    //   4637: invokestatic 907	com/google/ads/interactivemedia/v3/internal/ba:a	(Ljava/io/IOException;)Lcom/google/ads/interactivemedia/v3/internal/ba;
    //   4640: invokevirtual 902	com/google/ads/interactivemedia/v3/internal/cd:a	(Lcom/google/ads/interactivemedia/v3/internal/ba;)Lcom/google/ads/interactivemedia/v3/internal/cd;
    //   4643: putfield 129	com/google/ads/interactivemedia/v3/internal/bo:t	Lcom/google/ads/interactivemedia/v3/internal/cd;
    //   4646: aload_0
    //   4647: invokespecial 840	com/google/ads/interactivemedia/v3/internal/bo:c	()V
    //   4650: goto +39 -> 4689
    //   4653: astore_1
    //   4654: aload_0
    //   4655: astore_2
    //   4656: ldc_w 441
    //   4659: ldc_w 909
    //   4662: aload_1
    //   4663: invokestatic 448	com/google/ads/interactivemedia/v3/internal/vr:b	(Ljava/lang/String;Ljava/lang/String;Ljava/lang/Throwable;)V
    //   4666: aload_2
    //   4667: iconst_1
    //   4668: iconst_0
    //   4669: iconst_0
    //   4670: invokespecial 801	com/google/ads/interactivemedia/v3/internal/bo:a	(ZZZ)V
    //   4673: aload_2
    //   4674: aload_2
    //   4675: getfield 129	com/google/ads/interactivemedia/v3/internal/bo:t	Lcom/google/ads/interactivemedia/v3/internal/cd;
    //   4678: aload_1
    //   4679: invokevirtual 902	com/google/ads/interactivemedia/v3/internal/cd:a	(Lcom/google/ads/interactivemedia/v3/internal/ba;)Lcom/google/ads/interactivemedia/v3/internal/cd;
    //   4682: putfield 129	com/google/ads/interactivemedia/v3/internal/bo:t	Lcom/google/ads/interactivemedia/v3/internal/cd;
    //   4685: aload_0
    //   4686: invokespecial 840	com/google/ads/interactivemedia/v3/internal/bo:c	()V
    //   4689: iconst_1
    //   4690: ireturn
    // Local variable table:
    //   start	length	slot	name	signature
    //   0	4691	0	this	bo
    //   0	4691	1	paramMessage	Message
    //   1	4674	2	localObject1	Object
    //   6	4391	3	i1	int
    //   105	2656	4	localObject2	Object
    //   2800	35	4	localObject3	Object
    //   2997	1502	4	localObject4	Object
    //   154	511	5	f1	float
    //   178	3192	6	localObject5	Object
    //   183	4039	7	i2	int
    //   197	3358	8	localObject6	Object
    //   431	4196	9	bool1	boolean
    //   826	3470	10	l1	long
    //   963	2430	12	localObject7	Object
    //   967	2944	13	i3	int
    //   1335	106	14	localcd	cd
    //   1346	2009	15	localObject8	Object
    //   1353	2616	16	l2	long
    //   1360	1364	18	l3	long
    //   1394	1959	20	localObject9	Object
    //   1408	1345	21	l4	long
    //   3698	250	23	i4	int
    //   3701	474	24	i5	int
    //   4451	24	25	bool2	boolean
    // Exception table:
    //   from	to	target	type
    //   518	529	532	finally
    //   533	535	532	finally
    //   1508	1513	1526	java/io/IOException
    //   2089	2095	2227	java/io/IOException
    //   2218	2224	2227	java/io/IOException
    //   1417	1448	2234	java/lang/OutOfMemoryError
    //   1417	1448	2238	java/lang/RuntimeException
    //   1417	1448	2242	java/io/IOException
    //   1417	1448	2246	com/google/ads/interactivemedia/v3/internal/ba
    //   98	114	2250	java/io/IOException
    //   121	126	2250	java/io/IOException
    //   137	164	2250	java/io/IOException
    //   168	185	2250	java/io/IOException
    //   204	213	2250	java/io/IOException
    //   219	224	2250	java/io/IOException
    //   227	236	2250	java/io/IOException
    //   252	263	2250	java/io/IOException
    //   269	303	2250	java/io/IOException
    //   306	330	2250	java/io/IOException
    //   333	347	2250	java/io/IOException
    //   350	387	2250	java/io/IOException
    //   390	395	2250	java/io/IOException
    //   398	420	2250	java/io/IOException
    //   423	430	2250	java/io/IOException
    //   439	462	2250	java/io/IOException
    //   467	478	2250	java/io/IOException
    //   491	506	2250	java/io/IOException
    //   516	518	2250	java/io/IOException
    //   535	537	2250	java/io/IOException
    //   537	544	2250	java/io/IOException
    //   553	576	2250	java/io/IOException
    //   576	581	2250	java/io/IOException
    //   584	610	2250	java/io/IOException
    //   610	615	2250	java/io/IOException
    //   618	647	2250	java/io/IOException
    //   653	660	2250	java/io/IOException
    //   663	684	2250	java/io/IOException
    //   689	708	2250	java/io/IOException
    //   714	739	2250	java/io/IOException
    //   770	775	2250	java/io/IOException
    //   782	899	2250	java/io/IOException
    //   899	908	2250	java/io/IOException
    //   913	926	2250	java/io/IOException
    //   932	942	2250	java/io/IOException
    //   957	965	2250	java/io/IOException
    //   985	1003	2250	java/io/IOException
    //   1013	1024	2250	java/io/IOException
    //   1034	1061	2250	java/io/IOException
    //   1064	1107	2250	java/io/IOException
    //   1107	1140	2250	java/io/IOException
    //   1143	1177	2250	java/io/IOException
    //   1180	1267	2250	java/io/IOException
    //   1267	1271	2250	java/io/IOException
    //   1274	1382	2250	java/io/IOException
    //   2288	2299	2301	finally
    //   2302	2304	2301	finally
    //   2539	2553	2800	finally
    //   2565	2579	2800	finally
    //   2582	2605	2800	finally
    //   2610	2618	2800	finally
    //   2625	2643	2800	finally
    //   2654	2682	2800	finally
    //   2721	2730	2800	finally
    //   2759	2765	2800	finally
    //   3040	3045	3604	java/io/IOException
    //   3084	3089	3604	java/io/IOException
    //   2324	2332	4411	java/io/IOException
    //   4338	4343	4411	java/io/IOException
    //   1382	1417	4529	java/io/IOException
    //   1451	1468	4529	java/io/IOException
    //   1472	1508	4529	java/io/IOException
    //   1513	1523	4529	java/io/IOException
    //   1539	1575	4529	java/io/IOException
    //   1578	1588	4529	java/io/IOException
    //   1588	1594	4529	java/io/IOException
    //   1598	1612	4529	java/io/IOException
    //   1616	1620	4529	java/io/IOException
    //   1623	1650	4529	java/io/IOException
    //   1662	1730	4529	java/io/IOException
    //   1740	1767	4529	java/io/IOException
    //   1771	1775	4529	java/io/IOException
    //   1778	1828	4529	java/io/IOException
    //   1831	1853	4529	java/io/IOException
    //   1855	1869	4529	java/io/IOException
    //   1871	1887	4529	java/io/IOException
    //   1891	1906	4529	java/io/IOException
    //   1914	1932	4529	java/io/IOException
    //   1942	1948	4529	java/io/IOException
    //   1952	1959	4529	java/io/IOException
    //   1961	1968	4529	java/io/IOException
    //   1972	1979	4529	java/io/IOException
    //   1983	1995	4529	java/io/IOException
    //   1999	2034	4529	java/io/IOException
    //   2051	2060	4529	java/io/IOException
    //   2074	2084	4529	java/io/IOException
    //   2098	2107	4529	java/io/IOException
    //   2111	2124	4529	java/io/IOException
    //   2127	2160	4529	java/io/IOException
    //   2166	2173	4529	java/io/IOException
    //   2183	2215	4529	java/io/IOException
    //   2257	2288	4529	java/io/IOException
    //   2304	2306	4529	java/io/IOException
    //   2306	2311	4529	java/io/IOException
    //   2335	2346	4529	java/io/IOException
    //   2349	2377	4529	java/io/IOException
    //   2380	2406	4529	java/io/IOException
    //   2411	2431	4529	java/io/IOException
    //   2446	2483	4529	java/io/IOException
    //   2495	2515	4529	java/io/IOException
    //   2682	2702	4529	java/io/IOException
    //   2706	2714	4529	java/io/IOException
    //   2765	2785	4529	java/io/IOException
    //   2789	2797	4529	java/io/IOException
    //   2802	2822	4529	java/io/IOException
    //   2826	2834	4529	java/io/IOException
    //   2834	2837	4529	java/io/IOException
    //   2837	2853	4529	java/io/IOException
    //   2857	2868	4529	java/io/IOException
    //   2871	2908	4529	java/io/IOException
    //   2912	2931	4529	java/io/IOException
    //   2939	2950	4529	java/io/IOException
    //   2956	2963	4529	java/io/IOException
    //   2966	3040	4529	java/io/IOException
    //   3045	3053	4529	java/io/IOException
    //   3057	3064	4529	java/io/IOException
    //   3067	3081	4529	java/io/IOException
    //   3089	3097	4529	java/io/IOException
    //   3101	3118	4529	java/io/IOException
    //   3120	3133	4529	java/io/IOException
    //   3139	3147	4529	java/io/IOException
    //   3152	3181	4529	java/io/IOException
    //   3187	3244	4529	java/io/IOException
    //   3249	3262	4529	java/io/IOException
    //   3268	3320	4529	java/io/IOException
    //   3329	3347	4529	java/io/IOException
    //   3352	3362	4529	java/io/IOException
    //   3367	3389	4529	java/io/IOException
    //   3392	3399	4529	java/io/IOException
    //   3407	3422	4529	java/io/IOException
    //   3426	3432	4529	java/io/IOException
    //   3437	3455	4529	java/io/IOException
    //   3455	3468	4529	java/io/IOException
    //   3486	3490	4529	java/io/IOException
    //   3490	3515	4529	java/io/IOException
    //   3515	3580	4529	java/io/IOException
    //   3587	3599	4529	java/io/IOException
    //   3611	3619	4529	java/io/IOException
    //   3623	3632	4529	java/io/IOException
    //   3635	3682	4529	java/io/IOException
    //   3690	3696	4529	java/io/IOException
    //   3703	3711	4529	java/io/IOException
    //   3725	3752	4529	java/io/IOException
    //   3757	3767	4529	java/io/IOException
    //   3776	3793	4529	java/io/IOException
    //   3807	3824	4529	java/io/IOException
    //   3843	3863	4529	java/io/IOException
    //   3896	3903	4529	java/io/IOException
    //   3923	3932	4529	java/io/IOException
    //   3938	3947	4529	java/io/IOException
    //   3952	3959	4529	java/io/IOException
    //   3968	3981	4529	java/io/IOException
    //   3981	4000	4529	java/io/IOException
    //   4003	4030	4529	java/io/IOException
    //   4038	4045	4529	java/io/IOException
    //   4051	4076	4529	java/io/IOException
    //   4087	4115	4529	java/io/IOException
    //   4126	4142	4529	java/io/IOException
    //   4145	4171	4529	java/io/IOException
    //   4179	4196	4529	java/io/IOException
    //   4196	4216	4529	java/io/IOException
    //   4224	4232	4529	java/io/IOException
    //   4238	4256	4529	java/io/IOException
    //   4256	4264	4529	java/io/IOException
    //   4269	4278	4529	java/io/IOException
    //   4281	4289	4529	java/io/IOException
    //   4294	4303	4529	java/io/IOException
    //   4306	4314	4529	java/io/IOException
    //   4314	4317	4529	java/io/IOException
    //   4320	4325	4529	java/io/IOException
    //   4343	4349	4529	java/io/IOException
    //   4354	4362	4529	java/io/IOException
    //   4365	4373	4529	java/io/IOException
    //   4378	4391	4529	java/io/IOException
    //   4399	4408	4529	java/io/IOException
    //   4418	4434	4529	java/io/IOException
    //   4443	4450	4529	java/io/IOException
    //   4459	4522	4529	java/io/IOException
    //   4522	4526	4529	java/io/IOException
    //   2	7	4536	java/lang/OutOfMemoryError
    //   98	114	4536	java/lang/OutOfMemoryError
    //   121	126	4536	java/lang/OutOfMemoryError
    //   137	164	4536	java/lang/OutOfMemoryError
    //   168	185	4536	java/lang/OutOfMemoryError
    //   204	213	4536	java/lang/OutOfMemoryError
    //   219	224	4536	java/lang/OutOfMemoryError
    //   227	236	4536	java/lang/OutOfMemoryError
    //   252	263	4536	java/lang/OutOfMemoryError
    //   269	303	4536	java/lang/OutOfMemoryError
    //   306	330	4536	java/lang/OutOfMemoryError
    //   333	347	4536	java/lang/OutOfMemoryError
    //   350	387	4536	java/lang/OutOfMemoryError
    //   390	395	4536	java/lang/OutOfMemoryError
    //   398	420	4536	java/lang/OutOfMemoryError
    //   423	430	4536	java/lang/OutOfMemoryError
    //   439	462	4536	java/lang/OutOfMemoryError
    //   467	478	4536	java/lang/OutOfMemoryError
    //   491	506	4536	java/lang/OutOfMemoryError
    //   516	518	4536	java/lang/OutOfMemoryError
    //   535	537	4536	java/lang/OutOfMemoryError
    //   537	544	4536	java/lang/OutOfMemoryError
    //   553	576	4536	java/lang/OutOfMemoryError
    //   576	581	4536	java/lang/OutOfMemoryError
    //   584	610	4536	java/lang/OutOfMemoryError
    //   610	615	4536	java/lang/OutOfMemoryError
    //   618	647	4536	java/lang/OutOfMemoryError
    //   653	660	4536	java/lang/OutOfMemoryError
    //   663	684	4536	java/lang/OutOfMemoryError
    //   689	708	4536	java/lang/OutOfMemoryError
    //   714	739	4536	java/lang/OutOfMemoryError
    //   770	775	4536	java/lang/OutOfMemoryError
    //   782	899	4536	java/lang/OutOfMemoryError
    //   899	908	4536	java/lang/OutOfMemoryError
    //   913	926	4536	java/lang/OutOfMemoryError
    //   932	942	4536	java/lang/OutOfMemoryError
    //   957	965	4536	java/lang/OutOfMemoryError
    //   985	1003	4536	java/lang/OutOfMemoryError
    //   1013	1024	4536	java/lang/OutOfMemoryError
    //   1034	1061	4536	java/lang/OutOfMemoryError
    //   1064	1107	4536	java/lang/OutOfMemoryError
    //   1107	1140	4536	java/lang/OutOfMemoryError
    //   1143	1177	4536	java/lang/OutOfMemoryError
    //   1180	1267	4536	java/lang/OutOfMemoryError
    //   1267	1271	4536	java/lang/OutOfMemoryError
    //   1274	1382	4536	java/lang/OutOfMemoryError
    //   1382	1417	4536	java/lang/OutOfMemoryError
    //   1451	1468	4536	java/lang/OutOfMemoryError
    //   1472	1508	4536	java/lang/OutOfMemoryError
    //   1508	1513	4536	java/lang/OutOfMemoryError
    //   1513	1523	4536	java/lang/OutOfMemoryError
    //   1539	1575	4536	java/lang/OutOfMemoryError
    //   1578	1588	4536	java/lang/OutOfMemoryError
    //   1588	1594	4536	java/lang/OutOfMemoryError
    //   1598	1612	4536	java/lang/OutOfMemoryError
    //   1616	1620	4536	java/lang/OutOfMemoryError
    //   1623	1650	4536	java/lang/OutOfMemoryError
    //   1662	1730	4536	java/lang/OutOfMemoryError
    //   1740	1767	4536	java/lang/OutOfMemoryError
    //   1771	1775	4536	java/lang/OutOfMemoryError
    //   1778	1828	4536	java/lang/OutOfMemoryError
    //   1831	1853	4536	java/lang/OutOfMemoryError
    //   1855	1869	4536	java/lang/OutOfMemoryError
    //   1871	1887	4536	java/lang/OutOfMemoryError
    //   1891	1906	4536	java/lang/OutOfMemoryError
    //   1914	1932	4536	java/lang/OutOfMemoryError
    //   1942	1948	4536	java/lang/OutOfMemoryError
    //   1952	1959	4536	java/lang/OutOfMemoryError
    //   1961	1968	4536	java/lang/OutOfMemoryError
    //   1972	1979	4536	java/lang/OutOfMemoryError
    //   1983	1995	4536	java/lang/OutOfMemoryError
    //   1999	2034	4536	java/lang/OutOfMemoryError
    //   2051	2060	4536	java/lang/OutOfMemoryError
    //   2074	2084	4536	java/lang/OutOfMemoryError
    //   2089	2095	4536	java/lang/OutOfMemoryError
    //   2098	2107	4536	java/lang/OutOfMemoryError
    //   2111	2124	4536	java/lang/OutOfMemoryError
    //   2127	2160	4536	java/lang/OutOfMemoryError
    //   2166	2173	4536	java/lang/OutOfMemoryError
    //   2183	2215	4536	java/lang/OutOfMemoryError
    //   2218	2224	4536	java/lang/OutOfMemoryError
    //   2257	2288	4536	java/lang/OutOfMemoryError
    //   2304	2306	4536	java/lang/OutOfMemoryError
    //   2306	2311	4536	java/lang/OutOfMemoryError
    //   2324	2332	4536	java/lang/OutOfMemoryError
    //   2335	2346	4536	java/lang/OutOfMemoryError
    //   2349	2377	4536	java/lang/OutOfMemoryError
    //   2380	2406	4536	java/lang/OutOfMemoryError
    //   2411	2431	4536	java/lang/OutOfMemoryError
    //   2446	2483	4536	java/lang/OutOfMemoryError
    //   2495	2515	4536	java/lang/OutOfMemoryError
    //   2682	2702	4536	java/lang/OutOfMemoryError
    //   2706	2714	4536	java/lang/OutOfMemoryError
    //   2765	2785	4536	java/lang/OutOfMemoryError
    //   2789	2797	4536	java/lang/OutOfMemoryError
    //   2802	2822	4536	java/lang/OutOfMemoryError
    //   2826	2834	4536	java/lang/OutOfMemoryError
    //   2834	2837	4536	java/lang/OutOfMemoryError
    //   2837	2853	4536	java/lang/OutOfMemoryError
    //   2857	2868	4536	java/lang/OutOfMemoryError
    //   2871	2908	4536	java/lang/OutOfMemoryError
    //   2912	2931	4536	java/lang/OutOfMemoryError
    //   2939	2950	4536	java/lang/OutOfMemoryError
    //   2956	2963	4536	java/lang/OutOfMemoryError
    //   2966	3040	4536	java/lang/OutOfMemoryError
    //   3040	3045	4536	java/lang/OutOfMemoryError
    //   3045	3053	4536	java/lang/OutOfMemoryError
    //   3057	3064	4536	java/lang/OutOfMemoryError
    //   3067	3081	4536	java/lang/OutOfMemoryError
    //   3084	3089	4536	java/lang/OutOfMemoryError
    //   3089	3097	4536	java/lang/OutOfMemoryError
    //   3101	3118	4536	java/lang/OutOfMemoryError
    //   3120	3133	4536	java/lang/OutOfMemoryError
    //   3139	3147	4536	java/lang/OutOfMemoryError
    //   3152	3181	4536	java/lang/OutOfMemoryError
    //   3187	3244	4536	java/lang/OutOfMemoryError
    //   3249	3262	4536	java/lang/OutOfMemoryError
    //   3268	3320	4536	java/lang/OutOfMemoryError
    //   3329	3347	4536	java/lang/OutOfMemoryError
    //   3352	3362	4536	java/lang/OutOfMemoryError
    //   3367	3389	4536	java/lang/OutOfMemoryError
    //   3392	3399	4536	java/lang/OutOfMemoryError
    //   3407	3422	4536	java/lang/OutOfMemoryError
    //   3426	3432	4536	java/lang/OutOfMemoryError
    //   3437	3455	4536	java/lang/OutOfMemoryError
    //   3455	3468	4536	java/lang/OutOfMemoryError
    //   3486	3490	4536	java/lang/OutOfMemoryError
    //   3490	3515	4536	java/lang/OutOfMemoryError
    //   3515	3580	4536	java/lang/OutOfMemoryError
    //   3587	3599	4536	java/lang/OutOfMemoryError
    //   3611	3619	4536	java/lang/OutOfMemoryError
    //   3623	3632	4536	java/lang/OutOfMemoryError
    //   3635	3682	4536	java/lang/OutOfMemoryError
    //   3690	3696	4536	java/lang/OutOfMemoryError
    //   3703	3711	4536	java/lang/OutOfMemoryError
    //   3725	3752	4536	java/lang/OutOfMemoryError
    //   3757	3767	4536	java/lang/OutOfMemoryError
    //   3776	3793	4536	java/lang/OutOfMemoryError
    //   3807	3824	4536	java/lang/OutOfMemoryError
    //   3843	3863	4536	java/lang/OutOfMemoryError
    //   3896	3903	4536	java/lang/OutOfMemoryError
    //   3923	3932	4536	java/lang/OutOfMemoryError
    //   3938	3947	4536	java/lang/OutOfMemoryError
    //   3952	3959	4536	java/lang/OutOfMemoryError
    //   3968	3981	4536	java/lang/OutOfMemoryError
    //   3981	4000	4536	java/lang/OutOfMemoryError
    //   4003	4030	4536	java/lang/OutOfMemoryError
    //   4038	4045	4536	java/lang/OutOfMemoryError
    //   4051	4076	4536	java/lang/OutOfMemoryError
    //   4087	4115	4536	java/lang/OutOfMemoryError
    //   4126	4142	4536	java/lang/OutOfMemoryError
    //   4145	4171	4536	java/lang/OutOfMemoryError
    //   4179	4196	4536	java/lang/OutOfMemoryError
    //   4196	4216	4536	java/lang/OutOfMemoryError
    //   4224	4232	4536	java/lang/OutOfMemoryError
    //   4238	4256	4536	java/lang/OutOfMemoryError
    //   4256	4264	4536	java/lang/OutOfMemoryError
    //   4269	4278	4536	java/lang/OutOfMemoryError
    //   4281	4289	4536	java/lang/OutOfMemoryError
    //   4294	4303	4536	java/lang/OutOfMemoryError
    //   4306	4314	4536	java/lang/OutOfMemoryError
    //   4314	4317	4536	java/lang/OutOfMemoryError
    //   4320	4325	4536	java/lang/OutOfMemoryError
    //   4338	4343	4536	java/lang/OutOfMemoryError
    //   4343	4349	4536	java/lang/OutOfMemoryError
    //   4354	4362	4536	java/lang/OutOfMemoryError
    //   4365	4373	4536	java/lang/OutOfMemoryError
    //   4378	4391	4536	java/lang/OutOfMemoryError
    //   4399	4408	4536	java/lang/OutOfMemoryError
    //   4418	4434	4536	java/lang/OutOfMemoryError
    //   4443	4450	4536	java/lang/OutOfMemoryError
    //   4459	4522	4536	java/lang/OutOfMemoryError
    //   4522	4526	4536	java/lang/OutOfMemoryError
    //   2	7	4540	java/lang/RuntimeException
    //   98	114	4540	java/lang/RuntimeException
    //   121	126	4540	java/lang/RuntimeException
    //   137	164	4540	java/lang/RuntimeException
    //   168	185	4540	java/lang/RuntimeException
    //   204	213	4540	java/lang/RuntimeException
    //   219	224	4540	java/lang/RuntimeException
    //   227	236	4540	java/lang/RuntimeException
    //   252	263	4540	java/lang/RuntimeException
    //   269	303	4540	java/lang/RuntimeException
    //   306	330	4540	java/lang/RuntimeException
    //   333	347	4540	java/lang/RuntimeException
    //   350	387	4540	java/lang/RuntimeException
    //   390	395	4540	java/lang/RuntimeException
    //   398	420	4540	java/lang/RuntimeException
    //   423	430	4540	java/lang/RuntimeException
    //   439	462	4540	java/lang/RuntimeException
    //   467	478	4540	java/lang/RuntimeException
    //   491	506	4540	java/lang/RuntimeException
    //   516	518	4540	java/lang/RuntimeException
    //   535	537	4540	java/lang/RuntimeException
    //   537	544	4540	java/lang/RuntimeException
    //   553	576	4540	java/lang/RuntimeException
    //   576	581	4540	java/lang/RuntimeException
    //   584	610	4540	java/lang/RuntimeException
    //   610	615	4540	java/lang/RuntimeException
    //   618	647	4540	java/lang/RuntimeException
    //   653	660	4540	java/lang/RuntimeException
    //   663	684	4540	java/lang/RuntimeException
    //   689	708	4540	java/lang/RuntimeException
    //   714	739	4540	java/lang/RuntimeException
    //   770	775	4540	java/lang/RuntimeException
    //   782	899	4540	java/lang/RuntimeException
    //   899	908	4540	java/lang/RuntimeException
    //   913	926	4540	java/lang/RuntimeException
    //   932	942	4540	java/lang/RuntimeException
    //   957	965	4540	java/lang/RuntimeException
    //   985	1003	4540	java/lang/RuntimeException
    //   1013	1024	4540	java/lang/RuntimeException
    //   1034	1061	4540	java/lang/RuntimeException
    //   1064	1107	4540	java/lang/RuntimeException
    //   1107	1140	4540	java/lang/RuntimeException
    //   1143	1177	4540	java/lang/RuntimeException
    //   1180	1267	4540	java/lang/RuntimeException
    //   1267	1271	4540	java/lang/RuntimeException
    //   1274	1382	4540	java/lang/RuntimeException
    //   1382	1417	4540	java/lang/RuntimeException
    //   1451	1468	4540	java/lang/RuntimeException
    //   1472	1508	4540	java/lang/RuntimeException
    //   1508	1513	4540	java/lang/RuntimeException
    //   1513	1523	4540	java/lang/RuntimeException
    //   1539	1575	4540	java/lang/RuntimeException
    //   1578	1588	4540	java/lang/RuntimeException
    //   1588	1594	4540	java/lang/RuntimeException
    //   1598	1612	4540	java/lang/RuntimeException
    //   1616	1620	4540	java/lang/RuntimeException
    //   1623	1650	4540	java/lang/RuntimeException
    //   1662	1730	4540	java/lang/RuntimeException
    //   1740	1767	4540	java/lang/RuntimeException
    //   1771	1775	4540	java/lang/RuntimeException
    //   1778	1828	4540	java/lang/RuntimeException
    //   1831	1853	4540	java/lang/RuntimeException
    //   1855	1869	4540	java/lang/RuntimeException
    //   1871	1887	4540	java/lang/RuntimeException
    //   1891	1906	4540	java/lang/RuntimeException
    //   1914	1932	4540	java/lang/RuntimeException
    //   1942	1948	4540	java/lang/RuntimeException
    //   1952	1959	4540	java/lang/RuntimeException
    //   1961	1968	4540	java/lang/RuntimeException
    //   1972	1979	4540	java/lang/RuntimeException
    //   1983	1995	4540	java/lang/RuntimeException
    //   1999	2034	4540	java/lang/RuntimeException
    //   2051	2060	4540	java/lang/RuntimeException
    //   2074	2084	4540	java/lang/RuntimeException
    //   2089	2095	4540	java/lang/RuntimeException
    //   2098	2107	4540	java/lang/RuntimeException
    //   2111	2124	4540	java/lang/RuntimeException
    //   2127	2160	4540	java/lang/RuntimeException
    //   2166	2173	4540	java/lang/RuntimeException
    //   2183	2215	4540	java/lang/RuntimeException
    //   2218	2224	4540	java/lang/RuntimeException
    //   2257	2288	4540	java/lang/RuntimeException
    //   2304	2306	4540	java/lang/RuntimeException
    //   2306	2311	4540	java/lang/RuntimeException
    //   2324	2332	4540	java/lang/RuntimeException
    //   2335	2346	4540	java/lang/RuntimeException
    //   2349	2377	4540	java/lang/RuntimeException
    //   2380	2406	4540	java/lang/RuntimeException
    //   2411	2431	4540	java/lang/RuntimeException
    //   2446	2483	4540	java/lang/RuntimeException
    //   2495	2515	4540	java/lang/RuntimeException
    //   2682	2702	4540	java/lang/RuntimeException
    //   2706	2714	4540	java/lang/RuntimeException
    //   2765	2785	4540	java/lang/RuntimeException
    //   2789	2797	4540	java/lang/RuntimeException
    //   2802	2822	4540	java/lang/RuntimeException
    //   2826	2834	4540	java/lang/RuntimeException
    //   2834	2837	4540	java/lang/RuntimeException
    //   2837	2853	4540	java/lang/RuntimeException
    //   2857	2868	4540	java/lang/RuntimeException
    //   2871	2908	4540	java/lang/RuntimeException
    //   2912	2931	4540	java/lang/RuntimeException
    //   2939	2950	4540	java/lang/RuntimeException
    //   2956	2963	4540	java/lang/RuntimeException
    //   2966	3040	4540	java/lang/RuntimeException
    //   3040	3045	4540	java/lang/RuntimeException
    //   3045	3053	4540	java/lang/RuntimeException
    //   3057	3064	4540	java/lang/RuntimeException
    //   3067	3081	4540	java/lang/RuntimeException
    //   3084	3089	4540	java/lang/RuntimeException
    //   3089	3097	4540	java/lang/RuntimeException
    //   3101	3118	4540	java/lang/RuntimeException
    //   3120	3133	4540	java/lang/RuntimeException
    //   3139	3147	4540	java/lang/RuntimeException
    //   3152	3181	4540	java/lang/RuntimeException
    //   3187	3244	4540	java/lang/RuntimeException
    //   3249	3262	4540	java/lang/RuntimeException
    //   3268	3320	4540	java/lang/RuntimeException
    //   3329	3347	4540	java/lang/RuntimeException
    //   3352	3362	4540	java/lang/RuntimeException
    //   3367	3389	4540	java/lang/RuntimeException
    //   3392	3399	4540	java/lang/RuntimeException
    //   3407	3422	4540	java/lang/RuntimeException
    //   3426	3432	4540	java/lang/RuntimeException
    //   3437	3455	4540	java/lang/RuntimeException
    //   3455	3468	4540	java/lang/RuntimeException
    //   3486	3490	4540	java/lang/RuntimeException
    //   3490	3515	4540	java/lang/RuntimeException
    //   3515	3580	4540	java/lang/RuntimeException
    //   3587	3599	4540	java/lang/RuntimeException
    //   3611	3619	4540	java/lang/RuntimeException
    //   3623	3632	4540	java/lang/RuntimeException
    //   3635	3682	4540	java/lang/RuntimeException
    //   3690	3696	4540	java/lang/RuntimeException
    //   3703	3711	4540	java/lang/RuntimeException
    //   3725	3752	4540	java/lang/RuntimeException
    //   3757	3767	4540	java/lang/RuntimeException
    //   3776	3793	4540	java/lang/RuntimeException
    //   3807	3824	4540	java/lang/RuntimeException
    //   3843	3863	4540	java/lang/RuntimeException
    //   3896	3903	4540	java/lang/RuntimeException
    //   3923	3932	4540	java/lang/RuntimeException
    //   3938	3947	4540	java/lang/RuntimeException
    //   3952	3959	4540	java/lang/RuntimeException
    //   3968	3981	4540	java/lang/RuntimeException
    //   3981	4000	4540	java/lang/RuntimeException
    //   4003	4030	4540	java/lang/RuntimeException
    //   4038	4045	4540	java/lang/RuntimeException
    //   4051	4076	4540	java/lang/RuntimeException
    //   4087	4115	4540	java/lang/RuntimeException
    //   4126	4142	4540	java/lang/RuntimeException
    //   4145	4171	4540	java/lang/RuntimeException
    //   4179	4196	4540	java/lang/RuntimeException
    //   4196	4216	4540	java/lang/RuntimeException
    //   4224	4232	4540	java/lang/RuntimeException
    //   4238	4256	4540	java/lang/RuntimeException
    //   4256	4264	4540	java/lang/RuntimeException
    //   4269	4278	4540	java/lang/RuntimeException
    //   4281	4289	4540	java/lang/RuntimeException
    //   4294	4303	4540	java/lang/RuntimeException
    //   4306	4314	4540	java/lang/RuntimeException
    //   4314	4317	4540	java/lang/RuntimeException
    //   4320	4325	4540	java/lang/RuntimeException
    //   4338	4343	4540	java/lang/RuntimeException
    //   4343	4349	4540	java/lang/RuntimeException
    //   4354	4362	4540	java/lang/RuntimeException
    //   4365	4373	4540	java/lang/RuntimeException
    //   4378	4391	4540	java/lang/RuntimeException
    //   4399	4408	4540	java/lang/RuntimeException
    //   4418	4434	4540	java/lang/RuntimeException
    //   4443	4450	4540	java/lang/RuntimeException
    //   4459	4522	4540	java/lang/RuntimeException
    //   4522	4526	4540	java/lang/RuntimeException
    //   2	7	4605	java/io/IOException
    //   2	7	4653	com/google/ads/interactivemedia/v3/internal/ba
    //   98	114	4653	com/google/ads/interactivemedia/v3/internal/ba
    //   121	126	4653	com/google/ads/interactivemedia/v3/internal/ba
    //   137	164	4653	com/google/ads/interactivemedia/v3/internal/ba
    //   168	185	4653	com/google/ads/interactivemedia/v3/internal/ba
    //   204	213	4653	com/google/ads/interactivemedia/v3/internal/ba
    //   219	224	4653	com/google/ads/interactivemedia/v3/internal/ba
    //   227	236	4653	com/google/ads/interactivemedia/v3/internal/ba
    //   252	263	4653	com/google/ads/interactivemedia/v3/internal/ba
    //   269	303	4653	com/google/ads/interactivemedia/v3/internal/ba
    //   306	330	4653	com/google/ads/interactivemedia/v3/internal/ba
    //   333	347	4653	com/google/ads/interactivemedia/v3/internal/ba
    //   350	387	4653	com/google/ads/interactivemedia/v3/internal/ba
    //   390	395	4653	com/google/ads/interactivemedia/v3/internal/ba
    //   398	420	4653	com/google/ads/interactivemedia/v3/internal/ba
    //   423	430	4653	com/google/ads/interactivemedia/v3/internal/ba
    //   439	462	4653	com/google/ads/interactivemedia/v3/internal/ba
    //   467	478	4653	com/google/ads/interactivemedia/v3/internal/ba
    //   491	506	4653	com/google/ads/interactivemedia/v3/internal/ba
    //   516	518	4653	com/google/ads/interactivemedia/v3/internal/ba
    //   535	537	4653	com/google/ads/interactivemedia/v3/internal/ba
    //   537	544	4653	com/google/ads/interactivemedia/v3/internal/ba
    //   553	576	4653	com/google/ads/interactivemedia/v3/internal/ba
    //   576	581	4653	com/google/ads/interactivemedia/v3/internal/ba
    //   584	610	4653	com/google/ads/interactivemedia/v3/internal/ba
    //   610	615	4653	com/google/ads/interactivemedia/v3/internal/ba
    //   618	647	4653	com/google/ads/interactivemedia/v3/internal/ba
    //   653	660	4653	com/google/ads/interactivemedia/v3/internal/ba
    //   663	684	4653	com/google/ads/interactivemedia/v3/internal/ba
    //   689	708	4653	com/google/ads/interactivemedia/v3/internal/ba
    //   714	739	4653	com/google/ads/interactivemedia/v3/internal/ba
    //   770	775	4653	com/google/ads/interactivemedia/v3/internal/ba
    //   782	899	4653	com/google/ads/interactivemedia/v3/internal/ba
    //   899	908	4653	com/google/ads/interactivemedia/v3/internal/ba
    //   913	926	4653	com/google/ads/interactivemedia/v3/internal/ba
    //   932	942	4653	com/google/ads/interactivemedia/v3/internal/ba
    //   957	965	4653	com/google/ads/interactivemedia/v3/internal/ba
    //   985	1003	4653	com/google/ads/interactivemedia/v3/internal/ba
    //   1013	1024	4653	com/google/ads/interactivemedia/v3/internal/ba
    //   1034	1061	4653	com/google/ads/interactivemedia/v3/internal/ba
    //   1064	1107	4653	com/google/ads/interactivemedia/v3/internal/ba
    //   1107	1140	4653	com/google/ads/interactivemedia/v3/internal/ba
    //   1143	1177	4653	com/google/ads/interactivemedia/v3/internal/ba
    //   1180	1267	4653	com/google/ads/interactivemedia/v3/internal/ba
    //   1267	1271	4653	com/google/ads/interactivemedia/v3/internal/ba
    //   1274	1382	4653	com/google/ads/interactivemedia/v3/internal/ba
    //   1382	1417	4653	com/google/ads/interactivemedia/v3/internal/ba
    //   1451	1468	4653	com/google/ads/interactivemedia/v3/internal/ba
    //   1472	1508	4653	com/google/ads/interactivemedia/v3/internal/ba
    //   1508	1513	4653	com/google/ads/interactivemedia/v3/internal/ba
    //   1513	1523	4653	com/google/ads/interactivemedia/v3/internal/ba
    //   1539	1575	4653	com/google/ads/interactivemedia/v3/internal/ba
    //   1578	1588	4653	com/google/ads/interactivemedia/v3/internal/ba
    //   1588	1594	4653	com/google/ads/interactivemedia/v3/internal/ba
    //   1598	1612	4653	com/google/ads/interactivemedia/v3/internal/ba
    //   1616	1620	4653	com/google/ads/interactivemedia/v3/internal/ba
    //   1623	1650	4653	com/google/ads/interactivemedia/v3/internal/ba
    //   1662	1730	4653	com/google/ads/interactivemedia/v3/internal/ba
    //   1740	1767	4653	com/google/ads/interactivemedia/v3/internal/ba
    //   1771	1775	4653	com/google/ads/interactivemedia/v3/internal/ba
    //   1778	1828	4653	com/google/ads/interactivemedia/v3/internal/ba
    //   1831	1853	4653	com/google/ads/interactivemedia/v3/internal/ba
    //   1855	1869	4653	com/google/ads/interactivemedia/v3/internal/ba
    //   1871	1887	4653	com/google/ads/interactivemedia/v3/internal/ba
    //   1891	1906	4653	com/google/ads/interactivemedia/v3/internal/ba
    //   1914	1932	4653	com/google/ads/interactivemedia/v3/internal/ba
    //   1942	1948	4653	com/google/ads/interactivemedia/v3/internal/ba
    //   1952	1959	4653	com/google/ads/interactivemedia/v3/internal/ba
    //   1961	1968	4653	com/google/ads/interactivemedia/v3/internal/ba
    //   1972	1979	4653	com/google/ads/interactivemedia/v3/internal/ba
    //   1983	1995	4653	com/google/ads/interactivemedia/v3/internal/ba
    //   1999	2034	4653	com/google/ads/interactivemedia/v3/internal/ba
    //   2051	2060	4653	com/google/ads/interactivemedia/v3/internal/ba
    //   2074	2084	4653	com/google/ads/interactivemedia/v3/internal/ba
    //   2089	2095	4653	com/google/ads/interactivemedia/v3/internal/ba
    //   2098	2107	4653	com/google/ads/interactivemedia/v3/internal/ba
    //   2111	2124	4653	com/google/ads/interactivemedia/v3/internal/ba
    //   2127	2160	4653	com/google/ads/interactivemedia/v3/internal/ba
    //   2166	2173	4653	com/google/ads/interactivemedia/v3/internal/ba
    //   2183	2215	4653	com/google/ads/interactivemedia/v3/internal/ba
    //   2218	2224	4653	com/google/ads/interactivemedia/v3/internal/ba
    //   2257	2288	4653	com/google/ads/interactivemedia/v3/internal/ba
    //   2304	2306	4653	com/google/ads/interactivemedia/v3/internal/ba
    //   2306	2311	4653	com/google/ads/interactivemedia/v3/internal/ba
    //   2324	2332	4653	com/google/ads/interactivemedia/v3/internal/ba
    //   2335	2346	4653	com/google/ads/interactivemedia/v3/internal/ba
    //   2349	2377	4653	com/google/ads/interactivemedia/v3/internal/ba
    //   2380	2406	4653	com/google/ads/interactivemedia/v3/internal/ba
    //   2411	2431	4653	com/google/ads/interactivemedia/v3/internal/ba
    //   2446	2483	4653	com/google/ads/interactivemedia/v3/internal/ba
    //   2495	2515	4653	com/google/ads/interactivemedia/v3/internal/ba
    //   2682	2702	4653	com/google/ads/interactivemedia/v3/internal/ba
    //   2706	2714	4653	com/google/ads/interactivemedia/v3/internal/ba
    //   2765	2785	4653	com/google/ads/interactivemedia/v3/internal/ba
    //   2789	2797	4653	com/google/ads/interactivemedia/v3/internal/ba
    //   2802	2822	4653	com/google/ads/interactivemedia/v3/internal/ba
    //   2826	2834	4653	com/google/ads/interactivemedia/v3/internal/ba
    //   2834	2837	4653	com/google/ads/interactivemedia/v3/internal/ba
    //   2837	2853	4653	com/google/ads/interactivemedia/v3/internal/ba
    //   2857	2868	4653	com/google/ads/interactivemedia/v3/internal/ba
    //   2871	2908	4653	com/google/ads/interactivemedia/v3/internal/ba
    //   2912	2931	4653	com/google/ads/interactivemedia/v3/internal/ba
    //   2939	2950	4653	com/google/ads/interactivemedia/v3/internal/ba
    //   2956	2963	4653	com/google/ads/interactivemedia/v3/internal/ba
    //   2966	3040	4653	com/google/ads/interactivemedia/v3/internal/ba
    //   3040	3045	4653	com/google/ads/interactivemedia/v3/internal/ba
    //   3045	3053	4653	com/google/ads/interactivemedia/v3/internal/ba
    //   3057	3064	4653	com/google/ads/interactivemedia/v3/internal/ba
    //   3067	3081	4653	com/google/ads/interactivemedia/v3/internal/ba
    //   3084	3089	4653	com/google/ads/interactivemedia/v3/internal/ba
    //   3089	3097	4653	com/google/ads/interactivemedia/v3/internal/ba
    //   3101	3118	4653	com/google/ads/interactivemedia/v3/internal/ba
    //   3120	3133	4653	com/google/ads/interactivemedia/v3/internal/ba
    //   3139	3147	4653	com/google/ads/interactivemedia/v3/internal/ba
    //   3152	3181	4653	com/google/ads/interactivemedia/v3/internal/ba
    //   3187	3244	4653	com/google/ads/interactivemedia/v3/internal/ba
    //   3249	3262	4653	com/google/ads/interactivemedia/v3/internal/ba
    //   3268	3320	4653	com/google/ads/interactivemedia/v3/internal/ba
    //   3329	3347	4653	com/google/ads/interactivemedia/v3/internal/ba
    //   3352	3362	4653	com/google/ads/interactivemedia/v3/internal/ba
    //   3367	3389	4653	com/google/ads/interactivemedia/v3/internal/ba
    //   3392	3399	4653	com/google/ads/interactivemedia/v3/internal/ba
    //   3407	3422	4653	com/google/ads/interactivemedia/v3/internal/ba
    //   3426	3432	4653	com/google/ads/interactivemedia/v3/internal/ba
    //   3437	3455	4653	com/google/ads/interactivemedia/v3/internal/ba
    //   3455	3468	4653	com/google/ads/interactivemedia/v3/internal/ba
    //   3486	3490	4653	com/google/ads/interactivemedia/v3/internal/ba
    //   3490	3515	4653	com/google/ads/interactivemedia/v3/internal/ba
    //   3515	3580	4653	com/google/ads/interactivemedia/v3/internal/ba
    //   3587	3599	4653	com/google/ads/interactivemedia/v3/internal/ba
    //   3611	3619	4653	com/google/ads/interactivemedia/v3/internal/ba
    //   3623	3632	4653	com/google/ads/interactivemedia/v3/internal/ba
    //   3635	3682	4653	com/google/ads/interactivemedia/v3/internal/ba
    //   3690	3696	4653	com/google/ads/interactivemedia/v3/internal/ba
    //   3703	3711	4653	com/google/ads/interactivemedia/v3/internal/ba
    //   3725	3752	4653	com/google/ads/interactivemedia/v3/internal/ba
    //   3757	3767	4653	com/google/ads/interactivemedia/v3/internal/ba
    //   3776	3793	4653	com/google/ads/interactivemedia/v3/internal/ba
    //   3807	3824	4653	com/google/ads/interactivemedia/v3/internal/ba
    //   3843	3863	4653	com/google/ads/interactivemedia/v3/internal/ba
    //   3896	3903	4653	com/google/ads/interactivemedia/v3/internal/ba
    //   3923	3932	4653	com/google/ads/interactivemedia/v3/internal/ba
    //   3938	3947	4653	com/google/ads/interactivemedia/v3/internal/ba
    //   3952	3959	4653	com/google/ads/interactivemedia/v3/internal/ba
    //   3968	3981	4653	com/google/ads/interactivemedia/v3/internal/ba
    //   3981	4000	4653	com/google/ads/interactivemedia/v3/internal/ba
    //   4003	4030	4653	com/google/ads/interactivemedia/v3/internal/ba
    //   4038	4045	4653	com/google/ads/interactivemedia/v3/internal/ba
    //   4051	4076	4653	com/google/ads/interactivemedia/v3/internal/ba
    //   4087	4115	4653	com/google/ads/interactivemedia/v3/internal/ba
    //   4126	4142	4653	com/google/ads/interactivemedia/v3/internal/ba
    //   4145	4171	4653	com/google/ads/interactivemedia/v3/internal/ba
    //   4179	4196	4653	com/google/ads/interactivemedia/v3/internal/ba
    //   4196	4216	4653	com/google/ads/interactivemedia/v3/internal/ba
    //   4224	4232	4653	com/google/ads/interactivemedia/v3/internal/ba
    //   4238	4256	4653	com/google/ads/interactivemedia/v3/internal/ba
    //   4256	4264	4653	com/google/ads/interactivemedia/v3/internal/ba
    //   4269	4278	4653	com/google/ads/interactivemedia/v3/internal/ba
    //   4281	4289	4653	com/google/ads/interactivemedia/v3/internal/ba
    //   4294	4303	4653	com/google/ads/interactivemedia/v3/internal/ba
    //   4306	4314	4653	com/google/ads/interactivemedia/v3/internal/ba
    //   4314	4317	4653	com/google/ads/interactivemedia/v3/internal/ba
    //   4320	4325	4653	com/google/ads/interactivemedia/v3/internal/ba
    //   4338	4343	4653	com/google/ads/interactivemedia/v3/internal/ba
    //   4343	4349	4653	com/google/ads/interactivemedia/v3/internal/ba
    //   4354	4362	4653	com/google/ads/interactivemedia/v3/internal/ba
    //   4365	4373	4653	com/google/ads/interactivemedia/v3/internal/ba
    //   4378	4391	4653	com/google/ads/interactivemedia/v3/internal/ba
    //   4399	4408	4653	com/google/ads/interactivemedia/v3/internal/ba
    //   4418	4434	4653	com/google/ads/interactivemedia/v3/internal/ba
    //   4443	4450	4653	com/google/ads/interactivemedia/v3/internal/ba
    //   4459	4522	4653	com/google/ads/interactivemedia/v3/internal/ba
    //   4522	4526	4653	com/google/ads/interactivemedia/v3/internal/ba
  }
}

/* Location:
 * Qualified Name:     com.google.ads.interactivemedia.v3.internal.bo
 * Java Class Version: 6 (50.0)
 * JD-Core Version:    0.7.1
 */