package com.google.ads.interactivemedia.v3.internal;

import android.text.TextUtils;
import android.util.Base64;
import android.util.Log;
import android.util.Pair;
import java.io.IOException;
import java.util.ArrayList;
import java.util.List;
import java.util.UUID;
import java.util.regex.Matcher;
import java.util.regex.Pattern;
import org.xml.sax.helpers.DefaultHandler;
import org.xmlpull.v1.XmlPullParser;
import org.xmlpull.v1.XmlPullParserException;
import org.xmlpull.v1.XmlPullParserFactory;

public final class pw
  extends DefaultHandler
  implements uy<aaa>
{
  private static final Pattern a = Pattern.compile("(\\d+)(?:/(\\d+))?");
  private static final Pattern b = Pattern.compile("CC([1-4])=.*");
  private static final Pattern c = Pattern.compile("([1-9]|[1-5][0-9]|6[0-3])=.*");
  private final XmlPullParserFactory d;
  
  public pw()
  {
    try
    {
      d = XmlPullParserFactory.newInstance();
      return;
    }
    catch (XmlPullParserException localXmlPullParserException)
    {
      throw new RuntimeException("Couldn't create XmlPullParserFactory instance", localXmlPullParserException);
    }
  }
  
  private static float a(XmlPullParser paramXmlPullParser, float paramFloat)
  {
    paramXmlPullParser = paramXmlPullParser.getAttributeValue(null, "frameRate");
    float f = paramFloat;
    if (paramXmlPullParser != null)
    {
      paramXmlPullParser = a.matcher(paramXmlPullParser);
      f = paramFloat;
      if (paramXmlPullParser.matches())
      {
        int i = Integer.parseInt(paramXmlPullParser.group(1));
        paramXmlPullParser = paramXmlPullParser.group(2);
        if (!TextUtils.isEmpty(paramXmlPullParser)) {
          f = i / Integer.parseInt(paramXmlPullParser);
        } else {
          f = i;
        }
      }
    }
    return f;
  }
  
  private static int a(int paramInt1, int paramInt2)
  {
    if (paramInt1 == -1) {
      return paramInt2;
    }
    if (paramInt2 == -1) {
      return paramInt1;
    }
    boolean bool;
    if (paramInt1 == paramInt2) {
      bool = true;
    } else {
      bool = false;
    }
    rp.c(bool);
    return paramInt1;
  }
  
  private static int a(String paramString)
  {
    if (paramString == null) {
      return 0;
    }
    int i = -1;
    switch (paramString.hashCode())
    {
    default: 
      break;
    case 1855372047: 
      if (paramString.equals("supplementary")) {
        i = 10;
      }
      break;
    case 1629013393: 
      if (paramString.equals("emergency")) {
        i = 9;
      }
      break;
    case 899152809: 
      if (paramString.equals("commentary")) {
        i = 8;
      }
      break;
    case 552573414: 
      if (paramString.equals("caption")) {
        i = 7;
      }
      break;
    case 3530173: 
      if (paramString.equals("sign")) {
        i = 6;
      }
      break;
    case 3343801: 
      if (paramString.equals("main")) {
        i = 5;
      }
      break;
    case 99825: 
      if (paramString.equals("dub")) {
        i = 4;
      }
      break;
    case -1408024454: 
      if (paramString.equals("alternate")) {
        i = 3;
      }
      break;
    case -1580883024: 
      if (paramString.equals("enhanced-audio-intelligibility")) {
        i = 2;
      }
      break;
    case -1724546052: 
      if (paramString.equals("description")) {
        i = 1;
      }
      break;
    case -2060497896: 
      if (paramString.equals("subtitle")) {
        i = 0;
      }
      break;
    }
    switch (i)
    {
    default: 
      return 0;
    case 10: 
      return 4;
    case 9: 
      return 32;
    case 8: 
      return 8;
    case 7: 
      return 64;
    case 6: 
      return 256;
    case 5: 
      return 1;
    case 4: 
      return 16;
    case 3: 
      return 2;
    case 2: 
      return 2048;
    case 1: 
      return 512;
    }
    return 128;
  }
  
  private static int a(XmlPullParser paramXmlPullParser)
  {
    paramXmlPullParser = paramXmlPullParser.getAttributeValue(null, "contentType");
    if (!TextUtils.isEmpty(paramXmlPullParser))
    {
      if ("audio".equals(paramXmlPullParser)) {
        return 1;
      }
      if ("video".equals(paramXmlPullParser)) {
        return 2;
      }
      if ("text".equals(paramXmlPullParser)) {
        return 3;
      }
    }
    return -1;
  }
  
  private static int a(XmlPullParser paramXmlPullParser, String paramString, int paramInt)
  {
    paramXmlPullParser = paramXmlPullParser.getAttributeValue(null, paramString);
    if (paramXmlPullParser == null) {
      return paramInt;
    }
    return Integer.parseInt(paramXmlPullParser);
  }
  
  private final long a(List<ql> paramList, long paramLong1, long paramLong2, int paramInt, long paramLong3)
  {
    if (paramInt >= 0) {
      paramInt++;
    } else {
      paramInt = (int)wl.a(paramLong3 - paramLong1, paramLong2);
    }
    for (int i = 0; i < paramInt; i++)
    {
      paramList.add(new ql(paramLong1, paramLong2));
      paramLong1 += paramLong2;
    }
    return paramLong1;
  }
  
  private static long a(XmlPullParser paramXmlPullParser, String paramString, long paramLong)
  {
    paramXmlPullParser = paramXmlPullParser.getAttributeValue(null, paramString);
    if (paramXmlPullParser == null) {
      return paramLong;
    }
    return wl.f(paramXmlPullParser);
  }
  
  private static pz a(XmlPullParser paramXmlPullParser, String paramString)
    throws XmlPullParserException, IOException
  {
    String str1 = b(paramXmlPullParser, "schemeIdUri", "");
    String str2 = b(paramXmlPullParser, "value", null);
    String str3 = b(paramXmlPullParser, "id", null);
    do
    {
      paramXmlPullParser.next();
    } while (!rp.a(paramXmlPullParser, paramString));
    return new pz(str1, str2, str3);
  }
  
  private final qd a(XmlPullParser paramXmlPullParser, String paramString1, String paramString2)
  {
    paramString1 = paramXmlPullParser.getAttributeValue(null, paramString1);
    paramXmlPullParser = paramXmlPullParser.getAttributeValue(null, paramString2);
    long l2;
    if (paramXmlPullParser != null)
    {
      paramXmlPullParser = paramXmlPullParser.split("-");
      l1 = Long.parseLong(paramXmlPullParser[0]);
      l2 = l1;
      if (paramXmlPullParser.length == 2)
      {
        long l3 = Long.parseLong(paramXmlPullParser[1]) - l1 + 1L;
        l2 = l1;
        l1 = l3;
        break label79;
      }
    }
    else
    {
      l2 = 0L;
    }
    long l1 = -1L;
    label79:
    return new qd(paramString1, l2, l1);
  }
  
  private final qi a(XmlPullParser paramXmlPullParser, qi paramqi, List<pz> paramList, long paramLong)
    throws XmlPullParserException, IOException
  {
    long l1 = 1L;
    if (paramqi != null) {
      l2 = e;
    } else {
      l2 = 1L;
    }
    long l3 = c(paramXmlPullParser, "timescale", l2);
    if (paramqi != null) {
      l2 = f;
    } else {
      l2 = 0L;
    }
    long l4 = c(paramXmlPullParser, "presentationTimeOffset", l2);
    if (paramqi != null) {
      l2 = b;
    } else {
      l2 = -9223372036854775807L;
    }
    long l5 = c(paramXmlPullParser, "duration", l2);
    long l2 = l1;
    if (paramqi != null) {
      l2 = a;
    }
    l1 = c(paramXmlPullParser, "startNumber", l2);
    Object localObject1;
    for (int i = 0; i < paramList.size(); i++)
    {
      localObject1 = (pz)paramList.get(i);
      if ("http://dashif.org/guidelines/last-segment-number".equalsIgnoreCase(a))
      {
        l2 = Long.parseLong(b);
        break label171;
      }
    }
    l2 = -1L;
    label171:
    Object localObject2 = null;
    if (paramqi != null) {
      paramList = h;
    } else {
      paramList = null;
    }
    qm localqm1 = a(paramXmlPullParser, "media", paramList);
    if (paramqi != null) {
      paramList = g;
    } else {
      paramList = null;
    }
    qm localqm2 = a(paramXmlPullParser, "initialization", paramList);
    List<pz> localList = null;
    do
    {
      paramXmlPullParser.next();
      if (rp.b(paramXmlPullParser, "Initialization"))
      {
        paramList = c(paramXmlPullParser);
        localObject1 = localObject2;
      }
      else if (rp.b(paramXmlPullParser, "SegmentTimeline"))
      {
        localObject1 = a(paramXmlPullParser, l3, paramLong);
        paramList = localList;
      }
      else
      {
        e(paramXmlPullParser);
        paramList = localList;
        localObject1 = localObject2;
      }
      localObject2 = localObject1;
      localList = paramList;
    } while (!rp.a(paramXmlPullParser, "SegmentTemplate"));
    paramXmlPullParser = (XmlPullParser)localObject1;
    localList = paramList;
    if (paramqi != null)
    {
      if (paramList == null) {
        paramList = d;
      }
      if (localObject1 != null)
      {
        paramXmlPullParser = (XmlPullParser)localObject1;
        localList = paramList;
      }
      else
      {
        paramXmlPullParser = c;
        localList = paramList;
      }
    }
    return new qi(localList, l3, l4, l1, l2, l5, paramXmlPullParser, localqm2, localqm1);
  }
  
  private final qj a(XmlPullParser paramXmlPullParser, qj paramqj, long paramLong)
    throws XmlPullParserException, IOException
  {
    long l1 = 1L;
    if (paramqj != null) {
      l2 = e;
    } else {
      l2 = 1L;
    }
    long l3 = c(paramXmlPullParser, "timescale", l2);
    if (paramqj != null) {
      l2 = f;
    } else {
      l2 = 0L;
    }
    long l4 = c(paramXmlPullParser, "presentationTimeOffset", l2);
    if (paramqj != null) {
      l2 = b;
    } else {
      l2 = -9223372036854775807L;
    }
    long l5 = c(paramXmlPullParser, "duration", l2);
    long l2 = l1;
    if (paramqj != null) {
      l2 = a;
    }
    l2 = c(paramXmlPullParser, "startNumber", l2);
    Object localObject1 = null;
    Object localObject2 = null;
    Object localObject3 = localObject2;
    Object localObject4;
    Object localObject5;
    Object localObject6;
    do
    {
      paramXmlPullParser.next();
      if (rp.b(paramXmlPullParser, "Initialization"))
      {
        localObject4 = c(paramXmlPullParser);
        localObject5 = localObject1;
        localObject6 = localObject2;
      }
      else if (rp.b(paramXmlPullParser, "SegmentTimeline"))
      {
        localObject5 = a(paramXmlPullParser, l3, paramLong);
        localObject6 = localObject2;
        localObject4 = localObject3;
      }
      else if (rp.b(paramXmlPullParser, "SegmentURL"))
      {
        localObject6 = localObject2;
        if (localObject2 == null) {
          localObject6 = new ArrayList();
        }
        ((List)localObject6).add(a(paramXmlPullParser, "media", "mediaRange"));
        localObject5 = localObject1;
        localObject4 = localObject3;
      }
      else
      {
        e(paramXmlPullParser);
        localObject4 = localObject3;
        localObject6 = localObject2;
        localObject5 = localObject1;
      }
      localObject1 = localObject5;
      localObject2 = localObject6;
      localObject3 = localObject4;
    } while (!rp.a(paramXmlPullParser, "SegmentList"));
    localObject3 = localObject5;
    localObject2 = localObject6;
    paramXmlPullParser = (XmlPullParser)localObject4;
    if (paramqj != null)
    {
      if (localObject4 == null) {
        localObject4 = d;
      }
      if (localObject5 == null) {
        localObject5 = c;
      }
      if (localObject6 != null)
      {
        localObject3 = localObject5;
        localObject2 = localObject6;
        paramXmlPullParser = (XmlPullParser)localObject4;
      }
      else
      {
        localObject2 = g;
        paramXmlPullParser = (XmlPullParser)localObject4;
        localObject3 = localObject5;
      }
    }
    return new qj(paramXmlPullParser, l3, l4, l2, l5, (List)localObject3, (List)localObject2);
  }
  
  private final qk a(XmlPullParser paramXmlPullParser, qk paramqk)
    throws XmlPullParserException, IOException
  {
    long l1;
    if (paramqk != null) {
      l1 = e;
    } else {
      l1 = 1L;
    }
    long l2 = c(paramXmlPullParser, "timescale", l1);
    long l3 = 0L;
    if (paramqk != null) {
      l1 = f;
    } else {
      l1 = 0L;
    }
    long l4 = c(paramXmlPullParser, "presentationTimeOffset", l1);
    if (paramqk != null) {
      l1 = a;
    } else {
      l1 = 0L;
    }
    if (paramqk != null) {
      l3 = b;
    }
    Object localObject1 = null;
    Object localObject2 = paramXmlPullParser.getAttributeValue(null, "indexRange");
    if (localObject2 != null)
    {
      localObject2 = ((String)localObject2).split("-");
      l1 = Long.parseLong(localObject2[0]);
      l3 = Long.parseLong(localObject2[1]) - l1 + 1L;
    }
    if (paramqk != null) {
      localObject1 = d;
    }
    do
    {
      paramXmlPullParser.next();
      if (rp.b(paramXmlPullParser, "Initialization"))
      {
        paramqk = c(paramXmlPullParser);
      }
      else
      {
        e(paramXmlPullParser);
        paramqk = (qk)localObject1;
      }
      localObject1 = paramqk;
    } while (!rp.a(paramXmlPullParser, "SegmentBase"));
    return new qk(paramqk, l2, l4, l1, l3);
  }
  
  private static qm a(XmlPullParser paramXmlPullParser, String paramString, qm paramqm)
  {
    paramXmlPullParser = paramXmlPullParser.getAttributeValue(null, paramString);
    if (paramXmlPullParser != null) {
      return qm.a(paramXmlPullParser);
    }
    return paramqm;
  }
  
  private final List<ql> a(XmlPullParser paramXmlPullParser, long paramLong1, long paramLong2)
    throws XmlPullParserException, IOException
  {
    ArrayList localArrayList = new ArrayList();
    long l1 = 0L;
    int i = 0;
    int j = i;
    long l2 = -9223372036854775807L;
    long l3;
    long l4;
    int k;
    int m;
    do
    {
      paramXmlPullParser.next();
      if (rp.b(paramXmlPullParser, "S"))
      {
        l3 = c(paramXmlPullParser, "t", -9223372036854775807L);
        l4 = l1;
        if (i != 0) {
          l4 = a(localArrayList, l1, l2, j, l3);
        }
        if (l3 != -9223372036854775807L) {
          l1 = l3;
        } else {
          l1 = l4;
        }
        l3 = c(paramXmlPullParser, "d", -9223372036854775807L);
        k = a(paramXmlPullParser, "r", 0);
        m = 1;
        l4 = l1;
      }
      else
      {
        e(paramXmlPullParser);
        k = j;
        l3 = l2;
        l4 = l1;
        m = i;
      }
      i = m;
      l1 = l4;
      l2 = l3;
      j = k;
    } while (!rp.a(paramXmlPullParser, "SegmentTimeline"));
    if (m != 0) {
      a(localArrayList, l4, l3, k, wl.c(paramLong2, paramLong1, 1000L));
    }
    return localArrayList;
  }
  
  private static long b(XmlPullParser paramXmlPullParser, String paramString, long paramLong)
    throws ce
  {
    paramXmlPullParser = paramXmlPullParser.getAttributeValue(null, paramString);
    if (paramXmlPullParser == null) {
      return -9223372036854775807L;
    }
    return wl.g(paramXmlPullParser);
  }
  
  private static Pair<String, fe.a> b(XmlPullParser paramXmlPullParser)
    throws XmlPullParserException, IOException
  {
    Object localObject1 = null;
    Object localObject2 = paramXmlPullParser.getAttributeValue(null, "schemeIdUri");
    Object localObject3;
    Object localObject5;
    if (localObject2 != null)
    {
      localObject2 = wl.d((String)localObject2);
      localObject2.getClass();
      int i = -1;
      switch (((String)localObject2).hashCode())
      {
      default: 
        break;
      case 1812765994: 
        if (((String)localObject2).equals("urn:mpeg:dash:mp4protection:2011")) {
          i = 2;
        }
        break;
      case 755418770: 
        if (((String)localObject2).equals("urn:uuid:edef8ba9-79d6-4ace-a3c8-27dcd51d21ed")) {
          i = 1;
        }
        break;
      case 489446379: 
        if (((String)localObject2).equals("urn:uuid:9a04f079-9840-4286-ab92-e65be0885f95")) {
          i = 0;
        }
        break;
      }
      switch (i)
      {
      default: 
        break;
      case 2: 
        localObject3 = paramXmlPullParser.getAttributeValue(null, "value");
        localObject2 = rp.d(paramXmlPullParser, "default_KID");
        if ((!TextUtils.isEmpty((CharSequence)localObject2)) && (!"00000000-0000-0000-0000-000000000000".equals(localObject2)))
        {
          localObject4 = ((String)localObject2).split("\\s+");
          localObject2 = new UUID[localObject4.length];
          for (i = 0; i < localObject4.length; i++) {
            localObject2[i] = UUID.fromString(localObject4[i]);
          }
          localObject5 = av.b;
          localObject6 = hu.a((UUID)localObject5, (UUID[])localObject2, null);
          localObject4 = null;
          localObject7 = localObject3;
          break label295;
        }
        break;
      case 1: 
        localObject5 = av.d;
        break;
      case 0: 
        localObject5 = av.e;
      }
      localObject3 = null;
      localObject2 = localObject3;
    }
    else
    {
      localObject3 = null;
      localObject5 = null;
      localObject2 = null;
    }
    Object localObject4 = localObject2;
    Object localObject6 = localObject2;
    Object localObject7 = localObject3;
    label295:
    Object localObject8;
    label495:
    do
    {
      paramXmlPullParser.next();
      if (rp.b(paramXmlPullParser, "ms:laurl"))
      {
        localObject8 = paramXmlPullParser.getAttributeValue(null, "licenseUrl");
        localObject3 = localObject5;
        localObject2 = localObject6;
      }
      else if ((localObject6 == null) && (rp.c(paramXmlPullParser, "pssh")) && (paramXmlPullParser.next() == 4))
      {
        localObject2 = Base64.decode(paramXmlPullParser.getText(), 0);
        localObject5 = hu.a((byte[])localObject2);
        if (localObject5 == null)
        {
          Log.w("MpdParser", "Skipping malformed cenc:pssh data");
          localObject2 = null;
          localObject3 = localObject5;
          localObject8 = localObject4;
        }
        else
        {
          localObject3 = localObject5;
          localObject8 = localObject4;
        }
      }
      else
      {
        if (localObject6 == null)
        {
          localObject2 = av.e;
          if ((((UUID)localObject2).equals(localObject5)) && (rp.b(paramXmlPullParser, "mspr:pro")) && (paramXmlPullParser.next() == 4))
          {
            localObject2 = hu.a((UUID)localObject2, null, Base64.decode(paramXmlPullParser.getText(), 0));
            localObject3 = localObject5;
            localObject8 = localObject4;
            break label495;
          }
        }
        e(paramXmlPullParser);
        localObject8 = localObject4;
        localObject2 = localObject6;
        localObject3 = localObject5;
      }
      localObject5 = localObject3;
      localObject6 = localObject2;
      localObject4 = localObject8;
    } while (!rp.a(paramXmlPullParser, "ContentProtection"));
    paramXmlPullParser = (XmlPullParser)localObject1;
    if (localObject3 != null) {
      paramXmlPullParser = new fe.a((UUID)localObject3, (String)localObject8, "video/mp4", (byte[])localObject2);
    }
    return Pair.create(localObject7, paramXmlPullParser);
  }
  
  /* Error */
  private final aaa b(android.net.Uri paramUri, java.io.InputStream paramInputStream)
    throws IOException
  {
    // Byte code:
    //   0: aload_0
    //   1: astore_3
    //   2: ldc_w 448
    //   5: astore 4
    //   7: ldc_w 450
    //   10: astore 5
    //   12: ldc_w 452
    //   15: astore 6
    //   17: ldc -82
    //   19: astore 7
    //   21: ldc_w 454
    //   24: astore 8
    //   26: aload_3
    //   27: astore 9
    //   29: aload_3
    //   30: getfield 47	com/google/ads/interactivemedia/v3/internal/pw:d	Lorg/xmlpull/v1/XmlPullParserFactory;
    //   33: invokevirtual 458	org/xmlpull/v1/XmlPullParserFactory:newPullParser	()Lorg/xmlpull/v1/XmlPullParser;
    //   36: astore 10
    //   38: aconst_null
    //   39: astore 11
    //   41: aload_3
    //   42: astore 9
    //   44: aload 10
    //   46: aload_2
    //   47: aconst_null
    //   48: invokeinterface 462 3 0
    //   53: aload_3
    //   54: astore 9
    //   56: aload 10
    //   58: invokeinterface 177 1 0
    //   63: iconst_2
    //   64: if_icmpne +6074 -> 6138
    //   67: aload_3
    //   68: astore 9
    //   70: ldc_w 450
    //   73: aload 10
    //   75: invokeinterface 465 1 0
    //   80: invokevirtual 107	java/lang/String:equals	(Ljava/lang/Object;)Z
    //   83: ifeq +6055 -> 6138
    //   86: aload_3
    //   87: astore 9
    //   89: aload_1
    //   90: invokevirtual 470	android/net/Uri:toString	()Ljava/lang/String;
    //   93: astore_2
    //   94: aload_3
    //   95: astore 9
    //   97: aload 10
    //   99: ldc_w 472
    //   102: ldc2_w 225
    //   105: invokestatic 474	com/google/ads/interactivemedia/v3/internal/pw:b	(Lorg/xmlpull/v1/XmlPullParser;Ljava/lang/String;J)J
    //   108: lstore 12
    //   110: aload_3
    //   111: astore 9
    //   113: aload 10
    //   115: ldc_w 476
    //   118: ldc2_w 225
    //   121: invokestatic 478	com/google/ads/interactivemedia/v3/internal/pw:a	(Lorg/xmlpull/v1/XmlPullParser;Ljava/lang/String;J)J
    //   124: lstore 14
    //   126: aload_3
    //   127: astore 9
    //   129: aload 10
    //   131: ldc_w 480
    //   134: ldc2_w 225
    //   137: invokestatic 478	com/google/ads/interactivemedia/v3/internal/pw:a	(Lorg/xmlpull/v1/XmlPullParser;Ljava/lang/String;J)J
    //   140: lstore 16
    //   142: aload_3
    //   143: astore 9
    //   145: ldc_w 482
    //   148: aload 10
    //   150: aconst_null
    //   151: ldc_w 484
    //   154: invokeinterface 63 3 0
    //   159: invokevirtual 107	java/lang/String:equals	(Ljava/lang/Object;)Z
    //   162: istore 18
    //   164: iload 18
    //   166: ifeq +26 -> 192
    //   169: aload_3
    //   170: astore 9
    //   172: aload 10
    //   174: ldc_w 486
    //   177: ldc2_w 225
    //   180: invokestatic 478	com/google/ads/interactivemedia/v3/internal/pw:a	(Lorg/xmlpull/v1/XmlPullParser;Ljava/lang/String;J)J
    //   183: lstore 19
    //   185: goto +12 -> 197
    //   188: astore_1
    //   189: goto +5967 -> 6156
    //   192: ldc2_w 225
    //   195: lstore 19
    //   197: iload 18
    //   199: ifeq +22 -> 221
    //   202: aload_3
    //   203: astore 9
    //   205: aload 10
    //   207: ldc_w 488
    //   210: ldc2_w 225
    //   213: invokestatic 478	com/google/ads/interactivemedia/v3/internal/pw:a	(Lorg/xmlpull/v1/XmlPullParser;Ljava/lang/String;J)J
    //   216: lstore 21
    //   218: goto +8 -> 226
    //   221: ldc2_w 225
    //   224: lstore 21
    //   226: iload 18
    //   228: ifeq +22 -> 250
    //   231: aload_3
    //   232: astore 9
    //   234: aload 10
    //   236: ldc_w 490
    //   239: ldc2_w 225
    //   242: invokestatic 478	com/google/ads/interactivemedia/v3/internal/pw:a	(Lorg/xmlpull/v1/XmlPullParser;Ljava/lang/String;J)J
    //   245: lstore 23
    //   247: goto +8 -> 255
    //   250: ldc2_w 225
    //   253: lstore 23
    //   255: aload_3
    //   256: astore 9
    //   258: aload 10
    //   260: ldc_w 492
    //   263: ldc2_w 225
    //   266: invokestatic 474	com/google/ads/interactivemedia/v3/internal/pw:b	(Lorg/xmlpull/v1/XmlPullParser;Ljava/lang/String;J)J
    //   269: lstore 25
    //   271: aload_3
    //   272: astore 9
    //   274: new 298	java/util/ArrayList
    //   277: astore 27
    //   279: aload_3
    //   280: astore 9
    //   282: aload 27
    //   284: invokespecial 299	java/util/ArrayList:<init>	()V
    //   287: iload 18
    //   289: ifeq +11 -> 300
    //   292: ldc2_w 225
    //   295: lstore 28
    //   297: goto +6 -> 303
    //   300: lconst_0
    //   301: lstore 28
    //   303: aconst_null
    //   304: astore 30
    //   306: aload 30
    //   308: astore 31
    //   310: aload 31
    //   312: astore 32
    //   314: iconst_0
    //   315: istore 33
    //   317: iload 33
    //   319: istore 34
    //   321: aload_3
    //   322: astore_1
    //   323: lload 28
    //   325: lstore 35
    //   327: aload 27
    //   329: astore_3
    //   330: aload_1
    //   331: astore 9
    //   333: aload 10
    //   335: invokeinterface 177 1 0
    //   340: pop
    //   341: aload_1
    //   342: astore 9
    //   344: aload 10
    //   346: aload 8
    //   348: invokestatic 270	com/google/ads/interactivemedia/v3/internal/rp:b	(Lorg/xmlpull/v1/XmlPullParser;Ljava/lang/String;)Z
    //   351: istore 37
    //   353: iload 37
    //   355: ifeq +66 -> 421
    //   358: iload 33
    //   360: ifne +58 -> 418
    //   363: aload_1
    //   364: astore 9
    //   366: aload 10
    //   368: aload_2
    //   369: invokestatic 494	com/google/ads/interactivemedia/v3/internal/pw:b	(Lorg/xmlpull/v1/XmlPullParser;Ljava/lang/String;)Ljava/lang/String;
    //   372: astore 9
    //   374: aload 11
    //   376: astore_2
    //   377: iconst_1
    //   378: istore 33
    //   380: ldc2_w 225
    //   383: lstore 28
    //   385: aload 6
    //   387: astore 27
    //   389: aload 7
    //   391: astore 38
    //   393: aload_1
    //   394: astore 7
    //   396: aload_3
    //   397: astore_1
    //   398: aload 10
    //   400: astore 11
    //   402: aload_2
    //   403: astore 6
    //   405: aload 38
    //   407: astore 10
    //   409: aload 27
    //   411: astore_2
    //   412: aload 9
    //   414: astore_3
    //   415: goto +5573 -> 5988
    //   418: goto +5531 -> 5949
    //   421: aload_1
    //   422: astore 9
    //   424: aload 10
    //   426: aload 4
    //   428: invokestatic 270	com/google/ads/interactivemedia/v3/internal/rp:b	(Lorg/xmlpull/v1/XmlPullParser;Ljava/lang/String;)Z
    //   431: istore 37
    //   433: ldc_w 496
    //   436: astore 39
    //   438: iload 37
    //   440: ifeq +197 -> 637
    //   443: aload_1
    //   444: astore 9
    //   446: aload 10
    //   448: ldc_w 498
    //   451: aload 11
    //   453: invokestatic 170	com/google/ads/interactivemedia/v3/internal/pw:b	(Lorg/xmlpull/v1/XmlPullParser;Ljava/lang/String;Ljava/lang/String;)Ljava/lang/String;
    //   456: astore 40
    //   458: aload_1
    //   459: astore 9
    //   461: aload 10
    //   463: ldc_w 496
    //   466: aload 11
    //   468: invokestatic 170	com/google/ads/interactivemedia/v3/internal/pw:b	(Lorg/xmlpull/v1/XmlPullParser;Ljava/lang/String;Ljava/lang/String;)Ljava/lang/String;
    //   471: astore 41
    //   473: aload 11
    //   475: astore 9
    //   477: aload 9
    //   479: astore 27
    //   481: aload 9
    //   483: astore 38
    //   485: aload_1
    //   486: astore 9
    //   488: aload 10
    //   490: invokeinterface 177 1 0
    //   495: pop
    //   496: aload_1
    //   497: astore 9
    //   499: aload 10
    //   501: ldc_w 500
    //   504: invokestatic 270	com/google/ads/interactivemedia/v3/internal/rp:b	(Lorg/xmlpull/v1/XmlPullParser;Ljava/lang/String;)Z
    //   507: ifeq +18 -> 525
    //   510: aload_1
    //   511: astore 9
    //   513: aload 10
    //   515: invokeinterface 503 1 0
    //   520: astore 11
    //   522: goto +69 -> 591
    //   525: aload_1
    //   526: astore 9
    //   528: aload 10
    //   530: ldc_w 505
    //   533: invokestatic 270	com/google/ads/interactivemedia/v3/internal/rp:b	(Lorg/xmlpull/v1/XmlPullParser;Ljava/lang/String;)Z
    //   536: ifeq +18 -> 554
    //   539: aload_1
    //   540: astore 9
    //   542: aload 10
    //   544: invokeinterface 503 1 0
    //   549: astore 38
    //   551: goto +40 -> 591
    //   554: aload_1
    //   555: astore 9
    //   557: aload 10
    //   559: ldc_w 507
    //   562: invokestatic 270	com/google/ads/interactivemedia/v3/internal/rp:b	(Lorg/xmlpull/v1/XmlPullParser;Ljava/lang/String;)Z
    //   565: ifeq +18 -> 583
    //   568: aload_1
    //   569: astore 9
    //   571: aload 10
    //   573: invokeinterface 503 1 0
    //   578: astore 27
    //   580: goto +11 -> 591
    //   583: aload_1
    //   584: astore 9
    //   586: aload 10
    //   588: invokestatic 281	com/google/ads/interactivemedia/v3/internal/pw:e	(Lorg/xmlpull/v1/XmlPullParser;)V
    //   591: aload_1
    //   592: astore 9
    //   594: aload 10
    //   596: aload 4
    //   598: invokestatic 180	com/google/ads/interactivemedia/v3/internal/rp:a	(Lorg/xmlpull/v1/XmlPullParser;Ljava/lang/String;)Z
    //   601: ifeq +33 -> 634
    //   604: aload_1
    //   605: astore 9
    //   607: new 509	com/google/ads/interactivemedia/v3/internal/qa
    //   610: dup
    //   611: aload 11
    //   613: aload 38
    //   615: aload 27
    //   617: aload 40
    //   619: aload 41
    //   621: invokespecial 512	com/google/ads/interactivemedia/v3/internal/qa:<init>	(Ljava/lang/String;Ljava/lang/String;Ljava/lang/String;Ljava/lang/String;Ljava/lang/String;)V
    //   624: astore 30
    //   626: aload_2
    //   627: astore 9
    //   629: aconst_null
    //   630: astore_2
    //   631: goto -251 -> 380
    //   634: goto -149 -> 485
    //   637: aload_1
    //   638: astore 9
    //   640: aload 10
    //   642: ldc_w 514
    //   645: invokestatic 270	com/google/ads/interactivemedia/v3/internal/rp:b	(Lorg/xmlpull/v1/XmlPullParser;Ljava/lang/String;)Z
    //   648: istore 37
    //   650: ldc -91
    //   652: astore 38
    //   654: iload 37
    //   656: ifeq +38 -> 694
    //   659: aload_1
    //   660: astore 9
    //   662: new 516	com/google/ads/interactivemedia/v3/internal/qp
    //   665: dup
    //   666: aload 10
    //   668: aconst_null
    //   669: ldc -91
    //   671: invokeinterface 63 3 0
    //   676: aload 10
    //   678: aconst_null
    //   679: ldc -84
    //   681: invokeinterface 63 3 0
    //   686: invokespecial 519	com/google/ads/interactivemedia/v3/internal/qp:<init>	(Ljava/lang/String;Ljava/lang/String;)V
    //   689: astore 31
    //   691: goto +36 -> 727
    //   694: aload_1
    //   695: astore 9
    //   697: aload 10
    //   699: ldc_w 521
    //   702: invokestatic 270	com/google/ads/interactivemedia/v3/internal/rp:b	(Lorg/xmlpull/v1/XmlPullParser;Ljava/lang/String;)Z
    //   705: istore 37
    //   707: iload 37
    //   709: ifeq +26 -> 735
    //   712: aload_1
    //   713: astore 9
    //   715: aload 10
    //   717: invokeinterface 503 1 0
    //   722: invokestatic 525	android/net/Uri:parse	(Ljava/lang/String;)Landroid/net/Uri;
    //   725: astore 32
    //   727: aload_2
    //   728: astore 9
    //   730: aconst_null
    //   731: astore_2
    //   732: goto -352 -> 380
    //   735: aload_1
    //   736: astore 9
    //   738: aload 10
    //   740: ldc_w 527
    //   743: invokestatic 270	com/google/ads/interactivemedia/v3/internal/rp:b	(Lorg/xmlpull/v1/XmlPullParser;Ljava/lang/String;)Z
    //   746: ifeq +5195 -> 5941
    //   749: iload 34
    //   751: ifne +5190 -> 5941
    //   754: aload_1
    //   755: astore 9
    //   757: aload 10
    //   759: aconst_null
    //   760: aload 7
    //   762: invokeinterface 63 3 0
    //   767: astore 42
    //   769: aload_1
    //   770: astore 9
    //   772: aload 10
    //   774: ldc_w 529
    //   777: lload 35
    //   779: invokestatic 478	com/google/ads/interactivemedia/v3/internal/pw:a	(Lorg/xmlpull/v1/XmlPullParser;Ljava/lang/String;J)J
    //   782: lstore 43
    //   784: ldc2_w 225
    //   787: lstore 45
    //   789: aload_1
    //   790: astore 9
    //   792: aload 10
    //   794: ldc -28
    //   796: ldc2_w 225
    //   799: invokestatic 478	com/google/ads/interactivemedia/v3/internal/pw:a	(Lorg/xmlpull/v1/XmlPullParser;Ljava/lang/String;J)J
    //   802: lstore 28
    //   804: aload_1
    //   805: astore 9
    //   807: new 298	java/util/ArrayList
    //   810: astore 27
    //   812: aload_1
    //   813: astore 9
    //   815: aload 27
    //   817: invokespecial 299	java/util/ArrayList:<init>	()V
    //   820: ldc -84
    //   822: astore 47
    //   824: aload_1
    //   825: astore 9
    //   827: new 298	java/util/ArrayList
    //   830: astore 48
    //   832: aload_1
    //   833: astore 9
    //   835: aload 48
    //   837: invokespecial 299	java/util/ArrayList:<init>	()V
    //   840: iconst_0
    //   841: istore 49
    //   843: aconst_null
    //   844: astore 50
    //   846: aload_2
    //   847: astore 11
    //   849: lload 35
    //   851: lstore 51
    //   853: aload 8
    //   855: astore 53
    //   857: aload 7
    //   859: astore 8
    //   861: aload 6
    //   863: astore 41
    //   865: lload 45
    //   867: lstore 35
    //   869: aload_3
    //   870: astore 6
    //   872: aload 38
    //   874: astore 7
    //   876: aload 27
    //   878: astore_3
    //   879: aload_1
    //   880: astore 9
    //   882: aload 10
    //   884: invokeinterface 177 1 0
    //   889: pop
    //   890: aload_1
    //   891: astore 9
    //   893: aload 10
    //   895: aload 53
    //   897: invokestatic 270	com/google/ads/interactivemedia/v3/internal/rp:b	(Lorg/xmlpull/v1/XmlPullParser;Ljava/lang/String;)Z
    //   900: istore 37
    //   902: iload 37
    //   904: ifeq +83 -> 987
    //   907: iload 49
    //   909: ifne +71 -> 980
    //   912: aload_1
    //   913: astore 9
    //   915: aload 10
    //   917: aload 11
    //   919: invokestatic 494	com/google/ads/interactivemedia/v3/internal/pw:b	(Lorg/xmlpull/v1/XmlPullParser;Ljava/lang/String;)Ljava/lang/String;
    //   922: astore 54
    //   924: iconst_1
    //   925: istore 49
    //   927: aload 7
    //   929: astore 38
    //   931: aload_2
    //   932: astore 11
    //   934: aload 6
    //   936: astore 27
    //   938: lload 35
    //   940: lstore 45
    //   942: aload 41
    //   944: astore_2
    //   945: aload 10
    //   947: astore 6
    //   949: aload_3
    //   950: astore 9
    //   952: aload_1
    //   953: astore 7
    //   955: aload 8
    //   957: astore 10
    //   959: lload 28
    //   961: lstore 35
    //   963: lload 45
    //   965: lstore 28
    //   967: aload 27
    //   969: astore_1
    //   970: aload 11
    //   972: astore_3
    //   973: aload 53
    //   975: astore 8
    //   977: goto +4711 -> 5688
    //   980: aload 11
    //   982: astore 54
    //   984: goto -57 -> 927
    //   987: aload_1
    //   988: astore 9
    //   990: aload 10
    //   992: ldc_w 531
    //   995: invokestatic 270	com/google/ads/interactivemedia/v3/internal/rp:b	(Lorg/xmlpull/v1/XmlPullParser;Ljava/lang/String;)Z
    //   998: istore 37
    //   1000: aload 11
    //   1002: astore 54
    //   1004: aload 6
    //   1006: astore 55
    //   1008: iload 37
    //   1010: ifeq +3694 -> 4704
    //   1013: aload_1
    //   1014: astore 9
    //   1016: aload 10
    //   1018: aload 8
    //   1020: iconst_m1
    //   1021: invokestatic 340	com/google/ads/interactivemedia/v3/internal/pw:a	(Lorg/xmlpull/v1/XmlPullParser;Ljava/lang/String;I)I
    //   1024: istore 56
    //   1026: aload_1
    //   1027: astore 9
    //   1029: aload 10
    //   1031: invokestatic 533	com/google/ads/interactivemedia/v3/internal/pw:a	(Lorg/xmlpull/v1/XmlPullParser;)I
    //   1034: istore 57
    //   1036: aload_2
    //   1037: astore 27
    //   1039: aload_1
    //   1040: astore 9
    //   1042: aload 10
    //   1044: aconst_null
    //   1045: ldc_w 535
    //   1048: invokeinterface 63 3 0
    //   1053: astore 58
    //   1055: aload_3
    //   1056: astore 38
    //   1058: aload_1
    //   1059: astore 9
    //   1061: aload 10
    //   1063: aconst_null
    //   1064: ldc_w 537
    //   1067: invokeinterface 63 3 0
    //   1072: astore 59
    //   1074: aload 7
    //   1076: astore 40
    //   1078: aload_1
    //   1079: astore 9
    //   1081: aload 10
    //   1083: ldc_w 539
    //   1086: iconst_m1
    //   1087: invokestatic 340	com/google/ads/interactivemedia/v3/internal/pw:a	(Lorg/xmlpull/v1/XmlPullParser;Ljava/lang/String;I)I
    //   1090: istore 60
    //   1092: ldc_w 283
    //   1095: astore 6
    //   1097: aload_1
    //   1098: astore 9
    //   1100: aload 10
    //   1102: ldc_w 541
    //   1105: iconst_m1
    //   1106: invokestatic 340	com/google/ads/interactivemedia/v3/internal/pw:a	(Lorg/xmlpull/v1/XmlPullParser;Ljava/lang/String;I)I
    //   1109: istore 61
    //   1111: aload_1
    //   1112: astore 9
    //   1114: aload 10
    //   1116: ldc_w 542
    //   1119: invokestatic 544	com/google/ads/interactivemedia/v3/internal/pw:a	(Lorg/xmlpull/v1/XmlPullParser;F)F
    //   1122: fstore 62
    //   1124: aload_1
    //   1125: astore 9
    //   1127: aload 10
    //   1129: ldc_w 546
    //   1132: iconst_m1
    //   1133: invokestatic 340	com/google/ads/interactivemedia/v3/internal/pw:a	(Lorg/xmlpull/v1/XmlPullParser;Ljava/lang/String;I)I
    //   1136: istore 63
    //   1138: aload_1
    //   1139: astore 9
    //   1141: aload 10
    //   1143: aconst_null
    //   1144: aload 39
    //   1146: invokeinterface 63 3 0
    //   1151: astore_3
    //   1152: ldc_w 305
    //   1155: astore_2
    //   1156: aload_1
    //   1157: astore 9
    //   1159: aload 10
    //   1161: aconst_null
    //   1162: ldc_w 548
    //   1165: invokeinterface 63 3 0
    //   1170: astore 64
    //   1172: aload_1
    //   1173: astore 9
    //   1175: new 298	java/util/ArrayList
    //   1178: astore 65
    //   1180: aload_1
    //   1181: astore 9
    //   1183: aload 65
    //   1185: invokespecial 299	java/util/ArrayList:<init>	()V
    //   1188: aload_1
    //   1189: astore 9
    //   1191: new 298	java/util/ArrayList
    //   1194: astore 66
    //   1196: aload_1
    //   1197: astore 9
    //   1199: aload 66
    //   1201: invokespecial 299	java/util/ArrayList:<init>	()V
    //   1204: aload_1
    //   1205: astore 9
    //   1207: new 298	java/util/ArrayList
    //   1210: astore 67
    //   1212: aload_1
    //   1213: astore 9
    //   1215: aload 67
    //   1217: invokespecial 299	java/util/ArrayList:<init>	()V
    //   1220: new 298	java/util/ArrayList
    //   1223: astore 68
    //   1225: aload 68
    //   1227: invokespecial 299	java/util/ArrayList:<init>	()V
    //   1230: ldc_w 321
    //   1233: astore 9
    //   1235: new 298	java/util/ArrayList
    //   1238: astore 69
    //   1240: aload 69
    //   1242: invokespecial 299	java/util/ArrayList:<init>	()V
    //   1245: new 298	java/util/ArrayList
    //   1248: astore 70
    //   1250: aload 70
    //   1252: invokespecial 299	java/util/ArrayList:<init>	()V
    //   1255: iconst_0
    //   1256: istore 71
    //   1258: aload 50
    //   1260: astore 72
    //   1262: aload 54
    //   1264: astore 73
    //   1266: iconst_m1
    //   1267: istore 74
    //   1269: aconst_null
    //   1270: astore 7
    //   1272: lload 28
    //   1274: lstore 35
    //   1276: aload 55
    //   1278: astore 11
    //   1280: lload 51
    //   1282: lstore 28
    //   1284: aload 39
    //   1286: astore 75
    //   1288: aload 10
    //   1290: astore 76
    //   1292: aload 8
    //   1294: astore 77
    //   1296: aload 41
    //   1298: astore_1
    //   1299: aload 68
    //   1301: astore 10
    //   1303: aload 58
    //   1305: astore 41
    //   1307: aload 69
    //   1309: astore 8
    //   1311: aload 59
    //   1313: astore 39
    //   1315: aload 76
    //   1317: invokeinterface 177 1 0
    //   1322: pop
    //   1323: aload 76
    //   1325: aload 53
    //   1327: invokestatic 270	com/google/ads/interactivemedia/v3/internal/rp:b	(Lorg/xmlpull/v1/XmlPullParser;Ljava/lang/String;)Z
    //   1330: ifeq +102 -> 1432
    //   1333: iload 71
    //   1335: ifne +94 -> 1429
    //   1338: aload 76
    //   1340: aload 73
    //   1342: invokestatic 494	com/google/ads/interactivemedia/v3/internal/pw:b	(Lorg/xmlpull/v1/XmlPullParser;Ljava/lang/String;)Ljava/lang/String;
    //   1345: astore 55
    //   1347: iconst_1
    //   1348: istore 71
    //   1350: aload 7
    //   1352: astore 59
    //   1354: aload 53
    //   1356: astore 7
    //   1358: aload_3
    //   1359: astore 53
    //   1361: aload 55
    //   1363: astore_3
    //   1364: aload 40
    //   1366: astore 73
    //   1368: aload 38
    //   1370: astore 58
    //   1372: aload 27
    //   1374: astore 69
    //   1376: aload 41
    //   1378: astore 55
    //   1380: aload 10
    //   1382: astore 38
    //   1384: aload 9
    //   1386: astore 41
    //   1388: aload 11
    //   1390: astore 10
    //   1392: aload 6
    //   1394: astore 27
    //   1396: aload_3
    //   1397: astore 9
    //   1399: aload_2
    //   1400: astore 40
    //   1402: aload_1
    //   1403: astore_2
    //   1404: aload 8
    //   1406: astore 11
    //   1408: aload 10
    //   1410: astore_3
    //   1411: aload 69
    //   1413: astore_1
    //   1414: aload 7
    //   1416: astore 10
    //   1418: aload 58
    //   1420: astore 6
    //   1422: aload 73
    //   1424: astore 8
    //   1426: goto +2765 -> 4191
    //   1429: goto +2676 -> 4105
    //   1432: aload 73
    //   1434: astore 55
    //   1436: aload 76
    //   1438: ldc_w 431
    //   1441: invokestatic 270	com/google/ads/interactivemedia/v3/internal/rp:b	(Lorg/xmlpull/v1/XmlPullParser;Ljava/lang/String;)Z
    //   1444: ifeq +59 -> 1503
    //   1447: aload 76
    //   1449: invokestatic 550	com/google/ads/interactivemedia/v3/internal/pw:b	(Lorg/xmlpull/v1/XmlPullParser;)Landroid/util/Pair;
    //   1452: astore 73
    //   1454: aload 73
    //   1456: getfield 554	android/util/Pair:first	Ljava/lang/Object;
    //   1459: astore 59
    //   1461: aload 59
    //   1463: ifnull +10 -> 1473
    //   1466: aload 59
    //   1468: checkcast 97	java/lang/String
    //   1471: astore 7
    //   1473: aload 73
    //   1475: getfield 557	android/util/Pair:second	Ljava/lang/Object;
    //   1478: astore 73
    //   1480: aload 73
    //   1482: ifnull +14 -> 1496
    //   1485: aload 65
    //   1487: aload 73
    //   1489: checkcast 433	com/google/ads/interactivemedia/v3/internal/fe$a
    //   1492: invokevirtual 558	java/util/ArrayList:add	(Ljava/lang/Object;)Z
    //   1495: pop
    //   1496: aload 7
    //   1498: astore 59
    //   1500: goto -146 -> 1354
    //   1503: aload 53
    //   1505: astore 59
    //   1507: aload 76
    //   1509: ldc_w 560
    //   1512: invokestatic 270	com/google/ads/interactivemedia/v3/internal/rp:b	(Lorg/xmlpull/v1/XmlPullParser;Ljava/lang/String;)Z
    //   1515: ifeq +75 -> 1590
    //   1518: aload 76
    //   1520: aconst_null
    //   1521: aload 75
    //   1523: invokeinterface 63 3 0
    //   1528: astore 53
    //   1530: aload_3
    //   1531: ifnonnull +9 -> 1540
    //   1534: aload 53
    //   1536: astore_3
    //   1537: goto +20 -> 1557
    //   1540: aload 53
    //   1542: ifnonnull +6 -> 1548
    //   1545: goto +12 -> 1557
    //   1548: aload_3
    //   1549: aload 53
    //   1551: invokevirtual 107	java/lang/String:equals	(Ljava/lang/Object;)Z
    //   1554: invokestatic 95	com/google/ads/interactivemedia/v3/internal/rp:c	(Z)V
    //   1557: iload 57
    //   1559: aload 76
    //   1561: invokestatic 533	com/google/ads/interactivemedia/v3/internal/pw:a	(Lorg/xmlpull/v1/XmlPullParser;)I
    //   1564: invokestatic 562	com/google/ads/interactivemedia/v3/internal/pw:a	(II)I
    //   1567: istore 57
    //   1569: aload 59
    //   1571: astore 73
    //   1573: aload_3
    //   1574: astore 53
    //   1576: aload 55
    //   1578: astore_3
    //   1579: aload 7
    //   1581: astore 59
    //   1583: aload 73
    //   1585: astore 7
    //   1587: goto -223 -> 1364
    //   1590: aload 76
    //   1592: ldc_w 564
    //   1595: invokestatic 270	com/google/ads/interactivemedia/v3/internal/rp:b	(Lorg/xmlpull/v1/XmlPullParser;Ljava/lang/String;)Z
    //   1598: ifeq +20 -> 1618
    //   1601: aload 10
    //   1603: aload 76
    //   1605: ldc_w 564
    //   1608: invokestatic 566	com/google/ads/interactivemedia/v3/internal/pw:a	(Lorg/xmlpull/v1/XmlPullParser;Ljava/lang/String;)Lcom/google/ads/interactivemedia/v3/internal/pz;
    //   1611: invokevirtual 558	java/util/ArrayList:add	(Ljava/lang/Object;)Z
    //   1614: pop
    //   1615: goto -186 -> 1429
    //   1618: aload 76
    //   1620: ldc_w 568
    //   1623: invokestatic 270	com/google/ads/interactivemedia/v3/internal/rp:b	(Lorg/xmlpull/v1/XmlPullParser;Ljava/lang/String;)Z
    //   1626: ifeq +13 -> 1639
    //   1629: aload 76
    //   1631: invokestatic 570	com/google/ads/interactivemedia/v3/internal/pw:d	(Lorg/xmlpull/v1/XmlPullParser;)I
    //   1634: istore 74
    //   1636: goto -140 -> 1496
    //   1639: aload 76
    //   1641: ldc_w 572
    //   1644: invokestatic 270	com/google/ads/interactivemedia/v3/internal/rp:b	(Lorg/xmlpull/v1/XmlPullParser;Ljava/lang/String;)Z
    //   1647: ifeq +20 -> 1667
    //   1650: aload 67
    //   1652: aload 76
    //   1654: ldc_w 572
    //   1657: invokestatic 566	com/google/ads/interactivemedia/v3/internal/pw:a	(Lorg/xmlpull/v1/XmlPullParser;Ljava/lang/String;)Lcom/google/ads/interactivemedia/v3/internal/pz;
    //   1660: invokevirtual 558	java/util/ArrayList:add	(Ljava/lang/Object;)Z
    //   1663: pop
    //   1664: goto -49 -> 1615
    //   1667: aload 76
    //   1669: aload_1
    //   1670: invokestatic 270	com/google/ads/interactivemedia/v3/internal/rp:b	(Lorg/xmlpull/v1/XmlPullParser;Ljava/lang/String;)Z
    //   1673: ifeq +18 -> 1691
    //   1676: aload 8
    //   1678: aload 76
    //   1680: aload_1
    //   1681: invokestatic 566	com/google/ads/interactivemedia/v3/internal/pw:a	(Lorg/xmlpull/v1/XmlPullParser;Ljava/lang/String;)Lcom/google/ads/interactivemedia/v3/internal/pz;
    //   1684: invokevirtual 558	java/util/ArrayList:add	(Ljava/lang/Object;)Z
    //   1687: pop
    //   1688: goto -73 -> 1615
    //   1691: aload 76
    //   1693: ldc_w 574
    //   1696: invokestatic 270	com/google/ads/interactivemedia/v3/internal/rp:b	(Lorg/xmlpull/v1/XmlPullParser;Ljava/lang/String;)Z
    //   1699: istore 37
    //   1701: iload 37
    //   1703: ifeq +1958 -> 3661
    //   1706: aload 76
    //   1708: aconst_null
    //   1709: aload 77
    //   1711: invokeinterface 63 3 0
    //   1716: astore 78
    //   1718: aload 76
    //   1720: ldc_w 576
    //   1723: iconst_m1
    //   1724: invokestatic 340	com/google/ads/interactivemedia/v3/internal/pw:a	(Lorg/xmlpull/v1/XmlPullParser;Ljava/lang/String;I)I
    //   1727: istore 79
    //   1729: aload 76
    //   1731: ldc_w 535
    //   1734: aload 41
    //   1736: invokestatic 170	com/google/ads/interactivemedia/v3/internal/pw:b	(Lorg/xmlpull/v1/XmlPullParser;Ljava/lang/String;Ljava/lang/String;)Ljava/lang/String;
    //   1739: astore 80
    //   1741: aload 76
    //   1743: ldc_w 537
    //   1746: aload 39
    //   1748: invokestatic 170	com/google/ads/interactivemedia/v3/internal/pw:b	(Lorg/xmlpull/v1/XmlPullParser;Ljava/lang/String;Ljava/lang/String;)Ljava/lang/String;
    //   1751: astore 81
    //   1753: aload 76
    //   1755: ldc_w 539
    //   1758: iload 60
    //   1760: invokestatic 340	com/google/ads/interactivemedia/v3/internal/pw:a	(Lorg/xmlpull/v1/XmlPullParser;Ljava/lang/String;I)I
    //   1763: istore 82
    //   1765: aload 41
    //   1767: astore 83
    //   1769: iload 61
    //   1771: istore 84
    //   1773: aload 76
    //   1775: ldc_w 541
    //   1778: iload 84
    //   1780: invokestatic 340	com/google/ads/interactivemedia/v3/internal/pw:a	(Lorg/xmlpull/v1/XmlPullParser;Ljava/lang/String;I)I
    //   1783: istore 85
    //   1785: aload 76
    //   1787: fload 62
    //   1789: invokestatic 544	com/google/ads/interactivemedia/v3/internal/pw:a	(Lorg/xmlpull/v1/XmlPullParser;F)F
    //   1792: fstore 86
    //   1794: iload 60
    //   1796: istore 61
    //   1798: aload 76
    //   1800: ldc_w 546
    //   1803: iload 63
    //   1805: invokestatic 340	com/google/ads/interactivemedia/v3/internal/pw:a	(Lorg/xmlpull/v1/XmlPullParser;Ljava/lang/String;I)I
    //   1808: istore 87
    //   1810: new 298	java/util/ArrayList
    //   1813: astore 68
    //   1815: aload 68
    //   1817: invokespecial 299	java/util/ArrayList:<init>	()V
    //   1820: iload 63
    //   1822: istore 88
    //   1824: new 298	java/util/ArrayList
    //   1827: astore 89
    //   1829: aload 89
    //   1831: invokespecial 299	java/util/ArrayList:<init>	()V
    //   1834: new 298	java/util/ArrayList
    //   1837: astore 90
    //   1839: aload 90
    //   1841: invokespecial 299	java/util/ArrayList:<init>	()V
    //   1844: iconst_0
    //   1845: istore 63
    //   1847: iload 74
    //   1849: istore 60
    //   1851: aload 55
    //   1853: astore 73
    //   1855: aload 72
    //   1857: astore 41
    //   1859: aconst_null
    //   1860: astore 53
    //   1862: aload 59
    //   1864: astore 91
    //   1866: aload 39
    //   1868: astore 58
    //   1870: aload 10
    //   1872: astore 92
    //   1874: aload 55
    //   1876: astore 69
    //   1878: aload 53
    //   1880: astore 10
    //   1882: aload_2
    //   1883: astore 93
    //   1885: aload 6
    //   1887: astore 94
    //   1889: aload 27
    //   1891: astore 39
    //   1893: aload 11
    //   1895: astore 53
    //   1897: aload_1
    //   1898: astore 6
    //   1900: aload 73
    //   1902: astore_1
    //   1903: iload 57
    //   1905: istore 95
    //   1907: aload 80
    //   1909: astore 55
    //   1911: iload 84
    //   1913: istore 57
    //   1915: aload 8
    //   1917: astore 59
    //   1919: aload_3
    //   1920: astore 73
    //   1922: aload 76
    //   1924: invokeinterface 177 1 0
    //   1929: pop
    //   1930: aload 76
    //   1932: aload 91
    //   1934: invokestatic 270	com/google/ads/interactivemedia/v3/internal/rp:b	(Lorg/xmlpull/v1/XmlPullParser;Ljava/lang/String;)Z
    //   1937: ifeq +31 -> 1968
    //   1940: iload 63
    //   1942: ifne +23 -> 1965
    //   1945: aload 76
    //   1947: aload_1
    //   1948: invokestatic 494	com/google/ads/interactivemedia/v3/internal/pw:b	(Lorg/xmlpull/v1/XmlPullParser;Ljava/lang/String;)Ljava/lang/String;
    //   1951: astore_3
    //   1952: iconst_1
    //   1953: istore 63
    //   1955: aload 41
    //   1957: astore_2
    //   1958: iload 60
    //   1960: istore 84
    //   1962: goto +279 -> 2241
    //   1965: goto +267 -> 2232
    //   1968: aload 76
    //   1970: ldc_w 568
    //   1973: invokestatic 270	com/google/ads/interactivemedia/v3/internal/rp:b	(Lorg/xmlpull/v1/XmlPullParser;Ljava/lang/String;)Z
    //   1976: ifeq +18 -> 1994
    //   1979: aload 76
    //   1981: invokestatic 570	com/google/ads/interactivemedia/v3/internal/pw:d	(Lorg/xmlpull/v1/XmlPullParser;)I
    //   1984: istore 60
    //   1986: aload 41
    //   1988: astore_2
    //   1989: aload_1
    //   1990: astore_3
    //   1991: goto -33 -> 1958
    //   1994: aload 76
    //   1996: aload 9
    //   1998: invokestatic 270	com/google/ads/interactivemedia/v3/internal/rp:b	(Lorg/xmlpull/v1/XmlPullParser;Ljava/lang/String;)Z
    //   2001: ifeq +24 -> 2025
    //   2004: aload 41
    //   2006: checkcast 315	com/google/ads/interactivemedia/v3/internal/qk
    //   2009: astore_2
    //   2010: aload_0
    //   2011: aload 76
    //   2013: aload_2
    //   2014: invokespecial 578	com/google/ads/interactivemedia/v3/internal/pw:a	(Lorg/xmlpull/v1/XmlPullParser;Lcom/google/ads/interactivemedia/v3/internal/qk;)Lcom/google/ads/interactivemedia/v3/internal/qk;
    //   2017: astore_2
    //   2018: goto -29 -> 1989
    //   2021: astore_1
    //   2022: goto +4134 -> 6156
    //   2025: aload 76
    //   2027: aload 93
    //   2029: invokestatic 270	com/google/ads/interactivemedia/v3/internal/rp:b	(Lorg/xmlpull/v1/XmlPullParser;Ljava/lang/String;)Z
    //   2032: istore 37
    //   2034: iload 37
    //   2036: ifeq +26 -> 2062
    //   2039: aload_0
    //   2040: aload 76
    //   2042: aload 41
    //   2044: checkcast 307	com/google/ads/interactivemedia/v3/internal/qj
    //   2047: lload 35
    //   2049: invokespecial 580	com/google/ads/interactivemedia/v3/internal/pw:a	(Lorg/xmlpull/v1/XmlPullParser;Lcom/google/ads/interactivemedia/v3/internal/qj;J)Lcom/google/ads/interactivemedia/v3/internal/qj;
    //   2052: astore_2
    //   2053: aload_1
    //   2054: astore_3
    //   2055: iload 60
    //   2057: istore 84
    //   2059: goto +182 -> 2241
    //   2062: aload 76
    //   2064: aload 94
    //   2066: invokestatic 270	com/google/ads/interactivemedia/v3/internal/rp:b	(Lorg/xmlpull/v1/XmlPullParser;Ljava/lang/String;)Z
    //   2069: ifeq +34 -> 2103
    //   2072: aload_0
    //   2073: aload 76
    //   2075: aload 41
    //   2077: checkcast 252	com/google/ads/interactivemedia/v3/internal/qi
    //   2080: aload 59
    //   2082: lload 35
    //   2084: invokespecial 582	com/google/ads/interactivemedia/v3/internal/pw:a	(Lorg/xmlpull/v1/XmlPullParser;Lcom/google/ads/interactivemedia/v3/internal/qi;Ljava/util/List;J)Lcom/google/ads/interactivemedia/v3/internal/qi;
    //   2087: astore_2
    //   2088: aload 10
    //   2090: astore_3
    //   2091: aload_3
    //   2092: astore 10
    //   2094: aload_1
    //   2095: astore_3
    //   2096: iload 60
    //   2098: istore 84
    //   2100: goto +141 -> 2241
    //   2103: aload 76
    //   2105: ldc_w 431
    //   2108: invokestatic 270	com/google/ads/interactivemedia/v3/internal/rp:b	(Lorg/xmlpull/v1/XmlPullParser;Ljava/lang/String;)Z
    //   2111: ifeq +61 -> 2172
    //   2114: aload 76
    //   2116: invokestatic 550	com/google/ads/interactivemedia/v3/internal/pw:b	(Lorg/xmlpull/v1/XmlPullParser;)Landroid/util/Pair;
    //   2119: astore_2
    //   2120: aload_2
    //   2121: getfield 554	android/util/Pair:first	Ljava/lang/Object;
    //   2124: astore_3
    //   2125: aload_3
    //   2126: ifnull +9 -> 2135
    //   2129: aload_3
    //   2130: checkcast 97	java/lang/String
    //   2133: astore 10
    //   2135: aload_2
    //   2136: getfield 557	android/util/Pair:second	Ljava/lang/Object;
    //   2139: astore 8
    //   2141: aload 10
    //   2143: astore_3
    //   2144: aload 41
    //   2146: astore_2
    //   2147: aload 8
    //   2149: ifnull -58 -> 2091
    //   2152: aload 68
    //   2154: aload 8
    //   2156: checkcast 433	com/google/ads/interactivemedia/v3/internal/fe$a
    //   2159: invokevirtual 558	java/util/ArrayList:add	(Ljava/lang/Object;)Z
    //   2162: pop
    //   2163: aload 10
    //   2165: astore_3
    //   2166: aload 41
    //   2168: astore_2
    //   2169: goto -78 -> 2091
    //   2172: aload 76
    //   2174: ldc_w 584
    //   2177: invokestatic 270	com/google/ads/interactivemedia/v3/internal/rp:b	(Lorg/xmlpull/v1/XmlPullParser;Ljava/lang/String;)Z
    //   2180: ifeq +20 -> 2200
    //   2183: aload 89
    //   2185: aload 76
    //   2187: ldc_w 584
    //   2190: invokestatic 566	com/google/ads/interactivemedia/v3/internal/pw:a	(Lorg/xmlpull/v1/XmlPullParser;Ljava/lang/String;)Lcom/google/ads/interactivemedia/v3/internal/pz;
    //   2193: invokevirtual 558	java/util/ArrayList:add	(Ljava/lang/Object;)Z
    //   2196: pop
    //   2197: goto +35 -> 2232
    //   2200: aload 6
    //   2202: astore_2
    //   2203: aload 76
    //   2205: aload_2
    //   2206: invokestatic 270	com/google/ads/interactivemedia/v3/internal/rp:b	(Lorg/xmlpull/v1/XmlPullParser;Ljava/lang/String;)Z
    //   2209: ifeq +18 -> 2227
    //   2212: aload 90
    //   2214: aload 76
    //   2216: aload_2
    //   2217: invokestatic 566	com/google/ads/interactivemedia/v3/internal/pw:a	(Lorg/xmlpull/v1/XmlPullParser;Ljava/lang/String;)Lcom/google/ads/interactivemedia/v3/internal/pz;
    //   2220: invokevirtual 558	java/util/ArrayList:add	(Ljava/lang/Object;)Z
    //   2223: pop
    //   2224: goto +8 -> 2232
    //   2227: aload 76
    //   2229: invokestatic 281	com/google/ads/interactivemedia/v3/internal/pw:e	(Lorg/xmlpull/v1/XmlPullParser;)V
    //   2232: iload 60
    //   2234: istore 84
    //   2236: aload 41
    //   2238: astore_2
    //   2239: aload_1
    //   2240: astore_3
    //   2241: aload 94
    //   2243: astore 11
    //   2245: aload 40
    //   2247: astore 27
    //   2249: aload 93
    //   2251: astore 40
    //   2253: aload 91
    //   2255: astore 41
    //   2257: aload 55
    //   2259: astore 8
    //   2261: iload 57
    //   2263: istore 60
    //   2265: aload 83
    //   2267: astore 55
    //   2269: aload 68
    //   2271: astore 83
    //   2273: aload 76
    //   2275: ldc_w 574
    //   2278: invokestatic 180	com/google/ads/interactivemedia/v3/internal/rp:a	(Lorg/xmlpull/v1/XmlPullParser;Ljava/lang/String;)Z
    //   2281: ifeq +1336 -> 3617
    //   2284: aload 8
    //   2286: invokestatic 588	com/google/ads/interactivemedia/v3/internal/vs:a	(Ljava/lang/String;)Z
    //   2289: ifeq +12 -> 2301
    //   2292: aload 81
    //   2294: invokestatic 590	com/google/ads/interactivemedia/v3/internal/vs:e	(Ljava/lang/String;)Ljava/lang/String;
    //   2297: astore_1
    //   2298: goto +152 -> 2450
    //   2301: aload 8
    //   2303: invokestatic 592	com/google/ads/interactivemedia/v3/internal/vs:b	(Ljava/lang/String;)Z
    //   2306: ifeq +12 -> 2318
    //   2309: aload 81
    //   2311: invokestatic 593	com/google/ads/interactivemedia/v3/internal/vs:d	(Ljava/lang/String;)Ljava/lang/String;
    //   2314: astore_1
    //   2315: goto -17 -> 2298
    //   2318: aload 8
    //   2320: invokestatic 594	com/google/ads/interactivemedia/v3/internal/pw:b	(Ljava/lang/String;)Z
    //   2323: ifeq +9 -> 2332
    //   2326: aload 8
    //   2328: astore_1
    //   2329: goto +121 -> 2450
    //   2332: aload 8
    //   2334: astore_1
    //   2335: ldc_w 596
    //   2338: aload_1
    //   2339: invokevirtual 107	java/lang/String:equals	(Ljava/lang/Object;)Z
    //   2342: ifeq +44 -> 2386
    //   2345: aload 81
    //   2347: ifnull +101 -> 2448
    //   2350: aload 81
    //   2352: ldc_w 598
    //   2355: invokevirtual 601	java/lang/String:startsWith	(Ljava/lang/String;)Z
    //   2358: ifeq +10 -> 2368
    //   2361: ldc_w 603
    //   2364: astore_1
    //   2365: goto +85 -> 2450
    //   2368: aload 81
    //   2370: ldc_w 605
    //   2373: invokevirtual 601	java/lang/String:startsWith	(Ljava/lang/String;)Z
    //   2376: ifeq +72 -> 2448
    //   2379: ldc_w 607
    //   2382: astore_1
    //   2383: goto +67 -> 2450
    //   2386: ldc_w 609
    //   2389: aload_1
    //   2390: invokevirtual 107	java/lang/String:equals	(Ljava/lang/Object;)Z
    //   2393: ifeq +55 -> 2448
    //   2396: aload 81
    //   2398: ifnull +50 -> 2448
    //   2401: aload 81
    //   2403: ldc_w 611
    //   2406: invokevirtual 614	java/lang/String:contains	(Ljava/lang/CharSequence;)Z
    //   2409: ifeq +10 -> 2419
    //   2412: ldc_w 616
    //   2415: astore_1
    //   2416: goto +34 -> 2450
    //   2419: aload 81
    //   2421: ldc_w 618
    //   2424: invokevirtual 614	java/lang/String:contains	(Ljava/lang/CharSequence;)Z
    //   2427: ifne +14 -> 2441
    //   2430: aload 81
    //   2432: ldc_w 620
    //   2435: invokevirtual 614	java/lang/String:contains	(Ljava/lang/CharSequence;)Z
    //   2438: ifeq +10 -> 2448
    //   2441: ldc_w 622
    //   2444: astore_1
    //   2445: goto +5 -> 2450
    //   2448: aconst_null
    //   2449: astore_1
    //   2450: aload 8
    //   2452: astore 93
    //   2454: iconst_0
    //   2455: istore 57
    //   2457: aload 92
    //   2459: astore 8
    //   2461: aload 8
    //   2463: invokevirtual 623	java/util/ArrayList:size	()I
    //   2466: istore 63
    //   2468: ldc_w 625
    //   2471: astore 92
    //   2473: iload 57
    //   2475: iload 63
    //   2477: if_icmpge +62 -> 2539
    //   2480: aload 8
    //   2482: astore 68
    //   2484: aload 68
    //   2486: iload 57
    //   2488: invokevirtual 626	java/util/ArrayList:get	(I)Ljava/lang/Object;
    //   2491: checkcast 182	com/google/ads/interactivemedia/v3/internal/pz
    //   2494: astore 91
    //   2496: ldc_w 625
    //   2499: aload 91
    //   2501: getfield 244	com/google/ads/interactivemedia/v3/internal/pz:a	Ljava/lang/String;
    //   2504: invokevirtual 248	java/lang/String:equalsIgnoreCase	(Ljava/lang/String;)Z
    //   2507: ifeq +22 -> 2529
    //   2510: ldc 117
    //   2512: aload 91
    //   2514: getfield 250	com/google/ads/interactivemedia/v3/internal/pz:b	Ljava/lang/String;
    //   2517: invokevirtual 107	java/lang/String:equals	(Ljava/lang/Object;)Z
    //   2520: ifeq +9 -> 2529
    //   2523: iconst_1
    //   2524: istore 63
    //   2526: goto +16 -> 2542
    //   2529: iinc 57 1
    //   2532: aload 68
    //   2534: astore 8
    //   2536: goto -75 -> 2461
    //   2539: iconst_0
    //   2540: istore 63
    //   2542: iconst_0
    //   2543: istore 96
    //   2545: iload 96
    //   2547: istore 97
    //   2549: aload 8
    //   2551: astore 68
    //   2553: iload 96
    //   2555: aload 68
    //   2557: invokevirtual 623	java/util/ArrayList:size	()I
    //   2560: if_icmpge +56 -> 2616
    //   2563: aload 68
    //   2565: iload 96
    //   2567: invokevirtual 626	java/util/ArrayList:get	(I)Ljava/lang/Object;
    //   2570: checkcast 182	com/google/ads/interactivemedia/v3/internal/pz
    //   2573: astore 8
    //   2575: iload 97
    //   2577: istore 57
    //   2579: ldc_w 625
    //   2582: aload 8
    //   2584: getfield 244	com/google/ads/interactivemedia/v3/internal/pz:a	Ljava/lang/String;
    //   2587: invokevirtual 248	java/lang/String:equalsIgnoreCase	(Ljava/lang/String;)Z
    //   2590: ifeq +16 -> 2606
    //   2593: iload 97
    //   2595: aload 8
    //   2597: getfield 250	com/google/ads/interactivemedia/v3/internal/pz:b	Ljava/lang/String;
    //   2600: invokestatic 628	com/google/ads/interactivemedia/v3/internal/pw:a	(Ljava/lang/String;)I
    //   2603: ior
    //   2604: istore 57
    //   2606: iinc 96 1
    //   2609: iload 57
    //   2611: istore 97
    //   2613: goto -60 -> 2553
    //   2616: iconst_0
    //   2617: istore 96
    //   2619: iload 96
    //   2621: istore 98
    //   2623: aload 89
    //   2625: astore 91
    //   2627: aload 92
    //   2629: astore 8
    //   2631: iload 96
    //   2633: aload 67
    //   2635: invokevirtual 623	java/util/ArrayList:size	()I
    //   2638: if_icmpge +287 -> 2925
    //   2641: aload 67
    //   2643: iload 96
    //   2645: invokevirtual 626	java/util/ArrayList:get	(I)Ljava/lang/Object;
    //   2648: checkcast 182	com/google/ads/interactivemedia/v3/internal/pz
    //   2651: astore 92
    //   2653: aload 8
    //   2655: aload 92
    //   2657: getfield 244	com/google/ads/interactivemedia/v3/internal/pz:a	Ljava/lang/String;
    //   2660: invokevirtual 248	java/lang/String:equalsIgnoreCase	(Ljava/lang/String;)Z
    //   2663: ifeq +16 -> 2679
    //   2666: aload 92
    //   2668: getfield 250	com/google/ads/interactivemedia/v3/internal/pz:b	Ljava/lang/String;
    //   2671: invokestatic 628	com/google/ads/interactivemedia/v3/internal/pw:a	(Ljava/lang/String;)I
    //   2674: istore 57
    //   2676: goto +233 -> 2909
    //   2679: ldc_w 630
    //   2682: aload 92
    //   2684: getfield 244	com/google/ads/interactivemedia/v3/internal/pz:a	Ljava/lang/String;
    //   2687: invokevirtual 248	java/lang/String:equalsIgnoreCase	(Ljava/lang/String;)Z
    //   2690: ifeq +229 -> 2919
    //   2693: aload 92
    //   2695: getfield 250	com/google/ads/interactivemedia/v3/internal/pz:b	Ljava/lang/String;
    //   2698: astore 92
    //   2700: aload 92
    //   2702: ifnull +204 -> 2906
    //   2705: aload 92
    //   2707: invokevirtual 101	java/lang/String:hashCode	()I
    //   2710: tableswitch	default:+38->2748, 49:+109->2819, 50:+92->2802, 51:+75->2785, 52:+58->2768, 53:+38->2748, 54:+41->2751
    //   2748: goto +88 -> 2836
    //   2751: aload 92
    //   2753: ldc_w 632
    //   2756: invokevirtual 107	java/lang/String:equals	(Ljava/lang/Object;)Z
    //   2759: ifeq +77 -> 2836
    //   2762: iconst_4
    //   2763: istore 57
    //   2765: goto +74 -> 2839
    //   2768: aload 92
    //   2770: ldc_w 634
    //   2773: invokevirtual 107	java/lang/String:equals	(Ljava/lang/Object;)Z
    //   2776: ifeq +60 -> 2836
    //   2779: iconst_3
    //   2780: istore 57
    //   2782: goto +57 -> 2839
    //   2785: aload 92
    //   2787: ldc_w 636
    //   2790: invokevirtual 107	java/lang/String:equals	(Ljava/lang/Object;)Z
    //   2793: ifeq +43 -> 2836
    //   2796: iconst_2
    //   2797: istore 57
    //   2799: goto +40 -> 2839
    //   2802: aload 92
    //   2804: ldc_w 638
    //   2807: invokevirtual 107	java/lang/String:equals	(Ljava/lang/Object;)Z
    //   2810: ifeq +26 -> 2836
    //   2813: iconst_1
    //   2814: istore 57
    //   2816: goto +23 -> 2839
    //   2819: aload 92
    //   2821: ldc_w 640
    //   2824: invokevirtual 107	java/lang/String:equals	(Ljava/lang/Object;)Z
    //   2827: ifeq +9 -> 2836
    //   2830: iconst_0
    //   2831: istore 57
    //   2833: goto +6 -> 2839
    //   2836: iconst_m1
    //   2837: istore 57
    //   2839: iload 57
    //   2841: ifeq +57 -> 2898
    //   2844: iload 57
    //   2846: iconst_1
    //   2847: if_icmpeq +43 -> 2890
    //   2850: iload 57
    //   2852: iconst_2
    //   2853: if_icmpeq +31 -> 2884
    //   2856: iload 57
    //   2858: iconst_3
    //   2859: if_icmpeq +18 -> 2877
    //   2862: iload 57
    //   2864: iconst_4
    //   2865: if_icmpeq +6 -> 2871
    //   2868: goto +38 -> 2906
    //   2871: iconst_1
    //   2872: istore 57
    //   2874: goto +35 -> 2909
    //   2877: bipush 8
    //   2879: istore 57
    //   2881: goto +28 -> 2909
    //   2884: iconst_4
    //   2885: istore 57
    //   2887: goto +22 -> 2909
    //   2890: sipush 2048
    //   2893: istore 57
    //   2895: goto +14 -> 2909
    //   2898: sipush 512
    //   2901: istore 57
    //   2903: goto +6 -> 2909
    //   2906: iconst_0
    //   2907: istore 57
    //   2909: iload 98
    //   2911: iload 57
    //   2913: ior
    //   2914: istore 98
    //   2916: goto +3 -> 2919
    //   2919: iinc 96 1
    //   2922: goto -291 -> 2631
    //   2925: iload 97
    //   2927: iload 98
    //   2929: ior
    //   2930: istore 97
    //   2932: aload_1
    //   2933: astore 92
    //   2935: aload_1
    //   2936: ifnull +495 -> 3431
    //   2939: aload_1
    //   2940: astore 8
    //   2942: ldc_w 642
    //   2945: aload_1
    //   2946: invokevirtual 107	java/lang/String:equals	(Ljava/lang/Object;)Z
    //   2949: ifeq +72 -> 3021
    //   2952: iconst_0
    //   2953: istore 57
    //   2955: iload 57
    //   2957: aload 90
    //   2959: invokevirtual 623	java/util/ArrayList:size	()I
    //   2962: if_icmpge +54 -> 3016
    //   2965: aload 90
    //   2967: iload 57
    //   2969: invokevirtual 626	java/util/ArrayList:get	(I)Ljava/lang/Object;
    //   2972: checkcast 182	com/google/ads/interactivemedia/v3/internal/pz
    //   2975: astore_1
    //   2976: ldc_w 644
    //   2979: aload_1
    //   2980: getfield 244	com/google/ads/interactivemedia/v3/internal/pz:a	Ljava/lang/String;
    //   2983: invokevirtual 107	java/lang/String:equals	(Ljava/lang/Object;)Z
    //   2986: ifeq +24 -> 3010
    //   2989: ldc_w 646
    //   2992: aload_1
    //   2993: getfield 250	com/google/ads/interactivemedia/v3/internal/pz:b	Ljava/lang/String;
    //   2996: invokevirtual 107	java/lang/String:equals	(Ljava/lang/Object;)Z
    //   2999: ifeq +11 -> 3010
    //   3002: ldc_w 648
    //   3005: astore 8
    //   3007: goto +14 -> 3021
    //   3010: iinc 57 1
    //   3013: goto -58 -> 2955
    //   3016: ldc_w 642
    //   3019: astore 8
    //   3021: aload 8
    //   3023: invokestatic 592	com/google/ads/interactivemedia/v3/internal/vs:b	(Ljava/lang/String;)Z
    //   3026: ifeq +34 -> 3060
    //   3029: aload 78
    //   3031: aload 64
    //   3033: aload 93
    //   3035: aload 8
    //   3037: aload 81
    //   3039: aconst_null
    //   3040: iload 79
    //   3042: iload 82
    //   3044: iload 85
    //   3046: fload 86
    //   3048: aconst_null
    //   3049: iload 63
    //   3051: iload 97
    //   3053: invokestatic 653	com/google/ads/interactivemedia/v3/internal/bw:a	(Ljava/lang/String;Ljava/lang/String;Ljava/lang/String;Ljava/lang/String;Ljava/lang/String;Lcom/google/ads/interactivemedia/v3/internal/kd;IIIFLjava/util/List;II)Lcom/google/ads/interactivemedia/v3/internal/bw;
    //   3056: astore_1
    //   3057: goto +396 -> 3453
    //   3060: aload 8
    //   3062: invokestatic 588	com/google/ads/interactivemedia/v3/internal/vs:a	(Ljava/lang/String;)Z
    //   3065: ifeq +34 -> 3099
    //   3068: aload 78
    //   3070: aload 64
    //   3072: aload 93
    //   3074: aload 8
    //   3076: aload 81
    //   3078: aconst_null
    //   3079: iload 79
    //   3081: iload 84
    //   3083: iload 87
    //   3085: aconst_null
    //   3086: iload 63
    //   3088: iload 97
    //   3090: aload 73
    //   3092: invokestatic 656	com/google/ads/interactivemedia/v3/internal/bw:a	(Ljava/lang/String;Ljava/lang/String;Ljava/lang/String;Ljava/lang/String;Ljava/lang/String;Lcom/google/ads/interactivemedia/v3/internal/kd;IIILjava/util/List;IILjava/lang/String;)Lcom/google/ads/interactivemedia/v3/internal/bw;
    //   3095: astore_1
    //   3096: goto +357 -> 3453
    //   3099: aload 8
    //   3101: astore 92
    //   3103: aload 8
    //   3105: invokestatic 594	com/google/ads/interactivemedia/v3/internal/pw:b	(Ljava/lang/String;)Z
    //   3108: ifeq +323 -> 3431
    //   3111: ldc_w 622
    //   3114: aload 8
    //   3116: invokevirtual 107	java/lang/String:equals	(Ljava/lang/Object;)Z
    //   3119: ifeq +140 -> 3259
    //   3122: iconst_0
    //   3123: istore 57
    //   3125: iload 57
    //   3127: aload 67
    //   3129: invokevirtual 623	java/util/ArrayList:size	()I
    //   3132: if_icmpge +121 -> 3253
    //   3135: aload 67
    //   3137: iload 57
    //   3139: invokevirtual 626	java/util/ArrayList:get	(I)Ljava/lang/Object;
    //   3142: checkcast 182	com/google/ads/interactivemedia/v3/internal/pz
    //   3145: astore_1
    //   3146: ldc_w 658
    //   3149: aload_1
    //   3150: getfield 244	com/google/ads/interactivemedia/v3/internal/pz:a	Ljava/lang/String;
    //   3153: invokevirtual 107	java/lang/String:equals	(Ljava/lang/Object;)Z
    //   3156: ifeq +91 -> 3247
    //   3159: aload_1
    //   3160: getfield 250	com/google/ads/interactivemedia/v3/internal/pz:b	Ljava/lang/String;
    //   3163: astore 92
    //   3165: aload 92
    //   3167: ifnull +80 -> 3247
    //   3170: getstatic 29	com/google/ads/interactivemedia/v3/internal/pw:b	Ljava/util/regex/Pattern;
    //   3173: aload 92
    //   3175: invokevirtual 67	java/util/regex/Pattern:matcher	(Ljava/lang/CharSequence;)Ljava/util/regex/Matcher;
    //   3178: astore 92
    //   3180: aload 92
    //   3182: invokevirtual 73	java/util/regex/Matcher:matches	()Z
    //   3185: ifeq +17 -> 3202
    //   3188: aload 92
    //   3190: iconst_1
    //   3191: invokevirtual 77	java/util/regex/Matcher:group	(I)Ljava/lang/String;
    //   3194: invokestatic 83	java/lang/Integer:parseInt	(Ljava/lang/String;)I
    //   3197: istore 57
    //   3199: goto +57 -> 3256
    //   3202: aload_1
    //   3203: getfield 250	com/google/ads/interactivemedia/v3/internal/pz:b	Ljava/lang/String;
    //   3206: invokestatic 662	java/lang/String:valueOf	(Ljava/lang/Object;)Ljava/lang/String;
    //   3209: astore_1
    //   3210: aload_1
    //   3211: invokevirtual 665	java/lang/String:length	()I
    //   3214: ifeq +14 -> 3228
    //   3217: ldc_w 667
    //   3220: aload_1
    //   3221: invokevirtual 670	java/lang/String:concat	(Ljava/lang/String;)Ljava/lang/String;
    //   3224: astore_1
    //   3225: goto +14 -> 3239
    //   3228: new 97	java/lang/String
    //   3231: dup
    //   3232: ldc_w 667
    //   3235: invokespecial 673	java/lang/String:<init>	(Ljava/lang/String;)V
    //   3238: astore_1
    //   3239: ldc_w 418
    //   3242: aload_1
    //   3243: invokestatic 426	android/util/Log:w	(Ljava/lang/String;Ljava/lang/String;)I
    //   3246: pop
    //   3247: iinc 57 1
    //   3250: goto -125 -> 3125
    //   3253: iconst_m1
    //   3254: istore 57
    //   3256: goto +148 -> 3404
    //   3259: ldc_w 616
    //   3262: aload 8
    //   3264: invokevirtual 107	java/lang/String:equals	(Ljava/lang/Object;)Z
    //   3267: ifeq +134 -> 3401
    //   3270: iconst_0
    //   3271: istore 57
    //   3273: iload 57
    //   3275: aload 67
    //   3277: invokevirtual 623	java/util/ArrayList:size	()I
    //   3280: if_icmpge -27 -> 3253
    //   3283: aload 67
    //   3285: iload 57
    //   3287: invokevirtual 626	java/util/ArrayList:get	(I)Ljava/lang/Object;
    //   3290: checkcast 182	com/google/ads/interactivemedia/v3/internal/pz
    //   3293: astore_1
    //   3294: ldc_w 675
    //   3297: aload_1
    //   3298: getfield 244	com/google/ads/interactivemedia/v3/internal/pz:a	Ljava/lang/String;
    //   3301: invokevirtual 107	java/lang/String:equals	(Ljava/lang/Object;)Z
    //   3304: ifeq +91 -> 3395
    //   3307: aload_1
    //   3308: getfield 250	com/google/ads/interactivemedia/v3/internal/pz:b	Ljava/lang/String;
    //   3311: astore 92
    //   3313: aload 92
    //   3315: ifnull +80 -> 3395
    //   3318: getstatic 33	com/google/ads/interactivemedia/v3/internal/pw:c	Ljava/util/regex/Pattern;
    //   3321: aload 92
    //   3323: invokevirtual 67	java/util/regex/Pattern:matcher	(Ljava/lang/CharSequence;)Ljava/util/regex/Matcher;
    //   3326: astore 92
    //   3328: aload 92
    //   3330: invokevirtual 73	java/util/regex/Matcher:matches	()Z
    //   3333: ifeq +17 -> 3350
    //   3336: aload 92
    //   3338: iconst_1
    //   3339: invokevirtual 77	java/util/regex/Matcher:group	(I)Ljava/lang/String;
    //   3342: invokestatic 83	java/lang/Integer:parseInt	(Ljava/lang/String;)I
    //   3345: istore 57
    //   3347: goto -91 -> 3256
    //   3350: aload_1
    //   3351: getfield 250	com/google/ads/interactivemedia/v3/internal/pz:b	Ljava/lang/String;
    //   3354: invokestatic 662	java/lang/String:valueOf	(Ljava/lang/Object;)Ljava/lang/String;
    //   3357: astore_1
    //   3358: aload_1
    //   3359: invokevirtual 665	java/lang/String:length	()I
    //   3362: ifeq +14 -> 3376
    //   3365: ldc_w 677
    //   3368: aload_1
    //   3369: invokevirtual 670	java/lang/String:concat	(Ljava/lang/String;)Ljava/lang/String;
    //   3372: astore_1
    //   3373: goto +14 -> 3387
    //   3376: new 97	java/lang/String
    //   3379: dup
    //   3380: ldc_w 677
    //   3383: invokespecial 673	java/lang/String:<init>	(Ljava/lang/String;)V
    //   3386: astore_1
    //   3387: ldc_w 418
    //   3390: aload_1
    //   3391: invokestatic 426	android/util/Log:w	(Ljava/lang/String;Ljava/lang/String;)I
    //   3394: pop
    //   3395: iinc 57 1
    //   3398: goto -125 -> 3273
    //   3401: iconst_m1
    //   3402: istore 57
    //   3404: aload 78
    //   3406: aload 64
    //   3408: aload 93
    //   3410: aload 8
    //   3412: aload 81
    //   3414: iload 79
    //   3416: iload 63
    //   3418: iload 97
    //   3420: aload 73
    //   3422: iload 57
    //   3424: invokestatic 680	com/google/ads/interactivemedia/v3/internal/bw:a	(Ljava/lang/String;Ljava/lang/String;Ljava/lang/String;Ljava/lang/String;Ljava/lang/String;IIILjava/lang/String;I)Lcom/google/ads/interactivemedia/v3/internal/bw;
    //   3427: astore_1
    //   3428: goto +25 -> 3453
    //   3431: aload 78
    //   3433: aload 64
    //   3435: aload 93
    //   3437: aload 92
    //   3439: aload 81
    //   3441: iload 79
    //   3443: iload 63
    //   3445: iload 97
    //   3447: aload 73
    //   3449: invokestatic 683	com/google/ads/interactivemedia/v3/internal/bw:b	(Ljava/lang/String;Ljava/lang/String;Ljava/lang/String;Ljava/lang/String;Ljava/lang/String;IIILjava/lang/String;)Lcom/google/ads/interactivemedia/v3/internal/bw;
    //   3452: astore_1
    //   3453: aload_2
    //   3454: ifnull +6 -> 3460
    //   3457: goto +11 -> 3468
    //   3460: new 315	com/google/ads/interactivemedia/v3/internal/qk
    //   3463: dup
    //   3464: invokespecial 684	com/google/ads/interactivemedia/v3/internal/qk:<init>	()V
    //   3467: astore_2
    //   3468: new 686	com/google/ads/interactivemedia/v3/impl/data/aa
    //   3471: astore 8
    //   3473: aload 8
    //   3475: aload_1
    //   3476: aload_3
    //   3477: aload_2
    //   3478: aload 10
    //   3480: aload 83
    //   3482: aload 91
    //   3484: ldc2_w 199
    //   3487: invokespecial 689	com/google/ads/interactivemedia/v3/impl/data/aa:<init>	(Lcom/google/ads/interactivemedia/v3/internal/bw;Ljava/lang/String;Lcom/google/ads/interactivemedia/v3/internal/qh;Ljava/lang/String;Ljava/util/ArrayList;Ljava/util/ArrayList;J)V
    //   3490: aload 8
    //   3492: getfield 692	com/google/ads/interactivemedia/v3/impl/data/aa:a	Lcom/google/ads/interactivemedia/v3/internal/bw;
    //   3495: getfield 695	com/google/ads/interactivemedia/v3/internal/bw:i	Ljava/lang/String;
    //   3498: astore_1
    //   3499: aload_1
    //   3500: invokestatic 89	android/text/TextUtils:isEmpty	(Ljava/lang/CharSequence;)Z
    //   3503: ifne +42 -> 3545
    //   3506: aload_1
    //   3507: invokestatic 592	com/google/ads/interactivemedia/v3/internal/vs:b	(Ljava/lang/String;)Z
    //   3510: ifeq +9 -> 3519
    //   3513: iconst_2
    //   3514: istore 57
    //   3516: goto +32 -> 3548
    //   3519: aload_1
    //   3520: invokestatic 588	com/google/ads/interactivemedia/v3/internal/vs:a	(Ljava/lang/String;)Z
    //   3523: ifeq +9 -> 3532
    //   3526: iconst_1
    //   3527: istore 57
    //   3529: goto +19 -> 3548
    //   3532: aload_1
    //   3533: invokestatic 594	com/google/ads/interactivemedia/v3/internal/pw:b	(Ljava/lang/String;)Z
    //   3536: ifeq +9 -> 3545
    //   3539: iconst_3
    //   3540: istore 57
    //   3542: goto +6 -> 3548
    //   3545: iconst_m1
    //   3546: istore 57
    //   3548: iload 95
    //   3550: iload 57
    //   3552: invokestatic 562	com/google/ads/interactivemedia/v3/internal/pw:a	(II)I
    //   3555: istore 57
    //   3557: aload 70
    //   3559: aload 8
    //   3561: invokevirtual 558	java/util/ArrayList:add	(Ljava/lang/Object;)Z
    //   3564: pop
    //   3565: aload 6
    //   3567: astore_2
    //   3568: aload 9
    //   3570: astore 80
    //   3572: aload 69
    //   3574: astore 9
    //   3576: aload 68
    //   3578: astore 89
    //   3580: aload 58
    //   3582: astore 93
    //   3584: aload 59
    //   3586: astore 94
    //   3588: aload 53
    //   3590: astore_3
    //   3591: aload 39
    //   3593: astore_1
    //   3594: iload 60
    //   3596: istore 95
    //   3598: iload 88
    //   3600: istore 63
    //   3602: aload 41
    //   3604: astore 10
    //   3606: aload 38
    //   3608: astore 6
    //   3610: aload 27
    //   3612: astore 8
    //   3614: goto +210 -> 3824
    //   3617: aload_3
    //   3618: astore_1
    //   3619: aload 83
    //   3621: astore 68
    //   3623: aload 55
    //   3625: astore 83
    //   3627: iload 60
    //   3629: istore 57
    //   3631: aload 40
    //   3633: astore 93
    //   3635: aload 8
    //   3637: astore 55
    //   3639: aload 27
    //   3641: astore 40
    //   3643: aload 11
    //   3645: astore 94
    //   3647: aload 41
    //   3649: astore 91
    //   3651: aload_2
    //   3652: astore 41
    //   3654: iload 84
    //   3656: istore 60
    //   3658: goto -1736 -> 1922
    //   3661: aload 39
    //   3663: astore 93
    //   3665: lload 28
    //   3667: lstore 45
    //   3669: aload 38
    //   3671: astore 69
    //   3673: aload 40
    //   3675: astore 58
    //   3677: aload 6
    //   3679: astore 78
    //   3681: lload 35
    //   3683: lstore 51
    //   3685: fload 62
    //   3687: fstore 86
    //   3689: iload 61
    //   3691: istore 95
    //   3693: aload 59
    //   3695: astore 68
    //   3697: aload_3
    //   3698: astore 92
    //   3700: aload 41
    //   3702: astore 91
    //   3704: aload 10
    //   3706: astore 89
    //   3708: iload 57
    //   3710: istore 84
    //   3712: aload 11
    //   3714: astore 83
    //   3716: aload 27
    //   3718: astore 59
    //   3720: iload 60
    //   3722: istore 88
    //   3724: aload 8
    //   3726: astore 94
    //   3728: aload 76
    //   3730: astore 81
    //   3732: aload 9
    //   3734: astore 80
    //   3736: aload 81
    //   3738: aload 80
    //   3740: invokestatic 270	com/google/ads/interactivemedia/v3/internal/rp:b	(Lorg/xmlpull/v1/XmlPullParser;Ljava/lang/String;)Z
    //   3743: ifeq +120 -> 3863
    //   3746: aload 72
    //   3748: checkcast 315	com/google/ads/interactivemedia/v3/internal/qk
    //   3751: astore_3
    //   3752: aload_0
    //   3753: aload 81
    //   3755: aload_3
    //   3756: invokespecial 578	com/google/ads/interactivemedia/v3/internal/pw:a	(Lorg/xmlpull/v1/XmlPullParser;Lcom/google/ads/interactivemedia/v3/internal/qk;)Lcom/google/ads/interactivemedia/v3/internal/qk;
    //   3759: astore 72
    //   3761: aload 55
    //   3763: astore 9
    //   3765: aload_1
    //   3766: astore 27
    //   3768: aload_2
    //   3769: astore 40
    //   3771: lload 51
    //   3773: lstore 35
    //   3775: aload 78
    //   3777: astore 11
    //   3779: aload 58
    //   3781: astore 8
    //   3783: aload 69
    //   3785: astore 6
    //   3787: aload 68
    //   3789: astore 10
    //   3791: aload 59
    //   3793: astore_1
    //   3794: aload 83
    //   3796: astore_3
    //   3797: aload 91
    //   3799: astore 55
    //   3801: aload 92
    //   3803: astore 73
    //   3805: iload 88
    //   3807: istore 61
    //   3809: lload 45
    //   3811: lstore 28
    //   3813: fload 86
    //   3815: fstore 62
    //   3817: aload 27
    //   3819: astore_2
    //   3820: iload 84
    //   3822: istore 57
    //   3824: aload 11
    //   3826: astore 27
    //   3828: aload 80
    //   3830: astore 41
    //   3832: aload 89
    //   3834: astore 38
    //   3836: aload 93
    //   3838: astore 39
    //   3840: aload 94
    //   3842: astore 11
    //   3844: iload 61
    //   3846: istore 60
    //   3848: aload 73
    //   3850: astore 53
    //   3852: iload 95
    //   3854: istore 61
    //   3856: aload 7
    //   3858: astore 59
    //   3860: goto +331 -> 4191
    //   3863: aload 81
    //   3865: aload_2
    //   3866: invokestatic 270	com/google/ads/interactivemedia/v3/internal/rp:b	(Lorg/xmlpull/v1/XmlPullParser;Ljava/lang/String;)Z
    //   3869: ifeq +80 -> 3949
    //   3872: aload_0
    //   3873: aload 81
    //   3875: aload 72
    //   3877: checkcast 307	com/google/ads/interactivemedia/v3/internal/qj
    //   3880: lload 51
    //   3882: invokespecial 580	com/google/ads/interactivemedia/v3/internal/pw:a	(Lorg/xmlpull/v1/XmlPullParser;Lcom/google/ads/interactivemedia/v3/internal/qj;J)Lcom/google/ads/interactivemedia/v3/internal/qj;
    //   3885: astore 72
    //   3887: lload 51
    //   3889: lstore 35
    //   3891: aload 55
    //   3893: astore 9
    //   3895: iload 84
    //   3897: istore 57
    //   3899: aload_2
    //   3900: astore 40
    //   3902: aload_1
    //   3903: astore_2
    //   3904: fload 86
    //   3906: fstore 62
    //   3908: lload 45
    //   3910: lstore 28
    //   3912: iload 88
    //   3914: istore 61
    //   3916: aload 92
    //   3918: astore 73
    //   3920: aload 91
    //   3922: astore 55
    //   3924: aload 83
    //   3926: astore_3
    //   3927: aload 59
    //   3929: astore_1
    //   3930: aload 68
    //   3932: astore 10
    //   3934: aload 69
    //   3936: astore 6
    //   3938: aload 58
    //   3940: astore 8
    //   3942: aload 78
    //   3944: astore 11
    //   3946: goto -122 -> 3824
    //   3949: aload 81
    //   3951: aload 78
    //   3953: invokestatic 270	com/google/ads/interactivemedia/v3/internal/rp:b	(Lorg/xmlpull/v1/XmlPullParser;Ljava/lang/String;)Z
    //   3956: ifeq +108 -> 4064
    //   3959: aload 72
    //   3961: checkcast 252	com/google/ads/interactivemedia/v3/internal/qi
    //   3964: astore_3
    //   3965: lload 51
    //   3967: lstore 35
    //   3969: aload_0
    //   3970: aload 81
    //   3972: aload_3
    //   3973: aload 94
    //   3975: lload 35
    //   3977: invokespecial 582	com/google/ads/interactivemedia/v3/internal/pw:a	(Lorg/xmlpull/v1/XmlPullParser;Lcom/google/ads/interactivemedia/v3/internal/qi;Ljava/util/List;J)Lcom/google/ads/interactivemedia/v3/internal/qi;
    //   3980: astore 72
    //   3982: aload 78
    //   3984: astore 27
    //   3986: aload 55
    //   3988: astore 9
    //   3990: aload 80
    //   3992: astore 41
    //   3994: iload 84
    //   3996: istore 57
    //   3998: aload_2
    //   3999: astore 40
    //   4001: aload 89
    //   4003: astore 38
    //   4005: aload_1
    //   4006: astore_2
    //   4007: aload 93
    //   4009: astore 39
    //   4011: fload 86
    //   4013: fstore 62
    //   4015: lload 45
    //   4017: lstore 28
    //   4019: aload 94
    //   4021: astore 11
    //   4023: iload 88
    //   4025: istore 60
    //   4027: aload 92
    //   4029: astore 53
    //   4031: aload 91
    //   4033: astore 55
    //   4035: aload 83
    //   4037: astore_3
    //   4038: aload 59
    //   4040: astore_1
    //   4041: iload 95
    //   4043: istore 61
    //   4045: aload 7
    //   4047: astore 59
    //   4049: aload 68
    //   4051: astore 10
    //   4053: aload 69
    //   4055: astore 6
    //   4057: aload 58
    //   4059: astore 8
    //   4061: goto +130 -> 4191
    //   4064: aload 81
    //   4066: ldc_w 584
    //   4069: invokestatic 270	com/google/ads/interactivemedia/v3/internal/rp:b	(Lorg/xmlpull/v1/XmlPullParser;Ljava/lang/String;)Z
    //   4072: ifeq +20 -> 4092
    //   4075: aload 66
    //   4077: aload 81
    //   4079: ldc_w 584
    //   4082: invokestatic 566	com/google/ads/interactivemedia/v3/internal/pw:a	(Lorg/xmlpull/v1/XmlPullParser;Ljava/lang/String;)Lcom/google/ads/interactivemedia/v3/internal/pz;
    //   4085: invokevirtual 558	java/util/ArrayList:add	(Ljava/lang/Object;)Z
    //   4088: pop
    //   4089: goto +16 -> 4105
    //   4092: aload 81
    //   4094: invokestatic 698	com/google/ads/interactivemedia/v3/internal/rp:b	(Lorg/xmlpull/v1/XmlPullParser;)Z
    //   4097: ifeq +8 -> 4105
    //   4100: aload 81
    //   4102: invokestatic 281	com/google/ads/interactivemedia/v3/internal/pw:e	(Lorg/xmlpull/v1/XmlPullParser;)V
    //   4105: aload 40
    //   4107: astore 59
    //   4109: aload 38
    //   4111: astore 83
    //   4113: aload 53
    //   4115: astore 55
    //   4117: aload 27
    //   4119: astore 38
    //   4121: aload 11
    //   4123: astore 53
    //   4125: aload_3
    //   4126: astore 69
    //   4128: aload 8
    //   4130: astore 11
    //   4132: aload_1
    //   4133: astore 58
    //   4135: aload 10
    //   4137: astore 68
    //   4139: aload_2
    //   4140: astore 40
    //   4142: aload 6
    //   4144: astore 27
    //   4146: aload 59
    //   4148: astore 8
    //   4150: aload 83
    //   4152: astore 6
    //   4154: aload 55
    //   4156: astore 10
    //   4158: aload 7
    //   4160: astore 59
    //   4162: aload 38
    //   4164: astore_1
    //   4165: aload 53
    //   4167: astore_3
    //   4168: aload 41
    //   4170: astore 55
    //   4172: aload 69
    //   4174: astore 53
    //   4176: aload 58
    //   4178: astore_2
    //   4179: aload 68
    //   4181: astore 38
    //   4183: aload 9
    //   4185: astore 41
    //   4187: aload 73
    //   4189: astore 9
    //   4191: aload_0
    //   4192: astore 73
    //   4194: aload 70
    //   4196: astore 7
    //   4198: aload 76
    //   4200: ldc_w 531
    //   4203: invokestatic 180	com/google/ads/interactivemedia/v3/internal/rp:a	(Lorg/xmlpull/v1/XmlPullParser;Ljava/lang/String;)Z
    //   4206: ifeq +413 -> 4619
    //   4209: new 298	java/util/ArrayList
    //   4212: astore 40
    //   4214: aload 40
    //   4216: aload 7
    //   4218: invokevirtual 623	java/util/ArrayList:size	()I
    //   4221: invokespecial 701	java/util/ArrayList:<init>	(I)V
    //   4224: iconst_0
    //   4225: istore 74
    //   4227: aload 65
    //   4229: astore 9
    //   4231: iload 74
    //   4233: aload 7
    //   4235: invokevirtual 623	java/util/ArrayList:size	()I
    //   4238: if_icmpge +317 -> 4555
    //   4241: aload 7
    //   4243: iload 74
    //   4245: invokevirtual 626	java/util/ArrayList:get	(I)Ljava/lang/Object;
    //   4248: checkcast 686	com/google/ads/interactivemedia/v3/impl/data/aa
    //   4251: astore 41
    //   4253: aload 41
    //   4255: getfield 692	com/google/ads/interactivemedia/v3/impl/data/aa:a	Lcom/google/ads/interactivemedia/v3/internal/bw;
    //   4258: astore 38
    //   4260: aload 41
    //   4262: getfield 703	com/google/ads/interactivemedia/v3/impl/data/aa:d	Ljava/lang/String;
    //   4265: astore 27
    //   4267: aload 27
    //   4269: ifnull +6 -> 4275
    //   4272: goto +7 -> 4279
    //   4275: aload 59
    //   4277: astore 27
    //   4279: aload 41
    //   4281: getfield 706	com/google/ads/interactivemedia/v3/impl/data/aa:e	Ljava/util/ArrayList;
    //   4284: astore 39
    //   4286: aload 39
    //   4288: aload 9
    //   4290: invokevirtual 710	java/util/ArrayList:addAll	(Ljava/util/Collection;)Z
    //   4293: pop
    //   4294: aload 39
    //   4296: invokevirtual 712	java/util/ArrayList:isEmpty	()Z
    //   4299: ifne +117 -> 4416
    //   4302: aload 39
    //   4304: invokevirtual 623	java/util/ArrayList:size	()I
    //   4307: iconst_1
    //   4308: isub
    //   4309: istore 60
    //   4311: iload 60
    //   4313: iflt +77 -> 4390
    //   4316: aload 39
    //   4318: iload 60
    //   4320: invokevirtual 626	java/util/ArrayList:get	(I)Ljava/lang/Object;
    //   4323: checkcast 433	com/google/ads/interactivemedia/v3/internal/fe$a
    //   4326: astore 53
    //   4328: aload 53
    //   4330: invokevirtual 714	com/google/ads/interactivemedia/v3/internal/fe$a:a	()Z
    //   4333: ifne +51 -> 4384
    //   4336: iconst_0
    //   4337: istore 61
    //   4339: iload 61
    //   4341: aload 39
    //   4343: invokevirtual 623	java/util/ArrayList:size	()I
    //   4346: if_icmpge +38 -> 4384
    //   4349: aload 39
    //   4351: iload 61
    //   4353: invokevirtual 626	java/util/ArrayList:get	(I)Ljava/lang/Object;
    //   4356: checkcast 433	com/google/ads/interactivemedia/v3/internal/fe$a
    //   4359: aload 53
    //   4361: invokevirtual 717	com/google/ads/interactivemedia/v3/internal/fe$a:a	(Lcom/google/ads/interactivemedia/v3/internal/fe$a;)Z
    //   4364: ifeq +14 -> 4378
    //   4367: aload 39
    //   4369: iload 60
    //   4371: invokevirtual 720	java/util/ArrayList:remove	(I)Ljava/lang/Object;
    //   4374: pop
    //   4375: goto +9 -> 4384
    //   4378: iinc 61 1
    //   4381: goto -42 -> 4339
    //   4384: iinc 60 -1
    //   4387: goto -76 -> 4311
    //   4390: new 722	com/google/ads/interactivemedia/v3/internal/fe
    //   4393: astore 53
    //   4395: aload 53
    //   4397: aload 27
    //   4399: aload 39
    //   4401: invokespecial 725	com/google/ads/interactivemedia/v3/internal/fe:<init>	(Ljava/lang/String;Ljava/util/List;)V
    //   4404: aload 38
    //   4406: aload 53
    //   4408: invokevirtual 728	com/google/ads/interactivemedia/v3/internal/bw:a	(Lcom/google/ads/interactivemedia/v3/internal/fe;)Lcom/google/ads/interactivemedia/v3/internal/bw;
    //   4411: astore 27
    //   4413: goto +7 -> 4420
    //   4416: aload 38
    //   4418: astore 27
    //   4420: aload 41
    //   4422: getfield 730	com/google/ads/interactivemedia/v3/impl/data/aa:f	Ljava/util/ArrayList;
    //   4425: astore 39
    //   4427: aload 39
    //   4429: aload 66
    //   4431: invokevirtual 710	java/util/ArrayList:addAll	(Ljava/util/Collection;)Z
    //   4434: pop
    //   4435: aload 41
    //   4437: getfield 732	com/google/ads/interactivemedia/v3/impl/data/aa:g	J
    //   4440: lstore 51
    //   4442: aload 41
    //   4444: getfield 733	com/google/ads/interactivemedia/v3/impl/data/aa:b	Ljava/lang/String;
    //   4447: astore 53
    //   4449: aload 41
    //   4451: getfield 736	com/google/ads/interactivemedia/v3/impl/data/aa:c	Lcom/google/ads/interactivemedia/v3/internal/qh;
    //   4454: astore 41
    //   4456: aload 41
    //   4458: instanceof 315
    //   4461: ifeq +37 -> 4498
    //   4464: new 738	com/google/ads/interactivemedia/v3/internal/qe
    //   4467: astore 38
    //   4469: aload 38
    //   4471: lload 51
    //   4473: aload 27
    //   4475: aload 53
    //   4477: aload 41
    //   4479: checkcast 315	com/google/ads/interactivemedia/v3/internal/qk
    //   4482: aload 39
    //   4484: aconst_null
    //   4485: ldc2_w 199
    //   4488: invokespecial 741	com/google/ads/interactivemedia/v3/internal/qe:<init>	(JLcom/google/ads/interactivemedia/v3/internal/bw;Ljava/lang/String;Lcom/google/ads/interactivemedia/v3/internal/qk;Ljava/util/List;Ljava/lang/String;J)V
    //   4491: aload 38
    //   4493: astore 27
    //   4495: goto +33 -> 4528
    //   4498: aload 41
    //   4500: instanceof 222
    //   4503: ifeq +39 -> 4542
    //   4506: new 743	com/google/ads/interactivemedia/v3/internal/qf
    //   4509: dup
    //   4510: lload 51
    //   4512: aload 27
    //   4514: aload 53
    //   4516: aload 41
    //   4518: checkcast 222	com/google/ads/interactivemedia/v3/internal/qg
    //   4521: aload 39
    //   4523: invokespecial 746	com/google/ads/interactivemedia/v3/internal/qf:<init>	(JLcom/google/ads/interactivemedia/v3/internal/bw;Ljava/lang/String;Lcom/google/ads/interactivemedia/v3/internal/qg;Ljava/util/List;)V
    //   4526: astore 27
    //   4528: aload 40
    //   4530: aload 27
    //   4532: invokevirtual 558	java/util/ArrayList:add	(Ljava/lang/Object;)Z
    //   4535: pop
    //   4536: iinc 74 1
    //   4539: goto -308 -> 4231
    //   4542: new 748	java/lang/IllegalArgumentException
    //   4545: astore_1
    //   4546: aload_1
    //   4547: ldc_w 750
    //   4550: invokespecial 751	java/lang/IllegalArgumentException:<init>	(Ljava/lang/String;)V
    //   4553: aload_1
    //   4554: athrow
    //   4555: new 753	com/google/ads/interactivemedia/v3/internal/wa
    //   4558: astore 7
    //   4560: aload 7
    //   4562: iload 56
    //   4564: iload 57
    //   4566: aload 40
    //   4568: aload 67
    //   4570: aload 11
    //   4572: invokespecial 756	com/google/ads/interactivemedia/v3/internal/wa:<init>	(IILjava/util/List;Ljava/util/List;Ljava/util/List;)V
    //   4575: aload 6
    //   4577: astore 9
    //   4579: aload 9
    //   4581: aload 7
    //   4583: invokevirtual 558	java/util/ArrayList:add	(Ljava/lang/Object;)Z
    //   4586: pop
    //   4587: aload 77
    //   4589: astore 11
    //   4591: aload 76
    //   4593: astore 6
    //   4595: aload 73
    //   4597: astore 7
    //   4599: aload_3
    //   4600: astore 27
    //   4602: aload_1
    //   4603: astore_3
    //   4604: aload 75
    //   4606: astore 39
    //   4608: aload 10
    //   4610: astore 40
    //   4612: aload 8
    //   4614: astore 38
    //   4616: goto +888 -> 5504
    //   4619: aload 41
    //   4621: astore 58
    //   4623: aload 7
    //   4625: astore 70
    //   4627: aload 40
    //   4629: astore 69
    //   4631: aload 11
    //   4633: astore 41
    //   4635: aload 53
    //   4637: astore 73
    //   4639: aload_3
    //   4640: astore 11
    //   4642: aload 10
    //   4644: astore 53
    //   4646: aload 8
    //   4648: astore 40
    //   4650: aload 27
    //   4652: astore 7
    //   4654: aload 38
    //   4656: astore 10
    //   4658: aload_1
    //   4659: astore 27
    //   4661: aload 73
    //   4663: astore_3
    //   4664: aload 41
    //   4666: astore 8
    //   4668: aload 55
    //   4670: astore 41
    //   4672: aload 9
    //   4674: astore 73
    //   4676: aload_2
    //   4677: astore_1
    //   4678: aload 6
    //   4680: astore 38
    //   4682: aload 7
    //   4684: astore 6
    //   4686: aload 59
    //   4688: astore 7
    //   4690: aload 69
    //   4692: astore_2
    //   4693: aload 58
    //   4695: astore 9
    //   4697: goto -3382 -> 1315
    //   4700: astore_1
    //   4701: goto +1455 -> 6156
    //   4704: aload_2
    //   4705: astore 11
    //   4707: aload 7
    //   4709: astore 38
    //   4711: aload 41
    //   4713: astore_2
    //   4714: aload 8
    //   4716: astore 40
    //   4718: aload 53
    //   4720: astore 8
    //   4722: aload 55
    //   4724: astore 27
    //   4726: aload_3
    //   4727: astore 9
    //   4729: aload_1
    //   4730: astore 7
    //   4732: aload 10
    //   4734: astore 6
    //   4736: aload 6
    //   4738: ldc_w 758
    //   4741: invokestatic 270	com/google/ads/interactivemedia/v3/internal/rp:b	(Lorg/xmlpull/v1/XmlPullParser;Ljava/lang/String;)Z
    //   4744: ifeq +780 -> 5524
    //   4747: aload 38
    //   4749: astore_1
    //   4750: aload 6
    //   4752: aload_1
    //   4753: ldc -89
    //   4755: invokestatic 170	com/google/ads/interactivemedia/v3/internal/pw:b	(Lorg/xmlpull/v1/XmlPullParser;Ljava/lang/String;Ljava/lang/String;)Ljava/lang/String;
    //   4758: astore 38
    //   4760: aload 6
    //   4762: aload 47
    //   4764: ldc -89
    //   4766: invokestatic 170	com/google/ads/interactivemedia/v3/internal/pw:b	(Lorg/xmlpull/v1/XmlPullParser;Ljava/lang/String;Ljava/lang/String;)Ljava/lang/String;
    //   4769: astore 41
    //   4771: aload 6
    //   4773: ldc -42
    //   4775: lconst_1
    //   4776: invokestatic 216	com/google/ads/interactivemedia/v3/internal/pw:c	(Lorg/xmlpull/v1/XmlPullParser;Ljava/lang/String;J)J
    //   4779: lstore 35
    //   4781: new 298	java/util/ArrayList
    //   4784: astore 53
    //   4786: aload 53
    //   4788: invokespecial 299	java/util/ArrayList:<init>	()V
    //   4791: new 760	java/io/ByteArrayOutputStream
    //   4794: astore 55
    //   4796: aload 55
    //   4798: sipush 512
    //   4801: invokespecial 761	java/io/ByteArrayOutputStream:<init>	(I)V
    //   4804: aload 40
    //   4806: astore_3
    //   4807: aload 6
    //   4809: invokeinterface 177 1 0
    //   4814: pop
    //   4815: aload 6
    //   4817: ldc_w 763
    //   4820: invokestatic 270	com/google/ads/interactivemedia/v3/internal/rp:b	(Lorg/xmlpull/v1/XmlPullParser;Ljava/lang/String;)Z
    //   4823: ifeq +536 -> 5359
    //   4826: aload 6
    //   4828: aload_3
    //   4829: lconst_0
    //   4830: invokestatic 216	com/google/ads/interactivemedia/v3/internal/pw:c	(Lorg/xmlpull/v1/XmlPullParser;Ljava/lang/String;J)J
    //   4833: lstore 45
    //   4835: aload 6
    //   4837: ldc -28
    //   4839: ldc2_w 225
    //   4842: invokestatic 216	com/google/ads/interactivemedia/v3/internal/pw:c	(Lorg/xmlpull/v1/XmlPullParser;Ljava/lang/String;J)J
    //   4845: lstore 99
    //   4847: aload 6
    //   4849: ldc_w 765
    //   4852: lconst_0
    //   4853: invokestatic 216	com/google/ads/interactivemedia/v3/internal/pw:c	(Lorg/xmlpull/v1/XmlPullParser;Ljava/lang/String;J)J
    //   4856: lstore 101
    //   4858: lload 99
    //   4860: ldc2_w 341
    //   4863: lload 35
    //   4865: invokestatic 345	com/google/ads/interactivemedia/v3/internal/wl:c	(JJJ)J
    //   4868: lstore 99
    //   4870: lload 101
    //   4872: ldc2_w 766
    //   4875: lload 35
    //   4877: invokestatic 345	com/google/ads/interactivemedia/v3/internal/wl:c	(JJJ)J
    //   4880: lstore 101
    //   4882: aload 6
    //   4884: ldc_w 769
    //   4887: aconst_null
    //   4888: invokestatic 170	com/google/ads/interactivemedia/v3/internal/pw:b	(Lorg/xmlpull/v1/XmlPullParser;Ljava/lang/String;Ljava/lang/String;)Ljava/lang/String;
    //   4891: astore 40
    //   4893: aload 55
    //   4895: invokevirtual 772	java/io/ByteArrayOutputStream:reset	()V
    //   4898: invokestatic 778	android/util/Xml:newSerializer	()Lorg/xmlpull/v1/XmlSerializer;
    //   4901: astore 76
    //   4903: aload 76
    //   4905: aload 55
    //   4907: ldc_w 780
    //   4910: invokeinterface 786 3 0
    //   4915: aload 6
    //   4917: invokeinterface 789 1 0
    //   4922: pop
    //   4923: aload 6
    //   4925: ldc_w 763
    //   4928: invokestatic 180	com/google/ads/interactivemedia/v3/internal/rp:a	(Lorg/xmlpull/v1/XmlPullParser;Ljava/lang/String;)Z
    //   4931: ifne +360 -> 5291
    //   4934: aload 6
    //   4936: invokeinterface 792 1 0
    //   4941: tableswitch	default:+59->5000, 0:+328->5269, 1:+318->5259, 2:+237->5178, 3:+209->5150, 4:+188->5129, 5:+168->5109, 6:+148->5089, 7:+128->5069, 8:+108->5049, 9:+88->5029, 10:+68->5009
    //   5000: aload_1
    //   5001: astore 10
    //   5003: aload 10
    //   5005: astore_1
    //   5006: goto +274 -> 5280
    //   5009: aload 76
    //   5011: aload 6
    //   5013: invokeinterface 407 1 0
    //   5018: invokeinterface 795 2 0
    //   5023: aload_1
    //   5024: astore 10
    //   5026: goto -23 -> 5003
    //   5029: aload 76
    //   5031: aload 6
    //   5033: invokeinterface 407 1 0
    //   5038: invokeinterface 798 2 0
    //   5043: aload_1
    //   5044: astore 10
    //   5046: goto -43 -> 5003
    //   5049: aload 76
    //   5051: aload 6
    //   5053: invokeinterface 407 1 0
    //   5058: invokeinterface 801 2 0
    //   5063: aload_1
    //   5064: astore 10
    //   5066: goto -63 -> 5003
    //   5069: aload 76
    //   5071: aload 6
    //   5073: invokeinterface 407 1 0
    //   5078: invokeinterface 804 2 0
    //   5083: aload_1
    //   5084: astore 10
    //   5086: goto -83 -> 5003
    //   5089: aload 76
    //   5091: aload 6
    //   5093: invokeinterface 407 1 0
    //   5098: invokeinterface 807 2 0
    //   5103: aload_1
    //   5104: astore 10
    //   5106: goto -103 -> 5003
    //   5109: aload 76
    //   5111: aload 6
    //   5113: invokeinterface 407 1 0
    //   5118: invokeinterface 810 2 0
    //   5123: aload_1
    //   5124: astore 10
    //   5126: goto -123 -> 5003
    //   5129: aload 76
    //   5131: aload 6
    //   5133: invokeinterface 407 1 0
    //   5138: invokeinterface 813 2 0
    //   5143: pop
    //   5144: aload_1
    //   5145: astore 10
    //   5147: goto -144 -> 5003
    //   5150: aload 76
    //   5152: aload 6
    //   5154: invokeinterface 816 1 0
    //   5159: aload 6
    //   5161: invokeinterface 465 1 0
    //   5166: invokeinterface 820 3 0
    //   5171: pop
    //   5172: aload_1
    //   5173: astore 10
    //   5175: goto -172 -> 5003
    //   5178: aload 76
    //   5180: aload 6
    //   5182: invokeinterface 816 1 0
    //   5187: aload 6
    //   5189: invokeinterface 465 1 0
    //   5194: invokeinterface 823 3 0
    //   5199: pop
    //   5200: iconst_0
    //   5201: istore 57
    //   5203: aload_1
    //   5204: astore 10
    //   5206: iload 57
    //   5208: aload 6
    //   5210: invokeinterface 826 1 0
    //   5215: if_icmpge -212 -> 5003
    //   5218: aload 76
    //   5220: aload 6
    //   5222: iload 57
    //   5224: invokeinterface 829 2 0
    //   5229: aload 6
    //   5231: iload 57
    //   5233: invokeinterface 832 2 0
    //   5238: aload 6
    //   5240: iload 57
    //   5242: invokeinterface 834 2 0
    //   5247: invokeinterface 838 4 0
    //   5252: pop
    //   5253: iinc 57 1
    //   5256: goto -53 -> 5203
    //   5259: aload 76
    //   5261: invokeinterface 841 1 0
    //   5266: goto +14 -> 5280
    //   5269: aload 76
    //   5271: aconst_null
    //   5272: getstatic 847	java/lang/Boolean:FALSE	Ljava/lang/Boolean;
    //   5275: invokeinterface 851 3 0
    //   5280: aload 6
    //   5282: invokeinterface 789 1 0
    //   5287: pop
    //   5288: goto -365 -> 4923
    //   5291: aload 76
    //   5293: invokeinterface 854 1 0
    //   5298: aload 55
    //   5300: invokevirtual 858	java/io/ByteArrayOutputStream:toByteArray	()[B
    //   5303: astore 10
    //   5305: aload 40
    //   5307: ifnonnull +6 -> 5313
    //   5310: goto +10 -> 5320
    //   5313: aload 40
    //   5315: invokestatic 861	com/google/ads/interactivemedia/v3/internal/wl:c	(Ljava/lang/String;)[B
    //   5318: astore 10
    //   5320: new 863	com/google/ads/interactivemedia/v3/internal/kh
    //   5323: astore 40
    //   5325: aload 40
    //   5327: aload 38
    //   5329: aload 41
    //   5331: lload 99
    //   5333: lload 45
    //   5335: aload 10
    //   5337: invokespecial 866	com/google/ads/interactivemedia/v3/internal/kh:<init>	(Ljava/lang/String;Ljava/lang/String;JJ[B)V
    //   5340: aload 53
    //   5342: lload 101
    //   5344: invokestatic 869	java/lang/Long:valueOf	(J)Ljava/lang/Long;
    //   5347: aload 40
    //   5349: invokestatic 444	android/util/Pair:create	(Ljava/lang/Object;Ljava/lang/Object;)Landroid/util/Pair;
    //   5352: invokevirtual 558	java/util/ArrayList:add	(Ljava/lang/Object;)Z
    //   5355: pop
    //   5356: goto +8 -> 5364
    //   5359: aload 6
    //   5361: invokestatic 281	com/google/ads/interactivemedia/v3/internal/pw:e	(Lorg/xmlpull/v1/XmlPullParser;)V
    //   5364: aload_3
    //   5365: astore 10
    //   5367: aload 6
    //   5369: ldc_w 758
    //   5372: invokestatic 180	com/google/ads/interactivemedia/v3/internal/rp:a	(Lorg/xmlpull/v1/XmlPullParser;Ljava/lang/String;)Z
    //   5375: ifeq +143 -> 5518
    //   5378: aload 53
    //   5380: invokevirtual 623	java/util/ArrayList:size	()I
    //   5383: newarray <illegal type>
    //   5385: astore 40
    //   5387: aload 53
    //   5389: invokevirtual 623	java/util/ArrayList:size	()I
    //   5392: anewarray 863	com/google/ads/interactivemedia/v3/internal/kh
    //   5395: astore_3
    //   5396: iconst_0
    //   5397: istore 57
    //   5399: iload 57
    //   5401: aload 53
    //   5403: invokevirtual 623	java/util/ArrayList:size	()I
    //   5406: if_icmpge +49 -> 5455
    //   5409: aload 53
    //   5411: iload 57
    //   5413: invokevirtual 626	java/util/ArrayList:get	(I)Ljava/lang/Object;
    //   5416: checkcast 440	android/util/Pair
    //   5419: astore 55
    //   5421: aload 40
    //   5423: iload 57
    //   5425: aload 55
    //   5427: getfield 554	android/util/Pair:first	Ljava/lang/Object;
    //   5430: checkcast 195	java/lang/Long
    //   5433: invokevirtual 873	java/lang/Long:longValue	()J
    //   5436: lastore
    //   5437: aload_3
    //   5438: iload 57
    //   5440: aload 55
    //   5442: getfield 557	android/util/Pair:second	Ljava/lang/Object;
    //   5445: checkcast 863	com/google/ads/interactivemedia/v3/internal/kh
    //   5448: aastore
    //   5449: iinc 57 1
    //   5452: goto -53 -> 5399
    //   5455: new 875	com/google/ads/interactivemedia/v3/internal/py
    //   5458: astore 53
    //   5460: aload 53
    //   5462: aload 38
    //   5464: aload 41
    //   5466: lload 35
    //   5468: aload 40
    //   5470: aload_3
    //   5471: invokespecial 878	com/google/ads/interactivemedia/v3/internal/py:<init>	(Ljava/lang/String;Ljava/lang/String;J[J[Lcom/google/ads/interactivemedia/v3/internal/kh;)V
    //   5474: aload 48
    //   5476: aload 53
    //   5478: invokevirtual 558	java/util/ArrayList:add	(Ljava/lang/Object;)Z
    //   5481: pop
    //   5482: lload 28
    //   5484: lstore 35
    //   5486: aload_1
    //   5487: astore 38
    //   5489: aload 8
    //   5491: astore 40
    //   5493: aload 11
    //   5495: astore_3
    //   5496: lload 51
    //   5498: lstore 28
    //   5500: aload 10
    //   5502: astore 11
    //   5504: aload 11
    //   5506: astore 10
    //   5508: aload 27
    //   5510: astore_1
    //   5511: aload 40
    //   5513: astore 8
    //   5515: goto +48 -> 5563
    //   5518: aload 10
    //   5520: astore_3
    //   5521: goto -714 -> 4807
    //   5524: aload 40
    //   5526: astore 10
    //   5528: aload 6
    //   5530: ldc_w 321
    //   5533: invokestatic 270	com/google/ads/interactivemedia/v3/internal/rp:b	(Lorg/xmlpull/v1/XmlPullParser;Ljava/lang/String;)Z
    //   5536: ifeq +43 -> 5579
    //   5539: aload 7
    //   5541: aload 6
    //   5543: aconst_null
    //   5544: invokespecial 578	com/google/ads/interactivemedia/v3/internal/pw:a	(Lorg/xmlpull/v1/XmlPullParser;Lcom/google/ads/interactivemedia/v3/internal/qk;)Lcom/google/ads/interactivemedia/v3/internal/qk;
    //   5547: astore 50
    //   5549: lload 28
    //   5551: lstore 35
    //   5553: aload 11
    //   5555: astore_3
    //   5556: aload 27
    //   5558: astore_1
    //   5559: lload 51
    //   5561: lstore 28
    //   5563: ldc2_w 225
    //   5566: lstore 45
    //   5568: lload 28
    //   5570: lstore 51
    //   5572: lload 45
    //   5574: lstore 28
    //   5576: goto +112 -> 5688
    //   5579: aload 6
    //   5581: ldc_w 305
    //   5584: invokestatic 270	com/google/ads/interactivemedia/v3/internal/rp:b	(Lorg/xmlpull/v1/XmlPullParser;Ljava/lang/String;)Z
    //   5587: ifeq +32 -> 5619
    //   5590: aload 7
    //   5592: aload 6
    //   5594: aconst_null
    //   5595: lload 28
    //   5597: invokespecial 580	com/google/ads/interactivemedia/v3/internal/pw:a	(Lorg/xmlpull/v1/XmlPullParser;Lcom/google/ads/interactivemedia/v3/internal/qj;J)Lcom/google/ads/interactivemedia/v3/internal/qj;
    //   5600: astore 50
    //   5602: lload 28
    //   5604: lstore 35
    //   5606: lload 51
    //   5608: lstore 28
    //   5610: aload 27
    //   5612: astore_1
    //   5613: aload 11
    //   5615: astore_3
    //   5616: goto -53 -> 5563
    //   5619: aload 6
    //   5621: ldc_w 283
    //   5624: invokestatic 270	com/google/ads/interactivemedia/v3/internal/rp:b	(Lorg/xmlpull/v1/XmlPullParser;Ljava/lang/String;)Z
    //   5627: ifeq +41 -> 5668
    //   5630: invokestatic 884	java/util/Collections:emptyList	()Ljava/util/List;
    //   5633: astore_1
    //   5634: lload 28
    //   5636: lstore 35
    //   5638: ldc2_w 225
    //   5641: lstore 45
    //   5643: aload_0
    //   5644: aload 6
    //   5646: aconst_null
    //   5647: aload_1
    //   5648: lload 28
    //   5650: invokespecial 582	com/google/ads/interactivemedia/v3/internal/pw:a	(Lorg/xmlpull/v1/XmlPullParser;Lcom/google/ads/interactivemedia/v3/internal/qi;Ljava/util/List;J)Lcom/google/ads/interactivemedia/v3/internal/qi;
    //   5653: astore 50
    //   5655: lload 45
    //   5657: lstore 28
    //   5659: aload 27
    //   5661: astore_1
    //   5662: aload 11
    //   5664: astore_3
    //   5665: goto +23 -> 5688
    //   5668: lload 28
    //   5670: lstore 35
    //   5672: ldc2_w 225
    //   5675: lstore 28
    //   5677: aload 6
    //   5679: invokestatic 281	com/google/ads/interactivemedia/v3/internal/pw:e	(Lorg/xmlpull/v1/XmlPullParser;)V
    //   5682: aload 11
    //   5684: astore_3
    //   5685: aload 27
    //   5687: astore_1
    //   5688: aconst_null
    //   5689: astore 27
    //   5691: aload 6
    //   5693: ldc_w 527
    //   5696: invokestatic 180	com/google/ads/interactivemedia/v3/internal/rp:a	(Lorg/xmlpull/v1/XmlPullParser;Ljava/lang/String;)Z
    //   5699: ifeq +181 -> 5880
    //   5702: new 886	com/google/ads/interactivemedia/v3/internal/qb
    //   5705: astore 11
    //   5707: aload 11
    //   5709: aload 42
    //   5711: lload 43
    //   5713: aload 9
    //   5715: aload 48
    //   5717: invokespecial 889	com/google/ads/interactivemedia/v3/internal/qb:<init>	(Ljava/lang/String;JLjava/util/List;Ljava/util/List;)V
    //   5720: aload 11
    //   5722: lload 35
    //   5724: invokestatic 869	java/lang/Long:valueOf	(J)Ljava/lang/Long;
    //   5727: invokestatic 444	android/util/Pair:create	(Ljava/lang/Object;Ljava/lang/Object;)Landroid/util/Pair;
    //   5730: astore 9
    //   5732: aload 9
    //   5734: getfield 554	android/util/Pair:first	Ljava/lang/Object;
    //   5737: checkcast 886	com/google/ads/interactivemedia/v3/internal/qb
    //   5740: astore 11
    //   5742: aload 11
    //   5744: getfield 890	com/google/ads/interactivemedia/v3/internal/qb:b	J
    //   5747: lload 28
    //   5749: lcmp
    //   5750: ifne +71 -> 5821
    //   5753: iload 18
    //   5755: ifeq +21 -> 5776
    //   5758: iconst_1
    //   5759: istore 34
    //   5761: lload 51
    //   5763: lstore 35
    //   5765: aload 6
    //   5767: astore 11
    //   5769: aload 27
    //   5771: astore 6
    //   5773: goto +215 -> 5988
    //   5776: new 348	com/google/ads/interactivemedia/v3/internal/ce
    //   5779: astore_2
    //   5780: aload_1
    //   5781: invokevirtual 623	java/util/ArrayList:size	()I
    //   5784: istore 57
    //   5786: new 892	java/lang/StringBuilder
    //   5789: astore_1
    //   5790: aload_1
    //   5791: bipush 47
    //   5793: invokespecial 893	java/lang/StringBuilder:<init>	(I)V
    //   5796: aload_1
    //   5797: ldc_w 895
    //   5800: invokevirtual 899	java/lang/StringBuilder:append	(Ljava/lang/String;)Ljava/lang/StringBuilder;
    //   5803: pop
    //   5804: aload_1
    //   5805: iload 57
    //   5807: invokevirtual 902	java/lang/StringBuilder:append	(I)Ljava/lang/StringBuilder;
    //   5810: pop
    //   5811: aload_2
    //   5812: aload_1
    //   5813: invokevirtual 903	java/lang/StringBuilder:toString	()Ljava/lang/String;
    //   5816: invokespecial 904	com/google/ads/interactivemedia/v3/internal/ce:<init>	(Ljava/lang/String;)V
    //   5819: aload_2
    //   5820: athrow
    //   5821: aload 9
    //   5823: getfield 557	android/util/Pair:second	Ljava/lang/Object;
    //   5826: checkcast 195	java/lang/Long
    //   5829: invokevirtual 873	java/lang/Long:longValue	()J
    //   5832: lstore 35
    //   5834: lload 35
    //   5836: lload 28
    //   5838: lcmp
    //   5839: ifne +10 -> 5849
    //   5842: lload 28
    //   5844: lstore 35
    //   5846: goto +16 -> 5862
    //   5849: aload 11
    //   5851: getfield 890	com/google/ads/interactivemedia/v3/internal/qb:b	J
    //   5854: lload 35
    //   5856: ladd
    //   5857: lstore 35
    //   5859: goto -13 -> 5846
    //   5862: aload_1
    //   5863: aload 11
    //   5865: invokevirtual 558	java/util/ArrayList:add	(Ljava/lang/Object;)Z
    //   5868: pop
    //   5869: aload 6
    //   5871: astore 11
    //   5873: aload 27
    //   5875: astore 6
    //   5877: goto +111 -> 5988
    //   5880: aload 6
    //   5882: astore 11
    //   5884: aload 9
    //   5886: astore 6
    //   5888: aload 7
    //   5890: astore 9
    //   5892: aload_2
    //   5893: astore 41
    //   5895: lload 35
    //   5897: lstore 45
    //   5899: aload_3
    //   5900: astore_2
    //   5901: aload 8
    //   5903: astore 53
    //   5905: aload 38
    //   5907: astore 7
    //   5909: aload 6
    //   5911: astore_3
    //   5912: aload_1
    //   5913: astore 6
    //   5915: lload 28
    //   5917: lstore 35
    //   5919: aload 9
    //   5921: astore_1
    //   5922: lload 45
    //   5924: lstore 28
    //   5926: aload 10
    //   5928: astore 8
    //   5930: aload 11
    //   5932: astore 10
    //   5934: aload 54
    //   5936: astore 11
    //   5938: goto -5059 -> 879
    //   5941: aconst_null
    //   5942: astore 11
    //   5944: aload 10
    //   5946: invokestatic 281	com/google/ads/interactivemedia/v3/internal/pw:e	(Lorg/xmlpull/v1/XmlPullParser;)V
    //   5949: ldc2_w 225
    //   5952: lstore 28
    //   5954: aload 6
    //   5956: astore 27
    //   5958: aload_1
    //   5959: astore 6
    //   5961: aload 10
    //   5963: astore 9
    //   5965: aload_3
    //   5966: astore_1
    //   5967: aload_2
    //   5968: astore_3
    //   5969: aload 27
    //   5971: astore_2
    //   5972: aload 7
    //   5974: astore 10
    //   5976: aload 6
    //   5978: astore 7
    //   5980: aload 11
    //   5982: astore 6
    //   5984: aload 9
    //   5986: astore 11
    //   5988: aload 11
    //   5990: aload 5
    //   5992: invokestatic 180	com/google/ads/interactivemedia/v3/internal/rp:a	(Lorg/xmlpull/v1/XmlPullParser;Ljava/lang/String;)Z
    //   5995: ifeq +106 -> 6101
    //   5998: lload 14
    //   6000: lstore 51
    //   6002: lload 14
    //   6004: lload 28
    //   6006: lcmp
    //   6007: ifne +43 -> 6050
    //   6010: lload 35
    //   6012: lload 28
    //   6014: lcmp
    //   6015: ifeq +10 -> 6025
    //   6018: lload 35
    //   6020: lstore 51
    //   6022: goto +28 -> 6050
    //   6025: iload 18
    //   6027: ifeq +10 -> 6037
    //   6030: lload 14
    //   6032: lstore 51
    //   6034: goto +16 -> 6050
    //   6037: new 348	com/google/ads/interactivemedia/v3/internal/ce
    //   6040: astore_1
    //   6041: aload_1
    //   6042: ldc_w 906
    //   6045: invokespecial 904	com/google/ads/interactivemedia/v3/internal/ce:<init>	(Ljava/lang/String;)V
    //   6048: aload_1
    //   6049: athrow
    //   6050: aload_1
    //   6051: invokevirtual 712	java/util/ArrayList:isEmpty	()Z
    //   6054: ifne +34 -> 6088
    //   6057: new 908	com/google/ads/interactivemedia/v3/internal/aaa
    //   6060: dup
    //   6061: lload 12
    //   6063: lload 51
    //   6065: lload 16
    //   6067: iload 18
    //   6069: lload 19
    //   6071: lload 21
    //   6073: lload 23
    //   6075: lload 25
    //   6077: aload 30
    //   6079: aload 31
    //   6081: aload 32
    //   6083: aload_1
    //   6084: invokespecial 911	com/google/ads/interactivemedia/v3/internal/aaa:<init>	(JJJZJJJJLcom/google/ads/interactivemedia/v3/internal/qa;Lcom/google/ads/interactivemedia/v3/internal/qp;Landroid/net/Uri;Ljava/util/List;)V
    //   6087: areturn
    //   6088: new 348	com/google/ads/interactivemedia/v3/internal/ce
    //   6091: astore_1
    //   6092: aload_1
    //   6093: ldc_w 913
    //   6096: invokespecial 904	com/google/ads/interactivemedia/v3/internal/ce:<init>	(Ljava/lang/String;)V
    //   6099: aload_1
    //   6100: athrow
    //   6101: aload 7
    //   6103: astore 27
    //   6105: aload_2
    //   6106: astore 7
    //   6108: aload_3
    //   6109: astore_2
    //   6110: aload 6
    //   6112: astore 9
    //   6114: aload_1
    //   6115: astore_3
    //   6116: aload 27
    //   6118: astore_1
    //   6119: aload 7
    //   6121: astore 6
    //   6123: aload 10
    //   6125: astore 7
    //   6127: aload 11
    //   6129: astore 10
    //   6131: aload 9
    //   6133: astore 11
    //   6135: goto -5805 -> 330
    //   6138: new 348	com/google/ads/interactivemedia/v3/internal/ce
    //   6141: astore_1
    //   6142: aload_1
    //   6143: ldc_w 915
    //   6146: invokespecial 904	com/google/ads/interactivemedia/v3/internal/ce:<init>	(Ljava/lang/String;)V
    //   6149: aload_1
    //   6150: athrow
    //   6151: astore_1
    //   6152: goto +4 -> 6156
    //   6155: astore_1
    //   6156: new 348	com/google/ads/interactivemedia/v3/internal/ce
    //   6159: dup
    //   6160: aload_1
    //   6161: invokespecial 918	com/google/ads/interactivemedia/v3/internal/ce:<init>	(Ljava/lang/Throwable;)V
    //   6164: athrow
    // Local variable table:
    //   start	length	slot	name	signature
    //   0	6165	0	this	pw
    //   0	6165	1	paramUri	android.net.Uri
    //   0	6165	2	paramInputStream	java.io.InputStream
    //   1	6115	3	localObject1	Object
    //   5	592	4	str1	String
    //   10	5981	5	str2	String
    //   15	6107	6	localObject2	Object
    //   19	6107	7	localObject3	Object
    //   24	5905	8	localObject4	Object
    //   27	6105	9	localObject5	Object
    //   36	6094	10	localObject6	Object
    //   39	6095	11	localObject7	Object
    //   108	5954	12	l1	long
    //   124	5907	14	l2	long
    //   140	5926	16	l3	long
    //   162	5906	18	bool1	boolean
    //   183	5887	19	l4	long
    //   216	5856	21	l5	long
    //   245	5829	23	l6	long
    //   269	5807	25	l7	long
    //   277	5840	27	localObject8	Object
    //   295	5718	28	l8	long
    //   304	5774	30	localqa	qa
    //   308	5772	31	localObject9	Object
    //   312	5770	32	localObject10	Object
    //   315	64	33	i	int
    //   319	5441	34	j	int
    //   325	5694	35	l9	long
    //   351	1684	37	bool2	boolean
    //   391	5515	38	localObject11	Object
    //   436	4171	39	localObject12	Object
    //   456	5069	40	localObject13	Object
    //   471	5423	41	localObject14	Object
    //   767	4943	42	str3	String
    //   782	4930	43	l10	long
    //   787	5136	45	l11	long
    //   822	3941	47	str4	String
    //   830	4886	48	localArrayList1	ArrayList
    //   841	85	49	k	int
    //   844	4810	50	localObject15	Object
    //   851	5213	51	l12	long
    //   855	5049	53	localObject16	Object
    //   922	5013	54	localObject17	Object
    //   1006	4435	55	localObject18	Object
    //   1024	3539	56	m	int
    //   1034	4772	57	n	int
    //   1053	3641	58	localObject19	Object
    //   1072	3615	59	localObject20	Object
    //   1090	3295	60	i1	int
    //   1109	3270	61	i2	int
    //   1122	2892	62	f1	float
    //   1136	2465	63	i3	int
    //   1170	2264	64	str5	String
    //   1178	3050	65	localArrayList2	ArrayList
    //   1194	3236	66	localArrayList3	ArrayList
    //   1210	3359	67	localArrayList4	ArrayList
    //   1223	2957	68	localObject21	Object
    //   1238	3453	69	localObject22	Object
    //   1248	3378	70	localObject23	Object
    //   1256	93	71	i4	int
    //   1260	2721	72	localObject24	Object
    //   1264	3411	73	localObject25	Object
    //   1267	3270	74	i5	int
    //   1286	3319	75	localObject26	Object
    //   1290	4002	76	localObject27	Object
    //   1294	3294	77	localObject28	Object
    //   1716	2267	78	localObject29	Object
    //   1727	1715	79	i6	int
    //   1739	2252	80	localObject30	Object
    //   1751	2350	81	localObject31	Object
    //   1763	1280	82	i7	int
    //   1767	2384	83	localObject32	Object
    //   1771	2224	84	i8	int
    //   1783	1262	85	i9	int
    //   1792	2220	86	f2	float
    //   1808	1276	87	i10	int
    //   1822	2202	88	i11	int
    //   1827	2175	89	localObject33	Object
    //   1837	1129	90	localArrayList5	ArrayList
    //   1864	2168	91	localObject34	Object
    //   1872	2156	92	localObject35	Object
    //   1883	2125	93	localObject36	Object
    //   1887	2133	94	localObject37	Object
    //   1905	2137	95	i12	int
    //   2543	377	96	i13	int
    //   2547	899	97	i14	int
    //   2621	309	98	i15	int
    //   4845	487	99	l13	long
    //   4856	487	101	l14	long
    // Exception table:
    //   from	to	target	type
    //   172	185	188	org/xmlpull/v1/XmlPullParserException
    //   205	218	188	org/xmlpull/v1/XmlPullParserException
    //   234	247	188	org/xmlpull/v1/XmlPullParserException
    //   366	374	188	org/xmlpull/v1/XmlPullParserException
    //   446	458	188	org/xmlpull/v1/XmlPullParserException
    //   461	473	188	org/xmlpull/v1/XmlPullParserException
    //   488	496	188	org/xmlpull/v1/XmlPullParserException
    //   499	510	188	org/xmlpull/v1/XmlPullParserException
    //   513	522	188	org/xmlpull/v1/XmlPullParserException
    //   528	539	188	org/xmlpull/v1/XmlPullParserException
    //   542	551	188	org/xmlpull/v1/XmlPullParserException
    //   557	568	188	org/xmlpull/v1/XmlPullParserException
    //   571	580	188	org/xmlpull/v1/XmlPullParserException
    //   586	591	188	org/xmlpull/v1/XmlPullParserException
    //   594	604	188	org/xmlpull/v1/XmlPullParserException
    //   607	626	188	org/xmlpull/v1/XmlPullParserException
    //   662	691	188	org/xmlpull/v1/XmlPullParserException
    //   715	727	188	org/xmlpull/v1/XmlPullParserException
    //   915	924	188	org/xmlpull/v1/XmlPullParserException
    //   2010	2018	2021	org/xmlpull/v1/XmlPullParserException
    //   2039	2053	2021	org/xmlpull/v1/XmlPullParserException
    //   1220	1230	4700	org/xmlpull/v1/XmlPullParserException
    //   1235	1245	4700	org/xmlpull/v1/XmlPullParserException
    //   1245	1255	4700	org/xmlpull/v1/XmlPullParserException
    //   1315	1333	4700	org/xmlpull/v1/XmlPullParserException
    //   1338	1347	4700	org/xmlpull/v1/XmlPullParserException
    //   1436	1461	4700	org/xmlpull/v1/XmlPullParserException
    //   1466	1473	4700	org/xmlpull/v1/XmlPullParserException
    //   1473	1480	4700	org/xmlpull/v1/XmlPullParserException
    //   1485	1496	4700	org/xmlpull/v1/XmlPullParserException
    //   1507	1530	4700	org/xmlpull/v1/XmlPullParserException
    //   1548	1557	4700	org/xmlpull/v1/XmlPullParserException
    //   1557	1569	4700	org/xmlpull/v1/XmlPullParserException
    //   1590	1615	4700	org/xmlpull/v1/XmlPullParserException
    //   1618	1636	4700	org/xmlpull/v1/XmlPullParserException
    //   1639	1664	4700	org/xmlpull/v1/XmlPullParserException
    //   1667	1688	4700	org/xmlpull/v1/XmlPullParserException
    //   1691	1701	4700	org/xmlpull/v1/XmlPullParserException
    //   1706	1718	4700	org/xmlpull/v1/XmlPullParserException
    //   1718	1753	4700	org/xmlpull/v1/XmlPullParserException
    //   1753	1765	4700	org/xmlpull/v1/XmlPullParserException
    //   1773	1785	4700	org/xmlpull/v1/XmlPullParserException
    //   1785	1794	4700	org/xmlpull/v1/XmlPullParserException
    //   1798	1820	4700	org/xmlpull/v1/XmlPullParserException
    //   1824	1844	4700	org/xmlpull/v1/XmlPullParserException
    //   1922	1940	4700	org/xmlpull/v1/XmlPullParserException
    //   1945	1952	4700	org/xmlpull/v1/XmlPullParserException
    //   1968	1986	4700	org/xmlpull/v1/XmlPullParserException
    //   1994	2010	4700	org/xmlpull/v1/XmlPullParserException
    //   2025	2034	4700	org/xmlpull/v1/XmlPullParserException
    //   2062	2088	4700	org/xmlpull/v1/XmlPullParserException
    //   2103	2125	4700	org/xmlpull/v1/XmlPullParserException
    //   2129	2135	4700	org/xmlpull/v1/XmlPullParserException
    //   2135	2141	4700	org/xmlpull/v1/XmlPullParserException
    //   2152	2163	4700	org/xmlpull/v1/XmlPullParserException
    //   2172	2197	4700	org/xmlpull/v1/XmlPullParserException
    //   2203	2224	4700	org/xmlpull/v1/XmlPullParserException
    //   2227	2232	4700	org/xmlpull/v1/XmlPullParserException
    //   2273	2298	4700	org/xmlpull/v1/XmlPullParserException
    //   2301	2315	4700	org/xmlpull/v1/XmlPullParserException
    //   2318	2326	4700	org/xmlpull/v1/XmlPullParserException
    //   2335	2345	4700	org/xmlpull/v1/XmlPullParserException
    //   2350	2361	4700	org/xmlpull/v1/XmlPullParserException
    //   2368	2379	4700	org/xmlpull/v1/XmlPullParserException
    //   2386	2396	4700	org/xmlpull/v1/XmlPullParserException
    //   2401	2412	4700	org/xmlpull/v1/XmlPullParserException
    //   2419	2441	4700	org/xmlpull/v1/XmlPullParserException
    //   2461	2468	4700	org/xmlpull/v1/XmlPullParserException
    //   2484	2523	4700	org/xmlpull/v1/XmlPullParserException
    //   2553	2575	4700	org/xmlpull/v1/XmlPullParserException
    //   2579	2606	4700	org/xmlpull/v1/XmlPullParserException
    //   2631	2676	4700	org/xmlpull/v1/XmlPullParserException
    //   2679	2700	4700	org/xmlpull/v1/XmlPullParserException
    //   2705	2748	4700	org/xmlpull/v1/XmlPullParserException
    //   2751	2762	4700	org/xmlpull/v1/XmlPullParserException
    //   2768	2779	4700	org/xmlpull/v1/XmlPullParserException
    //   2785	2796	4700	org/xmlpull/v1/XmlPullParserException
    //   2802	2813	4700	org/xmlpull/v1/XmlPullParserException
    //   2819	2830	4700	org/xmlpull/v1/XmlPullParserException
    //   2942	2952	4700	org/xmlpull/v1/XmlPullParserException
    //   2955	3002	4700	org/xmlpull/v1/XmlPullParserException
    //   3021	3057	4700	org/xmlpull/v1/XmlPullParserException
    //   3060	3096	4700	org/xmlpull/v1/XmlPullParserException
    //   3103	3122	4700	org/xmlpull/v1/XmlPullParserException
    //   3125	3165	4700	org/xmlpull/v1/XmlPullParserException
    //   3170	3199	4700	org/xmlpull/v1/XmlPullParserException
    //   3202	3225	4700	org/xmlpull/v1/XmlPullParserException
    //   3228	3239	4700	org/xmlpull/v1/XmlPullParserException
    //   3239	3247	4700	org/xmlpull/v1/XmlPullParserException
    //   3259	3270	4700	org/xmlpull/v1/XmlPullParserException
    //   3273	3313	4700	org/xmlpull/v1/XmlPullParserException
    //   3318	3347	4700	org/xmlpull/v1/XmlPullParserException
    //   3350	3373	4700	org/xmlpull/v1/XmlPullParserException
    //   3376	3387	4700	org/xmlpull/v1/XmlPullParserException
    //   3387	3395	4700	org/xmlpull/v1/XmlPullParserException
    //   3404	3428	4700	org/xmlpull/v1/XmlPullParserException
    //   3431	3453	4700	org/xmlpull/v1/XmlPullParserException
    //   3460	3468	4700	org/xmlpull/v1/XmlPullParserException
    //   3468	3513	4700	org/xmlpull/v1/XmlPullParserException
    //   3519	3526	4700	org/xmlpull/v1/XmlPullParserException
    //   3532	3539	4700	org/xmlpull/v1/XmlPullParserException
    //   3548	3565	4700	org/xmlpull/v1/XmlPullParserException
    //   3736	3752	4700	org/xmlpull/v1/XmlPullParserException
    //   3752	3761	6151	org/xmlpull/v1/XmlPullParserException
    //   3863	3887	6151	org/xmlpull/v1/XmlPullParserException
    //   3949	3965	6151	org/xmlpull/v1/XmlPullParserException
    //   3969	3982	6151	org/xmlpull/v1/XmlPullParserException
    //   4064	4089	6151	org/xmlpull/v1/XmlPullParserException
    //   4092	4105	6151	org/xmlpull/v1/XmlPullParserException
    //   4198	4224	6151	org/xmlpull/v1/XmlPullParserException
    //   4231	4267	6151	org/xmlpull/v1/XmlPullParserException
    //   4279	4286	6151	org/xmlpull/v1/XmlPullParserException
    //   4286	4311	6151	org/xmlpull/v1/XmlPullParserException
    //   4316	4336	6151	org/xmlpull/v1/XmlPullParserException
    //   4339	4375	6151	org/xmlpull/v1/XmlPullParserException
    //   4390	4413	6151	org/xmlpull/v1/XmlPullParserException
    //   4420	4491	6151	org/xmlpull/v1/XmlPullParserException
    //   4498	4528	6151	org/xmlpull/v1/XmlPullParserException
    //   4528	4536	6151	org/xmlpull/v1/XmlPullParserException
    //   4542	4555	6151	org/xmlpull/v1/XmlPullParserException
    //   4555	4575	6151	org/xmlpull/v1/XmlPullParserException
    //   4579	4587	6151	org/xmlpull/v1/XmlPullParserException
    //   4736	4747	6151	org/xmlpull/v1/XmlPullParserException
    //   4750	4804	6151	org/xmlpull/v1/XmlPullParserException
    //   4807	4923	6151	org/xmlpull/v1/XmlPullParserException
    //   4923	5000	6151	org/xmlpull/v1/XmlPullParserException
    //   5009	5023	6151	org/xmlpull/v1/XmlPullParserException
    //   5029	5043	6151	org/xmlpull/v1/XmlPullParserException
    //   5049	5063	6151	org/xmlpull/v1/XmlPullParserException
    //   5069	5083	6151	org/xmlpull/v1/XmlPullParserException
    //   5089	5103	6151	org/xmlpull/v1/XmlPullParserException
    //   5109	5123	6151	org/xmlpull/v1/XmlPullParserException
    //   5129	5144	6151	org/xmlpull/v1/XmlPullParserException
    //   5150	5172	6151	org/xmlpull/v1/XmlPullParserException
    //   5178	5200	6151	org/xmlpull/v1/XmlPullParserException
    //   5206	5253	6151	org/xmlpull/v1/XmlPullParserException
    //   5259	5266	6151	org/xmlpull/v1/XmlPullParserException
    //   5269	5280	6151	org/xmlpull/v1/XmlPullParserException
    //   5280	5288	6151	org/xmlpull/v1/XmlPullParserException
    //   5291	5305	6151	org/xmlpull/v1/XmlPullParserException
    //   5313	5320	6151	org/xmlpull/v1/XmlPullParserException
    //   5320	5356	6151	org/xmlpull/v1/XmlPullParserException
    //   5359	5364	6151	org/xmlpull/v1/XmlPullParserException
    //   5367	5396	6151	org/xmlpull/v1/XmlPullParserException
    //   5399	5449	6151	org/xmlpull/v1/XmlPullParserException
    //   5455	5482	6151	org/xmlpull/v1/XmlPullParserException
    //   5528	5549	6151	org/xmlpull/v1/XmlPullParserException
    //   5579	5602	6151	org/xmlpull/v1/XmlPullParserException
    //   5619	5634	6151	org/xmlpull/v1/XmlPullParserException
    //   5643	5655	6151	org/xmlpull/v1/XmlPullParserException
    //   5677	5682	6151	org/xmlpull/v1/XmlPullParserException
    //   5691	5753	6151	org/xmlpull/v1/XmlPullParserException
    //   5776	5821	6151	org/xmlpull/v1/XmlPullParserException
    //   5821	5834	6151	org/xmlpull/v1/XmlPullParserException
    //   5849	5859	6151	org/xmlpull/v1/XmlPullParserException
    //   5862	5869	6151	org/xmlpull/v1/XmlPullParserException
    //   5944	5949	6151	org/xmlpull/v1/XmlPullParserException
    //   5988	5998	6151	org/xmlpull/v1/XmlPullParserException
    //   6037	6050	6151	org/xmlpull/v1/XmlPullParserException
    //   6050	6088	6151	org/xmlpull/v1/XmlPullParserException
    //   6088	6101	6151	org/xmlpull/v1/XmlPullParserException
    //   6138	6151	6151	org/xmlpull/v1/XmlPullParserException
    //   29	38	6155	org/xmlpull/v1/XmlPullParserException
    //   44	53	6155	org/xmlpull/v1/XmlPullParserException
    //   56	67	6155	org/xmlpull/v1/XmlPullParserException
    //   70	86	6155	org/xmlpull/v1/XmlPullParserException
    //   89	94	6155	org/xmlpull/v1/XmlPullParserException
    //   97	110	6155	org/xmlpull/v1/XmlPullParserException
    //   113	126	6155	org/xmlpull/v1/XmlPullParserException
    //   129	142	6155	org/xmlpull/v1/XmlPullParserException
    //   145	164	6155	org/xmlpull/v1/XmlPullParserException
    //   258	271	6155	org/xmlpull/v1/XmlPullParserException
    //   274	279	6155	org/xmlpull/v1/XmlPullParserException
    //   282	287	6155	org/xmlpull/v1/XmlPullParserException
    //   333	341	6155	org/xmlpull/v1/XmlPullParserException
    //   344	353	6155	org/xmlpull/v1/XmlPullParserException
    //   424	433	6155	org/xmlpull/v1/XmlPullParserException
    //   640	650	6155	org/xmlpull/v1/XmlPullParserException
    //   697	707	6155	org/xmlpull/v1/XmlPullParserException
    //   738	749	6155	org/xmlpull/v1/XmlPullParserException
    //   757	769	6155	org/xmlpull/v1/XmlPullParserException
    //   772	784	6155	org/xmlpull/v1/XmlPullParserException
    //   792	804	6155	org/xmlpull/v1/XmlPullParserException
    //   807	812	6155	org/xmlpull/v1/XmlPullParserException
    //   815	820	6155	org/xmlpull/v1/XmlPullParserException
    //   827	832	6155	org/xmlpull/v1/XmlPullParserException
    //   835	840	6155	org/xmlpull/v1/XmlPullParserException
    //   882	890	6155	org/xmlpull/v1/XmlPullParserException
    //   893	902	6155	org/xmlpull/v1/XmlPullParserException
    //   990	1000	6155	org/xmlpull/v1/XmlPullParserException
    //   1016	1026	6155	org/xmlpull/v1/XmlPullParserException
    //   1029	1036	6155	org/xmlpull/v1/XmlPullParserException
    //   1042	1055	6155	org/xmlpull/v1/XmlPullParserException
    //   1061	1074	6155	org/xmlpull/v1/XmlPullParserException
    //   1081	1092	6155	org/xmlpull/v1/XmlPullParserException
    //   1100	1111	6155	org/xmlpull/v1/XmlPullParserException
    //   1114	1124	6155	org/xmlpull/v1/XmlPullParserException
    //   1127	1138	6155	org/xmlpull/v1/XmlPullParserException
    //   1141	1152	6155	org/xmlpull/v1/XmlPullParserException
    //   1159	1172	6155	org/xmlpull/v1/XmlPullParserException
    //   1175	1180	6155	org/xmlpull/v1/XmlPullParserException
    //   1183	1188	6155	org/xmlpull/v1/XmlPullParserException
    //   1191	1196	6155	org/xmlpull/v1/XmlPullParserException
    //   1199	1204	6155	org/xmlpull/v1/XmlPullParserException
    //   1207	1212	6155	org/xmlpull/v1/XmlPullParserException
    //   1215	1220	6155	org/xmlpull/v1/XmlPullParserException
  }
  
  private static String b(XmlPullParser paramXmlPullParser, String paramString)
    throws XmlPullParserException, IOException
  {
    paramXmlPullParser.next();
    return rp.b(paramString, paramXmlPullParser.getText());
  }
  
  private static String b(XmlPullParser paramXmlPullParser, String paramString1, String paramString2)
  {
    paramXmlPullParser = paramXmlPullParser.getAttributeValue(null, paramString1);
    if (paramXmlPullParser == null) {
      return paramString2;
    }
    return paramXmlPullParser;
  }
  
  private static boolean b(String paramString)
  {
    return (vs.c(paramString)) || ("application/ttml+xml".equals(paramString)) || ("application/x-mp4-vtt".equals(paramString)) || ("application/cea-708".equals(paramString)) || ("application/cea-608".equals(paramString));
  }
  
  private static long c(XmlPullParser paramXmlPullParser, String paramString, long paramLong)
  {
    paramXmlPullParser = paramXmlPullParser.getAttributeValue(null, paramString);
    if (paramXmlPullParser == null) {
      return paramLong;
    }
    return Long.parseLong(paramXmlPullParser);
  }
  
  private final qd c(XmlPullParser paramXmlPullParser)
  {
    return a(paramXmlPullParser, "sourceURL", "range");
  }
  
  private static int d(XmlPullParser paramXmlPullParser)
    throws XmlPullParserException, IOException
  {
    String str = b(paramXmlPullParser, "schemeIdUri", null);
    boolean bool = "urn:mpeg:dash:23003:3:audio_channel_configuration:2011".equals(str);
    int i = 2;
    if (bool)
    {
      i = a(paramXmlPullParser, "value", -1);
    }
    else
    {
      int j;
      if ("tag:dolby.com,2014:dash:audio_channel_configuration:2011".equals(str))
      {
        str = wl.d(paramXmlPullParser.getAttributeValue(null, "value"));
        if (str != null)
        {
          switch (str.hashCode())
          {
          }
          do
          {
            do
            {
              do
              {
                do
                {
                  j = -1;
                  break;
                } while (!str.equals("fa01"));
                j = 3;
                break;
              } while (!str.equals("f801"));
              j = 2;
              break;
            } while (!str.equals("a000"));
            j = 1;
            break;
          } while (!str.equals("4000"));
          j = 0;
        }
      }
      switch (j)
      {
      default: 
        break;
      case 3: 
        i = 8;
        break;
      case 2: 
        i = 6;
        break;
      case 0: 
        i = 1;
        break label242;
        i = -1;
      }
    }
    label242:
    do
    {
      paramXmlPullParser.next();
    } while (!rp.a(paramXmlPullParser, "AudioChannelConfiguration"));
    return i;
  }
  
  private static void e(XmlPullParser paramXmlPullParser)
    throws IOException, XmlPullParserException
  {
    if (!rp.b(paramXmlPullParser)) {
      return;
    }
    int i = 1;
    while (i != 0)
    {
      paramXmlPullParser.next();
      if (rp.b(paramXmlPullParser)) {
        i++;
      } else if (rp.a(paramXmlPullParser)) {
        i--;
      }
    }
  }
}

/* Location:
 * Qualified Name:     com.google.ads.interactivemedia.v3.internal.pw
 * Java Class Version: 6 (50.0)
 * JD-Core Version:    0.7.1
 */