package eb;

public final class d1
{
  /* Error */
  public static java.util.List a(Class paramClass, java.util.List paramList, ClassLoader paramClassLoader, a parama)
  {
    // Byte code:
    //   0: ldc 14
    //   2: iconst_0
    //   3: aload_2
    //   4: invokestatic 20	java/lang/Class:forName	(Ljava/lang/String;ZLjava/lang/ClassLoader;)Ljava/lang/Class;
    //   7: pop
    //   8: iconst_1
    //   9: istore 4
    //   11: goto +8 -> 19
    //   14: astore 5
    //   16: iconst_0
    //   17: istore 4
    //   19: iload 4
    //   21: ifeq +117 -> 138
    //   24: new 22	java/util/ArrayList
    //   27: dup
    //   28: invokespecial 26	java/util/ArrayList:<init>	()V
    //   31: astore_2
    //   32: aload_1
    //   33: invokeinterface 32 1 0
    //   38: astore 5
    //   40: aload_2
    //   41: astore_1
    //   42: aload 5
    //   44: invokeinterface 38 1 0
    //   49: ifeq +114 -> 163
    //   52: aload 5
    //   54: invokeinterface 42 1 0
    //   59: checkcast 16	java/lang/Class
    //   62: astore 6
    //   64: aload 6
    //   66: aload_0
    //   67: invokevirtual 46	java/lang/Class:asSubclass	(Ljava/lang/Class;)Ljava/lang/Class;
    //   70: iconst_0
    //   71: anewarray 16	java/lang/Class
    //   74: invokevirtual 50	java/lang/Class:getConstructor	([Ljava/lang/Class;)Ljava/lang/reflect/Constructor;
    //   77: iconst_0
    //   78: anewarray 4	java/lang/Object
    //   81: invokevirtual 56	java/lang/reflect/Constructor:newInstance	([Ljava/lang/Object;)Ljava/lang/Object;
    //   84: astore_1
    //   85: goto +37 -> 122
    //   88: astore_0
    //   89: new 58	java/util/ServiceConfigurationError
    //   92: dup
    //   93: ldc 60
    //   95: iconst_2
    //   96: anewarray 4	java/lang/Object
    //   99: dup
    //   100: iconst_0
    //   101: aload 6
    //   103: invokevirtual 64	java/lang/Class:getName	()Ljava/lang/String;
    //   106: aastore
    //   107: dup
    //   108: iconst_1
    //   109: aload_0
    //   110: aastore
    //   111: invokestatic 70	java/lang/String:format	(Ljava/lang/String;[Ljava/lang/Object;)Ljava/lang/String;
    //   114: aload_0
    //   115: invokespecial 73	java/util/ServiceConfigurationError:<init>	(Ljava/lang/String;Ljava/lang/Throwable;)V
    //   118: athrow
    //   119: astore_1
    //   120: aconst_null
    //   121: astore_1
    //   122: aload_1
    //   123: ifnonnull +6 -> 129
    //   126: goto -86 -> 40
    //   129: aload_2
    //   130: aload_1
    //   131: invokevirtual 77	java/util/ArrayList:add	(Ljava/lang/Object;)Z
    //   134: pop
    //   135: goto -95 -> 40
    //   138: aload_0
    //   139: aload_2
    //   140: invokestatic 83	java/util/ServiceLoader:load	(Ljava/lang/Class;Ljava/lang/ClassLoader;)Ljava/util/ServiceLoader;
    //   143: astore_2
    //   144: aload_2
    //   145: astore_1
    //   146: aload_2
    //   147: invokevirtual 84	java/util/ServiceLoader:iterator	()Ljava/util/Iterator;
    //   150: invokeinterface 38 1 0
    //   155: ifne +8 -> 163
    //   158: aload_0
    //   159: invokestatic 87	java/util/ServiceLoader:load	(Ljava/lang/Class;)Ljava/util/ServiceLoader;
    //   162: astore_1
    //   163: new 22	java/util/ArrayList
    //   166: dup
    //   167: invokespecial 26	java/util/ArrayList:<init>	()V
    //   170: astore_0
    //   171: aload_1
    //   172: invokeinterface 32 1 0
    //   177: astore_1
    //   178: aload_1
    //   179: invokeinterface 38 1 0
    //   184: ifeq +32 -> 216
    //   187: aload_1
    //   188: invokeinterface 42 1 0
    //   193: astore_2
    //   194: aload_3
    //   195: aload_2
    //   196: invokeinterface 89 2 0
    //   201: ifne +6 -> 207
    //   204: goto -26 -> 178
    //   207: aload_0
    //   208: aload_2
    //   209: invokevirtual 77	java/util/ArrayList:add	(Ljava/lang/Object;)Z
    //   212: pop
    //   213: goto -35 -> 178
    //   216: aload_0
    //   217: new 91	eb/c1
    //   220: dup
    //   221: aload_3
    //   222: invokespecial 94	eb/c1:<init>	(Leb/d1$a;)V
    //   225: invokestatic 100	java/util/Collections:reverseOrder	(Ljava/util/Comparator;)Ljava/util/Comparator;
    //   228: invokestatic 104	java/util/Collections:sort	(Ljava/util/List;Ljava/util/Comparator;)V
    //   231: aload_0
    //   232: invokestatic 108	java/util/Collections:unmodifiableList	(Ljava/util/List;)Ljava/util/List;
    //   235: areturn
    // Local variable table:
    //   start	length	slot	name	signature
    //   0	236	0	paramClass	Class
    //   0	236	1	paramList	java.util.List
    //   0	236	2	paramClassLoader	ClassLoader
    //   0	236	3	parama	a
    //   9	11	4	i	int
    //   14	1	5	localException	Exception
    //   38	15	5	localIterator	java.util.Iterator
    //   62	40	6	localClass	Class
    // Exception table:
    //   from	to	target	type
    //   0	8	14	java/lang/Exception
    //   64	85	88	finally
    //   64	85	119	java/lang/ClassCastException
  }
  
  public static abstract interface a<T>
  {
    public abstract boolean a(T paramT);
    
    public abstract int b(T paramT);
  }
}

/* Location:
 * Qualified Name:     eb.d1
 * Java Class Version: 6 (50.0)
 * JD-Core Version:    0.7.1
 */