package F0;

import g0.z;
import java.util.List;

public final class d
{
  public final List a;
  public final int b;
  public final int c;
  public final int d;
  public final int e;
  public final int f;
  public final int g;
  public final int h;
  public final int i;
  public final int j;
  public final float k;
  public final String l;
  
  public d(List paramList, int paramInt1, int paramInt2, int paramInt3, int paramInt4, int paramInt5, int paramInt6, int paramInt7, int paramInt8, int paramInt9, float paramFloat, String paramString)
  {
    a = paramList;
    b = paramInt1;
    c = paramInt2;
    d = paramInt3;
    e = paramInt4;
    f = paramInt5;
    g = paramInt6;
    h = paramInt7;
    i = paramInt8;
    j = paramInt9;
    k = paramFloat;
    l = paramString;
  }
  
  public static byte[] a(z paramz)
  {
    int m = paramz.M();
    int n = paramz.f();
    paramz.U(m);
    return g0.d.d(paramz.e(), n, m);
  }
  
  /* Error */
  public static d b(z paramz)
  {
    // Byte code:
    //   0: aload_0
    //   1: iconst_4
    //   2: invokevirtual 63	g0/z:U	(I)V
    //   5: aload_0
    //   6: invokevirtual 77	g0/z:G	()I
    //   9: iconst_3
    //   10: iand
    //   11: iconst_1
    //   12: iadd
    //   13: istore_1
    //   14: iload_1
    //   15: iconst_3
    //   16: if_icmpeq +285 -> 301
    //   19: new 79	java/util/ArrayList
    //   22: astore_2
    //   23: aload_2
    //   24: invokespecial 80	java/util/ArrayList:<init>	()V
    //   27: aload_0
    //   28: invokevirtual 77	g0/z:G	()I
    //   31: bipush 31
    //   33: iand
    //   34: istore_3
    //   35: iconst_0
    //   36: istore 4
    //   38: iload 4
    //   40: iload_3
    //   41: if_icmpge +24 -> 65
    //   44: aload_2
    //   45: aload_0
    //   46: invokestatic 82	F0/d:a	(Lg0/z;)[B
    //   49: invokeinterface 88 2 0
    //   54: pop
    //   55: iinc 4 1
    //   58: goto -20 -> 38
    //   61: astore_0
    //   62: goto +249 -> 311
    //   65: aload_0
    //   66: invokevirtual 77	g0/z:G	()I
    //   69: istore 5
    //   71: iconst_0
    //   72: istore 4
    //   74: iload 4
    //   76: iload 5
    //   78: if_icmpge +20 -> 98
    //   81: aload_2
    //   82: aload_0
    //   83: invokestatic 82	F0/d:a	(Lg0/z;)[B
    //   86: invokeinterface 88 2 0
    //   91: pop
    //   92: iinc 4 1
    //   95: goto -21 -> 74
    //   98: iload_3
    //   99: ifle +124 -> 223
    //   102: aload_2
    //   103: iconst_0
    //   104: invokeinterface 92 2 0
    //   109: checkcast 94	[B
    //   112: astore_0
    //   113: aload_2
    //   114: iconst_0
    //   115: invokeinterface 92 2 0
    //   120: checkcast 94	[B
    //   123: iload_1
    //   124: aload_0
    //   125: arraylength
    //   126: invokestatic 99	h0/d:l	([BII)Lh0/d$c;
    //   129: astore_0
    //   130: aload_0
    //   131: getfield 102	h0/d$c:f	I
    //   134: istore 6
    //   136: aload_0
    //   137: getfield 103	h0/d$c:g	I
    //   140: istore 7
    //   142: aload_0
    //   143: getfield 104	h0/d$c:i	I
    //   146: istore 8
    //   148: aload_0
    //   149: getfield 105	h0/d$c:j	I
    //   152: istore 9
    //   154: aload_0
    //   155: getfield 108	h0/d$c:q	I
    //   158: istore 10
    //   160: aload_0
    //   161: getfield 111	h0/d$c:r	I
    //   164: istore 5
    //   166: aload_0
    //   167: getfield 114	h0/d$c:s	I
    //   170: istore_3
    //   171: aload_0
    //   172: getfield 117	h0/d$c:t	I
    //   175: istore 4
    //   177: aload_0
    //   178: getfield 119	h0/d$c:h	F
    //   181: fstore 11
    //   183: aload_0
    //   184: getfield 121	h0/d$c:a	I
    //   187: aload_0
    //   188: getfield 122	h0/d$c:b	I
    //   191: aload_0
    //   192: getfield 123	h0/d$c:c	I
    //   195: invokestatic 126	g0/d:a	(III)Ljava/lang/String;
    //   198: astore_0
    //   199: iload 9
    //   201: bipush 8
    //   203: iadd
    //   204: istore 12
    //   206: iinc 8 8
    //   209: iload 5
    //   211: istore 9
    //   213: iload_3
    //   214: istore 13
    //   216: iload 4
    //   218: istore 14
    //   220: goto +52 -> 272
    //   223: iconst_m1
    //   224: istore 6
    //   226: iload 6
    //   228: istore 4
    //   230: iload 4
    //   232: istore_3
    //   233: iload_3
    //   234: istore 5
    //   236: iload 5
    //   238: istore 10
    //   240: iload 10
    //   242: istore 8
    //   244: iload 8
    //   246: istore 13
    //   248: fconst_1
    //   249: fstore 11
    //   251: aconst_null
    //   252: astore_0
    //   253: bipush 16
    //   255: istore 14
    //   257: iload 8
    //   259: istore 9
    //   261: iload 5
    //   263: istore 12
    //   265: iload_3
    //   266: istore 8
    //   268: iload 4
    //   270: istore 7
    //   272: new 2	F0/d
    //   275: dup
    //   276: aload_2
    //   277: iload_1
    //   278: iload 6
    //   280: iload 7
    //   282: iload 8
    //   284: iload 12
    //   286: iload 10
    //   288: iload 9
    //   290: iload 13
    //   292: iload 14
    //   294: fload 11
    //   296: aload_0
    //   297: invokespecial 128	F0/d:<init>	(Ljava/util/List;IIIIIIIIIFLjava/lang/String;)V
    //   300: areturn
    //   301: new 130	java/lang/IllegalStateException
    //   304: astore_0
    //   305: aload_0
    //   306: invokespecial 131	java/lang/IllegalStateException:<init>	()V
    //   309: aload_0
    //   310: athrow
    //   311: ldc -123
    //   313: aload_0
    //   314: invokestatic 138	d0/A:a	(Ljava/lang/String;Ljava/lang/Throwable;)Ld0/A;
    //   317: athrow
    // Local variable table:
    //   start	length	slot	name	signature
    //   0	318	0	paramz	z
    //   13	265	1	m	int
    //   22	255	2	localArrayList	java.util.ArrayList
    //   34	232	3	n	int
    //   36	233	4	i1	int
    //   69	193	5	i2	int
    //   134	145	6	i3	int
    //   140	141	7	i4	int
    //   146	137	8	i5	int
    //   152	137	9	i6	int
    //   158	129	10	i7	int
    //   181	114	11	f1	float
    //   204	81	12	i8	int
    //   214	77	13	i9	int
    //   218	75	14	i10	int
    // Exception table:
    //   from	to	target	type
    //   0	14	61	java/lang/ArrayIndexOutOfBoundsException
    //   19	35	61	java/lang/ArrayIndexOutOfBoundsException
    //   44	55	61	java/lang/ArrayIndexOutOfBoundsException
    //   65	71	61	java/lang/ArrayIndexOutOfBoundsException
    //   81	92	61	java/lang/ArrayIndexOutOfBoundsException
    //   102	199	61	java/lang/ArrayIndexOutOfBoundsException
    //   272	301	61	java/lang/ArrayIndexOutOfBoundsException
    //   301	311	61	java/lang/ArrayIndexOutOfBoundsException
  }
}

/* Location:
 * Qualified Name:     F0.d
 * Java Class Version: 6 (50.0)
 * JD-Core Version:    0.7.1
 */