package com.google.android.gms.internal.firebase_auth_api;

public class zzady
{
  /* Error */
  public static Object zza(String paramString, java.lang.reflect.Type paramType)
  {
    // Byte code:
    //   0: aload_1
    //   1: ldc 15
    //   3: if_acmpne +81 -> 84
    //   6: new 17	com/google/android/gms/internal/firebase_auth_api/zzafu
    //   9: astore_1
    //   10: aload_1
    //   11: invokespecial 18	com/google/android/gms/internal/firebase_auth_api/zzafu:<init>	()V
    //   14: aload_1
    //   15: aload_0
    //   16: invokevirtual 21	com/google/android/gms/internal/firebase_auth_api/zzafu:zza	(Ljava/lang/String;)Lcom/google/android/gms/internal/firebase-auth-api/zzaea;
    //   19: checkcast 17	com/google/android/gms/internal/firebase_auth_api/zzafu
    //   22: astore_1
    //   23: aload_1
    //   24: invokevirtual 25	com/google/android/gms/internal/firebase_auth_api/zzafu:zzb	()Z
    //   27: ifeq +8 -> 35
    //   30: aload_1
    //   31: invokevirtual 28	com/google/android/gms/internal/firebase_auth_api/zzafu:zza	()Ljava/lang/String;
    //   34: areturn
    //   35: new 30	com/google/android/gms/internal/firebase_auth_api/zzabr
    //   38: astore_1
    //   39: new 32	java/lang/StringBuilder
    //   42: astore_2
    //   43: aload_2
    //   44: ldc 34
    //   46: invokespecial 37	java/lang/StringBuilder:<init>	(Ljava/lang/String;)V
    //   49: aload_2
    //   50: aload_0
    //   51: invokevirtual 41	java/lang/StringBuilder:append	(Ljava/lang/String;)Ljava/lang/StringBuilder;
    //   54: pop
    //   55: aload_1
    //   56: aload_2
    //   57: invokevirtual 44	java/lang/StringBuilder:toString	()Ljava/lang/String;
    //   60: invokespecial 45	com/google/android/gms/internal/firebase_auth_api/zzabr:<init>	(Ljava/lang/String;)V
    //   63: aload_1
    //   64: athrow
    //   65: astore_0
    //   66: new 30	com/google/android/gms/internal/firebase_auth_api/zzabr
    //   69: dup
    //   70: ldc 47
    //   72: aload_0
    //   73: invokevirtual 52	java/lang/Throwable:getMessage	()Ljava/lang/String;
    //   76: invokestatic 58	f:j	(Ljava/lang/String;Ljava/lang/String;)Ljava/lang/String;
    //   79: aload_0
    //   80: invokespecial 61	com/google/android/gms/internal/firebase_auth_api/zzabr:<init>	(Ljava/lang/String;Ljava/lang/Throwable;)V
    //   83: athrow
    //   84: aload_1
    //   85: ldc 63
    //   87: if_acmpne +5 -> 92
    //   90: aconst_null
    //   91: areturn
    //   92: aload_1
    //   93: checkcast 65	java/lang/Class
    //   96: iconst_0
    //   97: anewarray 65	java/lang/Class
    //   100: invokevirtual 69	java/lang/Class:getConstructor	([Ljava/lang/Class;)Ljava/lang/reflect/Constructor;
    //   103: iconst_0
    //   104: anewarray 4	java/lang/Object
    //   107: invokevirtual 75	java/lang/reflect/Constructor:newInstance	([Ljava/lang/Object;)Ljava/lang/Object;
    //   110: checkcast 77	com/google/android/gms/internal/firebase_auth_api/zzaea
    //   113: astore_2
    //   114: aload_2
    //   115: aload_0
    //   116: invokeinterface 78 2 0
    //   121: astore_0
    //   122: aload_0
    //   123: areturn
    //   124: astore_0
    //   125: new 30	com/google/android/gms/internal/firebase_auth_api/zzabr
    //   128: dup
    //   129: ldc 47
    //   131: aload_0
    //   132: invokevirtual 52	java/lang/Throwable:getMessage	()Ljava/lang/String;
    //   135: invokestatic 58	f:j	(Ljava/lang/String;Ljava/lang/String;)Ljava/lang/String;
    //   138: aload_0
    //   139: invokespecial 61	com/google/android/gms/internal/firebase_auth_api/zzabr:<init>	(Ljava/lang/String;Ljava/lang/Throwable;)V
    //   142: athrow
    //   143: astore_0
    //   144: new 30	com/google/android/gms/internal/firebase_auth_api/zzabr
    //   147: dup
    //   148: ldc 80
    //   150: aload_1
    //   151: invokestatic 84	java/lang/String:valueOf	(Ljava/lang/Object;)Ljava/lang/String;
    //   154: invokestatic 58	f:j	(Ljava/lang/String;Ljava/lang/String;)Ljava/lang/String;
    //   157: aload_0
    //   158: invokespecial 61	com/google/android/gms/internal/firebase_auth_api/zzabr:<init>	(Ljava/lang/String;Ljava/lang/Throwable;)V
    //   161: athrow
    // Local variable table:
    //   start	length	slot	name	signature
    //   0	162	0	paramString	String
    //   0	162	1	paramType	java.lang.reflect.Type
    //   42	73	2	localObject	Object
    // Exception table:
    //   from	to	target	type
    //   6	35	65	java/lang/Exception
    //   35	65	65	java/lang/Exception
    //   114	122	124	java/lang/Exception
    //   92	114	143	java/lang/Exception
  }
}

/* Location:
 * Qualified Name:     com.google.android.gms.internal.firebase_auth_api.zzady
 * Java Class Version: 6 (50.0)
 * JD-Core Version:    0.7.1
 */