package y6;

public final class b
{
  public static ClassLoader a;
  public static Thread b;
  
  /* Error */
  public static ClassLoader a()
  {
    // Byte code:
    //   0: ldc 2
    //   2: monitorenter
    //   3: getstatic 13	y6/b:a	Ljava/lang/ClassLoader;
    //   6: ifnonnull +370 -> 376
    //   9: getstatic 15	y6/b:b	Ljava/lang/Thread;
    //   12: astore_0
    //   13: aconst_null
    //   14: astore_1
    //   15: aconst_null
    //   16: astore_2
    //   17: aload_0
    //   18: astore_3
    //   19: aload_0
    //   20: ifnonnull +286 -> 306
    //   23: invokestatic 21	android/os/Looper:getMainLooper	()Landroid/os/Looper;
    //   26: invokevirtual 25	android/os/Looper:getThread	()Ljava/lang/Thread;
    //   29: invokevirtual 31	java/lang/Thread:getThreadGroup	()Ljava/lang/ThreadGroup;
    //   32: astore_3
    //   33: aload_3
    //   34: ifnonnull +8 -> 42
    //   37: aconst_null
    //   38: astore_0
    //   39: goto +247 -> 286
    //   42: ldc 33
    //   44: monitorenter
    //   45: aload_3
    //   46: invokevirtual 39	java/lang/ThreadGroup:activeGroupCount	()I
    //   49: istore 4
    //   51: iload 4
    //   53: anewarray 35	java/lang/ThreadGroup
    //   56: astore 5
    //   58: aload_3
    //   59: aload 5
    //   61: invokevirtual 43	java/lang/ThreadGroup:enumerate	([Ljava/lang/ThreadGroup;)I
    //   64: pop
    //   65: iconst_0
    //   66: istore 6
    //   68: iconst_0
    //   69: istore 7
    //   71: iload 7
    //   73: iload 4
    //   75: if_icmpge +30 -> 105
    //   78: aload 5
    //   80: iload 7
    //   82: aaload
    //   83: astore_0
    //   84: ldc 45
    //   86: aload_0
    //   87: invokevirtual 49	java/lang/ThreadGroup:getName	()Ljava/lang/String;
    //   90: invokevirtual 55	java/lang/String:equals	(Ljava/lang/Object;)Z
    //   93: ifeq +6 -> 99
    //   96: goto +11 -> 107
    //   99: iinc 7 1
    //   102: goto -31 -> 71
    //   105: aconst_null
    //   106: astore_0
    //   107: aload_0
    //   108: astore 5
    //   110: aload_0
    //   111: ifnonnull +16 -> 127
    //   114: new 35	java/lang/ThreadGroup
    //   117: astore 5
    //   119: aload 5
    //   121: aload_3
    //   122: ldc 45
    //   124: invokespecial 59	java/lang/ThreadGroup:<init>	(Ljava/lang/ThreadGroup;Ljava/lang/String;)V
    //   127: aload 5
    //   129: invokevirtual 62	java/lang/ThreadGroup:activeCount	()I
    //   132: istore 4
    //   134: iload 4
    //   136: anewarray 27	java/lang/Thread
    //   139: astore_3
    //   140: aload 5
    //   142: aload_3
    //   143: invokevirtual 65	java/lang/ThreadGroup:enumerate	([Ljava/lang/Thread;)I
    //   146: pop
    //   147: iload 6
    //   149: istore 7
    //   151: iload 7
    //   153: iload 4
    //   155: if_icmpge +33 -> 188
    //   158: aload_3
    //   159: iload 7
    //   161: aaload
    //   162: astore_0
    //   163: ldc 67
    //   165: aload_0
    //   166: invokevirtual 68	java/lang/Thread:getName	()Ljava/lang/String;
    //   169: invokevirtual 55	java/lang/String:equals	(Ljava/lang/Object;)Z
    //   172: istore 8
    //   174: iload 8
    //   176: ifeq +6 -> 182
    //   179: goto +11 -> 190
    //   182: iinc 7 1
    //   185: goto -34 -> 151
    //   188: aconst_null
    //   189: astore_0
    //   190: aload_0
    //   191: astore_3
    //   192: aload_0
    //   193: ifnonnull +88 -> 281
    //   196: new 70	y6/a
    //   199: astore_3
    //   200: aload_3
    //   201: aload 5
    //   203: invokespecial 73	y6/a:<init>	(Ljava/lang/ThreadGroup;)V
    //   206: aload_3
    //   207: aconst_null
    //   208: invokevirtual 77	java/lang/Thread:setContextClassLoader	(Ljava/lang/ClassLoader;)V
    //   211: aload_3
    //   212: invokevirtual 81	java/lang/Thread:start	()V
    //   215: goto +66 -> 281
    //   218: astore_0
    //   219: aload_3
    //   220: astore 5
    //   222: aload_0
    //   223: astore_3
    //   224: aload 5
    //   226: astore_0
    //   227: goto +14 -> 241
    //   230: astore_3
    //   231: goto +10 -> 241
    //   234: astore_0
    //   235: goto +66 -> 301
    //   238: astore_3
    //   239: aconst_null
    //   240: astore_0
    //   241: aload_3
    //   242: invokevirtual 86	java/lang/Throwable:getMessage	()Ljava/lang/String;
    //   245: astore 5
    //   247: new 88	java/lang/StringBuilder
    //   250: astore_3
    //   251: aload_3
    //   252: invokespecial 90	java/lang/StringBuilder:<init>	()V
    //   255: aload_3
    //   256: ldc 92
    //   258: invokevirtual 96	java/lang/StringBuilder:append	(Ljava/lang/String;)Ljava/lang/StringBuilder;
    //   261: pop
    //   262: aload_3
    //   263: aload 5
    //   265: invokevirtual 96	java/lang/StringBuilder:append	(Ljava/lang/String;)Ljava/lang/StringBuilder;
    //   268: pop
    //   269: ldc 98
    //   271: aload_3
    //   272: invokevirtual 101	java/lang/StringBuilder:toString	()Ljava/lang/String;
    //   275: invokestatic 107	android/util/Log:w	(Ljava/lang/String;Ljava/lang/String;)I
    //   278: pop
    //   279: aload_0
    //   280: astore_3
    //   281: ldc 33
    //   283: monitorexit
    //   284: aload_3
    //   285: astore_0
    //   286: aload_0
    //   287: putstatic 15	y6/b:b	Ljava/lang/Thread;
    //   290: aload_0
    //   291: astore_3
    //   292: aload_0
    //   293: ifnonnull +13 -> 306
    //   296: aload_1
    //   297: astore_0
    //   298: goto +67 -> 365
    //   301: ldc 33
    //   303: monitorexit
    //   304: aload_0
    //   305: athrow
    //   306: aload_3
    //   307: monitorenter
    //   308: getstatic 15	y6/b:b	Ljava/lang/Thread;
    //   311: invokevirtual 110	java/lang/Thread:getContextClassLoader	()Ljava/lang/ClassLoader;
    //   314: astore_0
    //   315: goto +48 -> 363
    //   318: astore_0
    //   319: goto +53 -> 372
    //   322: astore_0
    //   323: aload_0
    //   324: invokevirtual 86	java/lang/Throwable:getMessage	()Ljava/lang/String;
    //   327: astore 5
    //   329: new 88	java/lang/StringBuilder
    //   332: astore_0
    //   333: aload_0
    //   334: invokespecial 90	java/lang/StringBuilder:<init>	()V
    //   337: aload_0
    //   338: ldc 112
    //   340: invokevirtual 96	java/lang/StringBuilder:append	(Ljava/lang/String;)Ljava/lang/StringBuilder;
    //   343: pop
    //   344: aload_0
    //   345: aload 5
    //   347: invokevirtual 96	java/lang/StringBuilder:append	(Ljava/lang/String;)Ljava/lang/StringBuilder;
    //   350: pop
    //   351: ldc 98
    //   353: aload_0
    //   354: invokevirtual 101	java/lang/StringBuilder:toString	()Ljava/lang/String;
    //   357: invokestatic 107	android/util/Log:w	(Ljava/lang/String;Ljava/lang/String;)I
    //   360: pop
    //   361: aload_2
    //   362: astore_0
    //   363: aload_3
    //   364: monitorexit
    //   365: aload_0
    //   366: putstatic 13	y6/b:a	Ljava/lang/ClassLoader;
    //   369: goto +7 -> 376
    //   372: aload_3
    //   373: monitorexit
    //   374: aload_0
    //   375: athrow
    //   376: getstatic 13	y6/b:a	Ljava/lang/ClassLoader;
    //   379: astore_0
    //   380: ldc 2
    //   382: monitorexit
    //   383: aload_0
    //   384: areturn
    //   385: astore_0
    //   386: ldc 2
    //   388: monitorexit
    //   389: aload_0
    //   390: athrow
    // Local variable table:
    //   start	length	slot	name	signature
    //   12	181	0	localThread	Thread
    //   218	5	0	localSecurityException1	SecurityException
    //   226	1	0	localObject1	Object
    //   234	1	0	localObject2	Object
    //   240	75	0	localObject3	Object
    //   318	1	0	localObject4	Object
    //   322	2	0	localSecurityException2	SecurityException
    //   332	52	0	localObject5	Object
    //   385	5	0	localObject6	Object
    //   14	283	1	localObject7	Object
    //   16	346	2	localObject8	Object
    //   18	206	3	localObject9	Object
    //   230	1	3	localSecurityException3	SecurityException
    //   238	4	3	localSecurityException4	SecurityException
    //   250	123	3	localObject10	Object
    //   49	107	4	i	int
    //   56	290	5	localObject11	Object
    //   66	82	6	j	int
    //   69	114	7	k	int
    //   172	3	8	bool	boolean
    // Exception table:
    //   from	to	target	type
    //   206	215	218	java/lang/SecurityException
    //   196	206	230	java/lang/SecurityException
    //   45	65	234	finally
    //   84	96	234	finally
    //   114	127	234	finally
    //   127	147	234	finally
    //   163	174	234	finally
    //   196	206	234	finally
    //   206	215	234	finally
    //   241	279	234	finally
    //   281	284	234	finally
    //   301	304	234	finally
    //   45	65	238	java/lang/SecurityException
    //   84	96	238	java/lang/SecurityException
    //   114	127	238	java/lang/SecurityException
    //   127	147	238	java/lang/SecurityException
    //   163	174	238	java/lang/SecurityException
    //   308	315	318	finally
    //   323	361	318	finally
    //   363	365	318	finally
    //   372	374	318	finally
    //   308	315	322	java/lang/SecurityException
    //   3	13	385	finally
    //   23	33	385	finally
    //   42	45	385	finally
    //   286	290	385	finally
    //   304	306	385	finally
    //   306	308	385	finally
    //   365	369	385	finally
    //   374	376	385	finally
    //   376	380	385	finally
  }
}

/* Location:
 * Qualified Name:     y6.b
 * Java Class Version: 6 (50.0)
 * JD-Core Version:    0.7.1
 */