package E1;

import T1.a;
import android.content.Context;
import android.content.SharedPreferences;
import android.content.SharedPreferences.Editor;
import android.os.BaseBundle;
import android.os.Bundle;
import android.os.IBinder;
import java.lang.reflect.Method;
import java.util.ArrayList;
import java.util.Arrays;
import java.util.Collection;
import java.util.HashMap;
import java.util.Iterator;
import java.util.LinkedHashMap;
import java.util.List;
import java.util.Map;
import java.util.Map.Entry;
import java.util.Set;
import kotlin.jvm.internal.Intrinsics;
import org.json.JSONException;
import org.json.JSONObject;
import x1.B;

public final class i
{
  public static final i a = new i();
  public static final HashMap b = new HashMap();
  public static final HashMap c = new HashMap();
  public static final String d = B.l().getPackageName();
  public static final SharedPreferences e = B.l().getSharedPreferences("com.facebook.internal.SKU_DETAILS", 0);
  public static final SharedPreferences f = B.l().getSharedPreferences("com.facebook.internal.PURCHASE", 0);
  
  public static final Object a(Context paramContext, IBinder paramIBinder)
  {
    if (a.d(i.class)) {
      return null;
    }
    try
    {
      Intrinsics.checkNotNullParameter(paramContext, "context");
      paramContext = a.n(paramContext, "com.android.vending.billing.IInAppBillingService$Stub", "asInterface", null, new Object[] { paramIBinder });
      return paramContext;
    }
    finally
    {
      a.b(paramContext, i.class);
    }
    return null;
  }
  
  public static final void b()
  {
    if (a.d(i.class)) {
      return;
    }
    SharedPreferences.Editor localEditor;
    for (;;)
    {
      long l1;
      long l2;
      try
      {
        l1 = System.currentTimeMillis() / 1000L;
        Object localObject1 = e;
        l2 = ((SharedPreferences)localObject1).getLong("LAST_CLEARED_TIME", 0L);
        if (l2 == 0L)
        {
          localObject1 = ((SharedPreferences)localObject1).edit().putLong("LAST_CLEARED_TIME", l1);
          ((SharedPreferences.Editor)localObject1).apply();
        }
      }
      finally
      {
        break label99;
      }
      if (l1 - l2 <= 604800) {
        break;
      }
      localEditor = ((SharedPreferences)localObject2).edit().clear().putLong("LAST_CLEARED_TIME", l1);
    }
    return;
    label99:
    a.b(localEditor, i.class);
  }
  
  public static final ArrayList g(Context paramContext, Object paramObject)
  {
    if (a.d(i.class)) {
      return null;
    }
    try
    {
      Intrinsics.checkNotNullParameter(paramContext, "context");
      ArrayList localArrayList = new java/util/ArrayList;
      localArrayList.<init>();
      if (paramObject == null) {
        return localArrayList;
      }
      i locali = a;
      Class localClass = locali.d(paramContext, "com.android.vending.billing.IInAppBillingService");
      if (localClass == null) {
        return localArrayList;
      }
      if (locali.e(localClass, "getPurchaseHistory") == null) {
        return localArrayList;
      }
      paramContext = locali.c(locali.f(paramContext, paramObject, "inapp"));
      return paramContext;
    }
    finally
    {
      a.b(paramContext, i.class);
    }
    return null;
  }
  
  public static final ArrayList i(Context paramContext, Object paramObject)
  {
    if (a.d(i.class)) {
      return null;
    }
    try
    {
      Intrinsics.checkNotNullParameter(paramContext, "context");
      i locali = a;
      paramContext = locali.c(locali.h(paramContext, paramObject, "inapp"));
      return paramContext;
    }
    finally
    {
      a.b(paramContext, i.class);
    }
    return null;
  }
  
  public static final ArrayList j(Context paramContext, Object paramObject)
  {
    if (a.d(i.class)) {
      return null;
    }
    try
    {
      Intrinsics.checkNotNullParameter(paramContext, "context");
      i locali = a;
      paramContext = locali.c(locali.h(paramContext, paramObject, "subs"));
      return paramContext;
    }
    finally
    {
      a.b(paramContext, i.class);
    }
    return null;
  }
  
  public static final Map k(Context paramContext, ArrayList paramArrayList, Object paramObject, boolean paramBoolean)
  {
    if (a.d(i.class)) {
      return null;
    }
    try
    {
      Intrinsics.checkNotNullParameter(paramContext, "context");
      Intrinsics.checkNotNullParameter(paramArrayList, "skuList");
      Map localMap = a.p(paramArrayList);
      ArrayList localArrayList = new java/util/ArrayList;
      localArrayList.<init>();
      Iterator localIterator = paramArrayList.iterator();
      while (localIterator.hasNext())
      {
        paramArrayList = (String)localIterator.next();
        if (!localMap.containsKey(paramArrayList)) {
          localArrayList.add(paramArrayList);
        }
      }
      label114:
      return null;
    }
    finally
    {
      break label114;
      localMap.putAll(a.l(paramContext, localArrayList, paramObject, paramBoolean));
      return localMap;
      a.b(paramContext, i.class);
    }
  }
  
  public final ArrayList c(ArrayList paramArrayList)
  {
    if (a.d(this)) {
      return null;
    }
    for (;;)
    {
      try
      {
        localArrayList = new java/util/ArrayList;
        localArrayList.<init>();
        localEditor = f.edit();
        l1 = System.currentTimeMillis() / 1000L;
        paramArrayList = paramArrayList.iterator();
        if (paramArrayList.hasNext()) {
          str1 = (String)paramArrayList.next();
        }
      }
      finally
      {
        ArrayList localArrayList;
        SharedPreferences.Editor localEditor;
        try
        {
          long l1;
          String str1;
          Object localObject = new org/json/JSONObject;
          ((JSONObject)localObject).<init>(str1);
          String str2 = ((JSONObject)localObject).getString("productId");
          long l2 = ((JSONObject)localObject).getLong("purchaseTime");
          localObject = ((JSONObject)localObject).getString("purchaseToken");
          if ((l1 - l2 / 1000L > 86400L) || (Intrinsics.a(f.getString(str2, ""), localObject))) {
            continue;
          }
          localEditor.putString(str2, (String)localObject);
          localArrayList.add(str1);
        }
        catch (JSONException localJSONException) {}
        paramArrayList = finally;
        continue;
        localEditor.apply();
        return localArrayList;
        a.b(paramArrayList, this);
        return null;
      }
    }
  }
  
  public final Class d(Context paramContext, String paramString)
  {
    if (a.d(this)) {
      return null;
    }
    try
    {
      HashMap localHashMap = c;
      Class localClass = (Class)localHashMap.get(paramString);
      if (localClass != null) {
        return localClass;
      }
      paramContext = m.b(paramContext, paramString);
      if (paramContext != null) {
        localHashMap.put(paramString, paramContext);
      }
    }
    finally
    {
      break label59;
    }
    return paramContext;
    label59:
    a.b(paramContext, this);
    return null;
  }
  
  public final Method e(Class paramClass, String paramString)
  {
    if (a.d(this)) {
      return null;
    }
    HashMap localHashMap;
    try
    {
      localHashMap = b;
      localObject1 = (Method)localHashMap.get(paramString);
      if (localObject1 != null) {
        return (Method)localObject1;
      }
      int i = paramString.hashCode();
      switch (i)
      {
      }
    }
    finally
    {
      break label411;
    }
    if (paramString.equals("getSkuDetails"))
    {
      localObject1 = new Class[4];
      localObject2 = Integer.TYPE;
      Intrinsics.checkNotNullExpressionValue(localObject2, "TYPE");
      localObject1[0] = localObject2;
      localObject1[1] = String.class;
      localObject1[2] = String.class;
      localObject1[3] = Bundle.class;
      break label352;
      if (paramString.equals("getPurchaseHistory"))
      {
        localObject1 = new Class[5];
        localObject2 = Integer.TYPE;
        Intrinsics.checkNotNullExpressionValue(localObject2, "TYPE");
        localObject1[0] = localObject2;
        localObject1[1] = String.class;
        localObject1[2] = String.class;
        localObject1[3] = String.class;
        localObject1[4] = Bundle.class;
        break label352;
        if (paramString.equals("asInterface"))
        {
          localObject1 = new Class[1];
          localObject1[0] = IBinder.class;
          break label352;
          if (paramString.equals("isBillingSupported"))
          {
            localObject1 = new Class[3];
            localObject2 = Integer.TYPE;
            Intrinsics.checkNotNullExpressionValue(localObject2, "TYPE");
            localObject1[0] = localObject2;
            localObject1[1] = String.class;
            localObject1[2] = String.class;
            break label352;
            if (paramString.equals("getPurchases")) {
              break label310;
            }
          }
        }
      }
    }
    Object localObject1 = null;
    break label352;
    label310:
    localObject1 = new Class[4];
    Object localObject2 = Integer.TYPE;
    Intrinsics.checkNotNullExpressionValue(localObject2, "TYPE");
    localObject1[0] = localObject2;
    localObject1[1] = String.class;
    localObject1[2] = String.class;
    localObject1[3] = String.class;
    label352:
    if (localObject1 == null)
    {
      paramClass = m.c(paramClass, paramString, new Class[] { null });
    }
    else
    {
      localObject2 = m.a;
      paramClass = m.c(paramClass, paramString, (Class[])Arrays.copyOf((Object[])localObject1, localObject1.length));
    }
    if (paramClass != null) {
      localHashMap.put(paramString, paramClass);
    }
    return paramClass;
    label411:
    a.b(paramClass, this);
    return null;
  }
  
  /* Error */
  public final ArrayList f(Context paramContext, Object paramObject, String paramString)
  {
    // Byte code:
    //   0: aload_0
    //   1: invokestatic 62	T1/a:d	(Ljava/lang/Object;)Z
    //   4: ifeq +5 -> 9
    //   7: aconst_null
    //   8: areturn
    //   9: new 118	java/util/ArrayList
    //   12: astore 4
    //   14: aload 4
    //   16: invokespecial 119	java/util/ArrayList:<init>	()V
    //   19: aload_0
    //   20: aload_1
    //   21: aload_2
    //   22: aload_3
    //   23: invokevirtual 277	E1/i:o	(Landroid/content/Context;Ljava/lang/Object;Ljava/lang/String;)Z
    //   26: ifeq +252 -> 278
    //   29: aconst_null
    //   30: astore 5
    //   32: iconst_0
    //   33: istore 6
    //   35: iload 6
    //   37: istore 7
    //   39: getstatic 42	E1/i:d	Ljava/lang/String;
    //   42: astore 8
    //   44: new 253	android/os/Bundle
    //   47: astore 9
    //   49: aload 9
    //   51: invokespecial 278	android/os/Bundle:<init>	()V
    //   54: aload_0
    //   55: aload_1
    //   56: ldc 121
    //   58: ldc 126
    //   60: aload_2
    //   61: iconst_5
    //   62: anewarray 4	java/lang/Object
    //   65: dup
    //   66: iconst_0
    //   67: bipush 6
    //   69: invokestatic 282	java/lang/Integer:valueOf	(I)Ljava/lang/Integer;
    //   72: aastore
    //   73: dup
    //   74: iconst_1
    //   75: aload 8
    //   77: aastore
    //   78: dup
    //   79: iconst_2
    //   80: aload_3
    //   81: aastore
    //   82: dup
    //   83: iconst_3
    //   84: aload 5
    //   86: aastore
    //   87: dup
    //   88: iconst_4
    //   89: aload 9
    //   91: aastore
    //   92: invokevirtual 78	E1/i:n	(Landroid/content/Context;Ljava/lang/String;Ljava/lang/String;Ljava/lang/Object;[Ljava/lang/Object;)Ljava/lang/Object;
    //   95: astore 5
    //   97: aload 5
    //   99: ifnull +151 -> 250
    //   102: invokestatic 87	java/lang/System:currentTimeMillis	()J
    //   105: ldc2_w 88
    //   108: ldiv
    //   109: lstore 10
    //   111: aload 5
    //   113: checkcast 253	android/os/Bundle
    //   116: astore 5
    //   118: aload 5
    //   120: ldc_w 284
    //   123: invokevirtual 290	android/os/BaseBundle:getInt	(Ljava/lang/String;)I
    //   126: ifne +124 -> 250
    //   129: aload 5
    //   131: ldc_w 292
    //   134: invokevirtual 296	android/os/Bundle:getStringArrayList	(Ljava/lang/String;)Ljava/util/ArrayList;
    //   137: astore 8
    //   139: aload 8
    //   141: ifnonnull +6 -> 147
    //   144: goto +106 -> 250
    //   147: aload 8
    //   149: invokevirtual 156	java/util/ArrayList:iterator	()Ljava/util/Iterator;
    //   152: astore 8
    //   154: iload 7
    //   156: istore 12
    //   158: aload 8
    //   160: invokeinterface 162 1 0
    //   165: ifeq +72 -> 237
    //   168: aload 8
    //   170: invokeinterface 166 1 0
    //   175: checkcast 168	java/lang/String
    //   178: astore 13
    //   180: new 186	org/json/JSONObject
    //   183: astore 9
    //   185: aload 9
    //   187: aload 13
    //   189: invokespecial 189	org/json/JSONObject:<init>	(Ljava/lang/String;)V
    //   192: lload 10
    //   194: aload 9
    //   196: ldc -59
    //   198: invokevirtual 200	org/json/JSONObject:getLong	(Ljava/lang/String;)J
    //   201: ldc2_w 88
    //   204: ldiv
    //   205: lsub
    //   206: ldc2_w 297
    //   209: lcmp
    //   210: ifle +9 -> 219
    //   213: iconst_1
    //   214: istore 12
    //   216: goto +21 -> 237
    //   219: aload 4
    //   221: aload 13
    //   223: invokevirtual 176	java/util/ArrayList:add	(Ljava/lang/Object;)Z
    //   226: pop
    //   227: iinc 6 1
    //   230: goto -76 -> 154
    //   233: astore_1
    //   234: goto +47 -> 281
    //   237: aload 5
    //   239: ldc_w 300
    //   242: invokevirtual 301	android/os/BaseBundle:getString	(Ljava/lang/String;)Ljava/lang/String;
    //   245: astore 5
    //   247: goto +10 -> 257
    //   250: aconst_null
    //   251: astore 5
    //   253: iload 7
    //   255: istore 12
    //   257: iload 6
    //   259: bipush 30
    //   261: if_icmpge +17 -> 278
    //   264: aload 5
    //   266: ifnull +12 -> 278
    //   269: iload 12
    //   271: istore 7
    //   273: iload 12
    //   275: ifeq -236 -> 39
    //   278: aload 4
    //   280: areturn
    //   281: aload_1
    //   282: aload_0
    //   283: invokestatic 81	T1/a:b	(Ljava/lang/Throwable;Ljava/lang/Object;)V
    //   286: aconst_null
    //   287: areturn
    //   288: astore 9
    //   290: goto -136 -> 154
    // Local variable table:
    //   start	length	slot	name	signature
    //   0	293	0	this	i
    //   0	293	1	paramContext	Context
    //   0	293	2	paramObject	Object
    //   0	293	3	paramString	String
    //   12	267	4	localArrayList	ArrayList
    //   30	235	5	localObject1	Object
    //   33	229	6	i	int
    //   37	235	7	j	int
    //   42	127	8	localObject2	Object
    //   47	148	9	localObject3	Object
    //   288	1	9	localJSONException	JSONException
    //   109	84	10	l	long
    //   156	118	12	k	int
    //   178	44	13	str	String
    // Exception table:
    //   from	to	target	type
    //   9	29	233	finally
    //   39	97	233	finally
    //   102	139	233	finally
    //   147	154	233	finally
    //   158	180	233	finally
    //   180	213	233	finally
    //   219	227	233	finally
    //   237	247	233	finally
    //   180	213	288	org/json/JSONException
    //   219	227	288	org/json/JSONException
  }
  
  public final ArrayList h(Context paramContext, Object paramObject, String paramString)
  {
    if (a.d(this)) {
      return null;
    }
    ArrayList localArrayList;
    Object localObject2;
    do
    {
      int i;
      try
      {
        localArrayList = new java/util/ArrayList;
        localArrayList.<init>();
        if (paramObject == null) {
          return localArrayList;
        }
        if (!o(paramContext, paramObject, paramString)) {
          break;
        }
        localObject1 = null;
        i = 0;
        localObject2 = n(paramContext, "com.android.vending.billing.IInAppBillingService", "getPurchases", paramObject, new Object[] { Integer.valueOf(3), d, paramString, localObject1 });
        if (localObject2 != null)
        {
          localObject2 = (Bundle)localObject2;
          if (((BaseBundle)localObject2).getInt("RESPONSE_CODE") == 0)
          {
            localObject1 = ((Bundle)localObject2).getStringArrayList("INAPP_PURCHASE_DATA_LIST");
            if (localObject1 == null) {
              break;
            }
            i += ((ArrayList)localObject1).size();
            localArrayList.addAll((Collection)localObject1);
            localObject2 = ((BaseBundle)localObject2).getString("INAPP_CONTINUATION_TOKEN");
          }
        }
      }
      finally
      {
        break label176;
      }
      localObject2 = null;
      if (i >= 30) {
        break;
      }
      Object localObject1 = localObject2;
    } while (localObject2 != null);
    return localArrayList;
    label176:
    a.b(paramContext, this);
    return null;
  }
  
  public final Map l(Context paramContext, ArrayList paramArrayList, Object paramObject, boolean paramBoolean)
  {
    if (a.d(this)) {
      return null;
    }
    LinkedHashMap localLinkedHashMap;
    Bundle localBundle;
    int i;
    String str;
    try
    {
      localLinkedHashMap = new java/util/LinkedHashMap;
      localLinkedHashMap.<init>();
      if ((paramObject == null) || (paramArrayList.isEmpty())) {
        break label243;
      }
      localBundle = new android/os/Bundle;
      localBundle.<init>();
      localBundle.putStringArrayList("ITEM_ID_LIST", paramArrayList);
      i = 0;
      str = d;
      if (paramBoolean) {
        localObject = "subs";
      }
    }
    finally
    {
      break label246;
    }
    Object localObject = "inapp";
    paramContext = n(paramContext, "com.android.vending.billing.IInAppBillingService", "getSkuDetails", paramObject, new Object[] { Integer.valueOf(3), str, localObject, localBundle });
    if (paramContext != null)
    {
      paramContext = (Bundle)paramContext;
      if (paramContext.getInt("RESPONSE_CODE") == 0)
      {
        localObject = paramContext.getStringArrayList("DETAILS_LIST");
        if ((localObject != null) && (paramArrayList.size() == ((ArrayList)localObject).size()))
        {
          int j = paramArrayList.size() - 1;
          if (j >= 0) {
            for (;;)
            {
              int k = i + 1;
              paramObject = paramArrayList.get(i);
              Intrinsics.checkNotNullExpressionValue(paramObject, "skuList[i]");
              paramContext = ((ArrayList)localObject).get(i);
              Intrinsics.checkNotNullExpressionValue(paramContext, "skuDetailsList[i]");
              localLinkedHashMap.put(paramObject, paramContext);
              if (k > j) {
                break;
              }
              i = k;
            }
          }
        }
        q(localLinkedHashMap);
      }
    }
    label243:
    return localLinkedHashMap;
    label246:
    a.b(paramContext, this);
    return null;
  }
  
  /* Error */
  public final boolean m(String paramString)
  {
    // Byte code:
    //   0: aload_0
    //   1: invokestatic 62	T1/a:d	(Ljava/lang/Object;)Z
    //   4: istore_2
    //   5: iconst_0
    //   6: istore_3
    //   7: iload_2
    //   8: ifeq +5 -> 13
    //   11: iconst_0
    //   12: ireturn
    //   13: aload_1
    //   14: ldc_w 336
    //   17: invokestatic 70	kotlin/jvm/internal/Intrinsics:checkNotNullParameter	(Ljava/lang/Object;Ljava/lang/String;)V
    //   20: new 186	org/json/JSONObject
    //   23: astore 4
    //   25: aload 4
    //   27: aload_1
    //   28: invokespecial 189	org/json/JSONObject:<init>	(Ljava/lang/String;)V
    //   31: aload 4
    //   33: ldc_w 338
    //   36: invokevirtual 341	org/json/JSONObject:optString	(Ljava/lang/String;)Ljava/lang/String;
    //   39: astore_1
    //   40: iload_3
    //   41: istore_2
    //   42: aload_1
    //   43: ifnull +27 -> 70
    //   46: aload_1
    //   47: invokeinterface 346 1 0
    //   52: istore 5
    //   54: iload_3
    //   55: istore_2
    //   56: iload 5
    //   58: ifle +12 -> 70
    //   61: iconst_1
    //   62: istore_2
    //   63: goto +7 -> 70
    //   66: astore_1
    //   67: goto +5 -> 72
    //   70: iload_2
    //   71: ireturn
    //   72: aload_1
    //   73: aload_0
    //   74: invokestatic 81	T1/a:b	(Ljava/lang/Throwable;Ljava/lang/Object;)V
    //   77: iconst_0
    //   78: ireturn
    //   79: astore_1
    //   80: iload_3
    //   81: istore_2
    //   82: goto -12 -> 70
    // Local variable table:
    //   start	length	slot	name	signature
    //   0	85	0	this	i
    //   0	85	1	paramString	String
    //   4	78	2	bool1	boolean
    //   6	75	3	bool2	boolean
    //   23	9	4	localJSONObject	JSONObject
    //   52	5	5	i	int
    // Exception table:
    //   from	to	target	type
    //   13	20	66	finally
    //   20	40	66	finally
    //   46	54	66	finally
    //   20	40	79	org/json/JSONException
    //   46	54	79	org/json/JSONException
  }
  
  public final Object n(Context paramContext, String paramString1, String paramString2, Object paramObject, Object[] paramArrayOfObject)
  {
    if (a.d(this)) {
      return null;
    }
    try
    {
      paramContext = d(paramContext, paramString1);
      if (paramContext == null) {
        return null;
      }
      paramString2 = e(paramContext, paramString2);
      if (paramString2 == null) {
        return null;
      }
      paramString1 = m.a;
      paramContext = m.e(paramContext, paramString2, paramObject, Arrays.copyOf(paramArrayOfObject, paramArrayOfObject.length));
      return paramContext;
    }
    finally
    {
      a.b(paramContext, this);
    }
    return null;
  }
  
  public final boolean o(Context paramContext, Object paramObject, String paramString)
  {
    boolean bool1 = a.d(this);
    boolean bool2 = false;
    if (bool1) {
      return false;
    }
    if (paramObject == null) {
      return false;
    }
    try
    {
      paramContext = n(paramContext, "com.android.vending.billing.IInAppBillingService", "isBillingSupported", paramObject, new Object[] { Integer.valueOf(3), d, paramString });
      bool1 = bool2;
      if (paramContext != null)
      {
        int i = ((Integer)paramContext).intValue();
        bool1 = bool2;
        if (i == 0) {
          bool1 = true;
        }
      }
    }
    finally
    {
      break label94;
    }
    return bool1;
    label94:
    a.b(paramContext, this);
    return false;
  }
  
  public final Map p(ArrayList paramArrayList)
  {
    if (a.d(this)) {
      return null;
    }
    try
    {
      LinkedHashMap localLinkedHashMap = new java/util/LinkedHashMap;
      localLinkedHashMap.<init>();
      long l = System.currentTimeMillis() / 1000L;
      paramArrayList = paramArrayList.iterator();
      while (paramArrayList.hasNext())
      {
        String str = (String)paramArrayList.next();
        Object localObject = e.getString(str, null);
        if (localObject != null)
        {
          localObject = kotlin.text.i.V((CharSequence)localObject, new String[] { ";" }, false, 2, 2, null);
          if (l - Long.parseLong((String)((List)localObject).get(0)) < 43200L)
          {
            Intrinsics.checkNotNullExpressionValue(str, "sku");
            localLinkedHashMap.put(str, ((List)localObject).get(1));
          }
        }
      }
      label146:
      return null;
    }
    finally
    {
      break label146;
      return localLinkedHashMap;
      a.b(paramArrayList, this);
    }
  }
  
  public final void q(Map paramMap)
  {
    if (a.d(this)) {
      return;
    }
    try
    {
      long l = System.currentTimeMillis() / 1000L;
      SharedPreferences.Editor localEditor = e.edit();
      Iterator localIterator = paramMap.entrySet().iterator();
      while (localIterator.hasNext())
      {
        Object localObject = (Map.Entry)localIterator.next();
        paramMap = (String)((Map.Entry)localObject).getKey();
        localObject = (String)((Map.Entry)localObject).getValue();
        StringBuilder localStringBuilder = new java/lang/StringBuilder;
        localStringBuilder.<init>();
        localStringBuilder.append(l);
        localStringBuilder.append(';');
        localStringBuilder.append((String)localObject);
        localEditor.putString(paramMap, localStringBuilder.toString());
      }
      label146:
      return;
    }
    finally
    {
      break label146;
      localEditor.apply();
      return;
      a.b(paramMap, this);
    }
  }
}

/* Location:
 * Qualified Name:     E1.i
 * Java Class Version: 6 (50.0)
 * JD-Core Version:    0.7.1
 */