package u6;

public abstract class k
{
  public static final F a = new F("UNDEFINED");
  public static final F b = new F("REUSABLE_CLAIMED");
  
  /* Error */
  public static final void b(X5.d paramd, Object paramObject, g6.l paraml)
  {
    // Byte code:
    //   0: aload_0
    //   1: instanceof 28
    //   4: ifeq +299 -> 303
    //   7: aload_0
    //   8: checkcast 28	u6/j
    //   11: astore_3
    //   12: aload_1
    //   13: aload_2
    //   14: invokestatic 33	p6/D:b	(Ljava/lang/Object;Lg6/l;)Ljava/lang/Object;
    //   17: astore_0
    //   18: aload_3
    //   19: getfield 37	u6/j:r	Lp6/F;
    //   22: aload_3
    //   23: invokevirtual 41	u6/j:getContext	()LX5/g;
    //   26: invokevirtual 47	p6/F:F	(LX5/g;)Z
    //   29: ifeq +28 -> 57
    //   32: aload_3
    //   33: aload_0
    //   34: putfield 51	u6/j:t	Ljava/lang/Object;
    //   37: aload_3
    //   38: iconst_1
    //   39: putfield 57	p6/U:q	I
    //   42: aload_3
    //   43: getfield 37	u6/j:r	Lp6/F;
    //   46: aload_3
    //   47: invokevirtual 41	u6/j:getContext	()LX5/g;
    //   50: aload_3
    //   51: invokevirtual 61	p6/F:E	(LX5/g;Ljava/lang/Runnable;)V
    //   54: goto +256 -> 310
    //   57: getstatic 66	p6/L0:a	Lp6/L0;
    //   60: invokevirtual 69	p6/L0:b	()Lp6/a0;
    //   63: astore_2
    //   64: aload_2
    //   65: invokevirtual 75	p6/a0:O	()Z
    //   68: ifeq +21 -> 89
    //   71: aload_3
    //   72: aload_0
    //   73: putfield 51	u6/j:t	Ljava/lang/Object;
    //   76: aload_3
    //   77: iconst_1
    //   78: putfield 57	p6/U:q	I
    //   81: aload_2
    //   82: aload_3
    //   83: invokevirtual 79	p6/a0:K	(Lp6/U;)V
    //   86: goto +224 -> 310
    //   89: aload_2
    //   90: iconst_1
    //   91: invokevirtual 83	p6/a0:M	(Z)V
    //   94: aload_3
    //   95: invokevirtual 41	u6/j:getContext	()LX5/g;
    //   98: getstatic 89	p6/q0:n	Lp6/q0$b;
    //   101: invokeinterface 94 2 0
    //   106: checkcast 85	p6/q0
    //   109: astore 4
    //   111: aload 4
    //   113: ifnull +51 -> 164
    //   116: aload 4
    //   118: invokeinterface 96 1 0
    //   123: ifne +41 -> 164
    //   126: aload 4
    //   128: invokeinterface 100 1 0
    //   133: astore_1
    //   134: aload_3
    //   135: aload_0
    //   136: aload_1
    //   137: invokevirtual 103	u6/j:b	(Ljava/lang/Object;Ljava/lang/Throwable;)V
    //   140: getstatic 109	V5/n:o	LV5/n$a;
    //   143: astore_0
    //   144: aload_3
    //   145: aload_1
    //   146: invokestatic 114	V5/o:a	(Ljava/lang/Throwable;)Ljava/lang/Object;
    //   149: invokestatic 117	V5/n:a	(Ljava/lang/Object;)Ljava/lang/Object;
    //   152: invokeinterface 123 2 0
    //   157: goto +89 -> 246
    //   160: astore_0
    //   161: goto +125 -> 286
    //   164: aload_3
    //   165: getfield 126	u6/j:s	LX5/d;
    //   168: astore_0
    //   169: aload_3
    //   170: getfield 129	u6/j:u	Ljava/lang/Object;
    //   173: astore 5
    //   175: aload_0
    //   176: invokeinterface 130 1 0
    //   181: astore 4
    //   183: aload 4
    //   185: aload 5
    //   187: invokestatic 136	u6/J:c	(LX5/g;Ljava/lang/Object;)Ljava/lang/Object;
    //   190: astore 5
    //   192: aload 5
    //   194: getstatic 137	u6/J:a	Lu6/F;
    //   197: if_acmpeq +15 -> 212
    //   200: aload_0
    //   201: aload 4
    //   203: aload 5
    //   205: invokestatic 143	p6/E:g	(LX5/d;LX5/g;Ljava/lang/Object;)Lp6/N0;
    //   208: astore_0
    //   209: goto +5 -> 214
    //   212: aconst_null
    //   213: astore_0
    //   214: aload_3
    //   215: getfield 126	u6/j:s	LX5/d;
    //   218: aload_1
    //   219: invokeinterface 123 2 0
    //   224: getstatic 148	V5/t:a	LV5/t;
    //   227: astore_1
    //   228: aload_0
    //   229: ifnull +10 -> 239
    //   232: aload_0
    //   233: invokevirtual 153	p6/N0:K0	()Z
    //   236: ifeq +10 -> 246
    //   239: aload 4
    //   241: aload 5
    //   243: invokestatic 156	u6/J:a	(LX5/g;Ljava/lang/Object;)V
    //   246: aload_2
    //   247: invokevirtual 159	p6/a0:R	()Z
    //   250: istore 6
    //   252: iload 6
    //   254: ifne -8 -> 246
    //   257: aload_2
    //   258: iconst_1
    //   259: invokevirtual 162	p6/a0:H	(Z)V
    //   262: goto +48 -> 310
    //   265: astore_1
    //   266: aload_0
    //   267: ifnull +10 -> 277
    //   270: aload_0
    //   271: invokevirtual 153	p6/N0:K0	()Z
    //   274: ifeq +10 -> 284
    //   277: aload 4
    //   279: aload 5
    //   281: invokestatic 156	u6/J:a	(LX5/g;Ljava/lang/Object;)V
    //   284: aload_1
    //   285: athrow
    //   286: aload_3
    //   287: aload_0
    //   288: aconst_null
    //   289: invokevirtual 166	p6/U:h	(Ljava/lang/Throwable;Ljava/lang/Throwable;)V
    //   292: goto -35 -> 257
    //   295: astore_0
    //   296: aload_2
    //   297: iconst_1
    //   298: invokevirtual 162	p6/a0:H	(Z)V
    //   301: aload_0
    //   302: athrow
    //   303: aload_0
    //   304: aload_1
    //   305: invokeinterface 123 2 0
    //   310: return
    // Local variable table:
    //   start	length	slot	name	signature
    //   0	311	0	paramd	X5.d
    //   0	311	1	paramObject	Object
    //   0	311	2	paraml	g6.l
    //   11	276	3	localj	j
    //   109	169	4	localObject1	Object
    //   173	107	5	localObject2	Object
    //   250	3	6	bool	boolean
    // Exception table:
    //   from	to	target	type
    //   94	111	160	finally
    //   116	157	160	finally
    //   164	209	160	finally
    //   232	239	160	finally
    //   239	246	160	finally
    //   246	252	160	finally
    //   270	277	160	finally
    //   277	284	160	finally
    //   284	286	160	finally
    //   214	228	265	finally
    //   286	292	295	finally
  }
}

/* Location:
 * Qualified Name:     u6.k
 * Java Class Version: 6 (50.0)
 * JD-Core Version:    0.7.1
 */