package androidx.work;

public final class e
  implements Runnable
{
  public e(Worker paramWorker) {}
  
  /* Error */
  public final void run()
  {
    // Byte code:
    //   0: aload_0
    //   1: getfield 12	androidx/work/e:a	Landroidx/work/Worker;
    //   4: invokevirtual 23	androidx/work/Worker:j	()Landroidx/work/d$a;
    //   7: astore_1
    //   8: aload_0
    //   9: getfield 12	androidx/work/e:a	Landroidx/work/Worker;
    //   12: getfield 27	androidx/work/Worker:e	Lz2/c;
    //   15: aload_1
    //   16: invokevirtual 33	z2/c:i	(Ljava/lang/Object;)Z
    //   19: pop
    //   20: goto +16 -> 36
    //   23: astore_1
    //   24: aload_0
    //   25: getfield 12	androidx/work/e:a	Landroidx/work/Worker;
    //   28: getfield 27	androidx/work/Worker:e	Lz2/c;
    //   31: aload_1
    //   32: invokevirtual 36	z2/c:j	(Ljava/lang/Throwable;)Z
    //   35: pop
    //   36: return
    // Local variable table:
    //   start	length	slot	name	signature
    //   0	37	0	this	e
    //   7	9	1	locala	d.a
    //   23	9	1	localThrowable	Throwable
    // Exception table:
    //   from	to	target	type
    //   0	20	23	finally
  }
}

/* Location:
 * Qualified Name:     androidx.work.e
 * Java Class Version: 6 (50.0)
 * JD-Core Version:    0.7.1
 */