package gb;

public final class c
  implements Runnable
{
  public c(d.a parama, int paramInt) {}
  
  /* Error */
  public final void run()
  {
    // Byte code:
    //   0: invokestatic 26	pb/b:c	()V
    //   3: getstatic 29	pb/b:a	Lpb/a;
    //   6: astore_1
    //   7: aload_1
    //   8: invokevirtual 33	java/lang/Object:getClass	()Ljava/lang/Class;
    //   11: pop
    //   12: aload_0
    //   13: getfield 14	gb/c:b	Lgb/d$a;
    //   16: getfield 38	gb/d$a:a	Lgb/a0;
    //   19: aload_0
    //   20: getfield 16	gb/c:a	I
    //   23: invokeinterface 44 2 0
    //   28: aload_1
    //   29: invokevirtual 33	java/lang/Object:getClass	()Ljava/lang/Class;
    //   32: pop
    //   33: goto +34 -> 67
    //   36: astore_2
    //   37: getstatic 29	pb/b:a	Lpb/a;
    //   40: invokevirtual 33	java/lang/Object:getClass	()Ljava/lang/Class;
    //   43: pop
    //   44: goto +9 -> 53
    //   47: astore_1
    //   48: aload_2
    //   49: aload_1
    //   50: invokevirtual 50	java/lang/Throwable:addSuppressed	(Ljava/lang/Throwable;)V
    //   53: aload_2
    //   54: athrow
    //   55: astore_1
    //   56: aload_0
    //   57: getfield 14	gb/c:b	Lgb/d$a;
    //   60: checkcast 52	hb/h$b
    //   63: aload_1
    //   64: invokevirtual 55	hb/h$b:e	(Ljava/lang/Throwable;)V
    //   67: return
    // Local variable table:
    //   start	length	slot	name	signature
    //   0	68	0	this	c
    //   6	23	1	locala	pb.a
    //   47	3	1	localThrowable1	Throwable
    //   55	9	1	localThrowable2	Throwable
    //   36	18	2	localObject	Object
    // Exception table:
    //   from	to	target	type
    //   3	28	36	finally
    //   37	44	47	finally
    //   0	3	55	finally
    //   28	33	55	finally
    //   48	53	55	finally
    //   53	55	55	finally
  }
}

/* Location:
 * Qualified Name:     gb.c
 * Java Class Version: 6 (50.0)
 * JD-Core Version:    0.7.1
 */