package gb;

public final class f$a
  implements Runnable
{
  public f$a(f paramf, int paramInt) {}
  
  /* Error */
  public final void run()
  {
    // Byte code:
    //   0: aload_0
    //   1: getfield 19	gb/f$a:b	Lgb/f;
    //   4: getfield 30	gb/f:c	Lgb/i2;
    //   7: invokevirtual 36	gb/i2:isClosed	()Z
    //   10: ifeq +4 -> 14
    //   13: return
    //   14: aload_0
    //   15: getfield 19	gb/f$a:b	Lgb/f;
    //   18: getfield 30	gb/f:c	Lgb/i2;
    //   21: aload_0
    //   22: getfield 21	gb/f$a:a	I
    //   25: invokevirtual 37	gb/i2:f	(I)V
    //   28: goto +25 -> 53
    //   31: astore_1
    //   32: aload_0
    //   33: getfield 19	gb/f$a:b	Lgb/f;
    //   36: getfield 40	gb/f:b	Lgb/g;
    //   39: aload_1
    //   40: invokevirtual 46	gb/g:e	(Ljava/lang/Throwable;)V
    //   43: aload_0
    //   44: getfield 19	gb/f$a:b	Lgb/f;
    //   47: getfield 30	gb/f:c	Lgb/i2;
    //   50: invokevirtual 49	gb/i2:close	()V
    //   53: return
    // Local variable table:
    //   start	length	slot	name	signature
    //   0	54	0	this	a
    //   31	9	1	localThrowable	Throwable
    // Exception table:
    //   from	to	target	type
    //   14	28	31	finally
  }
}

/* Location:
 * Qualified Name:     gb.f.a
 * Java Class Version: 6 (50.0)
 * JD-Core Version:    0.7.1
 */