package gb;

import eb.u0.d;
import n7.p;
import x6.b;

public final class i0$c
  implements Runnable
{
  public final u0.d a;
  
  public i0$c(i0 parami0, u0.d paramd)
  {
    b.y(paramd, "savedListener");
    a = paramd;
  }
  
  /* Error */
  public final void run()
  {
    // Byte code:
    //   0: getstatic 40	gb/i0:s	Ljava/util/logging/Logger;
    //   3: astore_1
    //   4: getstatic 46	java/util/logging/Level:FINER	Ljava/util/logging/Level;
    //   7: astore_2
    //   8: aload_1
    //   9: aload_2
    //   10: invokevirtual 52	java/util/logging/Logger:isLoggable	(Ljava/util/logging/Level;)Z
    //   13: ifeq +29 -> 42
    //   16: ldc 54
    //   18: invokestatic 60	f:l	(Ljava/lang/String;)Ljava/lang/StringBuilder;
    //   21: astore_3
    //   22: aload_3
    //   23: aload_0
    //   24: getfield 19	gb/i0$c:b	Lgb/i0;
    //   27: getfield 63	gb/i0:f	Ljava/lang/String;
    //   30: invokevirtual 68	java/lang/StringBuilder:append	(Ljava/lang/String;)Ljava/lang/StringBuilder;
    //   33: pop
    //   34: aload_1
    //   35: aload_3
    //   36: invokevirtual 72	java/lang/StringBuilder:toString	()Ljava/lang/String;
    //   39: invokevirtual 76	java/util/logging/Logger:finer	(Ljava/lang/String;)V
    //   42: aconst_null
    //   43: astore 4
    //   45: aconst_null
    //   46: astore 5
    //   48: aconst_null
    //   49: astore 6
    //   51: aconst_null
    //   52: astore 7
    //   54: iconst_1
    //   55: istore 8
    //   57: iconst_1
    //   58: istore 9
    //   60: iconst_1
    //   61: istore 10
    //   63: iconst_1
    //   64: istore 11
    //   66: aload 5
    //   68: astore_3
    //   69: aload_0
    //   70: getfield 19	gb/i0$c:b	Lgb/i0;
    //   73: astore 12
    //   75: aload 5
    //   77: astore_3
    //   78: aload 12
    //   80: getfield 63	gb/i0:f	Ljava/lang/String;
    //   83: aload 12
    //   85: getfield 80	gb/i0:g	I
    //   88: invokestatic 86	java/net/InetSocketAddress:createUnresolved	(Ljava/lang/String;I)Ljava/net/InetSocketAddress;
    //   91: astore 13
    //   93: aload 5
    //   95: astore_3
    //   96: aload 12
    //   98: getfield 89	gb/i0:a	Leb/z0;
    //   101: aload 13
    //   103: invokeinterface 94 2 0
    //   108: astore 12
    //   110: aload 12
    //   112: ifnull +24 -> 136
    //   115: aload 5
    //   117: astore_3
    //   118: new 96	eb/u
    //   121: astore 13
    //   123: aload 5
    //   125: astore_3
    //   126: aload 13
    //   128: aload 12
    //   130: invokespecial 99	eb/u:<init>	(Ljava/net/SocketAddress;)V
    //   133: goto +6 -> 139
    //   136: aconst_null
    //   137: astore 13
    //   139: aload 5
    //   141: astore_3
    //   142: invokestatic 105	java/util/Collections:emptyList	()Ljava/util/List;
    //   145: astore 12
    //   147: aload 5
    //   149: astore_3
    //   150: getstatic 110	eb/a:b	Leb/a;
    //   153: astore 14
    //   155: aload 13
    //   157: ifnull +83 -> 240
    //   160: aload 5
    //   162: astore_3
    //   163: aload_1
    //   164: aload_2
    //   165: invokevirtual 52	java/util/logging/Logger:isLoggable	(Ljava/util/logging/Level;)Z
    //   168: ifeq +53 -> 221
    //   171: aload 5
    //   173: astore_3
    //   174: new 65	java/lang/StringBuilder
    //   177: astore 7
    //   179: aload 5
    //   181: astore_3
    //   182: aload 7
    //   184: invokespecial 111	java/lang/StringBuilder:<init>	()V
    //   187: aload 5
    //   189: astore_3
    //   190: aload 7
    //   192: ldc 113
    //   194: invokevirtual 68	java/lang/StringBuilder:append	(Ljava/lang/String;)Ljava/lang/StringBuilder;
    //   197: pop
    //   198: aload 5
    //   200: astore_3
    //   201: aload 7
    //   203: aload 13
    //   205: invokevirtual 116	java/lang/StringBuilder:append	(Ljava/lang/Object;)Ljava/lang/StringBuilder;
    //   208: pop
    //   209: aload 5
    //   211: astore_3
    //   212: aload_1
    //   213: aload 7
    //   215: invokevirtual 72	java/lang/StringBuilder:toString	()Ljava/lang/String;
    //   218: invokevirtual 76	java/util/logging/Logger:finer	(Ljava/lang/String;)V
    //   221: aload 5
    //   223: astore_3
    //   224: aload 13
    //   226: invokestatic 120	java/util/Collections:singletonList	(Ljava/lang/Object;)Ljava/util/List;
    //   229: astore 13
    //   231: aconst_null
    //   232: astore_3
    //   233: aload 4
    //   235: astore 7
    //   237: goto +112 -> 349
    //   240: aload 5
    //   242: astore_3
    //   243: aload_0
    //   244: getfield 19	gb/i0$c:b	Lgb/i0;
    //   247: invokevirtual 124	gb/i0:e	()Lgb/i0$a;
    //   250: astore 13
    //   252: aload 13
    //   254: getfield 129	gb/i0$a:a	Leb/e1;
    //   257: astore_3
    //   258: aload_3
    //   259: ifnull +46 -> 305
    //   262: aload_0
    //   263: getfield 32	gb/i0$c:a	Leb/u0$d;
    //   266: aload_3
    //   267: invokevirtual 134	eb/u0$d:a	(Leb/e1;)V
    //   270: aload 13
    //   272: getfield 129	gb/i0$a:a	Leb/e1;
    //   275: ifnonnull +6 -> 281
    //   278: goto +6 -> 284
    //   281: iconst_0
    //   282: istore 11
    //   284: aload_0
    //   285: getfield 19	gb/i0$c:b	Lgb/i0;
    //   288: getfield 138	gb/i0:j	Leb/h1;
    //   291: new 11	gb/i0$c$a
    //   294: dup
    //   295: aload_0
    //   296: iload 11
    //   298: invokespecial 141	gb/i0$c$a:<init>	(Lgb/i0$c;Z)V
    //   301: invokevirtual 147	eb/h1:execute	(Ljava/lang/Runnable;)V
    //   304: return
    //   305: aload 13
    //   307: getfield 150	gb/i0$a:b	Ljava/util/List;
    //   310: astore 4
    //   312: aload 12
    //   314: astore_3
    //   315: aload 4
    //   317: ifnull +6 -> 323
    //   320: aload 4
    //   322: astore_3
    //   323: aload 13
    //   325: getfield 153	gb/i0$a:c	Leb/u0$b;
    //   328: astore 4
    //   330: aload 4
    //   332: ifnull +7 -> 339
    //   335: aload 4
    //   337: astore 7
    //   339: aload 13
    //   341: astore 4
    //   343: aload_3
    //   344: astore 13
    //   346: aload 4
    //   348: astore_3
    //   349: aload_0
    //   350: getfield 32	gb/i0$c:a	Leb/u0$d;
    //   353: astore 4
    //   355: new 155	eb/u0$e
    //   358: astore 6
    //   360: aload 6
    //   362: aload 13
    //   364: aload 14
    //   366: aload 7
    //   368: invokespecial 158	eb/u0$e:<init>	(Ljava/util/List;Leb/a;Leb/u0$b;)V
    //   371: aload 4
    //   373: aload 6
    //   375: invokevirtual 161	eb/u0$d:b	(Leb/u0$e;)V
    //   378: aload_3
    //   379: ifnull +17 -> 396
    //   382: aload_3
    //   383: getfield 129	gb/i0$a:a	Leb/e1;
    //   386: ifnonnull +10 -> 396
    //   389: iload 8
    //   391: istore 11
    //   393: goto +6 -> 399
    //   396: iconst_0
    //   397: istore 11
    //   399: aload_0
    //   400: getfield 19	gb/i0$c:b	Lgb/i0;
    //   403: getfield 138	gb/i0:j	Leb/h1;
    //   406: astore_3
    //   407: new 11	gb/i0$c$a
    //   410: dup
    //   411: aload_0
    //   412: iload 11
    //   414: invokespecial 141	gb/i0$c$a:<init>	(Lgb/i0$c;Z)V
    //   417: astore 13
    //   419: goto +167 -> 586
    //   422: astore 13
    //   424: goto +169 -> 593
    //   427: astore 7
    //   429: aload_3
    //   430: astore 13
    //   432: aload 7
    //   434: astore_3
    //   435: goto +22 -> 457
    //   438: astore_3
    //   439: goto +164 -> 603
    //   442: astore 7
    //   444: goto +16 -> 460
    //   447: astore 13
    //   449: goto +144 -> 593
    //   452: astore_3
    //   453: aload 6
    //   455: astore 13
    //   457: aload_3
    //   458: astore 7
    //   460: aload 13
    //   462: astore_3
    //   463: aload_0
    //   464: getfield 32	gb/i0$c:a	Leb/u0$d;
    //   467: astore 4
    //   469: aload 13
    //   471: astore_3
    //   472: getstatic 166	eb/e1:n	Leb/e1;
    //   475: astore 6
    //   477: aload 13
    //   479: astore_3
    //   480: new 65	java/lang/StringBuilder
    //   483: astore 5
    //   485: aload 13
    //   487: astore_3
    //   488: aload 5
    //   490: invokespecial 111	java/lang/StringBuilder:<init>	()V
    //   493: aload 13
    //   495: astore_3
    //   496: aload 5
    //   498: ldc -88
    //   500: invokevirtual 68	java/lang/StringBuilder:append	(Ljava/lang/String;)Ljava/lang/StringBuilder;
    //   503: pop
    //   504: aload 13
    //   506: astore_3
    //   507: aload 5
    //   509: aload_0
    //   510: getfield 19	gb/i0$c:b	Lgb/i0;
    //   513: getfield 63	gb/i0:f	Ljava/lang/String;
    //   516: invokevirtual 68	java/lang/StringBuilder:append	(Ljava/lang/String;)Ljava/lang/StringBuilder;
    //   519: pop
    //   520: aload 13
    //   522: astore_3
    //   523: aload 4
    //   525: aload 6
    //   527: aload 5
    //   529: invokevirtual 72	java/lang/StringBuilder:toString	()Ljava/lang/String;
    //   532: invokevirtual 171	eb/e1:g	(Ljava/lang/String;)Leb/e1;
    //   535: aload 7
    //   537: invokevirtual 174	eb/e1:f	(Ljava/lang/Throwable;)Leb/e1;
    //   540: invokevirtual 134	eb/u0$d:a	(Leb/e1;)V
    //   543: aload 13
    //   545: ifnull +18 -> 563
    //   548: aload 13
    //   550: getfield 129	gb/i0$a:a	Leb/e1;
    //   553: ifnonnull +10 -> 563
    //   556: iload 9
    //   558: istore 11
    //   560: goto +6 -> 566
    //   563: iconst_0
    //   564: istore 11
    //   566: aload_0
    //   567: getfield 19	gb/i0$c:b	Lgb/i0;
    //   570: getfield 138	gb/i0:j	Leb/h1;
    //   573: astore_3
    //   574: new 11	gb/i0$c$a
    //   577: dup
    //   578: aload_0
    //   579: iload 11
    //   581: invokespecial 141	gb/i0$c$a:<init>	(Lgb/i0$c;Z)V
    //   584: astore 13
    //   586: aload_3
    //   587: aload 13
    //   589: invokevirtual 147	eb/h1:execute	(Ljava/lang/Runnable;)V
    //   592: return
    //   593: aload 13
    //   595: astore 7
    //   597: aload_3
    //   598: astore 13
    //   600: aload 7
    //   602: astore_3
    //   603: aload 13
    //   605: ifnull +18 -> 623
    //   608: aload 13
    //   610: getfield 129	gb/i0$a:a	Leb/e1;
    //   613: ifnonnull +10 -> 623
    //   616: iload 10
    //   618: istore 11
    //   620: goto +6 -> 626
    //   623: iconst_0
    //   624: istore 11
    //   626: aload_0
    //   627: getfield 19	gb/i0$c:b	Lgb/i0;
    //   630: getfield 138	gb/i0:j	Leb/h1;
    //   633: new 11	gb/i0$c$a
    //   636: dup
    //   637: aload_0
    //   638: iload 11
    //   640: invokespecial 141	gb/i0$c$a:<init>	(Lgb/i0$c;Z)V
    //   643: invokevirtual 147	eb/h1:execute	(Ljava/lang/Runnable;)V
    //   646: aload_3
    //   647: athrow
    // Local variable table:
    //   start	length	slot	name	signature
    //   0	648	0	this	c
    //   3	210	1	localLogger	java.util.logging.Logger
    //   7	158	2	localLevel	java.util.logging.Level
    //   21	414	3	localObject1	Object
    //   438	1	3	localObject2	Object
    //   452	6	3	localIOException1	java.io.IOException
    //   462	185	3	localObject3	Object
    //   43	481	4	localObject4	Object
    //   46	482	5	localStringBuilder	StringBuilder
    //   49	477	6	localObject5	Object
    //   52	315	7	localObject6	Object
    //   427	6	7	localIOException2	java.io.IOException
    //   442	1	7	localIOException3	java.io.IOException
    //   458	143	7	localObject7	Object
    //   55	335	8	bool1	boolean
    //   58	499	9	bool2	boolean
    //   61	556	10	bool3	boolean
    //   64	575	11	bool4	boolean
    //   73	240	12	localObject8	Object
    //   91	327	13	localObject9	Object
    //   422	1	13	localObject10	Object
    //   430	1	13	localObject11	Object
    //   447	1	13	localObject12	Object
    //   455	154	13	localObject13	Object
    //   153	212	14	locala	eb.a
    // Exception table:
    //   from	to	target	type
    //   349	378	422	finally
    //   349	378	427	java/io/IOException
    //   252	258	438	finally
    //   262	270	438	finally
    //   305	312	438	finally
    //   323	330	438	finally
    //   252	258	442	java/io/IOException
    //   262	270	442	java/io/IOException
    //   305	312	442	java/io/IOException
    //   323	330	442	java/io/IOException
    //   69	75	447	finally
    //   78	93	447	finally
    //   96	110	447	finally
    //   118	123	447	finally
    //   126	133	447	finally
    //   142	147	447	finally
    //   150	155	447	finally
    //   163	171	447	finally
    //   174	179	447	finally
    //   182	187	447	finally
    //   190	198	447	finally
    //   201	209	447	finally
    //   212	221	447	finally
    //   224	231	447	finally
    //   243	252	447	finally
    //   463	469	447	finally
    //   472	477	447	finally
    //   480	485	447	finally
    //   488	493	447	finally
    //   496	504	447	finally
    //   507	520	447	finally
    //   523	543	447	finally
    //   69	75	452	java/io/IOException
    //   78	93	452	java/io/IOException
    //   96	110	452	java/io/IOException
    //   118	123	452	java/io/IOException
    //   126	133	452	java/io/IOException
    //   142	147	452	java/io/IOException
    //   150	155	452	java/io/IOException
    //   163	171	452	java/io/IOException
    //   174	179	452	java/io/IOException
    //   182	187	452	java/io/IOException
    //   190	198	452	java/io/IOException
    //   201	209	452	java/io/IOException
    //   212	221	452	java/io/IOException
    //   224	231	452	java/io/IOException
    //   243	252	452	java/io/IOException
  }
  
  public final class a
    implements Runnable
  {
    public a(boolean paramBoolean) {}
    
    public final void run()
    {
      if (bool4)
      {
        Object localObject = b;
        l = true;
        if (i > 0L)
        {
          localObject = k;
          b = false;
          ((p)localObject).b();
        }
      }
      b.q = false;
    }
  }
}

/* Location:
 * Qualified Name:     gb.i0.c
 * Java Class Version: 6 (50.0)
 * JD-Core Version:    0.7.1
 */