package gb;

public final class q$b$b
  extends z
{
  public q$b$b(q.b paramb, n3.a parama)
  {
    super(c.f);
  }
  
  /* Error */
  public final void a()
  {
    // Byte code:
    //   0: invokestatic 35	pb/b:c	()V
    //   3: aload_0
    //   4: getfield 16	gb/q$b$b:c	Lgb/q$b;
    //   7: getfield 21	gb/q$b:c	Lgb/q;
    //   10: getfield 38	gb/q:b	Lpb/c;
    //   13: astore_1
    //   14: invokestatic 40	pb/b:a	()V
    //   17: getstatic 43	pb/b:a	Lpb/a;
    //   20: astore_1
    //   21: aload_1
    //   22: invokevirtual 49	java/lang/Object:getClass	()Ljava/lang/Class;
    //   25: pop
    //   26: aload_0
    //   27: invokevirtual 51	gb/q$b$b:b	()V
    //   30: aload_1
    //   31: invokevirtual 49	java/lang/Object:getClass	()Ljava/lang/Class;
    //   34: pop
    //   35: return
    //   36: astore_1
    //   37: getstatic 43	pb/b:a	Lpb/a;
    //   40: invokevirtual 49	java/lang/Object:getClass	()Ljava/lang/Class;
    //   43: pop
    //   44: goto +9 -> 53
    //   47: astore_2
    //   48: aload_1
    //   49: aload_2
    //   50: invokevirtual 57	java/lang/Throwable:addSuppressed	(Ljava/lang/Throwable;)V
    //   53: aload_1
    //   54: athrow
    // Local variable table:
    //   start	length	slot	name	signature
    //   0	55	0	this	b
    //   13	18	1	localObject1	Object
    //   36	18	1	localObject2	Object
    //   47	3	2	localThrowable	Throwable
    // Exception table:
    //   from	to	target	type
    //   3	30	36	finally
    //   37	44	47	finally
  }
  
  /* Error */
  public final void b()
  {
    // Byte code:
    //   0: aload_0
    //   1: getfield 16	gb/q$b$b:c	Lgb/q$b;
    //   4: getfield 60	gb/q$b:b	Leb/e1;
    //   7: ifnull +31 -> 38
    //   10: aload_0
    //   11: getfield 18	gb/q$b$b:b	Lgb/n3$a;
    //   14: astore_1
    //   15: getstatic 65	gb/v0:a	Ljava/util/logging/Logger;
    //   18: astore_2
    //   19: aload_1
    //   20: invokeinterface 71 1 0
    //   25: astore_2
    //   26: aload_2
    //   27: ifnull +10 -> 37
    //   30: aload_2
    //   31: invokestatic 74	gb/v0:b	(Ljava/io/Closeable;)V
    //   34: goto -15 -> 19
    //   37: return
    //   38: aload_0
    //   39: getfield 18	gb/q$b$b:b	Lgb/n3$a;
    //   42: invokeinterface 71 1 0
    //   47: astore_1
    //   48: aload_1
    //   49: ifnull +109 -> 158
    //   52: aload_0
    //   53: getfield 16	gb/q$b$b:c	Lgb/q$b;
    //   56: astore_2
    //   57: aload_2
    //   58: getfield 77	gb/q$b:a	Leb/e$a;
    //   61: aload_2
    //   62: getfield 21	gb/q$b:c	Lgb/q;
    //   65: getfield 80	gb/q:a	Leb/t0;
    //   68: getfield 86	eb/t0:e	Leb/t0$b;
    //   71: aload_1
    //   72: invokeinterface 91 2 0
    //   77: invokevirtual 96	eb/e$a:c	(Ljava/lang/Object;)V
    //   80: aload_1
    //   81: invokevirtual 101	java/io/InputStream:close	()V
    //   84: goto -46 -> 38
    //   87: astore_2
    //   88: aload_1
    //   89: invokestatic 74	gb/v0:b	(Ljava/io/Closeable;)V
    //   92: aload_2
    //   93: athrow
    //   94: astore_1
    //   95: aload_0
    //   96: getfield 18	gb/q$b$b:b	Lgb/n3$a;
    //   99: astore_2
    //   100: getstatic 65	gb/v0:a	Ljava/util/logging/Logger;
    //   103: astore_3
    //   104: aload_2
    //   105: invokeinterface 71 1 0
    //   110: astore_3
    //   111: aload_3
    //   112: ifnull +10 -> 122
    //   115: aload_3
    //   116: invokestatic 74	gb/v0:b	(Ljava/io/Closeable;)V
    //   119: goto -15 -> 104
    //   122: aload_0
    //   123: getfield 16	gb/q$b$b:c	Lgb/q$b;
    //   126: astore_2
    //   127: getstatic 105	eb/e1:f	Leb/e1;
    //   130: aload_1
    //   131: invokevirtual 108	eb/e1:f	(Ljava/lang/Throwable;)Leb/e1;
    //   134: ldc 110
    //   136: invokevirtual 114	eb/e1:g	(Ljava/lang/String;)Leb/e1;
    //   139: astore_1
    //   140: aload_2
    //   141: aload_1
    //   142: putfield 60	gb/q$b:b	Leb/e1;
    //   145: aload_2
    //   146: getfield 21	gb/q$b:c	Lgb/q;
    //   149: getfield 118	gb/q:j	Lgb/s;
    //   152: aload_1
    //   153: invokeinterface 124 2 0
    //   158: return
    // Local variable table:
    //   start	length	slot	name	signature
    //   0	159	0	this	b
    //   14	75	1	localObject1	Object
    //   94	37	1	localThrowable	Throwable
    //   139	14	1	locale1	eb.e1
    //   18	44	2	localObject2	Object
    //   87	6	2	localObject3	Object
    //   99	47	2	localObject4	Object
    //   103	13	3	localObject5	Object
    // Exception table:
    //   from	to	target	type
    //   52	80	87	finally
    //   38	48	94	finally
    //   80	84	94	finally
    //   88	94	94	finally
  }
}

/* Location:
 * Qualified Name:     gb.q.b.b
 * Java Class Version: 6 (50.0)
 * JD-Core Version:    0.7.1
 */