package gb;

import eb.c;
import eb.e.a;
import eb.e1;
import eb.e1.a;
import eb.s0;
import java.util.concurrent.Executor;

public final class q$b
  implements t
{
  public final e.a<RespT> a;
  public e1 b;
  
  public q$b(e.a<RespT> parama)
  {
    Object localObject;
    x6.b.y(localObject, "observer");
    a = ((e.a)localObject);
  }
  
  /* Error */
  public final void a(n3.a parama)
  {
    // Byte code:
    //   0: invokestatic 46	pb/b:c	()V
    //   3: aload_0
    //   4: getfield 25	gb/q$b:c	Lgb/q;
    //   7: getfield 49	gb/q:b	Lpb/c;
    //   10: astore_2
    //   11: invokestatic 51	pb/b:a	()V
    //   14: invokestatic 53	pb/b:b	()V
    //   17: aload_0
    //   18: getfield 25	gb/q$b:c	Lgb/q;
    //   21: getfield 56	gb/q:c	Ljava/util/concurrent/Executor;
    //   24: astore_3
    //   25: new 14	gb/q$b$b
    //   28: astore_2
    //   29: aload_2
    //   30: aload_0
    //   31: aload_1
    //   32: invokespecial 59	gb/q$b$b:<init>	(Lgb/q$b;Lgb/n3$a;)V
    //   35: aload_3
    //   36: aload_2
    //   37: invokeinterface 65 2 0
    //   42: getstatic 68	pb/b:a	Lpb/a;
    //   45: invokevirtual 72	java/lang/Object:getClass	()Ljava/lang/Class;
    //   48: pop
    //   49: return
    //   50: astore_2
    //   51: getstatic 68	pb/b:a	Lpb/a;
    //   54: invokevirtual 72	java/lang/Object:getClass	()Ljava/lang/Class;
    //   57: pop
    //   58: goto +9 -> 67
    //   61: astore_1
    //   62: aload_2
    //   63: aload_1
    //   64: invokevirtual 78	java/lang/Throwable:addSuppressed	(Ljava/lang/Throwable;)V
    //   67: aload_2
    //   68: athrow
    // Local variable table:
    //   start	length	slot	name	signature
    //   0	69	0	this	b
    //   0	69	1	parama	n3.a
    //   10	27	2	localObject1	Object
    //   50	18	2	localObject2	Object
    //   24	12	3	localExecutor	Executor
    // Exception table:
    //   from	to	target	type
    //   3	42	50	finally
    //   51	58	61	finally
  }
  
  /* Error */
  public final void b(s0 params0)
  {
    // Byte code:
    //   0: invokestatic 46	pb/b:c	()V
    //   3: aload_0
    //   4: getfield 25	gb/q$b:c	Lgb/q;
    //   7: getfield 49	gb/q:b	Lpb/c;
    //   10: astore_2
    //   11: invokestatic 51	pb/b:a	()V
    //   14: invokestatic 53	pb/b:b	()V
    //   17: aload_0
    //   18: getfield 25	gb/q$b:c	Lgb/q;
    //   21: getfield 56	gb/q:c	Ljava/util/concurrent/Executor;
    //   24: astore_2
    //   25: new 11	gb/q$b$a
    //   28: astore_3
    //   29: aload_3
    //   30: aload_0
    //   31: aload_1
    //   32: invokespecial 82	gb/q$b$a:<init>	(Lgb/q$b;Leb/s0;)V
    //   35: aload_2
    //   36: aload_3
    //   37: invokeinterface 65 2 0
    //   42: getstatic 68	pb/b:a	Lpb/a;
    //   45: invokevirtual 72	java/lang/Object:getClass	()Ljava/lang/Class;
    //   48: pop
    //   49: return
    //   50: astore_2
    //   51: getstatic 68	pb/b:a	Lpb/a;
    //   54: invokevirtual 72	java/lang/Object:getClass	()Ljava/lang/Class;
    //   57: pop
    //   58: goto +9 -> 67
    //   61: astore_1
    //   62: aload_2
    //   63: aload_1
    //   64: invokevirtual 78	java/lang/Throwable:addSuppressed	(Ljava/lang/Throwable;)V
    //   67: aload_2
    //   68: athrow
    // Local variable table:
    //   start	length	slot	name	signature
    //   0	69	0	this	b
    //   0	69	1	params0	s0
    //   10	26	2	localObject1	Object
    //   50	18	2	localObject2	Object
    //   28	9	3	locala	a
    // Exception table:
    //   from	to	target	type
    //   3	42	50	finally
    //   51	58	61	finally
  }
  
  /* Error */
  public final void c()
  {
    // Byte code:
    //   0: aload_0
    //   1: getfield 25	gb/q$b:c	Lgb/q;
    //   4: getfield 85	gb/q:a	Leb/t0;
    //   7: getfield 90	eb/t0:a	Leb/t0$c;
    //   10: astore_1
    //   11: aload_1
    //   12: invokevirtual 72	java/lang/Object:getClass	()Ljava/lang/Class;
    //   15: pop
    //   16: aload_1
    //   17: getstatic 93	eb/t0$c:a	Leb/t0$c;
    //   20: if_acmpeq +18 -> 38
    //   23: aload_1
    //   24: getstatic 95	eb/t0$c:b	Leb/t0$c;
    //   27: if_acmpne +6 -> 33
    //   30: goto +8 -> 38
    //   33: iconst_0
    //   34: istore_2
    //   35: goto +5 -> 40
    //   38: iconst_1
    //   39: istore_2
    //   40: iload_2
    //   41: ifeq +4 -> 45
    //   44: return
    //   45: invokestatic 46	pb/b:c	()V
    //   48: aload_0
    //   49: getfield 25	gb/q$b:c	Lgb/q;
    //   52: getfield 49	gb/q:b	Lpb/c;
    //   55: astore_1
    //   56: invokestatic 51	pb/b:a	()V
    //   59: invokestatic 53	pb/b:b	()V
    //   62: aload_0
    //   63: getfield 25	gb/q$b:c	Lgb/q;
    //   66: getfield 56	gb/q:c	Ljava/util/concurrent/Executor;
    //   69: astore_3
    //   70: new 16	gb/q$b$c
    //   73: astore_1
    //   74: aload_1
    //   75: aload_0
    //   76: invokespecial 98	gb/q$b$c:<init>	(Lgb/q$b;)V
    //   79: aload_3
    //   80: aload_1
    //   81: invokeinterface 65 2 0
    //   86: getstatic 68	pb/b:a	Lpb/a;
    //   89: invokevirtual 72	java/lang/Object:getClass	()Ljava/lang/Class;
    //   92: pop
    //   93: return
    //   94: astore_3
    //   95: getstatic 68	pb/b:a	Lpb/a;
    //   98: invokevirtual 72	java/lang/Object:getClass	()Ljava/lang/Class;
    //   101: pop
    //   102: goto +9 -> 111
    //   105: astore_1
    //   106: aload_3
    //   107: aload_1
    //   108: invokevirtual 78	java/lang/Throwable:addSuppressed	(Ljava/lang/Throwable;)V
    //   111: aload_3
    //   112: athrow
    // Local variable table:
    //   start	length	slot	name	signature
    //   0	113	0	this	b
    //   10	71	1	localObject1	Object
    //   105	3	1	localThrowable	Throwable
    //   34	7	2	i	int
    //   69	11	3	localExecutor	Executor
    //   94	18	3	localObject2	Object
    // Exception table:
    //   from	to	target	type
    //   48	86	94	finally
    //   95	102	105	finally
  }
  
  /* Error */
  public final void d(e1 parame1, t.a parama, s0 params0)
  {
    // Byte code:
    //   0: invokestatic 46	pb/b:c	()V
    //   3: aload_0
    //   4: getfield 25	gb/q$b:c	Lgb/q;
    //   7: getfield 49	gb/q:b	Lpb/c;
    //   10: astore_2
    //   11: invokestatic 51	pb/b:a	()V
    //   14: aload_0
    //   15: aload_1
    //   16: aload_3
    //   17: invokevirtual 104	gb/q$b:e	(Leb/e1;Leb/s0;)V
    //   20: getstatic 68	pb/b:a	Lpb/a;
    //   23: invokevirtual 72	java/lang/Object:getClass	()Ljava/lang/Class;
    //   26: pop
    //   27: return
    //   28: astore_1
    //   29: getstatic 68	pb/b:a	Lpb/a;
    //   32: invokevirtual 72	java/lang/Object:getClass	()Ljava/lang/Class;
    //   35: pop
    //   36: goto +9 -> 45
    //   39: astore_2
    //   40: aload_1
    //   41: aload_2
    //   42: invokevirtual 78	java/lang/Throwable:addSuppressed	(Ljava/lang/Throwable;)V
    //   45: aload_1
    //   46: athrow
    // Local variable table:
    //   start	length	slot	name	signature
    //   0	47	0	this	b
    //   0	47	1	parame1	e1
    //   0	47	2	parama	t.a
    //   0	47	3	params0	s0
    // Exception table:
    //   from	to	target	type
    //   3	20	28	finally
    //   29	36	39	finally
  }
  
  public final void e(e1 parame1, s0 params0)
  {
    Object localObject1 = c;
    Object localObject2 = i.a;
    f.getClass();
    localObject1 = localObject2;
    if (localObject2 == null) {
      localObject1 = null;
    }
    e1 locale1 = parame1;
    localObject2 = params0;
    if (a == e1.a.d)
    {
      locale1 = parame1;
      localObject2 = params0;
      if (localObject1 != null)
      {
        locale1 = parame1;
        localObject2 = params0;
        if (((eb.q)localObject1).g())
        {
          parame1 = new d2.q();
          c.j.i(parame1);
          params0 = e1.h;
          localObject1 = new StringBuilder();
          ((StringBuilder)localObject1).append("ClientCall was cancelled at or after deadline. ");
          ((StringBuilder)localObject1).append(parame1);
          locale1 = params0.a(((StringBuilder)localObject1).toString());
          localObject2 = new s0();
        }
      }
    }
    pb.b.b();
    c.c.execute(new r(this, locale1, (s0)localObject2));
  }
  
  public final class a
    extends z
  {
    public a(s0 params0)
    {
      super();
    }
    
    /* Error */
    public final void a()
    {
      // Byte code:
      //   0: invokestatic 35	pb/b:c	()V
      //   3: aload_0
      //   4: getfield 17	gb/q$b$a:c	Lgb/q$b;
      //   7: getfield 22	gb/q$b:c	Lgb/q;
      //   10: getfield 38	gb/q:b	Lpb/c;
      //   13: astore_1
      //   14: invokestatic 40	pb/b:a	()V
      //   17: getstatic 43	pb/b:a	Lpb/a;
      //   20: invokevirtual 49	java/lang/Object:getClass	()Ljava/lang/Class;
      //   23: pop
      //   24: aload_0
      //   25: getfield 17	gb/q$b$a:c	Lgb/q$b;
      //   28: astore_2
      //   29: aload_2
      //   30: getfield 52	gb/q$b:b	Leb/e1;
      //   33: astore_1
      //   34: aload_1
      //   35: ifnull +6 -> 41
      //   38: goto +54 -> 92
      //   41: aload_2
      //   42: getfield 55	gb/q$b:a	Leb/e$a;
      //   45: aload_0
      //   46: getfield 19	gb/q$b$a:b	Leb/s0;
      //   49: invokevirtual 60	eb/e$a:b	(Leb/s0;)V
      //   52: goto +40 -> 92
      //   55: astore_2
      //   56: aload_0
      //   57: getfield 17	gb/q$b$a:c	Lgb/q$b;
      //   60: astore_1
      //   61: getstatic 64	eb/e1:f	Leb/e1;
      //   64: aload_2
      //   65: invokevirtual 67	eb/e1:f	(Ljava/lang/Throwable;)Leb/e1;
      //   68: ldc 69
      //   70: invokevirtual 73	eb/e1:g	(Ljava/lang/String;)Leb/e1;
      //   73: astore_2
      //   74: aload_1
      //   75: aload_2
      //   76: putfield 52	gb/q$b:b	Leb/e1;
      //   79: aload_1
      //   80: getfield 22	gb/q$b:c	Lgb/q;
      //   83: getfield 77	gb/q:j	Lgb/s;
      //   86: aload_2
      //   87: invokeinterface 83 2 0
      //   92: getstatic 43	pb/b:a	Lpb/a;
      //   95: invokevirtual 49	java/lang/Object:getClass	()Ljava/lang/Class;
      //   98: pop
      //   99: return
      //   100: astore_2
      //   101: getstatic 43	pb/b:a	Lpb/a;
      //   104: invokevirtual 49	java/lang/Object:getClass	()Ljava/lang/Class;
      //   107: pop
      //   108: goto +9 -> 117
      //   111: astore_1
      //   112: aload_2
      //   113: aload_1
      //   114: invokevirtual 89	java/lang/Throwable:addSuppressed	(Ljava/lang/Throwable;)V
      //   117: aload_2
      //   118: athrow
      // Local variable table:
      //   start	length	slot	name	signature
      //   0	119	0	this	a
      //   13	67	1	localObject1	Object
      //   111	3	1	localThrowable1	Throwable
      //   28	14	2	localb	q.b
      //   55	10	2	localThrowable2	Throwable
      //   73	14	2	locale1	e1
      //   100	18	2	localObject2	Object
      // Exception table:
      //   from	to	target	type
      //   41	52	55	finally
      //   3	34	100	finally
      //   56	92	100	finally
      //   101	108	111	finally
    }
  }
  
  public final class b
    extends z
  {
    public b(n3.a parama)
    {
      super();
    }
    
    /* Error */
    public final void a()
    {
      // Byte code:
      //   0: invokestatic 35	pb/b:c	()V
      //   3: aload_0
      //   4: getfield 16	gb/q$b$b:c	Lgb/q$b;
      //   7: getfield 21	gb/q$b:c	Lgb/q;
      //   10: getfield 38	gb/q:b	Lpb/c;
      //   13: astore_1
      //   14: invokestatic 40	pb/b:a	()V
      //   17: getstatic 43	pb/b:a	Lpb/a;
      //   20: astore_1
      //   21: aload_1
      //   22: invokevirtual 49	java/lang/Object:getClass	()Ljava/lang/Class;
      //   25: pop
      //   26: aload_0
      //   27: invokevirtual 51	gb/q$b$b:b	()V
      //   30: aload_1
      //   31: invokevirtual 49	java/lang/Object:getClass	()Ljava/lang/Class;
      //   34: pop
      //   35: return
      //   36: astore_1
      //   37: getstatic 43	pb/b:a	Lpb/a;
      //   40: invokevirtual 49	java/lang/Object:getClass	()Ljava/lang/Class;
      //   43: pop
      //   44: goto +9 -> 53
      //   47: astore_2
      //   48: aload_1
      //   49: aload_2
      //   50: invokevirtual 57	java/lang/Throwable:addSuppressed	(Ljava/lang/Throwable;)V
      //   53: aload_1
      //   54: athrow
      // Local variable table:
      //   start	length	slot	name	signature
      //   0	55	0	this	b
      //   13	18	1	localObject1	Object
      //   36	18	1	localObject2	Object
      //   47	3	2	localThrowable	Throwable
      // Exception table:
      //   from	to	target	type
      //   3	30	36	finally
      //   37	44	47	finally
    }
    
    /* Error */
    public final void b()
    {
      // Byte code:
      //   0: aload_0
      //   1: getfield 16	gb/q$b$b:c	Lgb/q$b;
      //   4: getfield 60	gb/q$b:b	Leb/e1;
      //   7: ifnull +31 -> 38
      //   10: aload_0
      //   11: getfield 18	gb/q$b$b:b	Lgb/n3$a;
      //   14: astore_1
      //   15: getstatic 65	gb/v0:a	Ljava/util/logging/Logger;
      //   18: astore_2
      //   19: aload_1
      //   20: invokeinterface 71 1 0
      //   25: astore_2
      //   26: aload_2
      //   27: ifnull +10 -> 37
      //   30: aload_2
      //   31: invokestatic 74	gb/v0:b	(Ljava/io/Closeable;)V
      //   34: goto -15 -> 19
      //   37: return
      //   38: aload_0
      //   39: getfield 18	gb/q$b$b:b	Lgb/n3$a;
      //   42: invokeinterface 71 1 0
      //   47: astore_1
      //   48: aload_1
      //   49: ifnull +109 -> 158
      //   52: aload_0
      //   53: getfield 16	gb/q$b$b:c	Lgb/q$b;
      //   56: astore_2
      //   57: aload_2
      //   58: getfield 77	gb/q$b:a	Leb/e$a;
      //   61: aload_2
      //   62: getfield 21	gb/q$b:c	Lgb/q;
      //   65: getfield 80	gb/q:a	Leb/t0;
      //   68: getfield 86	eb/t0:e	Leb/t0$b;
      //   71: aload_1
      //   72: invokeinterface 91 2 0
      //   77: invokevirtual 96	eb/e$a:c	(Ljava/lang/Object;)V
      //   80: aload_1
      //   81: invokevirtual 101	java/io/InputStream:close	()V
      //   84: goto -46 -> 38
      //   87: astore_2
      //   88: aload_1
      //   89: invokestatic 74	gb/v0:b	(Ljava/io/Closeable;)V
      //   92: aload_2
      //   93: athrow
      //   94: astore_1
      //   95: aload_0
      //   96: getfield 18	gb/q$b$b:b	Lgb/n3$a;
      //   99: astore_2
      //   100: getstatic 65	gb/v0:a	Ljava/util/logging/Logger;
      //   103: astore_3
      //   104: aload_2
      //   105: invokeinterface 71 1 0
      //   110: astore_3
      //   111: aload_3
      //   112: ifnull +10 -> 122
      //   115: aload_3
      //   116: invokestatic 74	gb/v0:b	(Ljava/io/Closeable;)V
      //   119: goto -15 -> 104
      //   122: aload_0
      //   123: getfield 16	gb/q$b$b:c	Lgb/q$b;
      //   126: astore_2
      //   127: getstatic 105	eb/e1:f	Leb/e1;
      //   130: aload_1
      //   131: invokevirtual 108	eb/e1:f	(Ljava/lang/Throwable;)Leb/e1;
      //   134: ldc 110
      //   136: invokevirtual 114	eb/e1:g	(Ljava/lang/String;)Leb/e1;
      //   139: astore_1
      //   140: aload_2
      //   141: aload_1
      //   142: putfield 60	gb/q$b:b	Leb/e1;
      //   145: aload_2
      //   146: getfield 21	gb/q$b:c	Lgb/q;
      //   149: getfield 118	gb/q:j	Lgb/s;
      //   152: aload_1
      //   153: invokeinterface 124 2 0
      //   158: return
      // Local variable table:
      //   start	length	slot	name	signature
      //   0	159	0	this	b
      //   14	75	1	localObject1	Object
      //   94	37	1	localThrowable	Throwable
      //   139	14	1	locale1	e1
      //   18	44	2	localObject2	Object
      //   87	6	2	localObject3	Object
      //   99	47	2	localObject4	Object
      //   103	13	3	localObject5	Object
      // Exception table:
      //   from	to	target	type
      //   52	80	87	finally
      //   38	48	94	finally
      //   80	84	94	finally
      //   88	94	94	finally
    }
  }
  
  public final class c
    extends z
  {
    public c()
    {
      super();
    }
    
    /* Error */
    public final void a()
    {
      // Byte code:
      //   0: invokestatic 32	pb/b:c	()V
      //   3: aload_0
      //   4: getfield 15	gb/q$b$c:b	Lgb/q$b;
      //   7: getfield 18	gb/q$b:c	Lgb/q;
      //   10: getfield 35	gb/q:b	Lpb/c;
      //   13: astore_1
      //   14: invokestatic 37	pb/b:a	()V
      //   17: getstatic 40	pb/b:a	Lpb/a;
      //   20: invokevirtual 46	java/lang/Object:getClass	()Ljava/lang/Class;
      //   23: pop
      //   24: aload_0
      //   25: getfield 15	gb/q$b$c:b	Lgb/q$b;
      //   28: astore_2
      //   29: aload_2
      //   30: getfield 49	gb/q$b:b	Leb/e1;
      //   33: astore_1
      //   34: aload_1
      //   35: ifnull +6 -> 41
      //   38: goto +50 -> 88
      //   41: aload_2
      //   42: getfield 52	gb/q$b:a	Leb/e$a;
      //   45: invokevirtual 57	eb/e$a:d	()V
      //   48: goto +40 -> 88
      //   51: astore_2
      //   52: aload_0
      //   53: getfield 15	gb/q$b$c:b	Lgb/q$b;
      //   56: astore_1
      //   57: getstatic 61	eb/e1:f	Leb/e1;
      //   60: aload_2
      //   61: invokevirtual 64	eb/e1:f	(Ljava/lang/Throwable;)Leb/e1;
      //   64: ldc 66
      //   66: invokevirtual 70	eb/e1:g	(Ljava/lang/String;)Leb/e1;
      //   69: astore_2
      //   70: aload_1
      //   71: aload_2
      //   72: putfield 49	gb/q$b:b	Leb/e1;
      //   75: aload_1
      //   76: getfield 18	gb/q$b:c	Lgb/q;
      //   79: getfield 74	gb/q:j	Lgb/s;
      //   82: aload_2
      //   83: invokeinterface 80 2 0
      //   88: getstatic 40	pb/b:a	Lpb/a;
      //   91: invokevirtual 46	java/lang/Object:getClass	()Ljava/lang/Class;
      //   94: pop
      //   95: return
      //   96: astore_1
      //   97: getstatic 40	pb/b:a	Lpb/a;
      //   100: invokevirtual 46	java/lang/Object:getClass	()Ljava/lang/Class;
      //   103: pop
      //   104: goto +9 -> 113
      //   107: astore_2
      //   108: aload_1
      //   109: aload_2
      //   110: invokevirtual 86	java/lang/Throwable:addSuppressed	(Ljava/lang/Throwable;)V
      //   113: aload_1
      //   114: athrow
      // Local variable table:
      //   start	length	slot	name	signature
      //   0	115	0	this	c
      //   13	63	1	localObject1	Object
      //   96	18	1	localObject2	Object
      //   28	14	2	localb	q.b
      //   51	10	2	localThrowable1	Throwable
      //   69	14	2	locale1	e1
      //   107	3	2	localThrowable2	Throwable
      // Exception table:
      //   from	to	target	type
      //   41	48	51	finally
      //   3	34	96	finally
      //   52	88	96	finally
      //   97	104	107	finally
    }
  }
}

/* Location:
 * Qualified Name:     gb.q.b
 * Java Class Version: 6 (50.0)
 * JD-Core Version:    0.7.1
 */