package com.google.android.gms.internal.fido;

import java.util.Comparator;

final class zzcn
{
  public static final String zza;
  public static final Comparator zzb;
  
  /* Error */
  static
  {
    // Byte code:
    //   0: ldc 2
    //   2: invokevirtual 16	java/lang/Class:getName	()Ljava/lang/String;
    //   5: ldc 18
    //   7: invokevirtual 24	java/lang/String:concat	(Ljava/lang/String;)Ljava/lang/String;
    //   10: astore_0
    //   11: aload_0
    //   12: putstatic 26	com/google/android/gms/internal/fido/zzcn:zza	Ljava/lang/String;
    //   15: aload_0
    //   16: invokestatic 30	java/lang/Class:forName	(Ljava/lang/String;)Ljava/lang/Class;
    //   19: invokevirtual 34	java/lang/Class:getEnumConstants	()[Ljava/lang/Object;
    //   22: astore_0
    //   23: aload_0
    //   24: invokevirtual 38	java/lang/Object:getClass	()Ljava/lang/Class;
    //   27: pop
    //   28: aload_0
    //   29: iconst_0
    //   30: aaload
    //   31: checkcast 40	java/util/Comparator
    //   34: astore_0
    //   35: goto +8 -> 43
    //   38: astore_0
    //   39: getstatic 45	com/google/android/gms/internal/fido/zzcm:zza	Lcom/google/android/gms/internal/fido/zzcm;
    //   42: astore_0
    //   43: aload_0
    //   44: putstatic 47	com/google/android/gms/internal/fido/zzcn:zzb	Ljava/util/Comparator;
    //   47: return
    // Local variable table:
    //   start	length	slot	name	signature
    //   10	25	0	localObject1	Object
    //   38	1	0	localObject2	Object
    //   42	2	0	localzzcm	zzcm
    // Exception table:
    //   from	to	target	type
    //   15	35	38	finally
  }
}

/* Location:
 * Qualified Name:     com.google.android.gms.internal.fido.zzcn
 * Java Class Version: 6 (50.0)
 * JD-Core Version:    0.7.1
 */