package y5;

import java.util.HashMap;

public final class b
  extends Thread
{
  public b(HashMap paramHashMap) {}
  
  /* Error */
  public final void run()
  {
    // Byte code:
    //   0: aload_0
    //   1: getfield 10	y5/b:a	Ljava/util/Map;
    //   4: astore_1
    //   5: ldc 23
    //   7: invokestatic 29	android/net/Uri:parse	(Ljava/lang/String;)Landroid/net/Uri;
    //   10: invokevirtual 33	android/net/Uri:buildUpon	()Landroid/net/Uri$Builder;
    //   13: astore_2
    //   14: aload_1
    //   15: invokeinterface 39 1 0
    //   20: invokeinterface 45 1 0
    //   25: astore_3
    //   26: aload_3
    //   27: invokeinterface 51 1 0
    //   32: ifeq +35 -> 67
    //   35: aload_3
    //   36: invokeinterface 55 1 0
    //   41: checkcast 57	java/lang/String
    //   44: astore 4
    //   46: aload_2
    //   47: aload 4
    //   49: aload_1
    //   50: aload 4
    //   52: invokeinterface 61 2 0
    //   57: checkcast 57	java/lang/String
    //   60: invokevirtual 67	android/net/Uri$Builder:appendQueryParameter	(Ljava/lang/String;Ljava/lang/String;)Landroid/net/Uri$Builder;
    //   63: pop
    //   64: goto -38 -> 26
    //   67: aload_2
    //   68: invokevirtual 71	android/net/Uri$Builder:build	()Landroid/net/Uri;
    //   71: invokevirtual 75	android/net/Uri:toString	()Ljava/lang/String;
    //   74: astore_3
    //   75: sipush 263
    //   78: invokestatic 81	com/google/android/gms/internal/ads_identifier/zzi:zzb	(I)V
    //   81: new 83	java/net/URL
    //   84: astore_1
    //   85: aload_1
    //   86: aload_3
    //   87: invokespecial 86	java/net/URL:<init>	(Ljava/lang/String;)V
    //   90: aload_1
    //   91: invokevirtual 90	java/net/URL:openConnection	()Ljava/net/URLConnection;
    //   94: checkcast 92	java/net/HttpURLConnection
    //   97: astore_1
    //   98: aload_1
    //   99: invokevirtual 96	java/net/HttpURLConnection:getResponseCode	()I
    //   102: istore 5
    //   104: iload 5
    //   106: sipush 200
    //   109: if_icmplt +11 -> 120
    //   112: iload 5
    //   114: sipush 300
    //   117: if_icmplt +62 -> 179
    //   120: aload_3
    //   121: invokestatic 100	java/lang/String:valueOf	(Ljava/lang/Object;)Ljava/lang/String;
    //   124: invokevirtual 103	java/lang/String:length	()I
    //   127: istore 6
    //   129: new 105	java/lang/StringBuilder
    //   132: astore_2
    //   133: aload_2
    //   134: iload 6
    //   136: bipush 65
    //   138: iadd
    //   139: invokespecial 107	java/lang/StringBuilder:<init>	(I)V
    //   142: aload_2
    //   143: ldc 109
    //   145: invokevirtual 113	java/lang/StringBuilder:append	(Ljava/lang/String;)Ljava/lang/StringBuilder;
    //   148: pop
    //   149: aload_2
    //   150: iload 5
    //   152: invokevirtual 116	java/lang/StringBuilder:append	(I)Ljava/lang/StringBuilder;
    //   155: pop
    //   156: aload_2
    //   157: ldc 118
    //   159: invokevirtual 113	java/lang/StringBuilder:append	(Ljava/lang/String;)Ljava/lang/StringBuilder;
    //   162: pop
    //   163: aload_2
    //   164: aload_3
    //   165: invokevirtual 113	java/lang/StringBuilder:append	(Ljava/lang/String;)Ljava/lang/StringBuilder;
    //   168: pop
    //   169: ldc 120
    //   171: aload_2
    //   172: invokevirtual 121	java/lang/StringBuilder:toString	()Ljava/lang/String;
    //   175: invokestatic 127	android/util/Log:w	(Ljava/lang/String;Ljava/lang/String;)I
    //   178: pop
    //   179: aload_1
    //   180: invokevirtual 130	java/net/HttpURLConnection:disconnect	()V
    //   183: invokestatic 133	com/google/android/gms/internal/ads_identifier/zzi:zza	()V
    //   186: goto +180 -> 366
    //   189: astore_2
    //   190: aload_1
    //   191: invokevirtual 130	java/net/HttpURLConnection:disconnect	()V
    //   194: aload_2
    //   195: athrow
    //   196: astore_1
    //   197: goto +170 -> 367
    //   200: astore_1
    //   201: goto +4 -> 205
    //   204: astore_1
    //   205: aload_1
    //   206: invokevirtual 138	java/lang/Throwable:getMessage	()Ljava/lang/String;
    //   209: astore 4
    //   211: aload_3
    //   212: invokestatic 100	java/lang/String:valueOf	(Ljava/lang/Object;)Ljava/lang/String;
    //   215: invokevirtual 103	java/lang/String:length	()I
    //   218: istore 6
    //   220: aload 4
    //   222: invokestatic 100	java/lang/String:valueOf	(Ljava/lang/Object;)Ljava/lang/String;
    //   225: invokevirtual 103	java/lang/String:length	()I
    //   228: istore 5
    //   230: new 105	java/lang/StringBuilder
    //   233: astore_2
    //   234: aload_2
    //   235: iload 6
    //   237: bipush 27
    //   239: iadd
    //   240: iload 5
    //   242: iadd
    //   243: invokespecial 107	java/lang/StringBuilder:<init>	(I)V
    //   246: aload_2
    //   247: ldc -116
    //   249: invokevirtual 113	java/lang/StringBuilder:append	(Ljava/lang/String;)Ljava/lang/StringBuilder;
    //   252: pop
    //   253: aload_2
    //   254: aload_3
    //   255: invokevirtual 113	java/lang/StringBuilder:append	(Ljava/lang/String;)Ljava/lang/StringBuilder;
    //   258: pop
    //   259: aload_2
    //   260: ldc -114
    //   262: invokevirtual 113	java/lang/StringBuilder:append	(Ljava/lang/String;)Ljava/lang/StringBuilder;
    //   265: pop
    //   266: aload_2
    //   267: aload 4
    //   269: invokevirtual 113	java/lang/StringBuilder:append	(Ljava/lang/String;)Ljava/lang/StringBuilder;
    //   272: pop
    //   273: aload_2
    //   274: invokevirtual 121	java/lang/StringBuilder:toString	()Ljava/lang/String;
    //   277: astore_3
    //   278: ldc 120
    //   280: aload_3
    //   281: aload_1
    //   282: invokestatic 145	android/util/Log:w	(Ljava/lang/String;Ljava/lang/String;Ljava/lang/Throwable;)I
    //   285: pop
    //   286: goto -103 -> 183
    //   289: astore_1
    //   290: aload_1
    //   291: invokevirtual 138	java/lang/Throwable:getMessage	()Ljava/lang/String;
    //   294: astore 4
    //   296: aload_3
    //   297: invokestatic 100	java/lang/String:valueOf	(Ljava/lang/Object;)Ljava/lang/String;
    //   300: invokevirtual 103	java/lang/String:length	()I
    //   303: istore 5
    //   305: aload 4
    //   307: invokestatic 100	java/lang/String:valueOf	(Ljava/lang/Object;)Ljava/lang/String;
    //   310: invokevirtual 103	java/lang/String:length	()I
    //   313: istore 6
    //   315: new 105	java/lang/StringBuilder
    //   318: astore_2
    //   319: aload_2
    //   320: iload 5
    //   322: bipush 32
    //   324: iadd
    //   325: iload 6
    //   327: iadd
    //   328: invokespecial 107	java/lang/StringBuilder:<init>	(I)V
    //   331: aload_2
    //   332: ldc -109
    //   334: invokevirtual 113	java/lang/StringBuilder:append	(Ljava/lang/String;)Ljava/lang/StringBuilder;
    //   337: pop
    //   338: aload_2
    //   339: aload_3
    //   340: invokevirtual 113	java/lang/StringBuilder:append	(Ljava/lang/String;)Ljava/lang/StringBuilder;
    //   343: pop
    //   344: aload_2
    //   345: ldc -114
    //   347: invokevirtual 113	java/lang/StringBuilder:append	(Ljava/lang/String;)Ljava/lang/StringBuilder;
    //   350: pop
    //   351: aload_2
    //   352: aload 4
    //   354: invokevirtual 113	java/lang/StringBuilder:append	(Ljava/lang/String;)Ljava/lang/StringBuilder;
    //   357: pop
    //   358: aload_2
    //   359: invokevirtual 121	java/lang/StringBuilder:toString	()Ljava/lang/String;
    //   362: astore_3
    //   363: goto -85 -> 278
    //   366: return
    //   367: invokestatic 133	com/google/android/gms/internal/ads_identifier/zzi:zza	()V
    //   370: aload_1
    //   371: athrow
    // Local variable table:
    //   start	length	slot	name	signature
    //   0	372	0	this	b
    //   4	187	1	localObject1	Object
    //   196	1	1	localObject2	Object
    //   200	1	1	localRuntimeException	RuntimeException
    //   204	78	1	localIOException	java.io.IOException
    //   289	82	1	localIndexOutOfBoundsException	IndexOutOfBoundsException
    //   13	159	2	localObject3	Object
    //   189	6	2	localObject4	Object
    //   233	126	2	localStringBuilder	StringBuilder
    //   25	338	3	localObject5	Object
    //   44	309	4	str	String
    //   102	223	5	i	int
    //   127	201	6	j	int
    // Exception table:
    //   from	to	target	type
    //   98	104	189	finally
    //   120	179	189	finally
    //   75	98	196	finally
    //   179	183	196	finally
    //   190	196	196	finally
    //   205	278	196	finally
    //   278	286	196	finally
    //   290	363	196	finally
    //   75	98	200	java/lang/RuntimeException
    //   179	183	200	java/lang/RuntimeException
    //   190	196	200	java/lang/RuntimeException
    //   75	98	204	java/io/IOException
    //   179	183	204	java/io/IOException
    //   190	196	204	java/io/IOException
    //   75	98	289	java/lang/IndexOutOfBoundsException
    //   179	183	289	java/lang/IndexOutOfBoundsException
    //   190	196	289	java/lang/IndexOutOfBoundsException
  }
}

/* Location:
 * Qualified Name:     y5.b
 * Java Class Version: 6 (50.0)
 * JD-Core Version:    0.7.1
 */