package com.google.android.recaptcha.internal;

import b.z;
import rb.c;

public final class zzfa
  implements zzey
{
  private final c zza;
  
  public zzfa()
  {
    int i = zzav.zza;
    zza = z.n(zzez.zza);
  }
  
  /* Error */
  public final zzsc zza(String paramString, zzto paramzzto)
  {
    // Byte code:
    //   0: aconst_null
    //   1: astore_3
    //   2: aconst_null
    //   3: astore 4
    //   5: aconst_null
    //   6: astore 5
    //   8: aload_0
    //   9: getfield 30	com/google/android/recaptcha/internal/zzfa:zza	Lrb/c;
    //   12: invokeinterface 42 1 0
    //   17: checkcast 44	com/google/android/recaptcha/internal/zzex
    //   20: aload_1
    //   21: invokevirtual 47	com/google/android/recaptcha/internal/zzex:zza	(Ljava/lang/String;)Lcom/google/android/recaptcha/internal/zzew;
    //   24: astore_1
    //   25: aload_1
    //   26: astore 5
    //   28: aload_1
    //   29: astore_3
    //   30: aload_1
    //   31: astore 4
    //   33: aload_1
    //   34: invokevirtual 52	com/google/android/recaptcha/internal/zzew:zzc	()V
    //   37: aload_1
    //   38: astore 5
    //   40: aload_1
    //   41: astore_3
    //   42: aload_1
    //   43: astore 4
    //   45: aload_1
    //   46: aload_2
    //   47: invokevirtual 58	com/google/android/recaptcha/internal/zzko:zzd	()[B
    //   50: invokevirtual 62	com/google/android/recaptcha/internal/zzew:zze	([B)V
    //   53: aload_1
    //   54: astore 5
    //   56: aload_1
    //   57: astore_3
    //   58: aload_1
    //   59: astore 4
    //   61: aload_1
    //   62: invokestatic 68	com/google/android/recaptcha/internal/zzsc:zzi	()Lcom/google/android/recaptcha/internal/zzsc;
    //   65: invokevirtual 71	com/google/android/recaptcha/internal/zzew:zza	(Lcom/google/android/recaptcha/internal/zzoi;)Lcom/google/android/recaptcha/internal/zzoi;
    //   68: checkcast 64	com/google/android/recaptcha/internal/zzsc
    //   71: astore_2
    //   72: aload_1
    //   73: invokevirtual 73	com/google/android/recaptcha/internal/zzew:zzd	()V
    //   76: aload_2
    //   77: areturn
    //   78: astore_1
    //   79: goto +130 -> 209
    //   82: astore_2
    //   83: goto +7 -> 90
    //   86: astore_2
    //   87: goto +32 -> 119
    //   90: aload_3
    //   91: astore 5
    //   93: new 34	com/google/android/recaptcha/internal/zzbd
    //   96: astore_1
    //   97: aload_3
    //   98: astore 5
    //   100: aload_1
    //   101: getstatic 78	com/google/android/recaptcha/internal/zzbb:zzc	Lcom/google/android/recaptcha/internal/zzbb;
    //   104: getstatic 84	com/google/android/recaptcha/internal/zzba:zzF	Lcom/google/android/recaptcha/internal/zzba;
    //   107: aload_2
    //   108: invokevirtual 90	java/lang/Throwable:getMessage	()Ljava/lang/String;
    //   111: invokespecial 93	com/google/android/recaptcha/internal/zzbd:<init>	(Lcom/google/android/recaptcha/internal/zzbb;Lcom/google/android/recaptcha/internal/zzba;Ljava/lang/String;)V
    //   114: aload_3
    //   115: astore 5
    //   117: aload_1
    //   118: athrow
    //   119: aload 4
    //   121: ifnull +82 -> 203
    //   124: aload 4
    //   126: astore 5
    //   128: aload_2
    //   129: astore_1
    //   130: aload_2
    //   131: invokevirtual 96	com/google/android/recaptcha/internal/zzbd:zza	()Lcom/google/android/recaptcha/internal/zzba;
    //   134: getstatic 99	com/google/android/recaptcha/internal/zzba:zzau	Lcom/google/android/recaptcha/internal/zzba;
    //   137: invokestatic 105	ec/i:a	(Ljava/lang/Object;Ljava/lang/Object;)Z
    //   140: ifeq +57 -> 197
    //   143: aload 4
    //   145: astore 5
    //   147: aload 4
    //   149: invokevirtual 109	com/google/android/recaptcha/internal/zzew:zzb	()Ljava/net/HttpURLConnection;
    //   152: astore_1
    //   153: aload 4
    //   155: astore 5
    //   157: aload_1
    //   158: invokevirtual 115	java/net/HttpURLConnection:getErrorStream	()Ljava/io/InputStream;
    //   161: invokestatic 121	com/google/android/recaptcha/internal/zztu:zzg	(Ljava/io/InputStream;)Lcom/google/android/recaptcha/internal/zztu;
    //   164: invokevirtual 124	com/google/android/recaptcha/internal/zztu:zzi	()Lcom/google/android/recaptcha/internal/zztv;
    //   167: invokestatic 129	com/google/android/recaptcha/internal/zzbc:zza	(Lcom/google/android/recaptcha/internal/zztv;)Lcom/google/android/recaptcha/internal/zzbd;
    //   170: astore_1
    //   171: goto +26 -> 197
    //   174: astore_1
    //   175: aload 4
    //   177: astore 5
    //   179: new 34	com/google/android/recaptcha/internal/zzbd
    //   182: dup
    //   183: getstatic 78	com/google/android/recaptcha/internal/zzbb:zzc	Lcom/google/android/recaptcha/internal/zzbb;
    //   186: getstatic 132	com/google/android/recaptcha/internal/zzba:zzG	Lcom/google/android/recaptcha/internal/zzba;
    //   189: aload_1
    //   190: invokevirtual 90	java/lang/Throwable:getMessage	()Ljava/lang/String;
    //   193: invokespecial 93	com/google/android/recaptcha/internal/zzbd:<init>	(Lcom/google/android/recaptcha/internal/zzbb;Lcom/google/android/recaptcha/internal/zzba;Ljava/lang/String;)V
    //   196: astore_1
    //   197: aload 4
    //   199: astore 5
    //   201: aload_1
    //   202: athrow
    //   203: aload 4
    //   205: astore 5
    //   207: aload_2
    //   208: athrow
    //   209: aload 5
    //   211: ifnull +8 -> 219
    //   214: aload 5
    //   216: invokevirtual 73	com/google/android/recaptcha/internal/zzew:zzd	()V
    //   219: aload_1
    //   220: athrow
    // Local variable table:
    //   start	length	slot	name	signature
    //   0	221	0	this	zzfa
    //   0	221	1	paramString	String
    //   0	221	2	paramzzto	zzto
    //   1	114	3	str1	String
    //   3	201	4	str2	String
    //   6	209	5	str3	String
    // Exception table:
    //   from	to	target	type
    //   8	25	78	finally
    //   33	37	78	finally
    //   45	53	78	finally
    //   61	72	78	finally
    //   93	97	78	finally
    //   100	114	78	finally
    //   117	119	78	finally
    //   130	143	78	finally
    //   147	153	78	finally
    //   157	171	78	finally
    //   179	197	78	finally
    //   201	203	78	finally
    //   207	209	78	finally
    //   8	25	82	java/lang/Exception
    //   33	37	82	java/lang/Exception
    //   45	53	82	java/lang/Exception
    //   61	72	82	java/lang/Exception
    //   8	25	86	com/google/android/recaptcha/internal/zzbd
    //   33	37	86	com/google/android/recaptcha/internal/zzbd
    //   45	53	86	com/google/android/recaptcha/internal/zzbd
    //   61	72	86	com/google/android/recaptcha/internal/zzbd
    //   157	171	174	java/lang/Exception
  }
  
  /* Error */
  public final String zzb(String paramString)
  {
    // Byte code:
    //   0: new 135	java/net/URL
    //   3: dup
    //   4: aload_1
    //   5: invokespecial 138	java/net/URL:<init>	(Ljava/lang/String;)V
    //   8: astore_1
    //   9: aload_1
    //   10: invokevirtual 142	java/net/URL:openConnection	()Ljava/net/URLConnection;
    //   13: astore_1
    //   14: aload_1
    //   15: ldc -112
    //   17: invokestatic 148	ec/i:c	(Ljava/lang/Object;Ljava/lang/String;)V
    //   20: aload_1
    //   21: checkcast 111	java/net/HttpURLConnection
    //   24: astore_2
    //   25: aload_2
    //   26: ldc -106
    //   28: invokevirtual 153	java/net/HttpURLConnection:setRequestMethod	(Ljava/lang/String;)V
    //   31: aload_2
    //   32: iconst_1
    //   33: invokevirtual 159	java/net/URLConnection:setDoInput	(Z)V
    //   36: aload_2
    //   37: ldc -95
    //   39: ldc -93
    //   41: invokevirtual 167	java/net/URLConnection:setRequestProperty	(Ljava/lang/String;Ljava/lang/String;)V
    //   44: aload_2
    //   45: ldc -87
    //   47: ldc -85
    //   49: invokevirtual 167	java/net/URLConnection:setRequestProperty	(Ljava/lang/String;Ljava/lang/String;)V
    //   52: aload_2
    //   53: invokevirtual 174	java/net/URLConnection:connect	()V
    //   56: aload_2
    //   57: invokevirtual 178	java/net/HttpURLConnection:getResponseCode	()I
    //   60: sipush 200
    //   63: if_icmpne +117 -> 180
    //   66: ldc -85
    //   68: aload_2
    //   69: invokevirtual 181	java/net/URLConnection:getContentEncoding	()Ljava/lang/String;
    //   72: invokestatic 105	ec/i:a	(Ljava/lang/Object;Ljava/lang/Object;)Z
    //   75: ifeq +27 -> 102
    //   78: new 183	java/io/InputStreamReader
    //   81: astore_1
    //   82: new 185	java/util/zip/GZIPInputStream
    //   85: astore_3
    //   86: aload_3
    //   87: aload_2
    //   88: invokevirtual 188	java/net/URLConnection:getInputStream	()Ljava/io/InputStream;
    //   91: invokespecial 191	java/util/zip/GZIPInputStream:<init>	(Ljava/io/InputStream;)V
    //   94: aload_1
    //   95: aload_3
    //   96: invokespecial 192	java/io/InputStreamReader:<init>	(Ljava/io/InputStream;)V
    //   99: goto +15 -> 114
    //   102: new 183	java/io/InputStreamReader
    //   105: dup
    //   106: aload_2
    //   107: invokevirtual 188	java/net/URLConnection:getInputStream	()Ljava/io/InputStream;
    //   110: invokespecial 192	java/io/InputStreamReader:<init>	(Ljava/io/InputStream;)V
    //   113: astore_1
    //   114: new 194	java/io/StringWriter
    //   117: astore_2
    //   118: aload_2
    //   119: invokespecial 195	java/io/StringWriter:<init>	()V
    //   122: sipush 8192
    //   125: newarray <illegal type>
    //   127: astore_3
    //   128: aload_1
    //   129: aload_3
    //   130: invokevirtual 201	java/io/Reader:read	([C)I
    //   133: istore 4
    //   135: iload 4
    //   137: iflt +14 -> 151
    //   140: aload_2
    //   141: aload_3
    //   142: iconst_0
    //   143: iload 4
    //   145: invokevirtual 207	java/io/Writer:write	([CII)V
    //   148: goto -20 -> 128
    //   151: aload_2
    //   152: invokevirtual 210	java/io/StringWriter:toString	()Ljava/lang/String;
    //   155: astore_1
    //   156: aload_1
    //   157: ldc -44
    //   159: invokestatic 215	ec/i:d	(Ljava/lang/Object;Ljava/lang/String;)V
    //   162: aload_1
    //   163: areturn
    //   164: astore_1
    //   165: new 34	com/google/android/recaptcha/internal/zzbd
    //   168: dup
    //   169: getstatic 78	com/google/android/recaptcha/internal/zzbb:zzc	Lcom/google/android/recaptcha/internal/zzbb;
    //   172: getstatic 218	com/google/android/recaptcha/internal/zzba:zzP	Lcom/google/android/recaptcha/internal/zzba;
    //   175: aconst_null
    //   176: invokespecial 93	com/google/android/recaptcha/internal/zzbd:<init>	(Lcom/google/android/recaptcha/internal/zzbb;Lcom/google/android/recaptcha/internal/zzba;Ljava/lang/String;)V
    //   179: athrow
    //   180: new 34	com/google/android/recaptcha/internal/zzbd
    //   183: dup
    //   184: getstatic 78	com/google/android/recaptcha/internal/zzbb:zzc	Lcom/google/android/recaptcha/internal/zzbb;
    //   187: new 80	com/google/android/recaptcha/internal/zzba
    //   190: dup
    //   191: aload_2
    //   192: invokevirtual 178	java/net/HttpURLConnection:getResponseCode	()I
    //   195: invokespecial 221	com/google/android/recaptcha/internal/zzba:<init>	(I)V
    //   198: aconst_null
    //   199: invokespecial 93	com/google/android/recaptcha/internal/zzbd:<init>	(Lcom/google/android/recaptcha/internal/zzbb;Lcom/google/android/recaptcha/internal/zzba;Ljava/lang/String;)V
    //   202: athrow
    //   203: astore_1
    //   204: new 34	com/google/android/recaptcha/internal/zzbd
    //   207: dup
    //   208: getstatic 78	com/google/android/recaptcha/internal/zzbb:zzc	Lcom/google/android/recaptcha/internal/zzbb;
    //   211: getstatic 224	com/google/android/recaptcha/internal/zzba:zzO	Lcom/google/android/recaptcha/internal/zzba;
    //   214: aconst_null
    //   215: invokespecial 93	com/google/android/recaptcha/internal/zzbd:<init>	(Lcom/google/android/recaptcha/internal/zzbb;Lcom/google/android/recaptcha/internal/zzba;Ljava/lang/String;)V
    //   218: athrow
    //   219: astore_1
    //   220: new 34	com/google/android/recaptcha/internal/zzbd
    //   223: dup
    //   224: getstatic 226	com/google/android/recaptcha/internal/zzbb:zzb	Lcom/google/android/recaptcha/internal/zzbb;
    //   227: getstatic 229	com/google/android/recaptcha/internal/zzba:zzN	Lcom/google/android/recaptcha/internal/zzba;
    //   230: aconst_null
    //   231: invokespecial 93	com/google/android/recaptcha/internal/zzbd:<init>	(Lcom/google/android/recaptcha/internal/zzbb;Lcom/google/android/recaptcha/internal/zzba;Ljava/lang/String;)V
    //   234: athrow
    // Local variable table:
    //   start	length	slot	name	signature
    //   0	235	0	this	zzfa
    //   0	235	1	paramString	String
    //   24	168	2	localObject1	Object
    //   85	57	3	localObject2	Object
    //   133	11	4	i	int
    // Exception table:
    //   from	to	target	type
    //   66	99	164	java/lang/Exception
    //   102	114	164	java/lang/Exception
    //   114	128	164	java/lang/Exception
    //   128	135	164	java/lang/Exception
    //   140	148	164	java/lang/Exception
    //   151	162	164	java/lang/Exception
    //   9	56	203	java/lang/Exception
    //   0	9	219	java/lang/Exception
  }
}

/* Location:
 * Qualified Name:     com.google.android.recaptcha.internal.zzfa
 * Java Class Version: 6 (50.0)
 * JD-Core Version:    0.7.1
 */