package com.google.android.recaptcha.internal;

import dc.p;
import ub.e;
import wb.i;

final class zzfh
  extends i
  implements p
{
  public zzfh(zzfj paramzzfj, zzbr paramzzbr, zzsp paramzzsp, e parame)
  {
    super(2, parame);
  }
  
  public final e create(Object paramObject, e parame)
  {
    return new zzfh(zza, zzb, zzc, parame);
  }
  
  /* Error */
  public final Object invokeSuspend(Object paramObject)
  {
    // Byte code:
    //   0: getstatic 55	vb/a:a	Lvb/a;
    //   3: astore_2
    //   4: aload_1
    //   5: invokestatic 61	rb/f:b	(Ljava/lang/Object;)V
    //   8: aconst_null
    //   9: astore_2
    //   10: aconst_null
    //   11: astore_3
    //   12: aconst_null
    //   13: astore_1
    //   14: aload_0
    //   15: getfield 16	com/google/android/recaptcha/internal/zzfh:zza	Lcom/google/android/recaptcha/internal/zzfj;
    //   18: invokestatic 66	com/google/android/recaptcha/internal/zzfj:zza	(Lcom/google/android/recaptcha/internal/zzfj;)Lcom/google/android/recaptcha/internal/zzex;
    //   21: aload_0
    //   22: getfield 18	com/google/android/recaptcha/internal/zzfh:zzb	Lcom/google/android/recaptcha/internal/zzbr;
    //   25: invokevirtual 72	com/google/android/recaptcha/internal/zzbr:zzd	()Ljava/lang/String;
    //   28: invokevirtual 77	com/google/android/recaptcha/internal/zzex:zza	(Ljava/lang/String;)Lcom/google/android/recaptcha/internal/zzew;
    //   31: astore 4
    //   33: aload 4
    //   35: astore_1
    //   36: aload 4
    //   38: astore_2
    //   39: aload 4
    //   41: astore_3
    //   42: aload 4
    //   44: invokevirtual 82	com/google/android/recaptcha/internal/zzew:zzc	()V
    //   47: aload 4
    //   49: astore_1
    //   50: aload 4
    //   52: astore_2
    //   53: aload 4
    //   55: astore_3
    //   56: aload 4
    //   58: aload_0
    //   59: getfield 20	com/google/android/recaptcha/internal/zzfh:zzc	Lcom/google/android/recaptcha/internal/zzsp;
    //   62: invokevirtual 87	com/google/android/recaptcha/internal/zzko:zzd	()[B
    //   65: invokevirtual 91	com/google/android/recaptcha/internal/zzew:zze	([B)V
    //   68: aload 4
    //   70: astore_1
    //   71: aload 4
    //   73: astore_2
    //   74: aload 4
    //   76: astore_3
    //   77: aload 4
    //   79: invokestatic 97	com/google/android/recaptcha/internal/zzsr:zzi	()Lcom/google/android/recaptcha/internal/zzsr;
    //   82: invokevirtual 100	com/google/android/recaptcha/internal/zzew:zza	(Lcom/google/android/recaptcha/internal/zzoi;)Lcom/google/android/recaptcha/internal/zzoi;
    //   85: checkcast 93	com/google/android/recaptcha/internal/zzsr
    //   88: astore 5
    //   90: aload 4
    //   92: invokevirtual 102	com/google/android/recaptcha/internal/zzew:zzd	()V
    //   95: aload 5
    //   97: areturn
    //   98: astore_2
    //   99: goto +43 -> 142
    //   102: astore 4
    //   104: goto +7 -> 111
    //   107: astore_2
    //   108: goto +30 -> 138
    //   111: aload_2
    //   112: astore_1
    //   113: new 48	com/google/android/recaptcha/internal/zzbd
    //   116: astore_3
    //   117: aload_2
    //   118: astore_1
    //   119: aload_3
    //   120: getstatic 107	com/google/android/recaptcha/internal/zzbb:zzc	Lcom/google/android/recaptcha/internal/zzbb;
    //   123: getstatic 113	com/google/android/recaptcha/internal/zzba:zzF	Lcom/google/android/recaptcha/internal/zzba;
    //   126: aload 4
    //   128: invokevirtual 118	java/lang/Throwable:getMessage	()Ljava/lang/String;
    //   131: invokespecial 121	com/google/android/recaptcha/internal/zzbd:<init>	(Lcom/google/android/recaptcha/internal/zzbb;Lcom/google/android/recaptcha/internal/zzba;Ljava/lang/String;)V
    //   134: aload_2
    //   135: astore_1
    //   136: aload_3
    //   137: athrow
    //   138: aload_3
    //   139: astore_1
    //   140: aload_2
    //   141: athrow
    //   142: aload_1
    //   143: ifnull +7 -> 150
    //   146: aload_1
    //   147: invokevirtual 102	com/google/android/recaptcha/internal/zzew:zzd	()V
    //   150: aload_2
    //   151: athrow
    // Local variable table:
    //   start	length	slot	name	signature
    //   0	152	0	this	zzfh
    //   0	152	1	paramObject	Object
    //   3	71	2	localObject1	Object
    //   98	1	2	localObject2	Object
    //   107	44	2	localzzbd	zzbd
    //   11	128	3	localObject3	Object
    //   31	60	4	localzzew	zzew
    //   102	25	4	localException	Exception
    //   88	8	5	localzzsr	zzsr
    // Exception table:
    //   from	to	target	type
    //   14	33	98	finally
    //   42	47	98	finally
    //   56	68	98	finally
    //   77	90	98	finally
    //   113	117	98	finally
    //   119	134	98	finally
    //   136	138	98	finally
    //   140	142	98	finally
    //   14	33	102	java/lang/Exception
    //   42	47	102	java/lang/Exception
    //   56	68	102	java/lang/Exception
    //   77	90	102	java/lang/Exception
    //   14	33	107	com/google/android/recaptcha/internal/zzbd
    //   42	47	107	com/google/android/recaptcha/internal/zzbd
    //   56	68	107	com/google/android/recaptcha/internal/zzbd
    //   77	90	107	com/google/android/recaptcha/internal/zzbd
  }
}

/* Location:
 * Qualified Name:     com.google.android.recaptcha.internal.zzfh
 * Java Class Version: 6 (50.0)
 * JD-Core Version:    0.7.1
 */