package com.google.android.recaptcha.internal;

import java.lang.reflect.Field;
import java.util.AbstractMap;
import java.util.Arrays;
import java.util.HashMap;
import java.util.Iterator;
import java.util.List;
import java.util.Map.Entry;
import sun.misc.Unsafe;

final class zzol<T>
  implements zzow<T>
{
  private static final int[] zza = new int[0];
  private static final Unsafe zzb = zzps.zzg();
  private final int[] zzc;
  private final Object[] zzd;
  private final int zze;
  private final int zzf;
  private final zzoi zzg;
  private final boolean zzh;
  private final boolean zzi;
  private final int[] zzj;
  private final int zzk;
  private final int zzl;
  private final zzpl zzm;
  private final zzmp zzn;
  
  private zzol(int[] paramArrayOfInt1, Object[] paramArrayOfObject, int paramInt1, int paramInt2, zzoi paramzzoi, boolean paramBoolean, int[] paramArrayOfInt2, int paramInt3, int paramInt4, zzoo paramzzoo, zznv paramzznv, zzpl paramzzpl, zzmp paramzzmp, zzod paramzzod)
  {
    zzc = paramArrayOfInt1;
    zzd = paramArrayOfObject;
    zze = paramInt1;
    zzf = paramInt2;
    zzi = (paramzzoi instanceof zznd);
    boolean bool = false;
    paramBoolean = bool;
    if (paramzzmp != null)
    {
      paramBoolean = bool;
      if ((paramzzoi instanceof zzna)) {
        paramBoolean = true;
      }
    }
    zzh = paramBoolean;
    zzj = paramArrayOfInt2;
    zzk = paramInt3;
    zzl = paramInt4;
    zzm = paramzzpl;
    zzn = paramzzmp;
    zzg = paramzzoi;
  }
  
  private final Object zzA(Object paramObject, int paramInt)
  {
    zzow localzzow = zzx(paramInt);
    int i = zzu(paramInt);
    if (!zzN(paramObject, paramInt)) {
      return localzzow.zze();
    }
    long l = i & 0xFFFFF;
    paramObject = zzb.getObject(paramObject, l);
    if (zzQ(paramObject)) {
      return paramObject;
    }
    Object localObject = localzzow.zze();
    if (paramObject != null) {
      localzzow.zzg(localObject, paramObject);
    }
    return localObject;
  }
  
  private final Object zzB(Object paramObject, int paramInt1, int paramInt2)
  {
    zzow localzzow = zzx(paramInt2);
    if (!zzR(paramObject, paramInt1, paramInt2)) {
      return localzzow.zze();
    }
    Object localObject = zzb.getObject(paramObject, zzu(paramInt2) & 0xFFFFF);
    if (zzQ(localObject)) {
      return localObject;
    }
    paramObject = localzzow.zze();
    if (localObject != null) {
      localzzow.zzg(paramObject, localObject);
    }
    return paramObject;
  }
  
  private static Field zzC(Class paramClass, String paramString)
  {
    try
    {
      Field localField = paramClass.getDeclaredField(paramString);
      return localField;
    }
    catch (NoSuchFieldException localNoSuchFieldException)
    {
      for (localObject2 : paramClass.getDeclaredFields()) {
        if (paramString.equals(((Field)localObject2).getName())) {
          return (Field)localObject2;
        }
      }
      paramClass = paramClass.getName();
      ??? = Arrays.toString((Object[])???);
      Object localObject2 = new StringBuilder();
      ((StringBuilder)localObject2).append("Field ");
      ((StringBuilder)localObject2).append(paramString);
      ((StringBuilder)localObject2).append(" for ");
      ((StringBuilder)localObject2).append(paramClass);
      ((StringBuilder)localObject2).append(" not found. Known fields are ");
      ((StringBuilder)localObject2).append((String)???);
      throw new RuntimeException(((StringBuilder)localObject2).toString());
    }
  }
  
  private static void zzD(Object paramObject)
  {
    if (zzQ(paramObject)) {
      return;
    }
    throw new IllegalArgumentException("Mutating immutable message: ".concat(String.valueOf(paramObject)));
  }
  
  private final void zzE(Object paramObject1, Object paramObject2, int paramInt)
  {
    if (!zzN(paramObject2, paramInt)) {
      return;
    }
    int i = zzu(paramInt);
    Unsafe localUnsafe = zzb;
    long l = i & 0xFFFFF;
    Object localObject1 = localUnsafe.getObject(paramObject2, l);
    if (localObject1 != null)
    {
      zzow localzzow = zzx(paramInt);
      if (!zzN(paramObject1, paramInt))
      {
        if (!zzQ(localObject1))
        {
          localUnsafe.putObject(paramObject1, l, localObject1);
        }
        else
        {
          paramObject2 = localzzow.zze();
          localzzow.zzg(paramObject2, localObject1);
          localUnsafe.putObject(paramObject1, l, paramObject2);
        }
        zzH(paramObject1, paramInt);
        return;
      }
      Object localObject2 = localUnsafe.getObject(paramObject1, l);
      paramObject2 = localObject2;
      if (!zzQ(localObject2))
      {
        paramObject2 = localzzow.zze();
        localzzow.zzg(paramObject2, localObject2);
        localUnsafe.putObject(paramObject1, l, paramObject2);
      }
      localzzow.zzg(paramObject2, localObject1);
      return;
    }
    paramInt = zzc[paramInt];
    paramObject2 = paramObject2.toString();
    paramObject1 = new StringBuilder();
    ((StringBuilder)paramObject1).append("Source subfield ");
    ((StringBuilder)paramObject1).append(paramInt);
    ((StringBuilder)paramObject1).append(" is present but null: ");
    ((StringBuilder)paramObject1).append((String)paramObject2);
    throw new IllegalStateException(((StringBuilder)paramObject1).toString());
  }
  
  private final void zzF(Object paramObject1, Object paramObject2, int paramInt)
  {
    int i = zzc[paramInt];
    if (!zzR(paramObject2, i, paramInt)) {
      return;
    }
    int j = zzu(paramInt);
    Unsafe localUnsafe = zzb;
    long l = j & 0xFFFFF;
    Object localObject1 = localUnsafe.getObject(paramObject2, l);
    if (localObject1 != null)
    {
      zzow localzzow = zzx(paramInt);
      if (!zzR(paramObject1, i, paramInt))
      {
        if (!zzQ(localObject1))
        {
          localUnsafe.putObject(paramObject1, l, localObject1);
        }
        else
        {
          paramObject2 = localzzow.zze();
          localzzow.zzg(paramObject2, localObject1);
          localUnsafe.putObject(paramObject1, l, paramObject2);
        }
        zzI(paramObject1, i, paramInt);
        return;
      }
      Object localObject2 = localUnsafe.getObject(paramObject1, l);
      paramObject2 = localObject2;
      if (!zzQ(localObject2))
      {
        paramObject2 = localzzow.zze();
        localzzow.zzg(paramObject2, localObject2);
        localUnsafe.putObject(paramObject1, l, paramObject2);
      }
      localzzow.zzg(paramObject2, localObject1);
      return;
    }
    paramInt = zzc[paramInt];
    paramObject2 = paramObject2.toString();
    paramObject1 = new StringBuilder();
    ((StringBuilder)paramObject1).append("Source subfield ");
    ((StringBuilder)paramObject1).append(paramInt);
    ((StringBuilder)paramObject1).append(" is present but null: ");
    ((StringBuilder)paramObject1).append((String)paramObject2);
    throw new IllegalStateException(((StringBuilder)paramObject1).toString());
  }
  
  private final void zzG(Object paramObject, int paramInt, zzov paramzzov)
  {
    boolean bool = zzM(paramInt);
    long l = paramInt & 0xFFFFF;
    if (bool) {
      paramzzov = paramzzov.zzs();
    }
    for (;;)
    {
      zzps.zzs(paramObject, l, paramzzov);
      return;
      if (zzi) {
        paramzzov = paramzzov.zzr();
      } else {
        paramzzov = paramzzov.zzp();
      }
    }
  }
  
  private final void zzH(Object paramObject, int paramInt)
  {
    paramInt = zzr(paramInt);
    long l = 0xFFFFF & paramInt;
    if (l == 1048575L) {
      return;
    }
    zzps.zzq(paramObject, l, 1 << (paramInt >>> 20) | zzps.zzc(paramObject, l));
  }
  
  private final void zzI(Object paramObject, int paramInt1, int paramInt2)
  {
    zzps.zzq(paramObject, zzr(paramInt2) & 0xFFFFF, paramInt1);
  }
  
  private final void zzJ(Object paramObject1, int paramInt, Object paramObject2)
  {
    zzb.putObject(paramObject1, zzu(paramInt) & 0xFFFFF, paramObject2);
    zzH(paramObject1, paramInt);
  }
  
  private final void zzK(Object paramObject1, int paramInt1, int paramInt2, Object paramObject2)
  {
    zzb.putObject(paramObject1, zzu(paramInt2) & 0xFFFFF, paramObject2);
    zzI(paramObject1, paramInt1, paramInt2);
  }
  
  private final boolean zzL(Object paramObject1, Object paramObject2, int paramInt)
  {
    return zzN(paramObject1, paramInt) == zzN(paramObject2, paramInt);
  }
  
  private static boolean zzM(int paramInt)
  {
    return (paramInt & 0x20000000) != 0;
  }
  
  private final boolean zzN(Object paramObject, int paramInt)
  {
    int i = zzr(paramInt);
    long l = i & 0xFFFFF;
    if (l == 1048575L)
    {
      paramInt = zzu(paramInt);
      i = zzt(paramInt);
      l = paramInt & 0xFFFFF;
      switch (i)
      {
      default: 
        throw new IllegalArgumentException();
      case 17: 
        return zzps.zzf(paramObject, l) != null;
      case 16: 
        return zzps.zzd(paramObject, l) != 0L;
      case 15: 
        return zzps.zzc(paramObject, l) != 0;
      case 14: 
        return zzps.zzd(paramObject, l) != 0L;
      case 13: 
        return zzps.zzc(paramObject, l) != 0;
      case 12: 
        return zzps.zzc(paramObject, l) != 0;
      case 11: 
        return zzps.zzc(paramObject, l) != 0;
      case 10: 
        return !zzle.zzb.equals(zzps.zzf(paramObject, l));
      case 9: 
        return zzps.zzf(paramObject, l) != null;
      case 8: 
        paramObject = zzps.zzf(paramObject, l);
        if ((paramObject instanceof String)) {
          return !((String)paramObject).isEmpty();
        }
        if ((paramObject instanceof zzle)) {
          return !zzle.zzb.equals(paramObject);
        }
        throw new IllegalArgumentException();
      case 7: 
        return zzps.zzw(paramObject, l);
      case 6: 
        return zzps.zzc(paramObject, l) != 0;
      case 5: 
        return zzps.zzd(paramObject, l) != 0L;
      case 4: 
        return zzps.zzc(paramObject, l) != 0;
      case 3: 
        return zzps.zzd(paramObject, l) != 0L;
      case 2: 
        return zzps.zzd(paramObject, l) != 0L;
      case 1: 
        return Float.floatToRawIntBits(zzps.zzb(paramObject, l)) != 0;
      }
      return Double.doubleToRawLongBits(zzps.zza(paramObject, l)) != 0L;
    }
    return (zzps.zzc(paramObject, l) & 1 << (i >>> 20)) != 0;
  }
  
  private final boolean zzO(Object paramObject, int paramInt1, int paramInt2, int paramInt3, int paramInt4)
  {
    if (paramInt2 == 1048575) {
      return zzN(paramObject, paramInt1);
    }
    return (paramInt3 & paramInt4) != 0;
  }
  
  private static boolean zzP(Object paramObject, int paramInt, zzow paramzzow)
  {
    return paramzzow.zzl(zzps.zzf(paramObject, paramInt & 0xFFFFF));
  }
  
  private static boolean zzQ(Object paramObject)
  {
    if (paramObject == null) {
      return false;
    }
    if ((paramObject instanceof zznd)) {
      return ((zznd)paramObject).zzL();
    }
    return true;
  }
  
  private final boolean zzR(Object paramObject, int paramInt1, int paramInt2)
  {
    return zzps.zzc(paramObject, zzr(paramInt2) & 0xFFFFF) == paramInt1;
  }
  
  private static boolean zzS(Object paramObject, long paramLong)
  {
    return ((Boolean)zzps.zzf(paramObject, paramLong)).booleanValue();
  }
  
  private static final void zzT(int paramInt, Object paramObject, zzpy paramzzpy)
  {
    if ((paramObject instanceof String))
    {
      paramzzpy.zzG(paramInt, (String)paramObject);
      return;
    }
    paramzzpy.zzd(paramInt, (zzle)paramObject);
  }
  
  public static zzpm zzd(Object paramObject)
  {
    zznd localzznd = (zznd)paramObject;
    zzpm localzzpm = zzc;
    paramObject = localzzpm;
    if (localzzpm == zzpm.zzc())
    {
      paramObject = zzpm.zzf();
      zzc = ((zzpm)paramObject);
    }
    return (zzpm)paramObject;
  }
  
  public static zzol zzm(Class paramClass, zzof paramzzof, zzoo paramzzoo, zznv paramzznv, zzpl paramzzpl, zzmp paramzzmp, zzod paramzzod)
  {
    if ((paramzzof instanceof zzou))
    {
      zzou localzzou = (zzou)paramzzof;
      paramClass = localzzou.zzd();
      int i = paramClass.length();
      if (paramClass.charAt(0) >= 55296) {
        for (j = 1;; j = k)
        {
          k = j + 1;
          m = k;
          if (paramClass.charAt(j) < 55296) {
            break;
          }
        }
      }
      int m = 1;
      int j = m + 1;
      int k = paramClass.charAt(m);
      int n = j;
      m = k;
      int i1;
      if (k >= 55296)
      {
        k &= 0x1FFF;
        m = 13;
        for (i1 = j;; i1 = j)
        {
          j = i1 + 1;
          i1 = paramClass.charAt(i1);
          if (i1 < 55296) {
            break;
          }
          k |= (i1 & 0x1FFF) << m;
          m += 13;
        }
        m = k | i1 << m;
        n = j;
      }
      int i3;
      int i4;
      int i6;
      if (m == 0)
      {
        paramzzof = zza;
        k = 0;
        i2 = k;
        m = i2;
        j = m;
        i3 = j;
        i1 = i3;
        i4 = i1;
      }
      else
      {
        m = n + 1;
        i1 = paramClass.charAt(n);
        j = i1;
        k = m;
        if (i1 >= 55296)
        {
          k = i1 & 0x1FFF;
          j = 13;
          for (i1 = m;; i1 = m)
          {
            m = i1 + 1;
            i1 = paramClass.charAt(i1);
            if (i1 < 55296) {
              break;
            }
            k |= (i1 & 0x1FFF) << j;
            j += 13;
          }
          j = k | i1 << j;
          k = m;
        }
        m = k + 1;
        k = paramClass.charAt(k);
        i5 = k;
        i1 = m;
        if (k >= 55296)
        {
          i1 = k & 0x1FFF;
          k = 13;
          for (i2 = m;; i2 = m)
          {
            m = i2 + 1;
            i2 = paramClass.charAt(i2);
            if (i2 < 55296) {
              break;
            }
            i1 |= (i2 & 0x1FFF) << k;
            k += 13;
          }
          i5 = i1 | i2 << k;
          i1 = m;
        }
        k = i1 + 1;
        i1 = paramClass.charAt(i1);
        m = i1;
        i2 = k;
        if (i1 >= 55296)
        {
          i1 &= 0x1FFF;
          m = 13;
          for (i2 = k;; i2 = k)
          {
            k = i2 + 1;
            i2 = paramClass.charAt(i2);
            if (i2 < 55296) {
              break;
            }
            i1 |= (i2 & 0x1FFF) << m;
            m += 13;
          }
          m = i1 | i2 << m;
          i2 = k;
        }
        i1 = i2 + 1;
        n = paramClass.charAt(i2);
        k = n;
        i2 = i1;
        if (n >= 55296)
        {
          i2 = n & 0x1FFF;
          k = 13;
          for (n = i1;; n = i1)
          {
            i1 = n + 1;
            n = paramClass.charAt(n);
            if (n < 55296) {
              break;
            }
            i2 |= (n & 0x1FFF) << k;
            k += 13;
          }
          k = i2 | n << k;
          i2 = i1;
        }
        i1 = i2 + 1;
        i3 = paramClass.charAt(i2);
        i2 = i3;
        n = i1;
        if (i3 >= 55296)
        {
          n = i3 & 0x1FFF;
          i2 = 13;
          for (i3 = i1;; i3 = i1)
          {
            i1 = i3 + 1;
            i3 = paramClass.charAt(i3);
            if (i3 < 55296) {
              break;
            }
            n |= (i3 & 0x1FFF) << i2;
            i2 += 13;
          }
          i2 = n | i3 << i2;
          n = i1;
        }
        i1 = n + 1;
        i6 = paramClass.charAt(n);
        n = i6;
        i3 = i1;
        if (i6 >= 55296)
        {
          i3 = i6 & 0x1FFF;
          n = 13;
          for (i6 = i1;; i6 = i1)
          {
            i1 = i6 + 1;
            i6 = paramClass.charAt(i6);
            if (i6 < 55296) {
              break;
            }
            i3 |= (i6 & 0x1FFF) << n;
            n += 13;
          }
          n = i3 | i6 << n;
          i3 = i1;
        }
        i1 = i3 + 1;
        i4 = paramClass.charAt(i3);
        i6 = i4;
        i3 = i1;
        if (i4 >= 55296)
        {
          i6 = i4 & 0x1FFF;
          i3 = 13;
          for (i4 = i1;; i4 = i1)
          {
            i1 = i4 + 1;
            i4 = paramClass.charAt(i4);
            if (i4 < 55296) {
              break;
            }
            i6 |= (i4 & 0x1FFF) << i3;
            i3 += 13;
          }
          i6 |= i4 << i3;
          i3 = i1;
        }
        i4 = i3 + 1;
        i7 = paramClass.charAt(i3);
        i3 = i7;
        i1 = i4;
        if (i7 >= 55296)
        {
          i1 = i7 & 0x1FFF;
          i3 = 13;
          i7 = i4;
          i4 = i1;
          for (;;)
          {
            i1 = i7 + 1;
            i7 = paramClass.charAt(i7);
            if (i7 < 55296) {
              break;
            }
            i4 |= (i7 & 0x1FFF) << i3;
            i3 += 13;
            i7 = i1;
          }
          i3 = i4 | i7 << i3;
        }
        paramzzof = new int[i3 + n + i6];
        i6 = j + j + i5;
        i4 = j;
        i5 = i1;
        i1 = i3;
        i3 = k;
        j = m;
        m = n;
        k = i6;
        n = i5;
      }
      Unsafe localUnsafe = zzb;
      Object[] arrayOfObject1 = localzzou.zze();
      Class localClass = localzzou.zza().getClass();
      int i8 = i1 + m;
      int[] arrayOfInt = new int[i2 * 3];
      Object[] arrayOfObject2 = new Object[i2 + i2];
      m = i1;
      int i2 = i8;
      int i5 = 0;
      int i9 = 0;
      int i7 = i3;
      while (n < i)
      {
        int i10 = n + 1;
        i3 = paramClass.charAt(n);
        if (i3 >= 55296)
        {
          i6 = i3 & 0x1FFF;
          n = 13;
          for (;;)
          {
            i3 = i10 + 1;
            i10 = paramClass.charAt(i10);
            if (i10 < 55296) {
              break;
            }
            i6 |= (i10 & 0x1FFF) << n;
            n += 13;
            i10 = i3;
          }
          i10 = i6 | i10 << n;
          n = i3;
        }
        else
        {
          n = i10;
          i10 = i3;
        }
        int i11 = n + 1;
        int i12 = paramClass.charAt(n);
        if (i12 >= 55296)
        {
          i6 = i12 & 0x1FFF;
          n = 13;
          for (;;)
          {
            i3 = i11 + 1;
            i11 = paramClass.charAt(i11);
            if (i11 < 55296) {
              break;
            }
            i6 |= (i11 & 0x1FFF) << n;
            n += 13;
            i11 = i3;
          }
          i12 = i6 | i11 << n;
        }
        else
        {
          i3 = i11;
        }
        i11 = i5;
        if ((i12 & 0x400) != 0)
        {
          paramzzof[i5] = i9;
          i11 = i5 + 1;
        }
        int i13 = i12 & 0xFF;
        n = i12 & 0x800;
        int i14;
        int i15;
        label1683:
        Object localObject;
        if (i13 >= 51)
        {
          i5 = i3 + 1;
          i14 = paramClass.charAt(i3);
          if (i14 >= 55296)
          {
            i6 = i14 & 0x1FFF;
            i3 = 13;
            for (i14 = i5;; i14 = i5)
            {
              i5 = i14 + 1;
              i14 = paramClass.charAt(i14);
              if (i14 < 55296) {
                break;
              }
              i6 |= (i14 & 0x1FFF) << i3;
              i3 += 13;
            }
            i14 = i6 | i14 << i3;
            i3 = i5;
          }
          else
          {
            i3 = i5;
          }
          i15 = i13 - 51;
          if ((i15 != 9) && (i15 != 17))
          {
            i5 = n;
            i6 = k;
            if (i15 != 12) {
              break label1683;
            }
            if ((localzzou.zzc() != 1) && (n == 0))
            {
              i5 = 0;
              i6 = k;
              break label1683;
            }
            i5 = k + 1;
            i6 = i9 / 3;
            arrayOfObject2[(i6 + i6 + 1)] = arrayOfObject1[k];
            k = i5;
          }
          else
          {
            i5 = k + 1;
            i6 = i9 / 3;
            arrayOfObject2[(i6 + i6 + 1)] = arrayOfObject1[k];
            k = i5;
          }
          i6 = k;
          i5 = n;
          k = i14 + i14;
          localObject = arrayOfObject1[k];
          if ((localObject instanceof Field))
          {
            localObject = (Field)localObject;
          }
          else
          {
            localObject = zzC(localClass, (String)localObject);
            arrayOfObject1[k] = localObject;
          }
          i14 = (int)localUnsafe.objectFieldOffset((Field)localObject);
          k++;
          localObject = arrayOfObject1[k];
          if ((localObject instanceof Field))
          {
            localObject = (Field)localObject;
          }
          else
          {
            localObject = zzC(localClass, (String)localObject);
            arrayOfObject1[k] = localObject;
          }
          i15 = (int)localUnsafe.objectFieldOffset((Field)localObject);
          n = i6;
          k = i3;
          i6 = i15;
          i3 = 0;
          i15 = i5;
          i5 = i6;
          i6 = i2;
          i2 = k;
          k = j;
        }
        else
        {
          i14 = j;
          i5 = k + 1;
          Field localField = zzC(localClass, (String)arrayOfObject1[k]);
          if ((i13 != 9) && (i13 != 17))
          {
            if (i13 != 27)
            {
              if (i13 == 49)
              {
                j = i5 + 1;
              }
              else
              {
                if ((i13 != 12) && (i13 != 30) && (i13 != 44))
                {
                  if (i13 == 50)
                  {
                    k = i5 + 1;
                    j = m + 1;
                    paramzzof[m] = i9;
                    m = i9 / 3;
                    localObject = arrayOfObject1[i5];
                    m += m;
                    arrayOfObject2[m] = localObject;
                    if (n != 0)
                    {
                      i5 = k + 1;
                      arrayOfObject2[(m + 1)] = arrayOfObject1[k];
                      m = j;
                      k = n;
                      j = i5;
                      break label2171;
                    }
                    m = k;
                    n = j;
                    k = 0;
                    j = m;
                    m = n;
                    break label2171;
                  }
                  k = n;
                  j = i5;
                  break label2171;
                }
                if ((localzzou.zzc() != 1) && (n == 0))
                {
                  k = 0;
                  j = i5;
                  break label2171;
                }
                j = i5 + 1;
                k = i9 / 3;
                arrayOfObject2[(k + k + 1)] = arrayOfObject1[i5];
                break label2135;
              }
            }
            else {
              j = i5 + 1;
            }
            k = i9 / 3;
            arrayOfObject2[(k + k + 1)] = arrayOfObject1[i5];
            label2135:
            k = n;
          }
          else
          {
            j = i9 / 3;
            arrayOfObject2[(j + j + 1)] = localField.getType();
            j = i5;
            k = n;
          }
          label2171:
          localObject = paramClass;
          i16 = (int)localUnsafe.objectFieldOffset(localField);
          i5 = 1048575;
          if (((i12 & 0x1000) != 0) && (i13 <= 17))
          {
            n = i3 + 1;
            i3 = ((String)localObject).charAt(i3);
            if (i3 >= 55296)
            {
              i5 = i3 & 0x1FFF;
              i3 = 13;
              for (i6 = n;; i6 = n)
              {
                n = i6 + 1;
                i6 = ((String)localObject).charAt(i6);
                if (i6 < 55296) {
                  break;
                }
                i5 |= (i6 & 0x1FFF) << i3;
                i3 += 13;
              }
              i3 = i5 | i6 << i3;
            }
            i5 = i3 / 32 + (i4 + i4);
            localObject = arrayOfObject1[i5];
            if ((localObject instanceof Field))
            {
              localObject = (Field)localObject;
            }
            else
            {
              localObject = zzC(localClass, (String)localObject);
              arrayOfObject1[i5] = localObject;
            }
            i5 = (int)localUnsafe.objectFieldOffset((Field)localObject);
            i3 %= 32;
          }
          else
          {
            n = i3;
            i3 = 0;
          }
          i6 = i2;
          if (i13 >= 18)
          {
            i6 = i2;
            if (i13 <= 49)
            {
              paramzzof[i2] = i16;
              i6 = i2 + 1;
            }
          }
          i15 = k;
          k = i14;
          i2 = n;
          n = j;
          i14 = i16;
        }
        int i16 = i9 + 1;
        arrayOfInt[i9] = i10;
        int i17 = i16 + 1;
        if ((i12 & 0x200) != 0) {
          j = 536870912;
        } else {
          j = 0;
        }
        if ((i12 & 0x100) != 0) {
          i9 = 268435456;
        } else {
          i9 = 0;
        }
        if (i15 != 0) {
          i10 = Integer.MIN_VALUE;
        } else {
          i10 = 0;
        }
        arrayOfInt[i16] = (i14 | j | i9 | i10 | i13 << 20);
        i9 = i17 + 1;
        arrayOfInt[i17] = (i3 << 20 | i5);
        j = n;
        n = i2;
        i2 = k;
        k = j;
        j = i2;
        i5 = i11;
        i2 = i6;
      }
      return new zzol(arrayOfInt, arrayOfObject2, j, i7, localzzou.zza(), false, paramzzof, i1, i8, paramzzoo, paramzznv, paramzzpl, paramzzmp, paramzzod);
    }
    paramClass = (zzpf)paramzzof;
    throw null;
  }
  
  private static double zzn(Object paramObject, long paramLong)
  {
    return ((Double)zzps.zzf(paramObject, paramLong)).doubleValue();
  }
  
  private static float zzo(Object paramObject, long paramLong)
  {
    return ((Float)zzps.zzf(paramObject, paramLong)).floatValue();
  }
  
  private static int zzp(Object paramObject, long paramLong)
  {
    return ((Integer)zzps.zzf(paramObject, paramLong)).intValue();
  }
  
  private final int zzq(int paramInt)
  {
    if ((paramInt >= zze) && (paramInt <= zzf)) {
      return zzs(paramInt, 0);
    }
    return -1;
  }
  
  private final int zzr(int paramInt)
  {
    return zzc[(paramInt + 2)];
  }
  
  private final int zzs(int paramInt1, int paramInt2)
  {
    int i = zzc.length / 3 - 1;
    while (paramInt2 <= i)
    {
      int j = i + paramInt2 >>> 1;
      int k = j * 3;
      int m = zzc[k];
      if (paramInt1 == m) {
        return k;
      }
      if (paramInt1 < m) {
        i = j - 1;
      } else {
        paramInt2 = j + 1;
      }
    }
    return -1;
  }
  
  private static int zzt(int paramInt)
  {
    return paramInt >>> 20 & 0xFF;
  }
  
  private final int zzu(int paramInt)
  {
    return zzc[(paramInt + 1)];
  }
  
  private static long zzv(Object paramObject, long paramLong)
  {
    return ((Long)zzps.zzf(paramObject, paramLong)).longValue();
  }
  
  private final zznh zzw(int paramInt)
  {
    paramInt /= 3;
    return (zznh)zzd[(paramInt + paramInt + 1)];
  }
  
  private final zzow zzx(int paramInt)
  {
    Object localObject = zzd;
    paramInt /= 3;
    paramInt += paramInt;
    zzow localzzow = (zzow)localObject[paramInt];
    if (localzzow != null) {
      return localzzow;
    }
    localObject = zzos.zza().zzb((Class)localObject[(paramInt + 1)]);
    zzd[paramInt] = localObject;
    return (zzow)localObject;
  }
  
  private final Object zzy(Object paramObject1, int paramInt, Object paramObject2, zzpl paramzzpl, Object paramObject3)
  {
    int i = zzc[paramInt];
    paramObject1 = zzps.zzf(paramObject1, zzu(paramInt) & 0xFFFFF);
    if ((paramObject1 == null) || (zzw(paramInt) == null)) {
      return paramObject2;
    }
    paramObject1 = (zzoc)paramObject1;
    paramObject1 = (zzob)zzz(paramInt);
    throw null;
  }
  
  private final Object zzz(int paramInt)
  {
    paramInt /= 3;
    return zzd[(paramInt + paramInt)];
  }
  
  /* Error */
  public final int zza(Object paramObject)
  {
    // Byte code:
    //   0: getstatic 40	com/google/android/recaptcha/internal/zzol:zzb	Lsun/misc/Unsafe;
    //   3: astore_2
    //   4: iconst_0
    //   5: istore_3
    //   6: iload_3
    //   7: istore 4
    //   9: iload 4
    //   11: istore 5
    //   13: ldc 91
    //   15: istore 6
    //   17: iload 4
    //   19: istore 7
    //   21: iconst_0
    //   22: istore 8
    //   24: iconst_0
    //   25: istore 9
    //   27: iconst_0
    //   28: istore 10
    //   30: iconst_0
    //   31: istore 11
    //   33: iconst_0
    //   34: istore 12
    //   36: iconst_0
    //   37: istore 13
    //   39: iload 7
    //   41: aload_0
    //   42: getfield 47	com/google/android/recaptcha/internal/zzol:zzc	[I
    //   45: arraylength
    //   46: if_icmpge +3062 -> 3108
    //   49: aload_0
    //   50: iload 7
    //   52: invokespecial 83	com/google/android/recaptcha/internal/zzol:zzu	(I)I
    //   55: istore 14
    //   57: iload 14
    //   59: invokestatic 244	com/google/android/recaptcha/internal/zzol:zzt	(I)I
    //   62: istore 15
    //   64: aload_0
    //   65: getfield 47	com/google/android/recaptcha/internal/zzol:zzc	[I
    //   68: astore 16
    //   70: aload 16
    //   72: iload 7
    //   74: iaload
    //   75: istore 17
    //   77: aload 16
    //   79: iload 7
    //   81: iconst_2
    //   82: iadd
    //   83: iaload
    //   84: istore 18
    //   86: iload 18
    //   88: ldc 91
    //   90: iand
    //   91: istore 19
    //   93: iload 15
    //   95: bipush 17
    //   97: if_icmpgt +62 -> 159
    //   100: iload 6
    //   102: istore 4
    //   104: iload 19
    //   106: iload 6
    //   108: if_icmpeq +28 -> 136
    //   111: iload 19
    //   113: ldc 91
    //   115: if_icmpne +8 -> 123
    //   118: iconst_0
    //   119: istore_3
    //   120: goto +12 -> 132
    //   123: aload_2
    //   124: aload_1
    //   125: iload 19
    //   127: i2l
    //   128: invokevirtual 409	sun/misc/Unsafe:getInt	(Ljava/lang/Object;J)I
    //   131: istore_3
    //   132: iload 19
    //   134: istore 4
    //   136: iconst_1
    //   137: iload 18
    //   139: bipush 20
    //   141: iushr
    //   142: ishl
    //   143: istore 6
    //   145: iload 4
    //   147: istore 19
    //   149: iload_3
    //   150: istore 18
    //   152: iload 6
    //   154: istore 4
    //   156: goto +13 -> 169
    //   159: iconst_0
    //   160: istore 4
    //   162: iload_3
    //   163: istore 18
    //   165: iload 6
    //   167: istore 19
    //   169: iload 15
    //   171: getstatic 414	com/google/android/recaptcha/internal/zzmu:zzJ	Lcom/google/android/recaptcha/internal/zzmu;
    //   174: invokevirtual 416	com/google/android/recaptcha/internal/zzmu:zza	()I
    //   177: if_icmplt +10 -> 187
    //   180: getstatic 419	com/google/android/recaptcha/internal/zzmu:zzW	Lcom/google/android/recaptcha/internal/zzmu;
    //   183: invokevirtual 416	com/google/android/recaptcha/internal/zzmu:zza	()I
    //   186: pop
    //   187: ldc 91
    //   189: iload 14
    //   191: iand
    //   192: i2l
    //   193: lstore 20
    //   195: iload 15
    //   197: tableswitch	default:+291->488, 0:+2859->3056, 1:+2829->3026, 2:+2773->2970, 3:+2754->2951, 4:+2717->2914, 5:+2698->2895, 6:+2679->2876, 7:+2649->2846, 8:+2533->2730, 9:+2483->2680, 10:+2449->2646, 11:+2398->2595, 12:+2379->2576, 13:+2360->2557, 14:+2341->2538, 15:+2284->2481, 16:+2230->2427, 17:+2184->2381, 18:+2163->2360, 19:+2142->2339, 20:+2069->2266, 21:+2005->2202, 22:+1953->2150, 23:+2163->2360, 24:+2142->2339, 25:+1898->2095, 26:+1681->1878, 27:+1548->1745, 28:+1443->1640, 29:+1391->1588, 30:+1339->1536, 31:+2142->2339, 32:+2163->2360, 33:+1287->1484, 34:+1235->1432, 35:+1194->1391, 36:+1171->1368, 37:+1148->1345, 38:+1125->1322, 39:+1102->1299, 40:+1079->1276, 41:+1056->1253, 42:+1022->1219, 43:+999->1196, 44:+976->1173, 45:+953->1150, 46:+930->1127, 47:+907->1104, 48:+884->1081, 49:+791->988, 50:+700->897, 51:+685->882, 52:+670->867, 53:+641->838, 54:+626->823, 55:+598->795, 56:+583->780, 57:+568->765, 58:+553->750, 59:+502->699, 60:+478->675, 61:+448->645, 62:+420->617, 63:+405->602, 64:+390->587, 65:+375->572, 66:+347->544, 67:+318->515, 68:+294->491
    //   488: goto +941 -> 1429
    //   491: aload_0
    //   492: aload_1
    //   493: iload 17
    //   495: iload 7
    //   497: invokespecial 110	com/google/android/recaptcha/internal/zzol:zzR	(Ljava/lang/Object;II)Z
    //   500: ifeq +929 -> 1429
    //   503: aload_2
    //   504: aload_1
    //   505: lload 20
    //   507: invokevirtual 97	sun/misc/Unsafe:getObject	(Ljava/lang/Object;J)Ljava/lang/Object;
    //   510: astore 16
    //   512: goto +1894 -> 2406
    //   515: aload_0
    //   516: aload_1
    //   517: iload 17
    //   519: iload 7
    //   521: invokespecial 110	com/google/android/recaptcha/internal/zzol:zzR	(Ljava/lang/Object;II)Z
    //   524: ifeq +905 -> 1429
    //   527: iload 17
    //   529: iconst_3
    //   530: ishl
    //   531: istore 4
    //   533: aload_1
    //   534: lload 20
    //   536: invokestatic 421	com/google/android/recaptcha/internal/zzol:zzv	(Ljava/lang/Object;J)J
    //   539: lstore 20
    //   541: goto +1917 -> 2458
    //   544: aload_0
    //   545: aload_1
    //   546: iload 17
    //   548: iload 7
    //   550: invokespecial 110	com/google/android/recaptcha/internal/zzol:zzR	(Ljava/lang/Object;II)Z
    //   553: ifeq +876 -> 1429
    //   556: iload 17
    //   558: iconst_3
    //   559: ishl
    //   560: istore_3
    //   561: aload_1
    //   562: lload 20
    //   564: invokestatic 423	com/google/android/recaptcha/internal/zzol:zzp	(Ljava/lang/Object;J)I
    //   567: istore 4
    //   569: goto +1942 -> 2511
    //   572: aload_0
    //   573: aload_1
    //   574: iload 17
    //   576: iload 7
    //   578: invokespecial 110	com/google/android/recaptcha/internal/zzol:zzR	(Ljava/lang/Object;II)Z
    //   581: ifeq +848 -> 1429
    //   584: goto +310 -> 894
    //   587: aload_0
    //   588: aload_1
    //   589: iload 17
    //   591: iload 7
    //   593: invokespecial 110	com/google/android/recaptcha/internal/zzol:zzR	(Ljava/lang/Object;II)Z
    //   596: ifeq +833 -> 1429
    //   599: goto +280 -> 879
    //   602: aload_0
    //   603: aload_1
    //   604: iload 17
    //   606: iload 7
    //   608: invokespecial 110	com/google/android/recaptcha/internal/zzol:zzR	(Ljava/lang/Object;II)Z
    //   611: ifeq +818 -> 1429
    //   614: goto +193 -> 807
    //   617: aload_0
    //   618: aload_1
    //   619: iload 17
    //   621: iload 7
    //   623: invokespecial 110	com/google/android/recaptcha/internal/zzol:zzR	(Ljava/lang/Object;II)Z
    //   626: ifeq +803 -> 1429
    //   629: iload 17
    //   631: iconst_3
    //   632: ishl
    //   633: istore_3
    //   634: aload_1
    //   635: lload 20
    //   637: invokestatic 423	com/google/android/recaptcha/internal/zzol:zzp	(Ljava/lang/Object;J)I
    //   640: istore 4
    //   642: goto +1983 -> 2625
    //   645: aload_0
    //   646: aload_1
    //   647: iload 17
    //   649: iload 7
    //   651: invokespecial 110	com/google/android/recaptcha/internal/zzol:zzR	(Ljava/lang/Object;II)Z
    //   654: ifeq +775 -> 1429
    //   657: iload 17
    //   659: iconst_3
    //   660: ishl
    //   661: istore 4
    //   663: aload_2
    //   664: aload_1
    //   665: lload 20
    //   667: invokevirtual 97	sun/misc/Unsafe:getObject	(Ljava/lang/Object;J)Ljava/lang/Object;
    //   670: astore 16
    //   672: goto +2110 -> 2782
    //   675: aload_0
    //   676: aload_1
    //   677: iload 17
    //   679: iload 7
    //   681: invokespecial 110	com/google/android/recaptcha/internal/zzol:zzR	(Ljava/lang/Object;II)Z
    //   684: ifeq +745 -> 1429
    //   687: aload_2
    //   688: aload_1
    //   689: lload 20
    //   691: invokevirtual 97	sun/misc/Unsafe:getObject	(Ljava/lang/Object;J)Ljava/lang/Object;
    //   694: astore 16
    //   696: goto +2009 -> 2705
    //   699: aload_0
    //   700: aload_1
    //   701: iload 17
    //   703: iload 7
    //   705: invokespecial 110	com/google/android/recaptcha/internal/zzol:zzR	(Ljava/lang/Object;II)Z
    //   708: ifeq +721 -> 1429
    //   711: iload 17
    //   713: iconst_3
    //   714: ishl
    //   715: istore_3
    //   716: aload_2
    //   717: aload_1
    //   718: lload 20
    //   720: invokevirtual 97	sun/misc/Unsafe:getObject	(Ljava/lang/Object;J)Ljava/lang/Object;
    //   723: astore 22
    //   725: iload_3
    //   726: istore 4
    //   728: aload 22
    //   730: astore 16
    //   732: aload 22
    //   734: instanceof 252
    //   737: ifeq +2086 -> 2823
    //   740: iload_3
    //   741: istore 4
    //   743: aload 22
    //   745: astore 16
    //   747: goto +2035 -> 2782
    //   750: aload_0
    //   751: aload_1
    //   752: iload 17
    //   754: iload 7
    //   756: invokespecial 110	com/google/android/recaptcha/internal/zzol:zzR	(Ljava/lang/Object;II)Z
    //   759: ifeq +670 -> 1429
    //   762: goto +2100 -> 2862
    //   765: aload_0
    //   766: aload_1
    //   767: iload 17
    //   769: iload 7
    //   771: invokespecial 110	com/google/android/recaptcha/internal/zzol:zzR	(Ljava/lang/Object;II)Z
    //   774: ifeq +655 -> 1429
    //   777: goto +102 -> 879
    //   780: aload_0
    //   781: aload_1
    //   782: iload 17
    //   784: iload 7
    //   786: invokespecial 110	com/google/android/recaptcha/internal/zzol:zzR	(Ljava/lang/Object;II)Z
    //   789: ifeq +640 -> 1429
    //   792: goto +102 -> 894
    //   795: aload_0
    //   796: aload_1
    //   797: iload 17
    //   799: iload 7
    //   801: invokespecial 110	com/google/android/recaptcha/internal/zzol:zzR	(Ljava/lang/Object;II)Z
    //   804: ifeq +625 -> 1429
    //   807: iload 17
    //   809: iconst_3
    //   810: ishl
    //   811: istore 4
    //   813: aload_1
    //   814: lload 20
    //   816: invokestatic 423	com/google/android/recaptcha/internal/zzol:zzp	(Ljava/lang/Object;J)I
    //   819: istore_3
    //   820: goto +2124 -> 2944
    //   823: aload_0
    //   824: aload_1
    //   825: iload 17
    //   827: iload 7
    //   829: invokespecial 110	com/google/android/recaptcha/internal/zzol:zzR	(Ljava/lang/Object;II)Z
    //   832: ifeq +597 -> 1429
    //   835: goto +15 -> 850
    //   838: aload_0
    //   839: aload_1
    //   840: iload 17
    //   842: iload 7
    //   844: invokespecial 110	com/google/android/recaptcha/internal/zzol:zzR	(Ljava/lang/Object;II)Z
    //   847: ifeq +582 -> 1429
    //   850: iload 17
    //   852: iconst_3
    //   853: ishl
    //   854: istore 4
    //   856: aload_1
    //   857: lload 20
    //   859: invokestatic 421	com/google/android/recaptcha/internal/zzol:zzv	(Ljava/lang/Object;J)J
    //   862: lstore 20
    //   864: goto +2137 -> 3001
    //   867: aload_0
    //   868: aload_1
    //   869: iload 17
    //   871: iload 7
    //   873: invokespecial 110	com/google/android/recaptcha/internal/zzol:zzR	(Ljava/lang/Object;II)Z
    //   876: ifeq +553 -> 1429
    //   879: goto +2163 -> 3042
    //   882: aload_0
    //   883: aload_1
    //   884: iload 17
    //   886: iload 7
    //   888: invokespecial 110	com/google/android/recaptcha/internal/zzol:zzR	(Ljava/lang/Object;II)Z
    //   891: ifeq +538 -> 1429
    //   894: goto +2178 -> 3072
    //   897: aload_2
    //   898: aload_1
    //   899: lload 20
    //   901: invokevirtual 97	sun/misc/Unsafe:getObject	(Ljava/lang/Object;J)Ljava/lang/Object;
    //   904: astore 22
    //   906: aload_0
    //   907: iload 7
    //   909: invokespecial 403	com/google/android/recaptcha/internal/zzol:zzz	(I)Ljava/lang/Object;
    //   912: astore 16
    //   914: aload 22
    //   916: checkcast 399	com/google/android/recaptcha/internal/zzoc
    //   919: astore 22
    //   921: aload 16
    //   923: checkcast 405	com/google/android/recaptcha/internal/zzob
    //   926: astore 16
    //   928: aload 22
    //   930: invokevirtual 426	java/util/AbstractMap:isEmpty	()Z
    //   933: ifne +496 -> 1429
    //   936: aload 22
    //   938: invokevirtual 430	com/google/android/recaptcha/internal/zzoc:entrySet	()Ljava/util/Set;
    //   941: invokeinterface 436 1 0
    //   946: astore 16
    //   948: aload 16
    //   950: invokeinterface 441 1 0
    //   955: ifne +6 -> 961
    //   958: goto +471 -> 1429
    //   961: aload 16
    //   963: invokeinterface 444 1 0
    //   968: checkcast 446	java/util/Map$Entry
    //   971: astore_1
    //   972: aload_1
    //   973: invokeinterface 449 1 0
    //   978: pop
    //   979: aload_1
    //   980: invokeinterface 452 1 0
    //   985: pop
    //   986: aconst_null
    //   987: athrow
    //   988: aload_2
    //   989: aload_1
    //   990: lload 20
    //   992: invokevirtual 97	sun/misc/Unsafe:getObject	(Ljava/lang/Object;J)Ljava/lang/Object;
    //   995: checkcast 454	java/util/List
    //   998: astore 16
    //   1000: aload_0
    //   1001: iload 7
    //   1003: invokespecial 79	com/google/android/recaptcha/internal/zzol:zzx	(I)Lcom/google/android/recaptcha/internal/zzow;
    //   1006: astore 22
    //   1008: getstatic 458	com/google/android/recaptcha/internal/zzoy:zza	I
    //   1011: istore 4
    //   1013: aload 16
    //   1015: invokeinterface 461 1 0
    //   1020: istore 10
    //   1022: iload 10
    //   1024: ifne +10 -> 1034
    //   1027: iload 12
    //   1029: istore 4
    //   1031: goto +1298 -> 2329
    //   1034: iconst_0
    //   1035: istore_3
    //   1036: iload 13
    //   1038: istore 6
    //   1040: iload_3
    //   1041: istore 4
    //   1043: iload 6
    //   1045: iload 10
    //   1047: if_icmpge +31 -> 1078
    //   1050: iload_3
    //   1051: iload 17
    //   1053: aload 16
    //   1055: iload 6
    //   1057: invokeinterface 464 2 0
    //   1062: checkcast 466	com/google/android/recaptcha/internal/zzoi
    //   1065: aload 22
    //   1067: invokestatic 471	com/google/android/recaptcha/internal/zzln:zzw	(ILcom/google/android/recaptcha/internal/zzoi;Lcom/google/android/recaptcha/internal/zzow;)I
    //   1070: iadd
    //   1071: istore_3
    //   1072: iinc 6 1
    //   1075: goto -35 -> 1040
    //   1078: goto +1251 -> 2329
    //   1081: aload_2
    //   1082: aload_1
    //   1083: lload 20
    //   1085: invokevirtual 97	sun/misc/Unsafe:getObject	(Ljava/lang/Object;J)Ljava/lang/Object;
    //   1088: checkcast 454	java/util/List
    //   1091: invokestatic 474	com/google/android/recaptcha/internal/zzoy:zzj	(Ljava/util/List;)I
    //   1094: istore 4
    //   1096: iload 4
    //   1098: ifle +331 -> 1429
    //   1101: goto +310 -> 1411
    //   1104: aload_2
    //   1105: aload_1
    //   1106: lload 20
    //   1108: invokevirtual 97	sun/misc/Unsafe:getObject	(Ljava/lang/Object;J)Ljava/lang/Object;
    //   1111: checkcast 454	java/util/List
    //   1114: invokestatic 476	com/google/android/recaptcha/internal/zzoy:zzi	(Ljava/util/List;)I
    //   1117: istore 4
    //   1119: iload 4
    //   1121: ifle +308 -> 1429
    //   1124: goto +287 -> 1411
    //   1127: aload_2
    //   1128: aload_1
    //   1129: lload 20
    //   1131: invokevirtual 97	sun/misc/Unsafe:getObject	(Ljava/lang/Object;J)Ljava/lang/Object;
    //   1134: checkcast 454	java/util/List
    //   1137: invokestatic 478	com/google/android/recaptcha/internal/zzoy:zze	(Ljava/util/List;)I
    //   1140: istore 4
    //   1142: iload 4
    //   1144: ifle +285 -> 1429
    //   1147: goto +264 -> 1411
    //   1150: aload_2
    //   1151: aload_1
    //   1152: lload 20
    //   1154: invokevirtual 97	sun/misc/Unsafe:getObject	(Ljava/lang/Object;J)Ljava/lang/Object;
    //   1157: checkcast 454	java/util/List
    //   1160: invokestatic 480	com/google/android/recaptcha/internal/zzoy:zzc	(Ljava/util/List;)I
    //   1163: istore 4
    //   1165: iload 4
    //   1167: ifle +262 -> 1429
    //   1170: goto +241 -> 1411
    //   1173: aload_2
    //   1174: aload_1
    //   1175: lload 20
    //   1177: invokevirtual 97	sun/misc/Unsafe:getObject	(Ljava/lang/Object;J)Ljava/lang/Object;
    //   1180: checkcast 454	java/util/List
    //   1183: invokestatic 482	com/google/android/recaptcha/internal/zzoy:zza	(Ljava/util/List;)I
    //   1186: istore 4
    //   1188: iload 4
    //   1190: ifle +239 -> 1429
    //   1193: goto +218 -> 1411
    //   1196: aload_2
    //   1197: aload_1
    //   1198: lload 20
    //   1200: invokevirtual 97	sun/misc/Unsafe:getObject	(Ljava/lang/Object;J)Ljava/lang/Object;
    //   1203: checkcast 454	java/util/List
    //   1206: invokestatic 484	com/google/android/recaptcha/internal/zzoy:zzk	(Ljava/util/List;)I
    //   1209: istore 4
    //   1211: iload 4
    //   1213: ifle +216 -> 1429
    //   1216: goto +195 -> 1411
    //   1219: aload_2
    //   1220: aload_1
    //   1221: lload 20
    //   1223: invokevirtual 97	sun/misc/Unsafe:getObject	(Ljava/lang/Object;J)Ljava/lang/Object;
    //   1226: checkcast 454	java/util/List
    //   1229: astore 16
    //   1231: getstatic 458	com/google/android/recaptcha/internal/zzoy:zza	I
    //   1234: istore 4
    //   1236: aload 16
    //   1238: invokeinterface 461 1 0
    //   1243: istore 4
    //   1245: iload 4
    //   1247: ifle +182 -> 1429
    //   1250: goto +161 -> 1411
    //   1253: aload_2
    //   1254: aload_1
    //   1255: lload 20
    //   1257: invokevirtual 97	sun/misc/Unsafe:getObject	(Ljava/lang/Object;J)Ljava/lang/Object;
    //   1260: checkcast 454	java/util/List
    //   1263: invokestatic 480	com/google/android/recaptcha/internal/zzoy:zzc	(Ljava/util/List;)I
    //   1266: istore 4
    //   1268: iload 4
    //   1270: ifle +159 -> 1429
    //   1273: goto +138 -> 1411
    //   1276: aload_2
    //   1277: aload_1
    //   1278: lload 20
    //   1280: invokevirtual 97	sun/misc/Unsafe:getObject	(Ljava/lang/Object;J)Ljava/lang/Object;
    //   1283: checkcast 454	java/util/List
    //   1286: invokestatic 478	com/google/android/recaptcha/internal/zzoy:zze	(Ljava/util/List;)I
    //   1289: istore 4
    //   1291: iload 4
    //   1293: ifle +136 -> 1429
    //   1296: goto +115 -> 1411
    //   1299: aload_2
    //   1300: aload_1
    //   1301: lload 20
    //   1303: invokevirtual 97	sun/misc/Unsafe:getObject	(Ljava/lang/Object;J)Ljava/lang/Object;
    //   1306: checkcast 454	java/util/List
    //   1309: invokestatic 486	com/google/android/recaptcha/internal/zzoy:zzf	(Ljava/util/List;)I
    //   1312: istore 4
    //   1314: iload 4
    //   1316: ifle +113 -> 1429
    //   1319: goto +92 -> 1411
    //   1322: aload_2
    //   1323: aload_1
    //   1324: lload 20
    //   1326: invokevirtual 97	sun/misc/Unsafe:getObject	(Ljava/lang/Object;J)Ljava/lang/Object;
    //   1329: checkcast 454	java/util/List
    //   1332: invokestatic 488	com/google/android/recaptcha/internal/zzoy:zzl	(Ljava/util/List;)I
    //   1335: istore 4
    //   1337: iload 4
    //   1339: ifle +90 -> 1429
    //   1342: goto +69 -> 1411
    //   1345: aload_2
    //   1346: aload_1
    //   1347: lload 20
    //   1349: invokevirtual 97	sun/misc/Unsafe:getObject	(Ljava/lang/Object;J)Ljava/lang/Object;
    //   1352: checkcast 454	java/util/List
    //   1355: invokestatic 490	com/google/android/recaptcha/internal/zzoy:zzg	(Ljava/util/List;)I
    //   1358: istore 4
    //   1360: iload 4
    //   1362: ifle +67 -> 1429
    //   1365: goto +46 -> 1411
    //   1368: aload_2
    //   1369: aload_1
    //   1370: lload 20
    //   1372: invokevirtual 97	sun/misc/Unsafe:getObject	(Ljava/lang/Object;J)Ljava/lang/Object;
    //   1375: checkcast 454	java/util/List
    //   1378: invokestatic 480	com/google/android/recaptcha/internal/zzoy:zzc	(Ljava/util/List;)I
    //   1381: istore 4
    //   1383: iload 4
    //   1385: ifle +44 -> 1429
    //   1388: goto +23 -> 1411
    //   1391: aload_2
    //   1392: aload_1
    //   1393: lload 20
    //   1395: invokevirtual 97	sun/misc/Unsafe:getObject	(Ljava/lang/Object;J)Ljava/lang/Object;
    //   1398: checkcast 454	java/util/List
    //   1401: invokestatic 478	com/google/android/recaptcha/internal/zzoy:zze	(Ljava/util/List;)I
    //   1404: istore 4
    //   1406: iload 4
    //   1408: ifle +21 -> 1429
    //   1411: iload 17
    //   1413: iconst_3
    //   1414: ishl
    //   1415: invokestatic 492	com/google/android/recaptcha/internal/zzln:zzA	(I)I
    //   1418: istore_3
    //   1419: iload 4
    //   1421: invokestatic 492	com/google/android/recaptcha/internal/zzln:zzA	(I)I
    //   1424: istore 6
    //   1426: goto +1382 -> 2808
    //   1429: goto +1658 -> 3087
    //   1432: aload_2
    //   1433: aload_1
    //   1434: lload 20
    //   1436: invokevirtual 97	sun/misc/Unsafe:getObject	(Ljava/lang/Object;J)Ljava/lang/Object;
    //   1439: checkcast 454	java/util/List
    //   1442: astore 16
    //   1444: getstatic 458	com/google/android/recaptcha/internal/zzoy:zza	I
    //   1447: istore 4
    //   1449: aload 16
    //   1451: invokeinterface 461 1 0
    //   1456: istore_3
    //   1457: iload_3
    //   1458: ifne +10 -> 1468
    //   1461: iload 12
    //   1463: istore 4
    //   1465: goto +864 -> 2329
    //   1468: iload 17
    //   1470: iconst_3
    //   1471: ishl
    //   1472: istore 6
    //   1474: aload 16
    //   1476: invokestatic 474	com/google/android/recaptcha/internal/zzoy:zzj	(Ljava/util/List;)I
    //   1479: istore 4
    //   1481: goto +770 -> 2251
    //   1484: aload_2
    //   1485: aload_1
    //   1486: lload 20
    //   1488: invokevirtual 97	sun/misc/Unsafe:getObject	(Ljava/lang/Object;J)Ljava/lang/Object;
    //   1491: checkcast 454	java/util/List
    //   1494: astore 16
    //   1496: getstatic 458	com/google/android/recaptcha/internal/zzoy:zza	I
    //   1499: istore 4
    //   1501: aload 16
    //   1503: invokeinterface 461 1 0
    //   1508: istore_3
    //   1509: iload_3
    //   1510: ifne +10 -> 1520
    //   1513: iload 12
    //   1515: istore 4
    //   1517: goto +812 -> 2329
    //   1520: iload 17
    //   1522: iconst_3
    //   1523: ishl
    //   1524: istore 6
    //   1526: aload 16
    //   1528: invokestatic 476	com/google/android/recaptcha/internal/zzoy:zzi	(Ljava/util/List;)I
    //   1531: istore 4
    //   1533: goto +718 -> 2251
    //   1536: aload_2
    //   1537: aload_1
    //   1538: lload 20
    //   1540: invokevirtual 97	sun/misc/Unsafe:getObject	(Ljava/lang/Object;J)Ljava/lang/Object;
    //   1543: checkcast 454	java/util/List
    //   1546: astore 16
    //   1548: getstatic 458	com/google/android/recaptcha/internal/zzoy:zza	I
    //   1551: istore 4
    //   1553: aload 16
    //   1555: invokeinterface 461 1 0
    //   1560: istore_3
    //   1561: iload_3
    //   1562: ifne +10 -> 1572
    //   1565: iload 12
    //   1567: istore 4
    //   1569: goto +760 -> 2329
    //   1572: iload 17
    //   1574: iconst_3
    //   1575: ishl
    //   1576: istore 6
    //   1578: aload 16
    //   1580: invokestatic 482	com/google/android/recaptcha/internal/zzoy:zza	(Ljava/util/List;)I
    //   1583: istore 4
    //   1585: goto +666 -> 2251
    //   1588: aload_2
    //   1589: aload_1
    //   1590: lload 20
    //   1592: invokevirtual 97	sun/misc/Unsafe:getObject	(Ljava/lang/Object;J)Ljava/lang/Object;
    //   1595: checkcast 454	java/util/List
    //   1598: astore 16
    //   1600: getstatic 458	com/google/android/recaptcha/internal/zzoy:zza	I
    //   1603: istore 4
    //   1605: aload 16
    //   1607: invokeinterface 461 1 0
    //   1612: istore_3
    //   1613: iload_3
    //   1614: ifne +10 -> 1624
    //   1617: iload 12
    //   1619: istore 4
    //   1621: goto +708 -> 2329
    //   1624: iload 17
    //   1626: iconst_3
    //   1627: ishl
    //   1628: istore 6
    //   1630: aload 16
    //   1632: invokestatic 484	com/google/android/recaptcha/internal/zzoy:zzk	(Ljava/util/List;)I
    //   1635: istore 4
    //   1637: goto +614 -> 2251
    //   1640: aload_2
    //   1641: aload_1
    //   1642: lload 20
    //   1644: invokevirtual 97	sun/misc/Unsafe:getObject	(Ljava/lang/Object;J)Ljava/lang/Object;
    //   1647: checkcast 454	java/util/List
    //   1650: astore 16
    //   1652: getstatic 458	com/google/android/recaptcha/internal/zzoy:zza	I
    //   1655: istore 4
    //   1657: aload 16
    //   1659: invokeinterface 461 1 0
    //   1664: istore 4
    //   1666: iload 4
    //   1668: ifne +10 -> 1678
    //   1671: iload 12
    //   1673: istore 4
    //   1675: goto +654 -> 2329
    //   1678: iload 17
    //   1680: iconst_3
    //   1681: ishl
    //   1682: invokestatic 492	com/google/android/recaptcha/internal/zzln:zzA	(I)I
    //   1685: iload 4
    //   1687: imul
    //   1688: istore_3
    //   1689: iload 8
    //   1691: istore 6
    //   1693: iload_3
    //   1694: istore 4
    //   1696: iload 6
    //   1698: aload 16
    //   1700: invokeinterface 461 1 0
    //   1705: if_icmpge +37 -> 1742
    //   1708: aload 16
    //   1710: iload 6
    //   1712: invokeinterface 464 2 0
    //   1717: checkcast 252	com/google/android/recaptcha/internal/zzle
    //   1720: invokevirtual 494	com/google/android/recaptcha/internal/zzle:zzd	()I
    //   1723: istore 4
    //   1725: iload_3
    //   1726: iload 4
    //   1728: invokestatic 492	com/google/android/recaptcha/internal/zzln:zzA	(I)I
    //   1731: iload 4
    //   1733: iadd
    //   1734: iadd
    //   1735: istore_3
    //   1736: iinc 6 1
    //   1739: goto -46 -> 1693
    //   1742: goto +587 -> 2329
    //   1745: aload_2
    //   1746: aload_1
    //   1747: lload 20
    //   1749: invokevirtual 97	sun/misc/Unsafe:getObject	(Ljava/lang/Object;J)Ljava/lang/Object;
    //   1752: checkcast 454	java/util/List
    //   1755: astore 23
    //   1757: aload_0
    //   1758: iload 7
    //   1760: invokespecial 79	com/google/android/recaptcha/internal/zzol:zzx	(I)Lcom/google/android/recaptcha/internal/zzow;
    //   1763: astore 22
    //   1765: getstatic 458	com/google/android/recaptcha/internal/zzoy:zza	I
    //   1768: istore 4
    //   1770: aload 23
    //   1772: invokeinterface 461 1 0
    //   1777: istore 10
    //   1779: iload 10
    //   1781: ifne +10 -> 1791
    //   1784: iload 12
    //   1786: istore 4
    //   1788: goto +541 -> 2329
    //   1791: iload 17
    //   1793: iconst_3
    //   1794: ishl
    //   1795: invokestatic 492	com/google/android/recaptcha/internal/zzln:zzA	(I)I
    //   1798: iload 10
    //   1800: imul
    //   1801: istore_3
    //   1802: iload 9
    //   1804: istore 6
    //   1806: iload_3
    //   1807: istore 4
    //   1809: iload 6
    //   1811: iload 10
    //   1813: if_icmpge -735 -> 1078
    //   1816: aload 23
    //   1818: iload 6
    //   1820: invokeinterface 464 2 0
    //   1825: astore 16
    //   1827: aload 16
    //   1829: instanceof 496
    //   1832: ifeq +27 -> 1859
    //   1835: aload 16
    //   1837: checkcast 496	com/google/android/recaptcha/internal/zznt
    //   1840: invokevirtual 497	com/google/android/recaptcha/internal/zznt:zza	()I
    //   1843: istore 4
    //   1845: iload 4
    //   1847: invokestatic 492	com/google/android/recaptcha/internal/zzln:zzA	(I)I
    //   1850: iload 4
    //   1852: iadd
    //   1853: iload_3
    //   1854: iadd
    //   1855: istore_3
    //   1856: goto +16 -> 1872
    //   1859: aload 16
    //   1861: checkcast 466	com/google/android/recaptcha/internal/zzoi
    //   1864: aload 22
    //   1866: invokestatic 500	com/google/android/recaptcha/internal/zzln:zzy	(Lcom/google/android/recaptcha/internal/zzoi;Lcom/google/android/recaptcha/internal/zzow;)I
    //   1869: iload_3
    //   1870: iadd
    //   1871: istore_3
    //   1872: iinc 6 1
    //   1875: goto -69 -> 1806
    //   1878: aload_2
    //   1879: aload_1
    //   1880: lload 20
    //   1882: invokevirtual 97	sun/misc/Unsafe:getObject	(Ljava/lang/Object;J)Ljava/lang/Object;
    //   1885: checkcast 454	java/util/List
    //   1888: astore 16
    //   1890: getstatic 458	com/google/android/recaptcha/internal/zzoy:zza	I
    //   1893: istore 4
    //   1895: aload 16
    //   1897: invokeinterface 461 1 0
    //   1902: istore 13
    //   1904: iload 13
    //   1906: ifne +10 -> 1916
    //   1909: iload 12
    //   1911: istore 4
    //   1913: goto +416 -> 2329
    //   1916: iload 17
    //   1918: iconst_3
    //   1919: ishl
    //   1920: invokestatic 492	com/google/android/recaptcha/internal/zzln:zzA	(I)I
    //   1923: iload 13
    //   1925: imul
    //   1926: istore 4
    //   1928: iload 4
    //   1930: istore_3
    //   1931: iload 11
    //   1933: istore 6
    //   1935: aload 16
    //   1937: instanceof 502
    //   1940: ifeq +85 -> 2025
    //   1943: aload 16
    //   1945: checkcast 502	com/google/android/recaptcha/internal/zznu
    //   1948: astore 22
    //   1950: iload 10
    //   1952: istore 6
    //   1954: iload 4
    //   1956: istore_3
    //   1957: iload_3
    //   1958: istore 4
    //   1960: iload 6
    //   1962: iload 13
    //   1964: if_icmpge -222 -> 1742
    //   1967: aload 22
    //   1969: invokeinterface 504 1 0
    //   1974: astore 16
    //   1976: aload 16
    //   1978: instanceof 252
    //   1981: ifeq +27 -> 2008
    //   1984: aload 16
    //   1986: checkcast 252	com/google/android/recaptcha/internal/zzle
    //   1989: invokevirtual 494	com/google/android/recaptcha/internal/zzle:zzd	()I
    //   1992: istore 4
    //   1994: iload 4
    //   1996: invokestatic 492	com/google/android/recaptcha/internal/zzln:zzA	(I)I
    //   1999: iload 4
    //   2001: iadd
    //   2002: iload_3
    //   2003: iadd
    //   2004: istore_3
    //   2005: goto +14 -> 2019
    //   2008: aload 16
    //   2010: checkcast 132	java/lang/String
    //   2013: invokestatic 507	com/google/android/recaptcha/internal/zzln:zzz	(Ljava/lang/String;)I
    //   2016: iload_3
    //   2017: iadd
    //   2018: istore_3
    //   2019: iinc 6 1
    //   2022: goto -65 -> 1957
    //   2025: iload_3
    //   2026: istore 4
    //   2028: iload 6
    //   2030: iload 13
    //   2032: if_icmpge -290 -> 1742
    //   2035: aload 16
    //   2037: iload 6
    //   2039: invokeinterface 464 2 0
    //   2044: astore 22
    //   2046: aload 22
    //   2048: instanceof 252
    //   2051: ifeq +27 -> 2078
    //   2054: aload 22
    //   2056: checkcast 252	com/google/android/recaptcha/internal/zzle
    //   2059: invokevirtual 494	com/google/android/recaptcha/internal/zzle:zzd	()I
    //   2062: istore 4
    //   2064: iload 4
    //   2066: invokestatic 492	com/google/android/recaptcha/internal/zzln:zzA	(I)I
    //   2069: iload 4
    //   2071: iadd
    //   2072: iload_3
    //   2073: iadd
    //   2074: istore_3
    //   2075: goto +14 -> 2089
    //   2078: aload 22
    //   2080: checkcast 132	java/lang/String
    //   2083: invokestatic 507	com/google/android/recaptcha/internal/zzln:zzz	(Ljava/lang/String;)I
    //   2086: iload_3
    //   2087: iadd
    //   2088: istore_3
    //   2089: iinc 6 1
    //   2092: goto -67 -> 2025
    //   2095: aload_2
    //   2096: aload_1
    //   2097: lload 20
    //   2099: invokevirtual 97	sun/misc/Unsafe:getObject	(Ljava/lang/Object;J)Ljava/lang/Object;
    //   2102: checkcast 454	java/util/List
    //   2105: astore 16
    //   2107: getstatic 458	com/google/android/recaptcha/internal/zzoy:zza	I
    //   2110: istore 4
    //   2112: aload 16
    //   2114: invokeinterface 461 1 0
    //   2119: istore 4
    //   2121: iload 4
    //   2123: ifne +10 -> 2133
    //   2126: iload 12
    //   2128: istore 4
    //   2130: goto +199 -> 2329
    //   2133: iload 17
    //   2135: iconst_3
    //   2136: ishl
    //   2137: invokestatic 492	com/google/android/recaptcha/internal/zzln:zzA	(I)I
    //   2140: iconst_1
    //   2141: iadd
    //   2142: iload 4
    //   2144: imul
    //   2145: istore 4
    //   2147: goto +182 -> 2329
    //   2150: aload_2
    //   2151: aload_1
    //   2152: lload 20
    //   2154: invokevirtual 97	sun/misc/Unsafe:getObject	(Ljava/lang/Object;J)Ljava/lang/Object;
    //   2157: checkcast 454	java/util/List
    //   2160: astore 16
    //   2162: getstatic 458	com/google/android/recaptcha/internal/zzoy:zza	I
    //   2165: istore 4
    //   2167: aload 16
    //   2169: invokeinterface 461 1 0
    //   2174: istore_3
    //   2175: iload_3
    //   2176: ifne +10 -> 2186
    //   2179: iload 12
    //   2181: istore 4
    //   2183: goto +146 -> 2329
    //   2186: iload 17
    //   2188: iconst_3
    //   2189: ishl
    //   2190: istore 6
    //   2192: aload 16
    //   2194: invokestatic 486	com/google/android/recaptcha/internal/zzoy:zzf	(Ljava/util/List;)I
    //   2197: istore 4
    //   2199: goto +52 -> 2251
    //   2202: aload_2
    //   2203: aload_1
    //   2204: lload 20
    //   2206: invokevirtual 97	sun/misc/Unsafe:getObject	(Ljava/lang/Object;J)Ljava/lang/Object;
    //   2209: checkcast 454	java/util/List
    //   2212: astore 16
    //   2214: getstatic 458	com/google/android/recaptcha/internal/zzoy:zza	I
    //   2217: istore 4
    //   2219: aload 16
    //   2221: invokeinterface 461 1 0
    //   2226: istore_3
    //   2227: iload_3
    //   2228: ifne +10 -> 2238
    //   2231: iload 12
    //   2233: istore 4
    //   2235: goto +94 -> 2329
    //   2238: iload 17
    //   2240: iconst_3
    //   2241: ishl
    //   2242: istore 6
    //   2244: aload 16
    //   2246: invokestatic 488	com/google/android/recaptcha/internal/zzoy:zzl	(Ljava/util/List;)I
    //   2249: istore 4
    //   2251: iload 6
    //   2253: invokestatic 492	com/google/android/recaptcha/internal/zzln:zzA	(I)I
    //   2256: iload_3
    //   2257: imul
    //   2258: iload 4
    //   2260: iadd
    //   2261: istore 4
    //   2263: goto +66 -> 2329
    //   2266: aload_2
    //   2267: aload_1
    //   2268: lload 20
    //   2270: invokevirtual 97	sun/misc/Unsafe:getObject	(Ljava/lang/Object;J)Ljava/lang/Object;
    //   2273: checkcast 454	java/util/List
    //   2276: astore 16
    //   2278: getstatic 458	com/google/android/recaptcha/internal/zzoy:zza	I
    //   2281: istore 4
    //   2283: aload 16
    //   2285: invokeinterface 461 1 0
    //   2290: ifne +10 -> 2300
    //   2293: iload 12
    //   2295: istore 4
    //   2297: goto +32 -> 2329
    //   2300: aload 16
    //   2302: invokestatic 490	com/google/android/recaptcha/internal/zzoy:zzg	(Ljava/util/List;)I
    //   2305: istore 4
    //   2307: aload 16
    //   2309: invokeinterface 461 1 0
    //   2314: istore_3
    //   2315: iload 17
    //   2317: iconst_3
    //   2318: ishl
    //   2319: invokestatic 492	com/google/android/recaptcha/internal/zzln:zzA	(I)I
    //   2322: iload_3
    //   2323: imul
    //   2324: iload 4
    //   2326: iadd
    //   2327: istore 4
    //   2329: iload 5
    //   2331: iload 4
    //   2333: iadd
    //   2334: istore 4
    //   2336: goto +755 -> 3091
    //   2339: iload 17
    //   2341: aload_2
    //   2342: aload_1
    //   2343: lload 20
    //   2345: invokevirtual 97	sun/misc/Unsafe:getObject	(Ljava/lang/Object;J)Ljava/lang/Object;
    //   2348: checkcast 454	java/util/List
    //   2351: iconst_0
    //   2352: invokestatic 510	com/google/android/recaptcha/internal/zzoy:zzb	(ILjava/util/List;Z)I
    //   2355: istore 4
    //   2357: goto +21 -> 2378
    //   2360: iload 17
    //   2362: aload_2
    //   2363: aload_1
    //   2364: lload 20
    //   2366: invokevirtual 97	sun/misc/Unsafe:getObject	(Ljava/lang/Object;J)Ljava/lang/Object;
    //   2369: checkcast 454	java/util/List
    //   2372: iconst_0
    //   2373: invokestatic 512	com/google/android/recaptcha/internal/zzoy:zzd	(ILjava/util/List;Z)I
    //   2376: istore 4
    //   2378: goto +342 -> 2720
    //   2381: aload_0
    //   2382: aload_1
    //   2383: iload 7
    //   2385: iload 19
    //   2387: iload 18
    //   2389: iload 4
    //   2391: invokespecial 514	com/google/android/recaptcha/internal/zzol:zzO	(Ljava/lang/Object;IIII)Z
    //   2394: ifeq +693 -> 3087
    //   2397: aload_2
    //   2398: aload_1
    //   2399: lload 20
    //   2401: invokevirtual 97	sun/misc/Unsafe:getObject	(Ljava/lang/Object;J)Ljava/lang/Object;
    //   2404: astore 16
    //   2406: iload 17
    //   2408: aload 16
    //   2410: checkcast 466	com/google/android/recaptcha/internal/zzoi
    //   2413: aload_0
    //   2414: iload 7
    //   2416: invokespecial 79	com/google/android/recaptcha/internal/zzol:zzx	(I)Lcom/google/android/recaptcha/internal/zzow;
    //   2419: invokestatic 471	com/google/android/recaptcha/internal/zzln:zzw	(ILcom/google/android/recaptcha/internal/zzoi;Lcom/google/android/recaptcha/internal/zzow;)I
    //   2422: istore 4
    //   2424: goto +296 -> 2720
    //   2427: aload_0
    //   2428: aload_1
    //   2429: iload 7
    //   2431: iload 19
    //   2433: iload 18
    //   2435: iload 4
    //   2437: invokespecial 514	com/google/android/recaptcha/internal/zzol:zzO	(Ljava/lang/Object;IIII)Z
    //   2440: ifeq +647 -> 3087
    //   2443: iload 17
    //   2445: iconst_3
    //   2446: ishl
    //   2447: istore 4
    //   2449: aload_2
    //   2450: aload_1
    //   2451: lload 20
    //   2453: invokevirtual 517	sun/misc/Unsafe:getLong	(Ljava/lang/Object;J)J
    //   2456: lstore 20
    //   2458: iload 4
    //   2460: invokestatic 492	com/google/android/recaptcha/internal/zzln:zzA	(I)I
    //   2463: istore 4
    //   2465: lload 20
    //   2467: bipush 63
    //   2469: lshr
    //   2470: lload 20
    //   2472: lload 20
    //   2474: ladd
    //   2475: lxor
    //   2476: lstore 20
    //   2478: goto +530 -> 3008
    //   2481: aload_0
    //   2482: aload_1
    //   2483: iload 7
    //   2485: iload 19
    //   2487: iload 18
    //   2489: iload 4
    //   2491: invokespecial 514	com/google/android/recaptcha/internal/zzol:zzO	(Ljava/lang/Object;IIII)Z
    //   2494: ifeq +593 -> 3087
    //   2497: iload 17
    //   2499: iconst_3
    //   2500: ishl
    //   2501: istore_3
    //   2502: aload_2
    //   2503: aload_1
    //   2504: lload 20
    //   2506: invokevirtual 409	sun/misc/Unsafe:getInt	(Ljava/lang/Object;J)I
    //   2509: istore 4
    //   2511: iload_3
    //   2512: invokestatic 492	com/google/android/recaptcha/internal/zzln:zzA	(I)I
    //   2515: istore_3
    //   2516: iload 4
    //   2518: bipush 31
    //   2520: ishr
    //   2521: iload 4
    //   2523: iload 4
    //   2525: iadd
    //   2526: ixor
    //   2527: istore 6
    //   2529: iload_3
    //   2530: istore 4
    //   2532: iload 6
    //   2534: istore_3
    //   2535: goto +103 -> 2638
    //   2538: aload_0
    //   2539: aload_1
    //   2540: iload 7
    //   2542: iload 19
    //   2544: iload 18
    //   2546: iload 4
    //   2548: invokespecial 514	com/google/android/recaptcha/internal/zzol:zzO	(Ljava/lang/Object;IIII)Z
    //   2551: ifeq +536 -> 3087
    //   2554: goto +518 -> 3072
    //   2557: aload_0
    //   2558: aload_1
    //   2559: iload 7
    //   2561: iload 19
    //   2563: iload 18
    //   2565: iload 4
    //   2567: invokespecial 514	com/google/android/recaptcha/internal/zzol:zzO	(Ljava/lang/Object;IIII)Z
    //   2570: ifeq +517 -> 3087
    //   2573: goto +469 -> 3042
    //   2576: aload_0
    //   2577: aload_1
    //   2578: iload 7
    //   2580: iload 19
    //   2582: iload 18
    //   2584: iload 4
    //   2586: invokespecial 514	com/google/android/recaptcha/internal/zzol:zzO	(Ljava/lang/Object;IIII)Z
    //   2589: ifeq +498 -> 3087
    //   2592: goto +338 -> 2930
    //   2595: aload_0
    //   2596: aload_1
    //   2597: iload 7
    //   2599: iload 19
    //   2601: iload 18
    //   2603: iload 4
    //   2605: invokespecial 514	com/google/android/recaptcha/internal/zzol:zzO	(Ljava/lang/Object;IIII)Z
    //   2608: ifeq +479 -> 3087
    //   2611: iload 17
    //   2613: iconst_3
    //   2614: ishl
    //   2615: istore_3
    //   2616: aload_2
    //   2617: aload_1
    //   2618: lload 20
    //   2620: invokevirtual 409	sun/misc/Unsafe:getInt	(Ljava/lang/Object;J)I
    //   2623: istore 4
    //   2625: iload_3
    //   2626: invokestatic 492	com/google/android/recaptcha/internal/zzln:zzA	(I)I
    //   2629: istore 6
    //   2631: iload 4
    //   2633: istore_3
    //   2634: iload 6
    //   2636: istore 4
    //   2638: iload_3
    //   2639: invokestatic 492	com/google/android/recaptcha/internal/zzln:zzA	(I)I
    //   2642: istore_3
    //   2643: goto +371 -> 3014
    //   2646: aload_0
    //   2647: aload_1
    //   2648: iload 7
    //   2650: iload 19
    //   2652: iload 18
    //   2654: iload 4
    //   2656: invokespecial 514	com/google/android/recaptcha/internal/zzol:zzO	(Ljava/lang/Object;IIII)Z
    //   2659: ifeq +428 -> 3087
    //   2662: iload 17
    //   2664: iconst_3
    //   2665: ishl
    //   2666: istore 4
    //   2668: aload_2
    //   2669: aload_1
    //   2670: lload 20
    //   2672: invokevirtual 97	sun/misc/Unsafe:getObject	(Ljava/lang/Object;J)Ljava/lang/Object;
    //   2675: astore 16
    //   2677: goto +105 -> 2782
    //   2680: aload_0
    //   2681: aload_1
    //   2682: iload 7
    //   2684: iload 19
    //   2686: iload 18
    //   2688: iload 4
    //   2690: invokespecial 514	com/google/android/recaptcha/internal/zzol:zzO	(Ljava/lang/Object;IIII)Z
    //   2693: ifeq +394 -> 3087
    //   2696: aload_2
    //   2697: aload_1
    //   2698: lload 20
    //   2700: invokevirtual 97	sun/misc/Unsafe:getObject	(Ljava/lang/Object;J)Ljava/lang/Object;
    //   2703: astore 16
    //   2705: iload 17
    //   2707: aload 16
    //   2709: aload_0
    //   2710: iload 7
    //   2712: invokespecial 79	com/google/android/recaptcha/internal/zzol:zzx	(I)Lcom/google/android/recaptcha/internal/zzow;
    //   2715: invokestatic 520	com/google/android/recaptcha/internal/zzoy:zzh	(ILjava/lang/Object;Lcom/google/android/recaptcha/internal/zzow;)I
    //   2718: istore 4
    //   2720: iload 5
    //   2722: iload 4
    //   2724: iadd
    //   2725: istore 4
    //   2727: goto +364 -> 3091
    //   2730: aload_0
    //   2731: aload_1
    //   2732: iload 7
    //   2734: iload 19
    //   2736: iload 18
    //   2738: iload 4
    //   2740: invokespecial 514	com/google/android/recaptcha/internal/zzol:zzO	(Ljava/lang/Object;IIII)Z
    //   2743: ifeq +344 -> 3087
    //   2746: iload 17
    //   2748: iconst_3
    //   2749: ishl
    //   2750: istore_3
    //   2751: aload_2
    //   2752: aload_1
    //   2753: lload 20
    //   2755: invokevirtual 97	sun/misc/Unsafe:getObject	(Ljava/lang/Object;J)Ljava/lang/Object;
    //   2758: astore 22
    //   2760: iload_3
    //   2761: istore 4
    //   2763: aload 22
    //   2765: astore 16
    //   2767: aload 22
    //   2769: instanceof 252
    //   2772: ifeq +51 -> 2823
    //   2775: aload 22
    //   2777: astore 16
    //   2779: iload_3
    //   2780: istore 4
    //   2782: aload 16
    //   2784: checkcast 252	com/google/android/recaptcha/internal/zzle
    //   2787: astore 16
    //   2789: iload 4
    //   2791: invokestatic 492	com/google/android/recaptcha/internal/zzln:zzA	(I)I
    //   2794: istore 4
    //   2796: aload 16
    //   2798: invokevirtual 494	com/google/android/recaptcha/internal/zzle:zzd	()I
    //   2801: istore_3
    //   2802: iload_3
    //   2803: invokestatic 492	com/google/android/recaptcha/internal/zzln:zzA	(I)I
    //   2806: istore 6
    //   2808: iload 6
    //   2810: iload_3
    //   2811: iadd
    //   2812: iload 4
    //   2814: iadd
    //   2815: iload 5
    //   2817: iadd
    //   2818: istore 4
    //   2820: goto +271 -> 3091
    //   2823: aload 16
    //   2825: checkcast 132	java/lang/String
    //   2828: astore 16
    //   2830: iload 4
    //   2832: invokestatic 492	com/google/android/recaptcha/internal/zzln:zzA	(I)I
    //   2835: istore 4
    //   2837: aload 16
    //   2839: invokestatic 507	com/google/android/recaptcha/internal/zzln:zzz	(Ljava/lang/String;)I
    //   2842: istore_3
    //   2843: goto +171 -> 3014
    //   2846: aload_0
    //   2847: aload_1
    //   2848: iload 7
    //   2850: iload 19
    //   2852: iload 18
    //   2854: iload 4
    //   2856: invokespecial 514	com/google/android/recaptcha/internal/zzol:zzO	(Ljava/lang/Object;IIII)Z
    //   2859: ifeq +228 -> 3087
    //   2862: iload 17
    //   2864: iconst_3
    //   2865: ishl
    //   2866: invokestatic 492	com/google/android/recaptcha/internal/zzln:zzA	(I)I
    //   2869: iconst_1
    //   2870: iadd
    //   2871: istore 4
    //   2873: goto -153 -> 2720
    //   2876: aload_0
    //   2877: aload_1
    //   2878: iload 7
    //   2880: iload 19
    //   2882: iload 18
    //   2884: iload 4
    //   2886: invokespecial 514	com/google/android/recaptcha/internal/zzol:zzO	(Ljava/lang/Object;IIII)Z
    //   2889: ifeq +198 -> 3087
    //   2892: goto +150 -> 3042
    //   2895: aload_0
    //   2896: aload_1
    //   2897: iload 7
    //   2899: iload 19
    //   2901: iload 18
    //   2903: iload 4
    //   2905: invokespecial 514	com/google/android/recaptcha/internal/zzol:zzO	(Ljava/lang/Object;IIII)Z
    //   2908: ifeq +179 -> 3087
    //   2911: goto +161 -> 3072
    //   2914: aload_0
    //   2915: aload_1
    //   2916: iload 7
    //   2918: iload 19
    //   2920: iload 18
    //   2922: iload 4
    //   2924: invokespecial 514	com/google/android/recaptcha/internal/zzol:zzO	(Ljava/lang/Object;IIII)Z
    //   2927: ifeq +160 -> 3087
    //   2930: iload 17
    //   2932: iconst_3
    //   2933: ishl
    //   2934: istore 4
    //   2936: aload_2
    //   2937: aload_1
    //   2938: lload 20
    //   2940: invokevirtual 409	sun/misc/Unsafe:getInt	(Ljava/lang/Object;J)I
    //   2943: istore_3
    //   2944: iload_3
    //   2945: i2l
    //   2946: lstore 20
    //   2948: goto +53 -> 3001
    //   2951: aload_0
    //   2952: aload_1
    //   2953: iload 7
    //   2955: iload 19
    //   2957: iload 18
    //   2959: iload 4
    //   2961: invokespecial 514	com/google/android/recaptcha/internal/zzol:zzO	(Ljava/lang/Object;IIII)Z
    //   2964: ifeq +123 -> 3087
    //   2967: goto +19 -> 2986
    //   2970: aload_0
    //   2971: aload_1
    //   2972: iload 7
    //   2974: iload 19
    //   2976: iload 18
    //   2978: iload 4
    //   2980: invokespecial 514	com/google/android/recaptcha/internal/zzol:zzO	(Ljava/lang/Object;IIII)Z
    //   2983: ifeq +104 -> 3087
    //   2986: iload 17
    //   2988: iconst_3
    //   2989: ishl
    //   2990: istore 4
    //   2992: aload_2
    //   2993: aload_1
    //   2994: lload 20
    //   2996: invokevirtual 517	sun/misc/Unsafe:getLong	(Ljava/lang/Object;J)J
    //   2999: lstore 20
    //   3001: iload 4
    //   3003: invokestatic 492	com/google/android/recaptcha/internal/zzln:zzA	(I)I
    //   3006: istore 4
    //   3008: lload 20
    //   3010: invokestatic 523	com/google/android/recaptcha/internal/zzln:zzB	(J)I
    //   3013: istore_3
    //   3014: iload_3
    //   3015: iload 4
    //   3017: iadd
    //   3018: iload 5
    //   3020: iadd
    //   3021: istore 4
    //   3023: goto +68 -> 3091
    //   3026: aload_0
    //   3027: aload_1
    //   3028: iload 7
    //   3030: iload 19
    //   3032: iload 18
    //   3034: iload 4
    //   3036: invokespecial 514	com/google/android/recaptcha/internal/zzol:zzO	(Ljava/lang/Object;IIII)Z
    //   3039: ifeq +48 -> 3087
    //   3042: iload 17
    //   3044: iconst_3
    //   3045: ishl
    //   3046: invokestatic 492	com/google/android/recaptcha/internal/zzln:zzA	(I)I
    //   3049: iconst_4
    //   3050: iadd
    //   3051: istore 4
    //   3053: goto -333 -> 2720
    //   3056: aload_0
    //   3057: aload_1
    //   3058: iload 7
    //   3060: iload 19
    //   3062: iload 18
    //   3064: iload 4
    //   3066: invokespecial 514	com/google/android/recaptcha/internal/zzol:zzO	(Ljava/lang/Object;IIII)Z
    //   3069: ifeq +18 -> 3087
    //   3072: iload 17
    //   3074: iconst_3
    //   3075: ishl
    //   3076: invokestatic 492	com/google/android/recaptcha/internal/zzln:zzA	(I)I
    //   3079: bipush 8
    //   3081: iadd
    //   3082: istore 4
    //   3084: goto -364 -> 2720
    //   3087: iload 5
    //   3089: istore 4
    //   3091: iinc 7 3
    //   3094: iload 18
    //   3096: istore_3
    //   3097: iload 19
    //   3099: istore 6
    //   3101: iload 4
    //   3103: istore 5
    //   3105: goto -3084 -> 21
    //   3108: aload_1
    //   3109: checkcast 55	com/google/android/recaptcha/internal/zznd
    //   3112: getfield 310	com/google/android/recaptcha/internal/zznd:zzc	Lcom/google/android/recaptcha/internal/zzpm;
    //   3115: invokevirtual 524	com/google/android/recaptcha/internal/zzpm:zza	()I
    //   3118: iload 5
    //   3120: iadd
    //   3121: istore 6
    //   3123: iload 6
    //   3125: istore 4
    //   3127: aload_0
    //   3128: getfield 61	com/google/android/recaptcha/internal/zzol:zzh	Z
    //   3131: ifeq +142 -> 3273
    //   3134: aload_1
    //   3135: checkcast 59	com/google/android/recaptcha/internal/zzna
    //   3138: getfield 527	com/google/android/recaptcha/internal/zzna:zzb	Lcom/google/android/recaptcha/internal/zzmt;
    //   3141: astore 16
    //   3143: aload 16
    //   3145: getfield 532	com/google/android/recaptcha/internal/zzmt:zza	Lcom/google/android/recaptcha/internal/zzpe;
    //   3148: invokevirtual 535	com/google/android/recaptcha/internal/zzpe:zzc	()I
    //   3151: istore 5
    //   3153: iconst_0
    //   3154: istore_3
    //   3155: iconst_0
    //   3156: istore 4
    //   3158: iload_3
    //   3159: iload 5
    //   3161: if_icmpge +43 -> 3204
    //   3164: aload 16
    //   3166: getfield 532	com/google/android/recaptcha/internal/zzmt:zza	Lcom/google/android/recaptcha/internal/zzpe;
    //   3169: iload_3
    //   3170: invokevirtual 538	com/google/android/recaptcha/internal/zzpe:zzg	(I)Ljava/util/Map$Entry;
    //   3173: astore_1
    //   3174: iload 4
    //   3176: aload_1
    //   3177: checkcast 540	com/google/android/recaptcha/internal/zzpa
    //   3180: invokevirtual 543	com/google/android/recaptcha/internal/zzpa:zza	()Ljava/lang/Comparable;
    //   3183: checkcast 545	com/google/android/recaptcha/internal/zzms
    //   3186: aload_1
    //   3187: invokeinterface 452 1 0
    //   3192: invokestatic 548	com/google/android/recaptcha/internal/zzmt:zza	(Lcom/google/android/recaptcha/internal/zzms;Ljava/lang/Object;)I
    //   3195: iadd
    //   3196: istore 4
    //   3198: iinc 3 1
    //   3201: goto -43 -> 3158
    //   3204: aload 16
    //   3206: getfield 532	com/google/android/recaptcha/internal/zzmt:zza	Lcom/google/android/recaptcha/internal/zzpe;
    //   3209: invokevirtual 551	com/google/android/recaptcha/internal/zzpe:zzd	()Ljava/lang/Iterable;
    //   3212: invokeinterface 554 1 0
    //   3217: astore_1
    //   3218: aload_1
    //   3219: invokeinterface 441 1 0
    //   3224: ifeq +42 -> 3266
    //   3227: aload_1
    //   3228: invokeinterface 444 1 0
    //   3233: checkcast 446	java/util/Map$Entry
    //   3236: astore 16
    //   3238: iload 4
    //   3240: aload 16
    //   3242: invokeinterface 449 1 0
    //   3247: checkcast 545	com/google/android/recaptcha/internal/zzms
    //   3250: aload 16
    //   3252: invokeinterface 452 1 0
    //   3257: invokestatic 548	com/google/android/recaptcha/internal/zzmt:zza	(Lcom/google/android/recaptcha/internal/zzms;Ljava/lang/Object;)I
    //   3260: iadd
    //   3261: istore 4
    //   3263: goto -45 -> 3218
    //   3266: iload 6
    //   3268: iload 4
    //   3270: iadd
    //   3271: istore 4
    //   3273: iload 4
    //   3275: ireturn
    // Local variable table:
    //   start	length	slot	name	signature
    //   0	3276	0	this	zzol
    //   0	3276	1	paramObject	Object
    //   3	2990	2	localUnsafe	Unsafe
    //   5	3194	3	i	int
    //   7	3267	4	j	int
    //   11	3151	5	k	int
    //   15	3256	6	m	int
    //   19	3073	7	n	int
    //   22	1668	8	i1	int
    //   25	1778	9	i2	int
    //   28	1923	10	i3	int
    //   31	1901	11	i4	int
    //   34	2260	12	i5	int
    //   37	1996	13	i6	int
    //   55	137	14	i7	int
    //   62	134	15	i8	int
    //   68	3183	16	localObject1	Object
    //   75	3001	17	i9	int
    //   84	3011	18	i10	int
    //   91	3007	19	i11	int
    //   193	2816	20	l	long
    //   723	2053	22	localObject2	Object
    //   1755	62	23	localList	List
  }
  
  public final int zzb(Object paramObject)
  {
    int i = 0;
    for (int j = 0; i < zzc.length; j = m)
    {
      int k = zzu(i);
      Object localObject = zzc;
      m = zzt(k);
      int n = localObject[i];
      long l = 0xFFFFF & k;
      k = 37;
      boolean bool;
      float f;
      switch (m)
      {
      default: 
        m = j;
        break;
      case 68: 
        m = j;
        if (!zzR(paramObject, n, i)) {
          break label971;
        }
        break;
      case 67: 
        m = j;
        if (!zzR(paramObject, n, i)) {
          break label971;
        }
        break;
      case 66: 
        m = j;
        if (!zzR(paramObject, n, i)) {
          break label971;
        }
        break;
      case 65: 
        m = j;
        if (!zzR(paramObject, n, i)) {
          break label971;
        }
        break;
      case 64: 
        m = j;
        if (!zzR(paramObject, n, i)) {
          break label971;
        }
        break;
      case 63: 
        m = j;
        if (!zzR(paramObject, n, i)) {
          break label971;
        }
        break;
      case 62: 
        m = j;
        if (!zzR(paramObject, n, i)) {
          break label971;
        }
        break;
      case 61: 
        m = j;
        if (!zzR(paramObject, n, i)) {
          break label971;
        }
        break;
      case 60: 
        m = j;
        if (!zzR(paramObject, n, i)) {
          break label971;
        }
        break;
      case 59: 
        m = j;
        if (!zzR(paramObject, n, i)) {
          break label971;
        }
        break;
      case 58: 
        m = j;
        if (!zzR(paramObject, n, i)) {
          break label971;
        }
        m = j * 53;
        bool = zzS(paramObject, l);
        break;
      case 57: 
        m = j;
        if (!zzR(paramObject, n, i)) {
          break label971;
        }
        break;
      case 56: 
        m = j;
        if (!zzR(paramObject, n, i)) {
          break label971;
        }
        break;
      case 55: 
        m = j;
        if (!zzR(paramObject, n, i)) {
          break label971;
        }
        m = j * 53;
        j = zzp(paramObject, l);
        break;
      case 54: 
        m = j;
        if (!zzR(paramObject, n, i)) {
          break label971;
        }
        break;
      case 53: 
        m = j;
        if (!zzR(paramObject, n, i)) {
          break label971;
        }
        m = j * 53;
        l = zzv(paramObject, l);
        break;
      case 52: 
        m = j;
        if (!zzR(paramObject, n, i)) {
          break label971;
        }
        m = j * 53;
        f = zzo(paramObject, l);
        break;
      case 51: 
        m = j;
        if (!zzR(paramObject, n, i)) {
          break label971;
        }
        m = j * 53;
        d = zzn(paramObject, l);
        break;
      case 17: 
        n = j * 53;
        localObject = zzps.zzf(paramObject, l);
        m = n;
        j = k;
        if (localObject != null) {
          m = n;
        }
        break;
      case 10: 
      case 18: 
      case 19: 
      case 20: 
      case 21: 
      case 22: 
      case 23: 
      case 24: 
      case 25: 
      case 26: 
      case 27: 
      case 28: 
      case 29: 
      case 30: 
      case 31: 
      case 32: 
      case 33: 
      case 34: 
      case 35: 
      case 36: 
      case 37: 
      case 38: 
      case 39: 
      case 40: 
      case 41: 
      case 42: 
      case 43: 
      case 44: 
      case 45: 
      case 46: 
      case 47: 
      case 48: 
      case 49: 
      case 50: 
        m = j * 53;
        j = zzps.zzf(paramObject, l).hashCode();
        break;
      case 9: 
        n = j * 53;
        localObject = zzps.zzf(paramObject, l);
        m = n;
        j = k;
        if (localObject != null)
        {
          m = n;
          j = localObject.hashCode();
        }
        m += j;
        break;
      case 8: 
        m = j * 53;
        j = ((String)zzps.zzf(paramObject, l)).hashCode();
        break;
      case 7: 
        m = j * 53;
        bool = zzps.zzw(paramObject, l);
        j = zznl.zza(bool);
        break;
      case 4: 
      case 6: 
      case 11: 
      case 12: 
      case 13: 
      case 15: 
        m = j * 53;
        j = zzps.zzc(paramObject, l);
        break;
      case 2: 
      case 3: 
      case 5: 
      case 14: 
      case 16: 
        m = j * 53;
        l = zzps.zzd(paramObject, l);
        break;
      case 1: 
        m = j * 53;
        f = zzps.zzb(paramObject, l);
        j = Float.floatToIntBits(f);
        m = j + m;
        break;
      }
      m = j * 53;
      double d = zzps.zza(paramObject, l);
      l = Double.doubleToLongBits(d);
      localObject = zznl.zza;
      j = (int)(l ^ l >>> 32);
      m += j;
      label971:
      i += 3;
    }
    j = zzc.hashCode() + j * 53;
    int m = j;
    if (zzh) {
      m = j * 53 + zzb.zza.hashCode();
    }
    return m;
  }
  
  public final int zzc(Object paramObject, byte[] paramArrayOfByte, int paramInt1, int paramInt2, int paramInt3, zzkt paramzzkt)
  {
    Object localObject1 = this;
    int i = paramInt2;
    int j = paramInt3;
    Object localObject2 = paramzzkt;
    zzD(paramObject);
    Object localObject3 = zzb;
    int k = -1;
    int m = -1;
    int n = 0;
    int i1 = n;
    int i2 = i1;
    int i3 = 1048575;
    while (paramInt1 < i)
    {
      i1 = paramInt1 + 1;
      paramInt1 = paramArrayOfByte[paramInt1];
      if (paramInt1 < 0)
      {
        i1 = zzku.zzj(paramInt1, paramArrayOfByte, i1, (zzkt)localObject2);
        paramInt1 = zza;
      }
      int i4 = paramInt1 >>> 3;
      if (i4 > m)
      {
        i = n / 3;
        if ((i4 >= zze) && (i4 <= zzf)) {
          i = ((zzol)localObject1).zzs(i4, i);
        } else {
          i = k;
        }
      }
      else
      {
        i = ((zzol)localObject1).zzq(i4);
      }
      Object localObject4 = null;
      Object localObject6;
      boolean bool1;
      long l2;
      label1252:
      label1280:
      label1326:
      label1423:
      label1426:
      label1617:
      label1620:
      Object localObject7;
      if (i == k)
      {
        localObject5 = localObject1;
        m = k;
        localObject1 = localObject3;
        n = 0;
        i = i4;
        k = i1;
        localObject3 = localObject5;
        i4 = n;
        i1 = paramInt1;
        paramInt1 = j;
        j = m;
      }
      else
      {
        int i5 = paramInt1 & 0x7;
        localObject6 = zzc;
        n = localObject6[(i + 1)];
        k = i4;
        i6 = zzt(n);
        long l1 = n & 0xFFFFF;
        int i7;
        if (i6 <= 17)
        {
          j = localObject6[(i + 2)];
          m = 1 << (j >>> 20);
          j &= 0xFFFFF;
          if (j != i3)
          {
            if (i3 != 1048575) {
              ((Unsafe)localObject3).putInt(paramObject, i3, i2);
            }
            if (j == 1048575) {
              i2 = 0;
            } else {
              i2 = ((Unsafe)localObject3).getInt(paramObject, j);
            }
            i3 = j;
          }
          switch (i6)
          {
          default: 
            localObject1 = this;
            j = i;
            if (i5 == 3)
            {
              localObject5 = ((zzol)localObject1).zzA(paramObject, j);
              i1 = zzku.zzm(localObject5, ((zzol)localObject1).zzx(j), paramArrayOfByte, i1, paramInt2, k << 3 | 0x4, paramzzkt);
              ((zzol)localObject1).zzJ(paramObject, j, localObject5);
              localObject5 = localObject2;
              localObject2 = localObject3;
              i2 |= m;
              i4 = paramInt1;
              paramInt1 = i1;
              m = k;
              localObject3 = localObject1;
              i1 = i4;
            }
            break;
          case 16: 
            if (i5 == 0)
            {
              i1 = zzku.zzl(paramArrayOfByte, i1, (zzkt)localObject2);
              ((Unsafe)localObject3).putLong(paramObject, l1, zzli.zzG(zzb));
              i2 |= m;
            }
            else
            {
              localObject1 = this;
            }
            break;
          case 15: 
            if (i5 == 0)
            {
              i2 |= m;
              i1 = zzku.zzi(paramArrayOfByte, i1, (zzkt)localObject2);
              ((Unsafe)localObject3).putInt(paramObject, l1, zzli.zzF(zza));
              i6 = paramInt2;
              j = paramInt3;
              k = paramInt1;
              i7 = -1;
              localObject1 = this;
              paramInt1 = i1;
              m = i4;
              n = i;
              i1 = k;
              k = i7;
              i = i6;
            }
            break;
          case 12: 
            j = i;
            if (i5 == 0)
            {
              i1 = zzku.zzi(paramArrayOfByte, i1, (zzkt)localObject2);
              i = zza;
              localObject1 = zzw(j);
              if (((n & 0x80000000) != 0) && (localObject1 != null) && (!((zznh)localObject1).zza(i)))
              {
                zzd(paramObject).zzj(paramInt1, Long.valueOf(i));
              }
              else
              {
                i2 |= m;
                ((Unsafe)localObject3).putInt(paramObject, l1, i);
              }
              m = k;
              k = paramInt1;
              paramInt1 = i1;
              n = j;
            }
            else
            {
              localObject1 = this;
              k = i4;
            }
            break;
          case 10: 
            if (i5 == 2)
            {
              k = i2 | m;
              i1 = zzku.zza(paramArrayOfByte, i1, (zzkt)localObject2);
            }
            break;
          case 9: 
          case 8: 
            for (;;)
            {
              ((Unsafe)localObject3).putObject(paramObject, l1, zzc);
              break;
              localObject1 = this;
              j = i;
              if (i5 != 2) {
                break label1280;
              }
              localObject4 = ((zzol)localObject1).zzA(paramObject, j);
              localObject5 = ((zzol)localObject1).zzx(j);
              i1 = zzku.zzn(localObject4, (zzow)localObject5, paramArrayOfByte, i1, paramInt2, paramzzkt);
              ((zzol)localObject1).zzJ(paramObject, j, localObject4);
              i2 = m | i2;
              m = k;
              n = j;
              break label1252;
              if (i5 != 2) {
                break label1280;
              }
              if (zzM(n))
              {
                i1 = zzku.zzi(paramArrayOfByte, i1, (zzkt)localObject2);
                k = zza;
                if (k >= 0)
                {
                  if (k == 0)
                  {
                    zzc = "";
                  }
                  else
                  {
                    zzc = zzpv.zzd(paramArrayOfByte, i1, k);
                    i1 += k;
                  }
                  k = i2 | m;
                }
                else
                {
                  throw new zznn("CodedInputStream encountered an embedded string or message which claimed to have negative size.");
                }
              }
              else
              {
                i1 = zzku.zzg(paramArrayOfByte, i1, (zzkt)localObject2);
                k = i2 | m;
              }
            }
          case 7: 
            if (i5 == 0)
            {
              k = i2 | m;
              i1 = zzku.zzl(paramArrayOfByte, i1, (zzkt)localObject2);
              if (zzb != 0L) {
                bool1 = true;
              } else {
                bool1 = false;
              }
              zzps.zzm(paramObject, l1, bool1);
            }
            break;
          case 6: 
          case 13: 
            if (i5 == 5)
            {
              j = i1 + 4;
              k = i2 | m;
              i2 = zzku.zzb(paramArrayOfByte, i1);
              i1 = j;
            }
            break;
          case 5: 
          case 14: 
            if (i5 == 1)
            {
              j = i1 + 8;
              k = m | i2;
              l2 = zzku.zzp(paramArrayOfByte, i1);
              i1 = j;
            }
            break;
          case 4: 
          case 11: 
            if (i5 == 0)
            {
              k = i2 | m;
              i1 = zzku.zzi(paramArrayOfByte, i1, (zzkt)localObject2);
              i2 = zza;
              ((Unsafe)localObject3).putInt(paramObject, l1, i2);
              i2 = k;
              k = paramInt1;
              n = i;
              m = i4;
              paramInt1 = i1;
              i1 = k;
            }
            break;
          }
        }
        int i8;
        for (;;)
        {
          i = paramInt2;
          j = paramInt3;
          k = -1;
          localObject1 = this;
          break;
          if (i5 == 0)
          {
            k = m | i2;
            i1 = zzku.zzl(paramArrayOfByte, i1, (zzkt)localObject2);
            l2 = zzb;
            localObject1 = this;
            ((Unsafe)localObject3).putLong(paramObject, l1, l2);
            i2 = k;
            n = i;
            m = i4;
            i = paramInt2;
            k = paramInt1;
            i4 = -1;
            j = paramInt3;
            paramInt1 = i1;
            i1 = k;
            k = i4;
            break;
          }
          localObject1 = this;
          break label1326;
          localObject1 = this;
          if (i5 == 5)
          {
            k = i1 + 4;
            i2 |= m;
            zzps.zzp(paramObject, l1, Float.intBitsToFloat(zzku.zzb(paramArrayOfByte, i1)));
          }
          else
          {
            break label1426;
            if (i5 != 1) {
              break label1423;
            }
            k = i1 + 8;
            i2 |= m;
            zzps.zzo(paramObject, l1, Double.longBitsToDouble(zzku.zzp(paramArrayOfByte, i1)));
          }
          localObject1 = this;
          localObject5 = localObject2;
          localObject2 = localObject3;
          i1 = paramInt1;
          localObject3 = localObject1;
          m = i4;
          paramInt1 = k;
          for (;;)
          {
            i4 = paramInt2;
            j = paramInt3;
            k = -1;
            n = i;
            localObject1 = localObject3;
            localObject3 = localObject2;
            localObject2 = localObject5;
            i = i4;
            break;
            localObject1 = this;
            k = i4;
            m = -1;
            i4 = i;
            j = paramInt3;
            localObject5 = localObject3;
            localObject3 = localObject1;
            i = k;
            k = i1;
            i1 = paramInt1;
            paramInt1 = j;
            j = m;
            localObject1 = localObject5;
            break label5999;
            i8 = -1;
            j = i;
            if (i6 != 27) {
              break label1620;
            }
            if (i5 != 2) {
              break label1617;
            }
            localObject5 = (zznk)((Unsafe)localObject3).getObject(paramObject, l1);
            localObject2 = localObject5;
            if (!((zznk)localObject5).zzc())
            {
              i4 = ((List)localObject5).size();
              if (i4 == 0) {
                i4 = 10;
              } else {
                i4 += i4;
              }
              localObject2 = ((zznk)localObject5).zzd(i4);
              ((Unsafe)localObject3).putObject(paramObject, l1, localObject2);
            }
            i4 = zzku.zze(((zzol)localObject1).zzx(j), paramInt1, paramArrayOfByte, i1, paramInt2, (zznk)localObject2, paramzzkt);
            localObject5 = paramzzkt;
            localObject2 = localObject3;
            i1 = paramInt1;
            paramInt1 = i4;
            m = k;
            localObject3 = localObject1;
          }
          break label4997;
          localObject7 = paramzzkt;
          if (i6 <= 49)
          {
            l2 = n;
            localObject1 = zzb;
            localObject5 = (zznk)((Unsafe)localObject1).getObject(paramObject, l1);
            if (!((zznk)localObject5).zzc())
            {
              i = ((List)localObject5).size();
              localObject5 = ((zznk)localObject5).zzd(i + i);
              ((Unsafe)localObject1).putObject(paramObject, l1, localObject5);
            }
            boolean bool2;
            switch (i6)
            {
            default: 
              localObject2 = this;
              i7 = paramInt2;
              n = paramInt1;
              i6 = i1;
              if (i5 == 3)
              {
                i5 = n & 0xFFFFFFF8 | 0x4;
                localObject6 = ((zzol)localObject2).zzx(j);
                bool2 = true;
              }
              break;
            case 34: 
            case 48: 
            case 33: 
            case 47: 
            case 30: 
            case 44: 
            case 28: 
            case 27: 
            case 26: 
            case 25: 
            case 42: 
            case 24: 
            case 31: 
            case 41: 
            case 45: 
            case 23: 
            case 32: 
            case 40: 
            case 46: 
            case 22: 
            case 29: 
            case 39: 
            case 43: 
            case 20: 
            case 21: 
            case 37: 
            case 38: 
            case 19: 
            case 36: 
            case 18: 
            case 35: 
              label2169:
              label2251:
              label2282:
              label2405:
              label2613:
              label2624:
              label2641:
              label2710:
              label2917:
              label2928:
              label3169:
              label3180:
              label3922:
              label3960:
              label4473:
              label4604:
              label4615:
              label4706:
              int i9;
              for (m = zzku.zzc((zzow)localObject6, paramArrayOfByte, i6, paramInt2, i5, paramzzkt);; m = zzku.zzc((zzow)localObject6, paramArrayOfByte, i9, paramInt2, i5, paramzzkt))
              {
                ((List)localObject5).add(zzc);
                break label4706;
                if (i5 == 2)
                {
                  localObject1 = (zznx)localObject5;
                  i = zzku.zzi(paramArrayOfByte, i1, (zzkt)localObject7);
                  i4 = zza + i;
                  while (i < i4)
                  {
                    i = zzku.zzl(paramArrayOfByte, i, (zzkt)localObject7);
                    ((zznx)localObject1).zzg(zzli.zzG(zzb));
                  }
                  if (i != i4) {
                    throw new zznn("While parsing a protocol message, the input ended unexpectedly in the middle of a field.  This could mean either that the input has been truncated or that an embedded message misreported its own length.");
                  }
                }
                else
                {
                  if (i5 != 0) {
                    break label2282;
                  }
                  localObject1 = (zznx)localObject5;
                  for (i4 = zzku.zzl(paramArrayOfByte, i1, (zzkt)localObject7);; i4 = zzku.zzl(paramArrayOfByte, m, (zzkt)localObject7))
                  {
                    ((zznx)localObject1).zzg(zzli.zzG(zzb));
                    i = i4;
                    if (i4 >= paramInt2) {
                      break;
                    }
                    m = zzku.zzi(paramArrayOfByte, i4, (zzkt)localObject7);
                    i = i4;
                    if (paramInt1 != zza) {
                      break;
                    }
                  }
                  if (i5 != 2) {
                    break label2169;
                  }
                  localObject1 = (zzne)localObject5;
                  i = zzku.zzi(paramArrayOfByte, i1, (zzkt)localObject7);
                  i4 = zza + i;
                  while (i < i4)
                  {
                    i = zzku.zzi(paramArrayOfByte, i, (zzkt)localObject7);
                    ((zzne)localObject1).zzh(zzli.zzF(zza));
                  }
                  if (i == i4) {
                    break label2251;
                  }
                }
                throw new zznn("While parsing a protocol message, the input ended unexpectedly in the middle of a field.  This could mean either that the input has been truncated or that an embedded message misreported its own length.");
                if (i5 == 0)
                {
                  localObject1 = (zzne)localObject5;
                  for (i4 = zzku.zzi(paramArrayOfByte, i1, (zzkt)localObject7);; i4 = zzku.zzi(paramArrayOfByte, m, (zzkt)localObject7))
                  {
                    ((zzne)localObject1).zzh(zzli.zzF(zza));
                    i = i4;
                    if (i4 >= paramInt2) {
                      break;
                    }
                    m = zzku.zzi(paramArrayOfByte, i4, (zzkt)localObject7);
                    i = i4;
                    if (paramInt1 != zza) {
                      break;
                    }
                  }
                  localObject1 = this;
                  m = paramInt2;
                  n = paramInt1;
                  i4 = i1;
                  bool1 = true;
                  paramInt1 = i;
                  i1 = n;
                  i = m;
                  break label4827;
                }
                localObject1 = this;
                i = paramInt2;
                i4 = i1;
                bool1 = true;
                i1 = paramInt1;
                paramInt1 = i4;
                break label4818;
                if (i5 == 2) {}
                for (i = zzku.zzf(paramArrayOfByte, i1, (zznk)localObject5, (zzkt)localObject7);; i = zzku.zzk(paramInt1, paramArrayOfByte, i1, paramInt2, (zznk)localObject5, paramzzkt))
                {
                  localObject1 = this;
                  break;
                  if (i5 != 0) {
                    break label2405;
                  }
                }
                zzoy.zzn(paramObject, k, (List)localObject5, ((zzol)localObject1).zzw(j), null, zzm);
                bool1 = true;
                i4 = i;
                i = paramInt2;
                for (;;)
                {
                  localObject1 = this;
                  m = i1;
                  i1 = paramInt1;
                  paramInt1 = i4;
                  i4 = m;
                  break label4827;
                  localObject1 = this;
                  i = paramInt2;
                  bool1 = true;
                  i4 = i1;
                  i1 = paramInt1;
                  paramInt1 = i4;
                  break label4818;
                  i = paramInt2;
                  if (i5 != 2) {
                    break label2710;
                  }
                  n = zzku.zzi(paramArrayOfByte, i1, (zzkt)localObject7);
                  i6 = zza;
                  if (i6 < 0) {
                    break label2641;
                  }
                  if (i6 > paramArrayOfByte.length - n) {
                    break;
                  }
                  m = n;
                  i4 = i6;
                  if (i6 == 0) {}
                  for (i4 = n;; i4 = n)
                  {
                    ((List)localObject5).add(zzle.zzb);
                    do
                    {
                      ((List)localObject5).add(zzle.zzk(paramArrayOfByte, m, i4));
                      i4 = m + i4;
                      if (i4 >= i) {
                        break label2624;
                      }
                      m = zzku.zzi(paramArrayOfByte, i4, (zzkt)localObject7);
                      if (paramInt1 != zza) {
                        break label2624;
                      }
                      n = zzku.zzi(paramArrayOfByte, m, (zzkt)localObject7);
                      i6 = zza;
                      if (i6 < 0) {
                        break label2613;
                      }
                      if (i6 > paramArrayOfByte.length - n) {
                        break;
                      }
                      m = n;
                      i4 = i6;
                    } while (i6 != 0);
                  }
                  throw new zznn("While parsing a protocol message, the input ended unexpectedly in the middle of a field.  This could mean either that the input has been truncated or that an embedded message misreported its own length.");
                  throw new zznn("CodedInputStream encountered an embedded string or message which claimed to have negative size.");
                  bool1 = true;
                }
                throw new zznn("While parsing a protocol message, the input ended unexpectedly in the middle of a field.  This could mean either that the input has been truncated or that an embedded message misreported its own length.");
                throw new zznn("CodedInputStream encountered an embedded string or message which claimed to have negative size.");
                localObject1 = this;
                if (i5 == 2) {
                  i = zzku.zze(((zzol)localObject1).zzx(j), paramInt1, paramArrayOfByte, i1, paramInt2, (zznk)localObject5, paramzzkt);
                }
                for (;;)
                {
                  bool1 = true;
                  m = paramInt2;
                  i4 = i1;
                  localObject1 = this;
                  i1 = paramInt1;
                  paramInt1 = i;
                  i = m;
                  break label4827;
                  localObject1 = this;
                  bool1 = true;
                  i = paramInt2;
                  i4 = i1;
                  i1 = paramInt1;
                  paramInt1 = i4;
                  break label4818;
                  i4 = paramInt1;
                  if (i5 != 2) {
                    break label3180;
                  }
                  if ((l2 & 0x20000000) == 0L)
                  {
                    m = zzku.zzi(paramArrayOfByte, i1, (zzkt)localObject7);
                    i = zza;
                    if (i >= 0)
                    {
                      if (i == 0)
                      {
                        i = m;
                        ((List)localObject5).add("");
                      }
                      else
                      {
                        localObject1 = new String(paramArrayOfByte, m, i, zznl.zza);
                      }
                      for (;;)
                      {
                        ((List)localObject5).add(localObject1);
                        i = m + i;
                        if (i >= paramInt2) {
                          break label2928;
                        }
                        m = zzku.zzi(paramArrayOfByte, i, (zzkt)localObject7);
                        if (i4 != zza) {
                          break label2928;
                        }
                        i = zzku.zzi(paramArrayOfByte, m, (zzkt)localObject7);
                        n = zza;
                        if (n < 0) {
                          break label2917;
                        }
                        if (n == 0) {
                          break;
                        }
                        localObject1 = new String(paramArrayOfByte, i, n, zznl.zza);
                        m = i;
                        i = n;
                      }
                      throw new zznn("CodedInputStream encountered an embedded string or message which claimed to have negative size.");
                    }
                    else
                    {
                      throw new zznn("CodedInputStream encountered an embedded string or message which claimed to have negative size.");
                    }
                  }
                  else
                  {
                    m = zzku.zzi(paramArrayOfByte, i1, (zzkt)localObject7);
                    n = zza;
                    if (n < 0) {
                      break label3169;
                    }
                    if (n == 0)
                    {
                      i = m;
                      ((List)localObject5).add("");
                    }
                    else
                    {
                      i = m + n;
                      if (!zzpv.zze(paramArrayOfByte, m, i)) {
                        break;
                      }
                      ((List)localObject5).add(new String(paramArrayOfByte, m, n, zznl.zza));
                    }
                    for (;;)
                    {
                      if (i < paramInt2)
                      {
                        m = zzku.zzi(paramArrayOfByte, i, (zzkt)localObject7);
                        if (i4 == zza)
                        {
                          i = zzku.zzi(paramArrayOfByte, m, (zzkt)localObject7);
                          n = zza;
                          if (n >= 0)
                          {
                            if (n == 0) {
                              break;
                            }
                            m = i + n;
                            if (zzpv.zze(paramArrayOfByte, i, m))
                            {
                              ((List)localObject5).add(new String(paramArrayOfByte, i, n, zznl.zza));
                              i = m;
                              continue;
                            }
                            throw new zznn("Protocol message had invalid UTF-8.");
                          }
                          throw new zznn("CodedInputStream encountered an embedded string or message which claimed to have negative size.");
                        }
                      }
                    }
                  }
                }
                throw new zznn("Protocol message had invalid UTF-8.");
                throw new zznn("CodedInputStream encountered an embedded string or message which claimed to have negative size.");
                localObject1 = this;
                paramInt1 = i1;
                i = paramInt2;
                bool1 = true;
                i1 = i4;
                break label4818;
                i = i1;
                if (i5 == 2)
                {
                  localObject1 = (zzkv)localObject5;
                  i = zzku.zzi(paramArrayOfByte, i, (zzkt)localObject7);
                  i4 = zza + i;
                  while (i < i4)
                  {
                    i = zzku.zzl(paramArrayOfByte, i, (zzkt)localObject7);
                    if (zzb != 0L) {
                      bool1 = true;
                    } else {
                      bool1 = false;
                    }
                    ((zzkv)localObject1).zze(bool1);
                  }
                  if (i != i4) {
                    throw new zznn("While parsing a protocol message, the input ended unexpectedly in the middle of a field.  This could mean either that the input has been truncated or that an embedded message misreported its own length.");
                  }
                }
                else
                {
                  if (i5 != 0) {
                    break label3960;
                  }
                  localObject1 = (zzkv)localObject5;
                  i = zzku.zzl(paramArrayOfByte, i, (zzkt)localObject7);
                  i4 = i;
                  if (zzb != 0L) {}
                  for (i4 = i;; i4 = i)
                  {
                    bool1 = true;
                    do
                    {
                      bool1 = false;
                      ((zzkv)localObject1).zze(bool1);
                      i = i4;
                      if (i4 >= paramInt2) {
                        break;
                      }
                      m = zzku.zzi(paramArrayOfByte, i4, (zzkt)localObject7);
                      i = i4;
                      if (paramInt1 != zza) {
                        break;
                      }
                      i = zzku.zzl(paramArrayOfByte, m, (zzkt)localObject7);
                      i4 = i;
                    } while (zzb == 0L);
                  }
                  i = i1;
                  if (i5 == 2)
                  {
                    localObject1 = (zzne)localObject5;
                    i = zzku.zzi(paramArrayOfByte, i, (zzkt)localObject7);
                    m = zza;
                    i4 = i + m;
                    if (i4 <= paramArrayOfByte.length)
                    {
                      n = ((zzne)localObject1).size();
                      ((zzne)localObject1).zzi(m / 4 + n);
                      while (i < i4)
                      {
                        ((zzne)localObject1).zzh(zzku.zzb(paramArrayOfByte, i));
                        i += 4;
                      }
                      if (i != i4) {
                        throw new zznn("While parsing a protocol message, the input ended unexpectedly in the middle of a field.  This could mean either that the input has been truncated or that an embedded message misreported its own length.");
                      }
                    }
                    else
                    {
                      throw new zznn("While parsing a protocol message, the input ended unexpectedly in the middle of a field.  This could mean either that the input has been truncated or that an embedded message misreported its own length.");
                    }
                  }
                  else
                  {
                    if (i5 != 5) {
                      break label3960;
                    }
                    i4 = i + 4;
                    localObject1 = (zzne)localObject5;
                    ((zzne)localObject1).zzh(zzku.zzb(paramArrayOfByte, i));
                    for (;;)
                    {
                      i = i4;
                      if (i4 >= paramInt2) {
                        break;
                      }
                      m = zzku.zzi(paramArrayOfByte, i4, (zzkt)localObject7);
                      i = i4;
                      if (paramInt1 != zza) {
                        break;
                      }
                      ((zzne)localObject1).zzh(zzku.zzb(paramArrayOfByte, m));
                      i4 = m + 4;
                    }
                    m = paramInt2;
                    n = paramInt1;
                    i = i1;
                    if (i5 == 2)
                    {
                      localObject1 = (zznx)localObject5;
                      i = zzku.zzi(paramArrayOfByte, i, (zzkt)localObject7);
                      m = zza;
                      i4 = i + m;
                      if (i4 <= paramArrayOfByte.length)
                      {
                        n = ((zznx)localObject1).size();
                        ((zznx)localObject1).zzh(m / 8 + n);
                        while (i < i4)
                        {
                          ((zznx)localObject1).zzg(zzku.zzp(paramArrayOfByte, i));
                          i += 8;
                        }
                        if (i != i4) {
                          throw new zznn("While parsing a protocol message, the input ended unexpectedly in the middle of a field.  This could mean either that the input has been truncated or that an embedded message misreported its own length.");
                        }
                      }
                      else
                      {
                        throw new zznn("While parsing a protocol message, the input ended unexpectedly in the middle of a field.  This could mean either that the input has been truncated or that an embedded message misreported its own length.");
                      }
                    }
                    else
                    {
                      if (i5 == 1)
                      {
                        i4 = i + 8;
                        localObject1 = (zznx)localObject5;
                        ((zznx)localObject1).zzg(zzku.zzp(paramArrayOfByte, i));
                        for (;;)
                        {
                          i = i4;
                          if (i4 >= m) {
                            break;
                          }
                          i6 = zzku.zzi(paramArrayOfByte, i4, (zzkt)localObject7);
                          i = i4;
                          if (n != zza) {
                            break;
                          }
                          ((zznx)localObject1).zzg(zzku.zzp(paramArrayOfByte, i6));
                          i4 = i6 + 8;
                        }
                      }
                      i1 = n;
                      bool1 = true;
                      localObject1 = this;
                      paramInt1 = i;
                      i = m;
                      break label4818;
                      m = paramInt1;
                      n = i1;
                      if (i5 != 2) {
                        break label3922;
                      }
                      i = zzku.zzf(paramArrayOfByte, n, (zznk)localObject5, (zzkt)localObject7);
                    }
                  }
                }
                m = paramInt1;
                paramInt1 = i;
                localObject1 = this;
                i = paramInt2;
                i4 = i1;
                i1 = m;
                for (;;)
                {
                  bool1 = true;
                  break label4827;
                  if (i5 == 0)
                  {
                    i1 = m;
                    localObject1 = this;
                    i4 = n;
                    i = paramInt2;
                    paramInt1 = zzku.zzk(m, paramArrayOfByte, n, paramInt2, (zznk)localObject5, paramzzkt);
                  }
                  else
                  {
                    localObject1 = this;
                    i4 = i1;
                    i = paramInt2;
                    i1 = paramInt1;
                    paramInt1 = i4;
                    break label4473;
                    localObject2 = this;
                    m = paramInt2;
                    n = paramInt1;
                    i6 = i1;
                    if (i5 == 2)
                    {
                      localObject1 = (zznx)localObject5;
                      paramInt1 = zzku.zzi(paramArrayOfByte, i6, (zzkt)localObject7);
                      i1 = zza + paramInt1;
                      while (paramInt1 < i1)
                      {
                        paramInt1 = zzku.zzl(paramArrayOfByte, paramInt1, (zzkt)localObject7);
                        ((zznx)localObject1).zzg(zzb);
                      }
                      if (paramInt1 == i1)
                      {
                        i1 = n;
                        localObject1 = localObject2;
                        i4 = i6;
                        i = m;
                      }
                      else
                      {
                        throw new zznn("While parsing a protocol message, the input ended unexpectedly in the middle of a field.  This could mean either that the input has been truncated or that an embedded message misreported its own length.");
                      }
                    }
                    else
                    {
                      i1 = n;
                      localObject1 = localObject2;
                      paramInt1 = i6;
                      i = m;
                      if (i5 == 0)
                      {
                        localObject5 = (zznx)localObject5;
                        for (i7 = zzku.zzl(paramArrayOfByte, i6, (zzkt)localObject7);; i7 = zzku.zzl(paramArrayOfByte, i5, (zzkt)localObject7))
                        {
                          ((zznx)localObject5).zzg(zzb);
                          paramInt1 = i7;
                          i1 = n;
                          localObject1 = localObject2;
                          i4 = i6;
                          i = m;
                          if (i7 >= m) {
                            break;
                          }
                          i5 = zzku.zzi(paramArrayOfByte, i7, (zzkt)localObject7);
                          paramInt1 = i7;
                          i1 = n;
                          localObject1 = localObject2;
                          i4 = i6;
                          i = m;
                          if (n != zza) {
                            break;
                          }
                        }
                        localObject2 = this;
                        m = paramInt2;
                        i4 = paramInt1;
                        n = i1;
                        if (i5 == 2)
                        {
                          localObject1 = (zzmv)localObject5;
                          paramInt1 = zzku.zzi(paramArrayOfByte, n, (zzkt)localObject7);
                          i6 = zza;
                          i1 = paramInt1 + i6;
                          if (i1 <= paramArrayOfByte.length)
                          {
                            i = ((zzmv)localObject1).size();
                            ((zzmv)localObject1).zzg(i6 / 4 + i);
                            while (paramInt1 < i1)
                            {
                              ((zzmv)localObject1).zzf(Float.intBitsToFloat(zzku.zzb(paramArrayOfByte, paramInt1)));
                              paramInt1 += 4;
                            }
                            if (paramInt1 == i1)
                            {
                              i1 = i4;
                              localObject1 = localObject2;
                              i4 = n;
                              i = m;
                              continue;
                            }
                            throw new zznn("While parsing a protocol message, the input ended unexpectedly in the middle of a field.  This could mean either that the input has been truncated or that an embedded message misreported its own length.");
                          }
                          throw new zznn("While parsing a protocol message, the input ended unexpectedly in the middle of a field.  This could mean either that the input has been truncated or that an embedded message misreported its own length.");
                        }
                        i1 = i4;
                        localObject1 = localObject2;
                        paramInt1 = n;
                        i = m;
                        if (i5 == 5)
                        {
                          paramInt1 = n + 4;
                          localObject1 = (zzmv)localObject5;
                          ((zzmv)localObject1).zzf(Float.intBitsToFloat(zzku.zzb(paramArrayOfByte, n)));
                          while (paramInt1 < m)
                          {
                            i1 = zzku.zzi(paramArrayOfByte, paramInt1, (zzkt)localObject7);
                            if (i4 != zza) {
                              break;
                            }
                            ((zzmv)localObject1).zzf(Float.intBitsToFloat(zzku.zzb(paramArrayOfByte, i1)));
                            paramInt1 = i1 + 4;
                          }
                          i1 = i4;
                          localObject1 = localObject2;
                          i4 = n;
                          i = m;
                          continue;
                        }
                      }
                      bool1 = true;
                      break label4818;
                      localObject1 = this;
                      i = paramInt2;
                      m = paramInt1;
                      i4 = i1;
                      if (i5 != 2) {
                        break label4615;
                      }
                      localObject2 = (zzmi)localObject5;
                      paramInt1 = zzku.zzi(paramArrayOfByte, i4, (zzkt)localObject7);
                      n = zza;
                      i1 = paramInt1 + n;
                      if (i1 > paramArrayOfByte.length) {
                        break label4604;
                      }
                      i6 = ((zzmi)localObject2).size();
                      ((zzmi)localObject2).zzg(n / 8 + i6);
                      while (paramInt1 < i1)
                      {
                        ((zzmi)localObject2).zzf(Double.longBitsToDouble(zzku.zzp(paramArrayOfByte, paramInt1)));
                        paramInt1 += 8;
                      }
                      if (paramInt1 != i1) {
                        break;
                      }
                      i1 = m;
                    }
                  }
                }
                throw new zznn("While parsing a protocol message, the input ended unexpectedly in the middle of a field.  This could mean either that the input has been truncated or that an embedded message misreported its own length.");
                throw new zznn("While parsing a protocol message, the input ended unexpectedly in the middle of a field.  This could mean either that the input has been truncated or that an embedded message misreported its own length.");
                if (i5 != 1) {
                  break;
                }
                paramInt1 = i4 + 8;
                localObject2 = (zzmi)localObject5;
                ((zzmi)localObject2).zzf(Double.longBitsToDouble(zzku.zzp(paramArrayOfByte, i4)));
                while (paramInt1 < i)
                {
                  i1 = zzku.zzi(paramArrayOfByte, paramInt1, (zzkt)localObject7);
                  if (m != zza) {
                    break;
                  }
                  ((zzmi)localObject2).zzf(Double.longBitsToDouble(zzku.zzp(paramArrayOfByte, i1)));
                  paramInt1 = i1 + 8;
                }
                bool1 = true;
                i1 = m;
                break label4827;
                paramInt1 = m;
                i1 = n;
                localObject1 = localObject2;
                i4 = i6;
                i = i7;
                bool1 = bool2;
                if (m >= i7) {
                  break label4827;
                }
                i9 = zzku.zzi(paramArrayOfByte, m, (zzkt)localObject7);
                paramInt1 = m;
                i1 = n;
                localObject1 = localObject2;
                i4 = i6;
                i = i7;
                bool1 = bool2;
                if (n != zza) {
                  break label4827;
                }
              }
            }
            i = paramInt2;
            localObject1 = this;
            i4 = paramInt1;
            bool1 = true;
            paramInt1 = i1;
            i1 = i4;
            label4818:
            m = paramInt1;
            i4 = paramInt1;
            paramInt1 = m;
            label4827:
            localObject5 = localObject3;
            localObject2 = paramzzkt;
            if (paramInt1 != i4)
            {
              i4 = paramInt3;
              i6 = -1;
              localObject3 = localObject5;
              m = k;
              n = j;
              k = i6;
              j = i4;
              break;
            }
            m = paramInt3;
            localObject3 = localObject1;
            i = k;
            k = paramInt1;
            i4 = j;
            paramInt1 = m;
            j = i8;
            localObject1 = localObject5;
            break label5999;
          }
          localObject1 = localObject3;
          localObject2 = this;
          i7 = 1;
          m = paramInt1;
          if (i6 == 50)
          {
            localObject1 = localObject2;
            if (i5 == 2)
            {
              paramArrayOfByte = zzb;
              localObject3 = ((zzol)localObject2).zzz(j);
              localObject1 = paramArrayOfByte.getObject(paramObject, l1);
              if (zzod.zza(localObject1))
              {
                paramzzkt = zzoc.zza().zzb();
                zzod.zzb(paramzzkt, localObject1);
                paramArrayOfByte.putObject(paramObject, l1, paramzzkt);
              }
              paramObject = (zzob)localObject3;
              throw null;
            }
            label4997:
            localObject5 = localObject3;
            m = paramInt3;
            localObject2 = paramzzkt;
            i = k;
            k = i1;
            localObject3 = localObject1;
            i4 = j;
            i1 = paramInt1;
            paramInt1 = m;
            j = i8;
            localObject1 = localObject5;
            break label5999;
          }
          localObject5 = zzb;
          long l3 = localObject6[(j + 2)] & 0xFFFFF;
          switch (i6)
          {
          }
          for (;;)
          {
            break;
            if (i5 == 3)
            {
              localObject3 = ((zzol)localObject2).zzB(paramObject, k, j);
              i4 = zzku.zzm(localObject3, ((zzol)localObject2).zzx(j), paramArrayOfByte, i1, paramInt2, m & 0xFFFFFFF8 | 0x4, paramzzkt);
              ((zzol)localObject2).zzK(paramObject, k, j, localObject3);
              break label5929;
              localObject3 = paramzzkt;
              if (i5 == 0)
              {
                k = zzku.zzl(paramArrayOfByte, i1, (zzkt)localObject3);
                localObject3 = Long.valueOf(zzli.zzG(zzb));
                break label5392;
                localObject3 = paramzzkt;
                if (i5 == 0)
                {
                  k = zzku.zzi(paramArrayOfByte, i1, (zzkt)localObject3);
                  localObject3 = Integer.valueOf(zzli.zzF(zza));
                  break label5392;
                  localObject3 = paramzzkt;
                  if (i5 == 0)
                  {
                    k = zzku.zzi(paramArrayOfByte, i1, (zzkt)localObject3);
                    n = zza;
                    localObject3 = ((zzol)localObject2).zzw(j);
                    if ((localObject3 != null) && (!((zznh)localObject3).zza(n)))
                    {
                      zzd(paramObject).zzj(m, Long.valueOf(n));
                    }
                    else
                    {
                      localObject3 = Integer.valueOf(n);
                      break label5392;
                      localObject3 = paramzzkt;
                      if (i5 != 2) {
                        break label5481;
                      }
                      k = zzku.zza(paramArrayOfByte, i1, (zzkt)localObject3);
                      localObject3 = zzc;
                      label5392:
                      ((Unsafe)localObject5).putObject(paramObject, l1, localObject3);
                      ((Unsafe)localObject5).putInt(paramObject, l3, i4);
                    }
                    j = k;
                    k = i4;
                    i4 = j;
                    break label5714;
                    if (i5 == 2)
                    {
                      localObject3 = ((zzol)localObject2).zzB(paramObject, k, j);
                      i4 = zzku.zzn(localObject3, ((zzol)localObject2).zzx(j), paramArrayOfByte, i1, paramInt2, paramzzkt);
                      ((zzol)localObject2).zzK(paramObject, k, j, localObject3);
                      break label5929;
                    }
                  }
                }
              }
              label5481:
              k = i4;
              break label5604;
              localObject3 = paramzzkt;
              if (i5 == 2)
              {
                k = zzku.zzi(paramArrayOfByte, i1, (zzkt)localObject3);
                m = zza;
                if (m == 0)
                {
                  ((Unsafe)localObject5).putObject(paramObject, l1, "");
                }
                else
                {
                  j = k + m;
                  if (((n & 0x20000000) != 0) && (!zzpv.zze(paramArrayOfByte, k, j))) {
                    throw new zznn("Protocol message had invalid UTF-8.");
                  }
                  ((Unsafe)localObject5).putObject(paramObject, l1, new String(paramArrayOfByte, k, m, zznl.zza));
                  k = j;
                }
              }
              else
              {
                label5604:
                break label5717;
                localObject3 = paramzzkt;
                if (i5 != 0) {
                  break label5717;
                }
                k = zzku.zzl(paramArrayOfByte, i1, (zzkt)localObject3);
                if (zzb != 0L) {
                  bool1 = true;
                } else {
                  bool1 = false;
                }
                localObject3 = Boolean.valueOf(bool1);
                break label5682;
                j = i1;
                if (i5 != 5) {
                  break label5717;
                }
                k = j + 4;
                localObject3 = Integer.valueOf(zzku.zzb(paramArrayOfByte, j));
                label5682:
                ((Unsafe)localObject5).putObject(paramObject, l1, localObject3);
              }
              j = i4;
              ((Unsafe)localObject5).putInt(paramObject, l3, j);
              i4 = k;
              k = j;
              label5714:
              break label5929;
              label5717:
              break;
              j = i1;
              if (i5 == i7)
              {
                k = j + 8;
                l2 = zzku.zzp(paramArrayOfByte, j);
                j = k;
                break label5811;
                localObject3 = paramzzkt;
                if (i5 == 0)
                {
                  j = zzku.zzi(paramArrayOfByte, i1, (zzkt)localObject3);
                  localObject3 = Integer.valueOf(zza);
                  break label5894;
                  localObject3 = paramzzkt;
                  if (i5 == 0)
                  {
                    j = zzku.zzl(paramArrayOfByte, i1, (zzkt)localObject3);
                    l2 = zzb;
                    label5811:
                    localObject3 = Long.valueOf(l2);
                    break label5894;
                    j = i1;
                    if (i5 == 5)
                    {
                      k = j + 4;
                      localObject3 = Float.valueOf(Float.intBitsToFloat(zzku.zzb(paramArrayOfByte, j)));
                      j = k;
                      break label5894;
                      j = i1;
                      if (i5 == i7)
                      {
                        k = j + 8;
                        localObject3 = Double.valueOf(Double.longBitsToDouble(zzku.zzp(paramArrayOfByte, j)));
                        j = k;
                        label5894:
                        k = i4;
                        ((Unsafe)localObject5).putObject(paramObject, l1, localObject3);
                        ((Unsafe)localObject5).putInt(paramObject, l3, k);
                        i4 = j;
                        break label5929;
                      }
                    }
                  }
                }
              }
            }
          }
          i4 = i1;
          label5929:
          j = i;
          i = paramInt1;
          localObject2 = paramzzkt;
          localObject3 = this;
          if (i4 == i1) {
            break label5972;
          }
          paramInt1 = i4;
          i1 = i;
          localObject3 = localObject1;
          m = k;
          n = j;
        }
        label5972:
        paramInt1 = paramInt3;
        m = i4;
        i4 = j;
        j = i8;
        i1 = i;
        i = k;
        k = m;
      }
      label5999:
      if ((i1 == paramInt1) && (paramInt1 != 0))
      {
        paramInt3 = k;
        paramArrayOfByte = (byte[])localObject3;
        localObject3 = localObject1;
        break label6617;
      }
      if (zzh)
      {
        localObject5 = zzd;
        localObject7 = zzmo.zza;
        m = zzos.zza;
        if (localObject5 != zzmo.zza)
        {
          localObject7 = ((zzmo)localObject5).zza(zzg, i);
          if (localObject7 == null)
          {
            k = zzku.zzh(i1, paramArrayOfByte, k, paramInt2, zzd(paramObject), paramzzkt);
            break label6563;
          }
          localObject5 = (zzna)paramObject;
          ((zzna)localObject5).zzi();
          localObject6 = zzb;
          localObject5 = zza.zzb;
          if (localObject5 != zzpw.zzn)
          {
            switch (((Enum)localObject5).ordinal())
            {
            default: 
              localObject5 = localObject4;
              break;
            case 17: 
              k = zzku.zzl(paramArrayOfByte, k, (zzkt)localObject2);
              l2 = zzli.zzG(zzb);
              break;
            case 16: 
              k = zzku.zzi(paramArrayOfByte, k, (zzkt)localObject2);
              m = zzli.zzF(zza);
              break;
            case 13: 
              throw new IllegalStateException("Shouldn't reach here.");
            case 11: 
              k = zzku.zza(paramArrayOfByte, k, (zzkt)localObject2);
              break;
            case 10: 
              throw null;
            case 9: 
              throw null;
            case 8: 
              k = zzku.zzg(paramArrayOfByte, k, (zzkt)localObject2);
              localObject5 = zzc;
              break;
            case 7: 
              k = zzku.zzl(paramArrayOfByte, k, (zzkt)localObject2);
              if (zzb != 0L) {
                bool1 = true;
              } else {
                bool1 = false;
              }
              localObject5 = Boolean.valueOf(bool1);
              break;
            case 6: 
            case 14: 
              m = k + 4;
              localObject5 = Integer.valueOf(zzku.zzb(paramArrayOfByte, k));
              k = m;
              break;
            case 5: 
            case 15: 
              m = k + 8;
              localObject5 = Long.valueOf(zzku.zzp(paramArrayOfByte, k));
              k = m;
              break;
            case 4: 
            case 12: 
              k = zzku.zzi(paramArrayOfByte, k, (zzkt)localObject2);
              m = zza;
              localObject5 = Integer.valueOf(m);
              break;
            case 2: 
            case 3: 
              k = zzku.zzl(paramArrayOfByte, k, (zzkt)localObject2);
              l2 = zzb;
              localObject5 = Long.valueOf(l2);
              break;
            case 1: 
              m = k + 4;
              localObject5 = Float.valueOf(Float.intBitsToFloat(zzku.zzb(paramArrayOfByte, k)));
              k = m;
              break;
            }
            m = k + 8;
            localObject5 = Double.valueOf(Double.longBitsToDouble(zzku.zzp(paramArrayOfByte, k)));
            k = m;
            ((zzmt)localObject6).zzi(zza, localObject5);
            break label6563;
          }
          zzku.zzi(paramArrayOfByte, k, (zzkt)localObject2);
          throw null;
        }
      }
      k = zzku.zzh(i1, paramArrayOfByte, k, paramInt2, zzd(paramObject), paramzzkt);
      label6563:
      m = i;
      i = paramInt2;
      Object localObject5 = localObject1;
      int i6 = paramInt1;
      paramInt1 = k;
      n = i4;
      localObject1 = localObject3;
      k = j;
      localObject3 = localObject5;
      j = i6;
    }
    paramInt2 = i;
    paramArrayOfByte = (byte[])localObject1;
    paramInt3 = paramInt1;
    paramInt1 = j;
    label6617:
    if (i3 != 1048575) {
      ((Unsafe)localObject3).putInt(paramObject, i3, i2);
    }
    for (k = zzk; k < zzl; k++)
    {
      paramzzkt = zzj;
      localObject3 = zzm;
      zzy(paramObject, paramzzkt[k], null, (zzpl)localObject3, paramObject);
    }
    if (paramInt1 == 0)
    {
      if (paramInt3 != paramInt2) {
        throw new zznn("Failed to parse the message.");
      }
    }
    else {
      if ((paramInt3 > paramInt2) || (i1 != paramInt1)) {
        break label6724;
      }
    }
    return paramInt3;
    label6724:
    throw new zznn("Failed to parse the message.");
  }
  
  public final Object zze()
  {
    return ((zznd)zzg).zzv();
  }
  
  public final void zzf(Object paramObject)
  {
    if (zzQ(paramObject))
    {
      boolean bool = paramObject instanceof zznd;
      int i = 0;
      if (bool)
      {
        localObject1 = (zznd)paramObject;
        ((zznd)localObject1).zzJ(Integer.MAX_VALUE);
        zza = 0;
        ((zznd)localObject1).zzH();
      }
      Object localObject1 = zzc;
      while (i < localObject1.length)
      {
        int j = zzu(i);
        int k = zzt(j);
        long l = 0xFFFFF & j;
        if (k != 9)
        {
          if ((k != 60) && (k != 68)) {}
          switch (k)
          {
          default: 
            break;
          case 50: 
            Unsafe localUnsafe = zzb;
            Object localObject2 = localUnsafe.getObject(paramObject, l);
            if (localObject2 == null) {
              break label363;
            }
            ((zzoc)localObject2).zzc();
            localUnsafe.putObject(paramObject, l, localObject2);
            break;
          case 18: 
          case 19: 
          case 20: 
          case 21: 
          case 22: 
          case 23: 
          case 24: 
          case 25: 
          case 26: 
          case 27: 
          case 28: 
          case 29: 
          case 30: 
          case 31: 
          case 32: 
          case 33: 
          case 34: 
          case 35: 
          case 36: 
          case 37: 
          case 38: 
          case 39: 
          case 40: 
          case 41: 
          case 42: 
          case 43: 
          case 44: 
          case 45: 
          case 46: 
          case 47: 
          case 48: 
          case 49: 
            ((zznk)zzps.zzf(paramObject, l)).zzb();
            break label363;
            if (!zzR(paramObject, zzc[i], i)) {
              break label363;
            }
            break;
          }
        }
        else
        {
          if (!zzN(paramObject, i)) {
            break label363;
          }
        }
        zzx(i).zzf(zzb.getObject(paramObject, l));
        label363:
        i += 3;
      }
      zzm.zzi(paramObject);
      if (zzh) {
        zzn.zza(paramObject);
      }
    }
  }
  
  /* Error */
  public final void zzg(Object paramObject1, Object paramObject2)
  {
    // Byte code:
    //   0: aload_1
    //   1: invokestatic 583	com/google/android/recaptcha/internal/zzol:zzD	(Ljava/lang/Object;)V
    //   4: aload_2
    //   5: invokevirtual 341	java/lang/Object:getClass	()Ljava/lang/Class;
    //   8: pop
    //   9: iconst_0
    //   10: istore_3
    //   11: iload_3
    //   12: aload_0
    //   13: getfield 47	com/google/android/recaptcha/internal/zzol:zzc	[I
    //   16: arraylength
    //   17: if_icmpge +823 -> 840
    //   20: aload_0
    //   21: iload_3
    //   22: invokespecial 83	com/google/android/recaptcha/internal/zzol:zzu	(I)I
    //   25: istore 4
    //   27: aload_0
    //   28: getfield 47	com/google/android/recaptcha/internal/zzol:zzc	[I
    //   31: astore 5
    //   33: iload 4
    //   35: invokestatic 244	com/google/android/recaptcha/internal/zzol:zzt	(I)I
    //   38: istore 6
    //   40: aload 5
    //   42: iload_3
    //   43: iaload
    //   44: istore 7
    //   46: ldc 91
    //   48: iload 4
    //   50: iand
    //   51: i2l
    //   52: lstore 8
    //   54: iload 6
    //   56: tableswitch	default:+292->348, 0:+751->807, 1:+727->783, 2:+703->759, 3:+691->747, 4:+667->723, 5:+655->711, 6:+643->699, 7:+619->675, 8:+595->651, 9:+585->641, 10:+573->629, 11:+561->617, 12:+549->605, 13:+537->593, 14:+525->581, 15:+513->569, 16:+501->557, 17:+585->641, 18:+382->438, 19:+382->438, 20:+382->438, 21:+382->438, 22:+382->438, 23:+382->438, 24:+382->438, 25:+382->438, 26:+382->438, 27:+382->438, 28:+382->438, 29:+382->438, 30:+382->438, 31:+382->438, 32:+382->438, 33:+382->438, 34:+382->438, 35:+382->438, 36:+382->438, 37:+382->438, 38:+382->438, 39:+382->438, 40:+382->438, 41:+382->438, 42:+382->438, 43:+382->438, 44:+382->438, 45:+382->438, 46:+382->438, 47:+382->438, 48:+382->438, 49:+382->438, 50:+353->409, 51:+319->375, 52:+319->375, 53:+319->375, 54:+319->375, 55:+319->375, 56:+319->375, 57:+319->375, 58:+319->375, 59:+319->375, 60:+309->365, 61:+295->351, 62:+295->351, 63:+295->351, 64:+295->351, 65:+295->351, 66:+295->351, 67:+295->351, 68:+309->365
    //   348: goto +486 -> 834
    //   351: aload_0
    //   352: aload_2
    //   353: iload 7
    //   355: iload_3
    //   356: invokespecial 110	com/google/android/recaptcha/internal/zzol:zzR	(Ljava/lang/Object;II)Z
    //   359: ifeq +475 -> 834
    //   362: goto +24 -> 386
    //   365: aload_0
    //   366: aload_1
    //   367: aload_2
    //   368: iload_3
    //   369: invokespecial 852	com/google/android/recaptcha/internal/zzol:zzF	(Ljava/lang/Object;Ljava/lang/Object;I)V
    //   372: goto +462 -> 834
    //   375: aload_0
    //   376: aload_2
    //   377: iload 7
    //   379: iload_3
    //   380: invokespecial 110	com/google/android/recaptcha/internal/zzol:zzR	(Ljava/lang/Object;II)Z
    //   383: ifeq +451 -> 834
    //   386: aload_1
    //   387: lload 8
    //   389: aload_2
    //   390: lload 8
    //   392: invokestatic 247	com/google/android/recaptcha/internal/zzps:zzf	(Ljava/lang/Object;J)Ljava/lang/Object;
    //   395: invokestatic 216	com/google/android/recaptcha/internal/zzps:zzs	(Ljava/lang/Object;JLjava/lang/Object;)V
    //   398: aload_0
    //   399: aload_1
    //   400: iload 7
    //   402: iload_3
    //   403: invokespecial 203	com/google/android/recaptcha/internal/zzol:zzI	(Ljava/lang/Object;II)V
    //   406: goto +428 -> 834
    //   409: getstatic 458	com/google/android/recaptcha/internal/zzoy:zza	I
    //   412: istore 4
    //   414: aload_1
    //   415: lload 8
    //   417: aload_1
    //   418: lload 8
    //   420: invokestatic 247	com/google/android/recaptcha/internal/zzps:zzf	(Ljava/lang/Object;J)Ljava/lang/Object;
    //   423: aload_2
    //   424: lload 8
    //   426: invokestatic 247	com/google/android/recaptcha/internal/zzps:zzf	(Ljava/lang/Object;J)Ljava/lang/Object;
    //   429: invokestatic 764	com/google/android/recaptcha/internal/zzod:zzb	(Ljava/lang/Object;Ljava/lang/Object;)Ljava/lang/Object;
    //   432: invokestatic 216	com/google/android/recaptcha/internal/zzps:zzs	(Ljava/lang/Object;JLjava/lang/Object;)V
    //   435: goto +399 -> 834
    //   438: aload_1
    //   439: lload 8
    //   441: invokestatic 247	com/google/android/recaptcha/internal/zzps:zzf	(Ljava/lang/Object;J)Ljava/lang/Object;
    //   444: checkcast 679	com/google/android/recaptcha/internal/zznk
    //   447: astore 10
    //   449: aload_2
    //   450: lload 8
    //   452: invokestatic 247	com/google/android/recaptcha/internal/zzps:zzf	(Ljava/lang/Object;J)Ljava/lang/Object;
    //   455: checkcast 679	com/google/android/recaptcha/internal/zznk
    //   458: astore 11
    //   460: aload 10
    //   462: invokeinterface 461 1 0
    //   467: istore 6
    //   469: aload 11
    //   471: invokeinterface 461 1 0
    //   476: istore 4
    //   478: aload 10
    //   480: astore 5
    //   482: iload 6
    //   484: ifle +50 -> 534
    //   487: aload 10
    //   489: astore 5
    //   491: iload 4
    //   493: ifle +41 -> 534
    //   496: aload 10
    //   498: astore 5
    //   500: aload 10
    //   502: invokeinterface 681 1 0
    //   507: ifne +17 -> 524
    //   510: aload 10
    //   512: iload 4
    //   514: iload 6
    //   516: iadd
    //   517: invokeinterface 684 2 0
    //   522: astore 5
    //   524: aload 5
    //   526: aload 11
    //   528: invokeinterface 856 2 0
    //   533: pop
    //   534: iload 6
    //   536: ifgt +10 -> 546
    //   539: aload 11
    //   541: astore 5
    //   543: goto +3 -> 546
    //   546: aload_1
    //   547: lload 8
    //   549: aload 5
    //   551: invokestatic 216	com/google/android/recaptcha/internal/zzps:zzs	(Ljava/lang/Object;JLjava/lang/Object;)V
    //   554: goto +280 -> 834
    //   557: aload_0
    //   558: aload_2
    //   559: iload_3
    //   560: invokespecial 87	com/google/android/recaptcha/internal/zzol:zzN	(Ljava/lang/Object;I)Z
    //   563: ifeq +271 -> 834
    //   566: goto +202 -> 768
    //   569: aload_0
    //   570: aload_2
    //   571: iload_3
    //   572: invokespecial 87	com/google/android/recaptcha/internal/zzol:zzN	(Ljava/lang/Object;I)Z
    //   575: ifeq +259 -> 834
    //   578: goto +36 -> 614
    //   581: aload_0
    //   582: aload_2
    //   583: iload_3
    //   584: invokespecial 87	com/google/android/recaptcha/internal/zzol:zzN	(Ljava/lang/Object;I)Z
    //   587: ifeq +247 -> 834
    //   590: goto +178 -> 768
    //   593: aload_0
    //   594: aload_2
    //   595: iload_3
    //   596: invokespecial 87	com/google/android/recaptcha/internal/zzol:zzN	(Ljava/lang/Object;I)Z
    //   599: ifeq +235 -> 834
    //   602: goto +12 -> 614
    //   605: aload_0
    //   606: aload_2
    //   607: iload_3
    //   608: invokespecial 87	com/google/android/recaptcha/internal/zzol:zzN	(Ljava/lang/Object;I)Z
    //   611: ifeq +223 -> 834
    //   614: goto +118 -> 732
    //   617: aload_0
    //   618: aload_2
    //   619: iload_3
    //   620: invokespecial 87	com/google/android/recaptcha/internal/zzol:zzN	(Ljava/lang/Object;I)Z
    //   623: ifeq +211 -> 834
    //   626: goto +106 -> 732
    //   629: aload_0
    //   630: aload_2
    //   631: iload_3
    //   632: invokespecial 87	com/google/android/recaptcha/internal/zzol:zzN	(Ljava/lang/Object;I)Z
    //   635: ifeq +199 -> 834
    //   638: goto +22 -> 660
    //   641: aload_0
    //   642: aload_1
    //   643: aload_2
    //   644: iload_3
    //   645: invokespecial 858	com/google/android/recaptcha/internal/zzol:zzE	(Ljava/lang/Object;Ljava/lang/Object;I)V
    //   648: goto +186 -> 834
    //   651: aload_0
    //   652: aload_2
    //   653: iload_3
    //   654: invokespecial 87	com/google/android/recaptcha/internal/zzol:zzN	(Ljava/lang/Object;I)Z
    //   657: ifeq +177 -> 834
    //   660: aload_1
    //   661: lload 8
    //   663: aload_2
    //   664: lload 8
    //   666: invokestatic 247	com/google/android/recaptcha/internal/zzps:zzf	(Ljava/lang/Object;J)Ljava/lang/Object;
    //   669: invokestatic 216	com/google/android/recaptcha/internal/zzps:zzs	(Ljava/lang/Object;JLjava/lang/Object;)V
    //   672: goto +156 -> 828
    //   675: aload_0
    //   676: aload_2
    //   677: iload_3
    //   678: invokespecial 87	com/google/android/recaptcha/internal/zzol:zzN	(Ljava/lang/Object;I)Z
    //   681: ifeq +153 -> 834
    //   684: aload_1
    //   685: lload 8
    //   687: aload_2
    //   688: lload 8
    //   690: invokestatic 264	com/google/android/recaptcha/internal/zzps:zzw	(Ljava/lang/Object;J)Z
    //   693: invokestatic 657	com/google/android/recaptcha/internal/zzps:zzm	(Ljava/lang/Object;JZ)V
    //   696: goto +132 -> 828
    //   699: aload_0
    //   700: aload_2
    //   701: iload_3
    //   702: invokespecial 87	com/google/android/recaptcha/internal/zzol:zzN	(Ljava/lang/Object;I)Z
    //   705: ifeq +129 -> 834
    //   708: goto +24 -> 732
    //   711: aload_0
    //   712: aload_2
    //   713: iload_3
    //   714: invokespecial 87	com/google/android/recaptcha/internal/zzol:zzN	(Ljava/lang/Object;I)Z
    //   717: ifeq +117 -> 834
    //   720: goto +48 -> 768
    //   723: aload_0
    //   724: aload_2
    //   725: iload_3
    //   726: invokespecial 87	com/google/android/recaptcha/internal/zzol:zzN	(Ljava/lang/Object;I)Z
    //   729: ifeq +105 -> 834
    //   732: aload_1
    //   733: lload 8
    //   735: aload_2
    //   736: lload 8
    //   738: invokestatic 230	com/google/android/recaptcha/internal/zzps:zzc	(Ljava/lang/Object;J)I
    //   741: invokestatic 234	com/google/android/recaptcha/internal/zzps:zzq	(Ljava/lang/Object;JI)V
    //   744: goto +84 -> 828
    //   747: aload_0
    //   748: aload_2
    //   749: iload_3
    //   750: invokespecial 87	com/google/android/recaptcha/internal/zzol:zzN	(Ljava/lang/Object;I)Z
    //   753: ifeq +81 -> 834
    //   756: goto +12 -> 768
    //   759: aload_0
    //   760: aload_2
    //   761: iload_3
    //   762: invokespecial 87	com/google/android/recaptcha/internal/zzol:zzN	(Ljava/lang/Object;I)Z
    //   765: ifeq +69 -> 834
    //   768: aload_1
    //   769: lload 8
    //   771: aload_2
    //   772: lload 8
    //   774: invokestatic 250	com/google/android/recaptcha/internal/zzps:zzd	(Ljava/lang/Object;J)J
    //   777: invokestatic 860	com/google/android/recaptcha/internal/zzps:zzr	(Ljava/lang/Object;JJ)V
    //   780: goto +48 -> 828
    //   783: aload_0
    //   784: aload_2
    //   785: iload_3
    //   786: invokespecial 87	com/google/android/recaptcha/internal/zzol:zzN	(Ljava/lang/Object;I)Z
    //   789: ifeq +45 -> 834
    //   792: aload_1
    //   793: lload 8
    //   795: aload_2
    //   796: lload 8
    //   798: invokestatic 267	com/google/android/recaptcha/internal/zzps:zzb	(Ljava/lang/Object;J)F
    //   801: invokestatic 670	com/google/android/recaptcha/internal/zzps:zzp	(Ljava/lang/Object;JF)V
    //   804: goto +24 -> 828
    //   807: aload_0
    //   808: aload_2
    //   809: iload_3
    //   810: invokespecial 87	com/google/android/recaptcha/internal/zzol:zzN	(Ljava/lang/Object;I)Z
    //   813: ifeq +21 -> 834
    //   816: aload_1
    //   817: lload 8
    //   819: aload_2
    //   820: lload 8
    //   822: invokestatic 276	com/google/android/recaptcha/internal/zzps:zza	(Ljava/lang/Object;J)D
    //   825: invokestatic 677	com/google/android/recaptcha/internal/zzps:zzo	(Ljava/lang/Object;JD)V
    //   828: aload_0
    //   829: aload_1
    //   830: iload_3
    //   831: invokespecial 187	com/google/android/recaptcha/internal/zzol:zzH	(Ljava/lang/Object;I)V
    //   834: iinc 3 3
    //   837: goto -826 -> 11
    //   840: aload_0
    //   841: getfield 69	com/google/android/recaptcha/internal/zzol:zzm	Lcom/google/android/recaptcha/internal/zzpl;
    //   844: aload_1
    //   845: aload_2
    //   846: invokestatic 863	com/google/android/recaptcha/internal/zzoy:zzq	(Lcom/google/android/recaptcha/internal/zzpl;Ljava/lang/Object;Ljava/lang/Object;)V
    //   849: aload_0
    //   850: getfield 61	com/google/android/recaptcha/internal/zzol:zzh	Z
    //   853: ifeq +12 -> 865
    //   856: aload_0
    //   857: getfield 71	com/google/android/recaptcha/internal/zzol:zzn	Lcom/google/android/recaptcha/internal/zzmp;
    //   860: aload_1
    //   861: aload_2
    //   862: invokestatic 866	com/google/android/recaptcha/internal/zzoy:zzp	(Lcom/google/android/recaptcha/internal/zzmp;Ljava/lang/Object;Ljava/lang/Object;)V
    //   865: return
    // Local variable table:
    //   start	length	slot	name	signature
    //   0	866	0	this	zzol
    //   0	866	1	paramObject1	Object
    //   0	866	2	paramObject2	Object
    //   10	825	3	i	int
    //   25	492	4	j	int
    //   31	519	5	localObject	Object
    //   38	497	6	k	int
    //   44	357	7	m	int
    //   52	769	8	l	long
    //   447	64	10	localzznk1	zznk
    //   458	82	11	localzznk2	zznk
  }
  
  public final void zzh(Object paramObject, zzov paramzzov, zzmo paramzzmo)
  {
    paramzzmo.getClass();
    zzD(paramObject);
    zzpl localzzpl = zzm;
    Object localObject1 = null;
    Object localObject3 = localObject1;
    for (;;)
    {
      Object localObject4 = localObject1;
      try
      {
        i = paramzzov.zzc();
        localObject4 = localObject1;
        j = zzq(i);
        if (j < 0)
        {
          if (i == Integer.MAX_VALUE) {
            for (k = zzk;; k++)
            {
              paramzzov = (zzov)localObject1;
              if (k >= zzl) {
                break;
              }
              zzy(paramObject, zzj[k], localObject1, localzzpl, paramObject);
            }
          }
          localObject4 = localObject1;
          if (!zzh)
          {
            localObject5 = null;
          }
          else
          {
            localObject4 = localObject1;
            localObject5 = paramzzmo.zza(zzg, i);
          }
          if (localObject5 != null)
          {
            localObject6 = localObject3;
            if (localObject3 == null)
            {
              localObject4 = localObject1;
              localObject6 = ((zzna)paramObject).zzi();
            }
            localObject4 = localObject1;
            localObject3 = zza;
            localObject4 = localObject1;
            localObject7 = zzpw.zzn;
            localObject4 = localObject1;
            localObject3 = zzb;
            if (localObject3 != localObject7)
            {
              localObject4 = localObject1;
              switch (((Enum)localObject3).ordinal())
              {
              default: 
                break;
              case 17: 
                localObject4 = localObject1;
                l = paramzzov.zzn();
              case 16: 
              case 15: 
              case 14: 
              case 13: 
              case 12: 
              case 11: 
              case 10: 
              case 9: 
              case 8: 
              case 7: 
              case 6: 
              case 5: 
              case 4: 
              case 3: 
              case 2: 
                for (;;)
                {
                  localObject4 = localObject1;
                  localObject7 = Long.valueOf(l);
                  break label855;
                  localObject4 = localObject1;
                  k = paramzzov.zzi();
                  for (;;)
                  {
                    localObject4 = localObject1;
                    localObject7 = Integer.valueOf(k);
                    break label855;
                    localObject4 = localObject1;
                    l = paramzzov.zzm();
                    break label311;
                    localObject4 = localObject1;
                    k = paramzzov.zzh();
                    continue;
                    localObject4 = localObject1;
                    paramzzov = new java/lang/IllegalStateException;
                    localObject4 = localObject1;
                    paramzzov.<init>("Shouldn't reach here.");
                    localObject4 = localObject1;
                    throw paramzzov;
                    localObject4 = localObject1;
                    k = paramzzov.zzj();
                    continue;
                    localObject4 = localObject1;
                    localObject7 = paramzzov.zzp();
                    break label855;
                    localObject4 = localObject1;
                    localObject3 = ((zzmt)localObject6).zze(zza);
                    localObject4 = localObject1;
                    if ((localObject3 instanceof zznd))
                    {
                      localObject4 = localObject1;
                      localObject8 = zzos.zza().zzb(localObject3.getClass());
                      localObject7 = localObject3;
                      localObject4 = localObject1;
                      if (!((zznd)localObject3).zzL())
                      {
                        localObject4 = localObject1;
                        localObject7 = ((zzow)localObject8).zze();
                        localObject4 = localObject1;
                        ((zzow)localObject8).zzg(localObject7, localObject3);
                        localObject4 = localObject1;
                        ((zzmt)localObject6).zzi(zza, localObject7);
                      }
                      localObject4 = localObject1;
                      paramzzov.zzu(localObject7, (zzow)localObject8, paramzzmo);
                      localObject3 = localObject6;
                      break;
                    }
                    localObject4 = localObject1;
                    throw null;
                    localObject4 = localObject1;
                    localObject3 = ((zzmt)localObject6).zze(zza);
                    localObject4 = localObject1;
                    if ((localObject3 instanceof zznd))
                    {
                      localObject4 = localObject1;
                      localObject8 = zzos.zza().zzb(localObject3.getClass());
                      localObject7 = localObject3;
                      localObject4 = localObject1;
                      if (!((zznd)localObject3).zzL())
                      {
                        localObject4 = localObject1;
                        localObject7 = ((zzow)localObject8).zze();
                        localObject4 = localObject1;
                        ((zzow)localObject8).zzg(localObject7, localObject3);
                        localObject4 = localObject1;
                        ((zzmt)localObject6).zzi(zza, localObject7);
                      }
                      localObject4 = localObject1;
                      paramzzov.zzt(localObject7, (zzow)localObject8, paramzzmo);
                      localObject3 = localObject6;
                      break;
                    }
                    localObject4 = localObject1;
                    throw null;
                    localObject4 = localObject1;
                    localObject7 = paramzzov.zzr();
                    break label855;
                    localObject4 = localObject1;
                    localObject7 = Boolean.valueOf(paramzzov.zzN());
                    break label855;
                    localObject4 = localObject1;
                    k = paramzzov.zzf();
                    continue;
                    localObject4 = localObject1;
                    l = paramzzov.zzk();
                    break label311;
                    localObject4 = localObject1;
                    k = paramzzov.zzg();
                  }
                  localObject4 = localObject1;
                  l = paramzzov.zzo();
                  continue;
                  localObject4 = localObject1;
                  l = paramzzov.zzl();
                }
              case 1: 
                localObject4 = localObject1;
                localObject7 = Float.valueOf(paramzzov.zzb());
                break;
              case 0: 
                label311:
                localObject4 = localObject1;
                localObject7 = Double.valueOf(paramzzov.zza());
                break;
              }
              localObject7 = null;
              label855:
              localObject4 = localObject1;
              k = zza.zzb.ordinal();
              if ((k != 9) && (k != 10))
              {
                localObject3 = localObject7;
              }
              else
              {
                localObject4 = localObject1;
                localObject8 = ((zzmt)localObject6).zze(zza);
                localObject3 = localObject7;
                if (localObject8 != null)
                {
                  localObject4 = localObject1;
                  localObject3 = zznl.zza;
                  localObject4 = localObject1;
                  localObject3 = ((zzoi)localObject8).zzae().zzc((zzoi)localObject7).zzl();
                }
              }
              localObject4 = localObject1;
              ((zzmt)localObject6).zzi(zza, localObject3);
              localObject3 = localObject6;
              continue;
            }
            localObject4 = localObject1;
            paramzzov.zzg();
            localObject4 = localObject1;
            throw null;
          }
          localObject7 = localObject1;
          if (localObject1 == null)
          {
            localObject4 = localObject1;
            localObject7 = localzzpl.zza(paramObject);
          }
          localObject4 = localObject7;
          bool = localzzpl.zzk(localObject7, paramzzov, 0);
          localObject1 = localObject7;
          if (bool) {
            continue;
          }
          for (k = zzk;; k++)
          {
            paramzzov = (zzov)localObject7;
            if (k >= zzl) {
              break;
            }
            zzy(paramObject, zzj[k], localObject7, localzzpl, paramObject);
          }
        }
      }
      finally
      {
        int i;
        int j;
        Object localObject5;
        Object localObject7;
        long l;
        Object localObject8;
        boolean bool;
        break label4584;
        localObject4 = localObject1;
        int m = zzu(j);
        localObject4 = localObject1;
        Object localObject6 = localObject1;
        try
        {
          label1477:
          int n;
          label1748:
          float f;
          double d;
          switch (zzt(m))
          {
          default: 
            localObject7 = localObject1;
            if (localObject1 == null)
            {
              localObject4 = localObject1;
              localObject6 = localObject1;
              localObject7 = localzzpl.zza(paramObject);
            }
            break;
          case 68: 
            localObject4 = localObject1;
            localObject6 = localObject1;
            localObject7 = (zzoi)zzB(paramObject, i, j);
            localObject4 = localObject1;
            localObject6 = localObject1;
            paramzzov.zzt(localObject7, zzx(j), paramzzmo);
            localObject4 = localObject1;
            localObject6 = localObject1;
            zzK(paramObject, i, j, localObject7);
            break;
          case 67: 
            localObject4 = localObject1;
            localObject6 = localObject1;
            l = paramzzov.zzn();
            localObject4 = localObject1;
            localObject6 = localObject1;
            zzps.zzs(paramObject, m & 0xFFFFF, Long.valueOf(l));
          case 66: 
          case 65: 
          case 64: 
          case 63: 
          case 62: 
          case 61: 
          case 60: 
          case 59: 
          case 58: 
          case 57: 
          case 56: 
          case 55: 
          case 54: 
          case 53: 
          case 52: 
          case 51: 
            for (;;)
            {
              localObject4 = localObject1;
              localObject6 = localObject1;
              zzI(paramObject, i, j);
              break;
              localObject4 = localObject1;
              localObject6 = localObject1;
              k = paramzzov.zzi();
              localObject4 = localObject1;
              localObject6 = localObject1;
              zzps.zzs(paramObject, m & 0xFFFFF, Integer.valueOf(k));
              continue;
              localObject4 = localObject1;
              localObject6 = localObject1;
              l = paramzzov.zzm();
              localObject4 = localObject1;
              localObject6 = localObject1;
              zzps.zzs(paramObject, m & 0xFFFFF, Long.valueOf(l));
              continue;
              localObject4 = localObject1;
              localObject6 = localObject1;
              k = paramzzov.zzh();
              localObject4 = localObject1;
              localObject6 = localObject1;
              zzps.zzs(paramObject, m & 0xFFFFF, Integer.valueOf(k));
              continue;
              localObject4 = localObject1;
              localObject6 = localObject1;
              n = paramzzov.zze();
              localObject4 = localObject1;
              localObject6 = localObject1;
              localObject7 = zzw(j);
              if (localObject7 != null)
              {
                localObject4 = localObject1;
                k = n;
                localObject6 = localObject1;
                if (!((zznh)localObject7).zza(n))
                {
                  localObject4 = localObject1;
                  localObject6 = localObject1;
                  localObject1 = zzoy.zzo(paramObject, i, k, localObject1, localzzpl);
                  break;
                }
              }
              localObject4 = localObject1;
              localObject6 = localObject1;
              zzps.zzs(paramObject, m & 0xFFFFF, Integer.valueOf(n));
              continue;
              localObject4 = localObject1;
              localObject6 = localObject1;
              k = paramzzov.zzj();
              localObject4 = localObject1;
              localObject6 = localObject1;
              zzps.zzs(paramObject, m & 0xFFFFF, Integer.valueOf(k));
              continue;
              localObject4 = localObject1;
              localObject6 = localObject1;
              localObject7 = paramzzov.zzp();
              localObject4 = localObject1;
              localObject6 = localObject1;
              zzps.zzs(paramObject, m & 0xFFFFF, localObject7);
              continue;
              localObject4 = localObject1;
              localObject6 = localObject1;
              localObject7 = (zzoi)zzB(paramObject, i, j);
              localObject4 = localObject1;
              localObject6 = localObject1;
              paramzzov.zzu(localObject7, zzx(j), paramzzmo);
              break label1477;
              localObject4 = localObject1;
              localObject6 = localObject1;
              zzG(paramObject, m, paramzzov);
              continue;
              localObject4 = localObject1;
              localObject6 = localObject1;
              bool = paramzzov.zzN();
              localObject4 = localObject1;
              localObject6 = localObject1;
              zzps.zzs(paramObject, m & 0xFFFFF, Boolean.valueOf(bool));
              continue;
              localObject4 = localObject1;
              localObject6 = localObject1;
              k = paramzzov.zzf();
              localObject4 = localObject1;
              localObject6 = localObject1;
              zzps.zzs(paramObject, m & 0xFFFFF, Integer.valueOf(k));
              continue;
              localObject4 = localObject1;
              localObject6 = localObject1;
              l = paramzzov.zzk();
              localObject4 = localObject1;
              localObject6 = localObject1;
              zzps.zzs(paramObject, m & 0xFFFFF, Long.valueOf(l));
              continue;
              localObject4 = localObject1;
              localObject6 = localObject1;
              k = paramzzov.zzg();
              localObject4 = localObject1;
              localObject6 = localObject1;
              zzps.zzs(paramObject, m & 0xFFFFF, Integer.valueOf(k));
              continue;
              localObject4 = localObject1;
              localObject6 = localObject1;
              l = paramzzov.zzo();
              localObject4 = localObject1;
              localObject6 = localObject1;
              zzps.zzs(paramObject, m & 0xFFFFF, Long.valueOf(l));
              continue;
              localObject4 = localObject1;
              localObject6 = localObject1;
              l = paramzzov.zzl();
              localObject4 = localObject1;
              localObject6 = localObject1;
              zzps.zzs(paramObject, m & 0xFFFFF, Long.valueOf(l));
              continue;
              localObject4 = localObject1;
              localObject6 = localObject1;
              f = paramzzov.zzb();
              localObject4 = localObject1;
              localObject6 = localObject1;
              zzps.zzs(paramObject, m & 0xFFFFF, Float.valueOf(f));
              continue;
              localObject4 = localObject1;
              localObject6 = localObject1;
              d = paramzzov.zza();
              localObject4 = localObject1;
              localObject6 = localObject1;
              zzps.zzs(paramObject, m & 0xFFFFF, Double.valueOf(d));
            }
          case 50: 
            localObject4 = localObject1;
            localObject6 = localObject1;
            localObject8 = zzz(j);
            localObject4 = localObject1;
            localObject6 = localObject1;
            l = zzu(j) & 0xFFFFF;
            localObject4 = localObject1;
            localObject6 = localObject1;
            localObject5 = zzps.zzf(paramObject, l);
            if (localObject5 != null)
            {
              localObject4 = localObject1;
              localObject7 = localObject5;
              localObject6 = localObject1;
              if (zzod.zza(localObject5))
              {
                localObject4 = localObject1;
                localObject6 = localObject1;
                localObject7 = zzoc.zza().zzb();
                localObject4 = localObject1;
                localObject6 = localObject1;
                zzod.zzb(localObject7, localObject5);
                localObject4 = localObject1;
                localObject6 = localObject1;
                zzps.zzs(paramObject, l, localObject7);
              }
            }
            else
            {
              localObject4 = localObject1;
              localObject6 = localObject1;
              localObject7 = zzoc.zza().zzb();
              localObject4 = localObject1;
              localObject6 = localObject1;
              zzps.zzs(paramObject, l, localObject7);
            }
            localObject4 = localObject1;
            localObject6 = localObject1;
            localObject7 = (zzoc)localObject7;
            localObject4 = localObject1;
            localObject6 = localObject1;
            localObject7 = (zzob)localObject8;
            localObject4 = localObject1;
            localObject6 = localObject1;
            throw null;
          case 49: 
            localObject4 = localObject1;
            localObject6 = localObject1;
            localObject7 = zzx(j);
            localObject4 = localObject1;
            localObject6 = localObject1;
            paramzzov.zzC(zznv.zza(paramObject, m & 0xFFFFF), (zzow)localObject7, paramzzmo);
            break;
          case 48: 
            localObject4 = localObject1;
            localObject6 = localObject1;
            localObject7 = zznv.zza(paramObject, m & 0xFFFFF);
            localObject4 = localObject1;
            localObject6 = localObject1;
            paramzzov.zzJ((List)localObject7);
            break;
          case 47: 
            localObject4 = localObject1;
            localObject6 = localObject1;
            localObject7 = zznv.zza(paramObject, m & 0xFFFFF);
            localObject4 = localObject1;
            localObject6 = localObject1;
            paramzzov.zzI((List)localObject7);
            break;
          case 46: 
            localObject4 = localObject1;
            localObject6 = localObject1;
            localObject7 = zznv.zza(paramObject, m & 0xFFFFF);
            localObject4 = localObject1;
            localObject6 = localObject1;
            paramzzov.zzH((List)localObject7);
            break;
          case 45: 
            localObject4 = localObject1;
            localObject6 = localObject1;
            localObject7 = zznv.zza(paramObject, m & 0xFFFFF);
            localObject4 = localObject1;
            localObject6 = localObject1;
            paramzzov.zzG((List)localObject7);
            break;
          case 44: 
            localObject4 = localObject1;
            localObject6 = localObject1;
            localObject5 = zznv.zza(paramObject, m & 0xFFFFF);
            localObject4 = localObject1;
            localObject6 = localObject1;
            paramzzov.zzy((List)localObject5);
            localObject4 = localObject1;
            localObject6 = localObject1;
            localObject7 = zzw(j);
            localObject4 = localObject1;
            localObject6 = localObject1;
            localObject1 = zzoy.zzn(paramObject, i, (List)localObject5, (zznh)localObject7, localObject1, localzzpl);
            break;
          case 43: 
            localObject4 = localObject1;
            localObject6 = localObject1;
            localObject7 = zznv.zza(paramObject, m & 0xFFFFF);
            localObject4 = localObject1;
            localObject6 = localObject1;
            paramzzov.zzL((List)localObject7);
            break;
          case 42: 
            localObject4 = localObject1;
            localObject6 = localObject1;
            localObject7 = zznv.zza(paramObject, m & 0xFFFFF);
            localObject4 = localObject1;
            localObject6 = localObject1;
            paramzzov.zzv((List)localObject7);
            break;
          case 41: 
            localObject4 = localObject1;
            localObject6 = localObject1;
            localObject7 = zznv.zza(paramObject, m & 0xFFFFF);
            localObject4 = localObject1;
            localObject6 = localObject1;
            paramzzov.zzz((List)localObject7);
            break;
          case 40: 
            localObject4 = localObject1;
            localObject6 = localObject1;
            localObject7 = zznv.zza(paramObject, m & 0xFFFFF);
            localObject4 = localObject1;
            localObject6 = localObject1;
            paramzzov.zzA((List)localObject7);
            break;
          case 39: 
            localObject4 = localObject1;
            localObject6 = localObject1;
            localObject7 = zznv.zza(paramObject, m & 0xFFFFF);
            localObject4 = localObject1;
            localObject6 = localObject1;
            paramzzov.zzD((List)localObject7);
            break;
          case 38: 
            localObject4 = localObject1;
            localObject6 = localObject1;
            localObject7 = zznv.zza(paramObject, m & 0xFFFFF);
            localObject4 = localObject1;
            localObject6 = localObject1;
            paramzzov.zzM((List)localObject7);
            break;
          case 37: 
            localObject4 = localObject1;
            localObject6 = localObject1;
            localObject7 = zznv.zza(paramObject, m & 0xFFFFF);
            localObject4 = localObject1;
            localObject6 = localObject1;
            paramzzov.zzE((List)localObject7);
            break;
          case 36: 
            localObject4 = localObject1;
            localObject6 = localObject1;
            localObject7 = zznv.zza(paramObject, m & 0xFFFFF);
            localObject4 = localObject1;
            localObject6 = localObject1;
            paramzzov.zzB((List)localObject7);
            break;
          case 35: 
            localObject4 = localObject1;
            localObject6 = localObject1;
          case 34: 
          case 33: 
          case 32: 
          case 31: 
          case 30: 
          case 29: 
          case 28: 
          case 27: 
          case 26: 
          case 25: 
          case 24: 
          case 23: 
          case 22: 
          case 21: 
          case 20: 
          case 19: 
          case 18: 
            for (localObject7 = zznv.zza(paramObject, m & 0xFFFFF);; localObject7 = zznv.zza(paramObject, m & 0xFFFFF))
            {
              localObject4 = localObject1;
              localObject6 = localObject1;
              paramzzov.zzx((List)localObject7);
              break;
              localObject4 = localObject1;
              localObject6 = localObject1;
              localObject7 = zznv.zza(paramObject, m & 0xFFFFF);
              break label2549;
              localObject4 = localObject1;
              localObject6 = localObject1;
              localObject7 = zznv.zza(paramObject, m & 0xFFFFF);
              break label2588;
              localObject4 = localObject1;
              localObject6 = localObject1;
              localObject7 = zznv.zza(paramObject, m & 0xFFFFF);
              break label2627;
              localObject4 = localObject1;
              localObject6 = localObject1;
              localObject7 = zznv.zza(paramObject, m & 0xFFFFF);
              break label2666;
              localObject4 = localObject1;
              localObject6 = localObject1;
              localObject5 = zznv.zza(paramObject, m & 0xFFFFF);
              localObject4 = localObject1;
              localObject6 = localObject1;
              paramzzov.zzy((List)localObject5);
              localObject4 = localObject1;
              localObject6 = localObject1;
              localObject7 = zzw(j);
              break label2737;
              localObject4 = localObject1;
              localObject6 = localObject1;
              localObject7 = zznv.zza(paramObject, m & 0xFFFFF);
              break label2784;
              localObject4 = localObject1;
              localObject6 = localObject1;
              paramzzov.zzw(zznv.zza(paramObject, m & 0xFFFFF));
              break;
              localObject4 = localObject1;
              localObject6 = localObject1;
              localObject7 = zzx(j);
              localObject4 = localObject1;
              localObject6 = localObject1;
              paramzzov.zzF(zznv.zza(paramObject, m & 0xFFFFF), (zzow)localObject7, paramzzmo);
              break;
              localObject4 = localObject1;
              localObject6 = localObject1;
              if (zzM(m))
              {
                localObject4 = localObject1;
                localObject6 = localObject1;
                localObject7 = zznv.zza(paramObject, m & 0xFFFFF);
                localObject4 = localObject1;
                localObject6 = localObject1;
                ((zzlj)paramzzov).zzK((List)localObject7, true);
                break;
              }
              localObject4 = localObject1;
              localObject6 = localObject1;
              localObject7 = zznv.zza(paramObject, m & 0xFFFFF);
              localObject4 = localObject1;
              localObject6 = localObject1;
              ((zzlj)paramzzov).zzK((List)localObject7, false);
              break;
              localObject4 = localObject1;
              localObject6 = localObject1;
              localObject7 = zznv.zza(paramObject, m & 0xFFFFF);
              break label2823;
              localObject4 = localObject1;
              localObject6 = localObject1;
              localObject7 = zznv.zza(paramObject, m & 0xFFFFF);
              break label2862;
              localObject4 = localObject1;
              localObject6 = localObject1;
              localObject7 = zznv.zza(paramObject, m & 0xFFFFF);
              break label2901;
              localObject4 = localObject1;
              localObject6 = localObject1;
              localObject7 = zznv.zza(paramObject, m & 0xFFFFF);
              break label2940;
              localObject4 = localObject1;
              localObject6 = localObject1;
              localObject7 = zznv.zza(paramObject, m & 0xFFFFF);
              break label2979;
              localObject4 = localObject1;
              localObject6 = localObject1;
              localObject7 = zznv.zza(paramObject, m & 0xFFFFF);
              break label3018;
              localObject4 = localObject1;
              localObject6 = localObject1;
              localObject7 = zznv.zza(paramObject, m & 0xFFFFF);
              break label3057;
              localObject4 = localObject1;
              localObject6 = localObject1;
            }
          case 17: 
            localObject4 = localObject1;
            localObject6 = localObject1;
            localObject7 = (zzoi)zzA(paramObject, j);
            localObject4 = localObject1;
            localObject6 = localObject1;
            paramzzov.zzt(localObject7, zzx(j), paramzzmo);
            localObject4 = localObject1;
            localObject6 = localObject1;
            zzJ(paramObject, j, localObject7);
            break;
          case 16: 
            localObject4 = localObject1;
            localObject6 = localObject1;
            l = paramzzov.zzn();
            localObject4 = localObject1;
            localObject6 = localObject1;
            zzps.zzr(paramObject, m & 0xFFFFF, l);
          case 15: 
          case 14: 
          case 13: 
          case 12: 
          case 11: 
          case 10: 
          case 9: 
          case 8: 
          case 7: 
          case 6: 
          case 5: 
          case 4: 
          case 3: 
          case 2: 
          case 1: 
          case 0: 
            for (;;)
            {
              label2549:
              label2588:
              label2627:
              label2666:
              label2737:
              label2784:
              label2823:
              label2862:
              label2901:
              label2940:
              label2979:
              label3018:
              label3057:
              label3683:
              localObject4 = localObject1;
              localObject6 = localObject1;
              zzH(paramObject, j);
              break;
              localObject4 = localObject1;
              localObject6 = localObject1;
              k = paramzzov.zzi();
              localObject4 = localObject1;
              localObject6 = localObject1;
              zzps.zzq(paramObject, m & 0xFFFFF, k);
              continue;
              localObject4 = localObject1;
              localObject6 = localObject1;
              l = paramzzov.zzm();
              localObject4 = localObject1;
              localObject6 = localObject1;
              zzps.zzr(paramObject, m & 0xFFFFF, l);
              continue;
              localObject4 = localObject1;
              localObject6 = localObject1;
              k = paramzzov.zzh();
              localObject4 = localObject1;
              localObject6 = localObject1;
              zzps.zzq(paramObject, m & 0xFFFFF, k);
              continue;
              localObject4 = localObject1;
              localObject6 = localObject1;
              n = paramzzov.zze();
              localObject4 = localObject1;
              localObject6 = localObject1;
              localObject7 = zzw(j);
              if (localObject7 != null)
              {
                localObject4 = localObject1;
                k = n;
                localObject6 = localObject1;
                if (!((zznh)localObject7).zza(n)) {
                  break label1748;
                }
              }
              localObject4 = localObject1;
              localObject6 = localObject1;
              zzps.zzq(paramObject, m & 0xFFFFF, n);
              continue;
              localObject4 = localObject1;
              localObject6 = localObject1;
              k = paramzzov.zzj();
              localObject4 = localObject1;
              localObject6 = localObject1;
              zzps.zzq(paramObject, m & 0xFFFFF, k);
              continue;
              localObject4 = localObject1;
              localObject6 = localObject1;
              localObject7 = paramzzov.zzp();
              localObject4 = localObject1;
              localObject6 = localObject1;
              zzps.zzs(paramObject, m & 0xFFFFF, localObject7);
              continue;
              localObject4 = localObject1;
              localObject6 = localObject1;
              localObject7 = (zzoi)zzA(paramObject, j);
              localObject4 = localObject1;
              localObject6 = localObject1;
              paramzzov.zzu(localObject7, zzx(j), paramzzmo);
              break label3683;
              localObject4 = localObject1;
              localObject6 = localObject1;
              zzG(paramObject, m, paramzzov);
              continue;
              localObject4 = localObject1;
              localObject6 = localObject1;
              bool = paramzzov.zzN();
              localObject4 = localObject1;
              localObject6 = localObject1;
              zzps.zzm(paramObject, m & 0xFFFFF, bool);
              continue;
              localObject4 = localObject1;
              localObject6 = localObject1;
              k = paramzzov.zzf();
              localObject4 = localObject1;
              localObject6 = localObject1;
              zzps.zzq(paramObject, m & 0xFFFFF, k);
              continue;
              localObject4 = localObject1;
              localObject6 = localObject1;
              l = paramzzov.zzk();
              localObject4 = localObject1;
              localObject6 = localObject1;
              zzps.zzr(paramObject, m & 0xFFFFF, l);
              continue;
              localObject4 = localObject1;
              localObject6 = localObject1;
              k = paramzzov.zzg();
              localObject4 = localObject1;
              localObject6 = localObject1;
              zzps.zzq(paramObject, m & 0xFFFFF, k);
              continue;
              localObject4 = localObject1;
              localObject6 = localObject1;
              l = paramzzov.zzo();
              localObject4 = localObject1;
              localObject6 = localObject1;
              zzps.zzr(paramObject, m & 0xFFFFF, l);
              continue;
              localObject4 = localObject1;
              localObject6 = localObject1;
              l = paramzzov.zzl();
              localObject4 = localObject1;
              localObject6 = localObject1;
              zzps.zzr(paramObject, m & 0xFFFFF, l);
              continue;
              localObject4 = localObject1;
              localObject6 = localObject1;
              f = paramzzov.zzb();
              localObject4 = localObject1;
              localObject6 = localObject1;
              zzps.zzp(paramObject, m & 0xFFFFF, f);
              continue;
              localObject4 = localObject1;
              localObject6 = localObject1;
              d = paramzzov.zza();
              localObject4 = localObject1;
              localObject6 = localObject1;
              zzps.zzo(paramObject, m & 0xFFFFF, d);
            }
            localObject4 = localObject7;
            localObject6 = localObject7;
            bool = localzzpl.zzk(localObject7, paramzzov, 0);
            localObject1 = localObject7;
            if (bool) {
              continue;
            }
            for (k = zzk;; k++)
            {
              paramzzov = (zzov)localObject7;
              if (k >= zzl) {
                break;
              }
              zzy(paramObject, zzj[k], localObject7, localzzpl, paramObject);
            }
            Object localObject2;
            if (bool) {
              continue;
            }
          }
        }
        catch (zznm localzznm)
        {
          localObject7 = localObject6;
          if (localObject6 == null)
          {
            localObject4 = localObject6;
            localObject7 = localzzpl.zza(paramObject);
          }
          localObject4 = localObject7;
          bool = localzzpl.zzk(localObject7, paramzzov, 0);
          localObject2 = localObject7;
        }
        for (int k = zzk;; k++)
        {
          paramzzov = (zzov)localObject7;
          if (k >= zzl) {
            break;
          }
          zzy(paramObject, zzj[k], localObject7, localzzpl, paramObject);
        }
        if (paramzzov != null) {
          localzzpl.zzj(paramObject, paramzzov);
        }
        return;
        label4584:
        for (k = zzk; k < zzl; k++) {
          zzy(paramObject, zzj[k], localObject4, localzzpl, paramObject);
        }
        if (localObject4 != null) {
          localzzpl.zzj(paramObject, localObject4);
        }
      }
    }
  }
  
  public final void zzi(Object paramObject, byte[] paramArrayOfByte, int paramInt1, int paramInt2, zzkt paramzzkt)
  {
    zzc(paramObject, paramArrayOfByte, paramInt1, paramInt2, 0, paramzzkt);
  }
  
  public final void zzj(Object paramObject, zzpy paramzzpy)
  {
    if (zzh)
    {
      localObject1 = zzb;
      if (!zza.isEmpty())
      {
        localIterator = ((zzmt)localObject1).zzf();
        localObject1 = (Map.Entry)localIterator.next();
        break label50;
      }
    }
    Object localObject1 = null;
    Iterator localIterator = null;
    label50:
    int[] arrayOfInt = zzc;
    Unsafe localUnsafe = zzb;
    int i = 1048575;
    int j = 0;
    for (int k = 0; k < arrayOfInt.length; k += 3)
    {
      int m = zzu(k);
      Object localObject2 = zzc;
      int n = zzt(m);
      int i1 = localObject2[k];
      int i3;
      if (n <= 17)
      {
        int i2 = localObject2[(k + 2)];
        i3 = i2 & 0xFFFFF;
        if (i3 != i)
        {
          if (i3 == 1048575) {
            j = 0;
          } else {
            j = localUnsafe.getInt(paramObject, i3);
          }
          i = i3;
        }
        i3 = 1 << (i2 >>> 20);
      }
      else
      {
        i3 = 0;
      }
      while ((localObject1 != null) && (getKeyzza <= i1))
      {
        zzn.zzb(paramzzpy, (Map.Entry)localObject1);
        if (localIterator.hasNext()) {
          localObject1 = (Map.Entry)localIterator.next();
        } else {
          localObject1 = null;
        }
      }
      long l = m & 0xFFFFF;
      switch (n)
      {
      }
      for (;;)
      {
        break;
        if (zzR(paramObject, i1, k))
        {
          paramzzpy.zzq(i1, localUnsafe.getObject(paramObject, l), zzx(k));
          continue;
          if (zzR(paramObject, i1, k))
          {
            paramzzpy.zzD(i1, zzv(paramObject, l));
            continue;
            if (zzR(paramObject, i1, k))
            {
              paramzzpy.zzB(i1, zzp(paramObject, l));
              continue;
              if (zzR(paramObject, i1, k))
              {
                paramzzpy.zzz(i1, zzv(paramObject, l));
                continue;
                if (zzR(paramObject, i1, k))
                {
                  paramzzpy.zzx(i1, zzp(paramObject, l));
                  continue;
                  if (zzR(paramObject, i1, k))
                  {
                    paramzzpy.zzi(i1, zzp(paramObject, l));
                    continue;
                    if (zzR(paramObject, i1, k))
                    {
                      paramzzpy.zzI(i1, zzp(paramObject, l));
                      continue;
                      if (zzR(paramObject, i1, k))
                      {
                        paramzzpy.zzd(i1, (zzle)localUnsafe.getObject(paramObject, l));
                        continue;
                        if (zzR(paramObject, i1, k))
                        {
                          paramzzpy.zzv(i1, localUnsafe.getObject(paramObject, l), zzx(k));
                          continue;
                          if (zzR(paramObject, i1, k))
                          {
                            zzT(i1, localUnsafe.getObject(paramObject, l), paramzzpy);
                            continue;
                            if (zzR(paramObject, i1, k))
                            {
                              paramzzpy.zzb(i1, zzS(paramObject, l));
                              continue;
                              if (zzR(paramObject, i1, k))
                              {
                                paramzzpy.zzk(i1, zzp(paramObject, l));
                                continue;
                                if (zzR(paramObject, i1, k))
                                {
                                  paramzzpy.zzm(i1, zzv(paramObject, l));
                                  continue;
                                  if (zzR(paramObject, i1, k))
                                  {
                                    paramzzpy.zzr(i1, zzp(paramObject, l));
                                    continue;
                                    if (zzR(paramObject, i1, k))
                                    {
                                      paramzzpy.zzK(i1, zzv(paramObject, l));
                                      continue;
                                      if (zzR(paramObject, i1, k))
                                      {
                                        paramzzpy.zzt(i1, zzv(paramObject, l));
                                        continue;
                                        if (zzR(paramObject, i1, k))
                                        {
                                          paramzzpy.zzo(i1, zzo(paramObject, l));
                                          continue;
                                          if (zzR(paramObject, i1, k))
                                          {
                                            paramzzpy.zzf(i1, zzn(paramObject, l));
                                            continue;
                                            if (localUnsafe.getObject(paramObject, l) != null)
                                            {
                                              paramObject = (zzob)zzz(k);
                                              throw null;
                                              i1 = zzc[k];
                                              localObject2 = (List)localUnsafe.getObject(paramObject, l);
                                              Object localObject3 = zzx(k);
                                              i3 = zzoy.zza;
                                              if ((localObject2 != null) && (!((List)localObject2).isEmpty()))
                                              {
                                                i3 = 0;
                                                while (i3 < ((List)localObject2).size())
                                                {
                                                  Object localObject4 = ((List)localObject2).get(i3);
                                                  ((zzlo)paramzzpy).zzq(i1, localObject4, (zzow)localObject3);
                                                  i3++;
                                                  continue;
                                                  zzoy.zzC(zzc[k], (List)localUnsafe.getObject(paramObject, l), paramzzpy, true);
                                                  break;
                                                  zzoy.zzB(zzc[k], (List)localUnsafe.getObject(paramObject, l), paramzzpy, true);
                                                  break;
                                                  zzoy.zzA(zzc[k], (List)localUnsafe.getObject(paramObject, l), paramzzpy, true);
                                                  break;
                                                  zzoy.zzz(zzc[k], (List)localUnsafe.getObject(paramObject, l), paramzzpy, true);
                                                  break;
                                                  zzoy.zzt(zzc[k], (List)localUnsafe.getObject(paramObject, l), paramzzpy, true);
                                                  break;
                                                  zzoy.zzD(zzc[k], (List)localUnsafe.getObject(paramObject, l), paramzzpy, true);
                                                  break;
                                                  zzoy.zzr(zzc[k], (List)localUnsafe.getObject(paramObject, l), paramzzpy, true);
                                                  break;
                                                  zzoy.zzu(zzc[k], (List)localUnsafe.getObject(paramObject, l), paramzzpy, true);
                                                  break;
                                                  zzoy.zzv(zzc[k], (List)localUnsafe.getObject(paramObject, l), paramzzpy, true);
                                                  break;
                                                  zzoy.zzx(zzc[k], (List)localUnsafe.getObject(paramObject, l), paramzzpy, true);
                                                  break;
                                                  zzoy.zzE(zzc[k], (List)localUnsafe.getObject(paramObject, l), paramzzpy, true);
                                                  break;
                                                  zzoy.zzy(zzc[k], (List)localUnsafe.getObject(paramObject, l), paramzzpy, true);
                                                  break;
                                                  zzoy.zzw(zzc[k], (List)localUnsafe.getObject(paramObject, l), paramzzpy, true);
                                                  break;
                                                  zzoy.zzs(zzc[k], (List)localUnsafe.getObject(paramObject, l), paramzzpy, true);
                                                  break;
                                                  zzoy.zzC(zzc[k], (List)localUnsafe.getObject(paramObject, l), paramzzpy, false);
                                                  break label1728;
                                                  zzoy.zzB(zzc[k], (List)localUnsafe.getObject(paramObject, l), paramzzpy, false);
                                                  break label1728;
                                                  zzoy.zzA(zzc[k], (List)localUnsafe.getObject(paramObject, l), paramzzpy, false);
                                                  break label1728;
                                                  zzoy.zzz(zzc[k], (List)localUnsafe.getObject(paramObject, l), paramzzpy, false);
                                                  break label1728;
                                                  zzoy.zzt(zzc[k], (List)localUnsafe.getObject(paramObject, l), paramzzpy, false);
                                                  break label1728;
                                                  zzoy.zzD(zzc[k], (List)localUnsafe.getObject(paramObject, l), paramzzpy, false);
                                                  label1728:
                                                  break label2141;
                                                  i1 = zzc[k];
                                                  localObject2 = (List)localUnsafe.getObject(paramObject, l);
                                                  i3 = zzoy.zza;
                                                  if ((localObject2 != null) && (!((List)localObject2).isEmpty()))
                                                  {
                                                    paramzzpy.zze(i1, (List)localObject2);
                                                    break;
                                                    i1 = zzc[k];
                                                    localObject4 = (List)localUnsafe.getObject(paramObject, l);
                                                    localObject2 = zzx(k);
                                                    i3 = zzoy.zza;
                                                    if ((localObject4 != null) && (!((List)localObject4).isEmpty()))
                                                    {
                                                      i3 = 0;
                                                      while (i3 < ((List)localObject4).size())
                                                      {
                                                        localObject3 = ((List)localObject4).get(i3);
                                                        ((zzlo)paramzzpy).zzv(i1, localObject3, (zzow)localObject2);
                                                        i3++;
                                                        continue;
                                                        i1 = zzc[k];
                                                        localObject2 = (List)localUnsafe.getObject(paramObject, l);
                                                        i3 = zzoy.zza;
                                                        if ((localObject2 != null) && (!((List)localObject2).isEmpty())) {
                                                          paramzzpy.zzH(i1, (List)localObject2);
                                                        }
                                                      }
                                                    }
                                                  }
                                                }
                                              }
                                              continue;
                                              zzoy.zzr(zzc[k], (List)localUnsafe.getObject(paramObject, l), paramzzpy, false);
                                              break label2141;
                                              zzoy.zzu(zzc[k], (List)localUnsafe.getObject(paramObject, l), paramzzpy, false);
                                              break label2141;
                                              zzoy.zzv(zzc[k], (List)localUnsafe.getObject(paramObject, l), paramzzpy, false);
                                              break label2141;
                                              zzoy.zzx(zzc[k], (List)localUnsafe.getObject(paramObject, l), paramzzpy, false);
                                              break label2141;
                                              zzoy.zzE(zzc[k], (List)localUnsafe.getObject(paramObject, l), paramzzpy, false);
                                              break label2141;
                                              zzoy.zzy(zzc[k], (List)localUnsafe.getObject(paramObject, l), paramzzpy, false);
                                              break label2141;
                                              zzoy.zzw(zzc[k], (List)localUnsafe.getObject(paramObject, l), paramzzpy, false);
                                              break label2141;
                                              zzoy.zzs(zzc[k], (List)localUnsafe.getObject(paramObject, l), paramzzpy, false);
                                              label2141:
                                              break;
                                              if (zzO(paramObject, k, i, j, i3))
                                              {
                                                paramzzpy.zzq(i1, localUnsafe.getObject(paramObject, l), zzx(k));
                                                break;
                                                if (zzO(paramObject, k, i, j, i3))
                                                {
                                                  paramzzpy.zzD(i1, localUnsafe.getLong(paramObject, l));
                                                  break;
                                                  if (zzO(paramObject, k, i, j, i3))
                                                  {
                                                    paramzzpy.zzB(i1, localUnsafe.getInt(paramObject, l));
                                                    break;
                                                    if (zzO(paramObject, k, i, j, i3))
                                                    {
                                                      paramzzpy.zzz(i1, localUnsafe.getLong(paramObject, l));
                                                      break;
                                                      if (zzO(paramObject, k, i, j, i3))
                                                      {
                                                        paramzzpy.zzx(i1, localUnsafe.getInt(paramObject, l));
                                                        break;
                                                        if (zzO(paramObject, k, i, j, i3))
                                                        {
                                                          paramzzpy.zzi(i1, localUnsafe.getInt(paramObject, l));
                                                          break;
                                                          if (zzO(paramObject, k, i, j, i3))
                                                          {
                                                            paramzzpy.zzI(i1, localUnsafe.getInt(paramObject, l));
                                                            break;
                                                            if (zzO(paramObject, k, i, j, i3))
                                                            {
                                                              paramzzpy.zzd(i1, (zzle)localUnsafe.getObject(paramObject, l));
                                                              break;
                                                              if (zzO(paramObject, k, i, j, i3))
                                                              {
                                                                paramzzpy.zzv(i1, localUnsafe.getObject(paramObject, l), zzx(k));
                                                                break;
                                                                if (zzO(paramObject, k, i, j, i3))
                                                                {
                                                                  zzT(i1, localUnsafe.getObject(paramObject, l), paramzzpy);
                                                                  break;
                                                                  if (zzO(paramObject, k, i, j, i3))
                                                                  {
                                                                    paramzzpy.zzb(i1, zzps.zzw(paramObject, l));
                                                                    break;
                                                                    if (zzO(paramObject, k, i, j, i3))
                                                                    {
                                                                      paramzzpy.zzk(i1, localUnsafe.getInt(paramObject, l));
                                                                      break;
                                                                      if (zzO(paramObject, k, i, j, i3))
                                                                      {
                                                                        paramzzpy.zzm(i1, localUnsafe.getLong(paramObject, l));
                                                                        break;
                                                                        if (zzO(paramObject, k, i, j, i3))
                                                                        {
                                                                          paramzzpy.zzr(i1, localUnsafe.getInt(paramObject, l));
                                                                          break;
                                                                          if (zzO(paramObject, k, i, j, i3))
                                                                          {
                                                                            paramzzpy.zzK(i1, localUnsafe.getLong(paramObject, l));
                                                                            break;
                                                                            if (zzO(paramObject, k, i, j, i3))
                                                                            {
                                                                              paramzzpy.zzt(i1, localUnsafe.getLong(paramObject, l));
                                                                              break;
                                                                              if (zzO(paramObject, k, i, j, i3))
                                                                              {
                                                                                paramzzpy.zzo(i1, zzps.zzb(paramObject, l));
                                                                                break;
                                                                                if (zzO(paramObject, k, i, j, i3)) {
                                                                                  paramzzpy.zzf(i1, zzps.zza(paramObject, l));
                                                                                }
                                                                              }
                                                                            }
                                                                          }
                                                                        }
                                                                      }
                                                                    }
                                                                  }
                                                                }
                                                              }
                                                            }
                                                          }
                                                        }
                                                      }
                                                    }
                                                  }
                                                }
                                              }
                                            }
                                          }
                                        }
                                      }
                                    }
                                  }
                                }
                              }
                            }
                          }
                        }
                      }
                    }
                  }
                }
              }
            }
          }
        }
      }
    }
    while (localObject1 != null)
    {
      zzn.zzb(paramzzpy, (Map.Entry)localObject1);
      if (localIterator.hasNext()) {
        localObject1 = (Map.Entry)localIterator.next();
      } else {
        localObject1 = null;
      }
    }
    zzc.zzl(paramzzpy);
  }
  
  /* Error */
  public final boolean zzk(Object paramObject1, Object paramObject2)
  {
    // Byte code:
    //   0: iconst_0
    //   1: istore_3
    //   2: iload_3
    //   3: aload_0
    //   4: getfield 47	com/google/android/recaptcha/internal/zzol:zzc	[I
    //   7: arraylength
    //   8: if_icmpge +929 -> 937
    //   11: aload_0
    //   12: iload_3
    //   13: invokespecial 83	com/google/android/recaptcha/internal/zzol:zzu	(I)I
    //   16: istore 4
    //   18: iload 4
    //   20: invokestatic 244	com/google/android/recaptcha/internal/zzol:zzt	(I)I
    //   23: istore 5
    //   25: iload 4
    //   27: ldc 91
    //   29: iand
    //   30: i2l
    //   31: lstore 6
    //   33: iload 5
    //   35: tableswitch	default:+289->324, 0:+859->894, 1:+825->860, 2:+796->831, 3:+767->802, 4:+739->774, 5:+710->745, 6:+682->717, 7:+654->689, 8:+623->658, 9:+592->627, 10:+561->596, 11:+533->568, 12:+505->540, 13:+477->512, 14:+448->483, 15:+420->455, 16:+391->426, 17:+360->395, 18:+339->374, 19:+339->374, 20:+339->374, 21:+339->374, 22:+339->374, 23:+339->374, 24:+339->374, 25:+339->374, 26:+339->374, 27:+339->374, 28:+339->374, 29:+339->374, 30:+339->374, 31:+339->374, 32:+339->374, 33:+339->374, 34:+339->374, 35:+339->374, 36:+339->374, 37:+339->374, 38:+339->374, 39:+339->374, 40:+339->374, 41:+339->374, 42:+339->374, 43:+339->374, 44:+339->374, 45:+339->374, 46:+339->374, 47:+339->374, 48:+339->374, 49:+339->374, 50:+339->374, 51:+292->327, 52:+292->327, 53:+292->327, 54:+292->327, 55:+292->327, 56:+292->327, 57:+292->327, 58:+292->327, 59:+292->327, 60:+292->327, 61:+292->327, 62:+292->327, 63:+292->327, 64:+292->327, 65:+292->327, 66:+292->327, 67:+292->327, 68:+292->327
    //   324: goto +607 -> 931
    //   327: aload_0
    //   328: iload_3
    //   329: invokespecial 225	com/google/android/recaptcha/internal/zzol:zzr	(I)I
    //   332: ldc 91
    //   334: iand
    //   335: i2l
    //   336: lstore 8
    //   338: aload_1
    //   339: lload 8
    //   341: invokestatic 230	com/google/android/recaptcha/internal/zzps:zzc	(Ljava/lang/Object;J)I
    //   344: aload_2
    //   345: lload 8
    //   347: invokestatic 230	com/google/android/recaptcha/internal/zzps:zzc	(Ljava/lang/Object;J)I
    //   350: if_icmpne +579 -> 929
    //   353: aload_1
    //   354: lload 6
    //   356: invokestatic 247	com/google/android/recaptcha/internal/zzps:zzf	(Ljava/lang/Object;J)Ljava/lang/Object;
    //   359: aload_2
    //   360: lload 6
    //   362: invokestatic 247	com/google/android/recaptcha/internal/zzps:zzf	(Ljava/lang/Object;J)Ljava/lang/Object;
    //   365: invokestatic 1071	com/google/android/recaptcha/internal/zzoy:zzF	(Ljava/lang/Object;Ljava/lang/Object;)Z
    //   368: ifne +563 -> 931
    //   371: goto +558 -> 929
    //   374: aload_1
    //   375: lload 6
    //   377: invokestatic 247	com/google/android/recaptcha/internal/zzps:zzf	(Ljava/lang/Object;J)Ljava/lang/Object;
    //   380: aload_2
    //   381: lload 6
    //   383: invokestatic 247	com/google/android/recaptcha/internal/zzps:zzf	(Ljava/lang/Object;J)Ljava/lang/Object;
    //   386: invokestatic 1071	com/google/android/recaptcha/internal/zzoy:zzF	(Ljava/lang/Object;Ljava/lang/Object;)Z
    //   389: ifne +542 -> 931
    //   392: goto +537 -> 929
    //   395: aload_0
    //   396: aload_1
    //   397: aload_2
    //   398: iload_3
    //   399: invokespecial 1073	com/google/android/recaptcha/internal/zzol:zzL	(Ljava/lang/Object;Ljava/lang/Object;I)Z
    //   402: ifeq +527 -> 929
    //   405: aload_1
    //   406: lload 6
    //   408: invokestatic 247	com/google/android/recaptcha/internal/zzps:zzf	(Ljava/lang/Object;J)Ljava/lang/Object;
    //   411: aload_2
    //   412: lload 6
    //   414: invokestatic 247	com/google/android/recaptcha/internal/zzps:zzf	(Ljava/lang/Object;J)Ljava/lang/Object;
    //   417: invokestatic 1071	com/google/android/recaptcha/internal/zzoy:zzF	(Ljava/lang/Object;Ljava/lang/Object;)Z
    //   420: ifeq +509 -> 929
    //   423: goto +508 -> 931
    //   426: aload_0
    //   427: aload_1
    //   428: aload_2
    //   429: iload_3
    //   430: invokespecial 1073	com/google/android/recaptcha/internal/zzol:zzL	(Ljava/lang/Object;Ljava/lang/Object;I)Z
    //   433: ifeq +496 -> 929
    //   436: aload_1
    //   437: lload 6
    //   439: invokestatic 250	com/google/android/recaptcha/internal/zzps:zzd	(Ljava/lang/Object;J)J
    //   442: aload_2
    //   443: lload 6
    //   445: invokestatic 250	com/google/android/recaptcha/internal/zzps:zzd	(Ljava/lang/Object;J)J
    //   448: lcmp
    //   449: ifne +480 -> 929
    //   452: goto +479 -> 931
    //   455: aload_0
    //   456: aload_1
    //   457: aload_2
    //   458: iload_3
    //   459: invokespecial 1073	com/google/android/recaptcha/internal/zzol:zzL	(Ljava/lang/Object;Ljava/lang/Object;I)Z
    //   462: ifeq +467 -> 929
    //   465: aload_1
    //   466: lload 6
    //   468: invokestatic 230	com/google/android/recaptcha/internal/zzps:zzc	(Ljava/lang/Object;J)I
    //   471: aload_2
    //   472: lload 6
    //   474: invokestatic 230	com/google/android/recaptcha/internal/zzps:zzc	(Ljava/lang/Object;J)I
    //   477: if_icmpne +452 -> 929
    //   480: goto +451 -> 931
    //   483: aload_0
    //   484: aload_1
    //   485: aload_2
    //   486: iload_3
    //   487: invokespecial 1073	com/google/android/recaptcha/internal/zzol:zzL	(Ljava/lang/Object;Ljava/lang/Object;I)Z
    //   490: ifeq +439 -> 929
    //   493: aload_1
    //   494: lload 6
    //   496: invokestatic 250	com/google/android/recaptcha/internal/zzps:zzd	(Ljava/lang/Object;J)J
    //   499: aload_2
    //   500: lload 6
    //   502: invokestatic 250	com/google/android/recaptcha/internal/zzps:zzd	(Ljava/lang/Object;J)J
    //   505: lcmp
    //   506: ifne +423 -> 929
    //   509: goto +422 -> 931
    //   512: aload_0
    //   513: aload_1
    //   514: aload_2
    //   515: iload_3
    //   516: invokespecial 1073	com/google/android/recaptcha/internal/zzol:zzL	(Ljava/lang/Object;Ljava/lang/Object;I)Z
    //   519: ifeq +410 -> 929
    //   522: aload_1
    //   523: lload 6
    //   525: invokestatic 230	com/google/android/recaptcha/internal/zzps:zzc	(Ljava/lang/Object;J)I
    //   528: aload_2
    //   529: lload 6
    //   531: invokestatic 230	com/google/android/recaptcha/internal/zzps:zzc	(Ljava/lang/Object;J)I
    //   534: if_icmpne +395 -> 929
    //   537: goto +394 -> 931
    //   540: aload_0
    //   541: aload_1
    //   542: aload_2
    //   543: iload_3
    //   544: invokespecial 1073	com/google/android/recaptcha/internal/zzol:zzL	(Ljava/lang/Object;Ljava/lang/Object;I)Z
    //   547: ifeq +382 -> 929
    //   550: aload_1
    //   551: lload 6
    //   553: invokestatic 230	com/google/android/recaptcha/internal/zzps:zzc	(Ljava/lang/Object;J)I
    //   556: aload_2
    //   557: lload 6
    //   559: invokestatic 230	com/google/android/recaptcha/internal/zzps:zzc	(Ljava/lang/Object;J)I
    //   562: if_icmpne +367 -> 929
    //   565: goto +366 -> 931
    //   568: aload_0
    //   569: aload_1
    //   570: aload_2
    //   571: iload_3
    //   572: invokespecial 1073	com/google/android/recaptcha/internal/zzol:zzL	(Ljava/lang/Object;Ljava/lang/Object;I)Z
    //   575: ifeq +354 -> 929
    //   578: aload_1
    //   579: lload 6
    //   581: invokestatic 230	com/google/android/recaptcha/internal/zzps:zzc	(Ljava/lang/Object;J)I
    //   584: aload_2
    //   585: lload 6
    //   587: invokestatic 230	com/google/android/recaptcha/internal/zzps:zzc	(Ljava/lang/Object;J)I
    //   590: if_icmpne +339 -> 929
    //   593: goto +338 -> 931
    //   596: aload_0
    //   597: aload_1
    //   598: aload_2
    //   599: iload_3
    //   600: invokespecial 1073	com/google/android/recaptcha/internal/zzol:zzL	(Ljava/lang/Object;Ljava/lang/Object;I)Z
    //   603: ifeq +326 -> 929
    //   606: aload_1
    //   607: lload 6
    //   609: invokestatic 247	com/google/android/recaptcha/internal/zzps:zzf	(Ljava/lang/Object;J)Ljava/lang/Object;
    //   612: aload_2
    //   613: lload 6
    //   615: invokestatic 247	com/google/android/recaptcha/internal/zzps:zzf	(Ljava/lang/Object;J)Ljava/lang/Object;
    //   618: invokestatic 1071	com/google/android/recaptcha/internal/zzoy:zzF	(Ljava/lang/Object;Ljava/lang/Object;)Z
    //   621: ifeq +308 -> 929
    //   624: goto +307 -> 931
    //   627: aload_0
    //   628: aload_1
    //   629: aload_2
    //   630: iload_3
    //   631: invokespecial 1073	com/google/android/recaptcha/internal/zzol:zzL	(Ljava/lang/Object;Ljava/lang/Object;I)Z
    //   634: ifeq +295 -> 929
    //   637: aload_1
    //   638: lload 6
    //   640: invokestatic 247	com/google/android/recaptcha/internal/zzps:zzf	(Ljava/lang/Object;J)Ljava/lang/Object;
    //   643: aload_2
    //   644: lload 6
    //   646: invokestatic 247	com/google/android/recaptcha/internal/zzps:zzf	(Ljava/lang/Object;J)Ljava/lang/Object;
    //   649: invokestatic 1071	com/google/android/recaptcha/internal/zzoy:zzF	(Ljava/lang/Object;Ljava/lang/Object;)Z
    //   652: ifeq +277 -> 929
    //   655: goto +276 -> 931
    //   658: aload_0
    //   659: aload_1
    //   660: aload_2
    //   661: iload_3
    //   662: invokespecial 1073	com/google/android/recaptcha/internal/zzol:zzL	(Ljava/lang/Object;Ljava/lang/Object;I)Z
    //   665: ifeq +264 -> 929
    //   668: aload_1
    //   669: lload 6
    //   671: invokestatic 247	com/google/android/recaptcha/internal/zzps:zzf	(Ljava/lang/Object;J)Ljava/lang/Object;
    //   674: aload_2
    //   675: lload 6
    //   677: invokestatic 247	com/google/android/recaptcha/internal/zzps:zzf	(Ljava/lang/Object;J)Ljava/lang/Object;
    //   680: invokestatic 1071	com/google/android/recaptcha/internal/zzoy:zzF	(Ljava/lang/Object;Ljava/lang/Object;)Z
    //   683: ifeq +246 -> 929
    //   686: goto +245 -> 931
    //   689: aload_0
    //   690: aload_1
    //   691: aload_2
    //   692: iload_3
    //   693: invokespecial 1073	com/google/android/recaptcha/internal/zzol:zzL	(Ljava/lang/Object;Ljava/lang/Object;I)Z
    //   696: ifeq +233 -> 929
    //   699: aload_1
    //   700: lload 6
    //   702: invokestatic 264	com/google/android/recaptcha/internal/zzps:zzw	(Ljava/lang/Object;J)Z
    //   705: aload_2
    //   706: lload 6
    //   708: invokestatic 264	com/google/android/recaptcha/internal/zzps:zzw	(Ljava/lang/Object;J)Z
    //   711: if_icmpne +218 -> 929
    //   714: goto +217 -> 931
    //   717: aload_0
    //   718: aload_1
    //   719: aload_2
    //   720: iload_3
    //   721: invokespecial 1073	com/google/android/recaptcha/internal/zzol:zzL	(Ljava/lang/Object;Ljava/lang/Object;I)Z
    //   724: ifeq +205 -> 929
    //   727: aload_1
    //   728: lload 6
    //   730: invokestatic 230	com/google/android/recaptcha/internal/zzps:zzc	(Ljava/lang/Object;J)I
    //   733: aload_2
    //   734: lload 6
    //   736: invokestatic 230	com/google/android/recaptcha/internal/zzps:zzc	(Ljava/lang/Object;J)I
    //   739: if_icmpne +190 -> 929
    //   742: goto +189 -> 931
    //   745: aload_0
    //   746: aload_1
    //   747: aload_2
    //   748: iload_3
    //   749: invokespecial 1073	com/google/android/recaptcha/internal/zzol:zzL	(Ljava/lang/Object;Ljava/lang/Object;I)Z
    //   752: ifeq +177 -> 929
    //   755: aload_1
    //   756: lload 6
    //   758: invokestatic 250	com/google/android/recaptcha/internal/zzps:zzd	(Ljava/lang/Object;J)J
    //   761: aload_2
    //   762: lload 6
    //   764: invokestatic 250	com/google/android/recaptcha/internal/zzps:zzd	(Ljava/lang/Object;J)J
    //   767: lcmp
    //   768: ifne +161 -> 929
    //   771: goto +160 -> 931
    //   774: aload_0
    //   775: aload_1
    //   776: aload_2
    //   777: iload_3
    //   778: invokespecial 1073	com/google/android/recaptcha/internal/zzol:zzL	(Ljava/lang/Object;Ljava/lang/Object;I)Z
    //   781: ifeq +148 -> 929
    //   784: aload_1
    //   785: lload 6
    //   787: invokestatic 230	com/google/android/recaptcha/internal/zzps:zzc	(Ljava/lang/Object;J)I
    //   790: aload_2
    //   791: lload 6
    //   793: invokestatic 230	com/google/android/recaptcha/internal/zzps:zzc	(Ljava/lang/Object;J)I
    //   796: if_icmpne +133 -> 929
    //   799: goto +132 -> 931
    //   802: aload_0
    //   803: aload_1
    //   804: aload_2
    //   805: iload_3
    //   806: invokespecial 1073	com/google/android/recaptcha/internal/zzol:zzL	(Ljava/lang/Object;Ljava/lang/Object;I)Z
    //   809: ifeq +120 -> 929
    //   812: aload_1
    //   813: lload 6
    //   815: invokestatic 250	com/google/android/recaptcha/internal/zzps:zzd	(Ljava/lang/Object;J)J
    //   818: aload_2
    //   819: lload 6
    //   821: invokestatic 250	com/google/android/recaptcha/internal/zzps:zzd	(Ljava/lang/Object;J)J
    //   824: lcmp
    //   825: ifne +104 -> 929
    //   828: goto +103 -> 931
    //   831: aload_0
    //   832: aload_1
    //   833: aload_2
    //   834: iload_3
    //   835: invokespecial 1073	com/google/android/recaptcha/internal/zzol:zzL	(Ljava/lang/Object;Ljava/lang/Object;I)Z
    //   838: ifeq +91 -> 929
    //   841: aload_1
    //   842: lload 6
    //   844: invokestatic 250	com/google/android/recaptcha/internal/zzps:zzd	(Ljava/lang/Object;J)J
    //   847: aload_2
    //   848: lload 6
    //   850: invokestatic 250	com/google/android/recaptcha/internal/zzps:zzd	(Ljava/lang/Object;J)J
    //   853: lcmp
    //   854: ifne +75 -> 929
    //   857: goto +74 -> 931
    //   860: aload_0
    //   861: aload_1
    //   862: aload_2
    //   863: iload_3
    //   864: invokespecial 1073	com/google/android/recaptcha/internal/zzol:zzL	(Ljava/lang/Object;Ljava/lang/Object;I)Z
    //   867: ifeq +62 -> 929
    //   870: aload_1
    //   871: lload 6
    //   873: invokestatic 267	com/google/android/recaptcha/internal/zzps:zzb	(Ljava/lang/Object;J)F
    //   876: invokestatic 572	java/lang/Float:floatToIntBits	(F)I
    //   879: aload_2
    //   880: lload 6
    //   882: invokestatic 267	com/google/android/recaptcha/internal/zzps:zzb	(Ljava/lang/Object;J)F
    //   885: invokestatic 572	java/lang/Float:floatToIntBits	(F)I
    //   888: if_icmpne +41 -> 929
    //   891: goto +40 -> 931
    //   894: aload_0
    //   895: aload_1
    //   896: aload_2
    //   897: iload_3
    //   898: invokespecial 1073	com/google/android/recaptcha/internal/zzol:zzL	(Ljava/lang/Object;Ljava/lang/Object;I)Z
    //   901: ifeq +28 -> 929
    //   904: aload_1
    //   905: lload 6
    //   907: invokestatic 276	com/google/android/recaptcha/internal/zzps:zza	(Ljava/lang/Object;J)D
    //   910: invokestatic 575	java/lang/Double:doubleToLongBits	(D)J
    //   913: aload_2
    //   914: lload 6
    //   916: invokestatic 276	com/google/android/recaptcha/internal/zzps:zza	(Ljava/lang/Object;J)D
    //   919: invokestatic 575	java/lang/Double:doubleToLongBits	(D)J
    //   922: lcmp
    //   923: ifne +6 -> 929
    //   926: goto +5 -> 931
    //   929: iconst_0
    //   930: ireturn
    //   931: iinc 3 3
    //   934: goto -932 -> 2
    //   937: aload_1
    //   938: checkcast 55	com/google/android/recaptcha/internal/zznd
    //   941: getfield 310	com/google/android/recaptcha/internal/zznd:zzc	Lcom/google/android/recaptcha/internal/zzpm;
    //   944: aload_2
    //   945: checkcast 55	com/google/android/recaptcha/internal/zznd
    //   948: getfield 310	com/google/android/recaptcha/internal/zznd:zzc	Lcom/google/android/recaptcha/internal/zzpm;
    //   951: invokevirtual 1074	com/google/android/recaptcha/internal/zzpm:equals	(Ljava/lang/Object;)Z
    //   954: ifne +5 -> 959
    //   957: iconst_0
    //   958: ireturn
    //   959: aload_0
    //   960: getfield 61	com/google/android/recaptcha/internal/zzol:zzh	Z
    //   963: ifeq +21 -> 984
    //   966: aload_1
    //   967: checkcast 59	com/google/android/recaptcha/internal/zzna
    //   970: getfield 527	com/google/android/recaptcha/internal/zzna:zzb	Lcom/google/android/recaptcha/internal/zzmt;
    //   973: aload_2
    //   974: checkcast 59	com/google/android/recaptcha/internal/zzna
    //   977: getfield 527	com/google/android/recaptcha/internal/zzna:zzb	Lcom/google/android/recaptcha/internal/zzmt;
    //   980: invokevirtual 1075	com/google/android/recaptcha/internal/zzmt:equals	(Ljava/lang/Object;)Z
    //   983: ireturn
    //   984: iconst_1
    //   985: ireturn
    // Local variable table:
    //   start	length	slot	name	signature
    //   0	986	0	this	zzol
    //   0	986	1	paramObject1	Object
    //   0	986	2	paramObject2	Object
    //   1	931	3	i	int
    //   16	14	4	j	int
    //   23	11	5	k	int
    //   31	884	6	l1	long
    //   336	10	8	l2	long
  }
  
  public final boolean zzl(Object paramObject)
  {
    int i = 1048575;
    int j = 0;
    for (int k = j; k < zzk; k++)
    {
      Object localObject1 = zzj;
      Object localObject2 = zzc;
      int m = localObject1[k];
      int n = localObject2[m];
      int i1 = zzu(m);
      int i2 = zzc[(m + 2)];
      int i3 = i2 & 0xFFFFF;
      i2 = 1 << (i2 >>> 20);
      if (i3 != i)
      {
        if (i3 != 1048575)
        {
          long l = i3;
          j = zzb.getInt(paramObject, l);
        }
        i = i3;
      }
      if (((0x10000000 & i1) != 0) && (!zzO(paramObject, m, i, j, i2))) {
        return false;
      }
      i3 = zzt(i1);
      if ((i3 != 9) && (i3 != 17))
      {
        if (i3 != 27) {
          if ((i3 != 60) && (i3 != 68))
          {
            if (i3 != 49)
            {
              if ((i3 != 50) || (((zzoc)zzps.zzf(paramObject, i1 & 0xFFFFF)).isEmpty())) {
                continue;
              }
              paramObject = (zzob)zzz(m);
              throw null;
            }
          }
          else
          {
            if ((!zzR(paramObject, n, m)) || (zzP(paramObject, i1, zzx(m)))) {
              continue;
            }
            return false;
          }
        }
        localObject1 = (List)zzps.zzf(paramObject, i1 & 0xFFFFF);
        if (!((List)localObject1).isEmpty())
        {
          localObject2 = zzx(m);
          i3 = 0;
        }
      }
      else
      {
        while (i3 < ((List)localObject1).size())
        {
          if (!((zzow)localObject2).zzl(((List)localObject1).get(i3))) {
            return false;
          }
          i3++;
          continue;
          if ((zzO(paramObject, m, i, j, i2)) && (!zzP(paramObject, i1, zzx(m)))) {
            return false;
          }
        }
      }
    }
    return (!zzh) || (zzb.zzk());
  }
}

/* Location:
 * Qualified Name:     com.google.android.recaptcha.internal.zzol
 * Java Class Version: 6 (50.0)
 * JD-Core Version:    0.7.1
 */