package C3;

public final class A$b
  implements Runnable
{
  public Runnable o;
  
  public A$b(A paramA) {}
  
  /* Error */
  public final void a()
  {
    // Byte code:
    //   0: iconst_0
    //   1: istore_1
    //   2: iconst_0
    //   3: istore_2
    //   4: iload_2
    //   5: istore_3
    //   6: aload_0
    //   7: getfield 17	C3/A$b:p	LC3/A;
    //   10: invokestatic 30	C3/A:a	(LC3/A;)Ljava/util/Deque;
    //   13: astore 4
    //   15: iload_2
    //   16: istore_3
    //   17: aload 4
    //   19: monitorenter
    //   20: iload_1
    //   21: istore 5
    //   23: iload_1
    //   24: ifne +64 -> 88
    //   27: aload_0
    //   28: getfield 17	C3/A$b:p	LC3/A;
    //   31: invokestatic 33	C3/A:b	(LC3/A;)LC3/A$c;
    //   34: astore 6
    //   36: getstatic 39	C3/A$c:r	LC3/A$c;
    //   39: astore 7
    //   41: aload 6
    //   43: aload 7
    //   45: if_acmpne +22 -> 67
    //   48: aload 4
    //   50: monitorexit
    //   51: iload_2
    //   52: ifeq +9 -> 61
    //   55: invokestatic 45	java/lang/Thread:currentThread	()Ljava/lang/Thread;
    //   58: invokevirtual 48	java/lang/Thread:interrupt	()V
    //   61: return
    //   62: astore 6
    //   64: goto +193 -> 257
    //   67: aload_0
    //   68: getfield 17	C3/A$b:p	LC3/A;
    //   71: invokestatic 52	C3/A:d	(LC3/A;)J
    //   74: pop2
    //   75: aload_0
    //   76: getfield 17	C3/A$b:p	LC3/A;
    //   79: aload 7
    //   81: invokestatic 56	C3/A:c	(LC3/A;LC3/A$c;)LC3/A$c;
    //   84: pop
    //   85: iconst_1
    //   86: istore 5
    //   88: aload_0
    //   89: getfield 17	C3/A$b:p	LC3/A;
    //   92: invokestatic 30	C3/A:a	(LC3/A;)Ljava/util/Deque;
    //   95: invokeinterface 62 1 0
    //   100: checkcast 6	java/lang/Runnable
    //   103: astore 6
    //   105: aload_0
    //   106: aload 6
    //   108: putfield 64	C3/A$b:o	Ljava/lang/Runnable;
    //   111: aload 6
    //   113: ifnonnull +28 -> 141
    //   116: aload_0
    //   117: getfield 17	C3/A$b:p	LC3/A;
    //   120: getstatic 66	C3/A$c:o	LC3/A$c;
    //   123: invokestatic 56	C3/A:c	(LC3/A;LC3/A$c;)LC3/A$c;
    //   126: pop
    //   127: aload 4
    //   129: monitorexit
    //   130: iload_2
    //   131: ifeq +9 -> 140
    //   134: invokestatic 45	java/lang/Thread:currentThread	()Ljava/lang/Thread;
    //   137: invokevirtual 48	java/lang/Thread:interrupt	()V
    //   140: return
    //   141: aload 4
    //   143: monitorexit
    //   144: iload_2
    //   145: istore_3
    //   146: invokestatic 70	java/lang/Thread:interrupted	()Z
    //   149: istore 8
    //   151: iload_2
    //   152: iload 8
    //   154: ior
    //   155: istore_2
    //   156: aload_0
    //   157: getfield 64	C3/A$b:o	Ljava/lang/Runnable;
    //   160: invokeinterface 73 1 0
    //   165: iload_2
    //   166: istore_3
    //   167: aload_0
    //   168: aconst_null
    //   169: putfield 64	C3/A$b:o	Ljava/lang/Runnable;
    //   172: iload 5
    //   174: istore_1
    //   175: goto -171 -> 4
    //   178: astore 4
    //   180: goto +85 -> 265
    //   183: astore 4
    //   185: goto +60 -> 245
    //   188: astore 4
    //   190: invokestatic 77	C3/A:e	()Ljava/util/logging/Logger;
    //   193: astore 7
    //   195: getstatic 83	java/util/logging/Level:SEVERE	Ljava/util/logging/Level;
    //   198: astore 6
    //   200: new 85	java/lang/StringBuilder
    //   203: astore 9
    //   205: aload 9
    //   207: invokespecial 86	java/lang/StringBuilder:<init>	()V
    //   210: aload 9
    //   212: ldc 88
    //   214: invokevirtual 92	java/lang/StringBuilder:append	(Ljava/lang/String;)Ljava/lang/StringBuilder;
    //   217: pop
    //   218: aload 9
    //   220: aload_0
    //   221: getfield 64	C3/A$b:o	Ljava/lang/Runnable;
    //   224: invokevirtual 95	java/lang/StringBuilder:append	(Ljava/lang/Object;)Ljava/lang/StringBuilder;
    //   227: pop
    //   228: aload 7
    //   230: aload 6
    //   232: aload 9
    //   234: invokevirtual 99	java/lang/StringBuilder:toString	()Ljava/lang/String;
    //   237: aload 4
    //   239: invokevirtual 105	java/util/logging/Logger:log	(Ljava/util/logging/Level;Ljava/lang/String;Ljava/lang/Throwable;)V
    //   242: goto -77 -> 165
    //   245: iload_2
    //   246: istore_3
    //   247: aload_0
    //   248: aconst_null
    //   249: putfield 64	C3/A$b:o	Ljava/lang/Runnable;
    //   252: iload_2
    //   253: istore_3
    //   254: aload 4
    //   256: athrow
    //   257: aload 4
    //   259: monitorexit
    //   260: iload_2
    //   261: istore_3
    //   262: aload 6
    //   264: athrow
    //   265: iload_3
    //   266: ifeq +9 -> 275
    //   269: invokestatic 45	java/lang/Thread:currentThread	()Ljava/lang/Thread;
    //   272: invokevirtual 48	java/lang/Thread:interrupt	()V
    //   275: aload 4
    //   277: athrow
    // Local variable table:
    //   start	length	slot	name	signature
    //   0	278	0	this	b
    //   1	174	1	i	int
    //   3	258	2	bool1	boolean
    //   5	261	3	j	int
    //   13	129	4	localDeque	java.util.Deque
    //   178	1	4	localObject1	Object
    //   183	1	4	localObject2	Object
    //   188	88	4	localRuntimeException	RuntimeException
    //   21	152	5	k	int
    //   34	8	6	localc	A.c
    //   62	1	6	localObject3	Object
    //   103	160	6	localObject4	Object
    //   39	190	7	localObject5	Object
    //   149	6	8	bool2	boolean
    //   203	30	9	localStringBuilder	StringBuilder
    // Exception table:
    //   from	to	target	type
    //   27	41	62	finally
    //   48	51	62	finally
    //   67	85	62	finally
    //   88	111	62	finally
    //   116	130	62	finally
    //   141	144	62	finally
    //   257	260	62	finally
    //   6	15	178	finally
    //   17	20	178	finally
    //   146	151	178	finally
    //   167	172	178	finally
    //   247	252	178	finally
    //   254	257	178	finally
    //   262	265	178	finally
    //   156	165	183	finally
    //   190	242	183	finally
    //   156	165	188	java/lang/RuntimeException
  }
  
  public void run()
  {
    try
    {
      a();
      return;
    }
    catch (Error localError)
    {
      synchronized (A.a(p))
      {
        A.c(p, A.c.o);
        throw localError;
      }
    }
  }
  
  public String toString()
  {
    Object localObject = o;
    if (localObject != null)
    {
      StringBuilder localStringBuilder = new StringBuilder();
      localStringBuilder.append("SequentialExecutorWorker{running=");
      localStringBuilder.append(localObject);
      localStringBuilder.append("}");
      return localStringBuilder.toString();
    }
    localObject = new StringBuilder();
    ((StringBuilder)localObject).append("SequentialExecutorWorker{state=");
    ((StringBuilder)localObject).append(A.b(p));
    ((StringBuilder)localObject).append("}");
    return ((StringBuilder)localObject).toString();
  }
}

/* Location:
 * Qualified Name:     C3.A.b
 * Java Class Version: 6 (50.0)
 * JD-Core Version:    0.7.1
 */