package e7;

import com.google.android.gms.internal.measurement.zzdq;
import java.util.concurrent.atomic.AtomicReference;

public final class f4
  implements Runnable
{
  public f4(k3 paramk3, AtomicReference paramAtomicReference, String paramString1, String paramString2, boolean paramBoolean) {}
  
  public f4(w4 paramw4, String paramString1, String paramString2, k6 paramk6, boolean paramBoolean, zzdq paramzzdq) {}
  
  /* Error */
  public final void run()
  {
    // Byte code:
    //   0: aload_0
    //   1: getfield 22	e7/f4:a	I
    //   4: tableswitch	default:+20->24, 0:+23->27
    //   24: goto +80 -> 104
    //   27: aload_0
    //   28: getfield 34	e7/f4:o	Le7/j0;
    //   31: checkcast 44	e7/k3
    //   34: getfield 48	d2/q:b	Ljava/lang/Object;
    //   37: checkcast 50	e7/j2
    //   40: invokevirtual 54	e7/j2:l	()Le7/w4;
    //   43: astore_1
    //   44: aload_0
    //   45: getfield 24	e7/f4:e	Ljava/lang/Object;
    //   48: checkcast 56	java/util/concurrent/atomic/AtomicReference
    //   51: astore_2
    //   52: aload_0
    //   53: getfield 28	e7/f4:c	Ljava/lang/String;
    //   56: astore_3
    //   57: aload_0
    //   58: getfield 30	e7/f4:f	Ljava/lang/Object;
    //   61: checkcast 58	java/lang/String
    //   64: astore 4
    //   66: aload_0
    //   67: getfield 32	e7/f4:d	Z
    //   70: istore 5
    //   72: aload_1
    //   73: invokevirtual 62	e7/o0:l	()V
    //   76: aload_1
    //   77: invokevirtual 67	e7/j0:t	()V
    //   80: aload_1
    //   81: new 69	e7/h5
    //   84: dup
    //   85: aload_1
    //   86: aload_2
    //   87: aload_3
    //   88: aload 4
    //   90: aload_1
    //   91: iconst_0
    //   92: invokevirtual 74	e7/w4:I	(Z)Le7/k6;
    //   95: iload 5
    //   97: invokespecial 77	e7/h5:<init>	(Le7/w4;Ljava/util/concurrent/atomic/AtomicReference;Ljava/lang/String;Ljava/lang/String;Le7/k6;Z)V
    //   100: invokevirtual 81	e7/w4:x	(Ljava/lang/Runnable;)V
    //   103: return
    //   104: new 83	android/os/Bundle
    //   107: dup
    //   108: invokespecial 84	android/os/Bundle:<init>	()V
    //   111: astore_3
    //   112: aload_3
    //   113: astore_2
    //   114: aload_3
    //   115: astore 4
    //   117: aload_0
    //   118: getfield 34	e7/f4:o	Le7/j0;
    //   121: astore 6
    //   123: aload_3
    //   124: astore_2
    //   125: aload_3
    //   126: astore 4
    //   128: aload 6
    //   130: checkcast 71	e7/w4
    //   133: getfield 87	e7/w4:e	Le7/n0;
    //   136: astore_1
    //   137: aload_1
    //   138: ifnonnull +38 -> 176
    //   141: aload_3
    //   142: astore_2
    //   143: aload_3
    //   144: astore 4
    //   146: aload 6
    //   148: checkcast 71	e7/w4
    //   151: invokevirtual 91	d2/q:zzj	()Le7/a1;
    //   154: getfield 96	e7/a1:o	Le7/b1;
    //   157: ldc 98
    //   159: aload_0
    //   160: getfield 26	e7/f4:b	Ljava/lang/String;
    //   163: aload_0
    //   164: getfield 28	e7/f4:c	Ljava/lang/String;
    //   167: invokevirtual 103	e7/b1:d	(Ljava/lang/String;Ljava/lang/Object;Ljava/lang/Object;)V
    //   170: aload_3
    //   171: astore 4
    //   173: goto +104 -> 277
    //   176: aload_3
    //   177: astore_2
    //   178: aload_3
    //   179: astore 4
    //   181: aload_0
    //   182: getfield 24	e7/f4:e	Ljava/lang/Object;
    //   185: checkcast 105	e7/k6
    //   188: invokestatic 111	m6/j:i	(Ljava/lang/Object;)V
    //   191: aload_3
    //   192: astore_2
    //   193: aload_3
    //   194: astore 4
    //   196: aload_1
    //   197: aload_0
    //   198: getfield 26	e7/f4:b	Ljava/lang/String;
    //   201: aload_0
    //   202: getfield 28	e7/f4:c	Ljava/lang/String;
    //   205: aload_0
    //   206: getfield 32	e7/f4:d	Z
    //   209: aload_0
    //   210: getfield 24	e7/f4:e	Ljava/lang/Object;
    //   213: checkcast 105	e7/k6
    //   216: invokeinterface 117 5 0
    //   221: invokestatic 122	e7/r6:x	(Ljava/util/List;)Landroid/os/Bundle;
    //   224: astore_3
    //   225: aload_3
    //   226: astore_2
    //   227: aload_3
    //   228: astore 4
    //   230: aload_0
    //   231: getfield 34	e7/f4:o	Le7/j0;
    //   234: checkcast 71	e7/w4
    //   237: invokevirtual 125	e7/w4:H	()V
    //   240: aload_3
    //   241: astore 4
    //   243: goto +34 -> 277
    //   246: astore_3
    //   247: goto +88 -> 335
    //   250: astore_3
    //   251: aload 4
    //   253: astore_2
    //   254: aload_0
    //   255: getfield 34	e7/f4:o	Le7/j0;
    //   258: checkcast 71	e7/w4
    //   261: invokevirtual 91	d2/q:zzj	()Le7/a1;
    //   264: getfield 96	e7/a1:o	Le7/b1;
    //   267: ldc 127
    //   269: aload_0
    //   270: getfield 26	e7/f4:b	Ljava/lang/String;
    //   273: aload_3
    //   274: invokevirtual 103	e7/b1:d	(Ljava/lang/String;Ljava/lang/Object;Ljava/lang/Object;)V
    //   277: aload_0
    //   278: getfield 34	e7/f4:o	Le7/j0;
    //   281: checkcast 71	e7/w4
    //   284: invokevirtual 131	d2/q:k	()Le7/r6;
    //   287: astore_2
    //   288: aload_0
    //   289: getfield 30	e7/f4:f	Ljava/lang/Object;
    //   292: checkcast 133	com/google/android/gms/internal/measurement/zzdq
    //   295: astore_3
    //   296: aload_2
    //   297: invokevirtual 137	java/lang/Object:getClass	()Ljava/lang/Class;
    //   300: pop
    //   301: aload_3
    //   302: aload 4
    //   304: invokeinterface 141 2 0
    //   309: goto +25 -> 334
    //   312: astore 4
    //   314: aload_2
    //   315: getfield 48	d2/q:b	Ljava/lang/Object;
    //   318: checkcast 50	e7/j2
    //   321: invokevirtual 142	e7/j2:zzj	()Le7/a1;
    //   324: getfield 145	e7/a1:r	Le7/b1;
    //   327: ldc -109
    //   329: aload 4
    //   331: invokevirtual 150	e7/b1:c	(Ljava/lang/String;Ljava/lang/Object;)V
    //   334: return
    //   335: aload_0
    //   336: getfield 34	e7/f4:o	Le7/j0;
    //   339: checkcast 71	e7/w4
    //   342: invokevirtual 131	d2/q:k	()Le7/r6;
    //   345: astore 4
    //   347: aload_0
    //   348: getfield 30	e7/f4:f	Ljava/lang/Object;
    //   351: checkcast 133	com/google/android/gms/internal/measurement/zzdq
    //   354: astore_1
    //   355: aload 4
    //   357: invokevirtual 137	java/lang/Object:getClass	()Ljava/lang/Class;
    //   360: pop
    //   361: aload_1
    //   362: aload_2
    //   363: invokeinterface 141 2 0
    //   368: goto +24 -> 392
    //   371: astore_2
    //   372: aload 4
    //   374: getfield 48	d2/q:b	Ljava/lang/Object;
    //   377: checkcast 50	e7/j2
    //   380: invokevirtual 142	e7/j2:zzj	()Le7/a1;
    //   383: getfield 145	e7/a1:r	Le7/b1;
    //   386: ldc -109
    //   388: aload_2
    //   389: invokevirtual 150	e7/b1:c	(Ljava/lang/String;Ljava/lang/Object;)V
    //   392: aload_3
    //   393: athrow
    // Local variable table:
    //   start	length	slot	name	signature
    //   0	394	0	this	f4
    //   43	319	1	localObject1	Object
    //   51	312	2	localObject2	Object
    //   371	18	2	localRemoteException1	android.os.RemoteException
    //   56	185	3	localObject3	Object
    //   246	1	3	localObject4	Object
    //   250	24	3	localRemoteException2	android.os.RemoteException
    //   295	98	3	localzzdq	zzdq
    //   64	239	4	localObject5	Object
    //   312	18	4	localRemoteException3	android.os.RemoteException
    //   345	28	4	localr6	r6
    //   70	26	5	bool	boolean
    //   121	26	6	localj0	j0
    // Exception table:
    //   from	to	target	type
    //   117	123	246	finally
    //   128	137	246	finally
    //   146	170	246	finally
    //   181	191	246	finally
    //   196	225	246	finally
    //   230	240	246	finally
    //   254	277	246	finally
    //   117	123	250	android/os/RemoteException
    //   128	137	250	android/os/RemoteException
    //   146	170	250	android/os/RemoteException
    //   181	191	250	android/os/RemoteException
    //   196	225	250	android/os/RemoteException
    //   230	240	250	android/os/RemoteException
    //   301	309	312	android/os/RemoteException
    //   361	368	371	android/os/RemoteException
  }
}

/* Location:
 * Qualified Name:     e7.f4
 * Java Class Version: 6 (50.0)
 * JD-Core Version:    0.7.1
 */