package e7;

import java.util.concurrent.atomic.AtomicReference;

public final class h5
  implements Runnable
{
  public h5(w4 paramw4, AtomicReference paramAtomicReference, String paramString1, String paramString2, k6 paramk6, boolean paramBoolean) {}
  
  /* Error */
  public final void run()
  {
    // Byte code:
    //   0: aload_0
    //   1: getfield 22	e7/h5:a	Ljava/util/concurrent/atomic/AtomicReference;
    //   4: astore_1
    //   5: aload_1
    //   6: monitorenter
    //   7: aload_0
    //   8: getfield 34	e7/h5:o	Le7/w4;
    //   11: astore_2
    //   12: aload_2
    //   13: getfield 46	e7/w4:e	Le7/n0;
    //   16: astore_3
    //   17: aload_3
    //   18: ifnonnull +50 -> 68
    //   21: aload_2
    //   22: invokevirtual 52	d2/q:zzj	()Le7/a1;
    //   25: getfield 57	e7/a1:o	Le7/b1;
    //   28: aload_0
    //   29: getfield 24	e7/h5:b	Ljava/lang/String;
    //   32: invokestatic 61	e7/a1:p	(Ljava/lang/String;)Le7/e1;
    //   35: aload_0
    //   36: getfield 26	e7/h5:c	Ljava/lang/String;
    //   39: aload_0
    //   40: getfield 28	e7/h5:d	Ljava/lang/String;
    //   43: ldc 63
    //   45: invokevirtual 68	e7/b1:a	(Ljava/lang/Object;Ljava/lang/Object;Ljava/lang/Object;Ljava/lang/String;)V
    //   48: aload_0
    //   49: getfield 22	e7/h5:a	Ljava/util/concurrent/atomic/AtomicReference;
    //   52: invokestatic 74	java/util/Collections:emptyList	()Ljava/util/List;
    //   55: invokevirtual 80	java/util/concurrent/atomic/AtomicReference:set	(Ljava/lang/Object;)V
    //   58: aload_0
    //   59: getfield 22	e7/h5:a	Ljava/util/concurrent/atomic/AtomicReference;
    //   62: invokevirtual 83	java/lang/Object:notify	()V
    //   65: aload_1
    //   66: monitorexit
    //   67: return
    //   68: aload_0
    //   69: getfield 24	e7/h5:b	Ljava/lang/String;
    //   72: invokestatic 89	android/text/TextUtils:isEmpty	(Ljava/lang/CharSequence;)Z
    //   75: ifeq +41 -> 116
    //   78: aload_0
    //   79: getfield 30	e7/h5:e	Le7/k6;
    //   82: invokestatic 94	m6/j:i	(Ljava/lang/Object;)V
    //   85: aload_0
    //   86: getfield 22	e7/h5:a	Ljava/util/concurrent/atomic/AtomicReference;
    //   89: astore_2
    //   90: aload_3
    //   91: aload_0
    //   92: getfield 26	e7/h5:c	Ljava/lang/String;
    //   95: aload_0
    //   96: getfield 28	e7/h5:d	Ljava/lang/String;
    //   99: aload_0
    //   100: getfield 32	e7/h5:f	Z
    //   103: aload_0
    //   104: getfield 30	e7/h5:e	Le7/k6;
    //   107: invokeinterface 100 5 0
    //   112: astore_3
    //   113: goto +31 -> 144
    //   116: aload_0
    //   117: getfield 22	e7/h5:a	Ljava/util/concurrent/atomic/AtomicReference;
    //   120: astore_2
    //   121: aload_3
    //   122: aload_0
    //   123: getfield 24	e7/h5:b	Ljava/lang/String;
    //   126: aload_0
    //   127: getfield 26	e7/h5:c	Ljava/lang/String;
    //   130: aload_0
    //   131: getfield 28	e7/h5:d	Ljava/lang/String;
    //   134: aload_0
    //   135: getfield 32	e7/h5:f	Z
    //   138: invokeinterface 104 5 0
    //   143: astore_3
    //   144: aload_2
    //   145: aload_3
    //   146: invokevirtual 80	java/util/concurrent/atomic/AtomicReference:set	(Ljava/lang/Object;)V
    //   149: aload_0
    //   150: getfield 34	e7/h5:o	Le7/w4;
    //   153: invokevirtual 107	e7/w4:H	()V
    //   156: aload_0
    //   157: getfield 22	e7/h5:a	Ljava/util/concurrent/atomic/AtomicReference;
    //   160: astore_3
    //   161: goto +48 -> 209
    //   164: astore_3
    //   165: goto +51 -> 216
    //   168: astore_3
    //   169: aload_0
    //   170: getfield 34	e7/h5:o	Le7/w4;
    //   173: invokevirtual 52	d2/q:zzj	()Le7/a1;
    //   176: getfield 57	e7/a1:o	Le7/b1;
    //   179: aload_0
    //   180: getfield 24	e7/h5:b	Ljava/lang/String;
    //   183: invokestatic 61	e7/a1:p	(Ljava/lang/String;)Le7/e1;
    //   186: aload_0
    //   187: getfield 26	e7/h5:c	Ljava/lang/String;
    //   190: aload_3
    //   191: ldc 109
    //   193: invokevirtual 68	e7/b1:a	(Ljava/lang/Object;Ljava/lang/Object;Ljava/lang/Object;Ljava/lang/String;)V
    //   196: aload_0
    //   197: getfield 22	e7/h5:a	Ljava/util/concurrent/atomic/AtomicReference;
    //   200: invokestatic 74	java/util/Collections:emptyList	()Ljava/util/List;
    //   203: invokevirtual 80	java/util/concurrent/atomic/AtomicReference:set	(Ljava/lang/Object;)V
    //   206: goto -50 -> 156
    //   209: aload_3
    //   210: invokevirtual 83	java/lang/Object:notify	()V
    //   213: aload_1
    //   214: monitorexit
    //   215: return
    //   216: aload_0
    //   217: getfield 22	e7/h5:a	Ljava/util/concurrent/atomic/AtomicReference;
    //   220: invokevirtual 83	java/lang/Object:notify	()V
    //   223: aload_3
    //   224: athrow
    //   225: astore_3
    //   226: aload_1
    //   227: monitorexit
    //   228: aload_3
    //   229: athrow
    // Local variable table:
    //   start	length	slot	name	signature
    //   0	230	0	this	h5
    //   11	134	2	localObject1	Object
    //   16	145	3	localObject2	Object
    //   164	1	3	localObject3	Object
    //   168	56	3	localRemoteException	android.os.RemoteException
    //   225	4	3	localObject4	Object
    // Exception table:
    //   from	to	target	type
    //   7	17	164	finally
    //   21	58	164	finally
    //   68	113	164	finally
    //   116	144	164	finally
    //   144	156	164	finally
    //   169	206	164	finally
    //   7	17	168	android/os/RemoteException
    //   21	58	168	android/os/RemoteException
    //   68	113	168	android/os/RemoteException
    //   116	144	168	android/os/RemoteException
    //   144	156	168	android/os/RemoteException
    //   58	67	225	finally
    //   156	161	225	finally
    //   209	215	225	finally
    //   216	225	225	finally
    //   226	228	225	finally
  }
}

/* Location:
 * Qualified Name:     e7.h5
 * Java Class Version: 6 (50.0)
 * JD-Core Version:    0.7.1
 */