package e7;

public final class t3
  implements Runnable
{
  /* Error */
  public final void run()
  {
    // Byte code:
    //   0: aload_0
    //   1: getfield 16	e7/t3:a	I
    //   4: tableswitch	default:+20->24, 0:+23->27
    //   24: goto +81 -> 105
    //   27: aload_0
    //   28: getfield 18	e7/t3:b	Ljava/util/concurrent/atomic/AtomicReference;
    //   31: astore_1
    //   32: aload_1
    //   33: monitorenter
    //   34: aload_0
    //   35: getfield 18	e7/t3:b	Ljava/util/concurrent/atomic/AtomicReference;
    //   38: astore_2
    //   39: aload_0
    //   40: getfield 20	e7/t3:c	Le7/k3;
    //   43: invokevirtual 31	d2/q:h	()Le7/h;
    //   46: astore_3
    //   47: aload_0
    //   48: getfield 20	e7/t3:c	Le7/k3;
    //   51: invokevirtual 37	e7/o0:m	()Le7/t0;
    //   54: invokevirtual 43	e7/t0:v	()Ljava/lang/String;
    //   57: astore 4
    //   59: aload_3
    //   60: invokevirtual 47	java/lang/Object:getClass	()Ljava/lang/Class;
    //   63: pop
    //   64: aload_2
    //   65: aload_3
    //   66: aload 4
    //   68: getstatic 53	e7/h0:V	Le7/m0;
    //   71: invokevirtual 59	e7/h:x	(Ljava/lang/String;Le7/m0;)Z
    //   74: invokestatic 65	java/lang/Boolean:valueOf	(Z)Ljava/lang/Boolean;
    //   77: invokevirtual 71	java/util/concurrent/atomic/AtomicReference:set	(Ljava/lang/Object;)V
    //   80: aload_0
    //   81: getfield 18	e7/t3:b	Ljava/util/concurrent/atomic/AtomicReference;
    //   84: invokevirtual 74	java/lang/Object:notify	()V
    //   87: aload_1
    //   88: monitorexit
    //   89: return
    //   90: astore_2
    //   91: aload_0
    //   92: getfield 18	e7/t3:b	Ljava/util/concurrent/atomic/AtomicReference;
    //   95: invokevirtual 74	java/lang/Object:notify	()V
    //   98: aload_2
    //   99: athrow
    //   100: astore_2
    //   101: aload_1
    //   102: monitorexit
    //   103: aload_2
    //   104: athrow
    //   105: aload_0
    //   106: getfield 18	e7/t3:b	Ljava/util/concurrent/atomic/AtomicReference;
    //   109: astore_1
    //   110: aload_1
    //   111: monitorenter
    //   112: aload_0
    //   113: getfield 18	e7/t3:b	Ljava/util/concurrent/atomic/AtomicReference;
    //   116: aload_0
    //   117: getfield 20	e7/t3:c	Le7/k3;
    //   120: invokevirtual 31	d2/q:h	()Le7/h;
    //   123: aload_0
    //   124: getfield 20	e7/t3:c	Le7/k3;
    //   127: invokevirtual 37	e7/o0:m	()Le7/t0;
    //   130: invokevirtual 43	e7/t0:v	()Ljava/lang/String;
    //   133: getstatic 77	e7/h0:Y	Le7/m0;
    //   136: invokevirtual 81	e7/h:q	(Ljava/lang/String;Le7/m0;)I
    //   139: invokestatic 86	java/lang/Integer:valueOf	(I)Ljava/lang/Integer;
    //   142: invokevirtual 71	java/util/concurrent/atomic/AtomicReference:set	(Ljava/lang/Object;)V
    //   145: aload_0
    //   146: getfield 18	e7/t3:b	Ljava/util/concurrent/atomic/AtomicReference;
    //   149: invokevirtual 74	java/lang/Object:notify	()V
    //   152: aload_1
    //   153: monitorexit
    //   154: return
    //   155: astore_2
    //   156: aload_0
    //   157: getfield 18	e7/t3:b	Ljava/util/concurrent/atomic/AtomicReference;
    //   160: invokevirtual 74	java/lang/Object:notify	()V
    //   163: aload_2
    //   164: athrow
    //   165: astore_2
    //   166: aload_1
    //   167: monitorexit
    //   168: aload_2
    //   169: athrow
    // Local variable table:
    //   start	length	slot	name	signature
    //   0	170	0	this	t3
    //   31	136	1	localAtomicReference1	java.util.concurrent.atomic.AtomicReference
    //   38	27	2	localAtomicReference2	java.util.concurrent.atomic.AtomicReference
    //   90	9	2	localObject1	Object
    //   100	4	2	localObject2	Object
    //   155	9	2	localObject3	Object
    //   165	4	2	localObject4	Object
    //   46	20	3	localh	h
    //   57	10	4	str	String
    // Exception table:
    //   from	to	target	type
    //   34	80	90	finally
    //   80	89	100	finally
    //   91	100	100	finally
    //   101	103	100	finally
    //   112	145	155	finally
    //   145	154	165	finally
    //   156	165	165	finally
    //   166	168	165	finally
  }
}

/* Location:
 * Qualified Name:     e7.t3
 * Java Class Version: 6 (50.0)
 * JD-Core Version:    0.7.1
 */