package e7;

public final class v1
  implements Runnable
{
  /* Error */
  public final void run()
  {
    // Byte code:
    //   0: aload_0
    //   1: getfield 16	e7/v1:a	I
    //   4: tableswitch	default:+28->32, 0:+206->210, 1:+119->123, 2:+31->35
    //   32: goto +330 -> 362
    //   35: aload_0
    //   36: getfield 21	e7/v1:b	Ljava/lang/Object;
    //   39: checkcast 34	e7/w4
    //   42: astore_1
    //   43: aload_0
    //   44: getfield 23	e7/v1:c	Ljava/lang/Object;
    //   47: checkcast 36	e7/k6
    //   50: astore_2
    //   51: aload_0
    //   52: getfield 25	e7/v1:d	Ljava/lang/Object;
    //   55: checkcast 38	e7/e
    //   58: astore_3
    //   59: aload_1
    //   60: getfield 42	e7/w4:e	Le7/n0;
    //   63: astore 4
    //   65: aload 4
    //   67: ifnonnull +18 -> 85
    //   70: aload_1
    //   71: invokevirtual 48	d2/q:zzj	()Le7/a1;
    //   74: getfield 54	e7/a1:o	Le7/b1;
    //   77: ldc 56
    //   79: invokevirtual 61	e7/b1:b	(Ljava/lang/String;)V
    //   82: goto +40 -> 122
    //   85: aload 4
    //   87: aload_2
    //   88: aload_3
    //   89: invokeinterface 67 3 0
    //   94: aload_1
    //   95: invokevirtual 70	e7/w4:H	()V
    //   98: goto +24 -> 122
    //   101: astore_2
    //   102: aload_1
    //   103: invokevirtual 48	d2/q:zzj	()Le7/a1;
    //   106: getfield 54	e7/a1:o	Le7/b1;
    //   109: ldc 72
    //   111: aload_3
    //   112: getfield 75	e7/e:a	J
    //   115: invokestatic 81	java/lang/Long:valueOf	(J)Ljava/lang/Long;
    //   118: aload_2
    //   119: invokevirtual 84	e7/b1:d	(Ljava/lang/String;Ljava/lang/Object;Ljava/lang/Object;)V
    //   122: return
    //   123: aload_0
    //   124: getfield 25	e7/v1:d	Ljava/lang/Object;
    //   127: checkcast 86	com/google/android/gms/measurement/internal/zzig
    //   130: getfield 89	com/google/android/gms/measurement/internal/zzig:a	Le7/i6;
    //   133: invokevirtual 94	e7/i6:c0	()V
    //   136: aload_0
    //   137: getfield 21	e7/v1:b	Ljava/lang/Object;
    //   140: checkcast 96	e7/q6
    //   143: invokevirtual 100	e7/q6:D	()Ljava/lang/Object;
    //   146: ifnonnull +36 -> 182
    //   149: aload_0
    //   150: getfield 25	e7/v1:d	Ljava/lang/Object;
    //   153: checkcast 86	com/google/android/gms/measurement/internal/zzig
    //   156: getfield 89	com/google/android/gms/measurement/internal/zzig:a	Le7/i6;
    //   159: aload_0
    //   160: getfield 21	e7/v1:b	Ljava/lang/Object;
    //   163: checkcast 96	e7/q6
    //   166: getfield 103	e7/q6:b	Ljava/lang/String;
    //   169: aload_0
    //   170: getfield 23	e7/v1:c	Ljava/lang/Object;
    //   173: checkcast 36	e7/k6
    //   176: invokevirtual 107	e7/i6:v	(Ljava/lang/String;Le7/k6;)V
    //   179: goto +30 -> 209
    //   182: aload_0
    //   183: getfield 25	e7/v1:d	Ljava/lang/Object;
    //   186: checkcast 86	com/google/android/gms/measurement/internal/zzig
    //   189: getfield 89	com/google/android/gms/measurement/internal/zzig:a	Le7/i6;
    //   192: aload_0
    //   193: getfield 21	e7/v1:b	Ljava/lang/Object;
    //   196: checkcast 96	e7/q6
    //   199: aload_0
    //   200: getfield 23	e7/v1:c	Ljava/lang/Object;
    //   203: checkcast 36	e7/k6
    //   206: invokevirtual 111	e7/i6:r	(Le7/q6;Le7/k6;)V
    //   209: return
    //   210: aload_0
    //   211: getfield 25	e7/v1:d	Ljava/lang/Object;
    //   214: checkcast 113	e7/s1
    //   217: astore_1
    //   218: aload_1
    //   219: getfield 116	e7/s1:b	Le7/t1;
    //   222: astore_3
    //   223: aload_1
    //   224: getfield 118	e7/s1:a	Ljava/lang/String;
    //   227: astore_2
    //   228: aload_0
    //   229: getfield 21	e7/v1:b	Ljava/lang/Object;
    //   232: checkcast 120	com/google/android/gms/internal/measurement/zzbz
    //   235: astore 4
    //   237: aload_3
    //   238: getfield 125	e7/t1:a	Le7/j2;
    //   241: invokevirtual 131	e7/j2:zzl	()Le7/e2;
    //   244: invokevirtual 136	e7/e2:l	()V
    //   247: aload 4
    //   249: ifnull +70 -> 319
    //   252: new 138	android/os/Bundle
    //   255: dup
    //   256: invokespecial 139	android/os/Bundle:<init>	()V
    //   259: astore_1
    //   260: aload_1
    //   261: ldc -115
    //   263: aload_2
    //   264: invokevirtual 147	android/os/BaseBundle:putString	(Ljava/lang/String;Ljava/lang/String;)V
    //   267: aload 4
    //   269: aload_1
    //   270: invokeinterface 151 2 0
    //   275: ifnonnull +59 -> 334
    //   278: aload_3
    //   279: getfield 125	e7/t1:a	Le7/j2;
    //   282: invokevirtual 152	e7/j2:zzj	()Le7/a1;
    //   285: getfield 54	e7/a1:o	Le7/b1;
    //   288: ldc -102
    //   290: invokevirtual 61	e7/b1:b	(Ljava/lang/String;)V
    //   293: goto +41 -> 334
    //   296: astore_1
    //   297: aload_3
    //   298: getfield 125	e7/t1:a	Le7/j2;
    //   301: invokevirtual 152	e7/j2:zzj	()Le7/a1;
    //   304: getfield 54	e7/a1:o	Le7/b1;
    //   307: ldc -100
    //   309: aload_1
    //   310: invokevirtual 162	java/lang/Throwable:getMessage	()Ljava/lang/String;
    //   313: invokevirtual 165	e7/b1:c	(Ljava/lang/String;Ljava/lang/Object;)V
    //   316: goto +18 -> 334
    //   319: aload_3
    //   320: getfield 125	e7/t1:a	Le7/j2;
    //   323: invokevirtual 152	e7/j2:zzj	()Le7/a1;
    //   326: getfield 167	e7/a1:r	Le7/b1;
    //   329: ldc -87
    //   331: invokevirtual 61	e7/b1:b	(Ljava/lang/String;)V
    //   334: aload_3
    //   335: getfield 125	e7/t1:a	Le7/j2;
    //   338: invokevirtual 131	e7/j2:zzl	()Le7/e2;
    //   341: invokevirtual 136	e7/e2:l	()V
    //   344: aload_3
    //   345: getfield 125	e7/t1:a	Le7/j2;
    //   348: invokevirtual 173	java/lang/Object:getClass	()Ljava/lang/Class;
    //   351: pop
    //   352: new 175	java/lang/IllegalStateException
    //   355: dup
    //   356: ldc -79
    //   358: invokespecial 179	java/lang/IllegalStateException:<init>	(Ljava/lang/String;)V
    //   361: athrow
    //   362: aload_0
    //   363: getfield 21	e7/v1:b	Ljava/lang/Object;
    //   366: checkcast 181	java/util/concurrent/atomic/AtomicReference
    //   369: astore_1
    //   370: aload_1
    //   371: monitorenter
    //   372: aload_0
    //   373: getfield 25	e7/v1:d	Ljava/lang/Object;
    //   376: checkcast 34	e7/w4
    //   379: invokevirtual 185	d2/q:j	()Le7/l1;
    //   382: invokevirtual 191	e7/l1:y	()Le7/e3;
    //   385: invokevirtual 197	e7/e3:p	()Z
    //   388: ifne +78 -> 466
    //   391: aload_0
    //   392: getfield 25	e7/v1:d	Ljava/lang/Object;
    //   395: checkcast 34	e7/w4
    //   398: invokevirtual 48	d2/q:zzj	()Le7/a1;
    //   401: getfield 200	e7/a1:t	Le7/b1;
    //   404: ldc -54
    //   406: invokevirtual 61	e7/b1:b	(Ljava/lang/String;)V
    //   409: aload_0
    //   410: getfield 25	e7/v1:d	Ljava/lang/Object;
    //   413: checkcast 34	e7/w4
    //   416: invokevirtual 207	e7/o0:o	()Le7/k3;
    //   419: aconst_null
    //   420: invokevirtual 212	e7/k3:P	(Ljava/lang/String;)V
    //   423: aload_0
    //   424: getfield 25	e7/v1:d	Ljava/lang/Object;
    //   427: checkcast 34	e7/w4
    //   430: invokevirtual 185	d2/q:j	()Le7/l1;
    //   433: getfield 216	e7/l1:q	Le7/r1;
    //   436: aconst_null
    //   437: invokevirtual 219	e7/r1:b	(Ljava/lang/String;)V
    //   440: aload_0
    //   441: getfield 21	e7/v1:b	Ljava/lang/Object;
    //   444: checkcast 181	java/util/concurrent/atomic/AtomicReference
    //   447: aconst_null
    //   448: invokevirtual 223	java/util/concurrent/atomic/AtomicReference:set	(Ljava/lang/Object;)V
    //   451: aload_0
    //   452: getfield 21	e7/v1:b	Ljava/lang/Object;
    //   455: checkcast 181	java/util/concurrent/atomic/AtomicReference
    //   458: astore_3
    //   459: aload_3
    //   460: invokevirtual 226	java/lang/Object:notify	()V
    //   463: goto +181 -> 644
    //   466: aload_0
    //   467: getfield 25	e7/v1:d	Ljava/lang/Object;
    //   470: astore_3
    //   471: aload_3
    //   472: checkcast 34	e7/w4
    //   475: getfield 42	e7/w4:e	Le7/n0;
    //   478: astore_2
    //   479: aload_2
    //   480: ifnonnull +29 -> 509
    //   483: aload_3
    //   484: checkcast 34	e7/w4
    //   487: invokevirtual 48	d2/q:zzj	()Le7/a1;
    //   490: getfield 54	e7/a1:o	Le7/b1;
    //   493: ldc -28
    //   495: invokevirtual 61	e7/b1:b	(Ljava/lang/String;)V
    //   498: aload_0
    //   499: getfield 21	e7/v1:b	Ljava/lang/Object;
    //   502: checkcast 181	java/util/concurrent/atomic/AtomicReference
    //   505: astore_3
    //   506: goto -47 -> 459
    //   509: aload_0
    //   510: getfield 23	e7/v1:c	Ljava/lang/Object;
    //   513: checkcast 36	e7/k6
    //   516: invokestatic 233	m6/j:i	(Ljava/lang/Object;)V
    //   519: aload_0
    //   520: getfield 21	e7/v1:b	Ljava/lang/Object;
    //   523: checkcast 181	java/util/concurrent/atomic/AtomicReference
    //   526: aload_2
    //   527: aload_0
    //   528: getfield 23	e7/v1:c	Ljava/lang/Object;
    //   531: checkcast 36	e7/k6
    //   534: invokeinterface 237 2 0
    //   539: invokevirtual 223	java/util/concurrent/atomic/AtomicReference:set	(Ljava/lang/Object;)V
    //   542: aload_0
    //   543: getfield 21	e7/v1:b	Ljava/lang/Object;
    //   546: checkcast 181	java/util/concurrent/atomic/AtomicReference
    //   549: invokevirtual 240	java/util/concurrent/atomic/AtomicReference:get	()Ljava/lang/Object;
    //   552: checkcast 242	java/lang/String
    //   555: astore_3
    //   556: aload_3
    //   557: ifnull +34 -> 591
    //   560: aload_0
    //   561: getfield 25	e7/v1:d	Ljava/lang/Object;
    //   564: checkcast 34	e7/w4
    //   567: invokevirtual 207	e7/o0:o	()Le7/k3;
    //   570: aload_3
    //   571: invokevirtual 212	e7/k3:P	(Ljava/lang/String;)V
    //   574: aload_0
    //   575: getfield 25	e7/v1:d	Ljava/lang/Object;
    //   578: checkcast 34	e7/w4
    //   581: invokevirtual 185	d2/q:j	()Le7/l1;
    //   584: getfield 216	e7/l1:q	Le7/r1;
    //   587: aload_3
    //   588: invokevirtual 219	e7/r1:b	(Ljava/lang/String;)V
    //   591: aload_0
    //   592: getfield 25	e7/v1:d	Ljava/lang/Object;
    //   595: checkcast 34	e7/w4
    //   598: invokevirtual 70	e7/w4:H	()V
    //   601: aload_0
    //   602: getfield 21	e7/v1:b	Ljava/lang/Object;
    //   605: astore_3
    //   606: goto +30 -> 636
    //   609: astore_3
    //   610: goto +37 -> 647
    //   613: astore_3
    //   614: aload_0
    //   615: getfield 25	e7/v1:d	Ljava/lang/Object;
    //   618: checkcast 34	e7/w4
    //   621: invokevirtual 48	d2/q:zzj	()Le7/a1;
    //   624: getfield 54	e7/a1:o	Le7/b1;
    //   627: ldc -28
    //   629: aload_3
    //   630: invokevirtual 165	e7/b1:c	(Ljava/lang/String;Ljava/lang/Object;)V
    //   633: goto -32 -> 601
    //   636: aload_3
    //   637: checkcast 181	java/util/concurrent/atomic/AtomicReference
    //   640: astore_3
    //   641: goto -182 -> 459
    //   644: aload_1
    //   645: monitorexit
    //   646: return
    //   647: aload_0
    //   648: getfield 21	e7/v1:b	Ljava/lang/Object;
    //   651: checkcast 181	java/util/concurrent/atomic/AtomicReference
    //   654: invokevirtual 226	java/lang/Object:notify	()V
    //   657: aload_3
    //   658: athrow
    //   659: astore_3
    //   660: aload_1
    //   661: monitorexit
    //   662: aload_3
    //   663: athrow
    // Local variable table:
    //   start	length	slot	name	signature
    //   0	664	0	this	v1
    //   42	228	1	localObject1	Object
    //   296	14	1	localException	Exception
    //   50	38	2	localk6	k6
    //   101	18	2	localRemoteException1	android.os.RemoteException
    //   227	300	2	localObject2	Object
    //   58	548	3	localObject3	Object
    //   609	1	3	localObject4	Object
    //   613	24	3	localRemoteException2	android.os.RemoteException
    //   640	18	3	localAtomicReference2	java.util.concurrent.atomic.AtomicReference
    //   659	4	3	localObject5	Object
    //   63	205	4	localObject6	Object
    // Exception table:
    //   from	to	target	type
    //   85	98	101	android/os/RemoteException
    //   267	293	296	java/lang/Exception
    //   372	451	609	finally
    //   466	479	609	finally
    //   483	498	609	finally
    //   509	556	609	finally
    //   560	591	609	finally
    //   591	601	609	finally
    //   614	633	609	finally
    //   372	451	613	android/os/RemoteException
    //   466	479	613	android/os/RemoteException
    //   483	498	613	android/os/RemoteException
    //   509	556	613	android/os/RemoteException
    //   560	591	613	android/os/RemoteException
    //   591	601	613	android/os/RemoteException
    //   451	459	659	finally
    //   459	463	659	finally
    //   498	506	659	finally
    //   601	606	659	finally
    //   636	641	659	finally
    //   644	646	659	finally
    //   647	659	659	finally
    //   660	662	659	finally
  }
}

/* Location:
 * Qualified Name:     e7.v1
 * Java Class Version: 6 (50.0)
 * JD-Core Version:    0.7.1
 */