package e7;

import android.content.ComponentName;
import android.content.Context;
import android.content.Intent;
import android.content.SharedPreferences;
import android.content.SharedPreferences.Editor;
import android.content.pm.PackageManager;
import android.os.Looper;
import android.os.SystemClock;
import b.z;
import d2.q;
import i6.p;
import java.util.ArrayList;
import java.util.Iterator;
import java.util.List;
import java.util.concurrent.atomic.AtomicReference;
import m6.j;
import pb.c;

public final class w4
  extends j0
{
  public final i5 d;
  public n0 e;
  public volatile Boolean f;
  public final x4 o;
  public final c p;
  public final ArrayList q = new ArrayList();
  public final x4 r;
  
  public w4(j2 paramj2)
  {
    super(paramj2);
    p = new c(v);
    d = new i5(this);
    o = new x4(this, paramj2, 0);
    r = new x4(this, paramj2, 1);
  }
  
  public final void A()
  {
    l();
    t();
    if (C()) {
      return;
    }
    Object localObject1;
    Object localObject2;
    if (F())
    {
      localObject1 = d;
      c.l();
      localObject2 = c.zza();
      try
      {
        if (a) {
          localObject4 = c.zzj().w;
        }
        for (localObject2 = "Connection attempt already in progress";; localObject2 = "Already awaiting connection attempt")
        {
          ((b1)localObject4).b((String)localObject2);
          break label171;
          if ((b == null) || ((!b.isConnecting()) && (!b.isConnected()))) {
            break;
          }
          localObject4 = c.zzj().w;
        }
        Object localObject4 = new e7/z0;
        ((z0)localObject4).<init>((Context)localObject2, Looper.getMainLooper(), (i5)localObject1, (i5)localObject1);
        b = ((z0)localObject4);
        c.zzj().w.b("Connecting to remote service");
        a = true;
        j.i(b);
        b.checkAvailabilityAndConnect();
        label171:
        return;
      }
      finally {}
    }
    if (!h().C())
    {
      Object localObject6 = zza().getPackageManager().queryIntentServices(new Intent().setClassName(zza(), "com.google.android.gms.measurement.AppMeasurementService"), 65536);
      int i;
      if ((localObject6 != null) && (!((List)localObject6).isEmpty())) {
        i = 1;
      } else {
        i = 0;
      }
      if (i != 0)
      {
        localObject2 = new Intent("com.google.android.gms.measurement.START");
        ((Intent)localObject2).setComponent(new ComponentName(zza(), "com.google.android.gms.measurement.AppMeasurementService"));
        localObject6 = d;
        c.l();
        Context localContext = c.zza();
        localObject1 = u6.a.b();
        try
        {
          if (a)
          {
            c.zzj().w.b("Connection attempt already in progress");
          }
          else
          {
            c.zzj().w.b("Using local app measurement service");
            a = true;
            ((u6.a)localObject1).a(localContext, (Intent)localObject2, c.d, 129);
          }
          return;
        }
        finally {}
      }
      zzjo.b("Unable to use remote or local measurement implementation. Please register the AppMeasurementService service in the app manifest");
    }
  }
  
  public final void B()
  {
    l();
    t();
    i5 locali5 = d;
    if ((b != null) && ((b.isConnected()) || (b.isConnecting()))) {
      b.disconnect();
    }
    b = null;
    try
    {
      u6.a.b().c(zza(), d);
      e = null;
      return;
    }
    catch (IllegalStateException|IllegalArgumentException localIllegalStateException)
    {
      for (;;) {}
    }
  }
  
  public final boolean C()
  {
    l();
    t();
    return e != null;
  }
  
  public final boolean D()
  {
    l();
    t();
    if (!F()) {
      return true;
    }
    return k().s0() >= ((Integer)h0.E0.a(null)).intValue();
  }
  
  public final boolean E()
  {
    l();
    t();
    if (!F()) {
      return true;
    }
    return k().s0() >= 241200;
  }
  
  public final boolean F()
  {
    l();
    t();
    if (f == null)
    {
      l();
      t();
      Object localObject1 = j();
      ((q)localObject1).l();
      boolean bool1 = ((l1)localObject1).v().contains("use_service");
      int i = 0;
      if (!bool1) {
        localObject1 = null;
      } else {
        localObject1 = Boolean.valueOf(((l1)localObject1).v().getBoolean("use_service", false));
      }
      bool1 = true;
      boolean bool2 = true;
      boolean bool3 = true;
      if ((localObject1 != null) && (((Boolean)localObject1).booleanValue()))
      {
        bool3 = bool2;
      }
      else
      {
        Object localObject2 = m();
        ((j0)localObject2).t();
        if (u != 1)
        {
          zzjw.b("Checking service availability");
          localObject2 = k();
          localObject2.getClass();
          int j = j6.f.b.c(((q)localObject2).zza(), 12451000);
          if (j != 0)
          {
            if (j != 1)
            {
              if (j != 2)
              {
                if (j != 3)
                {
                  if (j != 9)
                  {
                    if (j != 18)
                    {
                      zzjr.c("Unexpected service status", Integer.valueOf(j));
                      break label272;
                    }
                    localObject1 = zzjr;
                    localObject2 = "Service updating";
                    break label362;
                  }
                  localObject2 = zzjr;
                  localObject1 = "Service invalid";
                }
                else
                {
                  localObject2 = zzjr;
                  localObject1 = "Service disabled";
                }
                ((b1)localObject2).b((String)localObject1);
                label272:
                bool3 = false;
                bool1 = bool3;
                break label371;
              }
              zzjv.b("Service container out of date");
              if (k().s0() >= 17443)
              {
                if (localObject1 == null) {
                  bool1 = bool3;
                } else {
                  bool1 = false;
                }
                bool3 = false;
                break label371;
              }
            }
            else
            {
              zzjw.b("Service missing");
            }
            bool3 = true;
            bool1 = false;
            break label371;
          }
          else
          {
            localObject1 = zzjw;
            localObject2 = "Service available";
          }
          label362:
          ((b1)localObject1).b((String)localObject2);
        }
        else
        {
          bool3 = true;
        }
        label371:
        if ((!bool1) && (h().C())) {
          zzjo.b("No way to upload. Consider using the full version of Analytics");
        } else {
          i = bool3;
        }
        bool3 = bool1;
        if (i != 0)
        {
          localObject1 = j();
          ((q)localObject1).l();
          localObject1 = ((l1)localObject1).v().edit();
          ((SharedPreferences.Editor)localObject1).putBoolean("use_service", bool1);
          ((SharedPreferences.Editor)localObject1).apply();
          bool3 = bool1;
        }
      }
      f = Boolean.valueOf(bool3);
    }
    return f.booleanValue();
  }
  
  public final void G()
  {
    l();
    zzjw.c("Processing queued up service tasks", Integer.valueOf(q.size()));
    Iterator localIterator = q.iterator();
    while (localIterator.hasNext())
    {
      Runnable localRunnable = (Runnable)localIterator.next();
      try
      {
        localRunnable.run();
      }
      catch (RuntimeException localRuntimeException)
      {
        zzjo.c("Task exception while flushing queue", localRuntimeException);
      }
    }
    q.clear();
    r.a();
  }
  
  public final void H()
  {
    l();
    c localc = p;
    ((z)b).getClass();
    a = SystemClock.elapsedRealtime();
    o.b(((Long)h0.U.a(null)).longValue());
  }
  
  /* Error */
  public final k6 I(boolean paramBoolean)
  {
    // Byte code:
    //   0: aload_0
    //   1: invokevirtual 281	e7/o0:m	()Le7/t0;
    //   4: astore_2
    //   5: aconst_null
    //   6: astore_3
    //   7: iload_1
    //   8: ifeq +15 -> 23
    //   11: aload_0
    //   12: invokevirtual 92	d2/q:zzj	()Le7/a1;
    //   15: invokevirtual 416	e7/a1:A	()Ljava/lang/String;
    //   18: astore 4
    //   20: goto +6 -> 26
    //   23: aconst_null
    //   24: astore 4
    //   26: aload_2
    //   27: invokevirtual 64	e7/o0:l	()V
    //   30: aload_2
    //   31: invokevirtual 418	e7/t0:v	()Ljava/lang/String;
    //   34: astore 5
    //   36: aload_2
    //   37: invokevirtual 420	e7/t0:w	()Ljava/lang/String;
    //   40: astore 6
    //   42: aload_2
    //   43: invokevirtual 67	e7/j0:t	()V
    //   46: aload_2
    //   47: getfield 423	e7/t0:e	Ljava/lang/String;
    //   50: astore 7
    //   52: aload_2
    //   53: invokevirtual 67	e7/j0:t	()V
    //   56: aload_2
    //   57: getfield 425	e7/t0:f	I
    //   60: i2l
    //   61: lstore 8
    //   63: aload_2
    //   64: invokevirtual 67	e7/j0:t	()V
    //   67: aload_2
    //   68: getfield 427	e7/t0:o	Ljava/lang/String;
    //   71: invokestatic 138	m6/j:i	(Ljava/lang/Object;)V
    //   74: aload_2
    //   75: getfield 427	e7/t0:o	Ljava/lang/String;
    //   78: astore 10
    //   80: aload_2
    //   81: invokevirtual 67	e7/j0:t	()V
    //   84: aload_2
    //   85: invokevirtual 64	e7/o0:l	()V
    //   88: aload_2
    //   89: getfield 429	e7/t0:q	J
    //   92: lconst_0
    //   93: lcmp
    //   94: ifne +199 -> 293
    //   97: aload_2
    //   98: getfield 430	d2/q:b	Ljava/lang/Object;
    //   101: checkcast 32	e7/j2
    //   104: invokevirtual 432	e7/j2:m	()Le7/r6;
    //   107: astore 11
    //   109: aload_2
    //   110: invokevirtual 84	d2/q:zza	()Landroid/content/Context;
    //   113: astore 12
    //   115: aload_2
    //   116: invokevirtual 84	d2/q:zza	()Landroid/content/Context;
    //   119: invokevirtual 435	android/content/Context:getPackageName	()Ljava/lang/String;
    //   122: astore 13
    //   124: aload 11
    //   126: invokevirtual 251	d2/q:l	()V
    //   129: aload 12
    //   131: invokestatic 138	m6/j:i	(Ljava/lang/Object;)V
    //   134: aload 13
    //   136: invokestatic 437	m6/j:e	(Ljava/lang/String;)V
    //   139: aload 12
    //   141: invokevirtual 154	android/content/Context:getPackageManager	()Landroid/content/pm/PackageManager;
    //   144: astore 14
    //   146: invokestatic 441	e7/r6:B0	()Ljava/security/MessageDigest;
    //   149: astore 15
    //   151: ldc2_w 442
    //   154: lstore 16
    //   156: aload 15
    //   158: ifnonnull +20 -> 178
    //   161: aload 11
    //   163: invokevirtual 92	d2/q:zzj	()Le7/a1;
    //   166: getfield 200	e7/a1:o	Le7/b1;
    //   169: ldc_w 445
    //   172: invokevirtual 106	e7/b1:b	(Ljava/lang/String;)V
    //   175: goto +88 -> 263
    //   178: aload 14
    //   180: ifnull +104 -> 284
    //   183: aload 11
    //   185: aload 12
    //   187: aload 13
    //   189: invokevirtual 449	e7/r6:m0	(Landroid/content/Context;Ljava/lang/String;)Z
    //   192: ifne +92 -> 284
    //   195: aload 12
    //   197: invokestatic 454	x6/d:a	(Landroid/content/Context;)Lx6/c;
    //   200: bipush 64
    //   202: aload 11
    //   204: invokevirtual 84	d2/q:zza	()Landroid/content/Context;
    //   207: invokevirtual 435	android/content/Context:getPackageName	()Ljava/lang/String;
    //   210: invokevirtual 459	x6/c:b	(ILjava/lang/String;)Landroid/content/pm/PackageInfo;
    //   213: getfield 465	android/content/pm/PackageInfo:signatures	[Landroid/content/pm/Signature;
    //   216: astore 14
    //   218: aload 14
    //   220: ifnull +29 -> 249
    //   223: aload 14
    //   225: arraylength
    //   226: ifle +23 -> 249
    //   229: aload 15
    //   231: aload 14
    //   233: iconst_0
    //   234: aaload
    //   235: invokevirtual 471	android/content/pm/Signature:toByteArray	()[B
    //   238: invokevirtual 477	java/security/MessageDigest:digest	([B)[B
    //   241: invokestatic 480	e7/r6:t	([B)J
    //   244: lstore 16
    //   246: goto +17 -> 263
    //   249: aload 11
    //   251: invokevirtual 92	d2/q:zzj	()Le7/a1;
    //   254: getfield 306	e7/a1:r	Le7/b1;
    //   257: ldc_w 482
    //   260: invokevirtual 106	e7/b1:b	(Ljava/lang/String;)V
    //   263: goto +24 -> 287
    //   266: astore 15
    //   268: aload 11
    //   270: invokevirtual 92	d2/q:zzj	()Le7/a1;
    //   273: getfield 200	e7/a1:o	Le7/b1;
    //   276: ldc_w 484
    //   279: aload 15
    //   281: invokevirtual 314	e7/b1:c	(Ljava/lang/String;Ljava/lang/Object;)V
    //   284: lconst_0
    //   285: lstore 16
    //   287: aload_2
    //   288: lload 16
    //   290: putfield 429	e7/t0:q	J
    //   293: aload_2
    //   294: getfield 429	e7/t0:q	J
    //   297: lstore 18
    //   299: aload_2
    //   300: getfield 430	d2/q:b	Ljava/lang/Object;
    //   303: checkcast 32	e7/j2
    //   306: invokevirtual 486	e7/j2:d	()Z
    //   309: istore 20
    //   311: aload_2
    //   312: invokevirtual 250	d2/q:j	()Le7/l1;
    //   315: getfield 488	e7/l1:B	Z
    //   318: istore 21
    //   320: aload_2
    //   321: invokevirtual 64	e7/o0:l	()V
    //   324: aload_2
    //   325: getfield 430	d2/q:b	Ljava/lang/Object;
    //   328: checkcast 32	e7/j2
    //   331: invokevirtual 486	e7/j2:d	()Z
    //   334: ifne +6 -> 340
    //   337: goto +59 -> 396
    //   340: invokestatic 492	com/google/android/gms/internal/measurement/zzpq:zza	()Z
    //   343: ifeq +33 -> 376
    //   346: aload_2
    //   347: invokevirtual 145	d2/q:h	()Le7/h;
    //   350: aconst_null
    //   351: getstatic 495	e7/h0:C0	Le7/m0;
    //   354: invokevirtual 499	e7/h:x	(Ljava/lang/String;Le7/m0;)Z
    //   357: ifeq +19 -> 376
    //   360: aload_2
    //   361: invokevirtual 92	d2/q:zzj	()Le7/a1;
    //   364: getfield 98	e7/a1:w	Le7/b1;
    //   367: astore_3
    //   368: ldc_w 501
    //   371: astore 11
    //   373: goto +130 -> 503
    //   376: aload_2
    //   377: invokevirtual 84	d2/q:zza	()Landroid/content/Context;
    //   380: invokevirtual 505	android/content/Context:getClassLoader	()Ljava/lang/ClassLoader;
    //   383: ldc_w 507
    //   386: invokevirtual 513	java/lang/ClassLoader:loadClass	(Ljava/lang/String;)Ljava/lang/Class;
    //   389: astore 11
    //   391: aload 11
    //   393: ifnonnull +6 -> 399
    //   396: goto +119 -> 515
    //   399: aload 11
    //   401: ldc_w 515
    //   404: iconst_1
    //   405: anewarray 517	java/lang/Class
    //   408: dup
    //   409: iconst_0
    //   410: ldc -106
    //   412: aastore
    //   413: invokevirtual 521	java/lang/Class:getDeclaredMethod	(Ljava/lang/String;[Ljava/lang/Class;)Ljava/lang/reflect/Method;
    //   416: astore 15
    //   418: aload_2
    //   419: invokevirtual 84	d2/q:zza	()Landroid/content/Context;
    //   422: astore_3
    //   423: aload 15
    //   425: aconst_null
    //   426: iconst_1
    //   427: anewarray 291	java/lang/Object
    //   430: dup
    //   431: iconst_0
    //   432: aload_3
    //   433: aastore
    //   434: invokevirtual 527	java/lang/reflect/Method:invoke	(Ljava/lang/Object;[Ljava/lang/Object;)Ljava/lang/Object;
    //   437: astore_3
    //   438: aload_3
    //   439: ifnonnull +6 -> 445
    //   442: goto +71 -> 513
    //   445: aload 11
    //   447: ldc_w 529
    //   450: iconst_0
    //   451: anewarray 517	java/lang/Class
    //   454: invokevirtual 521	java/lang/Class:getDeclaredMethod	(Ljava/lang/String;[Ljava/lang/Class;)Ljava/lang/reflect/Method;
    //   457: aload_3
    //   458: iconst_0
    //   459: anewarray 291	java/lang/Object
    //   462: invokevirtual 527	java/lang/reflect/Method:invoke	(Ljava/lang/Object;[Ljava/lang/Object;)Ljava/lang/Object;
    //   465: checkcast 531	java/lang/String
    //   468: astore_3
    //   469: goto +46 -> 515
    //   472: astore_3
    //   473: aload_2
    //   474: invokevirtual 92	d2/q:zzj	()Le7/a1;
    //   477: getfield 533	e7/a1:t	Le7/b1;
    //   480: astore_3
    //   481: ldc_w 535
    //   484: astore 11
    //   486: goto +17 -> 503
    //   489: astore_3
    //   490: aload_2
    //   491: invokevirtual 92	d2/q:zzj	()Le7/a1;
    //   494: getfield 538	e7/a1:s	Le7/b1;
    //   497: astore_3
    //   498: ldc_w 540
    //   501: astore 11
    //   503: aload_3
    //   504: aload 11
    //   506: invokevirtual 106	e7/b1:b	(Ljava/lang/String;)V
    //   509: goto +4 -> 513
    //   512: astore_3
    //   513: aconst_null
    //   514: astore_3
    //   515: aload_2
    //   516: getfield 430	d2/q:b	Ljava/lang/Object;
    //   519: checkcast 32	e7/j2
    //   522: astore 11
    //   524: aload 11
    //   526: invokevirtual 541	e7/j2:j	()Le7/l1;
    //   529: getfield 544	e7/l1:p	Le7/q1;
    //   532: invokevirtual 548	e7/q1:a	()J
    //   535: lstore 16
    //   537: lload 16
    //   539: lconst_0
    //   540: lcmp
    //   541: ifne +13 -> 554
    //   544: aload 11
    //   546: getfield 551	e7/j2:Q	J
    //   549: lstore 16
    //   551: goto +15 -> 566
    //   554: aload 11
    //   556: getfield 551	e7/j2:Q	J
    //   559: lload 16
    //   561: invokestatic 557	java/lang/Math:min	(JJ)J
    //   564: lstore 16
    //   566: aload_2
    //   567: invokevirtual 67	e7/j0:t	()V
    //   570: aload_2
    //   571: getfield 287	e7/t0:u	I
    //   574: istore 22
    //   576: aload_2
    //   577: invokevirtual 145	d2/q:h	()Le7/h;
    //   580: ldc_w 559
    //   583: invokevirtual 562	e7/h:v	(Ljava/lang/String;)Ljava/lang/Boolean;
    //   586: astore 11
    //   588: aload 11
    //   590: ifnull +19 -> 609
    //   593: aload 11
    //   595: invokevirtual 277	java/lang/Boolean:booleanValue	()Z
    //   598: ifeq +6 -> 604
    //   601: goto +8 -> 609
    //   604: iconst_0
    //   605: istore_1
    //   606: goto +5 -> 611
    //   609: iconst_1
    //   610: istore_1
    //   611: aload_2
    //   612: invokevirtual 250	d2/q:j	()Le7/l1;
    //   615: astore 11
    //   617: aload 11
    //   619: invokevirtual 251	d2/q:l	()V
    //   622: aload 11
    //   624: invokevirtual 256	e7/l1:v	()Landroid/content/SharedPreferences;
    //   627: ldc_w 564
    //   630: iconst_0
    //   631: invokeinterface 268 3 0
    //   636: istore 23
    //   638: aload_2
    //   639: invokevirtual 67	e7/j0:t	()V
    //   642: aload_2
    //   643: getfield 566	e7/t0:w	Ljava/lang/String;
    //   646: astore 12
    //   648: aload_2
    //   649: invokevirtual 145	d2/q:h	()Le7/h;
    //   652: ldc_w 568
    //   655: iconst_1
    //   656: invokevirtual 571	e7/h:t	(Ljava/lang/String;Z)Le7/g3;
    //   659: getstatic 576	e7/g3:e	Le7/g3;
    //   662: if_acmpeq +9 -> 671
    //   665: iconst_1
    //   666: istore 24
    //   668: goto +6 -> 674
    //   671: iconst_0
    //   672: istore 24
    //   674: aload_2
    //   675: getfield 578	e7/t0:r	J
    //   678: lstore 25
    //   680: aload_2
    //   681: getfield 581	e7/t0:s	Ljava/util/List;
    //   684: astore 13
    //   686: aload_2
    //   687: invokevirtual 250	d2/q:j	()Le7/l1;
    //   690: invokevirtual 585	e7/l1:y	()Le7/e3;
    //   693: invokevirtual 590	e7/e3:n	()Ljava/lang/String;
    //   696: astore 14
    //   698: aload_2
    //   699: getfield 592	e7/t0:t	Ljava/lang/String;
    //   702: ifnonnull +14 -> 716
    //   705: aload_2
    //   706: aload_2
    //   707: invokevirtual 220	d2/q:k	()Le7/r6;
    //   710: invokevirtual 595	e7/r6:A0	()Ljava/lang/String;
    //   713: putfield 592	e7/t0:t	Ljava/lang/String;
    //   716: aload_2
    //   717: getfield 592	e7/t0:t	Ljava/lang/String;
    //   720: astore 15
    //   722: aload_2
    //   723: invokevirtual 250	d2/q:j	()Le7/l1;
    //   726: invokevirtual 585	e7/l1:y	()Le7/e3;
    //   729: getstatic 600	e7/e3$a:c	Le7/e3$a;
    //   732: invokevirtual 603	e7/e3:j	(Le7/e3$a;)Z
    //   735: ifne +9 -> 744
    //   738: aconst_null
    //   739: astore 11
    //   741: goto +88 -> 829
    //   744: aload_2
    //   745: invokevirtual 64	e7/o0:l	()V
    //   748: aload_2
    //   749: getfield 605	e7/t0:y	J
    //   752: lconst_0
    //   753: lcmp
    //   754: ifeq +58 -> 812
    //   757: aload_2
    //   758: invokevirtual 609	d2/q:zzb	()Lv6/b;
    //   761: checkcast 386	b/z
    //   764: invokevirtual 295	java/lang/Object:getClass	()Ljava/lang/Class;
    //   767: pop
    //   768: invokestatic 614	java/lang/System:currentTimeMillis	()J
    //   771: lstore 27
    //   773: aload_2
    //   774: getfield 605	e7/t0:y	J
    //   777: lstore 29
    //   779: aload_2
    //   780: getfield 616	e7/t0:x	Ljava/lang/String;
    //   783: ifnull +29 -> 812
    //   786: lload 27
    //   788: lload 29
    //   790: lsub
    //   791: ldc2_w 617
    //   794: lcmp
    //   795: ifle +17 -> 812
    //   798: aload_2
    //   799: getfield 621	e7/t0:z	Ljava/lang/String;
    //   802: ifnonnull +10 -> 812
    //   805: aload_2
    //   806: invokevirtual 623	e7/t0:x	()V
    //   809: goto +3 -> 812
    //   812: aload_2
    //   813: getfield 616	e7/t0:x	Ljava/lang/String;
    //   816: ifnonnull +7 -> 823
    //   819: aload_2
    //   820: invokevirtual 623	e7/t0:x	()V
    //   823: aload_2
    //   824: getfield 616	e7/t0:x	Ljava/lang/String;
    //   827: astore 11
    //   829: lconst_0
    //   830: lstore 31
    //   832: aload_2
    //   833: invokevirtual 145	d2/q:h	()Le7/h;
    //   836: ldc_w 625
    //   839: invokevirtual 562	e7/h:v	(Ljava/lang/String;)Ljava/lang/Boolean;
    //   842: astore 33
    //   844: aload 33
    //   846: ifnonnull +9 -> 855
    //   849: iconst_0
    //   850: istore 34
    //   852: goto +10 -> 862
    //   855: aload 33
    //   857: invokevirtual 277	java/lang/Boolean:booleanValue	()Z
    //   860: istore 34
    //   862: aload_2
    //   863: invokevirtual 220	d2/q:k	()Le7/r6;
    //   866: astore 35
    //   868: aload_2
    //   869: invokevirtual 418	e7/t0:v	()Ljava/lang/String;
    //   872: astore 33
    //   874: aload 35
    //   876: invokevirtual 84	d2/q:zza	()Landroid/content/Context;
    //   879: invokevirtual 154	android/content/Context:getPackageManager	()Landroid/content/pm/PackageManager;
    //   882: ifnonnull +9 -> 891
    //   885: lconst_0
    //   886: lstore 29
    //   888: goto +64 -> 952
    //   891: aload 35
    //   893: invokevirtual 84	d2/q:zza	()Landroid/content/Context;
    //   896: invokestatic 454	x6/d:a	(Landroid/content/Context;)Lx6/c;
    //   899: astore 36
    //   901: aload 36
    //   903: iconst_0
    //   904: aload 33
    //   906: invokevirtual 628	x6/c:a	(ILjava/lang/String;)Landroid/content/pm/ApplicationInfo;
    //   909: astore 36
    //   911: aload 36
    //   913: ifnull +31 -> 944
    //   916: aload 36
    //   918: getfield 633	android/content/pm/ApplicationInfo:targetSdkVersion	I
    //   921: istore 37
    //   923: goto +24 -> 947
    //   926: astore 36
    //   928: aload 35
    //   930: invokevirtual 92	d2/q:zzj	()Le7/a1;
    //   933: getfield 635	e7/a1:u	Le7/b1;
    //   936: ldc_w 637
    //   939: aload 33
    //   941: invokevirtual 314	e7/b1:c	(Ljava/lang/String;Ljava/lang/Object;)V
    //   944: iconst_0
    //   945: istore 37
    //   947: iload 37
    //   949: i2l
    //   950: lstore 29
    //   952: aload_2
    //   953: invokevirtual 250	d2/q:j	()Le7/l1;
    //   956: invokevirtual 585	e7/l1:y	()Le7/e3;
    //   959: getfield 639	e7/e3:b	I
    //   962: istore 38
    //   964: aload_2
    //   965: invokevirtual 250	d2/q:j	()Le7/l1;
    //   968: invokevirtual 642	e7/l1:x	()Le7/x;
    //   971: getfield 646	e7/x:b	Ljava/lang/String;
    //   974: astore 33
    //   976: invokestatic 649	com/google/android/gms/internal/measurement/zzoy:zza	()Z
    //   979: ifeq +30 -> 1009
    //   982: aload_2
    //   983: invokevirtual 145	d2/q:h	()Le7/h;
    //   986: aconst_null
    //   987: getstatic 652	e7/h0:R0	Le7/m0;
    //   990: invokevirtual 499	e7/h:x	(Ljava/lang/String;Le7/m0;)Z
    //   993: ifeq +16 -> 1009
    //   996: aload_2
    //   997: invokevirtual 220	d2/q:k	()Le7/r6;
    //   1000: pop
    //   1001: invokestatic 655	e7/r6:k0	()I
    //   1004: istore 37
    //   1006: goto +6 -> 1012
    //   1009: iconst_0
    //   1010: istore 37
    //   1012: lload 31
    //   1014: lstore 27
    //   1016: invokestatic 649	com/google/android/gms/internal/measurement/zzoy:zza	()Z
    //   1019: ifeq +30 -> 1049
    //   1022: lload 31
    //   1024: lstore 27
    //   1026: aload_2
    //   1027: invokevirtual 145	d2/q:h	()Le7/h;
    //   1030: aconst_null
    //   1031: getstatic 652	e7/h0:R0	Le7/m0;
    //   1034: invokevirtual 499	e7/h:x	(Ljava/lang/String;Le7/m0;)Z
    //   1037: ifeq +12 -> 1049
    //   1040: aload_2
    //   1041: invokevirtual 220	d2/q:k	()Le7/r6;
    //   1044: invokevirtual 658	e7/r6:x0	()J
    //   1047: lstore 27
    //   1049: aload_2
    //   1050: invokevirtual 145	d2/q:h	()Le7/h;
    //   1053: getfield 660	e7/h:d	Ljava/lang/String;
    //   1056: astore 35
    //   1058: aload_2
    //   1059: invokevirtual 145	d2/q:h	()Le7/h;
    //   1062: ldc_w 568
    //   1065: iconst_1
    //   1066: invokevirtual 571	e7/h:t	(Ljava/lang/String;Z)Le7/g3;
    //   1069: invokestatic 663	e7/e3:a	(Le7/g3;)C
    //   1072: istore 39
    //   1074: aload_2
    //   1075: getfield 430	d2/q:b	Ljava/lang/Object;
    //   1078: checkcast 32	e7/j2
    //   1081: getfield 551	e7/j2:Q	J
    //   1084: lstore 31
    //   1086: aload_2
    //   1087: invokevirtual 145	d2/q:h	()Le7/h;
    //   1090: aconst_null
    //   1091: getstatic 666	e7/h0:M0	Le7/m0;
    //   1094: invokevirtual 499	e7/h:x	(Ljava/lang/String;Le7/m0;)Z
    //   1097: ifeq +41 -> 1138
    //   1100: aload_2
    //   1101: getfield 430	d2/q:b	Ljava/lang/Object;
    //   1104: checkcast 32	e7/j2
    //   1107: getfield 669	e7/j2:F	Le7/o4;
    //   1110: astore_2
    //   1111: aload_2
    //   1112: ifnull +15 -> 1127
    //   1115: aload_2
    //   1116: invokevirtual 674	e7/o4:w	()Lcom/google/android/gms/internal/measurement/zzgf$zzo$zza;
    //   1119: invokevirtual 678	com/google/android/gms/internal/measurement/zzgf$zzo$zza:zza	()I
    //   1122: istore 40
    //   1124: goto +17 -> 1141
    //   1127: new 205	java/lang/IllegalStateException
    //   1130: dup
    //   1131: ldc_w 680
    //   1134: invokespecial 681	java/lang/IllegalStateException:<init>	(Ljava/lang/String;)V
    //   1137: athrow
    //   1138: iconst_0
    //   1139: istore 40
    //   1141: new 683	e7/k6
    //   1144: dup
    //   1145: aload 5
    //   1147: aload 6
    //   1149: aload 7
    //   1151: lload 8
    //   1153: aload 10
    //   1155: ldc2_w 684
    //   1158: lload 18
    //   1160: aload 4
    //   1162: iload 20
    //   1164: iload 21
    //   1166: iconst_1
    //   1167: ixor
    //   1168: aload_3
    //   1169: lload 16
    //   1171: iload 22
    //   1173: iload_1
    //   1174: iload 23
    //   1176: aload 12
    //   1178: iload 24
    //   1180: invokestatic 274	java/lang/Boolean:valueOf	(Z)Ljava/lang/Boolean;
    //   1183: lload 25
    //   1185: aload 13
    //   1187: aload 14
    //   1189: aload 15
    //   1191: aload 11
    //   1193: iload 34
    //   1195: lload 29
    //   1197: iload 38
    //   1199: aload 33
    //   1201: iload 37
    //   1203: lload 27
    //   1205: aload 35
    //   1207: iload 39
    //   1209: invokestatic 688	java/lang/String:valueOf	(C)Ljava/lang/String;
    //   1212: lload 31
    //   1214: iload 40
    //   1216: invokespecial 691	e7/k6:<init>	(Ljava/lang/String;Ljava/lang/String;Ljava/lang/String;JLjava/lang/String;JJLjava/lang/String;ZZLjava/lang/String;JIZZLjava/lang/String;Ljava/lang/Boolean;JLjava/util/List;Ljava/lang/String;Ljava/lang/String;Ljava/lang/String;ZJILjava/lang/String;IJLjava/lang/String;Ljava/lang/String;JI)V
    //   1219: areturn
    //   1220: astore_3
    //   1221: goto -731 -> 490
    //   1224: astore 36
    //   1226: goto -298 -> 928
    // Local variable table:
    //   start	length	slot	name	signature
    //   0	1229	0	this	w4
    //   0	1229	1	paramBoolean	boolean
    //   4	1112	2	localObject1	Object
    //   6	463	3	localObject2	Object
    //   472	1	3	localException1	Exception
    //   480	1	3	localb11	b1
    //   489	1	3	localException2	Exception
    //   497	7	3	localb12	b1
    //   512	1	3	localClassNotFoundException	ClassNotFoundException
    //   514	655	3	str1	String
    //   1220	1	3	localException3	Exception
    //   18	1143	4	str2	String
    //   34	1112	5	str3	String
    //   40	1108	6	str4	String
    //   50	1100	7	str5	String
    //   61	1091	8	l1	long
    //   78	1076	10	str6	String
    //   107	1085	11	localObject3	Object
    //   113	1064	12	localObject4	Object
    //   122	1064	13	localObject5	Object
    //   144	1044	14	localObject6	Object
    //   149	81	15	localMessageDigest	java.security.MessageDigest
    //   266	14	15	localNameNotFoundException1	android.content.pm.PackageManager.NameNotFoundException
    //   416	774	15	localObject7	Object
    //   154	1016	16	l2	long
    //   297	862	18	l3	long
    //   309	854	20	bool1	boolean
    //   318	850	21	bool2	boolean
    //   574	598	22	i	int
    //   636	539	23	bool3	boolean
    //   666	513	24	bool4	boolean
    //   678	506	25	l4	long
    //   771	433	27	l5	long
    //   777	419	29	l6	long
    //   830	383	31	l7	long
    //   842	358	33	localObject8	Object
    //   850	344	34	bool5	boolean
    //   866	340	35	localObject9	Object
    //   899	18	36	localObject10	Object
    //   926	1	36	localNameNotFoundException2	android.content.pm.PackageManager.NameNotFoundException
    //   1224	1	36	localNameNotFoundException3	android.content.pm.PackageManager.NameNotFoundException
    //   921	281	37	j	int
    //   962	236	38	k	int
    //   1072	136	39	c	char
    //   1122	93	40	m	int
    // Exception table:
    //   from	to	target	type
    //   183	218	266	android/content/pm/PackageManager$NameNotFoundException
    //   223	246	266	android/content/pm/PackageManager$NameNotFoundException
    //   249	263	266	android/content/pm/PackageManager$NameNotFoundException
    //   445	469	472	java/lang/Exception
    //   399	423	489	java/lang/Exception
    //   376	391	512	java/lang/ClassNotFoundException
    //   891	901	926	android/content/pm/PackageManager$NameNotFoundException
    //   423	438	1220	java/lang/Exception
    //   901	911	1224	android/content/pm/PackageManager$NameNotFoundException
    //   916	923	1224	android/content/pm/PackageManager$NameNotFoundException
  }
  
  public final boolean s()
  {
    return false;
  }
  
  public final void v(f paramf)
  {
    l();
    t();
    Object localObject = n();
    ((q)localObject).k();
    byte[] arrayOfByte = r6.a0(paramf);
    boolean bool;
    if (arrayOfByte.length > 131072)
    {
      zzjp.b("Conditional user property too long for local database. Sending directly to service");
      bool = false;
    }
    else
    {
      bool = ((w0)localObject).w(arrayOfByte, 2);
    }
    localObject = new f(paramf);
    x(new g5(this, I(true), bool, (f)localObject, paramf));
  }
  
  /* Error */
  public final void w(n0 paramn0, n6.a parama, k6 paramk6)
  {
    // Byte code:
    //   0: aload_0
    //   1: invokevirtual 64	e7/o0:l	()V
    //   4: aload_0
    //   5: invokevirtual 67	e7/j0:t	()V
    //   8: iconst_0
    //   9: istore 4
    //   11: bipush 100
    //   13: istore 5
    //   15: iconst_0
    //   16: istore 6
    //   18: iload 6
    //   20: sipush 1001
    //   23: if_icmpge +2055 -> 2078
    //   26: iload 5
    //   28: bipush 100
    //   30: if_icmpne +2048 -> 2078
    //   33: new 23	java/util/ArrayList
    //   36: dup
    //   37: invokespecial 26	java/util/ArrayList:<init>	()V
    //   40: astore 7
    //   42: aload_0
    //   43: invokevirtual 695	e7/o0:n	()Le7/w0;
    //   46: astore 8
    //   48: aload 8
    //   50: invokevirtual 64	e7/o0:l	()V
    //   53: aload 8
    //   55: getfield 736	e7/w0:e	Z
    //   58: ifeq +14 -> 72
    //   61: iload 4
    //   63: istore 9
    //   65: iload 6
    //   67: istore 5
    //   69: goto +105 -> 174
    //   72: new 23	java/util/ArrayList
    //   75: dup
    //   76: invokespecial 26	java/util/ArrayList:<init>	()V
    //   79: astore 10
    //   81: aload 8
    //   83: invokevirtual 84	d2/q:zza	()Landroid/content/Context;
    //   86: ldc_w 738
    //   89: invokevirtual 742	android/content/Context:getDatabasePath	(Ljava/lang/String;)Ljava/io/File;
    //   92: invokevirtual 747	java/io/File:exists	()Z
    //   95: ifne +22 -> 117
    //   98: iload 6
    //   100: istore 5
    //   102: aload 10
    //   104: astore 11
    //   106: iload 4
    //   108: istore 6
    //   110: iload 5
    //   112: istore 4
    //   114: goto +1467 -> 1581
    //   117: iload 4
    //   119: istore 12
    //   121: iconst_5
    //   122: istore 13
    //   124: iload 12
    //   126: iconst_5
    //   127: if_icmpge +1425 -> 1552
    //   130: aload 8
    //   132: invokevirtual 750	e7/w0:z	()Landroid/database/sqlite/SQLiteDatabase;
    //   135: astore 11
    //   137: aload 11
    //   139: ifnonnull +46 -> 185
    //   142: aload 8
    //   144: iconst_1
    //   145: putfield 736	e7/w0:e	Z
    //   148: iload 4
    //   150: istore 9
    //   152: iload 6
    //   154: istore 5
    //   156: aload 11
    //   158: ifnull +16 -> 174
    //   161: aload 11
    //   163: invokevirtual 755	android/database/sqlite/SQLiteClosable:close	()V
    //   166: iload 6
    //   168: istore 5
    //   170: iload 4
    //   172: istore 9
    //   174: iload 9
    //   176: istore 6
    //   178: iload 5
    //   180: istore 4
    //   182: goto +1396 -> 1578
    //   185: aload 11
    //   187: invokevirtual 760	android/database/sqlite/SQLiteDatabase:beginTransaction	()V
    //   190: aload 11
    //   192: invokestatic 763	e7/w0:v	(Landroid/database/sqlite/SQLiteDatabase;)J
    //   195: lstore 14
    //   197: ldc2_w 442
    //   200: lstore 16
    //   202: lload 14
    //   204: ldc2_w 442
    //   207: lcmp
    //   208: ifeq +27 -> 235
    //   211: iconst_1
    //   212: anewarray 531	java/lang/String
    //   215: astore 18
    //   217: aload 18
    //   219: iload 4
    //   221: lload 14
    //   223: invokestatic 766	java/lang/String:valueOf	(J)Ljava/lang/String;
    //   226: aastore
    //   227: ldc_w 768
    //   230: astore 19
    //   232: goto +9 -> 241
    //   235: aconst_null
    //   236: astore 19
    //   238: aconst_null
    //   239: astore 18
    //   241: bipush 100
    //   243: invokestatic 772	java/lang/Integer:toString	(I)Ljava/lang/String;
    //   246: astore 20
    //   248: aload 11
    //   250: ldc_w 774
    //   253: iconst_3
    //   254: anewarray 531	java/lang/String
    //   257: dup
    //   258: iconst_0
    //   259: ldc_w 776
    //   262: aastore
    //   263: dup
    //   264: iconst_1
    //   265: ldc_w 778
    //   268: aastore
    //   269: dup
    //   270: iconst_2
    //   271: ldc_w 780
    //   274: aastore
    //   275: aload 19
    //   277: aload 18
    //   279: aconst_null
    //   280: aconst_null
    //   281: ldc_w 782
    //   284: aload 20
    //   286: invokevirtual 786	android/database/sqlite/SQLiteDatabase:query	(Ljava/lang/String;[Ljava/lang/String;Ljava/lang/String;[Ljava/lang/String;Ljava/lang/String;Ljava/lang/String;Ljava/lang/String;Ljava/lang/String;)Landroid/database/Cursor;
    //   289: astore 21
    //   291: aload 21
    //   293: astore 19
    //   295: aload 11
    //   297: astore 18
    //   299: aload 21
    //   301: invokeinterface 791 1 0
    //   306: istore 22
    //   308: iload 22
    //   310: ifeq +588 -> 898
    //   313: aload 21
    //   315: astore 19
    //   317: aload 11
    //   319: astore 18
    //   321: aload 21
    //   323: iload 4
    //   325: invokeinterface 795 2 0
    //   330: lstore 16
    //   332: aload 21
    //   334: astore 19
    //   336: aload 11
    //   338: astore 18
    //   340: aload 21
    //   342: iconst_1
    //   343: invokeinterface 799 2 0
    //   348: istore 4
    //   350: aload 21
    //   352: astore 19
    //   354: aload 11
    //   356: astore 18
    //   358: aload 21
    //   360: iconst_2
    //   361: invokeinterface 803 2 0
    //   366: astore 20
    //   368: iload 4
    //   370: ifne +139 -> 509
    //   373: aload 21
    //   375: astore 19
    //   377: aload 11
    //   379: astore 18
    //   381: invokestatic 809	android/os/Parcel:obtain	()Landroid/os/Parcel;
    //   384: astore 23
    //   386: aload 20
    //   388: arraylength
    //   389: istore 4
    //   391: aload 23
    //   393: aload 20
    //   395: iconst_0
    //   396: iload 4
    //   398: invokevirtual 813	android/os/Parcel:unmarshall	([BII)V
    //   401: aload 23
    //   403: iconst_0
    //   404: invokevirtual 817	android/os/Parcel:setDataPosition	(I)V
    //   407: getstatic 823	e7/f0:CREATOR	Landroid/os/Parcelable$Creator;
    //   410: aload 23
    //   412: invokeinterface 829 2 0
    //   417: checkcast 819	e7/f0
    //   420: astore 20
    //   422: aload 21
    //   424: astore 19
    //   426: aload 11
    //   428: astore 18
    //   430: aload 23
    //   432: invokevirtual 832	android/os/Parcel:recycle	()V
    //   435: aload 20
    //   437: ifnull +430 -> 867
    //   440: goto +314 -> 754
    //   443: astore 20
    //   445: goto +40 -> 485
    //   448: astore 20
    //   450: goto +35 -> 485
    //   453: astore 19
    //   455: aload 8
    //   457: invokevirtual 92	d2/q:zzj	()Le7/a1;
    //   460: getfield 200	e7/a1:o	Le7/b1;
    //   463: ldc_w 834
    //   466: invokevirtual 106	e7/b1:b	(Ljava/lang/String;)V
    //   469: aload 21
    //   471: astore 19
    //   473: aload 11
    //   475: astore 18
    //   477: aload 23
    //   479: invokevirtual 832	android/os/Parcel:recycle	()V
    //   482: goto +385 -> 867
    //   485: aload 21
    //   487: astore 19
    //   489: aload 11
    //   491: astore 18
    //   493: aload 23
    //   495: invokevirtual 832	android/os/Parcel:recycle	()V
    //   498: aload 21
    //   500: astore 19
    //   502: aload 11
    //   504: astore 18
    //   506: aload 20
    //   508: athrow
    //   509: iload 4
    //   511: iconst_1
    //   512: if_icmpne +133 -> 645
    //   515: aload 21
    //   517: astore 19
    //   519: aload 11
    //   521: astore 18
    //   523: invokestatic 809	android/os/Parcel:obtain	()Landroid/os/Parcel;
    //   526: astore 23
    //   528: aload 23
    //   530: aload 20
    //   532: iconst_0
    //   533: aload 20
    //   535: arraylength
    //   536: invokevirtual 813	android/os/Parcel:unmarshall	([BII)V
    //   539: aload 23
    //   541: iconst_0
    //   542: invokevirtual 817	android/os/Parcel:setDataPosition	(I)V
    //   545: getstatic 837	e7/q6:CREATOR	Landroid/os/Parcelable$Creator;
    //   548: aload 23
    //   550: invokeinterface 829 2 0
    //   555: checkcast 836	e7/q6
    //   558: astore 20
    //   560: aload 21
    //   562: astore 19
    //   564: aload 11
    //   566: astore 18
    //   568: aload 23
    //   570: invokevirtual 832	android/os/Parcel:recycle	()V
    //   573: goto +40 -> 613
    //   576: astore 20
    //   578: goto +43 -> 621
    //   581: astore 19
    //   583: aload 8
    //   585: invokevirtual 92	d2/q:zzj	()Le7/a1;
    //   588: getfield 200	e7/a1:o	Le7/b1;
    //   591: ldc_w 839
    //   594: invokevirtual 106	e7/b1:b	(Ljava/lang/String;)V
    //   597: aload 21
    //   599: astore 19
    //   601: aload 11
    //   603: astore 18
    //   605: aload 23
    //   607: invokevirtual 832	android/os/Parcel:recycle	()V
    //   610: aconst_null
    //   611: astore 20
    //   613: aload 20
    //   615: ifnull +252 -> 867
    //   618: goto +136 -> 754
    //   621: aload 21
    //   623: astore 19
    //   625: aload 11
    //   627: astore 18
    //   629: aload 23
    //   631: invokevirtual 832	android/os/Parcel:recycle	()V
    //   634: aload 21
    //   636: astore 19
    //   638: aload 11
    //   640: astore 18
    //   642: aload 20
    //   644: athrow
    //   645: iload 4
    //   647: iconst_2
    //   648: if_icmpne +149 -> 797
    //   651: aload 21
    //   653: astore 19
    //   655: aload 11
    //   657: astore 18
    //   659: invokestatic 809	android/os/Parcel:obtain	()Landroid/os/Parcel;
    //   662: astore 23
    //   664: aload 23
    //   666: aload 20
    //   668: iconst_0
    //   669: aload 20
    //   671: arraylength
    //   672: invokevirtual 813	android/os/Parcel:unmarshall	([BII)V
    //   675: aload 23
    //   677: iconst_0
    //   678: invokevirtual 817	android/os/Parcel:setDataPosition	(I)V
    //   681: getstatic 840	e7/f:CREATOR	Landroid/os/Parcelable$Creator;
    //   684: aload 23
    //   686: invokeinterface 829 2 0
    //   691: checkcast 711	e7/f
    //   694: astore 20
    //   696: aload 21
    //   698: astore 19
    //   700: aload 11
    //   702: astore 18
    //   704: aload 23
    //   706: invokevirtual 832	android/os/Parcel:recycle	()V
    //   709: goto +40 -> 749
    //   712: astore 20
    //   714: goto +59 -> 773
    //   717: astore 19
    //   719: aload 8
    //   721: invokevirtual 92	d2/q:zzj	()Le7/a1;
    //   724: getfield 200	e7/a1:o	Le7/b1;
    //   727: ldc_w 842
    //   730: invokevirtual 106	e7/b1:b	(Ljava/lang/String;)V
    //   733: aload 21
    //   735: astore 19
    //   737: aload 11
    //   739: astore 18
    //   741: aload 23
    //   743: invokevirtual 832	android/os/Parcel:recycle	()V
    //   746: aconst_null
    //   747: astore 20
    //   749: aload 20
    //   751: ifnull +116 -> 867
    //   754: aload 21
    //   756: astore 19
    //   758: aload 11
    //   760: astore 18
    //   762: aload 10
    //   764: aload 20
    //   766: invokevirtual 846	java/util/ArrayList:add	(Ljava/lang/Object;)Z
    //   769: pop
    //   770: goto +97 -> 867
    //   773: aload 21
    //   775: astore 19
    //   777: aload 11
    //   779: astore 18
    //   781: aload 23
    //   783: invokevirtual 832	android/os/Parcel:recycle	()V
    //   786: aload 21
    //   788: astore 19
    //   790: aload 11
    //   792: astore 18
    //   794: aload 20
    //   796: athrow
    //   797: iload 4
    //   799: iconst_3
    //   800: if_icmpne +29 -> 829
    //   803: aload 21
    //   805: astore 19
    //   807: aload 11
    //   809: astore 18
    //   811: aload 8
    //   813: invokevirtual 92	d2/q:zzj	()Le7/a1;
    //   816: getfield 306	e7/a1:r	Le7/b1;
    //   819: astore 20
    //   821: ldc_w 848
    //   824: astore 23
    //   826: goto +26 -> 852
    //   829: aload 21
    //   831: astore 19
    //   833: aload 11
    //   835: astore 18
    //   837: aload 8
    //   839: invokevirtual 92	d2/q:zzj	()Le7/a1;
    //   842: getfield 200	e7/a1:o	Le7/b1;
    //   845: astore 20
    //   847: ldc_w 850
    //   850: astore 23
    //   852: aload 21
    //   854: astore 19
    //   856: aload 11
    //   858: astore 18
    //   860: aload 20
    //   862: aload 23
    //   864: invokevirtual 106	e7/b1:b	(Ljava/lang/String;)V
    //   867: iconst_0
    //   868: istore 4
    //   870: goto -579 -> 291
    //   873: astore 20
    //   875: goto +13 -> 888
    //   878: astore 19
    //   880: goto +175 -> 1055
    //   883: astore 20
    //   885: goto +182 -> 1067
    //   888: iload 6
    //   890: istore 4
    //   892: iconst_0
    //   893: istore 6
    //   895: goto +336 -> 1231
    //   898: iload 6
    //   900: istore 4
    //   902: aload 21
    //   904: astore 19
    //   906: aload 11
    //   908: astore 18
    //   910: lload 16
    //   912: invokestatic 852	java/lang/Long:toString	(J)Ljava/lang/String;
    //   915: astore 20
    //   917: iconst_0
    //   918: istore 5
    //   920: iconst_0
    //   921: istore 9
    //   923: iconst_0
    //   924: istore 24
    //   926: iconst_0
    //   927: istore 6
    //   929: aload 21
    //   931: astore 19
    //   933: aload 11
    //   935: astore 18
    //   937: aload 11
    //   939: ldc_w 774
    //   942: ldc_w 854
    //   945: iconst_1
    //   946: anewarray 531	java/lang/String
    //   949: dup
    //   950: iconst_0
    //   951: aload 20
    //   953: aastore
    //   954: invokevirtual 858	android/database/sqlite/SQLiteDatabase:delete	(Ljava/lang/String;Ljava/lang/String;[Ljava/lang/String;)I
    //   957: aload 10
    //   959: invokevirtual 351	java/util/ArrayList:size	()I
    //   962: if_icmpge +25 -> 987
    //   965: aload 21
    //   967: astore 19
    //   969: aload 11
    //   971: astore 18
    //   973: aload 8
    //   975: invokevirtual 92	d2/q:zzj	()Le7/a1;
    //   978: getfield 200	e7/a1:o	Le7/b1;
    //   981: ldc_w 860
    //   984: invokevirtual 106	e7/b1:b	(Ljava/lang/String;)V
    //   987: aload 21
    //   989: astore 19
    //   991: aload 11
    //   993: astore 18
    //   995: aload 11
    //   997: invokevirtual 863	android/database/sqlite/SQLiteDatabase:setTransactionSuccessful	()V
    //   1000: aload 21
    //   1002: astore 19
    //   1004: aload 11
    //   1006: astore 18
    //   1008: aload 11
    //   1010: invokevirtual 866	android/database/sqlite/SQLiteDatabase:endTransaction	()V
    //   1013: aload 21
    //   1015: invokeinterface 867 1 0
    //   1020: aload 11
    //   1022: invokevirtual 755	android/database/sqlite/SQLiteClosable:close	()V
    //   1025: aload 10
    //   1027: astore 11
    //   1029: iload 24
    //   1031: istore 6
    //   1033: goto +548 -> 1581
    //   1036: astore 20
    //   1038: goto +193 -> 1231
    //   1041: astore 20
    //   1043: iload 9
    //   1045: istore 6
    //   1047: goto +381 -> 1428
    //   1050: astore 20
    //   1052: goto -164 -> 888
    //   1055: iload 6
    //   1057: istore 4
    //   1059: iconst_0
    //   1060: istore 6
    //   1062: goto +293 -> 1355
    //   1065: astore 20
    //   1067: iload 6
    //   1069: istore 4
    //   1071: iconst_0
    //   1072: istore 6
    //   1074: goto +354 -> 1428
    //   1077: astore_2
    //   1078: aload 18
    //   1080: astore_1
    //   1081: goto +449 -> 1530
    //   1084: astore 20
    //   1086: iload 6
    //   1088: istore 5
    //   1090: iload 4
    //   1092: istore 6
    //   1094: iload 5
    //   1096: istore 4
    //   1098: goto +133 -> 1231
    //   1101: astore 19
    //   1103: iload 6
    //   1105: istore 5
    //   1107: iload 4
    //   1109: istore 6
    //   1111: iload 5
    //   1113: istore 4
    //   1115: goto +240 -> 1355
    //   1118: astore 20
    //   1120: iload 6
    //   1122: istore 5
    //   1124: iload 4
    //   1126: istore 6
    //   1128: iload 5
    //   1130: istore 4
    //   1132: goto +296 -> 1428
    //   1135: astore_2
    //   1136: aload 11
    //   1138: astore_1
    //   1139: goto +66 -> 1205
    //   1142: astore 20
    //   1144: iload 6
    //   1146: istore 5
    //   1148: aconst_null
    //   1149: astore 21
    //   1151: iload 4
    //   1153: istore 6
    //   1155: iload 5
    //   1157: istore 4
    //   1159: goto +72 -> 1231
    //   1162: astore 19
    //   1164: iload 6
    //   1166: istore 5
    //   1168: aconst_null
    //   1169: astore 21
    //   1171: iload 4
    //   1173: istore 6
    //   1175: iload 5
    //   1177: istore 4
    //   1179: goto +176 -> 1355
    //   1182: astore 20
    //   1184: iload 6
    //   1186: istore 5
    //   1188: aconst_null
    //   1189: astore 21
    //   1191: iload 4
    //   1193: istore 6
    //   1195: iload 5
    //   1197: istore 4
    //   1199: goto +229 -> 1428
    //   1202: astore_2
    //   1203: aconst_null
    //   1204: astore_1
    //   1205: aconst_null
    //   1206: astore 19
    //   1208: goto +322 -> 1530
    //   1211: astore 20
    //   1213: iload 4
    //   1215: istore 5
    //   1217: aconst_null
    //   1218: astore 21
    //   1220: aconst_null
    //   1221: astore 11
    //   1223: iload 6
    //   1225: istore 4
    //   1227: iload 5
    //   1229: istore 6
    //   1231: aload 11
    //   1233: ifnull +32 -> 1265
    //   1236: aload 21
    //   1238: astore 19
    //   1240: aload 11
    //   1242: astore 18
    //   1244: aload 11
    //   1246: invokevirtual 870	android/database/sqlite/SQLiteDatabase:inTransaction	()Z
    //   1249: ifeq +16 -> 1265
    //   1252: aload 21
    //   1254: astore 19
    //   1256: aload 11
    //   1258: astore 18
    //   1260: aload 11
    //   1262: invokevirtual 866	android/database/sqlite/SQLiteDatabase:endTransaction	()V
    //   1265: aload 21
    //   1267: astore 19
    //   1269: aload 11
    //   1271: astore 18
    //   1273: aload 8
    //   1275: invokevirtual 92	d2/q:zzj	()Le7/a1;
    //   1278: getfield 200	e7/a1:o	Le7/b1;
    //   1281: ldc_w 872
    //   1284: aload 20
    //   1286: invokevirtual 314	e7/b1:c	(Ljava/lang/String;Ljava/lang/Object;)V
    //   1289: aload 21
    //   1291: astore 19
    //   1293: aload 11
    //   1295: astore 18
    //   1297: aload 8
    //   1299: iconst_1
    //   1300: putfield 736	e7/w0:e	Z
    //   1303: aload 21
    //   1305: ifnull +10 -> 1315
    //   1308: aload 21
    //   1310: invokeinterface 867 1 0
    //   1315: iload 13
    //   1317: istore 24
    //   1319: iload 6
    //   1321: istore 9
    //   1323: iload 4
    //   1325: istore 5
    //   1327: aload 11
    //   1329: ifnull +183 -> 1512
    //   1332: goto +163 -> 1495
    //   1335: astore 11
    //   1337: iload 4
    //   1339: istore 5
    //   1341: aconst_null
    //   1342: astore 21
    //   1344: aconst_null
    //   1345: astore 11
    //   1347: iload 6
    //   1349: istore 4
    //   1351: iload 5
    //   1353: istore 6
    //   1355: iload 13
    //   1357: i2l
    //   1358: lstore 16
    //   1360: aload 21
    //   1362: astore 19
    //   1364: aload 11
    //   1366: astore 18
    //   1368: lload 16
    //   1370: invokestatic 875	android/os/SystemClock:sleep	(J)V
    //   1373: iinc 13 20
    //   1376: aload 21
    //   1378: ifnull +10 -> 1388
    //   1381: aload 21
    //   1383: invokeinterface 867 1 0
    //   1388: iload 13
    //   1390: istore 24
    //   1392: iload 6
    //   1394: istore 9
    //   1396: iload 4
    //   1398: istore 5
    //   1400: aload 11
    //   1402: ifnull +110 -> 1512
    //   1405: goto +90 -> 1495
    //   1408: astore 20
    //   1410: iload 4
    //   1412: istore 5
    //   1414: aconst_null
    //   1415: astore 21
    //   1417: aconst_null
    //   1418: astore 11
    //   1420: iload 6
    //   1422: istore 4
    //   1424: iload 5
    //   1426: istore 6
    //   1428: aload 21
    //   1430: astore 19
    //   1432: aload 11
    //   1434: astore 18
    //   1436: aload 8
    //   1438: invokevirtual 92	d2/q:zzj	()Le7/a1;
    //   1441: getfield 200	e7/a1:o	Le7/b1;
    //   1444: ldc_w 872
    //   1447: aload 20
    //   1449: invokevirtual 314	e7/b1:c	(Ljava/lang/String;Ljava/lang/Object;)V
    //   1452: aload 21
    //   1454: astore 19
    //   1456: aload 11
    //   1458: astore 18
    //   1460: aload 8
    //   1462: iconst_1
    //   1463: putfield 736	e7/w0:e	Z
    //   1466: aload 21
    //   1468: ifnull +10 -> 1478
    //   1471: aload 21
    //   1473: invokeinterface 867 1 0
    //   1478: iload 13
    //   1480: istore 24
    //   1482: iload 6
    //   1484: istore 9
    //   1486: iload 4
    //   1488: istore 5
    //   1490: aload 11
    //   1492: ifnull +20 -> 1512
    //   1495: aload 11
    //   1497: invokevirtual 755	android/database/sqlite/SQLiteClosable:close	()V
    //   1500: iload 4
    //   1502: istore 5
    //   1504: iload 6
    //   1506: istore 9
    //   1508: iload 13
    //   1510: istore 24
    //   1512: iinc 12 1
    //   1515: iload 9
    //   1517: istore 4
    //   1519: iload 5
    //   1521: istore 6
    //   1523: iload 24
    //   1525: istore 13
    //   1527: goto -1403 -> 124
    //   1530: aload 19
    //   1532: ifnull +10 -> 1542
    //   1535: aload 19
    //   1537: invokeinterface 867 1 0
    //   1542: aload_1
    //   1543: ifnull +7 -> 1550
    //   1546: aload_1
    //   1547: invokevirtual 755	android/database/sqlite/SQLiteClosable:close	()V
    //   1550: aload_2
    //   1551: athrow
    //   1552: iload 4
    //   1554: istore 5
    //   1556: aload 8
    //   1558: invokevirtual 92	d2/q:zzj	()Le7/a1;
    //   1561: getfield 306	e7/a1:r	Le7/b1;
    //   1564: ldc_w 877
    //   1567: invokevirtual 106	e7/b1:b	(Ljava/lang/String;)V
    //   1570: iload 6
    //   1572: istore 4
    //   1574: iload 5
    //   1576: istore 6
    //   1578: aconst_null
    //   1579: astore 11
    //   1581: aload 11
    //   1583: ifnull +23 -> 1606
    //   1586: aload 7
    //   1588: aload 11
    //   1590: invokevirtual 881	java/util/ArrayList:addAll	(Ljava/util/Collection;)Z
    //   1593: pop
    //   1594: aload 11
    //   1596: invokeinterface 882 1 0
    //   1601: istore 5
    //   1603: goto +7 -> 1610
    //   1606: iload 6
    //   1608: istore 5
    //   1610: aload_2
    //   1611: ifnull +17 -> 1628
    //   1614: iload 5
    //   1616: bipush 100
    //   1618: if_icmpge +10 -> 1628
    //   1621: aload 7
    //   1623: aload_2
    //   1624: invokevirtual 846	java/util/ArrayList:add	(Ljava/lang/Object;)Z
    //   1627: pop
    //   1628: aload_0
    //   1629: invokevirtual 145	d2/q:h	()Le7/h;
    //   1632: aconst_null
    //   1633: getstatic 885	e7/h0:P0	Le7/m0;
    //   1636: invokevirtual 499	e7/h:x	(Ljava/lang/String;Le7/m0;)Z
    //   1639: istore 22
    //   1641: aload 7
    //   1643: invokevirtual 351	java/util/ArrayList:size	()I
    //   1646: istore 13
    //   1648: iload 6
    //   1650: istore 9
    //   1652: iload 9
    //   1654: iload 13
    //   1656: if_icmpge +405 -> 2061
    //   1659: aload 7
    //   1661: iload 9
    //   1663: invokevirtual 889	java/util/ArrayList:get	(I)Ljava/lang/Object;
    //   1666: checkcast 891	n6/a
    //   1669: astore 11
    //   1671: aload 11
    //   1673: instanceof 819
    //   1676: ifeq +273 -> 1949
    //   1679: iload 22
    //   1681: ifeq +72 -> 1753
    //   1684: aload_0
    //   1685: getfield 430	d2/q:b	Ljava/lang/Object;
    //   1688: checkcast 32	e7/j2
    //   1691: getfield 36	e7/j2:v	Lb/z;
    //   1694: invokevirtual 295	java/lang/Object:getClass	()Ljava/lang/Class;
    //   1697: pop
    //   1698: invokestatic 614	java/lang/System:currentTimeMillis	()J
    //   1701: lstore 14
    //   1703: aload_0
    //   1704: getfield 430	d2/q:b	Ljava/lang/Object;
    //   1707: checkcast 32	e7/j2
    //   1710: getfield 36	e7/j2:v	Lb/z;
    //   1713: invokevirtual 295	java/lang/Object:getClass	()Ljava/lang/Class;
    //   1716: pop
    //   1717: invokestatic 392	android/os/SystemClock:elapsedRealtime	()J
    //   1720: lstore 16
    //   1722: goto +37 -> 1759
    //   1725: astore 11
    //   1727: lload 14
    //   1729: lstore 16
    //   1731: goto +8 -> 1739
    //   1734: astore 11
    //   1736: lconst_0
    //   1737: lstore 16
    //   1739: lconst_0
    //   1740: lstore 25
    //   1742: lload 16
    //   1744: lstore 14
    //   1746: lload 25
    //   1748: lstore 16
    //   1750: goto +106 -> 1856
    //   1753: lconst_0
    //   1754: lstore 14
    //   1756: lconst_0
    //   1757: lstore 16
    //   1759: aload_1
    //   1760: aload 11
    //   1762: checkcast 819	e7/f0
    //   1765: aload_3
    //   1766: invokeinterface 897 3 0
    //   1771: iload 22
    //   1773: ifeq +282 -> 2055
    //   1776: aload_0
    //   1777: invokevirtual 92	d2/q:zzj	()Le7/a1;
    //   1780: getfield 98	e7/a1:w	Le7/b1;
    //   1783: ldc_w 899
    //   1786: invokevirtual 106	e7/b1:b	(Ljava/lang/String;)V
    //   1789: aload_0
    //   1790: getfield 430	d2/q:b	Ljava/lang/Object;
    //   1793: checkcast 32	e7/j2
    //   1796: invokestatic 904	e7/y0:a	(Le7/j2;)Le7/y0;
    //   1799: astore 11
    //   1801: aload_0
    //   1802: getfield 430	d2/q:b	Ljava/lang/Object;
    //   1805: checkcast 32	e7/j2
    //   1808: getfield 36	e7/j2:v	Lb/z;
    //   1811: invokevirtual 295	java/lang/Object:getClass	()Ljava/lang/Class;
    //   1814: pop
    //   1815: invokestatic 614	java/lang/System:currentTimeMillis	()J
    //   1818: lstore 25
    //   1820: aload_0
    //   1821: getfield 430	d2/q:b	Ljava/lang/Object;
    //   1824: checkcast 32	e7/j2
    //   1827: getfield 36	e7/j2:v	Lb/z;
    //   1830: invokevirtual 295	java/lang/Object:getClass	()Ljava/lang/Class;
    //   1833: pop
    //   1834: aload 11
    //   1836: iconst_0
    //   1837: invokestatic 392	android/os/SystemClock:elapsedRealtime	()J
    //   1840: lload 16
    //   1842: lsub
    //   1843: l2i
    //   1844: lload 14
    //   1846: lload 25
    //   1848: invokevirtual 907	e7/y0:b	(IIJJ)V
    //   1851: goto +204 -> 2055
    //   1854: astore 11
    //   1856: aload_0
    //   1857: invokevirtual 92	d2/q:zzj	()Le7/a1;
    //   1860: getfield 200	e7/a1:o	Le7/b1;
    //   1863: ldc_w 909
    //   1866: aload 11
    //   1868: invokevirtual 314	e7/b1:c	(Ljava/lang/String;Ljava/lang/Object;)V
    //   1871: iload 22
    //   1873: ifeq +182 -> 2055
    //   1876: lload 14
    //   1878: lconst_0
    //   1879: lcmp
    //   1880: ifeq +175 -> 2055
    //   1883: aload_0
    //   1884: getfield 430	d2/q:b	Ljava/lang/Object;
    //   1887: checkcast 32	e7/j2
    //   1890: invokestatic 904	e7/y0:a	(Le7/j2;)Le7/y0;
    //   1893: astore 11
    //   1895: aload_0
    //   1896: getfield 430	d2/q:b	Ljava/lang/Object;
    //   1899: checkcast 32	e7/j2
    //   1902: getfield 36	e7/j2:v	Lb/z;
    //   1905: invokevirtual 295	java/lang/Object:getClass	()Ljava/lang/Class;
    //   1908: pop
    //   1909: invokestatic 614	java/lang/System:currentTimeMillis	()J
    //   1912: lstore 25
    //   1914: aload_0
    //   1915: getfield 430	d2/q:b	Ljava/lang/Object;
    //   1918: checkcast 32	e7/j2
    //   1921: getfield 36	e7/j2:v	Lb/z;
    //   1924: invokevirtual 295	java/lang/Object:getClass	()Ljava/lang/Class;
    //   1927: pop
    //   1928: aload 11
    //   1930: bipush 13
    //   1932: invokestatic 392	android/os/SystemClock:elapsedRealtime	()J
    //   1935: lload 16
    //   1937: lsub
    //   1938: l2i
    //   1939: lload 14
    //   1941: lload 25
    //   1943: invokevirtual 907	e7/y0:b	(IIJJ)V
    //   1946: goto +109 -> 2055
    //   1949: aload 11
    //   1951: instanceof 836
    //   1954: ifeq +37 -> 1991
    //   1957: aload_1
    //   1958: aload 11
    //   1960: checkcast 836	e7/q6
    //   1963: aload_3
    //   1964: invokeinterface 913 3 0
    //   1969: goto +86 -> 2055
    //   1972: astore 18
    //   1974: aload_0
    //   1975: invokevirtual 92	d2/q:zzj	()Le7/a1;
    //   1978: getfield 200	e7/a1:o	Le7/b1;
    //   1981: astore 19
    //   1983: ldc_w 915
    //   1986: astore 11
    //   1988: goto +42 -> 2030
    //   1991: aload 11
    //   1993: instanceof 711
    //   1996: ifeq +46 -> 2042
    //   1999: aload_1
    //   2000: aload 11
    //   2002: checkcast 711	e7/f
    //   2005: aload_3
    //   2006: invokeinterface 918 3 0
    //   2011: goto +44 -> 2055
    //   2014: astore 18
    //   2016: aload_0
    //   2017: invokevirtual 92	d2/q:zzj	()Le7/a1;
    //   2020: getfield 200	e7/a1:o	Le7/b1;
    //   2023: astore 19
    //   2025: ldc_w 920
    //   2028: astore 11
    //   2030: aload 19
    //   2032: aload 11
    //   2034: aload 18
    //   2036: invokevirtual 314	e7/b1:c	(Ljava/lang/String;Ljava/lang/Object;)V
    //   2039: goto +16 -> 2055
    //   2042: aload_0
    //   2043: invokevirtual 92	d2/q:zzj	()Le7/a1;
    //   2046: getfield 200	e7/a1:o	Le7/b1;
    //   2049: ldc_w 922
    //   2052: invokevirtual 106	e7/b1:b	(Ljava/lang/String;)V
    //   2055: iinc 9 1
    //   2058: goto -406 -> 1652
    //   2061: iload 4
    //   2063: iconst_1
    //   2064: iadd
    //   2065: istore 9
    //   2067: iload 6
    //   2069: istore 4
    //   2071: iload 9
    //   2073: istore 6
    //   2075: goto -2057 -> 18
    //   2078: return
    //   2079: astore 19
    //   2081: goto -1626 -> 455
    //   2084: astore 19
    //   2086: goto -1031 -> 1055
    //   2089: astore 19
    //   2091: iload 5
    //   2093: istore 6
    //   2095: goto -740 -> 1355
    // Local variable table:
    //   start	length	slot	name	signature
    //   0	2098	0	this	w4
    //   0	2098	1	paramn0	n0
    //   0	2098	2	parama	n6.a
    //   0	2098	3	paramk6	k6
    //   9	2061	4	i	int
    //   13	2079	5	j	int
    //   16	2078	6	k	int
    //   40	1620	7	localArrayList1	ArrayList
    //   46	1511	8	localw0	w0
    //   63	2009	9	m	int
    //   79	947	10	localArrayList2	ArrayList
    //   104	1224	11	localObject1	Object
    //   1335	1	11	localSQLiteDatabaseLockedException1	android.database.sqlite.SQLiteDatabaseLockedException
    //   1345	327	11	localObject2	Object
    //   1725	1	11	localRemoteException1	android.os.RemoteException
    //   1734	27	11	localRemoteException2	android.os.RemoteException
    //   1799	36	11	localy0	y0
    //   1854	13	11	localRemoteException3	android.os.RemoteException
    //   1893	140	11	localObject3	Object
    //   119	1394	12	n	int
    //   122	1535	13	i1	int
    //   195	1745	14	l1	long
    //   200	1736	16	l2	long
    //   215	1244	18	localObject4	Object
    //   1972	1	18	localRemoteException4	android.os.RemoteException
    //   2014	21	18	localRemoteException5	android.os.RemoteException
    //   230	195	19	localObject5	Object
    //   453	1	19	locala1	n6.b.a
    //   471	92	19	localObject6	Object
    //   581	1	19	locala2	n6.b.a
    //   599	100	19	localObject7	Object
    //   717	1	19	locala3	n6.b.a
    //   735	120	19	localObject8	Object
    //   878	1	19	localSQLiteDatabaseLockedException2	android.database.sqlite.SQLiteDatabaseLockedException
    //   904	99	19	localObject9	Object
    //   1101	1	19	localSQLiteDatabaseLockedException3	android.database.sqlite.SQLiteDatabaseLockedException
    //   1162	1	19	localSQLiteDatabaseLockedException4	android.database.sqlite.SQLiteDatabaseLockedException
    //   1206	825	19	localObject10	Object
    //   2079	1	19	locala4	n6.b.a
    //   2084	1	19	localSQLiteDatabaseLockedException5	android.database.sqlite.SQLiteDatabaseLockedException
    //   2089	1	19	localSQLiteDatabaseLockedException6	android.database.sqlite.SQLiteDatabaseLockedException
    //   246	190	20	localObject11	Object
    //   443	1	20	localObject12	Object
    //   448	86	20	arrayOfByte	byte[]
    //   558	1	20	localq6	q6
    //   576	1	20	localObject13	Object
    //   611	84	20	localObject14	Object
    //   712	1	20	localObject15	Object
    //   747	114	20	localObject16	Object
    //   873	1	20	localSQLiteException1	android.database.sqlite.SQLiteException
    //   883	1	20	localSQLiteFullException1	android.database.sqlite.SQLiteFullException
    //   915	37	20	str	String
    //   1036	1	20	localSQLiteException2	android.database.sqlite.SQLiteException
    //   1041	1	20	localSQLiteFullException2	android.database.sqlite.SQLiteFullException
    //   1050	1	20	localSQLiteException3	android.database.sqlite.SQLiteException
    //   1065	1	20	localSQLiteFullException3	android.database.sqlite.SQLiteFullException
    //   1084	1	20	localSQLiteException4	android.database.sqlite.SQLiteException
    //   1118	1	20	localSQLiteFullException4	android.database.sqlite.SQLiteFullException
    //   1142	1	20	localSQLiteException5	android.database.sqlite.SQLiteException
    //   1182	1	20	localSQLiteFullException5	android.database.sqlite.SQLiteFullException
    //   1211	74	20	localSQLiteException6	android.database.sqlite.SQLiteException
    //   1408	40	20	localSQLiteFullException6	android.database.sqlite.SQLiteFullException
    //   289	1183	21	localCursor	android.database.Cursor
    //   306	1566	22	bool	boolean
    //   384	479	23	localObject17	Object
    //   924	600	24	i2	int
    //   1740	202	25	l3	long
    // Exception table:
    //   from	to	target	type
    //   391	422	443	finally
    //   455	469	443	finally
    //   386	391	448	finally
    //   386	391	453	n6/b$a
    //   528	560	576	finally
    //   583	597	576	finally
    //   528	560	581	n6/b$a
    //   664	696	712	finally
    //   719	733	712	finally
    //   664	696	717	n6/b$a
    //   321	332	873	android/database/sqlite/SQLiteException
    //   340	350	873	android/database/sqlite/SQLiteException
    //   358	368	873	android/database/sqlite/SQLiteException
    //   381	386	873	android/database/sqlite/SQLiteException
    //   321	332	878	android/database/sqlite/SQLiteDatabaseLockedException
    //   340	350	878	android/database/sqlite/SQLiteDatabaseLockedException
    //   358	368	878	android/database/sqlite/SQLiteDatabaseLockedException
    //   381	386	878	android/database/sqlite/SQLiteDatabaseLockedException
    //   321	332	883	android/database/sqlite/SQLiteFullException
    //   340	350	883	android/database/sqlite/SQLiteFullException
    //   358	368	883	android/database/sqlite/SQLiteFullException
    //   381	386	883	android/database/sqlite/SQLiteFullException
    //   937	965	1036	android/database/sqlite/SQLiteException
    //   973	987	1036	android/database/sqlite/SQLiteException
    //   995	1000	1036	android/database/sqlite/SQLiteException
    //   1008	1013	1036	android/database/sqlite/SQLiteException
    //   937	965	1041	android/database/sqlite/SQLiteFullException
    //   973	987	1041	android/database/sqlite/SQLiteFullException
    //   995	1000	1041	android/database/sqlite/SQLiteFullException
    //   1008	1013	1041	android/database/sqlite/SQLiteFullException
    //   430	435	1050	android/database/sqlite/SQLiteException
    //   477	482	1050	android/database/sqlite/SQLiteException
    //   493	498	1050	android/database/sqlite/SQLiteException
    //   506	509	1050	android/database/sqlite/SQLiteException
    //   523	528	1050	android/database/sqlite/SQLiteException
    //   568	573	1050	android/database/sqlite/SQLiteException
    //   605	610	1050	android/database/sqlite/SQLiteException
    //   629	634	1050	android/database/sqlite/SQLiteException
    //   642	645	1050	android/database/sqlite/SQLiteException
    //   659	664	1050	android/database/sqlite/SQLiteException
    //   704	709	1050	android/database/sqlite/SQLiteException
    //   741	746	1050	android/database/sqlite/SQLiteException
    //   762	770	1050	android/database/sqlite/SQLiteException
    //   781	786	1050	android/database/sqlite/SQLiteException
    //   794	797	1050	android/database/sqlite/SQLiteException
    //   811	821	1050	android/database/sqlite/SQLiteException
    //   837	847	1050	android/database/sqlite/SQLiteException
    //   860	867	1050	android/database/sqlite/SQLiteException
    //   910	917	1050	android/database/sqlite/SQLiteException
    //   430	435	1065	android/database/sqlite/SQLiteFullException
    //   477	482	1065	android/database/sqlite/SQLiteFullException
    //   493	498	1065	android/database/sqlite/SQLiteFullException
    //   506	509	1065	android/database/sqlite/SQLiteFullException
    //   523	528	1065	android/database/sqlite/SQLiteFullException
    //   568	573	1065	android/database/sqlite/SQLiteFullException
    //   605	610	1065	android/database/sqlite/SQLiteFullException
    //   629	634	1065	android/database/sqlite/SQLiteFullException
    //   642	645	1065	android/database/sqlite/SQLiteFullException
    //   659	664	1065	android/database/sqlite/SQLiteFullException
    //   704	709	1065	android/database/sqlite/SQLiteFullException
    //   741	746	1065	android/database/sqlite/SQLiteFullException
    //   762	770	1065	android/database/sqlite/SQLiteFullException
    //   781	786	1065	android/database/sqlite/SQLiteFullException
    //   794	797	1065	android/database/sqlite/SQLiteFullException
    //   811	821	1065	android/database/sqlite/SQLiteFullException
    //   837	847	1065	android/database/sqlite/SQLiteFullException
    //   860	867	1065	android/database/sqlite/SQLiteFullException
    //   910	917	1065	android/database/sqlite/SQLiteFullException
    //   299	308	1077	finally
    //   321	332	1077	finally
    //   340	350	1077	finally
    //   358	368	1077	finally
    //   381	386	1077	finally
    //   430	435	1077	finally
    //   477	482	1077	finally
    //   493	498	1077	finally
    //   506	509	1077	finally
    //   523	528	1077	finally
    //   568	573	1077	finally
    //   605	610	1077	finally
    //   629	634	1077	finally
    //   642	645	1077	finally
    //   659	664	1077	finally
    //   704	709	1077	finally
    //   741	746	1077	finally
    //   762	770	1077	finally
    //   781	786	1077	finally
    //   794	797	1077	finally
    //   811	821	1077	finally
    //   837	847	1077	finally
    //   860	867	1077	finally
    //   910	917	1077	finally
    //   937	965	1077	finally
    //   973	987	1077	finally
    //   995	1000	1077	finally
    //   1008	1013	1077	finally
    //   1244	1252	1077	finally
    //   1260	1265	1077	finally
    //   1273	1289	1077	finally
    //   1297	1303	1077	finally
    //   1368	1373	1077	finally
    //   1436	1452	1077	finally
    //   1460	1466	1077	finally
    //   299	308	1084	android/database/sqlite/SQLiteException
    //   299	308	1101	android/database/sqlite/SQLiteDatabaseLockedException
    //   299	308	1118	android/database/sqlite/SQLiteFullException
    //   142	148	1135	finally
    //   185	197	1135	finally
    //   211	227	1135	finally
    //   241	291	1135	finally
    //   142	148	1142	android/database/sqlite/SQLiteException
    //   185	197	1142	android/database/sqlite/SQLiteException
    //   211	227	1142	android/database/sqlite/SQLiteException
    //   241	291	1142	android/database/sqlite/SQLiteException
    //   142	148	1162	android/database/sqlite/SQLiteDatabaseLockedException
    //   185	197	1162	android/database/sqlite/SQLiteDatabaseLockedException
    //   211	227	1162	android/database/sqlite/SQLiteDatabaseLockedException
    //   241	291	1162	android/database/sqlite/SQLiteDatabaseLockedException
    //   142	148	1182	android/database/sqlite/SQLiteFullException
    //   185	197	1182	android/database/sqlite/SQLiteFullException
    //   211	227	1182	android/database/sqlite/SQLiteFullException
    //   241	291	1182	android/database/sqlite/SQLiteFullException
    //   130	137	1202	finally
    //   130	137	1211	android/database/sqlite/SQLiteException
    //   130	137	1335	android/database/sqlite/SQLiteDatabaseLockedException
    //   130	137	1408	android/database/sqlite/SQLiteFullException
    //   1703	1722	1725	android/os/RemoteException
    //   1684	1703	1734	android/os/RemoteException
    //   1759	1771	1854	android/os/RemoteException
    //   1776	1851	1854	android/os/RemoteException
    //   1957	1969	1972	android/os/RemoteException
    //   1999	2011	2014	android/os/RemoteException
    //   391	422	2079	n6/b$a
    //   430	435	2084	android/database/sqlite/SQLiteDatabaseLockedException
    //   477	482	2084	android/database/sqlite/SQLiteDatabaseLockedException
    //   493	498	2084	android/database/sqlite/SQLiteDatabaseLockedException
    //   506	509	2084	android/database/sqlite/SQLiteDatabaseLockedException
    //   523	528	2084	android/database/sqlite/SQLiteDatabaseLockedException
    //   568	573	2084	android/database/sqlite/SQLiteDatabaseLockedException
    //   605	610	2084	android/database/sqlite/SQLiteDatabaseLockedException
    //   629	634	2084	android/database/sqlite/SQLiteDatabaseLockedException
    //   642	645	2084	android/database/sqlite/SQLiteDatabaseLockedException
    //   659	664	2084	android/database/sqlite/SQLiteDatabaseLockedException
    //   704	709	2084	android/database/sqlite/SQLiteDatabaseLockedException
    //   741	746	2084	android/database/sqlite/SQLiteDatabaseLockedException
    //   762	770	2084	android/database/sqlite/SQLiteDatabaseLockedException
    //   781	786	2084	android/database/sqlite/SQLiteDatabaseLockedException
    //   794	797	2084	android/database/sqlite/SQLiteDatabaseLockedException
    //   811	821	2084	android/database/sqlite/SQLiteDatabaseLockedException
    //   837	847	2084	android/database/sqlite/SQLiteDatabaseLockedException
    //   860	867	2084	android/database/sqlite/SQLiteDatabaseLockedException
    //   910	917	2084	android/database/sqlite/SQLiteDatabaseLockedException
    //   937	965	2089	android/database/sqlite/SQLiteDatabaseLockedException
    //   973	987	2089	android/database/sqlite/SQLiteDatabaseLockedException
    //   995	1000	2089	android/database/sqlite/SQLiteDatabaseLockedException
    //   1008	1013	2089	android/database/sqlite/SQLiteDatabaseLockedException
  }
  
  public final void x(Runnable paramRunnable)
  {
    l();
    if (C())
    {
      paramRunnable.run();
      return;
    }
    if (q.size() >= 1000L)
    {
      zzjo.b("Discarding data. Max runnable queue size reached");
      return;
    }
    q.add(paramRunnable);
    r.b(60000L);
    A();
  }
  
  public final void y(AtomicReference<String> paramAtomicReference)
  {
    l();
    t();
    x(new v1(this, paramAtomicReference, I(false), 3));
  }
  
  public final void z(boolean paramBoolean)
  {
    l();
    t();
    if (D()) {
      x(new p(this, I(false), 8));
    }
  }
}

/* Location:
 * Qualified Name:     e7.w4
 * Java Class Version: 6 (50.0)
 * JD-Core Version:    0.7.1
 */