package y2;

public final class r$a
  implements Runnable
{
  public final r a;
  public final Runnable b;
  
  public r$a(r paramr, Runnable paramRunnable)
  {
    a = paramr;
    b = paramRunnable;
  }
  
  /* Error */
  public final void run()
  {
    // Byte code:
    //   0: aload_0
    //   1: getfield 21	y2/r$a:b	Ljava/lang/Runnable;
    //   4: invokeinterface 25 1 0
    //   9: aload_0
    //   10: getfield 19	y2/r$a:a	Ly2/r;
    //   13: getfield 29	y2/r:d	Ljava/lang/Object;
    //   16: astore_1
    //   17: aload_1
    //   18: monitorenter
    //   19: aload_0
    //   20: getfield 19	y2/r$a:a	Ly2/r;
    //   23: invokevirtual 31	y2/r:a	()V
    //   26: aload_1
    //   27: monitorexit
    //   28: return
    //   29: astore_2
    //   30: aload_1
    //   31: monitorexit
    //   32: aload_2
    //   33: athrow
    //   34: astore_2
    //   35: aload_0
    //   36: getfield 19	y2/r$a:a	Ly2/r;
    //   39: getfield 29	y2/r:d	Ljava/lang/Object;
    //   42: astore_1
    //   43: aload_1
    //   44: monitorenter
    //   45: aload_0
    //   46: getfield 19	y2/r$a:a	Ly2/r;
    //   49: invokevirtual 31	y2/r:a	()V
    //   52: aload_1
    //   53: monitorexit
    //   54: aload_2
    //   55: athrow
    //   56: astore_2
    //   57: aload_1
    //   58: monitorexit
    //   59: aload_2
    //   60: athrow
    // Local variable table:
    //   start	length	slot	name	signature
    //   0	61	0	this	a
    //   29	4	2	localObject2	Object
    //   34	21	2	localObject3	Object
    //   56	4	2	localObject4	Object
    // Exception table:
    //   from	to	target	type
    //   19	28	29	finally
    //   30	32	29	finally
    //   0	9	34	finally
    //   45	54	56	finally
    //   57	59	56	finally
  }
}

/* Location:
 * Qualified Name:     y2.r.a
 * Java Class Version: 6 (50.0)
 * JD-Core Version:    0.7.1
 */