package R2;

import java.util.concurrent.atomic.AtomicReference;

public final class f4
  implements Runnable
{
  public f4(C3 paramC3, AtomicReference paramAtomicReference) {}
  
  /* Error */
  public final void run()
  {
    // Byte code:
    //   0: aload_0
    //   1: getfield 16	R2/f4:o	Ljava/util/concurrent/atomic/AtomicReference;
    //   4: astore_1
    //   5: aload_1
    //   6: monitorenter
    //   7: aload_0
    //   8: getfield 16	R2/f4:o	Ljava/util/concurrent/atomic/AtomicReference;
    //   11: aload_0
    //   12: getfield 14	R2/f4:p	LR2/C3;
    //   15: invokevirtual 27	R2/m3:f	()LR2/g;
    //   18: aload_0
    //   19: getfield 14	R2/f4:p	LR2/C3;
    //   22: invokevirtual 32	R2/G1:p	()LR2/S1;
    //   25: invokevirtual 38	R2/S1:F	()Ljava/lang/String;
    //   28: getstatic 44	R2/K:O	LR2/P1;
    //   31: invokevirtual 50	R2/g:x	(Ljava/lang/String;LR2/P1;)J
    //   34: invokestatic 56	java/lang/Long:valueOf	(J)Ljava/lang/Long;
    //   37: invokevirtual 62	java/util/concurrent/atomic/AtomicReference:set	(Ljava/lang/Object;)V
    //   40: aload_0
    //   41: getfield 16	R2/f4:o	Ljava/util/concurrent/atomic/AtomicReference;
    //   44: invokevirtual 65	java/lang/Object:notify	()V
    //   47: aload_1
    //   48: monitorexit
    //   49: return
    //   50: astore_2
    //   51: goto +13 -> 64
    //   54: astore_2
    //   55: aload_0
    //   56: getfield 16	R2/f4:o	Ljava/util/concurrent/atomic/AtomicReference;
    //   59: invokevirtual 65	java/lang/Object:notify	()V
    //   62: aload_2
    //   63: athrow
    //   64: aload_1
    //   65: monitorexit
    //   66: aload_2
    //   67: athrow
    // Local variable table:
    //   start	length	slot	name	signature
    //   0	68	0	this	f4
    //   4	61	1	localAtomicReference	AtomicReference
    //   50	1	2	localObject1	Object
    //   54	13	2	localObject2	Object
    // Exception table:
    //   from	to	target	type
    //   40	49	50	finally
    //   55	64	50	finally
    //   64	66	50	finally
    //   7	40	54	finally
  }
}

/* Location:
 * Qualified Name:     R2.f4
 * Java Class Version: 6 (50.0)
 * JD-Core Version:    0.7.1
 */