package R2;

import com.google.android.gms.internal.measurement.y0;

public final class K4
  implements Runnable
{
  public K4(D4 paramD4, W5 paramW5, y0 paramy0) {}
  
  /* Error */
  public final void run()
  {
    // Byte code:
    //   0: aconst_null
    //   1: astore_1
    //   2: aconst_null
    //   3: astore_2
    //   4: aconst_null
    //   5: astore_3
    //   6: aload_1
    //   7: astore 4
    //   9: aload_2
    //   10: astore 5
    //   12: aload_0
    //   13: getfield 16	R2/K4:q	LR2/D4;
    //   16: invokevirtual 33	R2/m3:i	()LR2/l2;
    //   19: invokevirtual 39	R2/l2:J	()LR2/q3;
    //   22: invokevirtual 45	R2/q3:y	()Z
    //   25: ifne +90 -> 115
    //   28: aload_1
    //   29: astore 4
    //   31: aload_2
    //   32: astore 5
    //   34: aload_0
    //   35: getfield 16	R2/K4:q	LR2/D4;
    //   38: invokevirtual 49	R2/m3:j	()LR2/Y1;
    //   41: invokevirtual 55	R2/Y1:M	()LR2/a2;
    //   44: ldc 57
    //   46: invokevirtual 63	R2/a2:a	(Ljava/lang/String;)V
    //   49: aload_1
    //   50: astore 4
    //   52: aload_2
    //   53: astore 5
    //   55: aload_0
    //   56: getfield 16	R2/K4:q	LR2/D4;
    //   59: invokevirtual 69	R2/G1:r	()LR2/C3;
    //   62: aconst_null
    //   63: invokevirtual 74	R2/C3:T	(Ljava/lang/String;)V
    //   66: aload_1
    //   67: astore 4
    //   69: aload_2
    //   70: astore 5
    //   72: aload_0
    //   73: getfield 16	R2/K4:q	LR2/D4;
    //   76: invokevirtual 33	R2/m3:i	()LR2/l2;
    //   79: getfield 78	R2/l2:g	LR2/r2;
    //   82: aconst_null
    //   83: invokevirtual 83	R2/r2:b	(Ljava/lang/String;)V
    //   86: aload_3
    //   87: astore 5
    //   89: aload_0
    //   90: getfield 16	R2/K4:q	LR2/D4;
    //   93: invokevirtual 87	R2/m3:k	()LR2/S5;
    //   96: aload_0
    //   97: getfield 20	R2/K4:p	Lcom/google/android/gms/internal/measurement/y0;
    //   100: aload 5
    //   102: invokevirtual 93	R2/S5:V	(Lcom/google/android/gms/internal/measurement/y0;Ljava/lang/String;)V
    //   105: return
    //   106: astore 5
    //   108: goto +169 -> 277
    //   111: astore_3
    //   112: goto +142 -> 254
    //   115: aload_1
    //   116: astore 4
    //   118: aload_2
    //   119: astore 5
    //   121: aload_0
    //   122: getfield 16	R2/K4:q	LR2/D4;
    //   125: invokestatic 99	R2/D4:B	(LR2/D4;)LR2/R1;
    //   128: astore 6
    //   130: aload 6
    //   132: ifnonnull +30 -> 162
    //   135: aload_1
    //   136: astore 4
    //   138: aload_2
    //   139: astore 5
    //   141: aload_0
    //   142: getfield 16	R2/K4:q	LR2/D4;
    //   145: invokevirtual 49	R2/m3:j	()LR2/Y1;
    //   148: invokevirtual 102	R2/Y1:G	()LR2/a2;
    //   151: ldc 104
    //   153: invokevirtual 63	R2/a2:a	(Ljava/lang/String;)V
    //   156: aload_3
    //   157: astore 5
    //   159: goto -70 -> 89
    //   162: aload_1
    //   163: astore 4
    //   165: aload_2
    //   166: astore 5
    //   168: aload_0
    //   169: getfield 18	R2/K4:o	LR2/W5;
    //   172: invokestatic 109	A2/n:i	(Ljava/lang/Object;)Ljava/lang/Object;
    //   175: pop
    //   176: aload_1
    //   177: astore 4
    //   179: aload_2
    //   180: astore 5
    //   182: aload 6
    //   184: aload_0
    //   185: getfield 18	R2/K4:o	LR2/W5;
    //   188: invokeinterface 114 2 0
    //   193: astore_3
    //   194: aload_3
    //   195: ifnull +40 -> 235
    //   198: aload_3
    //   199: astore 4
    //   201: aload_3
    //   202: astore 5
    //   204: aload_0
    //   205: getfield 16	R2/K4:q	LR2/D4;
    //   208: invokevirtual 69	R2/G1:r	()LR2/C3;
    //   211: aload_3
    //   212: invokevirtual 74	R2/C3:T	(Ljava/lang/String;)V
    //   215: aload_3
    //   216: astore 4
    //   218: aload_3
    //   219: astore 5
    //   221: aload_0
    //   222: getfield 16	R2/K4:q	LR2/D4;
    //   225: invokevirtual 33	R2/m3:i	()LR2/l2;
    //   228: getfield 78	R2/l2:g	LR2/r2;
    //   231: aload_3
    //   232: invokevirtual 83	R2/r2:b	(Ljava/lang/String;)V
    //   235: aload_3
    //   236: astore 4
    //   238: aload_3
    //   239: astore 5
    //   241: aload_0
    //   242: getfield 16	R2/K4:q	LR2/D4;
    //   245: invokestatic 118	R2/D4:m0	(LR2/D4;)V
    //   248: aload_3
    //   249: astore 5
    //   251: goto -162 -> 89
    //   254: aload 5
    //   256: astore 4
    //   258: aload_0
    //   259: getfield 16	R2/K4:q	LR2/D4;
    //   262: invokevirtual 49	R2/m3:j	()LR2/Y1;
    //   265: invokevirtual 102	R2/Y1:G	()LR2/a2;
    //   268: ldc 104
    //   270: aload_3
    //   271: invokevirtual 121	R2/a2:b	(Ljava/lang/String;Ljava/lang/Object;)V
    //   274: goto -185 -> 89
    //   277: aload_0
    //   278: getfield 16	R2/K4:q	LR2/D4;
    //   281: invokevirtual 87	R2/m3:k	()LR2/S5;
    //   284: aload_0
    //   285: getfield 20	R2/K4:p	Lcom/google/android/gms/internal/measurement/y0;
    //   288: aload 4
    //   290: invokevirtual 93	R2/S5:V	(Lcom/google/android/gms/internal/measurement/y0;Ljava/lang/String;)V
    //   293: aload 5
    //   295: athrow
    // Local variable table:
    //   start	length	slot	name	signature
    //   0	296	0	this	K4
    //   1	176	1	localObject1	Object
    //   3	177	2	localObject2	Object
    //   5	82	3	localObject3	Object
    //   111	46	3	localRemoteException	android.os.RemoteException
    //   193	78	3	str	String
    //   7	282	4	localObject4	Object
    //   10	91	5	localObject5	Object
    //   106	1	5	localObject6	Object
    //   119	175	5	localObject7	Object
    //   128	55	6	localR1	R1
    // Exception table:
    //   from	to	target	type
    //   12	28	106	finally
    //   34	49	106	finally
    //   55	66	106	finally
    //   72	86	106	finally
    //   121	130	106	finally
    //   141	156	106	finally
    //   168	176	106	finally
    //   182	194	106	finally
    //   204	215	106	finally
    //   221	235	106	finally
    //   241	248	106	finally
    //   258	274	106	finally
    //   12	28	111	android/os/RemoteException
    //   34	49	111	android/os/RemoteException
    //   55	66	111	android/os/RemoteException
    //   72	86	111	android/os/RemoteException
    //   121	130	111	android/os/RemoteException
    //   141	156	111	android/os/RemoteException
    //   168	176	111	android/os/RemoteException
    //   182	194	111	android/os/RemoteException
    //   204	215	111	android/os/RemoteException
    //   221	235	111	android/os/RemoteException
    //   241	248	111	android/os/RemoteException
  }
}

/* Location:
 * Qualified Name:     R2.K4
 * Java Class Version: 6 (50.0)
 * JD-Core Version:    0.7.1
 */