package R2;

import com.google.android.gms.internal.measurement.y0;

public final class Y4
  implements Runnable
{
  public Y4(D4 paramD4, String paramString1, String paramString2, W5 paramW5, y0 paramy0) {}
  
  /* Error */
  public final void run()
  {
    // Byte code:
    //   0: new 36	java/util/ArrayList
    //   3: dup
    //   4: invokespecial 37	java/util/ArrayList:<init>	()V
    //   7: astore_1
    //   8: aload_1
    //   9: astore_2
    //   10: aload_1
    //   11: astore_3
    //   12: aload_0
    //   13: getfield 19	R2/Y4:s	LR2/D4;
    //   16: invokestatic 43	R2/D4:B	(LR2/D4;)LR2/R1;
    //   19: astore 4
    //   21: aload 4
    //   23: ifnonnull +56 -> 79
    //   26: aload_1
    //   27: astore_2
    //   28: aload_1
    //   29: astore_3
    //   30: aload_0
    //   31: getfield 19	R2/Y4:s	LR2/D4;
    //   34: invokevirtual 49	R2/m3:j	()LR2/Y1;
    //   37: invokevirtual 55	R2/Y1:G	()LR2/a2;
    //   40: ldc 57
    //   42: aload_0
    //   43: getfield 21	R2/Y4:o	Ljava/lang/String;
    //   46: aload_0
    //   47: getfield 23	R2/Y4:p	Ljava/lang/String;
    //   50: invokevirtual 63	R2/a2:c	(Ljava/lang/String;Ljava/lang/Object;Ljava/lang/Object;)V
    //   53: aload_1
    //   54: astore_3
    //   55: aload_0
    //   56: getfield 19	R2/Y4:s	LR2/D4;
    //   59: invokevirtual 67	R2/m3:k	()LR2/S5;
    //   62: aload_0
    //   63: getfield 27	R2/Y4:r	Lcom/google/android/gms/internal/measurement/y0;
    //   66: aload_3
    //   67: invokevirtual 73	R2/S5:W	(Lcom/google/android/gms/internal/measurement/y0;Ljava/util/ArrayList;)V
    //   70: return
    //   71: astore_3
    //   72: goto +91 -> 163
    //   75: astore_1
    //   76: goto +58 -> 134
    //   79: aload_1
    //   80: astore_2
    //   81: aload_1
    //   82: astore_3
    //   83: aload_0
    //   84: getfield 25	R2/Y4:q	LR2/W5;
    //   87: invokestatic 79	A2/n:i	(Ljava/lang/Object;)Ljava/lang/Object;
    //   90: pop
    //   91: aload_1
    //   92: astore_2
    //   93: aload_1
    //   94: astore_3
    //   95: aload 4
    //   97: aload_0
    //   98: getfield 21	R2/Y4:o	Ljava/lang/String;
    //   101: aload_0
    //   102: getfield 23	R2/Y4:p	Ljava/lang/String;
    //   105: aload_0
    //   106: getfield 25	R2/Y4:q	LR2/W5;
    //   109: invokeinterface 85 4 0
    //   114: invokestatic 89	R2/S5:t0	(Ljava/util/List;)Ljava/util/ArrayList;
    //   117: astore_1
    //   118: aload_1
    //   119: astore_2
    //   120: aload_1
    //   121: astore_3
    //   122: aload_0
    //   123: getfield 19	R2/Y4:s	LR2/D4;
    //   126: invokestatic 93	R2/D4:m0	(LR2/D4;)V
    //   129: aload_1
    //   130: astore_3
    //   131: goto -76 -> 55
    //   134: aload_3
    //   135: astore_2
    //   136: aload_0
    //   137: getfield 19	R2/Y4:s	LR2/D4;
    //   140: invokevirtual 49	R2/m3:j	()LR2/Y1;
    //   143: invokevirtual 55	R2/Y1:G	()LR2/a2;
    //   146: ldc 95
    //   148: aload_0
    //   149: getfield 21	R2/Y4:o	Ljava/lang/String;
    //   152: aload_0
    //   153: getfield 23	R2/Y4:p	Ljava/lang/String;
    //   156: aload_1
    //   157: invokevirtual 99	R2/a2:d	(Ljava/lang/String;Ljava/lang/Object;Ljava/lang/Object;Ljava/lang/Object;)V
    //   160: goto -105 -> 55
    //   163: aload_0
    //   164: getfield 19	R2/Y4:s	LR2/D4;
    //   167: invokevirtual 67	R2/m3:k	()LR2/S5;
    //   170: aload_0
    //   171: getfield 27	R2/Y4:r	Lcom/google/android/gms/internal/measurement/y0;
    //   174: aload_2
    //   175: invokevirtual 73	R2/S5:W	(Lcom/google/android/gms/internal/measurement/y0;Ljava/util/ArrayList;)V
    //   178: aload_3
    //   179: athrow
    // Local variable table:
    //   start	length	slot	name	signature
    //   0	180	0	this	Y4
    //   7	47	1	localArrayList1	java.util.ArrayList
    //   75	19	1	localRemoteException	android.os.RemoteException
    //   117	40	1	localArrayList2	java.util.ArrayList
    //   9	166	2	localObject1	Object
    //   11	56	3	localArrayList3	java.util.ArrayList
    //   71	1	3	localObject2	Object
    //   82	97	3	localObject3	Object
    //   19	77	4	localR1	R1
    // Exception table:
    //   from	to	target	type
    //   12	21	71	finally
    //   30	53	71	finally
    //   83	91	71	finally
    //   95	118	71	finally
    //   122	129	71	finally
    //   136	160	71	finally
    //   12	21	75	android/os/RemoteException
    //   30	53	75	android/os/RemoteException
    //   83	91	75	android/os/RemoteException
    //   95	118	75	android/os/RemoteException
    //   122	129	75	android/os/RemoteException
  }
}

/* Location:
 * Qualified Name:     R2.Y4
 * Java Class Version: 6 (50.0)
 * JD-Core Version:    0.7.1
 */